[
    {
        "source": "France Travail",
        "link": "https://candidat.francetravail.fr/offres/recherche/detail/2842644",
        "company": null,
        "location": "Hauts-de-Seine",
        "remote": null,
        "publication_date": "2024-08-24",
        "details": {
            "TypeContract": "CDI",
            "Salary": null,
            "Experience": "3 an(s)",
            "Level": null
        },
        "company_data": {
            "sector": null,
            "company_size": null,
            "turnover_in_millions": null
        },
        "description": "Description du poste :\nEn tant que cabinet de recrutement spécialisé dans l'emploi et le handicap, Talents Handicap accompagne de très nombreuses entreprises & organisations en France dans leurs recrutements de collaborateurs en situation de handicap. Dans ce cadre, nous recherchons pour le poste ci-dessous des candidats, en situation de handicap et vous invitons à postuler si vous correspondez au profil.\nL'entreprise Sopra Steria recherche activement des profils pour le poste suivant :\nDescription de l'entreprise\nSopra Steria, acteur majeur de la Tech en Europe avec 56 000 collaborateurs dans près de 30 pays, est reconnu pour ses activités de conseil, de services numériques et d'édition de logiciels. Il aide ses clients à mener leur transformation digitale et à obtenir des bénéfices concrets et durables. Le Groupe apporte une réponse globale aux enjeux de compétitivité des grandes entreprises et organisations, combinant une connaissance approfondie des secteurs d'activité et des technologies innovantes à une approche résolument collaborative.\nSopra Steria place l'humain au centre de son action et s'engage auprès de ses clients à tirer le meilleur parti du digital pour construire un avenir positif. En 2023, le Groupe a réalisé un chiffre d'affaires de 5,8 milliards d'euros.\nDescription du poste\nVotre futur environnement de travail :\nAu sein du vertical Services financiers, vous participez à des grands projets de transformations des systèmes d'informations de nos clients bancaires. \nActeur incontournable de l'avant-vente jusqu'à la mise en production, vous intervenez sur un périmètre large, au sein d'un environnement technique innovant. \nSopra Steria investit dans votre parcours professionnel en vous proposant des formations spécialisées (e-learning, présentiel), des parcours de certification et un accès des communautés internes. \nAu travers du collectif TechMe Up, Sopra Steria porte une attention toute particulière au bien-être et à l'épanouissement professionnel des population tech en proposant entre autres : ***Des journées de conférences tech biannuelles internes ***Des accès à des conférences externes ***Des pc « boostés » pour les développements ***Parcours de formation dédié pour nos experts techniques\nVos principales missions sont :***Vous communiquez avec de nombreuses parties prenantes de l'entreprise pour évaluer les besoins et les objectifs de la plateforme Data ***Vous évaluez l'architecture des données et les bases de données actuelles ***Vous recommandez les meilleures pratiques ETL pour l'ingestion des données***Vous faites des recommandations pour la plateforme cible en prenant en compte les usages existants et à venir***Vous mettez en place des architectures data en environnement multicloud/ cloud Hybride ***Vous veillez à l'exploitabilité continue du SI et l'ensemble des aspects de sécurité***Reconnu(e) pour votre expertise, vous participez activement à la montée en compétence des équipes***Enfin, vous assurez une veille technologique DATA et partagez cette connaissance au sein de la DSI et autres Directions\nEnvironnement technologique :\nBases de données Relationnelles et NoSQL,\nCloud (Azure, ou AWS notamment) en particulier leur capacité Data et IA, FinOps,\nTechnologies Big Data (Hadoop, Spark, Kafka, etc.),\nOutils de modélisation : Visio.\nLangages de programmation, Python et Java.\nDevOps & CI/CD : Maven, GitLab, Sonar, Checkmark, .\nQualifications\nVotre profil :\nVous possédez une forte expérience sur les technologies citées ci-dessus, ainsi qu'une réelle force de proposition en portant les sujets techniques ardus, et un comportement proactif pour embarquer l'équipe et le client dans le succès des projets.\nLe travail en équipe sera clé en interaction avec le client et aussi en interne avec une forte qualité pédagogique et d'intégration au sein des multiples équipes projets.\nVous êtes un vrai couteau suisse, permettant de descendre dans la technique sur les sujets ardus (exemplarité vis-à-vis des équipes techniques), tout en gardant du recul, et sachant aussi remonter plus haut au niveau DAT / Roadmap / Stratégie.\nVous êtes issu(e) d'un Master 2 ou équivalent (Ecole d'Ingénieurs ou Universitaire) et possédez au moins 5 ans d'expérience en tant qu'Architecte DATA, dans des environnements complexes et exigeants.\nInformations supplémentaires\nCe que nous proposons :***Un accord télétravail pour télétravailler jusqu'à 2 jours par semaine selon vos missions.\n* Un package avantages intéressants : une mutuelle, un CSE, des titres restaurants, un accord d'intéressement, des primes vacances et cooptation.\n* Un accompagnement individualisé avec un mentor que vous choisissez.\n* Des opportunités de carrières multiples : plus de 50 m",
        "title": "data architect",
        "skills": {
            "ProgLanguage": [
                "Java",
                "Python"
            ],
            "DataBase": [
                "NoSQL"
            ],
            "BigData": [
                "Spark",
                "Hadoop"
            ],
            "CloudComputing": [
                "Azure",
                "AWS"
            ],
            "Other": [
                "DevOps",
                "Big Data",
                "Cloud",
                "CI/CD"
            ]
        }
    }
]