[
    {
        "source": "France Travail",
        "link": "https://candidat.francetravail.fr/offres/recherche/detail/2745453",
        "company": null,
        "location": "Meylan",
        "remote": null,
        "publication_date": "2024-08-22",
        "details": {
            "TypeContract": "CDI",
            "Salary": null,
            "Experience": "expérience exigée",
            "Level": null
        },
        "company_data": {
            "sector": null,
            "company_size": null,
            "turnover_in_millions": null
        },
        "description": "DescriptionCiril GROUP, éditeur de logiciels et hébergeur Cloud, attire chaque année de nouveaux talents. Nous souhaitons mettre les compétences et savoir-faire de nos 450 collaborateurs au service d'une vision d'entreprise engagée : innover pour les hommes, en pensant la technologie comme un levier de transformation, d'accompagnement et de modernisation.Tenter l'expérience Ciril GROUP, c'est rejoindre l'un des acteurs majeurs de l'innovation française en matière de systèmes d'information métier et géographique interopérables, innovants, puissants, mais aussi en matière d'hébergement Cloud Haute Qualité, Haute Sécurité.MissionSous la responsabilité du responsable infrastructures et services managés, vous participerez à la mise en œuvre, l'administration et l'amélioration des pipelines de données et des bases de données pour nos solutions décisionnelles. Dans le cadre de vos missions, vous devrez notamment :Travailler en équipe pour assurer la gestion et l'exploitation des solutions décisionnelles des clients (bases de données, ETL, dataviz),Participer au support clients,Participer aux missions du service en réalisant, notamment, des prestations d'installation et de rédaction des procédures d'exploitation,Suivre la supervision des pipelines de données afin d'assurer la disponibilité et la sécurité de nos infrastructures,Participer à l'automatisation et l'optimisation des pipelines,Réaliser de la veille technologique et être force de proposition.Ainsi, en tant que spécialiste de la donnée, vous êtes capable de mettre en œuvre et maintenir un ensemble de pipelines de traitements de données, d'industrialiser et automatiser le nettoyage des données selon les spécifications retenues ainsi que de mettre en place une démarche de création de modèles d'analyses pour de la détection et de correction d'anomalies.De plus, vous participerez également activement à des projets variés comme la mise en place de solution décisionnelles, de flux inter-applicatifs ou de reprises de données métiers pour les clients Ciril GROUP ou pour notre plateforme interne. Voici quelques exemples :Participation aux phases d'analyse et de définition du cahier des charges,Etude des solutions techniques avec les différents acteurs (internes, clients ou prestataires),Modélisation des structures de bases de données dédiées au projet,Réalisation des phases de validation avant mise en production,Rédaction de documentations, de procédures et de supports de formations,Formation.ProfilIssu(e) d'une formation dans le domaine de l'informatique, vous disposez des compétences et connaissances suivantes :Un ou plusieurs SGBD : SQL Serveur, Oracle, PostgreSQLUn ou plusieurs langages de Scripting : ASP.net, Python, R, Bash, Yaml, Powershell, WinRMUn ou plusieurs ETL : OXIO DI, FME, Talend Open Studio, GDAL, DBTUn ou plusieurs outils de reporting / dataviz : Business Objects, QlikSenseConnaissances des systèmes d'exploitation suivants : Windows, LinuxUne connaissance des outils Docker, Airflow, Ansible, Jenkins et Keycloak sera valorisé.Vous recherchez la structure dans laquelle vous pourrez vous épanouir et donner un sens à votre travail ? Vous souhaitez devenir acteur sur les sujets qui nous concernent tous (environnement, sécurité, citoyenneté) ? Quels que soient votre parcours, vos attentes ou vos centres d'intérêt, les sujets que nous traitons vous concernent. Nous agissons pour vous. Alors rejoignez-nous !Poste CDI plein temps à Grenoble/Meylan (38).Pourquoi nous rejoindre ?Forfait Mobilité Durable pour les cyclistes, covoitureurs et covoiturés (20€ nets mensuels) Charte télétravail 12 jours de RTT par anParticipation aux résultatsIntéressementConvention collective Syntec (prime de vacances, jours d'ancienneté.)Carte titres restaurantPrise en charge de la mutuelle à 54%Démarche RSE Bonne ambiance de travail et locaux agréablesEvènements d'entreprise (tournois sportif, soirée gaming.)Management de proximité Equilibre vie professionnelle/vie personnelleCSE (arbre de Noël, site avec des réductions.) Un réinvestissement de 15% de notre CA en R&D",
        "title": "data engineer",
        "skills": {
            "ProgLanguage": [
                "R",
                "Python",
                "Bash"
            ],
            "DataBase": [
                "SQL"
            ],
            "DataAnalytics": [
                "R"
            ],
            "DevTools": [
                "Docker",
                "Jenkins"
            ],
            "OS": [
                "Windows"
            ],
            "Automation": [
                "Airflow",
                "Ansible"
            ],
            "Containers": [
                "Docker"
            ],
            "Other": [
                "Cloud"
            ]
        }
    },
    {
        "source": "France Travail",
        "link": "https://candidat.francetravail.fr/offres/recherche/detail/2701386",
        "company": null,
        "location": "MARTIGNY 76",
        "remote": null,
        "publication_date": "2024-08-22",
        "details": {
            "TypeContract": "CDI",
            "Salary": null,
            "Experience": "débutant accepté",
            "Level": null
        },
        "company_data": {
            "sector": null,
            "company_size": null,
            "turnover_in_millions": null
        },
        "description": "En tant que Cloud Data Engineer vous concevez et imple?mentez l'infrastructure Cloud Data et vous analysez les demandes business puis vous proposez des solutions d'imple?mentation Data. De plus, vous participez aux choix des outils et vous accompagnez les Data Scientist lors de leurs discussions lie?es aux besoins techniques. Vous ge?rez la mise en place des flux de donne?es et assurez la fiabilite? et la se?curite? des projets. Vous participez e?galement a? l'ame?lioration des processus, des templates et de la me?thodologie de travail (Data Analytics).\nDesign et imple?mentation d?une infrastructure Cloud Data\nAnalyse des demandes business, amener des ide?es et proposer l?imple?mentation de\nsolution du monde Data\nParticipation active aux choix des bons outils pour l'imple?mentation et a? la mise en place\nd?environnements techniques\nAccompagner les Data Scientists dans leurs re?flexions et dans leurs besoins\nAmener un regard critique sur la mise en place de nouveaux flux de donne?es\nS?assurer en tout temps de la qualite?, de la fiabilite?, de la cohe?rence, de la confidentialite?\net de la se?curite? des projets sous sa responsabilite?\nCollaborer a? l?ame?lioration des processus, des templates et des me?thodologies de travail\ndu de?partement Data Analytics\nOuvert au partage de ses compe?tences avec les membres de l?e?quipe et de l?organisation\nExcellentes connaissances Cloud Azure (Data Factory, Databricks; Azure ML un plus)\nBonnes connaissances de Python & SQL \nBonnes connaissances d'infrastructures containerise?es (Docker / Kubernetes)\nMai?trise des concepts Big Data\nUn plus :\no\nProfil candidat:\nDiplo?me d?Inge?nieur ou e?quivalent (Bac +5)\nBonne personnalite? et communication\nFranc?ais obligatoire / Anglais professionnel\nExpe?rience avec une plateforme Data Cloud (Azure, AWS, GCP).\nExpe?rience en conception et mise en ?uvre de solutions de se?curite? de la plateforme de donne?es.\nExpe?rience avec ElasticSearch, Terraform et les pratiques DevSecOps (CI/CD, git, security by design...).\nConnaissances Spark.",
        "title": "data engineer",
        "skills": {
            "ProgLanguage": [
                "Python"
            ],
            "DataBase": [
                "Elasticsearch",
                "SQL"
            ],
            "BigData": [
                "Spark",
                "Databricks"
            ],
            "CloudComputing": [
                "Azure",
                "AWS",
                "GCP"
            ],
            "DevTools": [
                "Docker",
                "Git"
            ],
            "Automation": [
                "Kubernetes"
            ],
            "InfrastructureAsCode": [
                "Terraform"
            ],
            "Containers": [
                "Kubernetes",
                "Docker"
            ],
            "Other": [
                "CI/CD",
                "Big Data",
                "ML",
                "Cloud"
            ],
            "EnSoftSkils": [
                "Communication"
            ]
        }
    },
    {
        "source": "France Travail",
        "link": "https://candidat.francetravail.fr/offres/recherche/detail/2703905",
        "company": "THALES LAS FRANCE SAS ",
        "location": "Essonne",
        "remote": null,
        "publication_date": "2024-08-22",
        "details": {
            "TypeContract": "CDI",
            "Salary": null,
            "Experience": "10 an(s)",
            "Level": null
        },
        "company_data": {
            "sector": null,
            "company_size": null,
            "turnover_in_millions": null
        },
        "description": "Chez Thales, nous sommes fiers de travailler ensemble pour imaginer des solutions innovantes qui contribuent à construire un avenir plus sûr, plus vert et plus inclusif. Un avenir de confiance. Mais ces technologies ne viennent pas de nulle part. L'intelligence humaine est le moteur derrière la technologie qui fait la renommée de Thales. Les projets que nous conduisons sont complexes et nos clients exigeants. Pour répondre aux besoins actuels et futurs de nos clients, nous maîtrisons plus d'une centaine de disciplines, de l'optique à la physique quantique, du traitement du signal à la connectivité et à l'intelligence artificielle. Rejoindre Thales, c'est repousser les limites de la technologie et la mettre au service du progrès et du développement durable de nos sociétés. C'est donc être au cœur d'une formidable aventure technique. Une attention portée à l'équilibre des collaborateurs au service de leur réussite. C'est pourquoi, notamment, nous nous efforçons de créer un environnement de travail accueillant et d'accorder la flexibilité nécessaire à l'équilibre entre vie professionnelle et vie personnelle. Nous savons que cet équilibre est essentiel à votre épanouissement et à la réussite des projets que nous vous confierons. Des parcours professionnels riches. Chez Thales, nous jouons collectif. Ce qui signifie travailler en équipe, côtoyer des experts et donc apprendre et développer ses compétences en permanence tout en faisant bénéficier le Groupe de son savoir-faire. C'est aussi la possibilité d'évoluer, de changer de fonction ou d'activité, voire de pays.\n    QUI SOMMES-NOUS ?\n    L'activité Systèmes terrestres et aériens conçoit des systèmes, des équipements, des capteurs et des services pour le contrôle du trafic aérien civil et militaire, la défense aérienne ainsi que le combat naval et terrestre.\n    A 20mn du cluster Paris-Saclay, le site de Limours réunit plus de 900 collaborateurs travaillant de la conception des solutions à la recette avec les clients, en passant par la production, des radars de surface. Ce site a connu ces dernières années de grandes évolutions et continue à s'adapter aux besoins des clients en termes de surveillance du ciel et de zones sensibles.\n    QUI ETES-VOUS ?\n     * De formation ingénieur ou équivalent, vous avez une expérience confirmée en architecture logiciel et/ou ingénierie des systèmes logiciels ?\n     * On vous reconnait une capacité à dynamiser les équipes ?\n     * Votre flexibilité et ouverture d'esprit vous permettent d'aboutir à des compromis dans vos négociations ?\n     * Vous avez une bonne capacité d'analyse et de méthode dans l'approche des problèmes ?\n    CE QUE NOUS POUVONS ACCOMPLIR ENSEMBLE :\n    Rattaché(e) au centre de compétences Radar Embedded Processing (REP) au sein du Domaine Surface Radar, vous êtes en charge de l'architecture complète d'un traitement numérique pour un des radars du portfolio du Surface Radar.\n    En nous rejoignant, vous vous verrez confier les missions suivantes :\n     * Définir l'architecture de la solution numérique complète, allouer les fonctions, définir les interfaces des produits à développer,\n     * Allouer les fonctionnalités logicielles du système complet aux sous-ensembles numériques (PCs, FPGA, DSP), en accord avec l'ingénierie radar et les responsables des sous-ensembles,\n     * Gérer les risques et opportunités techniques ainsi que les actions associées sur un produit avec un historique,\n     * Valider et commenter les documents de spécification logiciels,\n     * Proposer des innovations et participer à l'amélioration continue des méthodes de travail.\n    Vous collaborez avec :\n     * Les équipes d'ingénierie du Business Segment concerné pour appréhender et décliner les besoins,\n     * Les équipes REP, qui développent les constituants du traitement numérique :\n     + La plateforme matérielle\n     + La plateforme applicative constitué d'OS, de middleware et durcissements associés  \n     + Les logiciels de traitements sur PC (CPU, GPU) ou DPS et/ou FPGA\n     * Les équipes REP, qui intègrent les éléments du traitement numérique avant livraison aux équipes radar,\n     * Les équipes d'intégration radar pour la mise au point système.\n    VOTRE CARRIÈRE CHEZ THALES :\n    Différentes opportunités vous permettront de découvrir d'autres domaines ou sites. Vous pourrez évoluer et développer vos compétences dans différents domaines :\n     * Explorez un espace attentif au développement personnel\n     * Développez vos talents dans un autre domaine du groupe Thales, en découvrant de nouveaux produits, de nouveaux clients, un nouveau pays ou en vous orientant vers une solution plus complexe\n     * Choisissez entre une expertise technique ou un parcours de le",
        "title": "data architect",
        "skills": {}
    },
    {
        "source": "France Travail",
        "link": "https://candidat.francetravail.fr/offres/recherche/detail/2740701",
        "company": "AXA FRANCE ",
        "location": "Hauts-de-Seine",
        "remote": null,
        "publication_date": "2024-08-22",
        "details": {
            "TypeContract": "CDI",
            "Salary": null,
            "Experience": "expérience exigée",
            "Level": null
        },
        "company_data": {
            "sector": null,
            "company_size": null,
            "turnover_in_millions": null
        },
        "description": "Au sein de l'équipe Socles Big Data et Machine Learning, l'architecte solution Big Data & ML sera amené à :\n- Contribuer à l'évolution de l'offre de service de la plateforme Big Data & ML\n- Définir et maintenir le cadre de référence des principes d'architecture\n- D'accompagner les développeurs dans l'appropriation de ce cadre de référence,\n- Définir les solutions permettant de répondre aux besoins d'exposition, de consommation ou d'export de données des métiers\n- D'accompagner les développeurs et les différentes parties prenantes dans la mise en œuvre des solutions proposées.\n\nDe Formation scientifique (école d'ingénieur, école d'informatique), vous justifiez de :\nAu moins 5 ans dans la définition d'architecture de traitement de données Big Data et une connaissance avancée sur les principes de traitements distribués.\n\nVous avez eu une expérience professionnelle sur le cloud Microsoft Azure avec des outils comme Azure Databricks, Azure Data Lake Storage, Azure Data Factory et la topologie réseau sous-jacente. Terraform, Qlik seraient un plus.\n\nVous avez une connaissance solide des différents patterns d'architecture Big Data.\n\nVous êtes familiers aux principes cloud, devops et aux processus de continuous delivrery dans un environnement agile, ainsi qu'aux concepts ML et LLM.\n- La définition d'architecture cloud\n- l'automatisation des ressources azure\n- Gestion de sources Git et modèles de collaboration\n- Intégration & livraison continue avec Azure Pipelines\n- Gestion des artefacts avec Azure Artifact\n- Automatisation des déploiements\n- Traitements Big Data en mode Streaming\n- Pratiques et optimisations FinOps\n- Framework MLOps\n- Mise en place d'API LLM\n\nIdéalement vous avez déjà participé à la mise en œuvre d'architecture et solutions ML et LLM. AXA France développe actuellement un socle LLMOPS autour d'une solution groupe dont le cœur est AXA Secure GPT (API LLM). Cette solution nous permettra de tester plusieurs LLMs (Version de Chat GPT, Mistral, Claude, LLaMA, ...)\n\nDe nature pragmatique, vous êtes capable d'accompagner de manière pédagogique les métiers dans la définition de solutions répondant à leur besoin. Vous avez de bonnes aptitudes relationnelles, et vous faites preuve d'une grande curiosité et de capacité d'innovation et d'adaptation.\n\nNotre raison d'être chez AXA ? Chaque jour, nous agissons ensemble pour le progrès humain en protégeant ce qui compte. Une mission qui donne le sourire et envie de se lever le matin ! \n\nUn des leaders mondiaux de l'assurance dans la protection des biens, des personnes et des actifs, AXA c'est  collaborateurs et contributeurs qui s'engagent au quotidien pour nos clients, c'est 51 pays dans lesquels nous distribuons nos produits et services et plus de 90 millions de client qui nous font confiance dans le monde. Employeur citoyen et responsable, AXA s'engage au quotidien pour des causes sociétales & environnementales. Nous menons une politique inclusive engagée pour reconnaître et valoriser les différences individuelles. Ces ambitions vous parlent ? Alors venez changer le monde avec nous ! \n\nVictime ou témoin, en cas de discrimination, vous pouvez adresser vos signalements et/ou alertes discrimination à : \"Pour postuler, cliquez sur le bouton de candidature Monster\"\n\nNous sommes persuadés que pour bien prendre soin de nos clients, nous devons commencer par bien prendre soin de nos collaborateurs ! Les avantages que nous proposons à nos salariés sont nombreux. \n\n Nous choisir, c'est bénéficier par exemple : \n\n D'un  package de rémunération  complet comprenant un salaire fixe, un complément de rémunération variable, des primes, de la participation et de l'intéressement, la possibilité d'acquérir des actions AXA, ou encore des solutions d'épargne avantageuses ;  D'un  cadre de travail flexible  jusqu'à 3 jours de télétravail possible par semaine (selon profil du poste), des tickets restaurant pour les jours télétravaillés ou encore une participation à l'achat d'un écran ou fauteuil ergonomique ;  D'une politique visant à  concilier vie personnelle et vie professionnelle  avec 28 jours de congés payés, entre 14 et 16 RTT selon les années, des formules de travail à temps partiel ou encore des jours d'absence rémunérées pour la rentrée scolaire ou un déménagement par exemple ;  De la possibilité de s'engager pour une cause qui vous tient à cœur grâce à nos associations telles que AXA Atout Cœur, AXA Compétences Solidaires ou encore AXA Prévention ;  Et bien  plus encore  ! Perspectives de développement des compétences et de carrières immenses, CE, conciergerie, offres privilèges, soutien en cas d'épreuve s'arrête là, la liste est longue",
        "title": "data architect",
        "skills": {
            "BigData": [
                "Databricks"
            ],
            "CloudComputing": [
                "Azure"
            ],
            "DevTools": [
                "Git"
            ],
            "InfrastructureAsCode": [
                "Terraform"
            ],
            "Other": [
                "ML",
                "Machine Learning",
                "Big Data",
                "DevOps",
                "Cloud"
            ],
            "EnSoftSkils": [
                "Collaboration"
            ]
        }
    }
]