[
    {
        "source": "France Travail",
        "link": "https://candidat.francetravail.fr/offres/recherche/detail/2653053",
        "company": null,
        "location": "Hauts-de-Seine",
        "remote": null,
        "publication_date": "2024-08-21",
        "details": {
            "TypeContract": "CDI",
            "Salary": null,
            "Experience": "débutant accepté",
            "Level": null
        },
        "company_data": {
            "sector": null,
            "company_size": null,
            "turnover_in_millions": null
        },
        "description": "Entrez dans notre univers « être sérieux sans se prendre au sérieux » !\nCabinet à forte croissance, Cenova accompagne ses clients du #Luxe, du #Retail et du #Tourisme/Loisirs dans leurs projets de transformation Data et Digitale, et ce sur l'ensemble des problématiques métiers (marketing, produit, supply, RSE, .).\nVOTRE FUTURE MISSION :\nVous travaillerez pour le compte de l'un de nos clients, au sein de l'équipe Data sur le développement de solutions Data Analytics. Vos principales missions seront les suivantes :\n· Concevoir et mettre en œuvre des solutions de traitement de données dans un environnement #Cloud\n· Mener des études de faisabilité et préconiser les architectures data cibles\n· Créer, tester et déployer des pipelines de données d'extraction, de transformation et de chargement\n· Mettre en application les concepts de CI/CD via les outils dédiés\n· Participer à la mise en œuvre de produits de Data visualisation : dashboard, reporting...\n· Participer aux ateliers de collecte des besoins auprès des équipes métiers\n· Rédiger la documentation (spécification techniques, document d'exploitation, dossier d'architecture...) et analyser les solutions les plus adaptées\n· Assister les phases de recette utilisateurs (identification ou mise en place de jeux de tests, recueil et traitement des demandes de changements)\n· Accompagner et former les utilisateurs à la prise en main des solutions\nEnvironnement technique :\n· Cloud : #Azure, #GCP, #AWS\n· Langages : SQL, Python, Spark, Scala, Javascript\n· Base de données : SQL Server/SQL Cloud, Google BigQuery, Oracle, MySQL, MongoDB\n· Datamanagement : Azure Data Factory / Databricks/ Synapse (idéalement), Google Cloud Data Fusion / Datafllow, DBT, Talend, SQL Server Integration Services.\n· Datavisualisation : Power BI (idéalement), Tableau, Qlik, DataStudio/Looker\n· Repository : GIT, Azure DevOps, SVN\n· Systèmes d'exploitation : Unix, Linux, Windows\nVOTRE PROFIL :\nVous avez une expérience minimale de 2 ans sur des missions de Data Engineering et vous disposez d'une grande appétence technique.\nVous appréciez comprendre le cycle de vie de la donnée et vous êtes amateur de datavisualisation, notamment sur PowerBI.\nVous avez par ailleurs, le contact facile et vous comprenez les enjeux business et adaptez vos analyses en ce sens.\nVous êtes proactif(ve), autonome, bon(ne) communiquant(e) et vous êtes à l'aise en anglais.\nPOURQUOI NOUS REJOINDRE ?\nAu-delà de missions passionnantes dans des secteurs en pleine transformation, Cenova c'est avant tout un cabinet à taille humaine avec :\n¿ Un respect de vos attentes concernant vos missions et une réelle proximité managériale pour vous accompagner\n¿ La CenoAcademy pour vous former et nos CenoTalk pour partager nos expertises et connaissances\n¿ La CenoLife pour vous apporter une vie de cabinet stimulante (afterworks, séminaires, évènements sportifs...)\n¿ De multiples avantages en complément d'une rémunération attractive : la mutuelle Alan, un CE, des titres restaurants, des primes vacances, le télétravail et plein d'autres jolis avantages.\nCes quelques mots suscitent votre curiosité ? Candidatez ! Votre personnalité et votre savoir-faire feront le reste. Notre processus se déroule en 3 entretiens : RH, Manager et rencontre avec un associé !\nType d'emploi : Temps plein, CDI\nStatut : Cadre\nAvantages :\n* Prise en charge du transport quotidien\n* RTT\n* Travail à domicile occasionnel\nHoraires :\n* Du lundi au vendredi\nRémunération supplémentaire :\n* Prime annuelle\n* Primes\nLieu du poste : Télétravail hybride (92200 Neuilly-Sur-Seine)",
        "title": "data engineer",
        "skills": {
            "ProgLanguage": [
                "Python",
                "Scala"
            ],
            "DataBase": [
                "MongoDB",
                "SQL"
            ],
            "BigData": [
                "Spark",
                "Databricks"
            ],
            "DataVisualisation": [
                "Power BI",
                "Tableau"
            ],
            "CloudComputing": [
                "GCP",
                "Azure",
                "AWS"
            ],
            "DevTools": [
                "Git"
            ],
            "OS": [
                "Linux",
                "Windows"
            ],
            "DBMS": [
                "BigQuery",
                "SQL Server",
                "MySQL"
            ],
            "Other": [
                "CI/CD",
                "Cloud",
                "DevOps"
            ]
        }
    },
    {
        "source": "France Travail",
        "link": "https://candidat.francetravail.fr/offres/recherche/detail/2647714",
        "company": null,
        "location": "Rennes",
        "remote": null,
        "publication_date": "2024-08-21",
        "details": {
            "TypeContract": "CDI",
            "Salary": null,
            "Experience": "débutant accepté",
            "Level": null
        },
        "company_data": {
            "sector": null,
            "company_size": "-",
            "turnover_in_millions": null
        },
        "description": "La Direction Grand Ouest recherche un Expert Big Data pour renforcer ses équipes.Curieux et passionné(e) par le Big Data, vous êtes motivé(e) pour apporter votre expertise et vos compétences sur des technologies comme Hadoop, Spark, MongoDB, Kafka, Elastic Search,...Intégré(e) à l'équipe Big Data, vous prenez en charge plusieurs missions :Participer à la capitalisation du savoir déployé lors des projets et à son partage avec les agences du Groupe. Animer la montée en compétences des collaborateurs rattachés à votre domaine d'expertise Participer aux phases d'avant-vente: Rédaction de proposition commerciales, Chiffrages, Soutenances, ... Participer à des missions de conseil et/ou d'expertise auprès de nos clients  Gérer un ou plusieurs projets dans des contextes mono ou multi-client.Dans ce contexte, vous devez :Assurer une relation de proximité avec vos clients, auprès desquels vous serez l'interlocuteur privilégié. En relation avec la direction, vous préparez et animez les instances de décisionnelles que les comités de pilotage. Encadrer et faire progresser les différents intervenants sur les projets que vous gérez. Reporter et alerter sur la production, le planning, l'organisation et les membres de l'équipe. Dans ce cadre, vous êtes moteur sur les propositions de solutions à mettre en place et vous participez à l'élaboration et à la mise en oeuvre des plans d'action Détecter les nouveaux besoins client, que vous partagez avec le Directeur.  Promouvoir les offres et le savoir-faire d'Orange Business auprès de vos clients.",
        "title": "Other",
        "skills": {
            "DataBase": [
                "MongoDB"
            ],
            "BigData": [
                "Spark",
                "Hadoop"
            ],
            "MachineLearning": [
                "Orange"
            ],
            "Other": [
                "Big Data"
            ]
        }
    },
    {
        "source": "France Travail",
        "link": "https://candidat.francetravail.fr/offres/recherche/detail/2647411",
        "company": null,
        "location": "Rennes",
        "remote": null,
        "publication_date": "2024-08-21",
        "details": {
            "TypeContract": "CDI",
            "Salary": null,
            "Experience": "débutant accepté",
            "Level": null
        },
        "company_data": {
            "sector": null,
            "company_size": "-",
            "turnover_in_millions": null
        },
        "description": "Au sein de notre agence Rennaise, vous intégrez une équipe projet et contribuez à toutes les phases de mise en oeuvre d'une application décisionnelle.Vos principales missions :Animer des études de cadrage.Auditer des architectures DATA existantesDéployer des infrastructures DATA cloud ou on-premiseTransmettre ses compétences à des profils ayant une trajectoire d'expertiseRester informer, se former et former sur les nouvelles solutions DATADomaine de compétences techniques :Maîtrise des technologies du Big Data (Hadoop, Spark, Kafka, Nifi, ELK...)Maitrise des outils de déploiement automatisé et DEVOPS (ANSIBLE, JENKINS, DOCKER, KUBERNETES...)Connaissance au moins d'une architecture Cloud (AWS, AZURE, GCP...)Connaissances d'au moins un langage de programmation objets ou/et de langage scripts (Java, Javascript, Scala, Python...)Connaissances en solutions de bases de données (SQL, NoSQL...)Quelques exemples de missions actuelles :Revue d'une architecture hybride Cloudera/Azure pour un client souhaitant évoluer vers l'industrie 4.0Mise en place d'une plateforme data sous Kubernetes à base de composants open source pour bénéficier des avantages du cloud sur un environnement sécurisé souverainIndustrialisation d'outils de monitoring Kafka sous Ansible pour un client dans le secteur du transport",
        "title": "data architect",
        "skills": {
            "ProgLanguage": [
                "Java",
                "Python",
                "Scala"
            ],
            "DataBase": [
                "NoSQL",
                "SQL"
            ],
            "BigData": [
                "Spark",
                "Hadoop"
            ],
            "CloudComputing": [
                "GCP",
                "Azure",
                "AWS"
            ],
            "DevTools": [
                "Docker",
                "Jenkins"
            ],
            "Automation": [
                "Ansible",
                "Kubernetes"
            ],
            "Containers": [
                "Docker",
                "Kubernetes"
            ],
            "Other": [
                "Cloud",
                "DevOps",
                "Big Data"
            ]
        }
    }
]