[
    {
        "source": "LinkedIn",
        "company": "La Javaness",
        "location": "Paris, Île-de-France, France",
        "link": "https://fr.linkedin.com/jobs/view/data-architect-at-la-javaness-3646114499?position=2&pageNum=0&refId=a5rwPua%2FMvx%2F2M%2FPSF0oPA%3D%3D&trackingId=Yk0NP1kjoSKWXhEqbeXfPA%3D%3D&trk=public_jobs_jserp-result_search-card",
        "description": "En 5 ans, La Javaness s'est imposée comme leader français de l'IA pour les entreprises (BtoB). Sans tambour ni trompettes (mais avec beaucoup de R&D !), nous avons concentré nos forces à déployer l'Intelligence Artificielle à grande échelle au sein d'organisations publiques et privées en France et en Europe.\nMais pas n'importe comment ! Nous croyons en une IA éthique, responsable, au service des salariés et des citoyens européens. Nous militons pour la souveraineté des données et l'indépendance des entreprises européennes.\nPragmatiques et rationnels, nous déployons quotidiennement nos solutions « prêt-IA-porter » à un niveau industriel. Nous faisons aussi de la haute couture en développant des solutions IA sur-mesure pour répondre aux défis de certains de nos clients. Notre R&D bout sans relâche pour inventer, tester et déployer l'IA de demain.\nEn d'autres termes, dans la boutique de La Javaness, tu trouveras : Conseil data & IA, accélération par le design, développement front & back de pointe, défis business dans un joyeux mix exigeant d'intelligences. Avec ce super cocktail d'expertises et de créativité, nous intervenons sur tous les secteurs d'activité pour cracker les problèmes de nos clients !\nNous sommes le partenaire Data et IA de référence pour l'AMF, LCL, la Banque de France ou encore Pôle Emploi. Nous accélérons également des projets d'innovation digitale pour la Société Générale, Facebook, Enedis, Saint Gobain, Louvre Hôtels Group...\nComment ça marche au quotidien ?\nNos expertises Design, IT, Data, Delivery & Business, travaillent ensemble sur tous les projets afin de concevoir et déployer des solutions complètes et innovantes répondant aux besoins de nos clients.\nFort d'un collectif unique, la Javaness investit sans cesse dans des talents pointus, atypiques et complémentaires qui lui confèrent une force de frappe hors norme. Et parce qu'on est pas que des machines, la \"Fullstackerie\" s'exprime aussi joyeusement lors de nos fameux apéros au débotté et de notre séminaire annuel.\nSi ça te semble une aventure à ta mesure, c'est par ici pour nous rejoindre !\nDescriptif du poste:\nVos missions:\nAnalyser les étapes du cycle de vie des données manipulées par les processus métier de nos clients\nConcevoir, ou transformer après analyse préliminaire, les processus et outillages technologiques qui sous-tendent les processus métier, en fonction des besoins et contraintes métier et techniques\nCommuniquer les décisions d'architecture aux équipes\nParticiper à l'élaboration du référentiel de technologies, outils, procédures, normes, vocabulaire, sécurité des systèmes d'information\nParticiper à l'effort de veille technologique\nParticiper aux phases d'avant-vente par des études de faisabilité et d'impact, d'architecture, de choix technologiques et d'estimations de charges\nEtre en support de la phase de delivery des projets\nCollaborer avec les autres compétences Data science, Développeurs, Opérations, UX/UI, PM/PO, Business, de La Javaness\nParticiper au développement de La Javaness via le recrutement, la structuration et animation interne, le networking, l'événementiel, ..\nRequirements\nVous possédez une solide expérience:\nde l'appréhension du cycle de vie de la donnée et des processus métier associés,\nde l'élaboration d'architectures de données et de l'industrialisation de solutions de data management par leur intégration dans un SI complexe et sécurisé,\ndes technologies de data management et data engineering (ETL/ELT, DQM, portail de données, data preparation, data virtualization, data catalog, data lineage, BI),\ndes architectures de données et de leurs systèmes de gestion (Datawarehouse, Data Lake),\ndes exigences que font peser les architectures de données sur les infrastructures système et réseau\nde data science et machine learning (frameworks, librairies),\nde veille technologique. Vous êtes pédagogue, avez un bon relationnel et surtout, un esprit entrepreneurial !\nVous pouvez justifier d'expériences significatives (7 - 10 ans) dans ce type de poste, et en particulier en gestion de projets et accompagnements de solutions Big Data et IA.\nAnglais requis.\nBenefits\nAmbition et innovation\nPackage attractif : complémentaire santé, prime déjeuner 98€/mois, Navigo 100%, 25 jours de congés payés par an, RTT\nParis Bonne Nouvelle\nShow more\nShow less",
        "details": {
            "JobDetail": [
                "Full"
            ],
            "TypeContract": "",
            "Salary": "98",
            "Level": "",
            "Experience": "5 an(s)"
        },
        "title": "data architect",
        "skills": {
            "ProgLanguage": [
                "R"
            ],
            "DataAnalytics": [
                "R"
            ],
            "Other": [
                "Machine Learning",
                "Big Data"
            ]
        }
    },
    {
        "source": "LinkedIn",
        "company": "Ippon Technologies",
        "location": "Paris, Île-de-France, France",
        "link": "https://fr.linkedin.com/jobs/view/architecte-data-at-ippon-technologies-3851530940?position=3&pageNum=0&refId=a5rwPua%2FMvx%2F2M%2FPSF0oPA%3D%3D&trackingId=WUE05ZbK1%2BRSQiee2Y2X%2BA%3D%3D&trk=public_jobs_jserp-result_search-card",
        "description": "Ippon : cabinet de conseil et d'expertise en technologie, international et indépendant.\nVous intégrerez notre communauté data\n, composée d’une équipe de\n70 experts sur 9 agences en France.\nNotre spécialité est de\nconstruire des data platforms dans le cloud public avec les meilleures technos du moment.\nLa data chez Ippon, c’est déjà plus de\n250 certifications AWS, GCP et AZURE,\ndes\nspeakers à l’AWS Summit, des partenariats avec Snowflake, Databricks, DBT, un blog technique\navec des publications régulières.\nDescriptif du poste :\nCe poste est un vrai challenge aussi bien en termes de\ndéfis techniques que de gestion d’équipe.\nLa réussite de vos projets sera portée par votre capacité à vous adapter et à monopoliser un large panel de compétences techniques.\nVous devrez être le/la leader de votre équipe en gardant à l’esprit l’ensemble des\nbonnes pratiques d'architectes\n, de sécurité et d’automatisation nécessaires à la réussite du projet.\nEn tant que\nreprésentant(e) de l’engagement d’Ippon\nsur les sujets qui vous seront confiés, vous serez amené(e) à\ntravailler avec notre équipe commerciale\ndès les phases de qualification\net lors de la validation de jalons de la roadmap que vous aurez préalablement validé avec le client. Vous interviendrez également dans la sélection de l’équipe qui sera affectée à votre projet.\nVotre rôle :\nGrâce à votre position d’architecte vous avez une vision experte et systémique de l’ensemble des composants d’une Modern Data Platform.\nVous maîtrisez le panel des exigences fonctionnelles et non fonctionnelles à collecter afin d’assurer l’efficience opérationnelle et la pérennité de la data platform.\nVous êtes expert(e) et maîtrisez tous les outils et services d’au moins un écosystème parmi les 3 principaux leaders du marché (AWS, Azure et GCP) et avez des facilités pour étendre votre champ de compétences.\nVous êtes proactif/ve sur la veille technique et la capitalisation et veillez à garder toujours un temps d’avance sur l’état de l’art du secteur afin de pouvoir guider vos clients.\nEn tant qu’architecte expérimenté(e) vous pouvez indifféremment intervenir sur des missions de delivery pour concevoir la solution cible ou en phase de cadrage amont pour guider les choix et construire les roadmaps.\nVous êtes pédagogue et savez communiquer et vulgariser des réflexions complexes pour les rendre accessibles à tous.\nNotre éco-système technique :\nCloud : AWS, GCP, Azure\nLangage de programmation data : Python, SQL, Scala\nApproche Data Warehouse : Redshift, Snowflake, BigQuery\nApproche Data Lakehouse : Databricks, Starburst, Glue-Athena-S3\nIngestion : AWS Glue, Airbyte, dbt\nStockage : AWS S3, Google Cloud Storage, Azure Blob Storage\nOrchestration : Airflow, AWS Step function\nGouvernance : cataloging, sécurité, scope d'accès\nBatch et Streaming : Kafka, Amazon Kinesis, Google DataFlow\nOutil de visualisation : Tableau, Power BI, Metabase, Superset\nVotre évolution chez Ippon :\nVous serez accompagné(e) dans votre montée en compétences aussi bien technique que leadership grâce à\nnotre programme BlackBelt\n(programme de formation continue : mentoring, formations, certifications).\nEn tant que membre d’une communauté,\nvous pouvez avoir différents rôles :\nCelui de manager technique (MT) : manager d’une équipe de 7 ingénieur(e)s Ippon (onboarding, suivis, accompagnement, mise en place d’objectifs…). Vous conduirez les entretiens techniques en binôme\nResponsable de l’accomplissement d’une ou plusieurs actions stratégiques de la Core Team Data\nDevenir speaker lors de Meetup, Summit, Talks internes, auprès des écoles …\nDevenir formateur(trice) et accompagner la nouvelle génération d’Ippon dans leur montée en compétences\nVous avez d’autres souhaits, pas de soucis, nous en discuterons durant notre échange et répondrons à toutes vos questions.\nPrésentiel ou télé-travail ?\nLes deux !\nLa plupart de nos clients sont en hybride et notre politique de télétravail est classique : 3 jours présentiel / 2 jours TT.\nNotre processus de recrutement :\nUn call RH (20 min)\nPuis un entretien RH et Commerce pour que nous puissions échanger sur ce que vous recherchez et ce que nous pouvons vous proposer (1h)\nEnfin, un entretien technique avec un référent technique (1h)\nSi vous êtes intéressé(e) mais que vous avez encore des questions, n'hésitez pas à nous contacter sur LinkedIn\nSinon il ne vous reste plus qu’à cliquer sur\nPostuler\nShow more\nShow less",
        "details": {
            "JobDetail": [
                "Hybride"
            ],
            "TypeContract": "",
            "Salary": "",
            "Level": "",
            "Experience": null
        },
        "title": "data architect",
        "skills": {
            "ProgLanguage": [
                "Scala",
                "Python"
            ],
            "DataBase": [
                "SQL"
            ],
            "BigData": [
                "Databricks"
            ],
            "DataVisualisation": [
                "Power BI",
                "Tableau"
            ],
            "CloudComputing": [
                "GCP",
                "AWS",
                "Azure"
            ],
            "DBMS": [
                "BigQuery",
                "Snowflake"
            ],
            "Automation": [
                "Airflow"
            ],
            "Other": [
                "Cloud"
            ],
            "EnSoftSkils": [
                "Leadership"
            ]
        }
    },
    {
        "source": "LinkedIn",
        "company": "MCA",
        "location": "Marseille, Provence-Alpes-Côte d'Azur, France",
        "link": "https://fr.linkedin.com/jobs/view/data-architect-at-mca-3907802841?position=4&pageNum=0&refId=a5rwPua%2FMvx%2F2M%2FPSF0oPA%3D%3D&trackingId=AqBqXAtI3a6pEmFBU%2Bm1cQ%3D%3D&trk=public_jobs_jserp-result_search-card",
        "description": "MCA est un Groupe de Conseil en Ingénierie et Hautes Technologies qui compte 1500 collaborateurs en France et à l’International.\nFort de nos 30 ans d’expérience, nous accompagnons nos clients dans la réalisation de leurs projets.\nNous rejoindre, c'est intégrer une entreprise dynamique qui a à cœur d’accompagner ses collaborateurs.\nVous bénéficiez d'un suivi personnalisé et régulier ainsi que de nombreuses formations qui participeront à votre montée en compétences.\nDétail projet :\nDate de démarrage :\nASAP\nExpérience nécessaire :\n6 - 9 ans\nLangue :\nfrançais et anglais\n(Niveau C1)\nContexte de la mission\n:\nNous cherchons un Data Architect qui aura la responsabilité complète de l'architecture.\nNous recherchons une personne ayant une bonne compréhension globale des services disponibles d’Azure Analytics.\nCette personne travaillera en collaboration avec plusieurs équipes Produits. Il aura en charge l’architecture des données, et viendra en soutien aux équipes dans l’intégralité du cycle de vie de la gestion des données.\nLe consultant devra par ailleurs avoir une expérience opérationnelle afin d’être en mesure de configurer différents environnements et services.\nIl/Elle devra faire preuve de leadership dans le but d'endosser le rôle de Leader Technique, et point d’entrée avec les parties prenantes de l’entreprise\nUsage quotidien de l’anglais comme langue de communication dans la fonction\nTâches à réaliser\n:\nVous assurez le leadership technique, participez au développement, et représentez les ressources internes et externes de la plateforme\nVous serez un membre actif de l’équipe des architectes, afin de superviser le processus de gestion des données et fournir des conseils et orientations aux équipes de développement\nVous serez responsable de la conception, et de la documentation de la solution dans votre domaine\nCompétences recherchées :\nObligatoires\n:\nExpérience dans le développement, la documentation et la maintenance de modèles de données logiques et physiques\nExpérience sur Databricks, ADLS storage, SQL DB, ADF et Power BI\nExpérience dans la définition et la maîtrise d'une architecture de données évolutive de bout en bout, en tenant compte de l'architecture de l'entreprise et des normes industrielles.\nParticipation à l'élaboration d'architectures, stratégies et politiques en matière de données, y compris la sécurité des données\nLangage SQL Writing et modélisation de données\nData Architecture\nPower BI\nAzure ADFv2, Databricks, Synapse, Delta Lake\nEnvironnement et technologie Azure Advanced Analytics\nPython, Pyspark\nMicrosoft cloud basé sur modèle Delivery\nData Management, Data Governance et Data Quality\nDéploiement d’APIs et micro-services\nDevSecOps\nAgile\nExpérience professionnelle dans un environnement international\nOptionnelles :\nExpérience dans le secteur automobile\nVos perspectives d’évolution :\nNotre objectif premier est de vous donner toutes les clés pour réussir et ainsi accéder aux différentes évolutions que nous proposons.\nÀ terme, vous pourrez évoluer sur d'autres secteurs d'activités, mais aussi vous projeter en interne sur des postes en France ou à l'international.\nCe poste est ouvert aux personnes en situation de handicap.\nShow more\nShow less",
        "details": {
            "JobDetail": [],
            "TypeContract": "",
            "Salary": "",
            "Level": "",
            "Experience": "30 an(s)"
        },
        "title": "data architect",
        "skills": {
            "ProgLanguage": [
                "Python"
            ],
            "DataBase": [
                "SQL"
            ],
            "BigData": [
                "Databricks"
            ],
            "DataVisualisation": [
                "Power BI"
            ],
            "CloudComputing": [
                "Azure"
            ],
            "Other": [
                "Cloud"
            ],
            "EnSoftSkils": [
                "Leadership",
                "Communication",
                "Collaboration"
            ]
        }
    },
    {
        "source": "LinkedIn",
        "company": "CEVA Logistics",
        "location": "Marseille, Provence-Alpes-Côte d'Azur, France",
        "link": "https://fr.linkedin.com/jobs/view/senior-data-architect-at-ceva-logistics-3919628481?position=5&pageNum=0&refId=a5rwPua%2FMvx%2F2M%2FPSF0oPA%3D%3D&trackingId=0HGOhEn7s5L%2BPwRgFdatBw%3D%3D&trk=public_jobs_jserp-result_search-card",
        "description": "DATA FACTORY MANAGER / SENIOR DATA ARCHITECT\nBased in France (Marseille or Puteaux).\nWHAT ARE YOU GOING TO DO?\nThe Senior Data Architect will join the Global IT Data and Digital organization at CEVA Logistics within the Global CIO organization and will report to the Head of the CEVA Global Data Factory.\nThis role operates in complex decision-making environments impacting the CEVA enterprise, works with senior management from IT, BD and Operations to ensure the best possible global solutions are available for our customers and CEVA employees alike.\nThe data architect will operate in the context of the set of the new Cloud Data Platform of CEVA and will contribute to its set up, development and growth and built up of the internal teams and resources of data architects and data analysts.\nMain Responsabilities:\n· Developing and implementing an overall organizational data strategy in line with business processes. The strategy includes data model designs, database development standards, implementation and management of data warehouses and data analytics systems.\n· Identifying data sources, both internal and external, and working out a plan for data management that is aligned with organizational data strategy.\n· Coordinating and collaborating with cross-functional teams, stakeholders, and vendors for the smooth functioning of the enterprise data system.\n· Managing end-to-end data architecture, from selecting the platform, designing the technical architecture, and developing the application to finally testing and implementing the proposed solution.\n· Planning and execution of big data solutions using appropriate technologies and ensure their full lifecycle and interoperability.\n· Defining and managing the flow of data and dissemination of information within the organization.\n· Integrating technical functionality, ensuring data accessibility, accuracy, and security.\n· Conducting a continuous audit of data management system performance, refine whenever required, and report immediately any breach or loopholes to the stakeholders.\nWHAT ARE WE LOOKING FOR?\nMaster's degree in computer science or equivalent work experience\nMinimum of 10 years of experience in IT systems design or development.\nMinimum 5 years of experience gained in data architecture and delivering large scale analytics data platforms environments.\nKnowledge of systems development, including system development life cycle, project management approaches and requirements, design and testing techniques\nProven experience in design and building data models, data domains and understanding business data products (proficiency in data modeling and design, including SQL development and database administration).\nUnderstanding of predictive modeling, AI models and technologies, Data mining, visualization and Machine Learning\nAbility to implement common data management and reporting technologies, as well as the basics of columnar and NoSQL databases, data visualization, unstructured data, and predictive analytics.\nStrong and broad knowledge of latest technology stacks and trends, cloud-based data platforms and data lakes (preferably AWS and Snowflake technologies)\nExperience with data integration methods and technologies (e.g., ETL, Data Virtualization, Master Data Management, Data Warehouse/Lakehouse).\nUnderstanding of business strategy and ability to deliver recommendations in sync with key objectives and experience in developing and driving IT roadmaps.\nCapacity to coordinate and collaborate with users, system designers, and developers in their day-to-day functions. As such, soft skills like effective communication, team management, problem-solving, and leadership are highly desirable.\nStrong analytical skills and business acumen, ideally in the logistics sector.\nFluent English and proven practice.\nWHAT DO WE HAVE TO OFFER?\nPermanent contract.\nHybrid work: 4 days at the office and 1 remote.\nCompetitive salary.\nYou will work for one of the world 's leading logistics operators that will help you in your career development by offering you multiple opportunities.\nYou will receive on the job training that help you to better understand operational processes.\nABOUT TOMORROW\nWe offer professional opportunities for you to develop in CEVA. We value your professional and personal growth.\nJoin CEVA for a challenging carrer.\nCEVA Iberia is committed to attracting, acquiring and retaining the best possible candidates in an equitable and inclusive manner that is consistent with labor laws and best practices.\n#LI-SP1\nShow more\nShow less",
        "details": {
            "JobDetail": [
                "Remote",
                "Full",
                "Senior"
            ],
            "TypeContract": "",
            "Salary": "Salary",
            "Level": "",
            "Experience": null
        },
        "title": "data architect",
        "skills": {
            "DataBase": [
                "SQL",
                "NoSQL"
            ],
            "CloudComputing": [
                "AWS"
            ],
            "DBMS": [
                "Snowflake"
            ],
            "Collaboration": [
                "Teams"
            ],
            "Other": [
                "Machine Learning",
                "Cloud",
                "Big Data"
            ],
            "EnSoftSkils": [
                "Leadership",
                "Communication",
                "Organization"
            ]
        }
    },
    {
        "source": "LinkedIn",
        "company": "Airswift",
        "location": "Paris",
        "link": "https://fr.linkedin.com/jobs/view/solutions-architect-at-airswift-3919714188?position=6&pageNum=0&refId=a5rwPua%2FMvx%2F2M%2FPSF0oPA%3D%3D&trackingId=b3MGM2D190q9EWNC%2FP5I3A%3D%3D&trk=public_jobs_jserp-result_search-card",
        "description": "🚀\nNow Hiring: Data-Cloud Solution Architect - FREELANCE\n📍 Location: On-site near Paris (3 days a week)\nAre you ready to join a cutting-edge Data Transformation initiative? We are seeking a talented\nData-Cloud Solution Architect\nto play a pivotal role in shaping the future of our client's data capabilities. This role offers an exciting opportunity to work on a complete set of data functionalities, from architecture and engineering to visualization and warehousing.\nRole & Responsibilities:\nProvide technical guidance and establish best practices for Snowflake account setup and configuration.\nManage Infrastructure-as-code and maximize automation.\nLead enhancements and deployments to support a fully federated Platform.\nAct as a Subject Matter Expert (SME) for all Snowflake-related queries.\nOwn platform-specific Snowflake documentation, including decisions and best practices.\nDesign the cloud environment holistically to meet all functional and non-functional requirements.\nExecute deployment, maintenance, monitoring, and management tasks.\nOversee cloud security for the account.\nComplete the integration of new applications into the cloud environment.\nRequirements:\nHigher education completed, preferably with a degree in Computer Sciences.\n5 to 10 years of experience in implementing Data Platforms in a cloud environment.\nFluent in French & English (must).\nDeep expertise in Snowflake.\nStrong skills in platform architecture, DBA, and cloud database administration.\nProficiency in AWS Architecture and cloud networking.\nExcellent communication, coordination, and collaboration skills.\nAbility to manage stakeholders, mitigate risks, and demonstrate leadership.\nOpen-mindedness and willingness to take on challenges.\nHighly motivated, adaptable, and flexible.\nThis is a contract position lasting until the end of 2024, with the possibility of extension. Join us in driving innovation and shaping the future of data! #DataArchitect #Snowflake #AWS #CloudComputing #ParisJobs #TechJobs\nShow more\nShow less",
        "details": {
            "JobDetail": [
                "Full"
            ],
            "TypeContract": "",
            "Salary": "",
            "Level": "",
            "Experience": null
        },
        "title": "data architect",
        "skills": {
            "CloudComputing": [
                "AWS"
            ],
            "DBMS": [
                "Snowflake"
            ],
            "Other": [
                "Cloud"
            ],
            "EnSoftSkils": [
                "Initiative",
                "Leadership",
                "Communication",
                "Collaboration"
            ]
        }
    },
    {
        "source": "LinkedIn",
        "company": "Micropole",
        "location": "Levallois-Perret, Île-de-France, France",
        "link": "https://fr.linkedin.com/jobs/view/data-architect-f-h-at-micropole-3652819338?position=7&pageNum=0&refId=a5rwPua%2FMvx%2F2M%2FPSF0oPA%3D%3D&trackingId=yzPwOD7STCK0AuX%2BJ6fjKg%3D%3D&trk=public_jobs_jserp-result_search-card",
        "description": "Rejoignez le Groupe Micropole. Devenez un #InnovativePeople !\nMission\nEn Résumé\nLocalité : Levallois-Perret\nType de contrat : CDI\nNiveau d’expérience : au moins 7 ans\nAccord de télétravail & Flex office\nVous êtes\npassionné(e) par la data\n? Vous êtes convaincus que l’optimisation du\npatrimoine data des entreprises\nest la clé de leur performance ? Vous voulez\nrendre les entreprises data intelligentes\net les aider à se transformer pour préparer dès à présent leur futur ?\nVous souhaitez rejoindre un groupe pionnier des grandes innovations data et digitales ?\nSi vous avez\nrépondu « Oui »\nà chacune de ces questions alors devenez Data Architect pour l’un de\nnos clients grands-comptes.\nPrêt(e) à rejoindre l’aventure Micropole ? N’attendez plus !\nAu sein de Micropole, nous vous proposons de rejoindre notre practice « Data Governance et Architecture », composée de 80 #InnovativePeople et reconnue comme leader européen de la Gouvernance des données.\nEn Tant Qu' Architect\nLes données en entreprise sont trop souvent organisées en silos ne laissant aux métiers qu'une vision parcellaire de l'information.\nAfin d'amener une plus grande valeur et de l'efficacité au niveau des processus opérationnels et décisionnels de l'entreprise, nous accompagnons nos clients dans la gouvernance de leurs données en les hiérarchisant au sein du système d'information. Nous abordons ainsi, le cycle de vie de la donnée produit depuis la R&D jusqu'au Digital.\nAu sein de Micropole, nous vous proposons de rejoindre notre practice « Data Gouvernance et Architecture » basée à Levallois-Perret, composée de 80 #InnovativePeople et reconnue comme leader européen de la Gouvernance des données.\nDans Vos Missions Quotidiennes, Vous Êtes Amené(e)s à\nÊtre l’interface entre le client et l’équipe projet :\nPrise en compte des enjeux métier afin d’aligner l’architecture sur la stratégie de l’entreprise notamment vis-à-vis de la transformation digitale des entreprises et des enjeux réglementaires ;\nDéfinir la roadmap de mise en œuvre ;\nDéfinir les principes d’urbanisation autour des données ;\nCadrer les projets : référentiels (MDM), Data Hub, Big Data, gouvernance des données, échange (ETL/ESB/IPaaS) ;\nAuditer les architectures existantes sur les axes qualité, et urbanisation des données ;\nAnimer les workshops de conception dans le cadre de projets d’implémentation ;\nAccompagner sur les phases de cadrage à la définition des modèles de données et des processus de gouvernance opérationnelle ;\nRéaliser la conception technique et fonctionnelle des interfaces d’échange.\nParticiper activement aux avant-ventes et démarche de validation de concepts :\nParticipation aux phases de réponses à appel d’offre ;\nParticipation sur la production de démonstrateur en lien avec nos partenaires éditeurs ;\nAnimation de séminaires d’acculturation à la data.\nProfil\nVos Compétences Techniques\nVous maitrisez au moins une solution du marché liée à la gouvernance des données (MDM, Data Catalogue, DQM, Data Fabric, IPaaS, ETL/ESB).\nVos Atouts\nVous avez au moins 7 ans d’expérience professionnelle sur la définition d’architecture data ;\nVous maîtrisez les concepts de la gouvernance des données, et disposez d’une d’expérience projet sur une des solutions leaders du marché ;\nVéritable coéquipier(e), vous avez à cœur de contribuer à la montée en compétence de votre équipe ;\nVous disposez d’un bon niveau de français et d’anglais, à l’oral comme à l’écrit.\nLa Vie Chez Micropole, C’est\nUne vie interne rythmée pour se familiariser à la culture d’entreprise et aux valeurs de Micropole ;\nDes évènements internes réguliers pour partager les connaissances aussi bien techniques que fonctionnelles ;\nUne politique de formation attractive et éclectique ;\nUn travail en équipe valorisé pour une meilleure cohésion ;\nLa participation à des projets internes sur la base du volontariat.\nDevenir #INNOVATIVEPEOPLE, c’est :\nIntégrer une communauté de 1100 experts passionnés répartis entre la France, la Belgique, le Luxembourg, la Suisse, l’Espagne et la Chine ;\nConstruire ensemble les solutions stratégiques et innovantes de demain pour accompagner nos clients dans leur transformation data et digitale ;\nParticiper au développement de nos 4 centres d’excellences cloud : AWS, Microsoft Azure, Salesforce, GCP ;\nEvoluer continuellement au travers de formations et de certifications sur les plus grandes technologies grâce à Micropole Campus ;\nS’assurer d’une innovation continue grâce à : notre écosystème de partenaires technologiques ; notre accélérateur de start’up databoost’R ; nos lieux d’innovations « innovativeSpaces » et de co-construction avec les clients ; notre management par les talents naturels.\nProcessus De Recrutement\nChez Micropole, le processus de recrutement est réactif et transparent.\nEtape 1 – Si votre profil correspond à nos besoins, vous êtes recontactés dans les 72 heures qui suivent votre candidature par Victoria notre Talent Business Partner dédiée à Data Gouvernance & Architecture pour une qualification téléphonique ainsi qu'un premier entretien en visio ;\nEtape 2 – Vous rencontrez un manager avec l’un de nos experts comme Aurélien, Régis ou Jofrey.\nEn fonction du poste, vous pouvez passer des étapes supplémentaires (entretien ou test technique).\nÀ PROPOS DU GROUPE MICROPOLE\nGroupe international de conseil et technologies innovantes, MICROPOLE est spécialisé dans les domaines de la Data & Digital. Depuis ses 14 agences situées en Europe et en Chine, les 1200 #INNOVATIVE PEOPLE du Groupe (consultants, Data scientists, architectes IT, experts métiers, ingénieurs, UX designers…) accompagnent leurs clients partout dans le monde sur l'ensemble des phases de leurs projets, du conseil à leur réalisation, et sur la conduite du changement.\nMICROPOLE réalise 35% de son chiffre d’affaires à l’international et est coté sur le marché Eurolist compartiment C d’Euronext Paris, segment Next Economy.\nPour en savoir plus : https://www.linkedin.com/company/micropole/\nInfos pratiques\nA 200m, le métro Anatole France (Ligne 3) et un accès à l'ensemble des commerce du centre ville de Levallois-Perret à moins de 2 min à pied.\nMot du Manager\nFace à des enjeux de compliance toujours plus exigeants et rigoureux, la gouvernance des données devient absolument indispensable pour garantir la cohérence, maitriser la qualité et la connaissance du socle des données des entreprises et assurer leur bonne mise en conformité.\nShow more\nShow less",
        "details": {
            "JobDetail": [],
            "TypeContract": "CDI",
            "Salary": "",
            "Level": "",
            "Experience": "7 an(s)"
        },
        "title": "data architect",
        "skills": {
            "ProgLanguage": [
                "R"
            ],
            "DataAnalytics": [
                "R"
            ],
            "CloudComputing": [
                "GCP",
                "AWS",
                "Azure"
            ],
            "Other": [
                "Cloud",
                "Big Data"
            ]
        }
    },
    {
        "source": "LinkedIn",
        "company": "AXA",
        "location": "Paris",
        "link": "https://fr.linkedin.com/jobs/view/enterprise-architect-digital-workplace-at-axa-3845642526?position=8&pageNum=0&refId=a5rwPua%2FMvx%2F2M%2FPSF0oPA%3D%3D&trackingId=1QxAWv6oNOBK0QHumiAgPA%3D%3D&trk=public_jobs_jserp-result_search-card",
        "description": "AXA GROUP OPERATIONS\nAXA is becoming a sustainable tech-led company and at AXA Group Operations we are one of the major catalysts for this transformation.\nWe set the tone by triggering and empowering the evolution of our insurance business model through technology and innovation, driving its concrete implementation globally at speed, with a high quality of advisory and execution.\nWe are present across 17 countries with committed, highly qualified teams. We leverage technology, data, sourcing, security and investment allocation in a global way, but also achieve economies of scale and synergies when necessary.\nAt\nAXA Group Operations\n, we want to be recognized in three fields of action:\nState-of-the-art Data Technology to drive customer experience\nState-of-the-art Procurement & Sourcing to drive efficiency and better manage risks\nHigh-Performing Global Team for stronger partnerships with AXA entities\nWorking as part the Group’s Technology Office, the\nDigital Workplace Entrerprise Architect,\nis responsible for providing architecture, vision, governance, problem anticipation and solving for IT on a transversal architectural level. This transversal scope of the architecture covers business, security, data, application and technology architecture.\nHe manages and coordinates, for his areas of responsibility – here transversal Workplace topics – , the work carried out by the other Architects cross-domains and Chief Architects / Chief Technology Officers from AXA Group Operations and AXA entities in close collaboration with GO departments for the global assets, with Group Security for the Security part, and with Business Partnership and the Markets/Entities for the entities related part.\nTransversal\nWorkplace topics\nscope will cover this non exhaustive list:\nDevice Management\nApplication delivery\nCollaboration & Productivity\nUX / QoS Monitoring\nWorkplace interaction with other domains (Security, IAM, Network, Cloud, Compliance…)\nThe\nDigital Workplace Entrerprise Architect\n's role is to\nsteer the Architecture evolution\nacross AXA to ensure the\nproper implementation\nof the IT Strategy and to be able to adopt new technologies and new market solutions in line with the business priorities, the foundations of the products structure and with the aim support AXA to become a Tech Led Company.\nThe individual in this position understands the Group business strategy, the Information Systems (IS) of the Group and anticipates future directions of the IT industry to relate them to future business needs and initiatives. The Lead Architect Expert produces\nkey architecture deliverables\n, leads international workgroups and studies to\nestablish IT directions\nfor the Group and is responsible for the architecture review of projects related to technologies in his domain of responsibility.\nMAIN MISSIONS :\nThe objective of architecture is to ensure that we build sustainable, robust and secured Information Systems at the right cost and that bring business value to support the corporate business and lines of business strategies.\nThe Digital Workplace Entrerprise Architect main activity is to craft the IT Strategy of the Group and act as a change agent to implement this IT Strategy through the Target Enterprise Architecture of the Group, and of individual countries within the Group. He may also be called upon to directly support PMs on some key projects.\nThe core activities of the Lead Architect Expert include the following for his own area of responsibility :\n1- Vision and Strategy\nSupport the definition and management of the company Technology vision, strategies and plans with focus on domains related to his role\n2- Contribute to Technology/Architecture CTO Community and Technology Governance of the Group:\nTo cover global and local dimensions, which includes ensuring design and solution choices made in the entities are conform to Group Strategy in order to secure Group interests over the long-term (Architecture boards…)\nTo share technological visions, opportunities, and risks company-wide, and in particular interact with senior business and IT executives\n3- Define, build and maintain architecture & design patterns, jointly with Product engineering teams aiming to minimize technical complexity and leverage convergence opportunities:\nArchitecture landscape\nArchitecture Model & Maturity\nArchitecture evolution and product design blueprints, HLD\nSupporting LLD delivery with Product teams\n4- Market Watch:\nParticipate to forums of leading companies (cross-industries) and vendors in order to use and/or influence technology evolutions\nIn particular, study industry trends and technologies in close collaboration with Group Data & Technology Innovation\nManage evaluation, development, and deployment of relevant technologies (technology lifecycle & roadmaps)\n5- Provide support to all Group IT supporting functions, in particular for Procurement and Finance for large negotiations or assets\nPROFILE\nExperience :\nStrong experience in IT Strategy, enterprise and solution architecture (10+ years)\nExperience on solutions architecture designs for very large projects/environments in particular in Workplace (both Device management and Collaboration)\nStrong change management skills with practical experience of transformation in an international environment\nFinancials (princiles, business cases, budgeting, business-planning, savings)\nStrives for excellence with deliverables of high quality and ability to work in sometimes tight planning\nDemonstrates to be a strong team member with an open and collaborative mind-set.\nSoft skills :\nThe person will have to interact and collaborate with multiple global and local stakeholders and different levels (peers, managers, experts, C-Levels…). To succeed in his role, this can be achieved through:\nLeadership – Exhibits strong results orientation, change leadership, adaptability and the ability to drive collaborative behaviour.\nOpenness and reaching out – Strong human relationship skills, exhibit curiosity and can see opportunities in situations, not just problems.\nCommunication skills – Exhibits strong skills in listening, spoken and written communication, collaboration and the ability to work in a global team. Lead Architect Experts are expected to have the ability to understand and discuss with both senior managers and IT, and explain in clear language complicated architectural concepts and strategies.\nVision – Lead Architecture Expert demonstrates architectural vision and beliefs and is able to express them clearly, champion them, and debate his point of view in on-line forums or in-person workshops.\nEmbracing of the new AXA values and new ways of working with courage to promote them against tradition\nOpenness to different opinions and creation of consensus\nProblem solving orientation and strong analytical, logical and interpretive ability to interpret scenarios, express concepts or models with several dimensions: architecture, business value, procurement, program approach …\nHas a deep understanding of the organizational structures, in order to be in a position to better identify improvement points\nInternational profile – A proven ability to work effectively in an international environment. In addition, exhibits a strong proficiency in English.\nTechnical skills :\nExpert knowledge in IT strategy focusing on Workplace Architecture with related infrastructure good practices\nExpertise in Workplace with critical thinking and decision making, information systems knowledge, innovation, knowledge of emerging technology, planning, risk management, systems thinking, application rationalization/TCO, IT Security and technical problem solving.\nGood expertise in the practice of Architecture (frameworks) to deliver a holistic view (architecture model)\nShow more\nShow less",
        "details": {
            "JobDetail": [
                "Senior"
            ],
            "TypeContract": "",
            "Salary": "",
            "Level": "",
            "Experience": null
        },
        "title": "data architect",
        "skills": {
            "Collaboration": [
                "Teams"
            ],
            "Other": [
                "Cloud"
            ],
            "EnSoftSkils": [
                "Leadership",
                "Collaboration",
                "Problem Solving",
                "Adaptability",
                "Communication",
                "Critical Thinking"
            ]
        }
    },
    {
        "source": "LinkedIn",
        "company": "VISEO",
        "location": "Boulogne-Billancourt, Île-de-France, France",
        "link": "https://fr.linkedin.com/jobs/view/data-architect-cloud-f-h-at-viseo-3904217803?position=9&pageNum=0&refId=a5rwPua%2FMvx%2F2M%2FPSF0oPA%3D%3D&trackingId=267fBpZ5knn1TQJTgrSw8g%3D%3D&trk=public_jobs_jserp-result_search-card",
        "description": "Rejoignez\nVISEO\net explorez un univers de possibilités où\nl'Humain\n, le\nCollectif\net le\nChallenge\nsont au cœur de notre ADN.\nQui êtes-vous ?\nSi pour vous être\nArchitecte Cloud & Data\n, c'est :\nIntégrer une équipe d'experts en solutions cloud et en gestion de données ;\nConcevoir et déployer des architectures cloud scalables et sécurisées sur Google Cloud Platform et/ou Azure ;\nMaîtriser les services GCP (BigQuery, Cloud Composer, Cloud Functions , Cloud Run) et/ou Azure (Synapse , Data Factory , ADLS , SQL Database)\nMaitriser les pratiques DevOps (CI/CD, monitoring, logging) ;\nMaitriser Python et ses bibliothèques data\nDécouvrir et tester les nouvelles plateformes data (Exemple : Microsoft Fabric)\nOptimiser les coûts et les performances des solutions cloud pour garantir une efficacité maximale ;\nCollaborer avec les équipes de développement pour intégrer les meilleures pratiques de gestion des données et d'analytique...\nAlors, vous êtes la personne que nous recherchons !\nSi vous avez une expérience significative en\narchitecture cloud et data\net que vous êtes prêt à relever de nouveaux\ndéfis\net à enrichir votre parcours professionnel, c'est le moment idéal pour nous rejoindre.\nCe que nous allons faire ensemble ?\nDécouvrez comment votre quotidien sera révolutionné en intégrant notre équipe basée à Paris. Vous pourrez :\nÊtre acteur dans la conception des solutions cloud et data, en apportant votre expertise technique ;\nAssurer la qualité et la sécurité des infrastructures cloud (conformité, résilience, performance) ;\nPartager vos connaissances et innover au sein d'un collectif passionné par les technologies de pointe.\nCe que nous avons à vous offrir ?\nDes formations avancées, des certifications GCP et un accompagnement personnalisé pour votre développement professionnel ;\nUn cadre de travail dynamique, flexible et agile pour une carrière sans frontières ;\nUn engagement profond pour l'environnement, la société, l'égalité et l'inclusion ;\nUn accord télétravail pour une harmonie parfaite entre vie professionnelle et personnelle.\nCe qui nous différencie ?\nUne communauté active d'experts en cloud et data : des ateliers réguliers, la participation à des conférences spécialisées ;\nDes dispositifs d'épargne salariale attractifs (PEE et PERECO) et l'opportunité de devenir actionnaire de VISEO ;\nUn partenariat étroit avec Google & Microsoft, offrant un accès privilégié aux dernières innovations et technologies cloud.\nEnvie de nous rejoindre ? Contactez-nous et adoptez le #VISEOspirit\nEn tant qu'employeur, VISEO s'engage en faveur de la diversité et de l'inclusion.\nÀ propos de VISEO\nAvec 3 000 collaborateurs présents sur 5 continents, VISEO combine agilité et expertise pour transformer le numérique en un véritable levier de compétitivité et de performance.\n#PositiveDigitalMakers\nGDPR MESSAGE:\nOur privacy policy has been updated to comply with the new regulations. We invite you to consult it by clicking here: https://www.viseo.com/fr/politique-de-confidentialite. The VISEO Group uses the data collected as part of your application to assess your suitability for the job in question. We use the Jazz HR tool to help us in our recruitment process. This tool complies with current regulations on the protection of personal data. The tool is hosted in the United States and is PrivacyShield certified for HR data. In all cases, we may keep your file for 5 years so that we can contact you again if another position matches your profile. You may, of course, object to this. To find out more about how your data is used and how you can exercise your rights, please consult our privacy policy https://www.viseo.com/fr/politique-de-confidentialite.\nShow more\nShow less",
        "details": {
            "JobDetail": [],
            "TypeContract": "",
            "Salary": "",
            "Level": "",
            "Experience": null
        },
        "title": "data architect",
        "skills": {
            "ProgLanguage": [
                "Python"
            ],
            "DataBase": [
                "SQL"
            ],
            "CloudComputing": [
                "GCP",
                "Google Cloud Platform",
                "Azure"
            ],
            "DBMS": [
                "BigQuery"
            ],
            "Other": [
                "Cloud",
                "DevOps",
                "CI/CD"
            ]
        }
    },
    {
        "source": "LinkedIn",
        "company": "PROXIAD",
        "location": "Lyon, Auvergne-Rhône-Alpes, France",
        "link": "https://fr.linkedin.com/jobs/view/data-architect-h-f-at-proxiad-3908705011?position=10&pageNum=0&refId=a5rwPua%2FMvx%2F2M%2FPSF0oPA%3D%3D&trackingId=5T%2Ftx9Gs0LAlbOyht9BGDw%3D%3D&trk=public_jobs_jserp-result_search-card",
        "description": "Dans le cadre de notre développement, nous recrutons pour intégrer notre équipe sur Lyon (69) :\nData Architect (H/F)\nVos missions, si vous les acceptez :\nVous assurez le leadership technique, participez au développement, et représentez les ressources internes et externes de la plateforme\nVous serez un membre actif de l’équipe des architectes, afin de superviser le processus de gestion des données et fournir des conseils et orientations aux équipes de développement\nVous serez responsable de la conception, et de la documentation de la solution dans votre domaine\nVous aurez la responsabilité complète de l’architecture\nVous serez support aux équipes techniques dans l’intégralité du cycle de vie de la gestion des données.\nEnvironnement Technique :\nExpérience dans le développement, la documentation et la maintenance de modèles de données logiques et physiques\nExpérience sur Databricks, ADLS storage, SQL DB, ADF et Power BI\nExpérience dans la définition et la maîtrise d'une architecture de données évolutive de bout en bout, en tenant compte de l'architecture de l'entreprise et des normes industrielles.\nParticipation à l'élaboration d'architectures, stratégies et politiques en matière de données, y compris la sécurité des données\nLangage SQL Writing et modélisation de données\nData Architecture\nPower BI\nAzure ADFv2, Databricks, Synapse, Delta Lake\nEnvironnement et technologie Azure Advanced Analytics\nPython, Pyspark\nMicrosoft cloud basé sur modèle Delivery\nData Management, Data Governance et Data Quality\nDéploiement d’APIs et micro-services\nDevSecOps\nAgile\nExpérience professionnelle dans un environnement international\nLe profil que nous recherchons :\nDe formation informatique, vous possédez une expérience significative d’au moins 4 ans minimum en tant que Data Architect.\nVous avez le sens de l’écoute, une bonne gestion des priorités, vous avez un bon relationnel et de la rigueur.\nVous disposez d’une excellente communication.\nVous vous reconnaissez dans cette description ? Echangeons !\nPourquoi nous rejoindre ?\nL’innovation, la qualité et l’agilité sont au cœur du développement de nos activités IT, encadrées et assurées par nos 850 collaborateurs et collaboratrices français(es) et bulgares !\nNotre savoir-faire ?\nConseil, Développement, Analyse et Expertise Informatique pour accompagner nos clients dans l'évolution et la transformation de leur SI.\nEn plus de notre maîtrise des technologies PHP, JavaEE et .Net qui sont des composantes fortes de notre savoir-faire, nous mettons en avant une expertise dédiée aux applications mobiles et XNet (Inter, Intra et Extranet) et au développement de notre offre infrastructure (systèmes, réseaux, cybersécurité…).\nNos valeurs ?\nL’engagement, le pragmatisme, la proximité, l’évolution et le partage. Aussi bien avec nos clients qu’avec nos collaborateurs (F/H).\nRésultats ?\nUne entreprise en pleine croissance avec des collaborateurs (F/H) épanouis et reconnus au quotidien ! Des clients fidèles et reconnaissants de la qualité des prestations fournies !\nNos collaborateurs œuvrent chaque jour à satisfaire et concrétiser les idées les plus folles et innovantes de nos clients !... N’attendez plus et tentez l’expérience PROXIAD !\nToutes les demandes seront traitées avec la plus stricte confidentialité. Seuls les candidats retenus seront contactés.\nShow more\nShow less",
        "details": {
            "JobDetail": [],
            "TypeContract": "",
            "Salary": "",
            "Level": "",
            "Experience": "4 an(s)"
        },
        "title": "data architect",
        "skills": {
            "ProgLanguage": [
                "Python"
            ],
            "DataBase": [
                "SQL"
            ],
            "BigData": [
                "Databricks"
            ],
            "DataVisualisation": [
                "Power BI"
            ],
            "CloudComputing": [
                "Azure"
            ],
            "Other": [
                "Cloud"
            ],
            "EnSoftSkils": [
                "Leadership",
                "Communication"
            ]
        }
    },
    {
        "source": "LinkedIn",
        "company": "Coders Connect",
        "location": "Paris, Île-de-France, France",
        "link": "https://fr.linkedin.com/jobs/view/solutions-architect-digital-data-at-coders-connect-3889484245?position=11&pageNum=0&refId=a5rwPua%2FMvx%2F2M%2FPSF0oPA%3D%3D&trackingId=wYBT2jbq5kAyS9RkDIEUCw%3D%3D&trk=public_jobs_jserp-result_search-card",
        "description": "Coders Connect\nand\nSanofi\nare joining forces to bring an electrifying twist to the biopharmaceutical world!\nWork with a rhythm that suits your style (2 days remote and 3 days onsite magic).\nLanguage:\nProficiency in English is required for this role to ensure effective communication within our diverse, global team.\nAbout Sanofi:\nWe're not just a company; we're a global movement, focused on human health and making a real difference. Our mission? To battle pain, ease suffering, and sprinkle a little bit of magic in the process by developing life-changing medicines and vaccines through breakthrough science and wizard-level technology.\nDigital & Data: The Pulse of Our Mission\nAt the heart of our quest lies our digital and data powerhouse. Think of us as the digital healthcare platform of your dreams, where innovation meets speed, and technology shakes hands with medicine. With our scale, deep-rooted connections in health ecosystems worldwide, and a knack for pushing boundaries, we're here to revolutionize medicine, one digital solution at a time.\nYour Mission as a Solution Architect:\n​\nAs our Solution Architect, you're the master planner of our digital architecture, crafting scalable and sustainable solutions that power advanced analytics, AI, and ML initiatives. You'll design the blueprint for our data platforms and technology stacks, ensuring they align with our strategic goals and adhere to the highest standards of quality and innovation.\nRequirements\nCloud Mastery:\nDeep expertise in cloud-based services, particularly AWS managed services, to architect scalable and resilient solutions.\nAgile and DevOps:\nA solid foundation in Agile development processes and DevOps principles, including proficiency with GIT (GitHub), CI/CD practices (GitHub Actions), and Infrastructure as Code (Terraform).\nTech Stack Expertise\n: Hands-on experience with Linux, containers (Kubernetes), serverless architectures, and programming skills in JavaScript, Node.js, React, and Flutter.\nData Engineering:\nKnowledge of SQL, relational databases (AWS RDS), and familiarity with data warehousing solutions like Snowflake and AWS Redshift. Integration Services experience (Informatica Cloud, Airflow) is a significant plus.\nMessaging and Integration:\nCompetency in messaging solutions (EventBridge, SNS, SQS, Rabbit MQ, Kafka) to ensure seamless data flow and integration across systems.\nCompliance and Security:\nAwareness of compliance and cybersecurity requirements in the healthcare industry, with experience in navigating quality, regulatory data privacy (GxP, SOX) standards.\nCertifications:\nRelevant cloud certifications (AWS, Azure, Snowflake) are highly regarded, reflecting a commitment to staying at the forefront of technology.\nThe Reward:\nA chance to play a crucial role in a collaboration that's redefining healthcare through digital transformation.\nA seat at the round table of diversity and inclusion, where different backgrounds and experiences conjure the richness of our culture.\nAn endless horizon of professional growth, learning opportunities, and the chance to contribute to a future where better health is a global reality.\nThe Call to Adventure:\nIf you're ready to join a quest for better – better treatments, better outcomes, and better science – and believe in the magic of bringing diverse talents together to make miracles happen, we want you. Let's embark on this journey together and transform the future of healthcare.\nBetter is out there. Are you ready to find it with us?\nShow more\nShow less",
        "details": {
            "JobDetail": [
                "Remote"
            ],
            "TypeContract": "",
            "Salary": "",
            "Level": "",
            "Experience": null
        },
        "title": "data architect",
        "skills": {
            "DataBase": [
                "SQL"
            ],
            "CloudComputing": [
                "AWS",
                "Azure"
            ],
            "DevTools": [
                "Git"
            ],
            "OS": [
                "Linux"
            ],
            "DBMS": [
                "Snowflake"
            ],
            "Automation": [
                "Airflow",
                "Kubernetes"
            ],
            "InfrastructureAsCode": [
                "Terraform"
            ],
            "Containers": [
                "Kubernetes"
            ],
            "Other": [
                "ML",
                "Cloud",
                "DevOps",
                "CI/CD"
            ],
            "EnSoftSkils": [
                "Communication",
                "Collaboration"
            ]
        }
    },
    {
        "source": "LinkedIn",
        "company": "Capgemini",
        "location": "Lyon",
        "link": "https://fr.linkedin.com/jobs/view/architecte-big-data-cloud-lyon-at-capgemini-3907764355?position=12&pageNum=0&refId=a5rwPua%2FMvx%2F2M%2FPSF0oPA%3D%3D&trackingId=7dtgcERGKyLxdC5FPR81ng%3D%3D&trk=public_jobs_jserp-result_search-card",
        "description": "À propos de l’offre d’emploi\nCapgemini en quelques mots\nChoisir Capgemini, c'est choisir une entreprise où vous serez en mesure de façonner votre carrière selon vos aspirations, où vous serez soutenu et inspiré par une communauté d’experts dans le monde entier, où vous pourrez réécrire votre futur. Rejoignez-nous pour redéfinir les limites de ce qui est possible, contribuer à libérer la valeur de la technologie pour les plus grandes organisations et participez à la construction d’un monde plus durable et inclusif.\nVos missions :\nVous répondez aux problématiques de nos clients en proposant des\nsolutions big data « on premise » et/ou dans le cloud (MS Azure, AWS et GCP).\nVous adaptez chaque architecture en fonction du contexte grâce à votre maitrise des caractéristiques fondamentales de chaque solution (catalogue des offres de services managés, performance, sécurité, déploiement des data centers …).\nVous utilisez les solutions d’intégration associées et les solutions décisionnelles ainsi qu’analytiques qui viennent consommer les données manipulées.\nVous êtes en mesure d’encadrer les équipes de data engineers dans la mise en place des architectures préconisées et/ ou des plateformes Big Data.\nVous êtes en mesure d’appuyer les équipes commerciales dans les réponses aux appels d’offres Big Data.\nVotre profil :\nFormation Bac + 5 en école d’ingénieur ou équivalent universitaire avec une spécialisation Big Data,\nA partir de 7 ans d’expérience,\nVous êtes un(e) passionné(e) de la Data et maitrisez aussi bien Linux et Spark que Script shell\nHadoop (cloudera/Hortonworks/MapR) n'a pas de secret pour vous mais vous avez pris le virage du cloud (AWS, GCP, MS Azure ),\nEnglish speaker, because we are French but also international.\n3 raisons de nous rejoindre :\nQualité de vie au travail :\naccord de télétravail en France et à l’international, accord sur l’égalité professionnelle, la parentalité, l’équilibre des temps et la mobilité durable.\nApprentissage en continu :\ncertifications et formations en libre accès, accompagnement sur mesure avec votre carreer manager, parcours d’intégration sur 9 mois.\nAvantages groupe & CSE :\nplan actionnariat, activités à tarifs préférentiels, remboursement partiel vacances, remboursement de votre abonnement sportif ou culturel.\nNos engagements et priorités :\nLe groupe Capgemini encourage une\nculture inclusive dans un cadre multiculturel et handi-accueillant.\nEn nous rejoignant, vous intégrez un collectif qui valorise la diversité, développe le potentiel de ses talents, s’engage dans des\ninitiatives solidaires avec ses partenaires, et se mobilise pour réduire son impact environnemental sur tous ses sites et auprès de ses clients.\nCapgemini\nest un\nleader mondial,\nresponsable et multiculturel, regroupant près de 350 000 personnes dans plus de 50 pays. Fort de\n55 ans d’expérience\n, nous sommes un partenaire stratégique des entreprises pour la transformation de leurs activités en tirant profit de toute la puissance de la technologie et des innovations dans les domaines en perpétuelle évolution tels que\nle cloud, la data, l’Intelligence Artificielle, la connectivité, les logiciels, l’ingénierie digitale ou les plateformes.\nGet The Future You Want* | www.capgemini.com/fr-fr\n*Capgemini, le futur que vous voulez\nShow more\nShow less",
        "details": {
            "JobDetail": [],
            "TypeContract": "",
            "Salary": "",
            "Level": "",
            "Experience": "7 an(s)"
        },
        "title": "data architect",
        "skills": {
            "BigData": [
                "Hadoop",
                "Spark"
            ],
            "CloudComputing": [
                "GCP",
                "AWS",
                "Azure"
            ],
            "OS": [
                "Linux"
            ],
            "Other": [
                "Cloud",
                "Big Data"
            ]
        }
    },
    {
        "source": "LinkedIn",
        "company": "ANFSI - Agence du numérique des forces de sécurité intérieure",
        "location": "Issy-les-Moulineaux, Île-de-France, France",
        "link": "https://fr.linkedin.com/jobs/view/architecte-data-at-anfsi-agence-du-num%C3%A9rique-des-forces-de-s%C3%A9curit%C3%A9-int%C3%A9rieure-3907477086?position=13&pageNum=0&refId=a5rwPua%2FMvx%2F2M%2FPSF0oPA%3D%3D&trackingId=Y3Rnq%2BGRbOfIeubfaQbhvg%3D%3D&trk=public_jobs_jserp-result_search-card",
        "description": "Vos activités principales\nConception et Stratégie\n• Analyse des besoins métiers pour les systèmes de collecte et de stockage de données à un niveau stratégique.\n• Conception des architectures globales de données pour la collecte et le stockage de données, y compris l'intégration via des API au travers de solutions on-premise et cloud.\n• Supervision des tests et de l'intégration pour garantir l'efficacité et la fiabilité des systèmes.\n• Stratégie globales d'automatisation pour l'automatisation des traitements.\nGouvernance\n• Politiques de nettoyage de données en s'alignant sur les objectifs de l'administration.\n• Gestion stratégique des bases de données incluant des stratégies pour l'intégration de données diverses.\n• Conformité et sécurité des données dans le respect de normes comme le RGPD.\n• Planification de la maintenance et du suivi des systèmes de données.\nDirection des Projets\n• Définition des standards techniques et des meilleures pratiques pour les projets de développement de données.\n• Coordination et reporting : se coordonner avec les chefs de projet et les équipes techniques en vue de l'alignement architectural des projets.\n•Accompagner et coacher les autres experts et développeurs, afin qu'ils\nmontent en compétences sur les sujets liés à l'intégration et à la\ngouvernance des données.\nLeadership et Innovation\n• Veille stratégique.\n• Leadership en documentation : Définir les standards pour la documentation technique, incluant la gestion des connaissances et le partage des meilleures pratiques.\nVotre environnement professionnel\nActivités du service\nL’Agence du Numérique des Forces de Sécurité Intérieure (ANFSI) est chargée de piloter et de conduire les projets de systèmes d’information, de communication, de commandement et des moyens technologiques connexes dédiés aux utilisateurs de la sécurité intérieure.\nComposition et effectifs du service\nL’ANFSI est composée de six directions : la Direction des Supports Opérationnels (DSO), la Direction de la sécurité et de l’architecture (DSA), la Direction de l’appui à l’investigation (DAI), la Direction des applications d’appui au commandement (DAAC), la Direction des communications tactiques (DCT), et la Direction de la proximité et de l’appui à l’innovation (DPAI). Son effectif est composéde personnels de la police et de la gendarmerie nationales ainsi que de contractuels.\nLa Section de mise à disposition des données, où le poste est ouvert, est composée de 9 personnes. Vous serez l’adjoint du chef de section qui est un ingénieur officier de gendarmerie. L’activité principale de la section consiste à récupérer les données métier des logiciels de rédaction de procédures des FSI et à les mettre à disposition d’applications tierces, comme le fichier des personnes recherchées, le fichier des objets et véhicules volés, ou le traitement des antécédents judiciaires. L’architecte apporte son expérience dans la mise en œuvre d’ETL et/ou d’ESB, et API manager.\nVos compétences principales mises en œuvre :\nConnaissances techniques\nAvoir des compétences en informatique - bureautique niveau maîtrise requis\nConnaître l'environnement professionnel niveau maîtrise à acquérir\nSavoir-faire\nSavoir analyser niveau expert requis\nSavoir manager niveau maîtrise requis\nSavoir rédiger niveau pratique requis\nAvoir l'esprit de synthèse niveau maîtrise requis\nSavoir s'organiser niveau maîtrise requis\nSavoir travailler en équipe niveau maîtrise requis\nSavoir-être\navoir le sens des relations humaines niveau maîtrise requis\nsavoir s'adapter niveau expert requis\nsavoir communiquer niveau maîtrise à acquérir\nsavoir s'exprimer oralement niveau maîtrise à acquérir\nProfil recherché :\nTitulaire d'un diplôme d'ingénieur (Bac +5) ou équivalent, votre passion pour la technologie vous rend apte à résoudre des défis complexes liés à la Data. Avec au moins cinq ans d'expérience en technologies ETL/ESB, message broker et API management, vous maîtrisez ces domaines. Une expérience approfondie dans la conception d'architectures de plateformes d'échanges est essentielle. Une connaissance de la plateforme Mulesoft est un plus.\nVos perspectives\n:\nDans un contexte d’accélération de l'évolution du numérique et des besoins de réactivité associés : enrichissement du réseau professionnel, approfondissement des connaissances et expérience professionnelles, maîtrise des procédures et compétences « métier » de la GN/PN. Implication dans la mise en place de projets innovants (PN/GN) et transverses. S’ouvrir aux nouvelles méthodologies de conduite de projet.\nDurée attendue sur le poste\n:\n3 ans\nSpécificités du poste / Contraintes / Sujétions :\n39 heures hebdomadaires - 25 jours CA -22 jours de RTT\nLes candidat.e.s pourront être soumis à une enquête administrative de sécurité sur le fondement de l'article L.114-1 du code de la sécurité intérieure.\nLocalisation géographique :\n4, rue Claude Bernard – 92130 Issy-les-Moulineaux\nShow more\nShow less",
        "details": {
            "JobDetail": [],
            "TypeContract": "",
            "Salary": "",
            "Level": "",
            "Experience": "3 an(s)"
        },
        "title": "data architect",
        "skills": {
            "Automation": [
                "Chef"
            ],
            "Other": [
                "Cloud"
            ],
            "EnSoftSkils": [
                "Leadership",
                "Communication"
            ]
        }
    },
    {
        "source": "LinkedIn",
        "company": "Capgemini",
        "location": "Issy-les-Moulineaux, Île-de-France, France",
        "link": "https://fr.linkedin.com/jobs/view/architecte-big-data-cloud-at-capgemini-3902965293?position=14&pageNum=0&refId=a5rwPua%2FMvx%2F2M%2FPSF0oPA%3D%3D&trackingId=AwEXZKzHyJPYvt0z8HzQVw%3D%3D&trk=public_jobs_jserp-result_search-card",
        "description": "Capgemini en quelques mots\nChoisir Capgemini, c'est choisir une entreprise où vous serez en mesure de façonner votre carrière selon vos aspirations, où vous serez soutenu et inspiré par une communauté d’experts dans le monde entier, où vous pourrez réécrire votre futur. Rejoignez-nous pour redéfinir les limites de ce qui est possible, contribuer à libérer la valeur de la technologie pour les plus grandes organisations et participez à la construction d’un monde plus durable et inclusif.\nVos missions :\nVous répondez aux problématiques de nos clients en proposant des\nsolutions big data « on premise » et/ou dans le cloud (MS Azure, AWS et GCP).\nVous adaptez chaque architecture en fonction du contexte grâce à votre maitrise des caractéristiques fondamentales de chaque solution (catalogue des offres de services managés, performance, sécurité, déploiement des data centers …).\nVous utilisez les solutions d’intégration associées et les solutions décisionnelles ainsi qu’analytiques qui viennent consommer les données manipulées.\nVous êtes en mesure d’encadrer les équipes de data engineers dans la mise en place des architectures préconisées et/ ou des plateformes Big Data.\nVous êtes en mesure d’appuyer les équipes commerciales dans les réponses aux appels d’offres Big Data.\nVotre profil :\nFormation Bac + 5 en école d’ingénieur ou équivalent universitaire avec une spécialisation Big Data,\nA partir de 7 ans d’expérience,\nVous êtes un(e) passionné(e) de la Data et maitrisez aussi bien Linux et Spark que Script shell\nHadoop (cloudera/Hortonworks/MapR) n'a pas de secret pour vous mais vous avez pris le virage du cloud (AWS, GCP, MS Azure ),\nEnglish speaker, because we are French but also international.\n3 raisons de nous rejoindre :\nQualité de vie au travail :\naccord de télétravail en France et à l’international, accord sur l’égalité professionnelle, la parentalité, l’équilibre des temps et la mobilité durable.\nApprentissage en continu :\ncertifications et formations en libre accès, accompagnement sur mesure avec votre carreer manager, parcours d’intégration sur 9 mois.\nAvantages groupe & CSE :\nplan actionnariat, activités à tarifs préférentiels, remboursement partiel vacances, remboursement de votre abonnement sportif ou culturel.\nNos engagements et priorités :\nLe groupe Capgemini encourage une\nculture inclusive dans un cadre multiculturel et handi-accueillant.\nEn nous rejoignant, vous intégrez un collectif qui valorise la diversité, développe le potentiel de ses talents, s’engage dans des\ninitiatives solidaires avec ses partenaires, et se mobilise pour réduire son impact environnemental sur tous ses sites et auprès de ses clients.\nCapgemini\nest un\nleader mondial,\nresponsable et multiculturel, regroupant près de 350 000 personnes dans plus de 50 pays. Fort de\n55 ans d’expérience\n, nous sommes un partenaire stratégique des entreprises pour la transformation de leurs activités en tirant profit de toute la puissance de la technologie et des innovations dans les domaines en perpétuelle évolution tels que\nle cloud, la data, l’Intelligence Artificielle, la connectivité, les logiciels, l’ingénierie digitale ou les plateformes.\nGet The Future You Want* | www.capgemini.com/fr-fr\n*Capgemini, le futur que vous voulez\nShow more\nShow less",
        "details": {
            "JobDetail": [],
            "TypeContract": "",
            "Salary": "",
            "Level": "",
            "Experience": "7 an(s)"
        },
        "title": "data architect",
        "skills": {
            "BigData": [
                "Hadoop",
                "Spark"
            ],
            "CloudComputing": [
                "GCP",
                "AWS",
                "Azure"
            ],
            "OS": [
                "Linux"
            ],
            "Other": [
                "Cloud",
                "Big Data"
            ]
        }
    },
    {
        "source": "LinkedIn",
        "company": "Harnham",
        "location": "Paris, Île-de-France, France",
        "link": "https://fr.linkedin.com/jobs/view/data-architect-at-harnham-3907820245?position=15&pageNum=0&refId=a5rwPua%2FMvx%2F2M%2FPSF0oPA%3D%3D&trackingId=safltM8yfEOH1tQrs0R5zw%3D%3D&trk=public_jobs_jserp-result_search-card",
        "description": "DATA ARCHITECT\nPARIS (75) / LILLE (59)\n50-55K EUR\nUne nouvelle opportunité s’ouvre pour un Data Architecte dans le domaine de l’assurance. Une entreprise qui combine l’expertise des grands groupes et l’agilité d’une start-up, qui vous permettra d’innover ! Si vous recherchez un défi stimulant dans un environnement qui encourage les nouvelles idées, cette opportunité est faite pour vous.\nVOTRE MISSION :\nElaborer et Concevoir l’architecture des données en réponse aux besoins métiers\nCollaboration pour comprendre les exigences des parties prenantes et les traduire en solutions architecturales\nConcevoir et implémenter des modèles de données efficaces et évolutifs\nAssurer la cohérence et l’intégrité des données à travers tout le système.\nFournir des recommandations pour assurer une gestion efficace des données\nVOTRE PROFIL :\n4 ans d’expérience dans un rôle similaire\nCompétences solides en Python, Cloud AWS, Tableau\nCompétencesavec le Machine Learning\nAnglais: Fluent obligatoire\nN’hésitez plus pour postuler !\nShow more\nShow less",
        "details": {
            "JobDetail": [],
            "TypeContract": "",
            "Salary": "",
            "Level": "",
            "Experience": "4 an(s)"
        },
        "title": "data architect",
        "skills": {
            "ProgLanguage": [
                "Python"
            ],
            "DataVisualisation": [
                "Tableau"
            ],
            "CloudComputing": [
                "AWS"
            ],
            "Other": [
                "Machine Learning",
                "Cloud"
            ],
            "EnSoftSkils": [
                "Collaboration"
            ]
        }
    },
    {
        "source": "LinkedIn",
        "company": "Vallum Associates",
        "location": "Paris, Île-de-France, France",
        "link": "https://fr.linkedin.com/jobs/view/data-cloud-solution-architect-at-vallum-associates-3916589273?position=16&pageNum=0&refId=a5rwPua%2FMvx%2F2M%2FPSF0oPA%3D%3D&trackingId=4Zq3y89MIEfOPdGqnw0nGg%3D%3D&trk=public_jobs_jserp-result_search-card",
        "description": "Skills:\nFluent in French & English\n(must)\nDeep Snowflake expertise\nPlatform architecture\nDBA experience\nCloud database admin\nAWS Architecture\nCloud networking specialist\nExcellence in communication, coordination & collaboration, stakeholder & risk management and especially with drive & leadership\nOpen minded and accepting challenges\nHighly motivated, adaptable and flexible. Willing to integrate an existing environment and an existing project team\nShow more\nShow less",
        "details": {
            "JobDetail": [],
            "TypeContract": "",
            "Salary": "",
            "Level": "",
            "Experience": null
        },
        "title": "data architect",
        "skills": {
            "CloudComputing": [
                "AWS"
            ],
            "DBMS": [
                "Snowflake"
            ],
            "Other": [
                "Cloud"
            ],
            "EnSoftSkils": [
                "Leadership",
                "Communication",
                "Collaboration"
            ]
        }
    },
    {
        "source": "LinkedIn",
        "company": "Agyla.Cloud",
        "location": "France",
        "link": "https://fr.linkedin.com/jobs/view/data-architect-h-f-at-agyla-cloud-3885512739?position=17&pageNum=0&refId=a5rwPua%2FMvx%2F2M%2FPSF0oPA%3D%3D&trackingId=iq1NzP0cg3me9Ol5f2LP2A%3D%3D&trk=public_jobs_jserp-result_search-card",
        "description": "Agyla est depuis le 1er Juillet, LA référence en cloud public du groupe IBM Consulting.\nNous sommes un cabinet de conseil informatique spécialisé en Cloud & DevOps. Ce sont 90 experts qui interviennent au cœur de la transformation technologique de nos clients, de la conception à la sécurisation en production.\nNos technologies clés: AWS, Azure, GCP/Kubernetes, HashiCorp, tout sur la CICD, Cloud Security, cloud native developpement.\nFaire partie d’Agyla c’est booster sa carrière et rejoindre notre communauté d’experts, recrutés pour leurs talents.\nNos experts sont accompagnés dans leur carrière et renforcent leurs expertises à travers des certifications techniques pour une montée en compétence constante. Ils participent au collectif en partageant leur savoir et en faisant grandir l’entreprise auprès de ses clients.\nNous recrutons notre futur(e) Data Architect ! Vous souhaitez rejoindre une mission passionnante dans le secteur du retail ? Alors c'est par ici que ça se passe :\nVos tâches :\nAccompagner et conseiller l'équipe notamment dans le cadre de modélisation de données\nÉtablir et faciliter un forum d'architecture des données, où les options d'architecture des données sont examinées et discutées avec l'équipe.\nVeiller à ce que la documentation appropriée soit créée au fil du temps (suivi des décisions du forum d'architecture des données, vérification que l'architecture des données pour chaque livraison réalisée par les équipes soit correctement documentée).\nReprésenter les intérêts de l'équipe dans certains projets menés par d'autres équipes\nVos qualifications :\nExpérience en modélisation de données.\nCapacité à influencer les autres (pour soutenir mais aussi remettre en question les conceptions des produits de données réalisées).\nAppétence pour les processus/documentation, car l'idée est de renforcer la manière de documenter et de gouverner l'architecture des données.\nMaîtrise d'un cloud public (Azure ou GCP)\nNB : La mission se déroule en full remote.\nAgyla.cloud a bâti sa croissance sur la puissance de son équipe. Vous deviendrez un membre actif du succès collectif.\nVous avez l’attitude d’un consultant : à l’écoute, bienveillant, vous partagez votre expérience et faites grandir le client. Vous savez prendre des initiatives et avec une excellente communication orale et écrite.\nAgyla-Déclaration spécifique de confidentialité\nAgyla est une filiale IBM qui a été acquise par IBM et qui sera intégrée à l'organisation IBM. Agyla sera l'entité d'embauche. En procédant à cette candidature, vous comprenez qu'Agyla partagera vos informations personnelles avec IBM et d'autres filiales IBM impliquées dans votre processus de recrutement, où qu'elles se trouvent. Plus d'informations sur la façon dont IBM protège vos informations personnelles, y compris les garanties en cas de transfert de données transfrontière, sont disponibles ici:\nhttps://www.ibm.com/fr-fr/privacy\nShow more\nShow less",
        "details": {
            "JobDetail": [
                "Remote",
                "Full"
            ],
            "TypeContract": "",
            "Salary": "",
            "Level": "",
            "Experience": null
        },
        "title": "data architect",
        "skills": {
            "CloudComputing": [
                "GCP",
                "AWS",
                "Azure"
            ],
            "Automation": [
                "Kubernetes"
            ],
            "Containers": [
                "Kubernetes"
            ],
            "Other": [
                "Cloud",
                "DevOps"
            ],
            "EnSoftSkils": [
                "Communication"
            ]
        }
    },
    {
        "source": "LinkedIn",
        "company": "INSEAD",
        "location": "Fontainebleau, Île-de-France, France",
        "link": "https://fr.linkedin.com/jobs/view/solution-architect-at-insead-3868439514?position=18&pageNum=0&refId=a5rwPua%2FMvx%2F2M%2FPSF0oPA%3D%3D&trackingId=Y%2F3BfUWMhpQ%2Bmh97Cx%2FrVA%3D%3D&trk=public_jobs_jserp-result_search-card",
        "description": "INSEAD brings together people, cultures and ideas from around the world to educate leaders who transform business and society. As a mission-driven school, INSEAD focuses on three values: open, rigorous, and entrepreneurial. As one of the world’s leading and largest graduate business schools, With campuses in Europe (France), Asia (Singapore), Middle East (Abu Dhabi) and an American Hub (San Francisco), INSEAD’s business and research spans four continents.\nWe are currently looking for a\nSolution Architect\nto join our Data & Enterprise Architecture team in the IT department. This is a permanent and full-time position, based either on our\nAsia Campus in Singapore\nor on our\nEurope Campus in Fontainebleau, France\n. A hybrid working model is in place – 3 days on campus, 2 days from home.\nThe Solution Architect will analyse the current state of the enterprise environment from a technical and functional point of view. He/she will develop and design the future state architecture and the roadmap to reach it, balancing risks in terms of timeline and costs while meeting business requirements and enabling capability. The Solution Architect will devise technical or functional solutions to achieve enterprise and business objectives, this effort will consistently align with the IT strategy.\nKey Responsibilities include:\n• Support large project implementation: (1) Formulate the solutions in which business and IT viewpoints are synthesised into a solution. (2) Develop the digital interoperability for new platforms to embed the INSEAD eco-system (3) Setup the plan for state-of-the-art operationalisation and maintenance of the new platform.\n• Develop continuous integration & delivery practices in IT. Work out the best possible optimisation and automation of tasks and process(es), costing time and energy to the organisation.\n• Formulate the architecture strategy and govern it: (1) Develop and communicate architectural standards (2) Add architecture consideration into business discussions to develop roadmaps and implementation plans considering a sustainable IT portfolio. (T.I.M.E from Gartner)\n• Understand the enterprise needs and anticipate a major technology shift from the industry. This encompasses the need to educate/ inform the IT and school senior leadership about it so they can better prepare for the near future. It means driving the cost versus benefits, risks, impact, and technology priorities.\nWe are looking for a hands-on candidate who meets the following profile:\n• A minimum of 5 years of professional experience with application development.\n• Expert with DevSecOps practices. Hand’s on with suite of CI/CD platforms and utilities.\n• Track record of enterprise architecture application (certify TOGAF is a plus).\n• Expertise in process design as well as Data modelling (certify ArchiMate is a plus).\n• Knowledge of Salesforce, Oracle Cloud and ServiceNow is a plus.\n• Demonstrated polished consulting skills with a keen awareness of sensitive client topics, and the ability to navigate client messaging and recommendations tactfully.\n• Proven ability to establish credibility with Senior Executives, team members and external partners, with excellent analytical and problem-solving skills for managing large and small projects.\n• Strong prioritization skills with attention to detail, and the capability to quickly define dependencies, issues, and mitigation plans against risks.\n• Effective communication skills bridging technology and business communities, with a consistent track record of business-building successes.\n• Fluency in English, with proficiency in French is advantageous.\n• Enthusiasm for exploring unknown technological territories and a strong technical curiosity to understand how things work.\nWe are happy to receive your resume and cover letter for this exciting opportunity. Please send your application to Talent Acquisition Europe talent.acquisition@insead.edu\nDiversity is one of INSEAD’s founding values and as such we commit to cultivating a community that pursues equity, exemplifies inclusion and cherishes diversity in all its dimensions. Our jobs are open to all talents, so apply and join us!\nWe regret that only shortlisted candidates will be contacted.\nShow more\nShow less",
        "details": {
            "JobDetail": [
                "Full",
                "Senior"
            ],
            "TypeContract": "",
            "Salary": "",
            "Level": "",
            "Experience": null
        },
        "title": "data architect",
        "skills": {
            "Other": [
                "Cloud",
                "CI/CD"
            ],
            "EnSoftSkils": [
                "Leadership",
                "Communication"
            ]
        }
    },
    {
        "source": "LinkedIn",
        "company": "Capgemini",
        "location": "Lille, Hauts-de-France, France",
        "link": "https://fr.linkedin.com/jobs/view/architecte-big-data-cloud-lille-at-capgemini-3861939159?position=19&pageNum=0&refId=a5rwPua%2FMvx%2F2M%2FPSF0oPA%3D%3D&trackingId=Rii39Sm%2BCo0XrM2FDDa1DA%3D%3D&trk=public_jobs_jserp-result_search-card",
        "description": "Capgemini en quelques mots\nChoisir Capgemini, c'est choisir une entreprise où vous serez en mesure de façonner votre carrière selon vos aspirations, où vous serez soutenu et inspiré par une communauté d’experts dans le monde entier, où vous pourrez réécrire votre futur. Rejoignez-nous pour redéfinir les limites de ce qui est possible, contribuer à libérer la valeur de la technologie pour les plus grandes organisations et participez à la construction d’un monde plus durable et inclusif.\nVos missions\nInteragir au plus proche de nos clients, des partenaires pour concevoir et mettre en œuvre des solutions/projets innovants et compétitifs\nRépondre aux problématiques de nos clients en proposant la meilleure plateforme data dans un environnement Agile\nAdapter chaque architecture en fonction du contexte grâce à votre maitrise des caractéristiques fondamentales de chaque solution (catalogue des offres de services managés, performance, sécurité, déploiement des data centers …)\nUtiliser les solutions d’intégration associées et les solutions décisionnelles ainsi qu’analytiques qui viennent consommer les données manipulées\nEncadrer les équipes dans la mise en place des architectures préconisées et/ ou des plateformes Data.\nVotre profil\nAu moins 6 ans d’expérience (au sein d’une ESN ou chez un intégrateur) en conseil clientèle\nUne solide culture technologique\nUn bon niveau d’anglais\nDes qualités de pédagogue et un intérêt pour la phase d’avant-vente.\n3 raisons de nous rejoindre\nQualité de vie au travail :\naccord de télétravail en France et à l’international, accord sur l’égalité\nprofessionnelle, la parentalité, l’équilibre des temps et la mobilité durable.\nApprentissage en continu :\ncertifications et formations en libre accès, accompagnement sur mesure avec\nvotre carreer manager, parcours d’intégration sur 9 mois.\nAvantages groupe & CSE :\nplan actionnariat, activités à tarifs préférentiels, remboursement partiel\nvacances, remboursement de votre abonnement sportif ou culturel\nNos engagements et priorités\nLe groupe Capgemini encourage une\nculture inclusive dans un cadre multiculturel et handi-accueillant.\nEn nous rejoignant, vous intégrez un collectif qui valorise la diversité, développe le potentiel de ses talents, s’engage dans des\ninitiatives solidaires avec ses partenaires, et se mobilise pour réduire son impact environnemental sur tous ses sites et auprès de ses clients.\nCapgemini\nest un\nleader mondial\n, responsable et multiculturel, regroupant près de 350 000 personnes dans plus de 50 pays. Fort de\n55 ans d’expérience,\nnous sommes un partenaire stratégique des entreprises pour la transformation de leurs activités en tirant profit de toute la puissance de la technologie et des innovations dans les domaines en perpétuelle évolution tels que le\ncloud, la data, l’Intelligence Artificielle, la connectivité, les logiciels, l’ingénierie digitale ou les plateformes.\nGet The Future You Want* | www.capgemini.com/fr-fr\n*Capgemini, le futur que vous voulez\nShow more\nShow less",
        "details": {
            "JobDetail": [],
            "TypeContract": "",
            "Salary": "",
            "Level": "",
            "Experience": "6 an(s)"
        },
        "title": "data architect",
        "skills": {
            "Other": [
                "Cloud"
            ]
        }
    },
    {
        "source": "LinkedIn",
        "company": "LEM",
        "location": "Lyon, Auvergne-Rhône-Alpes, France",
        "link": "https://fr.linkedin.com/jobs/view/it-data-architect-at-lem-3916801738?position=20&pageNum=0&refId=a5rwPua%2FMvx%2F2M%2FPSF0oPA%3D%3D&trackingId=KptAY1vG1vOswIxM2PaP3Q%3D%3D&trk=public_jobs_jserp-result_search-card",
        "description": "LEM – Life Energy Motion\nAt LEM, we help our customers and society accelerate the transition to a sustainable future.\nOur global team of 1,700 professionals which spans over 15 countries is dedicated to converting technology potential into powerful solutions, which enable the decarbonization of the world.\nA leading company in electrical measurement, LEM engineers the best solutions for energy efficiency and electrical mobility, ensuring our customers, systems are optimized, reliable and safe.\nLEM is listed on the SIX Swiss Exchange since 1986, with the ticker symbol LEHN.\nThe future needs our ingenuity, we need your Spark.\n#BringYourSpar\nIn order to build the analytic team, we are looking for an IT DATA architect.\nThis is an exciting new opportunity working as part of the Corporate IT team to develop new capabilities and establish a supportable model of platform and applications, growing the companies use of modern technologies.\nThe IT Data architect is responsible for defining policies, procedures, models, and technologies that will be used to collect, organize, store, and retrieve information for the organization.\nHe / she understands how data drives the development of applications and business requirements through appropriate design principles, methodologies, and tools.\nHe / she sets the rules and structure for the data strategy, choosing the ETL approach and setting additional requirements.\nThe main tasks will be related to:\nApplication Design\nData model definition: Define the data architecture, data contract interfaces, data quality into the systems, best practices,\nData flow overview: Take the ownership of the current and future data flows. Take responsibilities for data quality and timeliness,\n& ensure the evolution of data flows, using the global data standards and business rules to input data into the systems,\nQuality assurance: Perform data quality checks for correctness and completeness according to defined business rules,\nMaster Data System: maintain accurate & up to date data for assigned business processes,\nto continuous improvements of systems and processes. Ensure data alignment between contract documentation and customer master data,\nup to date process documentation and training material,\nSupport: Ensure issues are identified, tracked, reported on and resolved in a timely manner.\nDevelopment & maintenance\nRole of expert for the designated product or product domain.\nDeals with user requests, service tickets, incidents, modifications\nAssume the 3rd level support activities\nWrites and maintains the documentation\nParticipates in creating user guides\nEnsures that knowhow of domain is transferred to team members.\nEnsures compliance with data security at all times.\nEvaluates applications and databases performance and enhances when possible\nCarry out or supervise development and system integration activities.\nProject management\nLead data related projects as IT representative\nDefines scope of the project, plans and follows project developments and deployments of applications.\nSupervise external resources during project phase.\nSkills required:\nCustomer driven approach\nExperience working in azure DF, Synapse, AWS, or other\nworking with Agile methodologies\nproblem solving, ability to work under pressure and able to prioritise\nand ability to work independently with limited supervision\ncommunication and interpersonal skills, ability to work effectively with remote teams\ngood oral and written communication\nin English\nDate of Employment: ASAP\nShow more\nShow less",
        "details": {
            "JobDetail": [
                "Remote"
            ],
            "TypeContract": "",
            "Salary": "",
            "Level": "",
            "Experience": null
        },
        "title": "data architect",
        "skills": {
            "BigData": [
                "Spark"
            ],
            "CloudComputing": [
                "AWS",
                "Azure"
            ],
            "Collaboration": [
                "Teams"
            ],
            "EnSoftSkils": [
                "Problem Solving",
                "Communication",
                "Organization",
                "Interpersonal Skills"
            ]
        }
    },
    {
        "source": "LinkedIn",
        "company": "JSS ASSOCIATES",
        "location": "Paris, Île-de-France, France",
        "link": "https://fr.linkedin.com/jobs/view/senior-data-architect-consultant-at-jss-associates-3912573427?position=21&pageNum=0&refId=a5rwPua%2FMvx%2F2M%2FPSF0oPA%3D%3D&trackingId=ksX%2FYtGaX9xFT9xx8JPlNw%3D%3D&trk=public_jobs_jserp-result_search-card",
        "description": "Senior Data Architect / Consultant\nFor one of my leading clients focused in data advisory, we are looking for an experienced Data Architect / Consultant to join their dynamic team based in an affluent and upscale suburb west of Paris.\nMy client is renowned by industry experts for its commitment to empowering its clients in establishing robust data frameworks. Offering bespoke solutions span from fostering cultural shifts and technological empowerment to ensuring data consistency, security, and precision. With expertise in Data Advisory, Architecture, Academy, and Green Data, as well as proficiency in implementing Platform Data solutions such as Data Preparation and Integration. My client caters to diverse clients across the world. Driven by core values, they strive for sustainable consulting services, leveraging innovation and pragmatism in their data-centric approach.\nRole Overview:\nReporting to either the Data Advisory Manager or the Director of the Data Advisory Business Line, you will collaborate with clients on multifaceted missions. You will participate in pre-sales activities, response to calls for tenders and support and participate in internal projects related to the development of my clients business interests.\nCommercial aspect:\nParticipate in pre-sales activities, response to calls for tenders and support, all of the entrusted activities are carried out in compliance with my clients quality level. Participate in internal projects related to the development of my clients business interests.\nManagement responsibilities:\nSupervise and develop the skills of consultants within your scope.\nEnsure the skills development of junior/confirmed consultants, coaching and monitoring\nData Architecture section:\nSupport audit or urbanization missions of data platforms and tools responding to the company's new challenges: definition of the scope, estimation of costs, planning and organization, promotion of the methodology.\nBe responsible for the quality of project deliverables/documentation;\nLead meetings and write reports;\nSupport and advise the client in defining their data architectures;\nValidate the company's expectations in terms of functionality and functional and non-functional coverage of the solutions;\nLead and arbitrate debates defining architectural orientations;\nConduct individual interviews with the various mission contacts for Coaching or Audit;\nProject management: lead a project independently from start to finish under the supervision of your project director;\nDefinition of feedback, self-criticism and retrospectives of milestones.\nIn addition you will support a project to set up a “Data Academy” organization: definition of the scope, estimation of costs, planning and organization, promotion of the methodology.\nBe responsible for the quality of project deliverables;\nLead meetings and write reports;\nSupport and advise the client in managing change in their organization to support implementation;\nValidate the company's expectations in terms of acculturation and maturity around data;\nLead and arbitrate debates defining strategic orientations;\nConduct individual interviews with the various project stakeholders for Coaching or Audit;\nProject management: lead a project independently from start to finish under the supervision of your project director;\nDefinition of feedback, self-criticism and retrospectives of milestones.\nData governance component:\nFramework a governance initiative: identification of use cases, customer needs in terms of data governance, and the appropriate methodology;\nDesign and implement a data governance solution: glossary, business, metadata, processes, roles and responsibilities, lineage.\nDefine the roadmap to improve governance.\nYour profile:\nRequired skills:\nA Data Architect profile with a functional/technical background capable of:\nParticipate in pre-sales/proposals and the definition and audit of the architecture;\nPrepare and lead various Workshop committees;\nSupport Architects and Data Advisors;\nHave solid experience in enterprise architecture and consulting activities, be able to advise the best typical model according to needs.\nMinimum of Bac+5 training within a major engineering or IT school, you have at least 5 years of experience in this type of role;\nYou have worked in the field of information management in the company, data governance, or the implementation of Data solutions (MDM, DQM, Data Catalog Data Science, Data Preparation);\nDynamic and enthusiastic, you like teamwork and you want to actively participate in the development of our company and the training of consultants. Your thirst for entrepreneurship and your desire to participate in our development will be determining elements;\nThanks to your good level of English, you will participate with ease in international missions;\nYou will work in a very motivating and friendly context and you will benefit from significant freedom over the missions you will have to accomplish.\nShow more\nShow less",
        "details": {
            "JobDetail": [
                "Confirmed",
                "Junior",
                "Senior"
            ],
            "TypeContract": "",
            "Salary": "",
            "Level": "Bac+5",
            "Experience": null
        },
        "title": "data architect",
        "skills": {
            "EnSoftSkils": [
                "Initiative",
                "Teamwork",
                "Organization"
            ]
        }
    },
    {
        "source": "LinkedIn",
        "company": "Lincoln France",
        "location": "Boulogne-Billancourt, Île-de-France, France",
        "link": "https://fr.linkedin.com/jobs/view/data-architect-senior-h-f-at-lincoln-france-3909573086?position=22&pageNum=0&refId=a5rwPua%2FMvx%2F2M%2FPSF0oPA%3D%3D&trackingId=e90%2FpCVUztPl3zl6iZg0KA%3D%3D&trk=public_jobs_jserp-result_search-card",
        "description": "Poste CDI : Data Architect Senior - H/F\n📊 8 ans minimum\nLincoln Pure Player Data\n💡: Réinventant l'analyse\ndepuis 30 ans\n. Experts en Modern BI, Big Data et Science des données 📊. Nous transformons vos données en solutions pour les grands comptes, des secteurs bancaire, retail, télécoms, industriel, santé, et plus encore 💼.\nDescription du poste :\nNous recherchons un\nData Architect\nexpérimenté pour rejoindre notre équipe dynamique. Vous intégrerez\nla direction Conseil Innovation et Développement de Lincoln\nau sein de laquelle vous pourrez développer tout votre savoir\n🎯\nMissions\n:\nConcevoir et développer\nl'architecture de données\n, en alignant les besoins de l'entreprise avec les meilleures pratiques du secteur. (Savoir utiliser les services cloud / outils pour répondre aux besoin de l’entreprise)\nCollaborer avec\nles équipes techniques et métiers\npour définir les exigences et les objectifs en matière de données.\nDéfinir et maintenir\nles normes et les directives de gouvernance des données\n.\nConcevoir et mettre en œuvre des\nsolutions de sécurité des données pour protéger l'intégrité et la confidentialité des informations sensibles\n.\nGérer les\nprocessus d'intégration, de transformation et de migration\ndes données.\nÉvaluer et sélectionner les outils et les technologies adaptés à l'architecture de données de l'entreprise.\nParticiper à\nl'évaluation des risques et à la planification de la continuité des activités\nliées aux données.\nParticiper à la réalisation de missions de conseil\n(audit, étude de migration de plateforme, design d’architecture DATA…)\nConcevoir et superviser l'architecture de données du client\n, en veillant à ce qu'elle réponde aux besoins actuels et futurs de l'organisation\nParticiper aux réponses aux\nappels d’offre\nSupport technique\nau partenariat éditeur de Lincoln\nRéaliser de\nla veille technologiques\n(solution DATA, cloud/on premise)\n🔍\nPrérequis\n:\nExpérience avérée en tant que Data Architect ou dans un rôle similaire.\nConnaissance approfondie des concepts et des principes de l'architecture de données.\nTrès bonne connaissance des environnements de cloud (spécialiste sur au moins une technologie – GCP, Azure, Aws, Snowflake, Databricks…)\nMaîtrise des technologies et des outils de gestion de données, tels que les bases de données relationnelles, les entrepôts de données, les outils ETL, etc.\nSolide compréhension des principes de sécurité des données et de la conformité aux réglementations en vigueur.\nExcellentes compétences analytiques et de résolution de problèmes.\nCapacité à travailler efficacement en équipe et à communiquer clairement avec des interlocuteurs techniques et non techniques.\nDiplôme d’ingénieur ou universitaire en informatique, en science des données ou dans un domaine connexe (un atout).\nConnaissance de modélisation des données (3FN, étoile, flocon)\nEnvironnements techniques :\nEnvironnement de cloud (GCP, Azure, AWS) vs On premises (Hadoop, Cloudera)\nBases de données relationnelles et base de données NoSql (MySQL, Oracle, SQL Server, PostgreSQL, Mango DB, Cassandra, GCP Big query, Snowflake, Redshift)\nLangage : Python, Pyspark, SQL\nOutils ETL / ELT: Informatica, Talend, IBM DataStage, DBT\n🌟\nAvantages :\nEnvironnement collaboratif et innovant\nFormations certifiantes et accompagnement individualisé\nTélétravail et horaires flexibles\nRémunération compétitive avec avantages sociaux attrayants\nPossibilité de mobilité à Lille, Lyon ou Aix-en-Provence\n✨\nProcessus de recrutement\n: 2 entretiens (RH et technique)\nSi vous êtes passionné par les défis de la Data et que vous souhaitez rejoindre une équipe dynamique et innovante,\npostulez dès maintenant et contribuez à redéfinir l'avenir de l'analyse de données chez Lincoln! 😉\nShow more\nShow less",
        "details": {
            "JobDetail": [
                "Senior"
            ],
            "TypeContract": "CDI",
            "Salary": "",
            "Level": "",
            "Experience": "8 an(s)"
        },
        "title": "data architect",
        "skills": {
            "ProgLanguage": [
                "Python"
            ],
            "DataBase": [
                "SQL",
                "Cassandra",
                "NoSQL"
            ],
            "BigData": [
                "Databricks",
                "Hadoop"
            ],
            "CloudComputing": [
                "GCP",
                "AWS",
                "Azure"
            ],
            "DBMS": [
                "SQL Server",
                "MySQL",
                "Big Query",
                "PostgreSQL",
                "Snowflake"
            ],
            "SoftBigDataProcessing": [
                "Cassandra"
            ],
            "Other": [
                "Cloud",
                "Big Data"
            ]
        }
    },
    {
        "source": "LinkedIn",
        "company": "Akkodis",
        "location": "France",
        "link": "https://fr.linkedin.com/jobs/view/data-architect-h-f-at-akkodis-3894683359?position=23&pageNum=0&refId=a5rwPua%2FMvx%2F2M%2FPSF0oPA%3D%3D&trackingId=I9eYsNqP6O%2FDAy8ljoEwxA%3D%3D&trk=public_jobs_jserp-result_search-card",
        "description": "La ligne de service Consulting & Solutions d Akkodis France renforce ses équipes et recrute\nun Data Architect H/F\nen CDI dans l’un de nos sites principaux en Ile de France ou en Province.\nDescription de la mission :\nL’offre data intelligence d’AKKODIS fait partie des 7 expertises internationales du Groupe. Elle adresse aujourd’hui des projets sur de nombreux secteurs d’activité : Aéronautique, Transport, Energie, Banque & Assurance, Défense.\nSon objectif est d’aider nos clients à améliorer leurs processus opérationnels, leur time-to-market et leur prise de décision en permettant :\n- la mise en place de la continuité digitale\n- de gagner en maturité dans l’utilisation et la valorisation des données\nvia la mise en œuvre de technologies et plateformes data et l’utilisation data sciences et de l’IA.\nNotre stratégie de croissance nous amène aujourd’hui à renforcer nos compétences métier dans le domaine de la Data Intelligence et dans ce cadre nous recherchons un(e) Data Architect capable d’apporter son expertise sur les projets présents dans notre portefeuille actuel et auprès des consultants Akkodis tout en travaillant sur les sujets d’avant-vente et de construction d’offre afin d’élargir notre scope d’intervention.\nIntégré(e) à l’équipe Data Intelligence, vous travaillerez en collaboration avec une équipe d’une trentaine de personnes et participerez au développement de projets innovants (Jumeau numérique, Industrie 4.0, maintenance prédictive, IA générative,..)\nVous vous verrez confier les missions suivantes :\n· Participer à la conception de l'architecture de notre plateforme Data ainsi qu’à celles de nos clients (On Premise, Cloud, Hybride)\n· Participer à la veille technologique et prendre en charge l'expérimentation de nouvelles solutions du marché\n· Réaliser des missions d’audit et conseil en architecture pour nos clients ; implémentation de projets data\nDiplômé(e) d'un Bac + 3/+5 en informatique, vous justifiez d’une expérience de 10 ans minimum dans les domaines de la Data et maitrisez les technologies Python, PySpark, Kafla, Spark et l’environnement Linux.\nVous disposez expériences probantes dans l’implémentation de projets data au sein de cloud providers (MS Azure, GCP ou AWS) et êtes en capacité de benchmarker les solutions proposées, de conseiller nos clients sur les architectures et outils à mettre en place. Vous avez de bonnes capacités de synthèse et savez convaincre. Vous avez le sens du relationnel et faites preuve d'adaptabilité et de flexibilité. Vous êtes curieux et imaginatif pour trouver des solutions adaptées.\nAlors n'hésitez plus, rejoignez-nous en nous transmettant votre CV !\nA compétences égales, le poste est ouvert aux personnes en situation de handicap.\nEn intégrant AKKODIS vous rejoindrez une entreprise dans laquelle votre savoir-être et votre savoir-faire feront la différence pour inventer le futur de nos clients. Votre rôle s’inscrit dans un véritable projet d'entreprise.\nAkkodis accompagne ses clients dans la mondialisation de leurs projets, aussi un anglais courant est requis pour l ensemble de nos collaborateurs.\nChez Akkodis nous sommes convaincus que de l’intelligence collective naît le succès. Il n’existe pas qu’un modèle, nous valorisons l’agilité et l’excellence, l’audace et la créativité.\nEt si nous parlions ensemble de vos ambitions pour les prochaines années ?\nAkkodis est une entreprise handi-engagée et inclusive. Tous nos postes sont ouverts aux handicaps et à la diversité. Tous différents, tous compétents !\nAkkodis, est un acteur mondial de l’ingénierie et de l’IT et un leader dans la smart industrie. Nous accompagnons nos clients dans leurs projets de transformation digitale via 4 lignes de service : Consulting, Solutions, Talent et Academy. Akkodis est un partenaire technologique de confiance pour ses clients à l’échelle internationale. Nous co-créons et nous imaginons des solutions de pointe pour répondre aux défis majeurs de notre société, qu'il s'agisse d'accélérer la transition énergétique et de développer la mobilité verte, ou encore de construire des approches centrées sur les utilisateurs.\nDotés d’une forte culture de l’inclusion et de la diversité, nos 50 000 experts en IT et en ingénierie, présents dans 30 pays, allient les meilleures compétences technologiques à une connaissance transverse de toutes les industries pour façonner un futur plus durable. Nous sommes passionnés par l’idée d’inventer ensemble un avenir meilleur.\nAkkodis en France, ce sont près de 9.000 experts en IT et en ingénierie répartis sur l'ensemble du territoire, des collaborateurs partageant des valeurs fortes d'honnêteté, de respect, d'équité et d'inclusion. Notre engagement : leur permettre au quotidien d'être eux-mêmes au travail, et acteurs de leur vie et de leur développement au sein d'Akkodis..\nAkkodis est la marque technologique de The Adecco Group\n*Akkodis est une marque commerciale sous laquelle les entités AKKA et Modis opèrent\nShow more\nShow less",
        "details": {
            "JobDetail": [
                "Hybride"
            ],
            "TypeContract": "CDI",
            "Salary": "",
            "Level": "",
            "Experience": "10 an(s)"
        },
        "title": "data architect",
        "skills": {
            "ProgLanguage": [
                "Python"
            ],
            "BigData": [
                "Spark"
            ],
            "CloudComputing": [
                "GCP",
                "AWS",
                "Azure"
            ],
            "OS": [
                "Linux"
            ],
            "Other": [
                "Cloud"
            ],
            "EnSoftSkils": [
                "Collaboration"
            ]
        }
    },
    {
        "source": "LinkedIn",
        "company": "Schneider Electric",
        "location": "Lattes, Occitanie, France",
        "link": "https://fr.linkedin.com/jobs/view/data-model-architect-f-h-at-schneider-electric-3864654667?position=24&pageNum=0&refId=a5rwPua%2FMvx%2F2M%2FPSF0oPA%3D%3D&trackingId=v3%2F141hz7OHIAN2jbFJZAA%3D%3D&trk=public_jobs_jserp-result_search-card",
        "description": "Missions\nAs a Data Architect, you will play a crucial role in shaping and optimizing our product's data infrastructure. You will be responsible for designing, implementing, and maintaining scalable and efficient data solutions that meet business needs. This role requires a deep understanding of data management and a strategic mindset to align data architecture with overall business strategies:\nData Modeling and Design:\nEnsure compliance with industry standards such as IEC61850\nDevelop and maintain conceptual, logical, and physical data models\nDesign data structures and relationships that support business requirements and enable efficient data retrieval\nData Governance:\nEstablish and enforce data governance policies and procedures\nDefine data standards, naming conventions, and data quality rules\nData Integration:\nDesign and implement data integration solutions to ensure seamless flow of information across systems\nCollaborate with other IT teams to integrate data sources and maintain data consistency\nCollaboration and Communication:\nWork closely with business stakeholders to understand their data needs and translate them into effective data solutions\nCollaborate with cross-functional teams including analysts and developers\nSecurity and Compliance:\nImplement data security measures to protect sensitive information\nProvide leadership, analysis, and design tasks related to the development or upgrade of a solution to ensure the application provides expected business value. Provide architecture guidance and support on activities performed to maintain, improve, or support applications.\nProfile\nBachelor's or Master's degree in Computer Science, Information Technology, or a related field\nMinimum of 5 years of experience as a Data Architect or in a similar role\nKnowledge of IEC61850\nStrong knowledge of database management systems and data modeling techniques\nUnderstanding of agile methods and processes, and the capability of supporting agile project teams\nAnalytical and strategic thinking\nExcellent communication and collaboration skills\nProblem-solving and troubleshooting abilities\nStay updated on emerging trends and technologies in data management\nWhy us?\nSchneider Electric is leading the digital transformation of energy management and automation. Our technologies enable the world to use energy in a safe, efficient and sustainable manner. We strive to promote a global economy that is both ecologically viable and highly productive.\n€34bn global revenue\n128 000+ employees in 100+ countries\n45% of revenue from IoT\n5% of revenue devoted for R&D\nYou must submit an online application to be considered for any position with us. This position will be posted until filled\nIt is the policy of Schneider Electric to provide equal employment and advancement opportunities in the areas of recruiting, hiring, training, transferring, and promoting all qualified individuals regardless of race, religion, color, gender, disability, national origin, ancestry, age, military status, sexual orientation, marital status, or any other legally protected characteristic or conduct. Concerning agencies: Schneider Electric does not accept unsolicited resumes and will not be responsible for fees related to such.\nShow more\nShow less",
        "details": {
            "JobDetail": [],
            "TypeContract": "",
            "Salary": "",
            "Level": "",
            "Experience": null
        },
        "title": "data architect",
        "skills": {
            "ProgLanguage": [
                "R"
            ],
            "DataAnalytics": [
                "R"
            ],
            "Collaboration": [
                "Teams"
            ],
            "EnSoftSkils": [
                "Leadership",
                "Communication",
                "Collaboration"
            ]
        }
    },
    {
        "source": "LinkedIn",
        "company": "Harnham",
        "location": "Paris",
        "link": "https://fr.linkedin.com/jobs/view/data-architect-at-harnham-3911912252?position=25&pageNum=0&refId=a5rwPua%2FMvx%2F2M%2FPSF0oPA%3D%3D&trackingId=%2BTxN4OcYZuigrD5W0hnoCQ%3D%3D&trk=public_jobs_jserp-result_search-card",
        "description": "DATA ARCHITECT\nPARIS (75)\nUP TO 65K€ FIXE\nAWS - Tableau - Pyspark - Data Modeling\nVous êtes à la recherche d'un nouveau challenge de Data Architect dans le domaine de l'assurance ? Ne cherchez plus, voici l'opportunité de vos rêves ! Une entreprise spécialisée dans l'assurance automobile des particuliers, recherche un Data Architect dans le cadre de la création d'une nouvelle plateforme data en Europe.\nLE POSTE\nEn tant que Data Architect, vous allez définir les architectures et les normes pour la stratégie de données. Vous définirez la vision et les lignes directrices pour la livraison des produits de données.\nVoici vos responsabilités au quotidien :\nDéfinir l'architecture cible\nCommuniquer avec les Product Owner pour atteindre l'objectif du wagon\nTravailler en étroite collaboration avec les data scientists pour opérationnaliser les modèles ML au sein de la plateforme de données\nTravailler en étroite collaboration avec les data engineer et data ops pour le suivi de l'architecture cible\nTravailler en mode agile au quotidien\nVOTRE PROFIL\nDiplôme d'ingénieur en computer engineering ou mathématiques\n5 ans d'expérience en architecture data\nConnaissance des architectures de plateformes de données opérationnelles\nConnaissance de la modélisation de données et bases de données\nConnaissance du cloud AWS\nConnaissance d'outils BI principalement Tableau\nBilingue (fançais et anglais)\nNice to have : connaissance en Machine Learning\nPOUR POSTULER\nMerci de me faire part de votre CV et je vous recontacterai au plus vite.\nShow more\nShow less",
        "details": {
            "JobDetail": [],
            "TypeContract": "",
            "Salary": "",
            "Level": "",
            "Experience": "5 an(s)"
        },
        "title": "data architect",
        "skills": {
            "DataVisualisation": [
                "Tableau"
            ],
            "CloudComputing": [
                "AWS"
            ],
            "Other": [
                "Machine Learning",
                "Cloud",
                "ML"
            ],
            "EnSoftSkils": [
                "Collaboration"
            ]
        }
    },
    {
        "source": "LinkedIn",
        "company": "FRG Technology Consulting",
        "location": "Paris, Île-de-France, France",
        "link": "https://fr.linkedin.com/jobs/view/architecte-data-at-frg-technology-consulting-3917370845?position=26&pageNum=0&refId=a5rwPua%2FMvx%2F2M%2FPSF0oPA%3D%3D&trackingId=mFbs%2FJJcyFdi2JyuXmjTDA%3D%3D&trk=public_jobs_jserp-result_search-card",
        "description": "Notre client, entreprise renommée dans le secteur du luxe et des cosmétiques, basé sur Paris, est à la recherche de son/sa futur(e) Architecte Data.\nEn tant que membre de la DSI, votre rôle est de participer à la transformation digitale de l’entreprise, par une meilleure capture, analyse et exploitation des données clients.\nPrincipales missions :\nAnalyse et réponses aux besoins des métiers (BI, analyses externes, etc.),\nConception de nouveaux modèles de données\nConstruction des pipelines de données\nTransformation de données (Pyspark) et le stockage de données dans le Data Lake / Data Warehouse du Groupe\nRun et le suivi de la TMA\nDescription du profil :\nTitulaire Bac +5 informatique ou diplôme ingénieur\n6 années minimum en expertise Data\nUne bonne maîtrise des outils suivants : Azure, SQL, Snowflake, Databricks, Spark, Python, ELK,..\nUne bonne affinité avec les best practices DevOps, CI/CD, unit-testing et méthodologies de travail agile\nDes notions en data science sur l’entraînement, la validation et le déploiement de modèles ML supervisés et non-supervisés serait un plus.\nQualités requises : Bon esprit analytique et de synthèse, rigoureux, autonome, bonne communication, curieux, force de proposition, vulgarisation des problématiques techniques auprès du métier\nAvantages :\nPackage (variable / participation / intéressement) + avantages attractifs\nÉquipe Data à taille humaine (très bon accompagnement en interne)\nForte valeur ajoutée des projets\nTélétravail\nCandidatures confidentielles\nShow more\nShow less",
        "details": {
            "JobDetail": [],
            "TypeContract": "",
            "Salary": "Package",
            "Level": "",
            "Experience": null
        },
        "title": "data architect",
        "skills": {
            "ProgLanguage": [
                "Python"
            ],
            "DataBase": [
                "SQL"
            ],
            "BigData": [
                "Databricks",
                "Spark"
            ],
            "CloudComputing": [
                "Azure"
            ],
            "DBMS": [
                "Snowflake"
            ],
            "Other": [
                "ML",
                "DevOps",
                "CI/CD"
            ],
            "EnSoftSkils": [
                "Communication"
            ]
        }
    },
    {
        "source": "LinkedIn",
        "company": "Ippon Technologies",
        "location": "Lyon",
        "link": "https://fr.linkedin.com/jobs/view/architecte-data-f-h-at-ippon-technologies-3893256404?position=27&pageNum=0&refId=a5rwPua%2FMvx%2F2M%2FPSF0oPA%3D%3D&trackingId=6CvjRcGeId%2FV7kMGgeTUyg%3D%3D&trk=public_jobs_jserp-result_search-card",
        "description": "Qui sommes-nous ?\nIppon\n, c'est l’énergie du collectif au service de la technologie ! Nous sommes un cabinet de conseil et d’expertise technique. Nos équipes ont pour leitmotive de transformer des idées innovantes en solutions logicielles de haute qualité avec un focus particulier sur la valeur apportée aux utilisateurs.\nCréée en 2017, l’agence de Lyon, ce sont des passionnés intervenant sur des projets à forte technicité ou en conseil et architecture : Fullstack, Data, DevOps, Cloud, Agile, Design et ne compte pas s’arrêter en si bon chemin !\nLa pluridisciplinarité, l’expertise, l’écoute, l’adaptabilité mais aussi le partage de connaissances fondent notre engagement au service de nos partenariats.\nVous intégrerez notre Communauté Data\n, composée d’une équipe de\n80 experts sur 10 agences en France.\nNotre spécialité est de\nconstruire des data platforms dans le Cloud public avec les meilleures technos du moment.\nLa\nData chez Ippon, c’est déjà plus de\n250 certifications AWS, GCP et AZURE,\ndes\nspeakers à l’AWS Summit, des partenariats avec Snowflake, Databricks, DBT, un blog technique\navec des publications régulières.\nCe poste est un vrai challenge aussi bien en termes de\ndéfis techniques que de gestion d'équipe.\nLa\nréussite de vos projets sera portée par votre capacité à vous adapter et à monopoliser un large panel de compétences techniques. Vous devrez être le/la leader de votre équipe en gardant à l’esprit l’ensemble des\nbonnes pratiques d'architectes\n, de sécurité et d’automatisation nécessaires à la réussite du projet. En tant que\nreprésentant(e) de l’engagement d’Ippon\nsur les sujets qui vous seront confiés, vous serez amené(e) à\ntravailler avec notre équipe Commerce dès les phases de qualification\net lors de la validation de jalons de la roadmap que vous aurez préalablement validé avec le client. Vous interviendrez également dans la sélection de l’équipe qui sera affectée à votre projet.\nVotre rôle :\n- Grâce à votre position d’architecte vous avez une vision experte et systémique de l’ensemble des composants d’une Modern Data Platform.\n- Vous maîtrisez le panel des exigences fonctionnelles et non fonctionnelles à collecter afin d’assurer l’efficience opérationnelle et la pérennité de la data platform.\n- Vous êtes expert(e) et maîtrisez tous les outils et services d’au moins un écosystème parmi les 3 principaux leaders du marché (AWS, Azure et GCP) et avez des facilités pour étendre votre champ de compétences.\n- Vous êtes proactif/ve sur la veille technique et la capitalisation et veillez à garder toujours un temps d’avance sur l’état de l’art du secteur afin de pouvoir guider vos clients.\n- En tant qu’architecte expérimenté(e) vous pouvez indifféremment intervenir sur des missions de delivery pour concevoir la solution cible ou en phase de cadrage amont pour guider les choix et construire les roadmaps.\n- Vous êtes pédagogue et savez communiquer et vulgariser des réflexions complexes pour les rendre accessibles à tous.\nNotre éco-système technique :\n- Cloud : AWS, GCP, Azure\n- Langage de programmation data : Python, SQL, Scala\n- Approche Data Warehouse : Redshift, Snowflake, BigQuery\n- Approche Data Lakehouse : Databricks, Starburst, Glue-Athena-S3Ingestion : AWS Glue, Airbyte, dbt Stockage : AWS S3, Google Cloud Storage, Azure Blob Storage\n- Orchestration : Airflow, AWS Step function\n- Gouvernance : cataloging, sécurité, scope d'accèsBatch et Streaming : Kafka, Amazon Kinesis, Google DataFlow\n- Outil de visualisation : Tableau, Power BI, Metabase, Superset\nVotre évolution chez Ippon :\nVous serez accompagné(e) dans votre montée en compétences aussi bien technique que leadership grâce à\nnotre programme BlackBelt\n(programme de formation continue : mentoring, formations, certifications).\nEn tant que membre d’une communauté,\nvous pouvez avoir différents rôles :\n- Celui de Manager Technique (MT) : manager d’une équipe de 7 ingénieur(e)s Ippon (onboarding, suivis, accompagnement, mise en place d’objectifs…). Vous conduirez les entretiens techniques en binôme\n- Responsable de l’accomplissement d’une ou plusieurs actions stratégiques de la CoreTeam Data\n- Devenir speaker lors de Meetup, Summit, Talks internes, auprès des écoles …\n- Devenir formateur(trice) et accompagner la nouvelle génération d’Ippon dans leur montée en compétencesVous avez d’autres souhaits, pas de soucis, nous en discuterons durant notre échange et répondrons à toutes vos questions.\nLes Next Steps :\n1 Echange RH\n1 Echange Technique\n1 Echange avec la Direction\nSi le match est bon des deux côtés : Vous vous lancerez sur le tatami Ippon !\nShow more\nShow less",
        "details": {
            "JobDetail": [
                "Full"
            ],
            "TypeContract": "",
            "Salary": "",
            "Level": "",
            "Experience": null
        },
        "title": "data architect",
        "skills": {
            "ProgLanguage": [
                "Scala",
                "Python"
            ],
            "DataBase": [
                "SQL"
            ],
            "BigData": [
                "Databricks"
            ],
            "DataVisualisation": [
                "Power BI",
                "Tableau"
            ],
            "CloudComputing": [
                "GCP",
                "AWS",
                "Azure"
            ],
            "DBMS": [
                "BigQuery",
                "Snowflake"
            ],
            "Automation": [
                "Airflow"
            ],
            "Other": [
                "Cloud",
                "DevOps"
            ],
            "EnSoftSkils": [
                "Leadership"
            ]
        }
    },
    {
        "source": "LinkedIn",
        "company": "Akademija Oxford",
        "location": "Boulogne-Billancourt, Île-de-France, France",
        "link": "https://fr.linkedin.com/jobs/view/data-analyst-junior-h-f-at-akademija-oxford-3917871112?position=28&pageNum=0&refId=a5rwPua%2FMvx%2F2M%2FPSF0oPA%3D%3D&trackingId=f1yl%2BuAsrVAr6V%2FZJ%2F13UQ%3D%3D&trk=public_jobs_jserp-result_search-card",
        "description": "Notre entreprise partenaire, spécialiste de la vente de médicaments et produits de santé, recherche un apprenti Data Analyst (H/F) préparant un bac +4/+5 en filière Big Data pour la rentrée de Septembre 2021.\nShow more\nShow less",
        "details": {
            "JobDetail": [],
            "TypeContract": "",
            "Salary": "",
            "Level": "",
            "Experience": null
        },
        "title": "data analyst",
        "skills": {
            "Other": [
                "Big Data"
            ]
        }
    },
    {
        "source": "LinkedIn",
        "company": "FRG Technology Consulting",
        "location": "Paris, Île-de-France, France",
        "link": "https://fr.linkedin.com/jobs/view/data-architect-azure-at-frg-technology-consulting-3902057360?position=29&pageNum=0&refId=a5rwPua%2FMvx%2F2M%2FPSF0oPA%3D%3D&trackingId=zMsO%2FBb3IByPj0twNDoAAQ%3D%3D&trk=public_jobs_jserp-result_search-card",
        "description": "FRG Consulting recrute pour l'un de ses clients, une société finale renommée dans le secteur du luxe et des cosmétiques, un Data Architect expert en Azure. Niché au cœur de Paris, vous aurez l'opportunité de travailler au sein d'une équipe passionnée par la recherche et l'innovation, évoluant dans un environnement stimulant et créatif.\nVos missions captivantes :\nContribuer à l'évolution de nos systèmes en développant de nouveaux connecteurs et pipelines pour l'extraction de données, qu'il s'agisse de batch (utilisant Sqoop, scripts bash, Java ou des API) ou de streaming (via Kafka, ELK).\nParticiper activement à la transformation des données à l'aide de Pyspark, ainsi qu'au stockage dans notre Data Lake et notre Data Warehouse.\nConcevoir de nouveaux modèles de données et mettre à disposition des tables ad-hoc sur Snowflake et Impala, répondant ainsi aux besoins métier en termes de BI et d'analyses externes.\nAssurer le bon fonctionnement et le suivi de la TMA du Data Lake, garantissant ainsi la fiabilité et la performance de nos systèmes.\nProfil recherché :\nVous bénéficiez d'au moins 8 ans d'expérience dans le domaine.\nVous maîtrisez les outils et frameworks de notre stack technique Big Data : Azure, SQL, Snowflake, Databricks, Spark, Python, ELK.\nVous êtes familier des best practices DevOps, CI/CD, et des méthodologies de travail agile.\nDes compétences en data science, notamment sur l'entraînement, la validation et le déploiement de modèles ML supervisés et non-supervisés, seraient grandement appréciées.\nLa maîtrise de l'anglais est indispensable pour évoluer dans un environnement international et dynamique.\nShow more\nShow less",
        "details": {
            "JobDetail": [],
            "TypeContract": "",
            "Salary": "",
            "Level": "",
            "Experience": "8 an(s)"
        },
        "title": "data architect",
        "skills": {
            "ProgLanguage": [
                "Java",
                "Bash",
                "Python"
            ],
            "DataBase": [
                "SQL"
            ],
            "BigData": [
                "Databricks",
                "Spark"
            ],
            "CloudComputing": [
                "Azure"
            ],
            "DBMS": [
                "Snowflake"
            ],
            "Other": [
                "ML",
                "Big Data",
                "DevOps",
                "CI/CD"
            ]
        }
    },
    {
        "source": "LinkedIn",
        "company": "TeamWork Corporate",
        "location": "Saint-Priest, Auvergne-Rhône-Alpes, France",
        "link": "https://fr.linkedin.com/jobs/view/data-architect-senior-freelance-h-f-at-teamwork-corporate-3916528778?position=30&pageNum=0&refId=a5rwPua%2FMvx%2F2M%2FPSF0oPA%3D%3D&trackingId=K%2BcSw9XhUoNNd0%2BsEaReTg%3D%3D&trk=public_jobs_jserp-result_search-card",
        "description": "Description de l'entreprise\nTeamWork est un acteur majeur du conseil, de l’intégration technologique et de l’innovation, implanté en Europe, en Asie et en Amérique du Nord.\nAu travers de ses univers, SAP Business Solutions, Data Analytics, Technology Platform et Salesforce, nous sommes reconnus par nos clients pour accroître leur performance opérationnelle.\nLa transformation digitale est un enjeu majeur pour toute organisation.\nLa nécessité de digitaliser ses processus, d’imaginer de nouvelles façons d’interagir avec ses clients, d’en conquérir de nouveaux et de proposer de nouveaux outils pour anticiper les besoins de pilotage n’a jamais été aussi forte.\nL’univers Data Analytics de TeamWork accompagne les organisations autour de :\nLa réflexion et identification de cas d’usage pour les transformer en trajectoires moyen et long terme\nLe design et l’implémentation de plateforme de données et des outils périphériques (data ingestion/intégration)\nLa mise en place des premières solutions d’Analytics (Business Intelligence, EPM,)\nSupport, extension et optimisation des solutions\nDans le cadre du développement de ces activités, nous recrutons un\nData Architect Senior (H/F)\nen Freelance pour une mission entre 2 à 3 mois.\nDescription du poste\nEn tant qu’Architecte Data vous intervenez dans le cadre de projets et missions qui répondent aux enjeux clients d’exploitation des données. Vous participez aux phases d’avant-vente, aux études d’architecture, et à la réalisation des solutions avec une responsabilité d’encadrement technique des projets (tant sur des forfaits que des missions clients). Vous aurez des missions avec de réelles responsabilités et très diversifiées (secteurs d’activités variés).\nVos principales missions s’articulent autour de :\nL’analyse et la qualification des besoins et problématiques « métiers » de nos clients\nAssurer la conception, le développement et la mise en oeuvre de l'architecture des données sur la plateforme Databricks\nLa définition et mise en œuvre des architectures Data adaptées aux contextes des projets : Modern Datawarehouse, LakeHouse, DataMesh etc.\nL’accompagnement des Consultants et des Ingénieurs spécialistes Data sur les projets. Vous œuvrez à qualité de leurs réalisations et des livrables.\nLa collaboration sur tous les domaines d’activités DATA : BI, Big Data, IoT, IA\nL’apport d’un regard critique et la capacité à conseiller sur le choix des technologies Data\nLa participation à la définition des bonnes pratiques de mises en œuvres techniques et la veille à leurs applications selon les méthodes en vigueur (Zero Trust Security, DataOps, Infra-as-Code, Tests automatisés etc.)\nQualifications\nTechniques :\nVous avez :\nTrès bonnes connaissances de Databricks\nLa capacité à réaliser la conception et l’implémentation de solutions d’analytique à l’échelle de l’entreprise ; SQL\nLa connaissance d’un ou plusieurs outils ETL (Azure Data Factory ou autres) et Data Visualisation (PowerBI par exemple)\nLa capacité à mettre en place une solution Data end-to-end La connaissances des typologies d’architectures (Modern Datawarehouse, LakeHouse ou DataMesh)\nVous connaissez l’environnement Azure, MSBI, SQL Server ou si vous avez des notions dans l’IA (Python, R, Machine Learning)\nMaitrise le traitement et l'analyse des données en Python (Expérience dans la conception et le développement de processus ETL/ELT)\nMaitrise d’outils de traitement et de stockage distribués parmi Hadoop, Spark, Databricks, Snowflake et/ou Kafka\nConnaissance des bonnes pratiques de conception d’architecture data (sécurité, disponibilité, scalabilité, confidentialité) et des principes d’une architecture Data Mesh.\nCapacité à concevoir des architectures basées sur les services d’une plateforme Cloud : AWS ou Azure\nSoft Skills\n:\nVous êtes proactif et appréciez travailler dans un environnement ambitieux et innovant.\nVous aimez ne pas rester sur vos acquis et toujours apprendre par le biais de formations, votre veille technologique ou encore par la participation aux événements communautaires.\nHabitué à travailler aussi bien de façon autonome qu’à collaborer en équipe\nConnaissance des méthodologies Agile (SCRUM ou autres)\nEnvie d’apprendre et de partager vos savoir-faire\nCuriosité\nLangues :\nFrançais (Courant)\nAnglais (A l’aise en communication orale et écrite)\nFormation\n:\nVéritable passionné par la DATA et diplômé d’une école d’ingénieur (Bac+3 minimum) ou d'une formation spécifique orientée Data avec une expérience significative en Data Engineering et architecture.\nVous avez une expérience de plus de 7 ans en environnement informatique, dont 3 à 4 ans minimum sur un poste senior en environnement Databricks (Team Lead, Architecte ou encore Consultant Senior).\nNous attacherons davantage d’importance à votre capacité à vouloir apprendre et progresser et votre motivation qu’à votre diplôme.\nInformations supplémentaires\nTeamWork, où votre épanouissement professionnel est clé. Récompensés par le label 'Great Place to Work 2023', nous plaçons l'humain au cœur de notre entreprise.\nAu-delà des compétences, nous valorisons les personnalités qui partagent nos valeurs de solidarité et d'esprit d'équipe.\nSi ces principes vous parlent, rejoignez-nous ! Nous sommes dédiés à l'équité et à la diversité, ouvrant nos portes à tous les talents, y compris aux personnes en situation de handicap.\nPostulez et devenez un acteur de notre réussite collective chez TeamWork.\nShow more\nShow less",
        "details": {
            "JobDetail": [
                "Senior"
            ],
            "TypeContract": "",
            "Salary": "",
            "Level": "Bac+3",
            "Experience": "7 an(s)"
        },
        "title": "data architect",
        "skills": {
            "ProgLanguage": [
                "R",
                "Python"
            ],
            "DataBase": [
                "SQL"
            ],
            "DataAnalytics": [
                "R"
            ],
            "BigData": [
                "Databricks",
                "Hadoop",
                "Spark"
            ],
            "CloudComputing": [
                "AWS",
                "Azure"
            ],
            "DBMS": [
                "SQL Server",
                "Snowflake"
            ],
            "Other": [
                "Machine Learning",
                "Cloud",
                "Big Data"
            ],
            "EnSoftSkils": [
                "Teamwork",
                "Communication",
                "Collaboration"
            ]
        }
    },
    {
        "source": "LinkedIn",
        "company": "Airbus",
        "location": "Saint-Nazaire",
        "link": "https://fr.linkedin.com/jobs/view/airbus-atlantic-architecte-data-all-gender-at-airbus-3916426275?position=31&pageNum=0&refId=a5rwPua%2FMvx%2F2M%2FPSF0oPA%3D%3D&trackingId=gQfwmP6313P%2BMZbEabRRXA%3D%3D&trk=public_jobs_jserp-result_search-card",
        "description": "Job Description\nEt si VOTRE aventure avec NOUS commençait ?!\nNous vous proposons de travailler chez Airbus Atlantic, nouveau champion de dimension mondiale, n°2 des aérostructures, n°1 des sièges pilotes et dans le Top 3 des fauteuils passagers Premium.\nNotre site Airbus Atlantic basé\nà Toulouse (possibilité de travailler à Montoir de Bretagne)\nrecherche son futur\nArchitecte Data (All Gender)\nLe poste d’architecte Data est rattaché au domaine « Architecture » au sein du département « Architecture Digital & Sécurité ».\nVous serez en interface avec les architectes du Système d'Information et les différents métiers consommateurs des architectures.\nVos Principales Missions Seront Les Suivantes\nFixer les orientations et définir des politiques concernant la modélisation des données, en collaboration avec les autres architectes,\nCréer des modèles de données logiques et physiques en utilisant les meilleures pratiques pour garantir une qualité élevée des données et une réduction de leur redondance,\nInstancier, implémenter, construire, tester et maintenir les architectures data définies\nAnalyser, évaluer, tester et recommander les briques technologiques nécessaires pour l’acquisition, l’analyse et l’implémentation des données,\nAnalyser les problèmes d'intégration des systèmes liés aux données et proposer des solutions appropriées,\nDéterminer les « Data set process » c’est à dire comment les données sont intégrées et transformées pour qu’elles soient prêtes à être analysées (ex : ETL)\nParticiper aux processus d'extraction performants et qualitatifs des données des sources requises afin de répondre aux besoins de l'entreprise\nMaintenir les modèles de données conceptuels, logiques et physiques ainsi que les métadonnées correspondantes (pour la data gouvernance).\nDévelopper les meilleures pratiques pour les conventions de dénomination standard et les pratiques de codage afin d'assurer la cohérence des modèles de données,\nRespecter les normes de sécurité des données, de contrôle des exportations et de protection des données.\nConstruire les pipelines qui permettront aux Data Scientist/Analysts/Developers de mettre leurs modèles en production\nEtre garant de la fiabilité, de la qualité et de l’efficacité du traitement des données\nMaintenir les modèles créés.\nParticiper aux idéations et proposer des innovations aux services.\nDocumenter ses activités et mettre à jour le référentiel documentaire.\nParlons de vous !\nVous disposez d'une\ne\nxp\nérience de minimum 5 ans en Data & Informatique sur un poste similaire.\nLes compétences techniques à détenir pour le poste :\nL’optimisation et les standards Qualité des données informatiques\nComprendre et savoir mettre en place les différentes Structure et stockage de données\nGestion des problèmes lié à la donnée, l'architecture\nIdéalement, l'expérience des technologies suivantes serait un plus : Ressources & services data MS Azure (Databricks, Azure ML …), SGBD (SQL, MongoDB, PostGreSQL, redis), Outils ETL (Qlik replicate, Alteryx, …), Outils BI (PowerBI, Qlik, Grafana ...),\nLangages de programmation (python, SCALA, R, DAX)\nLes certifications de Azure (DP-203, AZ-300, AZ-303, AZ-304, AZ-400, AI-900) seraient un plus,\nVotre Personnalité\nFort volonté de travailler en équipe\nBonnes habitudes de documentation\nNiveau avancé en Français et en Anglais (niveau minimum B1)\nFaire preuve d’innovation et être source de proposition\nSavoir exprimer ses idées de manière claire et concise\nEtre à l'écoute\nParlons de nous !\nEnvironnement & Conditions De Travail\nAirbus Atlantic c’est aussi :\nPrendre part à des projets ambitieux, à la pointe de la technologie pour construire l’avion de demain, en lien avec les enjeux environnementaux.\nUn environnement qui valorise la proximité et la dimension humaine, au sein d’un collectif engagé et solidaire.\nL’opportunité d’apprendre et d’évoluer tout au long de votre parcours, en étant accompagné dans votre développement pour une carrière sur-mesure.\nAvoir la liberté d’entreprendre et de laisser libre court à vos initiatives.\nSes conditions de travail attractives et ses avantages : restaurant d’entreprise sur site, CSE (avantages loisirs & famille), parking entreprise, mutuelle d’entreprise (famille).\nSa politique de diversité et d'inclusion : Airbus Atlantic s’engage en faveur de l’égalité des chances pour tous.\nSon plan d'actionnariat salarié et son plan d’épargne salariale.\nNotre Processus De Recrutement\nNous avons à cœur de mieux vous connaître et de comprendre ce qui vous motive à nous rejoindre. Aussi, notre process de recrutement se déroule en plusieurs étapes après analyse de votre candidature :\nEntretien vidéo différé via la plateforme Hirevue\nEntretien avec le Manager Recruteur\nEntretien avec le/la Chargé(e) de Recrutement qui peut être complété par un questionnaire de personnalité\nEntretien avec le/la Human Resources Business Partner.\nThis job requires an awareness of any potential compliance risks and a commitment to act with integrity, as the foundation for the Company’s success, reputation and sustainable growth.\nCompany\nAirbus Atlantic\nContract Type\nPermanent\nClasse Emploi (France): Classe G13\nExperience Level\nProfessional\nJob Family\nDigital\nBy submitting your CV or application you are consenting to Airbus using and storing information about you for monitoring purposes relating to your application or future employment. This information will only be used by Airbus.\nAirbus is committed to achieving workforce diversity and creating an inclusive working environment. We welcome all applications irrespective of social and cultural background, age, gender, disability, sexual orientation or religious belief.\nAirbus is, and always has been, committed to equal opportunities for all. As such, we will never ask for any type of monetary exchange in the frame of a recruitment process. Any impersonation of Airbus to do so should be reported to emsom@airbus.com.\nAt Airbus, we support you to work, connect and collaborate more easily and flexibly. Wherever possible, we foster flexible working arrangements to stimulate innovative thinking.\nShow more\nShow less",
        "details": {
            "JobDetail": [],
            "TypeContract": "",
            "Salary": "",
            "Level": "",
            "Experience": "5 an(s)"
        },
        "title": "data architect",
        "skills": {
            "ProgLanguage": [
                "R",
                "Scala",
                "Python"
            ],
            "DataBase": [
                "SQL",
                "MongoDB"
            ],
            "DataAnalytics": [
                "R"
            ],
            "BigData": [
                "Databricks"
            ],
            "CloudComputing": [
                "Azure"
            ],
            "DBMS": [
                "PostgreSQL"
            ],
            "Other": [
                "ML"
            ],
            "EnSoftSkils": [
                "Collaboration"
            ]
        }
    },
    {
        "source": "LinkedIn",
        "company": "Capgemini",
        "location": "Nantes, Pays de la Loire, France",
        "link": "https://fr.linkedin.com/jobs/view/architecte-technique-bi-big-data-nantes-at-capgemini-3803994992?position=32&pageNum=0&refId=a5rwPua%2FMvx%2F2M%2FPSF0oPA%3D%3D&trackingId=fUq1PzQau5f0BciSOTZc7A%3D%3D&trk=public_jobs_jserp-result_search-card",
        "description": "Capgemini\nChoisir Capgemini, c'est choisir une entreprise où vous serez en mesure de façonner votre carrière selon vos aspirations, où vous serez soutenu et inspiré par une communauté d’experts dans le monde entier, où vous pourrez réécrire votre futur. Rejoignez-nous pour redéfinir les limites de ce qui est possible, contribuer à libérer la valeur de la technologie pour les plus grandes organisations et participez à la construction d’un monde plus durable et inclusif.\nVos missions :\nIntégré(e) au sein d'une équipe projets intervenant pour des clients dans des secteurs d'activités variées, vous serez notamment en charge des missions suivantes :\nInteragir avec nos clients, nos partenaires pour concevoir et mettre en œuvre des solutions/projets innovants et compétitifs\nRépondre aux problématiques de nos clients en proposant la meilleure plateforme data dans un environnement Agile\nAdapter chaque architecture en fonction du contexte grâce à votre maîtrise des caractéristiques fondamentales de chaque solution (catalogue des offres de services managés, performance, sécurité, déploiement des data centers …)\nUtiliser les solutions d’intégration associées et les solutions décisionnelles ainsi qu’analytiques qui viennent consommer les données manipulées\nEncadrer les équipes dans la mise en place des architectures préconisées et/ ou des plateformes Data\nVous avez acquis de l’expérience sur les cadres de référence et patterns d’architecture Data, DevOps.\nVotre profil :\nDiplôme d’ingénieur ou équivalent universitaire\nMinimum 6 ans d'expérience\nAnglais courant\nExpertise dans la conception d’architecture, la mise en œuvre et/ou le support d’applications hautement distribuées\nSensibilisation à la méthode devops et connaissance d’un outil de de Continuous Integration/Continuous Delivery (CI-CD)\nExpertise sur les services Cloud Data suivants (Azure, AWS, GCP)\nGrande aisance dans la communication orale et écrite, leadership afin de fédérer des équipes\n3 raisons de nous rejoindre :\nQualité de vie au travail : accord de télétravail en France et à l’international, accord sur l’égalité\nprofessionnelle, la parentalité, l’équilibre des temps et la mobilité durable.\nApprentissage en continu : certifications et formations en libre accès, accompagnement sur mesure avec votre carreer manager, parcours d’intégration sur 9 mois.\nAvantages groupe & CSE : plan actionnariat, activités à tarifs préférentiels, remboursement partiel\nvacances, remboursement de votre abonnement sportif ou culturel.\nNos engagements et priorités :\nLe groupe Capgemini encourage une culture inclusive dans un cadre multiculturel et handi-accueillant. En nous rejoignant, vous intégrez un collectif qui valorise la diversité, développe le potentiel de ses talents, s’engage dans des initiatives solidaires avec ses partenaires, et se mobilise pour réduire son impact environnemental sur tous ses sites et auprès de ses clients.\nCapgemini\nCapgemini est un leader mondial, responsable et multiculturel, regroupant près de 350 000 personnes dans plus de 50 pays. Fort de 55 ans d’expérience, nous sommes un partenaire stratégique des entreprises pour la transformation de leurs activités en tirant profit de toute la puissance de la technologie et des innovations dans les domaines en perpétuelle évolution tels que le cloud, la data, l’Intelligence Artificielle, la connectivité, les logiciels, l’ingénierie digitale ou les plateformes.\nGet The Future You Want* | www.capgemini.com/fr-fr\n*Capgemini, le futur que vous voulez\nShow more\nShow less",
        "details": {
            "JobDetail": [],
            "TypeContract": "",
            "Salary": "",
            "Level": "",
            "Experience": "6 an(s)"
        },
        "title": "data architect",
        "skills": {
            "CloudComputing": [
                "GCP",
                "AWS",
                "Azure"
            ],
            "Other": [
                "Cloud",
                "DevOps"
            ],
            "EnSoftSkils": [
                "Leadership",
                "Communication"
            ]
        }
    },
    {
        "source": "LinkedIn",
        "company": "EXAKIS NELITE",
        "location": "Grenoble, Auvergne-Rhône-Alpes, France",
        "link": "https://fr.linkedin.com/jobs/view/architecte-conseil-data-h-f-at-exakis-nelite-3813458944?position=33&pageNum=0&refId=a5rwPua%2FMvx%2F2M%2FPSF0oPA%3D%3D&trackingId=hL5G3DbYXckmlMW9KGBYrA%3D%3D&trk=public_jobs_jserp-result_search-card",
        "description": "Exakis Nelite, entité du groupe\nMagellan Partners\n, est le\n1er partenaire pure-player Microsoft\nindépendant en France avec l’ambition de devenir le premier partenaire Européen et en Afrique Francophone avec sa forte présence au Maroc.\nNés du rapprochement de 2 leaders spécialistes de l’intégration des solutions Microsoft, nous allions expertise technique et fonctionnelle pour répondre concrètement aux enjeux de demain : accélération de la transformation digitale,\nCyberSécurité, Intelligence Artificielle, IoT, Data, transformation vers le cloud Azure, Services Cognitifs …\nEn rejoignant la communauté Exakis Nelite dans l’une de nos 12 agences (680 collaborateurs), vous intégrerez une équipe passionnée et impliquée dans les projets les plus innovants. Vous rejoindrez une structure construite autour de valeurs tournées vers ses collaborateurs : intelligence collective, convivialité et bienveillance.\nExakis Nelite a reçu la certification\nGreat Place to Work\net se place\n3ème de sa catégorie\nen 2024 parmi les entreprises où il fait bon travailler en France !\nÀ quoi ressembleront vos futures missions ?\nEn tant qu’Architecte et Conseil, dans les domaines Data et Business Intelligence, vous serez amené à travailler sur des projets d’envergure mettant à l’épreuve votre expérience des systèmes de données et votre ouverture vers les technologies de BI moderne et cloud.\nVotre rôle d’architecte et de conseil auprès de nos clients trouvera son sens dans la compétence que pourrez apporter autour des solutions Microsoft (Power BI, Azure…), et aussi dans la connaissance globale que vous aurez acquise par vos expériences variées. Cette combinaison compétence/expérience aura pour but d’orchestrer l’implémentation des technologies Microsoft dans des systèmes d’information et décisionnels technologiquement hétérogènes.\nVotre passion, votre curiosité et votre envie sont les maîtres mots pour réussir dans ce poste. Vous êtes motivé pour travailler dans un environnement dynamique où la donnée se décline autour de nos projets innovants (IoT, Industrie 4.0, IA…). Vous avez une vision claire des enjeux actuels autour de la donnée.\nDescription du poste\nSelon les missions vous serez amené à :\nAccompagner nos clients dans leur stratégie digitale\nAnimer des ateliers d’architecture technique\nAppréhender les besoins fonctionnels et les contraintes techniques du client\nPréconiser des architectures complexes pour répondre à une problématique ou un besoin métier\nDéfinir et améliorer les standards, patterns d’architecture et le catalogue de services\nSuperviser et mettre en œuvre, dans le cadre des projets, les préconisations techniques établies dans le cadre des cahiers des charges\nRéaliser l’architecture de données dans des environnements on Premise\nIntervenir sur l’architecture Azure data\nRédiger les documents associés (HLD, LLD, etc.)\nPiloter des projets et des hommes\nIntervenir en toute autonomie sur les phases de cadrage technique et/ou avant ventes\nAssurer une veille technologique\nProfil\nFort d’une expérience de 3 à 15 ans dans les domaines, Data, BI et Big Data, vous portez de l’intérêt aux technologies du Cloud, aux approches de BI moderne et à leur développement. Vous êtes un professionnel aguerri des environnements Data, de l’architecture et de l’utilisation des technologies Cloud.\nLa connaissance des environnements Microsoft (Power BI, SQL Server, Azure…) est un plus mais n’est pas une obligation. La diversité de vos expériences dans le champ d’activité Data/BI est le facteur clef de succès de ce poste.\nCurieux et dynamique, vous avez le gout du challenge et souhaitez prendre part au développement important d’Exakis Nelite et de Magellan Partners dans le domaine des Data-sciences.\nShow more\nShow less",
        "details": {
            "JobDetail": [],
            "TypeContract": "",
            "Salary": "",
            "Level": "",
            "Experience": "15 an(s)"
        },
        "title": "data architect",
        "skills": {
            "DataBase": [
                "SQL"
            ],
            "DataVisualisation": [
                "Power BI"
            ],
            "CloudComputing": [
                "Azure"
            ],
            "DBMS": [
                "SQL Server"
            ],
            "Other": [
                "Cloud",
                "Big Data"
            ]
        }
    },
    {
        "source": "LinkedIn",
        "company": "SIBIOS",
        "location": "Lyon, Auvergne-Rhône-Alpes, France",
        "link": "https://fr.linkedin.com/jobs/view/data-architect-manager-at-sibios-3881612188?position=34&pageNum=0&refId=a5rwPua%2FMvx%2F2M%2FPSF0oPA%3D%3D&trackingId=BeZElBp3vNJZRE6yKafYDg%3D%3D&trk=public_jobs_jserp-result_search-card",
        "description": "SIBIOS recherche un consultant Senior DATA / ARCHITECT Manager avec minium 10 ans d'expérience pour un nouveau projet dans le secteur industriel.\nUne bonne connaissance d'architecture fonctionnelle et l'urbanisation data, ainsi que des règles de sécurité.\nVous avez une maîtrise de la gestion des données et des outils/langages correspondants (SQL, Power BI, modélisation et visualisation des données, ...)\nDiriger des projets Data sur divers domaines fonctionnels (Métier et IT) pour définir les feuilles de route.\nDéfinir la gouvernance de chaque projet et suivre le planning, le budget, la qualité et les risques sur chaque projet\nPiloter la gestion du changement et communiquer autour des projets\nIndustrialisation des innovations digitales : gouvernance, socle technique, documentation et support\nPour un entretien immédiat, merci de nous faire suivre votre cv mis á jour en word format ainsi que votre date de disponibilité et TJM.\nShow more\nShow less",
        "details": {
            "JobDetail": [
                "Senior"
            ],
            "TypeContract": "",
            "Salary": "",
            "Level": "",
            "Experience": "10 an(s)"
        },
        "title": "data architect",
        "skills": {
            "DataBase": [
                "SQL"
            ],
            "DataVisualisation": [
                "Power BI"
            ]
        }
    },
    {
        "source": "LinkedIn",
        "company": "Darwin Recruitment",
        "location": "Paris, Île-de-France, France",
        "link": "https://fr.linkedin.com/jobs/view/aws-full-stack-solution-architect-at-darwin-recruitment-3918853578?position=35&pageNum=0&refId=a5rwPua%2FMvx%2F2M%2FPSF0oPA%3D%3D&trackingId=VNRlrafCbgn7Z%2FzxGie1uQ%3D%3D&trk=public_jobs_jserp-result_search-card",
        "description": "Data Cloud Full Stack Solution Architect - 9 Months + extensions\nJob:\nData Cloud Full Stack Solution Architect\nClient Location:\nParis, France\nHybrid structure:\n3 days per week onsite with 2 days remote.\nContract Length:\n9 months + possibility for extensions\nRole and responsibilities:\nAs part of a significant Data Transformation initiative encompassing our entire spectrum of data capabilities-from Data Architecture and Engineering to Data Modelling, Storage for Data & Analytics, Data Visualization, Data Science, Data Integration, Metadata Management, and Data Storage and Warehousing-this role will support the future technical architecture activities of our Data Foundation platform. Key responsibilities include:\nProviding technical guidance and establishing best practices for Snowflake account setup and configuration.\nManaging Infrastructure-as-code to maximize automation and efficiency.\nOverseeing enhancements and deployments to bolster a fully federated Platform.\nServing as the Subject Matter Expert (SME) for all Snowflake-related queries on the project.\nMaintaining platform-specific Snowflake documentation, including decisions, best practices, and features.\nCommunicating and demonstrating new features to relevant stakeholders.\nDesigning the cloud environment comprehensively to ensure alignment with functional and non-functional requirements.\nConducting deployment, maintenance, monitoring, and management tasks.\nOverseeing cloud security for the account.\nFacilitating the integration of new applications into the cloud environment.\nRequirements:\nEducation: Completion of higher education with a degree in Computer Sciences or related field.\nExperience: 5 to 10 years of experience, including a proven track record in implementing Data Platforms in a cloud environment.\nSkills:\nFluency in both French and English (mandatory).\nDeep expertise in Snowflake.\nStrong understanding of platform architecture.\nExperience as a Database Administrator (DBA) and Cloud Database Administrator.\nProficiency in AWS Architecture and cloud networking.\nExcellent communication, coordination, collaboration, stakeholder management, and risk management skills, coupled with strong leadership abilities.\nOpen-mindedness and willingness to tackle challenges.\nHigh motivation, adaptability, and flexibility, with a readiness to integrate into existing environments and project teams.\nIf this role is of interest, please send an up to date CV to\ntaylor.lewis@darwinrecruitment.com\nDarwin Recruitment AG is a Zurich based, SECO licensed, privately owned subsidiary of Darwin Professional Staffing Group Ltd (a Global IT Recruitment Consultancy).\nDarwin Recruitment AG manages client relationships whilst also utilising Darwin Professional Staffing Group databases and networks to source Candidates and fulfil client requests.\nWe do not ask for a placement fee from Candidates/Employees.\nIf you wish to contact a specialist regarding this role, or your job search in general, please contact +41 (0)43 456 29 09\nShow more\nShow less",
        "details": {
            "JobDetail": [
                "Remote",
                "Full"
            ],
            "TypeContract": "",
            "Salary": "",
            "Level": "",
            "Experience": null
        },
        "title": "data architect",
        "skills": {
            "CloudComputing": [
                "AWS"
            ],
            "DBMS": [
                "Snowflake"
            ],
            "Collaboration": [
                "Teams"
            ],
            "Other": [
                "Cloud"
            ],
            "EnSoftSkils": [
                "Leadership",
                "Collaboration",
                "Flexibility",
                "Initiative",
                "Adaptability",
                "Communication"
            ]
        }
    },
    {
        "source": "LinkedIn",
        "company": "Sibylone",
        "location": "Paris, Île-de-France, France",
        "link": "https://fr.linkedin.com/jobs/view/architecte-data-at-sibylone-3888828561?position=36&pageNum=0&refId=a5rwPua%2FMvx%2F2M%2FPSF0oPA%3D%3D&trackingId=2yYnTKdQk5RoeQD6oXhgJw%3D%3D&trk=public_jobs_jserp-result_search-card",
        "description": "SIBYLONE, société de conseil spécialisée dans les systèmes d’information de synthèse et de pilotage, aide ses clients à tirer toute la valeur de leur patrimoine de données, levier stratégique majeur de développement et de rentabilité.\nNotre ambition : rendre les différents acteurs de l’entreprise autonomes dans l’exploitation des données, libérer les usages Métier, pour qu’ils soient en mesure de relever les défis de performance, de couverture de risque, de financement, de conquête client, de RSE… qui s’imposent à eux.\nSpécialistes reconnus, nos consultants s’appuient pour cela sur une connaissance approfondie de l’activité business de nos clients, en lien avec nos trois piliers que sont le Métier, la Data et le Projet.\nVos missions\nRéaliser\nles études de faisabilité technique et proposer une\nmigration vers le Cloud.\nAssister et conseiller\nles équipes dans les différentes étapes des projets\nPrendre en charge\nles instructions d’études techniques (réalisation des livrables correspondant, coordination des contributeurs techniques)\nConstruire\nl’architecture technique et de sécurité des applications concernés\nDéfinir et concevoir\nles architectures techniques des projets métiers\nGarantir\nl’exploitabilité, l’évolutivité et la performance des architectures proposées\nCollaborer et animer\nla communauté d’experts techniques pour définir les bonnes pratiques d’architecture et d’exploitabilité des solutions\nDocumenter et partager\nles modes opératoires suite aux migrations effectuées.\nRédiger et présenter\nles dossiers d’architecture devant les différents comités de validation\nRéaliser la veille technologique\nsur les outils et pratiques de développement\nAssurer\nla cohérence et l’industrialisation du SI\nOptimiser\nle design de l’architecture et le dimensionnement des infrastructures en fonction des évolutions des besoins\nVous évoluerez dans un environnement technique nécessitant une\nbonne maîtrise des architectures n-tiers, des problématiques liées au Cloud, des API (Management, REST) et webservices.\nPourquoi pas vous ?\nFormation supérieure Bac +5 en informatique\nExpérience réussie de migration de workflow on premise vers le Cloud.\nConnaissances techniques dans certains des domaines suivants : design de blueprint Cloud, architecture de bases de données, technologies Big Data Analytics, Machine Learning, virtualisation, architecture de stockage, sécurité.\nPremière bonne expérience réussie dans un ou des projets de transformation et de transitions vers le Cloud.\nExpérience > 6 ans en conception d’applications au sens large\nUne expérience dans un environnement agile est un plus\nLes + Sibylone !\nEvoluer au sein d’une société qui exige le meilleur de ses collaborateurs tout en cultivant la cohésion et l’esprit d’équipe !\nS’engager dans une politique RSE exigeante : labellisation Ecovadis\nAvoir un Partenariat EcoTree France : 1 recrutement = 1 arbre planté !\nUn Lab RSE ouvert à tous, pour améliorer la qualité de vie au travail des collaborateurs et nos engagements environnementaux au sein de SIBYLONE\nContribuer activement au bien-être de ses collaborateurs : participation aux frais d’abonnements activités ou achat 2 roues\nAvoir de nombreux moments de convivialités : séminaires, afterworks, conférences et petits déjeuners, sports en groupe via l’application Gymlib\nLes actions et missions solidaires : notre partenariat avec la start-up spécialisée en RSE Vendredi permet à nos collaborateurs de réaliser des missions auprès d’associations\nDonner une offre de formation innovante et à la pointe des nouvelles technologies\nAccord de télétravail en vigueur\nVous vous reconnaissez dans la description du poste ?\nVous souhaitez travailler dans un environnement stimulant et dynamique ?\nVous souhaitez rejoindre une société ambitieuse ?\nVous souhaitez comprendre l’origine de Sibylone ?\nVenez-nous rencontrer : Notre Team Talent Acquisition\nsera ravie d’échanger avec vous !\nCe poste est ouvert aux personnes en situation de handicap.\nShow more\nShow less",
        "details": {
            "JobDetail": [],
            "TypeContract": "",
            "Salary": "",
            "Level": "",
            "Experience": "6 an(s)"
        },
        "title": "data architect",
        "skills": {
            "Other": [
                "Machine Learning",
                "Cloud",
                "Big Data"
            ]
        }
    },
    {
        "source": "LinkedIn",
        "company": "Airbus",
        "location": "Toulouse, Occitanie, France",
        "link": "https://fr.linkedin.com/jobs/view/airbus-atlantic-architecte-data-all-gender-at-airbus-3916426276?position=37&pageNum=0&refId=a5rwPua%2FMvx%2F2M%2FPSF0oPA%3D%3D&trackingId=qkxCD4D6DkGDb8EneBG3mw%3D%3D&trk=public_jobs_jserp-result_search-card",
        "description": "Job Description\nEt si VOTRE aventure avec NOUS commençait ?!\nNous vous proposons de travailler chez Airbus Atlantic, nouveau champion de dimension mondiale, n°2 des aérostructures, n°1 des sièges pilotes et dans le Top 3 des fauteuils passagers Premium.\nNotre site Airbus Atlantic basé\nà Toulouse (possibilité de travailler à Montoir de Bretagne)\nrecherche son futur\nArchitecte Data (All Gender)\nLe poste d’architecte Data est rattaché au domaine « Architecture » au sein du département « Architecture Digital & Sécurité ».\nVous serez en interface avec les architectes du Système d'Information et les différents métiers consommateurs des architectures.\nVos Principales Missions Seront Les Suivantes\nFixer les orientations et définir des politiques concernant la modélisation des données, en collaboration avec les autres architectes,\nCréer des modèles de données logiques et physiques en utilisant les meilleures pratiques pour garantir une qualité élevée des données et une réduction de leur redondance,\nInstancier, implémenter, construire, tester et maintenir les architectures data définies\nAnalyser, évaluer, tester et recommander les briques technologiques nécessaires pour l’acquisition, l’analyse et l’implémentation des données,\nAnalyser les problèmes d'intégration des systèmes liés aux données et proposer des solutions appropriées,\nDéterminer les « Data set process » c’est à dire comment les données sont intégrées et transformées pour qu’elles soient prêtes à être analysées (ex : ETL)\nParticiper aux processus d'extraction performants et qualitatifs des données des sources requises afin de répondre aux besoins de l'entreprise\nMaintenir les modèles de données conceptuels, logiques et physiques ainsi que les métadonnées correspondantes (pour la data gouvernance).\nDévelopper les meilleures pratiques pour les conventions de dénomination standard et les pratiques de codage afin d'assurer la cohérence des modèles de données,\nRespecter les normes de sécurité des données, de contrôle des exportations et de protection des données.\nConstruire les pipelines qui permettront aux Data Scientist/Analysts/Developers de mettre leurs modèles en production\nEtre garant de la fiabilité, de la qualité et de l’efficacité du traitement des données\nMaintenir les modèles créés.\nParticiper aux idéations et proposer des innovations aux services.\nDocumenter ses activités et mettre à jour le référentiel documentaire.\nParlons de vous !\nVous disposez d'une\ne\nxp\nérience de minimum 5 ans en Data & Informatique sur un poste similaire.\nLes compétences techniques à détenir pour le poste :\nL’optimisation et les standards Qualité des données informatiques\nComprendre et savoir mettre en place les différentes Structure et stockage de données\nGestion des problèmes lié à la donnée, l'architecture\nIdéalement, l'expérience des technologies suivantes serait un plus : Ressources & services data MS Azure (Databricks, Azure ML …), SGBD (SQL, MongoDB, PostGreSQL, redis), Outils ETL (Qlik replicate, Alteryx, …), Outils BI (PowerBI, Qlik, Grafana ...),\nLangages de programmation (python, SCALA, R, DAX)\nLes certifications de Azure (DP-203, AZ-300, AZ-303, AZ-304, AZ-400, AI-900) seraient un plus,\nVotre Personnalité\nFort volonté de travailler en équipe\nBonnes habitudes de documentation\nNiveau avancé en Français et en Anglais (niveau minimum B1)\nFaire preuve d’innovation et être source de proposition\nSavoir exprimer ses idées de manière claire et concise\nEtre à l'écoute\nParlons de nous !\nEnvironnement & Conditions De Travail\nAirbus Atlantic c’est aussi :\nPrendre part à des projets ambitieux, à la pointe de la technologie pour construire l’avion de demain, en lien avec les enjeux environnementaux.\nUn environnement qui valorise la proximité et la dimension humaine, au sein d’un collectif engagé et solidaire.\nL’opportunité d’apprendre et d’évoluer tout au long de votre parcours, en étant accompagné dans votre développement pour une carrière sur-mesure.\nAvoir la liberté d’entreprendre et de laisser libre court à vos initiatives.\nSes conditions de travail attractives et ses avantages : restaurant d’entreprise sur site, CSE (avantages loisirs & famille), parking entreprise, mutuelle d’entreprise (famille).\nSa politique de diversité et d'inclusion : Airbus Atlantic s’engage en faveur de l’égalité des chances pour tous.\nSon plan d'actionnariat salarié et son plan d’épargne salariale.\nNotre Processus De Recrutement\nNous avons à cœur de mieux vous connaître et de comprendre ce qui vous motive à nous rejoindre. Aussi, notre process de recrutement se déroule en plusieurs étapes après analyse de votre candidature :\nEntretien vidéo différé via la plateforme Hirevue\nEntretien avec le Manager Recruteur\nEntretien avec le/la Chargé(e) de Recrutement qui peut être complété par un questionnaire de personnalité\nEntretien avec le/la Human Resources Business Partner.\nThis job requires an awareness of any potential compliance risks and a commitment to act with integrity, as the foundation for the Company’s success, reputation and sustainable growth.\nCompany\nAirbus Atlantic\nContract Type\nPermanent\nClasse Emploi (France): Classe G13\nExperience Level\nProfessional\nJob Family\nDigital\nBy submitting your CV or application you are consenting to Airbus using and storing information about you for monitoring purposes relating to your application or future employment. This information will only be used by Airbus.\nAirbus is committed to achieving workforce diversity and creating an inclusive working environment. We welcome all applications irrespective of social and cultural background, age, gender, disability, sexual orientation or religious belief.\nAirbus is, and always has been, committed to equal opportunities for all. As such, we will never ask for any type of monetary exchange in the frame of a recruitment process. Any impersonation of Airbus to do so should be reported to emsom@airbus.com.\nAt Airbus, we support you to work, connect and collaborate more easily and flexibly. Wherever possible, we foster flexible working arrangements to stimulate innovative thinking.\nShow more\nShow less",
        "details": {
            "JobDetail": [],
            "TypeContract": "",
            "Salary": "",
            "Level": "",
            "Experience": "5 an(s)"
        },
        "title": "data architect",
        "skills": {
            "ProgLanguage": [
                "R",
                "Scala",
                "Python"
            ],
            "DataBase": [
                "SQL",
                "MongoDB"
            ],
            "DataAnalytics": [
                "R"
            ],
            "BigData": [
                "Databricks"
            ],
            "CloudComputing": [
                "Azure"
            ],
            "DBMS": [
                "PostgreSQL"
            ],
            "Other": [
                "ML"
            ],
            "EnSoftSkils": [
                "Collaboration"
            ]
        }
    },
    {
        "source": "LinkedIn",
        "company": "E.Leclerc",
        "location": "Ivry-sur-Seine, Île-de-France, France",
        "link": "https://fr.linkedin.com/jobs/view/lead-data-architect-h-f-at-e-leclerc-3688059702?position=38&pageNum=0&refId=a5rwPua%2FMvx%2F2M%2FPSF0oPA%3D%3D&trackingId=m6aEKnUwuFaLecnTTcpZRA%3D%3D&trk=public_jobs_jserp-result_search-card",
        "description": "Description\nAu sein de la Direction Support et Organisation, la DSI est composée de 5 services :\nService Solutions Finance & Qualité,\nService Solutions Client,\nService Solutions Offre,\nService Support Utilisateurs,\nService TECH,\nLe Service TECH a Pour Mission\nD’animer les constructions stratégiques SI et technologies,\nD’explorer et d’innover en technologie,\nDe fournir et d’opérer des infrastructures sécurisées,\nD’apporter de l’expertise aux développeurs,\nD’opérer la sécurité,\nNous recherchons pour le Service Tech un(e) Lead Data Architect.\nLe Lead Data Architect est responsable de la conception et de la gestion de l'architecture des données sur la plateforme GCP. Son rôle consiste à définir l'architecture des données, à établir les normes, standards et les bonnes pratiques de développement des traitements de données. Il/elle collabore aussi étroitement avec les équipes de Data Architects et de Data Engineers de l’intégrateur ainsi qu’avec les architectes Cloud GCP afin de s’assurer que les solutions de traitement des données mises en place sur la plateforme soient robustes, scalables et sécurisées. Enfin, il/elle encadre fonctionnellement une équipe interne constituée d’un Data Architect et de deux Data Engineers.\nRattaché(e) au Responsable Développement, vos responsabilités sont les suivantes :\nConception de l'architecture des données : Définir l'architecture des données et des traitements de données en tenant compte des besoins fonctionnels et non fonctionnels, des exigences de performance, de scalabilité, de sécurité et de conformité. Concevoir des modèles et des pipelines de données en s’appuyant sur DBT ;\nSélection et configuration des services GCP : Évaluer et sélectionner les services et les outils de GCP tels que BigQuery, Cloud Storage, Composer, Pub/Sub, etc. les mieux adaptés aux besoins de chaque usage métier.\nGestion des données : Concevoir les solutions pour la gestion des données en streaming et en batch. Établir et maintenir les normes, les standards et les bonnes pratiques de développement en s’appuyant sur l’intégrateur. Contribuer à la mise en place et à la maintenance des pipelines de données pour la collecte, le traitement et l'analyse des données. Assister et supporter les Data Engineers dans cette tâche ;\nSécurité et gouvernance des données : Définir des mécanismes de sécurité et de gouvernance des données sur GCP pour garantir la confidentialité, l'intégrité et la conformité réglementaire (RGPD). Définir les contrôles d'accès, les politiques de sécurité des données et les mécanismes de traçabilité à mettre en œuvre ;\nIndustrialisation et déploiement : Mettre en place des pipelines CI/CD pour automatiser le déploiement, les tests, et la gestion des développements. Automatiser la création et la configuration des ressources sur GCP nécessaires en utilisant l’IaC/Terraform pour définir et gérer l'infrastructure de manière programmable et reproductible ;\nCollaboration avec les équipes : Travailler en étroite collaboration avec les équipes de l’intégrateur (Data Architects et Data Engineers), les squads big data pour proposer les solutions techniques adaptées aux besoins des métiers et assurer la mise en œuvre réussie des projets data sur GCP ;\nVeille technologique : Rester à jour sur les dernières avancées technologiques et les tendances du marché sur GCP et autres. Évaluer et recommander de nouvelles solutions ou des améliorations aux solutions existantes.\nProfil\nVous êtes issu(e) de formation supérieure en statistiques/marketing/informatique et vous justifiez d'une expérience significative en tant que data architect sur Google Cloud Platform (GCP). Vous avez de solides compétences en conception de pipelines de données et en modélisation de bases de données structurées et non structurées. Vous avez une connaissance approfondie des services GCP, tels que BigQuery, Cloud Storage, Cloud Composer, Pub/Sub, etc et des frameworks de développement tels que DBT.\nVous avez une expérience pratique en DevOps, CI/CD, avec une bonne compréhension des principes et des pratiques de génie logiciel (Azure DevOps, Jenkins, GitLab,..). Vous avez une connaissance de l'IaC (Infrastructure as Code) et utilisation d'outils tels que Terraform. Vous avez une compréhension des réglementations relatives à la protection des données et de la confidentialité, telles que le RGPD.\nVous avez une expérience en encadrement d’équipes techniques.\nDoté(e) d'une grande aisance relationnelle, vous avez le sens de l'écoute et de la diplomatie. Vous êtes rigoureux(se), vous avez un bon sens relationnel, une bonne capacité de communication et rédactionnelle.\nEnfin, vous avez une capacité à vous maintenir à jour sur les technologies data.\nNous recherchons des personnalités dynamiques, sachant prendre des initiatives et qui souhaitent s’impliquer dans les évolutions de notre secteur et du mouvement. Il est important que nos candidats démontrent un réel engagement, des valeurs communes aux valeurs fortes portées par le mouvement Leclerc depuis sa fondation.\nEn rejoignant le Galec, vous pourrez valoriser et démontrer votre potentiel, développer vos compétences et acquérir une expérience enrichissante, à travers des passerelles entre les différents marchés et entités du Mouvement !\nEnvie de challenge ? Vous souhaitez tenter l'aventure dans un univers dynamique, enrichissant, au plus près des entrepreneurs ?\nMieux nous connaitre\nLe Mouvement E.LECLERC est un groupement coopératif dont les adhérents sont les propriétaires de magasins, soit 592 entrepreneurs, dont Michel-Edouard Leclerc est le porte-parole. Le Mouvement E.leclerc compte 133 000 collaborateurs, qui travaillent collectivement à la réussite de nos 721 magasins (hypers, supers et express), 690 Drives et 2 541 enseignes spécialisées.\nLe Galec est l'entité au cœur du système, c'est même le réacteur ! Le Galec conjugue les talents d’une équipe de plus de 824 collaborateurs qui travaillent ensemble au service du front de vente omnicanal de l’Enseigne, c’est-à-dire les hyper/supermarchés, les magasins spécialisés, le drive, le site marchand E.Leclerc et E.Leclerc relais.\nShow more\nShow less",
        "details": {
            "JobDetail": [],
            "TypeContract": "",
            "Salary": "",
            "Level": "",
            "Experience": null
        },
        "title": "data architect",
        "skills": {
            "CloudComputing": [
                "GCP",
                "Google Cloud Platform",
                "Azure"
            ],
            "DevTools": [
                "Jenkins"
            ],
            "DBMS": [
                "BigQuery"
            ],
            "InfrastructureAsCode": [
                "Terraform"
            ],
            "Other": [
                "CI/CD",
                "Big Data",
                "Statistiques",
                "Cloud",
                "DevOps"
            ],
            "EnSoftSkils": [
                "Communication",
                "Collaboration"
            ]
        }
    },
    {
        "source": "LinkedIn",
        "company": "PROPULSE IT",
        "location": "Massy, Île-de-France, France",
        "link": "https://fr.linkedin.com/jobs/view/architecte-data-power-bi-azure-at-propulse-it-3902536487?position=39&pageNum=0&refId=a5rwPua%2FMvx%2F2M%2FPSF0oPA%3D%3D&trackingId=XOow3ZIRcrdBggn90nLaPw%3D%3D&trk=public_jobs_jserp-result_search-card",
        "description": "PROPULSE IT accompagne ses clients grands comptes et PME dans la mise en œuvre des projets It et digitaux.\nPROPULSE IT est un réseau de consultants à forte valeur ajoutée, complètement associé à notre démarche qualité de suivi des besoins et projets de nos clients.\nA ce jour, le réseau de freelance PROPULSE IT comporte plus de 18000 consultants sur toute la France, et couvre l'ensemble des besoins IT et digitaux.\nEn constituant ce réseau par cooptation de clients ou de consultants, nous avons privilégié la constance dans le savoir-faire technique et le savoir-être, pour devenir un véritable partenaire privilégié de nos clients.\nParallèlement, nous avons développé un réseau de partenaires sélectionnées pour leur expertise technique, et l'adhésion aux valeurs de notre entreprise.\nAujourd'hui PROPULSE IT est une société en pleine croissance organique, Champion de la Croissance du journal Les Echos 4 années consécutives.\nCe développement s'appuie sur la qualité et la pérennité des missions réalisées.\nLa satisfaction client est ainsi liée à l'épanouissement des consultants !\nAlors, n'hésitez pas à postuler !\nLe Poste\nNous recherchons un(e) DATA ARCHITECTE POWER BI / AZURE\nDans le respect de la stratégie IT établie par le DSI, votre mission consiste à :\nResponsabilités\nAnalyser les besoins fonctionnels.\nLocaliser les données de production.\nDéterminer les spécifications techniques.\nDéfinir l'architecture.\nModéliser les datawarehouse (entrepôts de données) et les datamarts (magasins de données) dédiés à une fonction particulière dans l'entreprise.\nAccompagner le client dans la réalisation du projet.\nMaintenir les sources de données à jour\nMettre à disposition les données aux métiers\nSuperviser les flux de données et en contrôler l'intégrité\nProfil\nStack Technique :\nPower BI / DAX / Langage M\nAzure Data Factory\nAzure Synapse\nData Lake, Logical Datawarehouse\nMicrosoft Fabric\nIntégration et la livraison continue (CI/CD)\nSavoir-faire\nRigueur\nShow more\nShow less",
        "details": {
            "JobDetail": [],
            "TypeContract": "",
            "Salary": "",
            "Level": "",
            "Experience": null
        },
        "title": "data architect",
        "skills": {
            "DataVisualisation": [
                "Power BI"
            ],
            "CloudComputing": [
                "Azure"
            ],
            "Other": [
                "CI/CD"
            ]
        }
    },
    {
        "source": "LinkedIn",
        "company": "Fieldbox",
        "location": "Bordeaux, Nouvelle-Aquitaine, France",
        "link": "https://fr.linkedin.com/jobs/view/cloud-solution-architect-paris-bordeaux-remote-at-fieldbox-3881559118?position=40&pageNum=0&refId=a5rwPua%2FMvx%2F2M%2FPSF0oPA%3D%3D&trackingId=BfoYE0VTuCfRtXGAWXoRVg%3D%3D&trk=public_jobs_jserp-result_search-card",
        "description": "Our business:\nWe help industrial companies to accelerate their digital transformation and dramatically improve their operational efficiency and competitiveness with data, software and AI. Our clients include CAC 40 companies, as well as small and medium-sized companies on five continents and over 150 industrial sites.\nWhat makes us special:\nWe offer a complete range of services, combined with the use of latest technologies, covering the entire lifecycle of data-driven solutions, from ideation, business value assessment, industrialized solution development, to deployment, run and scale.\nOur positioning:\nWe seek long term partnership-relation with our clients. We can help them define their digital strategy and AI roadmap, build & run a solution, train, and transfer skills, set up and professionalize R&D or innovation units or digital & AI factories.\nOur teams:\nA virtuous combination of three areas of expertise:\nBusiness expertise: industrial operations & engineering.\nTechnical expertise: data science, software engineering & devops.\nDelivery management expertise: managing digital projects and setting digital factories.\nYour missions:\nAs a Cloud Architect,you will design and participate in the implementation of cloud solutions to support the digital transformation of our clients. You will work in agile mode, in an international context, on industrial projects.\nYour main missions :\nSupport pre-sales technical activities by translating client’s requirements into state-of-the-art architectures, while guiding customers through their digital transformation journey in the cloud :\nLead workshops to study and define customer requirements\nImagine and define the architecture that would best meet the specifications provided while taking in account the financial and security constraints of the client.\nHandle and resolve technical questions and challenges encountered by clients during the first phases of their projects\nDefine deployment methodologies and integration of the solution into the existing client’s ecosystem.\nParticipate in pre-sales meeting with clients to present the envisioned architectures\nLead end-to-end architecture projects (web applications, data engineering & processing pipelines) involving intensive use of industrial data, with a focus on performance, scalability and security issues\nSupervise the deployment and industrialization of the target architectures\nEnsure the security and reliability of deployed environments\nWork in collaboration with multidisciplinary teams, including DevOps, back-end, front-end, data, product and business skills to make every project a success.\nExperience and skills required:\nAt least 2 years' experience in Architect or tech lead full stack role\nYou have experience with the following technologies:\nCloud: Azure, Google Cloud, AWS, OVH\nDatabases & storage : PostgreSQL, TimeScaleDB, Redis, InfluxDB, S3 and alike\nProcessing and scheduling: Azure Data Factory, Azure Functions, Azure Synapse, Airflow, Argo, AWS Batch, AWS Step\nStreaming: Kafka, RabbitMQ, Kinesis, SQS\nDevops: Docker, Kubernetes\nMoreover :\nYou have proven experience in cloud or hybrid architectures\nYou love architecture diagrams ! (Excalidraw, Draw.io)\nYou demonstrate technical leadership and are able to communicate complex ideas effectively.\nYou know how to challenge customer requirements and Fieldbox objectives in order to optimize the proposed architecture.\nYou successfully manage the complex constraints of a production application through analysis and resolution.\nYou are customer and solution-oriented and have excellent interpersonal skills.\nFluency in English\nKnowledge of an industrial sector is a plus\nKnowledge in python is a plus\nAdvantage and benefits:\nFull remote possible (Metropolitan France only)\nWhat about our offices\nBordeaux: meet with your colleagues in a peaceful and calm space with an amazing view on “Les bassins à flots”\nParis: enjoy a coworking space on the top of the Montparnasse tower with a 360 view of Paris\nWhat about our values :\nJoin a company which values care where everyone is in position to reach their full potential\nYou will work within an energetic team with a strong technical skill. Weekly engineering are organized every week to present and discuss technical topics\nCreate immediate impact on the company\nA quiz is sent every month in order to improve your comfort at work\nFun Activity:\nAfterwork every month with different theme ( bowling , board game , darts, beers bar, etc. )\nLunch break : outside lunchs, board game parties, and sport! (running, badminton, darts, yoga)\nCTFs\nTypical process includes 3 steps :\nHR interview\nInterview with operational team, aiming at testing your fit to the specific job,\nInterview with one or several founders to validate the application\nShow more\nShow less",
        "details": {
            "JobDetail": [
                "Remote",
                "Full"
            ],
            "TypeContract": "",
            "Salary": "",
            "Level": "",
            "Experience": null
        },
        "title": "data architect",
        "skills": {
            "ProgLanguage": [
                "R",
                "Python"
            ],
            "DataAnalytics": [
                "R"
            ],
            "CloudComputing": [
                "AWS",
                "Azure"
            ],
            "DevTools": [
                "Docker"
            ],
            "DBMS": [
                "PostgreSQL"
            ],
            "Automation": [
                "Airflow",
                "Kubernetes"
            ],
            "Containers": [
                "Docker",
                "Kubernetes"
            ],
            "Collaboration": [
                "Teams"
            ],
            "Other": [
                "Cloud",
                "DevOps"
            ],
            "EnSoftSkils": [
                "Leadership",
                "Interpersonal Skills",
                "Collaboration"
            ]
        }
    },
    {
        "source": "LinkedIn",
        "company": "Amadeus",
        "location": "Nice, Provence-Alpes-Côte d'Azur, France",
        "link": "https://fr.linkedin.com/jobs/view/data-architect-at-amadeus-3796958716?position=41&pageNum=0&refId=a5rwPua%2FMvx%2F2M%2FPSF0oPA%3D%3D&trackingId=ljKoPwTz1epZhroaEEkg%2Fw%3D%3D&trk=public_jobs_jserp-result_search-card",
        "description": "Job Title\nData Architect\nDigital Transformation Services (DTS) Is Committed To Drive Positive Change In Amadeus By Assembling, Leveraging, And Managing Digital And Transformation Services To Internal Customers Along Two Service Areas, Business Transformation Services And Enterprise Digital Services, Aiming To\nSpeed up and simplify business agility, value perception and compliance.\nGrow business value guided by the Amadeus Evolution Principles.\nDeliver end-to-end services and transformation programs to Amadeus.\nEngage, empower and develop a global team, proficient and engaged and nurturing our culture.\nDTS Solutions Architects and IBS Engineering Principal Specialists drive activities of developing a direction for managing a suit of solutions -including systems (applications and underlying IT stacks), processes and information, shared infrastructure services, and shared application services and components- in order to better match business requirements.\nAs such, DTS Solutions Architects act as leaders, with deep understanding of business goals, processes and enterprise architecture, to conceptualize and assemble technology solution architecture’s designs. These designs optimize the response to business needs (i.e.: cost, time to market, usability, continuity, etc.), while ensuring and improving architecture consistency.\nIn This Role You’ll / Your Main Responsibilities\nAs a Data Architect, you will play a crucial role in shaping and optimizing our organization's data infrastructure. You will be responsible for designing, implementing, and maintaining scalable and efficient data solutions that meet business needs. This role requires a deep understanding of data management, database technologies, and a strategic mindset to align data architecture with overall business strategies.\nKey Responsibilities\nData Modeling and Design:\nDevelop and maintain conceptual, logical, and physical data models.\nDesign data structures and relationships that support business requirements and enable efficient data retrieval.\nDatabase Management:\nSelect and implement appropriate database technologies based on project requirements.\nOptimize database performance and ensure data integrity.\nData Governance:\nEstablish and enforce data governance policies and procedures.\nDefine data standards, naming conventions, and data quality rules.\nData Integration:\nDesign and implement data integration solutions to ensure seamless flow of information across systems.\nCollaborate with other IT teams to integrate data sources and maintain data consistency.\nCollaboration and Communication:\nWork closely with business stakeholders to understand their data needs and translate them into effective data solutions.\nCollaborate with cross-functional teams including data scientists, analysts, and developers.\nSecurity and Compliance:\nImplement data security measures to protect sensitive information.\nEnsure compliance with data privacy regulations and industry standards.\nUse and leverage new technology solutions, to enable the organization's future-state business capabilities, facilitating and orchestrating the delivery of targeted business outcomes.\nProvide leadership, analysis and design tasks related to the development or upgrade of a solution to ensure application provides expected business value.\nProvide architecture guidance and support on activities performed to maintain, improve or support applications.\nAbout The Ideal Candidate\nBachelor's or Master's degree in Computer Science, Information Technology, or related field.\nProven experience as a Data Architect or in a similar role.\nStrong knowledge of database management systems, data warehousing, and data modeling techniques.\nProficiency in SQL and other query languages.\nFamiliarity with middleware, cloud-based data platforms and big data technologies.\nUnderstanding of agile methods and processes, and capability of supporting agile project teams.\nAnalytical and strategic thinking.\nExcellent communication and collaboration skills.\nProblem-solving and troubleshooting abilities.\nStay updated on emerging trends and technologies in data management.\nWhat we can offer you\nAn Extensive Range Of Benefits Including\nYou will be part of a multi-cultural team with international scope.\nYou will benefit from a permanent contract and a competitive employee benefits package such as pension plan, travel, life and healthcare insurance as well as lunch allowance.\nSkill development and career path.\nExperience in one of the world’s top IT companies.\nYou will be based in our Nice office (Hybrid Model, 3 days office 2 days work from home).\nApplication process\nThe application process takes no longer than 10 minutes! Create your candidate profile, upload your CV and apply. Once we’ve received your application, one of our recruiters may get in touch with you to arrange a telephone interview.\nAre you the one we’re looking for? Apply now!\nDiversity & Inclusion\nWe are an Equal Opportunity Employer and seek to hire the best candidate regardless of age, beliefs, disability, ethnicity, gender or sexual orientation.\nShow more\nShow less",
        "details": {
            "JobDetail": [],
            "TypeContract": "",
            "Salary": "3",
            "Level": "",
            "Experience": null
        },
        "title": "data architect",
        "skills": {
            "DataBase": [
                "SQL"
            ],
            "Collaboration": [
                "Teams"
            ],
            "Other": [
                "Cloud",
                "Big Data"
            ],
            "EnSoftSkils": [
                "Leadership",
                "Communication",
                "Organization",
                "Collaboration"
            ]
        }
    },
    {
        "source": "LinkedIn",
        "company": "Capgemini",
        "location": "Toulouse, Occitanie, France",
        "link": "https://fr.linkedin.com/jobs/view/architecte-big-data-cloud-toulouse-at-capgemini-3810332150?position=42&pageNum=0&refId=a5rwPua%2FMvx%2F2M%2FPSF0oPA%3D%3D&trackingId=d9gP0d9GUsgTzuxm6aSX1w%3D%3D&trk=public_jobs_jserp-result_search-card",
        "description": "Capgemini en quelques mots\nChoisir Capgemini, c'est choisir une entreprise où vous serez en mesure de façonner votre carrière selon vos aspirations, où vous serez soutenu et inspiré par une communauté d’experts dans le monde entier, où vous pourrez réécrire votre futur. Rejoignez-nous pour redéfinir les limites de ce qui est possible, contribuer à libérer la valeur de la technologie pour les plus grandes organisations et participez à la construction d’un monde plus durable et inclusif.\nVos missions\nVous intégrez une communauté d’experts passionnés reconnus par nos clients sur des technologies de pointe (Google Cloud Platform, Azure, AWS)\nVous interagissez au plus proche de nos clients, des partenaires pour concevoir et mettre en œuvre des solutions/projets innovants et compétitifs\nVous répondez aux problématiques de nos clients en proposant la meilleure plateforme data dans un environnement Agile\nVous avez acquis de l’expérience sur les cadres de référence et patterns d’architecture Data, DevOps\nVous adaptez chaque architecture en fonction du contexte grâce à votre maitrise des caractéristiques fondamentales de chaque solution (catalogue des offres de services managés, performance, sécurité, déploiement des data centers …)\nVous utilisez les solutions d’intégration associées et les solutions décisionnelles ainsi qu’analytiques qui viennent consommer les données manipulées\nVous êtes en mesure d’encadrer les équipes dans la mise en place des architectures préconisées et/ ou des plateformes Data\nVotre profil\nDe formation Bac + 5 en école d’ingénieur ou équivalent universitaire\nAu moins 6 ans d’expérience\nBon niveau d'anglais\nQualités de pédagogue, transmission de compétences\nLa phase d'avant-vente vous intéresse\n3 raisons de nous rejoindre\nQualité de vie au travail :\naccord de télétravail en France et à l’international, accord sur l’égalité\nprofessionnelle, la parentalité, l’équilibre des temps et la mobilité durable.\nApprentissage en continu :\ncertifications et formations en libre accès, accompagnement sur mesure avec\nvotre carreer manager, parcours d’intégration sur 9 mois.\nAvantages groupe & CSE :\nplan actionnariat, activités à tarifs préférentiels, remboursement partiel\nvacances, remboursement de votre abonnement sportif ou culturel\nNos engagements et priorités\nLe groupe Capgemini encourage une\nculture inclusive dans un cadre multiculturel et handi-accueillant.\nEn nous rejoignant, vous intégrez un collectif qui valorise la diversité, développe le potentiel de ses talents, s’engage dans des\ninitiatives solidaires avec ses partenaires, et se mobilise pour réduire son impact environnemental sur tous ses sites et auprès de ses clients.\nCapgemini\nest un\nleader mondial\n, responsable et multiculturel, regroupant près de 350 000 personnes dans plus de 50 pays. Fort de\n55 ans d’expérience\n, nous sommes un partenaire stratégique des entreprises pour la transformation de leurs activités en tirant profit de toute la puissance de la technologie et des innovations dans les domaines en perpétuelle évolution tels que\nle cloud, la data, l’Intelligence Artificielle, la connectivité, les logiciels, l’ingénierie digitale ou les plateformes.\nGet The Future You Want* | www.capgemini.com/fr-fr\n*Capgemini, le futur que vous voulez\nShow more\nShow less",
        "details": {
            "JobDetail": [],
            "TypeContract": "",
            "Salary": "",
            "Level": "",
            "Experience": "6 an(s)"
        },
        "title": "data architect",
        "skills": {
            "CloudComputing": [
                "AWS",
                "Google Cloud Platform",
                "Azure"
            ],
            "Other": [
                "Cloud",
                "DevOps"
            ]
        }
    },
    {
        "source": "LinkedIn",
        "company": "Cyborg Intelligence",
        "location": "Lyon, Auvergne-Rhône-Alpes, France",
        "link": "https://fr.linkedin.com/jobs/view/data-architect-agile-at-cyborg-intelligence-3913820683?position=43&pageNum=0&refId=a5rwPua%2FMvx%2F2M%2FPSF0oPA%3D%3D&trackingId=QfZxY%2F2KgP%2BSZeHlfhURMA%3D%3D&trk=public_jobs_jserp-result_search-card",
        "description": "Pour l'un de nos clients suisses de prestige - L'anglais et le français sont des impératifs incontournables pour ce poste en CDI\nResponsabilités\nL'architecte des données informatiques est responsable de la définition des politiques, des procédures, des modèles et\ntechnologies qui seront utilisées pour collecter, organiser, stocker et récupérer des informations pour\nl'organisation.\nIl/elle comprend comment les données déterminent le développement d'applications et\nexigences commerciales grâce à des principes de conception, des méthodologies et des\noutils.\nIl/elle fixe les règles et la structure de la stratégie data, en choisissant l'ETL\napproche et définition d’exigences supplémentaires\nDéfinition du modèle de données : définir l'architecture des données, les interfaces des contrats de données, les données\nqualité dans les systèmes, les meilleures pratiques,\nAperçu des flux de données : devenez propriétaire des flux de données actuels et futurs.\nAssumer la responsabilité de la qualité et de l'actualité des données,\nMaintenir et assurer l'évolution des flux de données, en utilisant les standards mondiaux de données\net des règles métier pour saisir les données dans les systèmes,\nAssurance qualité : effectuer des contrôles de qualité des données pour vérifier leur exactitude et\nl'exhaustivité selon des règles métier définies,\nSystème de données principal : maintenir des données précises et à jour pour les activités assignées\nprocessus,\nContribuer à l’amélioration continue des systèmes et des processus. Garantir les données\nalignement entre la documentation contractuelle et les données de base client,\nMaintenir à jour la documentation des processus et le matériel de formation,\nAssistance : assurez-vous que les problèmes sont identifiés, suivis, signalés et résolus de manière rapide.\nen temps opportun.\nDéveloppement & maintenance\nRôle d'expert pour le produit ou le domaine de produit désigné.\n1. Traite les demandes des utilisateurs, les tickets de service, les incidents, les modifications\n2. Assumer les activités de support de 3ème niveau\n3. Rédige et maintient la documentation\n4. Participe à la création des guides d'utilisation\nS'assure que le savoir-faire du domaine est transféré aux membres de l'équipe.\n5. Assure le respect de la sécurité des données à tout moment.\n6. Évalue les performances des applications et des bases de données et les améliore lorsque cela est possible\n7. Réaliser ou superviser les activités de développement et d'intégration de systèmes.\nGestion de projet\n1. Diriger des projets liés aux données en tant que représentant informatique\n2. Définit la portée du projet, planifie et suit les développements du projet et\ndéploiements d'applications.\n3. Superviser les ressources externes pendant la phase du projet.\nQualifications\nApproche axée sur le client\n• Expérience de travail dans Azure DF, Synapse, AWS ou autre\n• Expérience de travail avec les méthodologies Agile\n• Forte résolution de problèmes, capacité à travailler sous pression et capacité à établir des priorités.\n• Autogestion et capacité à travailler de manière indépendante avec une supervision limitée\n• Bonnes compétences en communication et en relations interpersonnelles, capacité à travailler efficacement avec\néquipes à distance\n• Très bonne communication orale et écrite\n• Anglais courant\nShow more\nShow less",
        "details": {
            "JobDetail": [],
            "TypeContract": "CDI",
            "Salary": "",
            "Level": "",
            "Experience": null
        },
        "title": "data architect",
        "skills": {
            "CloudComputing": [
                "AWS",
                "Azure"
            ],
            "EnSoftSkils": [
                "Communication"
            ]
        }
    },
    {
        "source": "LinkedIn",
        "company": "ENGIE",
        "location": "Courbevoie, Île-de-France, France",
        "link": "https://fr.linkedin.com/jobs/view/get-data-architect-m-f-at-engie-3596026403?position=44&pageNum=0&refId=a5rwPua%2FMvx%2F2M%2FPSF0oPA%3D%3D&trackingId=5EGkaG7PyxLRHfA4k%2BzyOw%3D%3D&trk=public_jobs_jserp-result_search-card",
        "description": "Come join one of the most ambitious Transformation Program of Engie\nENGIE's strategy to drive the energy transition and to industrialize the company, making it simpler,\nfaster, and more integrated, is set.\nGET, Global Enterprise Transformation\n, is the Program decided by ENGIE to accelerate and standardize the ERP system as well as the effectiveness of processes, embarking the Company on a centrally steered and business-led transformation focused on making ENGIE an integrated industrial company.\nTherefore, GET Program is among the top 5 ENGIE priorities with genuine ExCom sponsorship.\nBe part of the Change and come build the Future at one of the most ambitious Transformation Program of the moment.\nWith a view to harmonization, ENGIE has embarked on a major program to transform its processes and IT tools. This project, which extends over several years, concerns all the entities of the group and requires a sustained support.\nTo implement this support, we are looking to recruit a :\nGET –\nData Architect (M/F)\nThe head office is based in Courbevoie (La Défense), but the physical presence on the head office is not mandatory. We are also looking for international profiles.\nThe GET program aims to deliver the future business and IT core model with a central “one ERP / One ARIBA” platform. The functional context of the program covers a set of functional areas including accounting, controlling and procurement as main areas.\nThe GET program offers a unique opportunity to onboard on one of the most ambitious and strategic Enterprise transformation programs with a very high IT footprint with S/4 & SAP ARIBA as central IT components. Innovation is at the heart of GET Program with an ambition to implement a best in class processes & solution.\nThe\nGET Data Architect\nrole is proposed to reinforce the internal team supporting the core model delivery and coordinating the pilots/rollouts.\nThis role will be N-2 to GET IT Lead and directly reporting to the core model IT lead.\nJob Responsibilities:\nBring high level expertise on MDM and especially SAP MDG\nHelp the business teams in business requirement definition and ensure coherence with the SAP capabilities\nResponsible for reviewing the integrator delivery and challenge the proposed solutions\nAlign with the business team to ensure the proposed solution is aligned with the core model and the program guidelines\nWork with the integrator teams and SAP teams to secure design authority presentations for arbitrations\nSecure testing phases and ensure quality of test delivery by the IT integrator\nDrive discussions in multi-cultural / global context with multiple stakeholders\nPosition Requirements\nVery good knowledge of the SAP MDG and overall the MDM area.\nUnderstanding the process of translating business requirements and processes into data collection and usage principles in MDG.\nAt least 5 years experience in similar position\nGood references in the previous experiences with other customers\nFluent English (oral/written)\nMay require national & international mobility.\n\"Priority position reserved for ENGIE SA Corporate employees whose position is removed and for DTR employees\".\nShow more\nShow less",
        "details": {
            "JobDetail": [],
            "TypeContract": "",
            "Salary": "",
            "Level": "",
            "Experience": null
        },
        "title": "data architect",
        "skills": {
            "Collaboration": [
                "Teams"
            ]
        }
    },
    {
        "source": "LinkedIn",
        "company": "SOFTEAM",
        "location": "Île-de-France, France",
        "link": "https://fr.linkedin.com/jobs/view/data-architect-solution-azure-f-h-at-softeam-3839977121?position=45&pageNum=0&refId=a5rwPua%2FMvx%2F2M%2FPSF0oPA%3D%3D&trackingId=nJC8wyzoJbZwI7vYjHDuaw%3D%3D&trk=public_jobs_jserp-result_search-card",
        "description": "Vous évoluez dans le domaine de la\nData\net souhaitez intégrer un leader de la transformation numérique spécialisé dans les secteurs de la\nBanque, du Luxe, de l'Assurance, de la Finance, de l'Energie\net la possibilité d'évoluer au sein du\nGroupe Docaposte\n!\nSofteam\nest labellisé \"\nHappyIndex® AtWork\n\" 2022 pour la\n5ème\nannée consécutive !\nNos collaborateurs travaillent en « mode projet » autour des\nModern DATA Platform\n☁ et\ntechnologies Big Data AWS Cloud / On premise\net autre \"playeur\" du marché. Nous accompagnons de bout en bout nos clients sur des problématiques de\nGouvernance, d’Intégration, de Visualisation et d’IA.\nCE QUE NOUS RECHERCHONS\nData Architect Solution Azure\nF/H, disposant de l’expérience dans la mise en place des\nModern Data Platform\ndans\nAzure\n.\nCE QUE NOUS ATTENDONS DE VOUS\nEn tant que\nData Architect Solution Azure\nF/H, vous intervenez sur nos projets et contribuer au développement de notre activité.\nVOS MISSIONS DETAILLEES\nAccompagner et conseiller le client dans son adoption des Modern Data Platform dans Azure (Etude d’architecture, préparation des DAT, FinOps, DevOps)\nConcevoir des architectures Cloud Data exploitant efficacement les services de données managés d'Azure\nConduire des projets de déploiement des Modern Data Platform (Applications Cloud Native, Migration d’applications existantes) et participer à la mise en œuvre\nEtablir des relations de confiance avec les décisionnaires techniques et métiers afin de favoriser l’adoption du Cloud Azure à long terme au sein de l’entreprise.\nFournir une expertise technique approfondie aux équipes projets\nAssister et former le client sur les usages et outils Data du Cloud Azure\nRéaliser une veille technologique permanente sur les tendances du marché et les perspectives concurrentielles\nVOUS ETES\nIngénieur(e) de formation, vous disposez d'une expertise reconnue et d'une expérience de 5 ans dans un rôle d’𝐀𝐫𝐜𝐡𝐢𝐭𝐞𝐜𝐭𝐞 𝐒𝐨𝐥𝐮𝐭𝐢𝐨𝐧 𝐂𝐥𝐨𝐮𝐝 𝐃𝐚𝐭𝐚 ou 𝐓𝐞𝐜𝐡 𝐋𝐞𝐚𝐝 𝐃𝐚𝐭𝐚, avec une expérience significative sur Azure.\nVous avez des compétences approfondies dans un ou plusieurs de ces domaines : Opérations / Gestion des systèmes, Conception ou développement de logiciels, Processus DevOps et outillage, Stratégie d'entreprise, Infrastructure Cloud (virtualisation, mise en réseau, stockage, base de données), Sécurité et conformité.\nVous êtes sensibilisé à la démarche DevOps et connaissez au moins un outil pour la mise en œuvre de Continuous Integration/Continuous Delivery (CI-CD)\nLa possession de certifications sur des services Azure est un plus.\nNOUS VOUS OFFRONS\nDes missions engageantes auprès des grands acteurs du marché.\nUn management de proximité avec Gilles SALVADOR, Directeur du Centre d'Expertise Data, toujours bienveillant et à l'écoute et avec qui vous pourrez échanger au quotidien sur les enjeux de votre mission et évoquer vos futurs projets afin que nous puissions vous aider à les réaliser.\nLa possibilité d’évoluer et de monter en compétences grâce à des formations et à des certifications auprès de nos clients et de nos consultants, des 12@13, notre Entité Softeam Institute, Organisme de formation interne de renommé qui délivre des formations auprès de nos clients...\nQUI SOMMES-NOUS ?\nSOFTEAM DATA est une marque de DOCAPOSTE spécialisée dans l'informatique décisionnelle et les nouvelles technologies. Nous apportons notre expertise à nos clients, principalement des Grands Comptes de la place financière française, dans des projets de transformation digitale et cognitive.\n2000 Softeamien.nes sont dédié.es à la transformation métier et digitale de nos clients et ont généré 200 M€ de chiffre d’affaires en 2020.\nSOFTEAM SPIRIT\nDes communautés d'expertises sur les sujets de la Data ;\nDe super nouveaux locaux qui sont en plus accessibles facilement ;\nUne école de formation intégrée ;\nDes évènements : des soirées avec les consultants, des 12@13... ;\nUne entreprise labellisée \"Happy at Work\" pour la 5ème année consécutive.\nN’attendez plus, rejoignez SOFTEAM et venez nous rencontrer dans nos nouveaux locaux situés à la Défense #DevenezSofteamien !\nShow more\nShow less",
        "details": {
            "JobDetail": [],
            "TypeContract": "",
            "Salary": "",
            "Level": "",
            "Experience": "5 an(s)"
        },
        "title": "data architect",
        "skills": {
            "CloudComputing": [
                "AWS",
                "Azure"
            ],
            "Other": [
                "Cloud",
                "Big Data",
                "DevOps"
            ]
        }
    },
    {
        "source": "LinkedIn",
        "company": "HP",
        "location": "Hauts de Bienne, France",
        "link": "https://fr.linkedin.com/jobs/view/principal-data-architect-at-hp-3902461217?position=46&pageNum=0&refId=a5rwPua%2FMvx%2F2M%2FPSF0oPA%3D%3D&trackingId=oNBWg9krxvuDIl9%2BoJg16A%3D%3D&trk=public_jobs_jserp-result_search-card",
        "description": "HP is a Fortune 100 technology company with $58+ Billion in revenue, with over 50,000 employees operating in more than 170 countries around the world. We provide technology and services that help people and companies address their problems and challenges, and realize their possibilities, aspirations, and dreams. We apply new thinking and ideas to create simpler, more valuable, and trusted experiences with technology, continuously improving the way our customers live and work.\nIn the GTM advanced analytics COE, our mission is to deliver impact by building machine learning (ML) products to optimize pricing, marketing investments and provide guidance to sales and other HP teams.\nWe're looking for a principal data architect to join our data engineering team.\nQualifications\nTypically 5+ years of experience in software or data engineering.\nExtensive experience in data modeling, data integration and processing of structured and unstructured data.\nHighly proficient in one or more programming languages (Python preferred).\nStrong SQL proficiency (experience with NoSQL – advantage).\nHighly experienced with Apache Spark / pyspark\nExcellent communication skills; mastery in English and local language.\nAbility to effectively communicate product architectures, design and change proposals.\nFamiliar with best practices of the data and software engineering lifecycle and/or best practices of the above platforms and tools.\nAdditional Preferred Qualifications / Advantages\nDatabricks\nPandas\nDataiku DSS\nShow more\nShow less",
        "details": {
            "JobDetail": [],
            "TypeContract": "",
            "Salary": "",
            "Level": "",
            "Experience": null
        },
        "title": "data architect",
        "skills": {
            "ProgLanguage": [
                "Python"
            ],
            "DataBase": [
                "SQL",
                "NoSQL"
            ],
            "DataAnalytics": [
                "Pandas"
            ],
            "BigData": [
                "Databricks",
                "Spark"
            ],
            "Collaboration": [
                "Teams"
            ],
            "Other": [
                "Machine Learning",
                "ML"
            ],
            "EnSoftSkils": [
                "Communication"
            ]
        }
    },
    {
        "source": "LinkedIn",
        "company": "EXAKIS NELITE",
        "location": "Aix-en-Provence, Provence-Alpes-Côte d'Azur, France",
        "link": "https://fr.linkedin.com/jobs/view/architecte-cloud-azure-data-h-f-at-exakis-nelite-3904805434?position=47&pageNum=0&refId=a5rwPua%2FMvx%2F2M%2FPSF0oPA%3D%3D&trackingId=%2Fb%2F4oxKpQrWu%2F5dO2fGNpg%3D%3D&trk=public_jobs_jserp-result_search-card",
        "description": "Exakis Nelite, entité du groupe Magellan Partners, est le premier partenaire pure-player Microsoft indépendant en France avec l’ambition de devenir le premier partenaire Européen et en Afrique Francophone avec sa forte présence au Maroc.\nNés du rapprochement de 2 leaders spécialistes de l’intégration des solutions Microsoft, nous allions expertise technique et fonctionnelle pour répondre concrètement aux enjeux de demain : accélération de la transformation digitale, CyberSécurité, Intelligence Artificielle, IoT, Data, transformation vers le cloud Azure, Services Cognitifs et Intelligence Artificielle…\nEn rejoignant la communauté Exakis Nelite dans l’une de nos 15 agences, vous intégrerez une équipe passionnée et impliquée dans les projets les plus innovants. Vous rejoindrez une structure construite autour de valeurs tournées vers ses collaborateurs : intelligence collective, convivialité et bienveillance.\nA la pointe des nouvelles technologies, vous intégrerez la communauté Modern Apps pour accompagner les grands comptes d'Aix-en-Provence dans leur stratégie digitale et l’adoption du cloud qui en découle.\nPoste et missions:\nEn tant qu’Architecte Cloud Azure H/F, votre autonomie et votre force de proposition prendront toute leur ampleur en prenant en charge des missions d’expertise ou des projets de plusieurs centaines de jours.\nVous travaillerez dans une ambiance conviviale, constructive, sereine, laissant une grande place à l’initiative et au développement personnel.\nSelon les missions vous serez amené(e) à :\nAccompagner nos clients dans leur stratégie digitale\nAnimer des ateliers d’architecture technique\nAppréhender les besoins fonctionnels et les contraintes techniques du client\nPréconiser des architectures complexes pour répondre à une problématique ou un besoin métier\nDéfinir et améliorer les standards, patterns d’architecture et le catalogue de services\nSuperviser et mettre en œuvre, dans le cadre des projets, les préconisations techniques établies dans le cadre des cahiers des charges\nRédiger les documents associés (HLD, LLD, etc.)\nPiloter des projets et des hommes\nIntervenir en toute autonomie sur les phases de cadrage technique et/ou avant ventes\nAssurer une veille technologique\nCompétences techniques attendues :\nBonne connaissance de la plateforme Azure dans son ensemble et de l’écosystème associé.\nPlutôt DATA ?\nConnaissances requises :\nServices DATA dans Azure (DataFactory, Azure Synapse, Spark, Hadoop, etc.)\nBases de données (SQL, MYSQL,\nDes problématiques de stockage et traitement de la donnée dans Azure (Storage Account, Datalake store, Data Factory, Logic App)\n« Securité » de la donnée dans Azure\nLa connaissance de la gestion des données liées à l’IOT dans Azure est un plus\nProfil :\nDe formation BAC+5, vous justifiez d'une expérience significative dans l'infrastructure informatique en cloud et notamment sur la plateforme Azure.\nBon(ne) communicant(e), vous êtes capable de vous adapter à la fois au travail en équipe et aux projets de nos clients.\nUne certaine aisance orale est indispensable. Un rédactionnel de qualité est obligatoire. Une bonne maitrise de l’anglais est obligatoire.\nExpérience: minimum 5 ans\nAvantages :\nMutuelle prise en charge à 100%, télétravail, remboursement du titre de transport à 100%, primes de congés d'été, participation/intéressement, avantages CSE.\nVous vous reconnaissez dans cette annonce? N'hésitez pas à postuler! Nous avons hâte de vous rencontrer!\nShow more\nShow less",
        "details": {
            "JobDetail": [],
            "TypeContract": "",
            "Salary": "",
            "Level": "Bac+5",
            "Experience": "5 an(s)"
        },
        "title": "data architect",
        "skills": {
            "DataBase": [
                "SQL"
            ],
            "BigData": [
                "Hadoop",
                "Spark"
            ],
            "CloudComputing": [
                "Azure"
            ],
            "DBMS": [
                "MySQL"
            ],
            "Other": [
                "Cloud"
            ],
            "EnSoftSkils": [
                "Initiative"
            ]
        }
    },
    {
        "source": "LinkedIn",
        "company": "Groupement des Mousquetaires",
        "location": "Vitré, Brittany, France",
        "link": "https://fr.linkedin.com/jobs/view/architecte-data-h-f-at-groupement-des-mousquetaires-3889132514?position=48&pageNum=0&refId=a5rwPua%2FMvx%2F2M%2FPSF0oPA%3D%3D&trackingId=cmkYqYRJ7JbipE08px2xQQ%3D%3D&trk=public_jobs_jserp-result_search-card",
        "description": "Description De L'entreprise\nLe Groupement Les Mousquetaires, ce sont 7 enseignes de la grande distribution portées haut et fort par plus de 3 000 chefs d’entreprise indépendants ! Ce sont aussi 150 000 collaborateurs mobilisés autour de notre modèle « Producteurs et commerçants ».\nDans toutes les fonctions au service des points de vente, de la logistique à l’immobilier, en passant par l’industrie agroalimentaire ou l’informatique, nos équipes font nos succès.\nAgromousquetaires est le pôle industriel du Groupement Les Mousquetaires. Premier fabricant de marques de distributeurs en France.\nAgromousquetaires c'est avant tout 11 000 hommes et femmes aux sensibilités diverses, regroupés au sein de 70 sites industriels et logistiques, dont une cinquantaine d'usines, et 6 Pôles de Performance.\nNous rejoindre, c'est partager une culture commune, celle de l'entrepreneuriat et de l'engagement c’est être « Producteurs et Commerçants » !\nAlors, prêt à vous lancer au service du « Mieux Produire pour Mieux Vivre » ?\nAgroM Services héberge à l'AgroHub (35), à Lanester (56) et au Parc de Tréville (91), l'ensemble des métiers transverses ayant vocation à accompagner et répondre aux besoins opérationnels de nos 6 pôles.\nVous souhaitez participer au développement d'un acteur majeur de la Grande Distribution en Europe sur un poste qui offre une forte exposition pour l'avenir du Groupe ? Alors cette opportunité pourrait vous intéresser. Seul distributeur à être à la fois « Producteurs et Commerçants » avec des gammes de produits de qualité, dans des secteurs variés et 100% made in France.\nDescription Du Poste\nNous recherchons\nun(e) Architecte Data (H/F)\nPoste à pourvoir en CDI sur notre site basé à Vitré (35)\nRattaché(e) au Responsable Département Data & Analytics, vous serez en charge de concevoir, développer et maintenir notre architecture de données, en veillant à garantir l’intégrité, la disponibilité et la confidentialité des données.\nVos missions seront les suivantes :\nDéfinir notre stratégie d’architecture des données sur l’alimentation, la transformation, la modélisation, jusqu’à l’exposition des données pour les usages tiers (BI notamment)\nÊtre garant de la modélisation de notre patrimoine de données au sein de la plateforme data Cloud\nAdministrer notre plateforme de données sous GCP\nDéfinir et mettre en œuvre une stratégie FinOps\nDévelopper ou faire développer à l’équipe Flux Inter-Applicatifs les jobs ETL d’alimentation et de transformation de données sous Talend\nDéfinir les missions et piloter les Prestataires informatiques intervenant sur notre plateforme de données\nCommuniquer notre stratégie data au sein de l’entreprise\nDocumenter ou s’assurer que la documentation a été réalisée\nCollaborer sur les différents projets applicatifs nécessitant de stocker de la donnée\nContribuer au plan de transformation sur la gouvernance de la donnée, comprenant le traitement de la qualité des données\nPrendre en compte les contraintes cybersécurité et de conformité réglementaire (RGPD) dans la conception des architectures\nS’assurer que toute solution mise en œuvre respecte la stratégie du département Data & Analytics, et plus généralement de la DSI\nRespecter les méthodologies projet en vigueur et établies par le département SI Gouvernance\nAssurer une veille technologique autour des sujets traitant de la donnée et être force de proposition sur la transformation de nos usages data\nQualifications\nVous avez :\nUne formation supérieure de niveau Bac +5 en informatique ou sciences des données, de type Master ou Diplôme d'Ingénieur.\nVous disposez d'une expérience similaire de minimum 3 ans.\nVous devrez :\nAvoir de solides connaissances sur la plateforme Google Cloud Platform (Big Query, GCS notamment)\nMaîtriser des outils et technologies liés à la gestion des données, tels que les bases de données, les entrepôts de données, les outils ETL (Talend de préférence), …\nUtiliser des méthodes de modélisations (UML, BPMN ou équivalent).\nSavoir travailler en équipe, et collaboration avec les parties prenantes,\nRédiger de manière claire et concise,\nAvoir une bonne communication orale et écrite\nVotre rigueur, votre adaptabilité, votre sens de l’écoute, votre relationnel et votre proactivité (et oui rien que ça 😊), vous permettront de mener à bien ces missions !\nInformations supplémentaires\nVous vous reconnaissez sur ce poste ?\nAlors postulez et discutons de votre avenir !\nVous devrez réaliser votre travail dans une ambiance agréable, accompagnés de collègues sympathiques et ça en seulement 3 jours de présence obligatoire sur site (2 jours de télétravail possible après 2 mois d’ancienneté dans le groupe).\nAGROMOUSQUETAIRES s'engage à promouvoir la diversité, notamment en favorisant l'emploi de Travailleurs en situation de Handicap.\nAGROMOUSQUETAIRESRECRUTE\nShow more\nShow less",
        "details": {
            "JobDetail": [],
            "TypeContract": "CDI",
            "Salary": "",
            "Level": "",
            "Experience": "3 an(s)"
        },
        "title": "data architect",
        "skills": {
            "CloudComputing": [
                "GCP",
                "Google Cloud Platform"
            ],
            "DBMS": [
                "Big Query"
            ],
            "Other": [
                "Cloud"
            ],
            "EnSoftSkils": [
                "Communication",
                "Collaboration"
            ]
        }
    },
    {
        "source": "LinkedIn",
        "company": "Capgemini",
        "location": "Aix-en-Provence, Provence-Alpes-Côte d'Azur, France",
        "link": "https://fr.linkedin.com/jobs/view/architecte-data-aix-en-provence-at-capgemini-3822433643?position=49&pageNum=0&refId=a5rwPua%2FMvx%2F2M%2FPSF0oPA%3D%3D&trackingId=ljqGAvYAe8YRObUU%2FcFj8A%3D%3D&trk=public_jobs_jserp-result_search-card",
        "description": "Choisir Capgemini, c'est choisir une entreprise où vous serez en mesure de façonner votre carrière selon vos aspirations. Avec le soutien et l'inspiration d’une communauté d’experts dans le monde entier, où vous pourrez réécrire votre futur. Rejoignez-nous pour redéfinir les limites de ce qui est possible, contribuer à libérer la valeur de la technologie pour les plus grandes organisations et participer à la construction d’un monde plus durable et inclusif.\nVOS MISSIONS\n• Préconiser une architecture et des technologies\n• Elaborer des standards technologies internes\n• Garantir la cohérence technique de la solution et son évolution\n• Prototyper les solutions techniques préconisées\n• Assister l'équipe de développement dans la mise en œuvre des solutions techniques préconisées • Développer des composants techniques\n• Encadrer les équipes de consultants grâce à la formation et le coaching\nDans votre quotidien, vous contribuerez au partage et à la capitalisation des savoirs et des pratiques au sein de la Communauté des Architectes de Capgemini.\nVous participerez à la construction de points de vue par l'expérience et le savoir-faire reconnu dans un domaine technique\nL’ENVIRONNEMENT TECHNIQUE\nDataHub :\n• ETL (Talend, Informatica ou SSIS),\n• Traitement de données Spark, Python, Scala…\n• Bases de données (Oracle, SQL Server, Postgres),\n• Datalake / Big Data : Horton Works, Cloudera, ELK,…\nData Viz & IA / Machine Learning :\n• Qlik, Tableau\n• Python, R…\nVOTRE PROFIL\n• De formation supérieure, vous justifiez d'une expérience reconnue (6 à 10 ans) sur des projets de cadrage ou de mise en œuvre d’applications / d’architectures visant à collecter, stocker, raffiner et valoriser les données ;\n• Vous êtes habitué à travailler dans des contextes Agile et DevOps.Vous avez côtoyé une/des démarches de transformation SI (SOA, CLOUD, BigData, CLIENT/SERVEUR, EIM, …) et une/des méthodologies d'architecture des SI (TOGAF, IAF)\n• Vous maîtrisez l'anglais à l'oral et à l'écrit\n3 RAISONS DE NOUS REJOINDRE :\nQualité de vie au travail\n: accord de télétravail en France et à l’international, accord sur l’égalité professionnelle, la parentalité, l’équilibre des temps et la mobilité durable.\nApprentissage en continu\n: certifications et formations en libre accès, accompagnement sur mesure avec votre career manager, parcours d’intégration sur 9 mois.\nAvantages groupe & CSE\n: plan actionnariat, tarif préférentiels, remboursement partiel vacances, remboursement de votre abonnement sportif ou culturel.\nNOS ENGAGEMENTS ET PRIORITES :\nLe groupe Capgemini encourage une culture inclusive dans un cadre multiculturel et handi-accueillant. En nous rejoignant, vous intégrez un collectif qui valorise la diversité, développe le potentiel de ses talents, s’engage dans des initiatives solidaires avec ses partenaires, et se mobilise pour réduire son impact environnemental sur tous ses sites et auprès de ses clients.\nA PROPOS DE CAPGEMINI :\nCapgemini est un leader mondial, responsable et multiculturel, regroupant près de 350 000 personnes dans plus de 50 pays. Fort de 55 ans d’expérience, nous sommes un partenaire stratégique des entreprises pour la transformation de leurs activités en tirant profit de toute la puissance de la technologie et des innovations dans les domaines en perpétuelle évolution tels que le cloud, la data, l’Intelligence Artificielle, la connectivité, les logiciels, l’ingénierie digitale ou les plateformes.\nGet The Future You Want* | www.capgemini.com/fr-fr\n*Capgemini, le futur que vous voulez\nShow more\nShow less",
        "details": {
            "JobDetail": [],
            "TypeContract": "",
            "Salary": "",
            "Level": "",
            "Experience": "10 an(s)"
        },
        "title": "data architect",
        "skills": {
            "ProgLanguage": [
                "R",
                "Scala",
                "Python"
            ],
            "DataBase": [
                "SQL"
            ],
            "DataAnalytics": [
                "R"
            ],
            "BigData": [
                "Spark"
            ],
            "DataVisualisation": [
                "Tableau"
            ],
            "DBMS": [
                "SQL Server"
            ],
            "Other": [
                "Machine Learning",
                "Cloud",
                "Big Data",
                "DevOps"
            ]
        }
    },
    {
        "source": "LinkedIn",
        "company": "HP",
        "location": "Grenoble, Auvergne-Rhône-Alpes, France",
        "link": "https://fr.linkedin.com/jobs/view/data-architect-m-f-at-hp-3903406324?position=50&pageNum=0&refId=a5rwPua%2FMvx%2F2M%2FPSF0oPA%3D%3D&trackingId=40S%2FgOr47a%2BHSzAk7zUjAw%3D%3D&trk=public_jobs_jserp-result_search-card",
        "description": "Who we are?\nHP creates new possibilities for technology to have a meaningful impact on people, businesses, governments and society. The world’s largest technology company and ranked 10 on the Fortune 500 list for 2012, HP brings together a portfolio that spans printing, personal computing, software, services and IT infrastructure to serve more than 1 billion customers in over 170 countries on six continents.\nHP invents, engineers, and delivers technology solutions that drive business value, create social value, and improve the lives of our clients. At HP, we know that our people and values are the most important elements in this success. And we want you to add your voice and imagination to our mission.\nDiversity drives our innovation engine\nDiverse teams create transformative solutions that better serve our customers and advance how the world works and lives.\nWe’re reinventing the standard for diversity and inclusion — in how we operate as a company and impact society. Diversity is embedded in all we do, and every HP employee at every level plays a part. By valuing differences, we engage top industry talent to drive our company’s long-term success.\nWhat can we do together?\nIn the GTM advanced analytics COE, our mission is to deliver impact by building machine learning (ML) products to optimize pricing, marketing investments and provide guidance to sales and other HP teams.\nWe are looking for a Data Architect / Senior Data Engineer to join our data engineering team. If you are passionate about solving problems and making improvements through data and technology, we are eager to talk to you. The ideal candidate has both a willingness and desire to work in a dynamic environment, is able to apply Agile methodologies in day-to-day activities, and is a self-motivated developer who also enjoys working in a team environment. Our people have a creative, innovative, fun, and collaborative attitude, and are dedicated to creating new and valuable solutions for HP.\nThe data engineering architect applies developed subject matter knowledge to solve common and complex business issues within established guidelines and recommends appropriate alternatives.\nWorks on problems of diverse complexity and scope.\nMay act as a team or project leader providing direction to team activities and facilitates information validation and team decision making process.\nExercises independent judgment within generally defined policies and practices to identify and select a solution.\nAbility to handle most unique situations.\nMay seek advice in order to make decisions on complex business issues.\nWho you are?\n3+ years of experience in software or data engineering architecture.\nProficient in data modeling, data integration and processing of structured and unstructured data.\nProficient in one or more programming languages (Python preferred).\nStrong SQL proficiency (experience with NoSQL – advantage).\nExperienced with Apache Spark / pyspark\nExcellent communication skills; mastery in English and local language.\nAbility to effectively communicate product architectures, design and change proposals.\nAdditional Preferred Qualifications Advantages\nDatabricks\nPandas\nFamiliar with best practices of the data and software engineering lifecycle and/or best practices of the above platforms and tools.\nDataiku DSS\nWhy joining HP France?\nAt HP France, you will be immersed in an inspiring workplace where all our people love to be, collaborate well together and where they can learn, grow and develop professionally as well as personally. We offer empowering responsibilities. You will have the opportunity to evolve through your commitment, your skills and your sense of initiative! This position can be the 1st step in a great career within our teams!\nJoining us also means a great work-life balance and benefits such as meal vouchers, discounts on HP products and more! Driven by a strong corporate culture, our employees are involved in numerous initiatives through internal networks (Next Gen, Women@hp, workplace well-being team, ect.) and external volunteering (Nos Quartiers ont du Talent, Hour of Code).\nHP is also committed to an equal opportunities policy, from recruitment to career development. Job offers are open to all, including people with disabilities.\nOur promise: To create a diverse and inclusive working environment! So, what are you waiting for?\nThis role is based in Grenoble (38) within our international skills and expertise center. We offer a collaborative, stimulating and ultra-connected working environment in the heart of the mountains and just a 10 minute walk from the train station.\nShow more\nShow less",
        "details": {
            "JobDetail": [
                "Senior"
            ],
            "TypeContract": "",
            "Salary": "",
            "Level": "",
            "Experience": null
        },
        "title": "data architect",
        "skills": {
            "ProgLanguage": [
                "Python"
            ],
            "DataBase": [
                "SQL",
                "NoSQL"
            ],
            "DataAnalytics": [
                "Pandas"
            ],
            "BigData": [
                "Databricks",
                "Spark"
            ],
            "Collaboration": [
                "Teams"
            ],
            "Other": [
                "Machine Learning",
                "ML"
            ],
            "EnSoftSkils": [
                "Initiative",
                "Communication"
            ]
        }
    },
    {
        "source": "LinkedIn",
        "company": "Mars",
        "location": "Aimargues, Occitanie, France",
        "link": "https://fr.linkedin.com/jobs/view/frontend-architect-f-m-x-at-mars-3914282604?position=51&pageNum=0&refId=a5rwPua%2FMvx%2F2M%2FPSF0oPA%3D%3D&trackingId=4YR1fYkda7creVM7OiFI5Q%3D%3D&trk=public_jobs_jserp-result_search-card",
        "description": "Job Description\nLocalisation:\nAimargues (30 minutes from Montpellier)\nType of contract:\npermanent contract\nTo achieve its ambition to be the reference in pet health through nutrition, Royal Canin wants to continue to push the barriers of nutrition and individualization.\nThe digital transformation is driving both new opportunities to serve more pets but also new challenges for our existing business models. Join the Royal Canin Digital Factory to participate to this transformation. You will join a multi-cultural, dynamic and caring team working all together and closely on all the digital projects of the brand. Royal Canin's Digital Factory is key in achieving this strategy through the multiplicity of its practices: UX/UI, Development, Product Ownership, Market deployment, Architecture, Governance...\nWhile the team will develop new digitally enabled business models that will shape the future of Royal Canin and Eukanuba, they also support the transformation of our existing business models.\nIn This Digital Acceleration Context, Royal Canin Needs To Reinforce Its Internal Strengths With Digital, User Centric And Data Capabilities. Based In Aimargues, This Job Will Sit In Our Digital Factory, Which Mission Are To\nDevelop our Service-driven and digital platforms supporting “Pet Health Guardians”\nDevelop our key capabilities on Design Thinking, UX, Agile Management, Mobile/Web/Ecommerce development, Digital Platform deployment and Data-driven transformation.\nLeverage those capabilities to design and build our future Business Models\nHelp in acquiring data and driving traffic to our owned assets, which will help transform data collected into digital performance metrics and business insights.\nPush from global to deploy@ scale and pull from local to global synergy\nThe Digital factory, as part of the Direct to Pet Owner organization, works in strong partnership with Marketing and sales team and Innovation team.\nReporting to the Develop Factory Lead, we are hiring a\nFrontend Architect\n, who will define and drive the frontend technology strategy across the Digital Factory to support the organization ambitions.\nWhat are we looking for ?\n7 to 15 years' experience in Frontend Development for digital environment\nManagement of complex technical projects on an international level & in Agile methodology (Scrum, Kanban, SAFe)\nAbility to work with different teams and various team dynamics to achieve challenging delivery objectives\nLead of technical teams with external and internal actors\nFast Learner, Influencing and negotiations skills\nFluent in English\nWhat will be your key responsibilities ?\nThe role of\nFrontend Architect\nfor Supervision Angular/React Developers entails leading, guiding, and supervising multiple development teams working on projects utilizing Node.js, Angular, and/or React technologies. The\nFrontend Architect\nplays a crucial role in designing and implementing robust and scalable technical solutions, ensuring the quality, performance, and consistency of the developed applications.\nLeadership\nAs\nFrontend Architect\n, you will have to:\nHe/she can establish the software architecture of his/her project or steer it in a different direction, in alignment with the technical direction of the project.\nHe/she oversees the quality of what is produced by his/her team.\nHe/she communicates on technical matters, leveraging his/her expertise and contributing to the visibility of his/her team's expertise.\nThe Architect is the technical lead of the project. He/she ensures internal coordination between his teams and other teams involved in the project.\nHe/she ensures the flow of information and validates, if necessary, the various technical actions to be taken.\nHe/she can propose the right design based on functional and business challenges, and he advocates for his choices in front of the stakeholders.\nTechnical Leadership: Lead and mentor multiple development teams in designing, implementing, and maintaining software solutions based on Angular, and/or React.\nSystem Architecture: Design and define the technical architecture of applications, ensuring scalability, security, and performance.\nCollaboration: Collaborate closely with development teams, Delivery Leads, and PO to understand business requirements and define appropriate technical solutions.\nStandards and Best Practices: Establish and enforce coding standards, best practices, and development conventions within the teams.\nRisk Management: Identify and mitigate technical risks throughout the development lifecycle.\nMeetings\nSynchronization with frontend lead devs of all product squads\nTechnical retrospective: Once per sprint, exchange with the entire DEV team on technical improvements => Deliverables are technical tickets to be included in sprints (optional guest), leads must document decisions with CRs\nBack and Front Design Authority (weekly)\nSynchronization with front and back teams (sharing new topics, roadmaps, ..)\nSynchronization with DevOps\nWhat can you expect from Mars?\nAt Mars, we believe in a relationship of mutual trust, dignity and respect between our company and Associates that is more meaningful than the standard employer/employee relationship.\nAs Associates, we can expect to be respected, supported and valued as individuals, to be treated fairly and equitably.\nAn environment where you are empowered to be proactive and to take initiatives to make a difference.\nYou will work in a multicultural environment (more than 40 nationalities) and where your dog will be welcomed by more than 100 other Associates’ dogs at the office!\nA unique and ideal work environment to become the leader in health through nutrition for cats and dogs!\nMars is an equal opportunity employer and all qualified applicants will receive consideration for employment without regard to race, color, religion, sex, sexual orientation, gender identity, national origin, disability status, protected veteran status, or any other characteristic protected by law. If you need assistance or an accommodation during the application process because of a disability, it is available upon request. The company is pleased to provide such assistance, and no applicant will be penalized as a result of such a request.\nShow more\nShow less",
        "details": {
            "JobDetail": [],
            "TypeContract": "",
            "Salary": "",
            "Level": "",
            "Experience": null
        },
        "title": "data architect",
        "skills": {
            "Collaboration": [
                "Teams"
            ],
            "Other": [
                "DevOps"
            ],
            "EnSoftSkils": [
                "Leadership",
                "Organization",
                "Collaboration"
            ]
        }
    },
    {
        "source": "LinkedIn",
        "company": "University of Strasbourg",
        "location": "Strasbourg, Grand Est, France",
        "link": "https://fr.linkedin.com/jobs/view/architecte-data-f-h-syst%C3%A8me-r%C3%A9seaux-donn%C3%A9es-h-f-at-university-of-strasbourg-3912809071?position=52&pageNum=0&refId=a5rwPua%2FMvx%2F2M%2FPSF0oPA%3D%3D&trackingId=RVJPCVX4Zg3%2B7sxclxk9CQ%3D%3D&trk=public_jobs_jserp-result_search-card",
        "description": "Cette offre d’emploi est fournie par Pôle emploi\nDescription\nDescriptif du poste: Emploi ouvert aux agents contractuels uniquement CDD de projet de 3 ans à compter du 10/06/2024 Catégorie : A Corps : Ingénieur d'études Rémunération selon grille de la Fonction Publique La fiche de poste détaillée est disponible sur le site de l'Université. Mission : L'architecte data aura pour principale mission d'optimiser les process de collecte de données issues des systèmes d'information des partenaires du Pôle Universitaire d'Innovation Alsace (PUI-A) et les bases de données disponibles en « open data », en vue d'assurer le déploiement de la démarche de pilotage stratégique et opérationnel par la donnée mise en œuvre dans le cadre du projet PUI-A. Activités principales : * Cartographier les données disponibles au sein des systèmes d'informations des membres fondateurs du PUI-A et des bases de données utiles aux activités du PUI-A notamment accessibles en « open data » * Définir et mettre en place les normes, méthodes, procédures, outils et référentiels de collecte et de gestion de données * Concevoir une approche de regroupement et d'organisation des données collectées. Activités associées : * Contribuer aux travaux d'exploitation des données * Contribuer à l'élaboration des outils de pilotage stratégique et opérationnel par la donnée du PUI-A. Contact pour renseignements sur le poste : David-Alexandre BONNE, Responsable du Pôle Universitaire d'Innovation Alsace Profil recherché: Profil recherché : Formation Bac+5 à Bac+8 dans un des domaines en lien avec le poste (statistique, économétrie, mathématiques, informatique, traitement de l'information). Connaissances : * Architecture et environnement technique d'un système d'information * Outils de gestion (ex. SQL, ETL) et d'exploitation (ex. R, Python) de bases de données * Techniques statistiques et informatiques de collecte et de traitement de données * Méthodes, outils, normes et procédures de la qualité * Méthodologie de conduite de projet * Organisation et fonctionnement de l'enseignement supérieur et de la recherche, ainsi que des écosystèmes de recherche et d'innovation (en Alsace ou dans d'autres territoires) * Langue anglaise : B2 à C1 (cadre européen commun de référence pour les langues). Compétences opérationnelles : * Piloter un projet * Construire et gérer une base de données * Rédiger la documentation fonctionnelle et technique pour les utilisateurs * Gérer la sécurité de l'information * Mettre au point ou adapter des techniques nouvelles, notamment d'automatisation * Apporter des réponses à des besoins spécifiques * Accompagner et conseiller * Communiquer et faire preuve de pédagogie * Travailler en équipe. Compétences comportementales : * Capacité de conceptualisation * Créativité : sens de l'innovation * Sens de l'initiative * Rigueur * Curiosité intellectuelle et ouverture d'esprit * Persévérance * Capacité d'adaptation * Sens de l'organisation * Sens relationnel * Capacité d'écoute.\nPROFIL SOUHAITÉ\nExpérience\nDébutant accepté\nSource: Pole emploi (https://www.pole-emploi.fr)\nShow more\nShow less",
        "details": {
            "JobDetail": [],
            "TypeContract": "CDD",
            "Salary": "",
            "Level": "Bac+5",
            "Experience": "3 an(s)"
        },
        "title": "data architect",
        "skills": {
            "ProgLanguage": [
                "R",
                "Python"
            ],
            "DataBase": [
                "SQL"
            ],
            "DataAnalytics": [
                "R"
            ],
            "Other": [
                "Statistiques"
            ],
            "EnSoftSkils": [
                "Initiative"
            ]
        }
    },
    {
        "source": "LinkedIn",
        "company": "FRG Technology Consulting",
        "location": "Paris, Île-de-France, France",
        "link": "https://fr.linkedin.com/jobs/view/data-architect-talend-bi-at-frg-technology-consulting-3908855754?position=53&pageNum=0&refId=a5rwPua%2FMvx%2F2M%2FPSF0oPA%3D%3D&trackingId=mF7ZBqw31ah5zMA856l4cg%3D%3D&trk=public_jobs_jserp-result_search-card",
        "description": "FRG Consulting est à la recherche d'un Data Architect BI / Talend avec une solide maîtrise de Java pour rejoindre une équipe basée dans le sud de Paris. Dans ce rôle, vous serez responsable de l'évaluation de l'architecture des données et des bases de données actuelles, ainsi que de la collecte, de l'organisation et de l'agrégation des données internes et externes pour les rendre accessibles.\nResponsabilités :\nÉvaluer l'architecture des données et les bases de données actuelles, y compris DataWarehouse, Datamart et les bases de données tampons.\nCollecter, organiser et agréger les données internes et externes en utilisant les meilleures pratiques ETL pour l'alimentation du DataWarehouse.\nDéfinir et maintenir la cartographie des données (applications, flux de données) et assurer la cohérence des données.\nOptimiser l'utilisation, par les métiers, des services et solutions mis à disposition par la DSI, en identifiant les opportunités de proposer de nouveaux produits ou services et en participant à leur définition.\nParticiper à la mise en place des projets en collectant les besoins exprimés par les métiers, en traduisant ces besoins en spécifications techniques, modèles de données et user stories (avec une maîtrise des concepts Agile), et en accompagnant les projets dans la définition des besoins, la description et l'usage des données en collaboration avec les équipes DSI.\nS'assurer que les projets déployés par la DSI s'inscrivent dans la roadmap data et assurer un rôle de conseil auprès des équipes DSI et métiers.\nRéaliser un suivi quotidien des performances et de l'efficacité des bases de données.\nQualifications :\nExpérience significative dans un poste similaire, avec une solide expertise en Java et Talend.\nConnaissance approfondie des bases de données, des architectures de données et des meilleures pratiques ETL.\nCompétences avancées en analyse et modélisation de données.\nExcellentes compétences en communication et en collaboration, avec la capacité de travailler efficacement avec des équipes interfonctionnelles.\nMaîtrise des concepts Agile et capacité à travailler dans un environnement Agile.\nCapacité démontrée à résoudre des problèmes complexes et à prendre des décisions éclairées.\nAutonomie, proactivité et capacité à travailler de manière autonome tout en faisant partie d'une équipe.\nShow more\nShow less",
        "details": {
            "JobDetail": [],
            "TypeContract": "",
            "Salary": "",
            "Level": "",
            "Experience": null
        },
        "title": "data architect",
        "skills": {
            "ProgLanguage": [
                "Java"
            ],
            "EnSoftSkils": [
                "Communication",
                "Collaboration"
            ]
        }
    },
    {
        "source": "LinkedIn",
        "company": "Schneider Electric",
        "location": "Lattes, Occitanie, France",
        "link": "https://fr.linkedin.com/jobs/view/architecte-data-model-f-h-at-schneider-electric-3864653832?position=54&pageNum=0&refId=a5rwPua%2FMvx%2F2M%2FPSF0oPA%3D%3D&trackingId=FuZ7MUBxPrGA%2B6wwUn0FZQ%3D%3D&trk=public_jobs_jserp-result_search-card",
        "description": "Missions\nEn tant qu’ Architecte Data-Model, vous jouerez un rôle crucial dans le façonnement et l'optimisation de l'infrastructure de données de notre produit. Vous serez responsable de la conception, de la mise en œuvre et de la maintenance de solutions de données évolutives et efficaces répondant aux besoins de l'entreprise. Ce rôle nécessite une compréhension approfondie de la gestion des données et une vision stratégique pour aligner l'architecture des données avec les stratégies commerciales globales :\nModélisation et Conception de Données :\nVeiller à la conformité de normes telles que l'IEC61850\nDévelopper et maintenir des modèles de données conceptuels, logiques et physiques\nConcevoir des structures de données et des relations qui soutiennent les exigences commerciales et permettent une récupération efficace des données\nGouvernance des Données :\nÉtablir et appliquer des politiques et procédures de gouvernance des données\nDéfinir les normes de données, les conventions de dénomination et les règles de qualité des données\nIntégration des Données :\nConcevoir et mettre en œuvre des solutions d'intégration de données pour assurer un flux d'informations transparent à travers les systèmes\nCollaborer avec d'autres équipes informatiques pour intégrer les sources de données\nCollaboration et Communication :\nTravailler en étroite collaboration avec les parties prenantes métier pour comprendre leurs besoins et les traduire en solutions de données efficaces\nCollaborer avec des équipes pluridisciplinaires, y compris des Analystes et des Développeurs\nSécurité et Conformité :\nMettre en œuvre des mesures de sécurité des données pour protéger les informations sensibles\nFournir un leadership, des analyses et des tâches de conception afin de garantir une application en phase avec la valeur commerciale attendue. Fournir des conseils en architecture et un soutien sur les activités réalisées pour maintenir et améliorer les applications.\nProfil\nBac+5 minimum de type Ecole d’Ingénieur ou équivalent en informatique, technologie de l'information ou domaine connexe\nAu moins 5 ans d'expérience en tant qu'Architecte de Données ou dans un rôle similaire\nConnaissance de l'IEC61850\nSolide connaissance des systèmes de gestion de bases de données et des techniques de modélisation de données\nCompréhension des méthodes et processus agiles, et capacité à soutenir des équipes de projet agiles\nCapacité d’analyse et de synthèse, bon sens de la communication et de la collaboration\nCapacités de résolution de problèmes et de dépannage\nRester en veille concernant les tendances émergentes et technologies en gestion des données\nPourquoi nous?\nSchneider Electric est la référence en matière de transformation numérique de la gestion de l'énergie et de l'automatisation. Nos technologies permettent au monde d'utiliser l'énergie de manière sûre, efficace et durable. Nous nous efforçons de promouvoir une économie mondiale à la fois viable sur le plan écologique et hautement productive.\n34 milliards d'euros de chiffre d'affaires global\n128 000+ employés dans plus de 100 pays\n45 % du chiffre d'affaires de l'IoT\n5 % du chiffre d'affaires consacré à la R&D\nVous devez soumettre une demande en ligne pour que votre profil soit pris en considération pour un poste chez nous. Ce poste sera visible jusqu'à ce qu'il soit pourvu.\nSchneider Electric a pour politique de fournir des possibilités d'emploi et d'avancement égales dans les domaines du recrutement, de l'embauche, de la formation, du transfert et de la promotion de toutes les personnes qualifiées, quelle que soit leur race, religion, couleur, sexe, handicap, origine nationale, ascendance, âge, statut militaire, orientation sexuelle, état matrimonial ou toute autre caractéristique ou conduite légalement protégée. Agences concernées : Schneider Electric n’accepte pas de curriculum vitæ soumis de façon spontanée et ne sera pas responsable des frais occasionnés par de tels envois.\nShow more\nShow less",
        "details": {
            "JobDetail": [],
            "TypeContract": "",
            "Salary": "",
            "Level": "Bac+5",
            "Experience": "5 an(s)"
        },
        "title": "data architect",
        "skills": {
            "ProgLanguage": [
                "R"
            ],
            "DataAnalytics": [
                "R"
            ],
            "EnSoftSkils": [
                "Leadership",
                "Communication",
                "Collaboration"
            ]
        }
    },
    {
        "source": "LinkedIn",
        "company": "Mars",
        "location": "Haguenau, Grand Est, France",
        "link": "https://fr.linkedin.com/jobs/view/frontend-architect-f-m-x-at-mars-3914284362?position=55&pageNum=0&refId=a5rwPua%2FMvx%2F2M%2FPSF0oPA%3D%3D&trackingId=GlRyZYi%2FaDs%2F1w84FA7kOw%3D%3D&trk=public_jobs_jserp-result_search-card",
        "description": "Job Description\nLocalisation:\nAimargues (30 minutes from Montpellier)\nType of contract:\npermanent contract\nTo achieve its ambition to be the reference in pet health through nutrition, Royal Canin wants to continue to push the barriers of nutrition and individualization.\nThe digital transformation is driving both new opportunities to serve more pets but also new challenges for our existing business models. Join the Royal Canin Digital Factory to participate to this transformation. You will join a multi-cultural, dynamic and caring team working all together and closely on all the digital projects of the brand. Royal Canin's Digital Factory is key in achieving this strategy through the multiplicity of its practices: UX/UI, Development, Product Ownership, Market deployment, Architecture, Governance...\nWhile the team will develop new digitally enabled business models that will shape the future of Royal Canin and Eukanuba, they also support the transformation of our existing business models.\nIn This Digital Acceleration Context, Royal Canin Needs To Reinforce Its Internal Strengths With Digital, User Centric And Data Capabilities. Based In Aimargues, This Job Will Sit In Our Digital Factory, Which Mission Are To\nDevelop our Service-driven and digital platforms supporting “Pet Health Guardians”\nDevelop our key capabilities on Design Thinking, UX, Agile Management, Mobile/Web/Ecommerce development, Digital Platform deployment and Data-driven transformation.\nLeverage those capabilities to design and build our future Business Models\nHelp in acquiring data and driving traffic to our owned assets, which will help transform data collected into digital performance metrics and business insights.\nPush from global to deploy@ scale and pull from local to global synergy\nThe Digital factory, as part of the Direct to Pet Owner organization, works in strong partnership with Marketing and sales team and Innovation team.\nReporting to the Develop Factory Lead, we are hiring a\nFrontend Architect\n, who will define and drive the frontend technology strategy across the Digital Factory to support the organization ambitions.\nWhat are we looking for ?\n7 to 15 years' experience in Frontend Development for digital environment\nManagement of complex technical projects on an international level & in Agile methodology (Scrum, Kanban, SAFe)\nAbility to work with different teams and various team dynamics to achieve challenging delivery objectives\nLead of technical teams with external and internal actors\nFast Learner, Influencing and negotiations skills\nFluent in English\nWhat will be your key responsibilities ?\nThe role of\nFrontend Architect\nfor Supervision Angular/React Developers entails leading, guiding, and supervising multiple development teams working on projects utilizing Node.js, Angular, and/or React technologies. The\nFrontend Architect\nplays a crucial role in designing and implementing robust and scalable technical solutions, ensuring the quality, performance, and consistency of the developed applications.\nLeadership\nAs\nFrontend Architect\n, you will have to:\nHe/she can establish the software architecture of his/her project or steer it in a different direction, in alignment with the technical direction of the project.\nHe/she oversees the quality of what is produced by his/her team.\nHe/she communicates on technical matters, leveraging his/her expertise and contributing to the visibility of his/her team's expertise.\nThe Architect is the technical lead of the project. He/she ensures internal coordination between his teams and other teams involved in the project.\nHe/she ensures the flow of information and validates, if necessary, the various technical actions to be taken.\nHe/she can propose the right design based on functional and business challenges, and he advocates for his choices in front of the stakeholders.\nTechnical Leadership: Lead and mentor multiple development teams in designing, implementing, and maintaining software solutions based on Angular, and/or React.\nSystem Architecture: Design and define the technical architecture of applications, ensuring scalability, security, and performance.\nCollaboration: Collaborate closely with development teams, Delivery Leads, and PO to understand business requirements and define appropriate technical solutions.\nStandards and Best Practices: Establish and enforce coding standards, best practices, and development conventions within the teams.\nRisk Management: Identify and mitigate technical risks throughout the development lifecycle.\nMeetings\nSynchronization with frontend lead devs of all product squads\nTechnical retrospective: Once per sprint, exchange with the entire DEV team on technical improvements => Deliverables are technical tickets to be included in sprints (optional guest), leads must document decisions with CRs\nBack and Front Design Authority (weekly)\nSynchronization with front and back teams (sharing new topics, roadmaps, ..)\nSynchronization with DevOps\nWhat can you expect from Mars?\nAt Mars, we believe in a relationship of mutual trust, dignity and respect between our company and Associates that is more meaningful than the standard employer/employee relationship.\nAs Associates, we can expect to be respected, supported and valued as individuals, to be treated fairly and equitably.\nAn environment where you are empowered to be proactive and to take initiatives to make a difference.\nYou will work in a multicultural environment (more than 40 nationalities) and where your dog will be welcomed by more than 100 other Associates’ dogs at the office!\nA unique and ideal work environment to become the leader in health through nutrition for cats and dogs!\nMars is an equal opportunity employer and all qualified applicants will receive consideration for employment without regard to race, color, religion, sex, sexual orientation, gender identity, national origin, disability status, protected veteran status, or any other characteristic protected by law. If you need assistance or an accommodation during the application process because of a disability, it is available upon request. The company is pleased to provide such assistance, and no applicant will be penalized as a result of such a request.\nShow more\nShow less",
        "details": {
            "JobDetail": [],
            "TypeContract": "",
            "Salary": "",
            "Level": "",
            "Experience": null
        },
        "title": "data architect",
        "skills": {
            "Collaboration": [
                "Teams"
            ],
            "Other": [
                "DevOps"
            ],
            "EnSoftSkils": [
                "Leadership",
                "Organization",
                "Collaboration"
            ]
        }
    },
    {
        "source": "LinkedIn",
        "company": "FRG Technology Consulting",
        "location": "Paris, Île-de-France, France",
        "link": "https://fr.linkedin.com/jobs/view/data-architect-at-frg-technology-consulting-3837380867?position=56&pageNum=0&refId=a5rwPua%2FMvx%2F2M%2FPSF0oPA%3D%3D&trackingId=kJraF7KaJQuIzQUTGcV6pw%3D%3D&trk=public_jobs_jserp-result_search-card",
        "description": "FRG recrute, pour l'un de ses clients un Data Architect. Notre client est une société de conseil à taille humaine, en pleine croissance, qui accompagne ses clients dans leur transformation numérique.\nMissions principales\nConcevoir et mettre en œuvre les plateformes Data\nDévelopper et maintenir l'architecture pour garantir une gestion efficace et sécurisée des informations chez les clients\nMise en œuvre des stratégies de la plateforme Data\nElaboration et mise en œuvre d'architecture Data\nAutomatisation et optimisation des opérations de maintenance pour veiller à l'amélioration continue de l'efficacité des ressources sur les plateformes\nContribuer aux missions d'avant-vente : étude de faisabilité, évaluation d'impact\nProfil\n8 à 10 d'expérience dans l'IT dont 5 ans d'expérience sur l'un des Cloud Providers (AWS ; Azure ; GCP)\nExpérience confirmée dans l'implémentation des pratiques DevOps, la gestion de l'infrastructure et le déploiement de services dans le cloud\nMaîtrise des technologies de gestion des données (ETL...) et de la virtualisation des données\nCertifications fortement appréciées\nBonne communication à l'oral et à l'écrit, anglais courant\nShow more\nShow less",
        "details": {
            "JobDetail": [
                "Confirmé"
            ],
            "TypeContract": "",
            "Salary": "",
            "Level": "",
            "Experience": "5 an(s)"
        },
        "title": "data architect",
        "skills": {
            "CloudComputing": [
                "GCP",
                "AWS",
                "Azure"
            ],
            "Other": [
                "Cloud",
                "DevOps"
            ],
            "EnSoftSkils": [
                "Communication"
            ]
        }
    },
    {
        "source": "LinkedIn",
        "company": "EXAKIS NELITE",
        "location": "Aix-en-Provence, Provence-Alpes-Côte d'Azur, France",
        "link": "https://fr.linkedin.com/jobs/view/architecte-avant-vente-cloud-application-data-innovation-h-f-at-exakis-nelite-3904807120?position=57&pageNum=0&refId=a5rwPua%2FMvx%2F2M%2FPSF0oPA%3D%3D&trackingId=aX0ftkgaybh2MNefSEJg9A%3D%3D&trk=public_jobs_jserp-result_search-card",
        "description": "Exakis Nelite, entité du groupe Magellan Partners, est le premier partenaire pure-player Microsoft indépendant en France avec l’ambition de devenir le premier partenaire Européen et en Afrique Francophone avec sa forte présence au Maroc.\nNés du rapprochement de 2 leaders spécialistes de l’intégration des solutions Microsoft, nous allions expertise technique et fonctionnelle pour répondre concrètement aux enjeux de demain : accélération de la transformation digitale, transformation vers le cloud Azure, Services Cognitifs et Intelligence Artificielle…\nEn rejoignant la communauté Exakis Nelite dans l’une de nos 15 agences, vous intégrerez une équipe passionnée et impliquée dans les projets les plus innovants. Vous rejoindrez une structure construite autour de valeurs tournées vers ses collaborateurs : intelligence collective, convivialité et bienveillance.\nPoste et missions:\nVous évoluerez au sein de l’Enterprise Solution Center (ESC) de la région SUD pour relever de nouveaux défis autour des enjeux de développement Cloud et Digital.\nEn tant que Business Architect and Analyst, vous serez amené à suivre et accompagner nos clients grands comptes sur leurs sujets de transformation digitale des processus métiers et sur la valorisation de leurs données #Data. Vous les accompagnerez également lors des projets de migration vers ces nouvelles plateformes.\nVous accompagnerez le développement de la Région SUD sur ces enjeux en définissant les orientations, les offres, et les projets innovants.\nSelon les missions vous serez amené à :\nAborder une posture de conseil pour accompagner nos clients stratégiques,\nDéfinir les offres et propositions de valeurs qui feront le portefeuille de services autour de la transformation digitale vers le Cloud.\nAssurer le Bid Management des réponses commerciales au client,\nDéfinir, choisir et argumenter des architectures applicatives et techniques,\nImaginer des scénarios de valorisation des données,\nConcevoir une architecture en adéquation avec les besoins métier,\nPrendre en considération les problématiques de performance et de sécurité,\nAccompagner l’intégration des solutions dans le système d’information,\nRéaliser de la veille technologique sur les solutions et les innovations.\nAccompagner nos équipes de Delivery et nos experts dans la prise en compte des nouveaux enjeux, des projets, et des solutions.\nParticiper et piloter les phases critiques des projets innovants,\nMettre en place des partenariats avec les acteurs clés du marché.\nProfil:\nDe formation BAC+5 idéalement en ingénierie, vous justifiez d’une expérience significative dans le développement de l’infrastructure informatique en cloud et notamment sur la plateforme Azure à forte valeur ajoutée.\nVous avez la capacité de :\nLeader les avant ventes structurantes\nProposer des orientations stratégiques autour des applications à destination du Cloud public et de la gouvernance de la Data\nRelever des défis pour répondre aux enjeux des clients\nÊtre force de proposition\nCoacher, animer, et suivre des consultants passionnés\nBonne connaissance de la plateforme Azure dans son ensemble et de l’écosystème associé.\nConnaissances requises :\nServices réseaux dans Azure (VNet / Subnet, VPN S2S, ExpressRoute, Azure Firewall, Load Balancer, Application Gateway, Traffic Manager)\nAzure AD\nService machine virtuelle\nAutomatisation (modèle de déploiement ARM et / ou Terraform, Ansible)\nConteneurisation (docker, Azure Container Instance, Azure Kubernetes Service)\nGouvernance dans Azure (Azure Policy, Azure tags, Azure Cost Management, etc.)\nAspects haute disponibilité et reprise d’activité après sinistre\nDoué(e) d’un bon rédactionnel, vous maitrisez l’anglais à l’oral comme à l’écrit.\nUne expérience en ESN est indispensable !\nAvantages :\nMutuelle prise en charge à 100%, télétravail, remboursement du titre de transport à 100%, primes de congés d'été, participation/intéressement, avantages CSE.\nVous vous reconnaissez dans cette annonce? N'hésitez pas à postuler! Nous avons hâte de vous rencontrer!\nShow more\nShow less",
        "details": {
            "JobDetail": [],
            "TypeContract": "",
            "Salary": "",
            "Level": "Bac+5",
            "Experience": null
        },
        "title": "data architect",
        "skills": {
            "CloudComputing": [
                "Azure"
            ],
            "DevTools": [
                "Docker"
            ],
            "Automation": [
                "Kubernetes",
                "Ansible"
            ],
            "InfrastructureAsCode": [
                "Terraform"
            ],
            "NetworkSecurty": [
                "Firewall",
                "VPN"
            ],
            "Containers": [
                "Docker",
                "Kubernetes"
            ],
            "Other": [
                "Cloud"
            ]
        }
    },
    {
        "source": "LinkedIn",
        "company": "TotalEnergies",
        "location": "Paris, Île-de-France, France",
        "link": "https://fr.linkedin.com/jobs/view/data-architect-totalenergies-digital-factory-at-totalenergies-3915417534?position=58&pageNum=0&refId=a5rwPua%2FMvx%2F2M%2FPSF0oPA%3D%3D&trackingId=u97hBoyKUyuCRt2bDzyVOA%3D%3D&trk=public_jobs_jserp-result_search-card",
        "description": "TotalEnergies est une\ncompagnie multi-énergies mondiale\nde production et de fourniture d'énergies : pétrole et biocarburants, gaz naturel et gaz verts, renouvelables et électricité.\nLa Digital Factory de TotalEnergies est composée de 300 personnes, 30 Squads, 39% de femmes et 25 nationalités. Elle offre un environnement de travail international et interculturel en plein cœur de Paris, engagé dans la diversité et l'inclusion. Elle permet d'\naccélérer\nla production interne de\nsolutions digitales\npour les activités de la Compagnie\ndans les 130 pays où elle est présente.\nPour ce faire, elle allie l'\nagilité\net l'\nesprit pionnier\nd'une entreprise technologique à la\nrobustesse\net à la\nrigueur\nd'une entité de production à grande échelle. Elle crée et déploie des solutions digitales sur l'ensemble des sites de la compagnie TotalEnergies afin de fournir une énergie propre, fiable et abordable au plus grand nombre.\nRejoins-nous en plein cœur de Paris en tant que Data Architect, tu seras intégré(e) dans la Tech Authority qui réunit environ une vingtaine de personnes (Assurance Qualité, Sécurité, Architecte Software et Technique...).\nL'équipe évolue dans un contexte agile à tous les niveaux de l'organisation, en mode itératif et co-constructif, en s'appuyant sur l'intelligence collective. Au sein de la Tech Authority, tu participes à déterminer la gouvernance technique des projets. Tu es également un soutien et un accompagnateur pour les Squads durant les différentes phases de leur projet.\nNous attendons techniquement de toi que tu :\nDéfinisses l'architecture en phase de framing.\nCo-construises cette architecture avec les Squads en phase build. Tu seras principalement en lien avec les Data Engineers et les Tech Leads. Tu valides également l'architecture lorsque le besoin évolue. Tu es amené(e) à prendre des décisions d'architecture tout au long de la phase de build.\nValides les modélisations\nEffectues des revues périodiques avec la Squad pour étudier le code et sa qualité.\nRevois l'architecture de la solution avant le transfert au métier.\nTu devras également faire de la veille et de l'accompagnement. Ainsi, nous attendons de toi que tu :\nDéfinisses les bonnes pratiques en matière d'architecture data et que tu t'assures qu'elles sont bien respectées par l'ensemble des Squads.\nTe tiennes informé(e) des tendances, des évolutions technologiques et des innovations en vigueur dans ton domaine d'intervention.\nCoaches les Squads dans les différentes phases de réalisation de leur projet avec les Chapter Lead.\nDébloques les Squads si nécessaire lorsqu'elles rencontrent un souci avec les architectures data dans les plateformes AWS et Azure.\nAnimes les communautés Tech sur l'architecture au travers des Communities of Practices présentes à la Digital Factory de TotalEnergies.\nCe que nous t'offrons:\nLe développement de tes compétences avec le support de la Digital Academy et une enveloppe équivalente à environ 10 jours de formations par an que tu peux choisir en toute autonomie (formations externes et internes).\nLa possibilité de te certifier sur les plateformes AWS et Azure, DataBricks, …\nUn programme de mentorat pour t'accompagner.\nUn équilibre vie professionnelle et vie personnelle avec le recours possible aux horaires flexibles et au télétravail à domicile.\nUn environnement de travail international et interculturel en plein cœur de Paris, engagé dans la diversité et l'inclusion\nTu as une expérience réussie de 10 minimum dans la data dont 4 ans en tant que Data Architect.\nLes compétences qui sont attendues de toi en tant que Data Architect :\nLes méthodes de travail Agile vous sont familières.\nTu as une bonne connaissance dans les principes de base de data management, dans les traitements de data flow, dans les standards de data modeling et les bases du machine learning, deeplearning et dans l'industrialisation des architectures datascience.\nLes compétences technologiques qui te seront indispensables :\nCloud (Azure, AWS)\nDevOps\nLangages de scripting (Python, Java...)\nBases de données SQL et NoSQL\nProcessus et outils ETL ou ELT\nLes certifications suivantes sont également attendues :\nMicrosoft Certified : Azure fundamentals\nAWS certified: Solution Architect Associate\nShow more\nShow less",
        "details": {
            "JobDetail": [],
            "TypeContract": "",
            "Salary": "",
            "Level": "",
            "Experience": "4 an(s)"
        },
        "title": "data architect",
        "skills": {
            "ProgLanguage": [
                "Java",
                "Python"
            ],
            "DataBase": [
                "SQL",
                "NoSQL"
            ],
            "BigData": [
                "Databricks"
            ],
            "CloudComputing": [
                "AWS",
                "Azure"
            ],
            "Other": [
                "Machine Learning",
                "Cloud",
                "DevOps"
            ]
        }
    },
    {
        "source": "LinkedIn",
        "company": "Templeton and Partners - Tech Recruitment",
        "location": "Lyon, Auvergne-Rhône-Alpes, France",
        "link": "https://fr.linkedin.com/jobs/view/architecte-data-at-templeton-and-partners-tech-recruitment-3904841784?position=59&pageNum=0&refId=a5rwPua%2FMvx%2F2M%2FPSF0oPA%3D%3D&trackingId=RpoZyxSOnAcVD67qvV4WFQ%3D%3D&trk=public_jobs_jserp-result_search-card",
        "description": "Architecte Data\nSecteur\n: Industriel\nDémarrage:\nASAP\nMission :\nLongue\nCadence :\nFull time\nHybrid :\n3 jours sur site (Est lyonnais)\nNous recherchons un Architecte de Données qui fera partie de l'équipe stable de BI & Analytics, axée sur le Marketing & la Communication.\nLa Mission :\nEn tant qu'Architecte de Données, vous veillerez à ce que les produits livrés par votre équipe stable soient alignés sur l'architecture cible mondiale du client. Pour soutenir ce poste, nous recherchons un Architecte de Données Azure avec une bonne compréhension générale des services disponibles dans la pile d'analyse Azure.\nCette personne travaillera avec le DPO, l'Analyste de Données, l'Ingénieur de Données et le Data Scientist de l'équipe stable, mais aussi avec la communauté des Architectes pour définir une architecture de qualité, de valeur commerciale pertinente et de maintenabilité à long terme.\nDe plus, il/elle doit également avoir des compétences en leadership pour assumer le rôle de leader technique et discuter avec les Parties Prenantes Métier et l'Architecture d'Entreprise.\nVous fournissez un leadership technique, vous participez aux efforts de développement et vous représentez l'ensemble des capacités internes et externes de la plateforme.\nVous serez un membre actif de la guilde des architectes pour superviser le processus de gestion des données et fournir des orientations aux équipes de développement.\nVous êtes responsable de la conception et de la documentation de la solution dans votre domaine.\nVous avez de l'expérience sur Databricks, le stockage ADLS, SQL DB, ADF et Power BI.\nVous avez de l'expérience dans la définition et la possession d'une architecture de données évolutive de bout en bout en tenant compte de l'architecture d'entreprise et des normes de l'industrie.\nVous êtes habitué à développer, documenter et maintenir des modèles de données logiques et physiques.\nVotre future équipe :\nDans le cadre du Marketing & de la Communication, vous rencontrerez de nombreux défis et sujets intéressants :\nCréer un tableau de bord client 360 basé sur les données CRM et des sources externes pour soutenir le processus marketing.\nCalculer le prix prédictif des produits utilisés basé sur les données de l'OCDE grâce à un processus d'IA.\nTableau de bord des ventes pour piloter le processus de vente.\nMettre en place un produit de données pour soutenir l'approche CAST (produit réutilisable partagé) conforme à la stratégie du Groupe Volvo.\nFaire partie de l'équipe de maintenance pour assurer la continuité des processus métier.\nCompétences & Aptitudes Obligatoires :\nL'Architecture de Données est votre domaine depuis au moins 4 ans.\nÉcrire du SQL et réaliser de la modélisation de données vous est naturel.\nConception d'Architecture de Données.\nPower BI.\nComposants Azure comme ADFv2, Databricks, Delta Lake.\nTechnologies et cadres d'Analyse Avancée Azure.\nLangage de programmation lié à l'Analyse Avancée : Python, Pyspark.\nModèle de livraison basé sur le Cloud Microsoft.\nGestion des Données, Gouvernance des Données et Qualité des Données.\nDéploiement d'API ou de microservices.\nDevSecOps.\nAgile.\nVous avez de l'expérience de travail dans un environnement mondial.\nVous avez d'excellentes compétences en communication en français et en anglais (niveau C1).\nShow more\nShow less",
        "details": {
            "JobDetail": [
                "Full"
            ],
            "TypeContract": "",
            "Salary": "",
            "Level": "",
            "Experience": "4 an(s)"
        },
        "title": "data architect",
        "skills": {
            "ProgLanguage": [
                "Python"
            ],
            "DataBase": [
                "SQL"
            ],
            "BigData": [
                "Databricks"
            ],
            "DataVisualisation": [
                "Power BI",
                "Tableau"
            ],
            "CloudComputing": [
                "Azure"
            ],
            "Other": [
                "Cloud"
            ],
            "EnSoftSkils": [
                "Leadership",
                "Communication"
            ]
        }
    },
    {
        "source": "LinkedIn",
        "company": "Harnham",
        "location": "Paris",
        "link": "https://fr.linkedin.com/jobs/view/data-architect-at-harnham-3911912252?position=1&pageNum=2&refId=s27%2F43wenQFDag2sabINKw%3D%3D&trackingId=RVF4m9iXGLslJjBwC1Tixw%3D%3D&trk=public_jobs_jserp-result_search-card",
        "description": "DATA ARCHITECT\nPARIS (75)\nUP TO 65K€ FIXE\nAWS - Tableau - Pyspark - Data Modeling\nVous êtes à la recherche d'un nouveau challenge de Data Architect dans le domaine de l'assurance ? Ne cherchez plus, voici l'opportunité de vos rêves ! Une entreprise spécialisée dans l'assurance automobile des particuliers, recherche un Data Architect dans le cadre de la création d'une nouvelle plateforme data en Europe.\nLE POSTE\nEn tant que Data Architect, vous allez définir les architectures et les normes pour la stratégie de données. Vous définirez la vision et les lignes directrices pour la livraison des produits de données.\nVoici vos responsabilités au quotidien :\nDéfinir l'architecture cible\nCommuniquer avec les Product Owner pour atteindre l'objectif du wagon\nTravailler en étroite collaboration avec les data scientists pour opérationnaliser les modèles ML au sein de la plateforme de données\nTravailler en étroite collaboration avec les data engineer et data ops pour le suivi de l'architecture cible\nTravailler en mode agile au quotidien\nVOTRE PROFIL\nDiplôme d'ingénieur en computer engineering ou mathématiques\n5 ans d'expérience en architecture data\nConnaissance des architectures de plateformes de données opérationnelles\nConnaissance de la modélisation de données et bases de données\nConnaissance du cloud AWS\nConnaissance d'outils BI principalement Tableau\nBilingue (fançais et anglais)\nNice to have : connaissance en Machine Learning\nPOUR POSTULER\nMerci de me faire part de votre CV et je vous recontacterai au plus vite.\nShow more\nShow less",
        "details": {
            "JobDetail": [],
            "TypeContract": "",
            "Salary": "",
            "Level": "",
            "Experience": "5 an(s)"
        },
        "title": "data architect",
        "skills": {
            "DataVisualisation": [
                "Tableau"
            ],
            "CloudComputing": [
                "AWS"
            ],
            "Other": [
                "Machine Learning",
                "Cloud",
                "ML"
            ],
            "EnSoftSkils": [
                "Collaboration"
            ]
        }
    },
    {
        "source": "LinkedIn",
        "company": "FRG Technology Consulting",
        "location": "Paris, Île-de-France, France",
        "link": "https://fr.linkedin.com/jobs/view/architecte-data-at-frg-technology-consulting-3917370845?position=2&pageNum=2&refId=s27%2F43wenQFDag2sabINKw%3D%3D&trackingId=c%2F%2F%2BmrSZ6WTY%2B99bPhM%2Fjg%3D%3D&trk=public_jobs_jserp-result_search-card",
        "description": "Notre client, entreprise renommée dans le secteur du luxe et des cosmétiques, basé sur Paris, est à la recherche de son/sa futur(e) Architecte Data.\nEn tant que membre de la DSI, votre rôle est de participer à la transformation digitale de l’entreprise, par une meilleure capture, analyse et exploitation des données clients.\nPrincipales missions :\nAnalyse et réponses aux besoins des métiers (BI, analyses externes, etc.),\nConception de nouveaux modèles de données\nConstruction des pipelines de données\nTransformation de données (Pyspark) et le stockage de données dans le Data Lake / Data Warehouse du Groupe\nRun et le suivi de la TMA\nDescription du profil :\nTitulaire Bac +5 informatique ou diplôme ingénieur\n6 années minimum en expertise Data\nUne bonne maîtrise des outils suivants : Azure, SQL, Snowflake, Databricks, Spark, Python, ELK,..\nUne bonne affinité avec les best practices DevOps, CI/CD, unit-testing et méthodologies de travail agile\nDes notions en data science sur l’entraînement, la validation et le déploiement de modèles ML supervisés et non-supervisés serait un plus.\nQualités requises : Bon esprit analytique et de synthèse, rigoureux, autonome, bonne communication, curieux, force de proposition, vulgarisation des problématiques techniques auprès du métier\nAvantages :\nPackage (variable / participation / intéressement) + avantages attractifs\nÉquipe Data à taille humaine (très bon accompagnement en interne)\nForte valeur ajoutée des projets\nTélétravail\nCandidatures confidentielles\nShow more\nShow less",
        "details": {
            "JobDetail": [],
            "TypeContract": "",
            "Salary": "Package",
            "Level": "",
            "Experience": null
        },
        "title": "data architect",
        "skills": {
            "ProgLanguage": [
                "Python"
            ],
            "DataBase": [
                "SQL"
            ],
            "BigData": [
                "Databricks",
                "Spark"
            ],
            "CloudComputing": [
                "Azure"
            ],
            "DBMS": [
                "Snowflake"
            ],
            "Other": [
                "ML",
                "DevOps",
                "CI/CD"
            ],
            "EnSoftSkils": [
                "Communication"
            ]
        }
    },
    {
        "source": "LinkedIn",
        "company": "Ippon Technologies",
        "location": "Lyon",
        "link": "https://fr.linkedin.com/jobs/view/architecte-data-f-h-at-ippon-technologies-3893256404?position=3&pageNum=2&refId=s27%2F43wenQFDag2sabINKw%3D%3D&trackingId=eNgv9c6B5TkdwhMVrnYkxg%3D%3D&trk=public_jobs_jserp-result_search-card",
        "description": "Qui sommes-nous ?\nIppon\n, c'est l’énergie du collectif au service de la technologie ! Nous sommes un cabinet de conseil et d’expertise technique. Nos équipes ont pour leitmotive de transformer des idées innovantes en solutions logicielles de haute qualité avec un focus particulier sur la valeur apportée aux utilisateurs.\nCréée en 2017, l’agence de Lyon, ce sont des passionnés intervenant sur des projets à forte technicité ou en conseil et architecture : Fullstack, Data, DevOps, Cloud, Agile, Design et ne compte pas s’arrêter en si bon chemin !\nLa pluridisciplinarité, l’expertise, l’écoute, l’adaptabilité mais aussi le partage de connaissances fondent notre engagement au service de nos partenariats.\nVous intégrerez notre Communauté Data\n, composée d’une équipe de\n80 experts sur 10 agences en France.\nNotre spécialité est de\nconstruire des data platforms dans le Cloud public avec les meilleures technos du moment.\nLa\nData chez Ippon, c’est déjà plus de\n250 certifications AWS, GCP et AZURE,\ndes\nspeakers à l’AWS Summit, des partenariats avec Snowflake, Databricks, DBT, un blog technique\navec des publications régulières.\nCe poste est un vrai challenge aussi bien en termes de\ndéfis techniques que de gestion d'équipe.\nLa\nréussite de vos projets sera portée par votre capacité à vous adapter et à monopoliser un large panel de compétences techniques. Vous devrez être le/la leader de votre équipe en gardant à l’esprit l’ensemble des\nbonnes pratiques d'architectes\n, de sécurité et d’automatisation nécessaires à la réussite du projet. En tant que\nreprésentant(e) de l’engagement d’Ippon\nsur les sujets qui vous seront confiés, vous serez amené(e) à\ntravailler avec notre équipe Commerce dès les phases de qualification\net lors de la validation de jalons de la roadmap que vous aurez préalablement validé avec le client. Vous interviendrez également dans la sélection de l’équipe qui sera affectée à votre projet.\nVotre rôle :\n- Grâce à votre position d’architecte vous avez une vision experte et systémique de l’ensemble des composants d’une Modern Data Platform.\n- Vous maîtrisez le panel des exigences fonctionnelles et non fonctionnelles à collecter afin d’assurer l’efficience opérationnelle et la pérennité de la data platform.\n- Vous êtes expert(e) et maîtrisez tous les outils et services d’au moins un écosystème parmi les 3 principaux leaders du marché (AWS, Azure et GCP) et avez des facilités pour étendre votre champ de compétences.\n- Vous êtes proactif/ve sur la veille technique et la capitalisation et veillez à garder toujours un temps d’avance sur l’état de l’art du secteur afin de pouvoir guider vos clients.\n- En tant qu’architecte expérimenté(e) vous pouvez indifféremment intervenir sur des missions de delivery pour concevoir la solution cible ou en phase de cadrage amont pour guider les choix et construire les roadmaps.\n- Vous êtes pédagogue et savez communiquer et vulgariser des réflexions complexes pour les rendre accessibles à tous.\nNotre éco-système technique :\n- Cloud : AWS, GCP, Azure\n- Langage de programmation data : Python, SQL, Scala\n- Approche Data Warehouse : Redshift, Snowflake, BigQuery\n- Approche Data Lakehouse : Databricks, Starburst, Glue-Athena-S3Ingestion : AWS Glue, Airbyte, dbt Stockage : AWS S3, Google Cloud Storage, Azure Blob Storage\n- Orchestration : Airflow, AWS Step function\n- Gouvernance : cataloging, sécurité, scope d'accèsBatch et Streaming : Kafka, Amazon Kinesis, Google DataFlow\n- Outil de visualisation : Tableau, Power BI, Metabase, Superset\nVotre évolution chez Ippon :\nVous serez accompagné(e) dans votre montée en compétences aussi bien technique que leadership grâce à\nnotre programme BlackBelt\n(programme de formation continue : mentoring, formations, certifications).\nEn tant que membre d’une communauté,\nvous pouvez avoir différents rôles :\n- Celui de Manager Technique (MT) : manager d’une équipe de 7 ingénieur(e)s Ippon (onboarding, suivis, accompagnement, mise en place d’objectifs…). Vous conduirez les entretiens techniques en binôme\n- Responsable de l’accomplissement d’une ou plusieurs actions stratégiques de la CoreTeam Data\n- Devenir speaker lors de Meetup, Summit, Talks internes, auprès des écoles …\n- Devenir formateur(trice) et accompagner la nouvelle génération d’Ippon dans leur montée en compétencesVous avez d’autres souhaits, pas de soucis, nous en discuterons durant notre échange et répondrons à toutes vos questions.\nLes Next Steps :\n1 Echange RH\n1 Echange Technique\n1 Echange avec la Direction\nSi le match est bon des deux côtés : Vous vous lancerez sur le tatami Ippon !\nShow more\nShow less",
        "details": {
            "JobDetail": [
                "Full"
            ],
            "TypeContract": "",
            "Salary": "",
            "Level": "",
            "Experience": null
        },
        "title": "data architect",
        "skills": {
            "ProgLanguage": [
                "Scala",
                "Python"
            ],
            "DataBase": [
                "SQL"
            ],
            "BigData": [
                "Databricks"
            ],
            "DataVisualisation": [
                "Power BI",
                "Tableau"
            ],
            "CloudComputing": [
                "GCP",
                "AWS",
                "Azure"
            ],
            "DBMS": [
                "BigQuery",
                "Snowflake"
            ],
            "Automation": [
                "Airflow"
            ],
            "Other": [
                "Cloud",
                "DevOps"
            ],
            "EnSoftSkils": [
                "Leadership"
            ]
        }
    },
    {
        "source": "LinkedIn",
        "company": "Akademija Oxford",
        "location": "Boulogne-Billancourt, Île-de-France, France",
        "link": "https://fr.linkedin.com/jobs/view/data-analyst-junior-h-f-at-akademija-oxford-3917871112?position=4&pageNum=2&refId=s27%2F43wenQFDag2sabINKw%3D%3D&trackingId=A3sTIrvtclaO2d7xjfPfTw%3D%3D&trk=public_jobs_jserp-result_search-card",
        "description": "Notre entreprise partenaire, spécialiste de la vente de médicaments et produits de santé, recherche un apprenti Data Analyst (H/F) préparant un bac +4/+5 en filière Big Data pour la rentrée de Septembre 2021.\nShow more\nShow less",
        "details": {
            "JobDetail": [],
            "TypeContract": "",
            "Salary": "",
            "Level": "",
            "Experience": null
        },
        "title": "data analyst",
        "skills": {
            "Other": [
                "Big Data"
            ]
        }
    },
    {
        "source": "LinkedIn",
        "company": "FRG Technology Consulting",
        "location": "Paris, Île-de-France, France",
        "link": "https://fr.linkedin.com/jobs/view/data-architect-azure-at-frg-technology-consulting-3902057360?position=5&pageNum=2&refId=s27%2F43wenQFDag2sabINKw%3D%3D&trackingId=NwAL8xb%2BL044hdpxUUfrXA%3D%3D&trk=public_jobs_jserp-result_search-card",
        "description": "FRG Consulting recrute pour l'un de ses clients, une société finale renommée dans le secteur du luxe et des cosmétiques, un Data Architect expert en Azure. Niché au cœur de Paris, vous aurez l'opportunité de travailler au sein d'une équipe passionnée par la recherche et l'innovation, évoluant dans un environnement stimulant et créatif.\nVos missions captivantes :\nContribuer à l'évolution de nos systèmes en développant de nouveaux connecteurs et pipelines pour l'extraction de données, qu'il s'agisse de batch (utilisant Sqoop, scripts bash, Java ou des API) ou de streaming (via Kafka, ELK).\nParticiper activement à la transformation des données à l'aide de Pyspark, ainsi qu'au stockage dans notre Data Lake et notre Data Warehouse.\nConcevoir de nouveaux modèles de données et mettre à disposition des tables ad-hoc sur Snowflake et Impala, répondant ainsi aux besoins métier en termes de BI et d'analyses externes.\nAssurer le bon fonctionnement et le suivi de la TMA du Data Lake, garantissant ainsi la fiabilité et la performance de nos systèmes.\nProfil recherché :\nVous bénéficiez d'au moins 8 ans d'expérience dans le domaine.\nVous maîtrisez les outils et frameworks de notre stack technique Big Data : Azure, SQL, Snowflake, Databricks, Spark, Python, ELK.\nVous êtes familier des best practices DevOps, CI/CD, et des méthodologies de travail agile.\nDes compétences en data science, notamment sur l'entraînement, la validation et le déploiement de modèles ML supervisés et non-supervisés, seraient grandement appréciées.\nLa maîtrise de l'anglais est indispensable pour évoluer dans un environnement international et dynamique.\nShow more\nShow less",
        "details": {
            "JobDetail": [],
            "TypeContract": "",
            "Salary": "",
            "Level": "",
            "Experience": "8 an(s)"
        },
        "title": "data architect",
        "skills": {
            "ProgLanguage": [
                "Java",
                "Bash",
                "Python"
            ],
            "DataBase": [
                "SQL"
            ],
            "BigData": [
                "Databricks",
                "Spark"
            ],
            "CloudComputing": [
                "Azure"
            ],
            "DBMS": [
                "Snowflake"
            ],
            "Other": [
                "ML",
                "Big Data",
                "DevOps",
                "CI/CD"
            ]
        }
    },
    {
        "source": "LinkedIn",
        "company": "TeamWork Corporate",
        "location": "Saint-Priest, Auvergne-Rhône-Alpes, France",
        "link": "https://fr.linkedin.com/jobs/view/data-architect-senior-freelance-h-f-at-teamwork-corporate-3916528778?position=6&pageNum=2&refId=s27%2F43wenQFDag2sabINKw%3D%3D&trackingId=yaz2%2FJwMWVF6OWDperGC1w%3D%3D&trk=public_jobs_jserp-result_search-card",
        "description": "Description de l'entreprise\nTeamWork est un acteur majeur du conseil, de l’intégration technologique et de l’innovation, implanté en Europe, en Asie et en Amérique du Nord.\nAu travers de ses univers, SAP Business Solutions, Data Analytics, Technology Platform et Salesforce, nous sommes reconnus par nos clients pour accroître leur performance opérationnelle.\nLa transformation digitale est un enjeu majeur pour toute organisation.\nLa nécessité de digitaliser ses processus, d’imaginer de nouvelles façons d’interagir avec ses clients, d’en conquérir de nouveaux et de proposer de nouveaux outils pour anticiper les besoins de pilotage n’a jamais été aussi forte.\nL’univers Data Analytics de TeamWork accompagne les organisations autour de :\nLa réflexion et identification de cas d’usage pour les transformer en trajectoires moyen et long terme\nLe design et l’implémentation de plateforme de données et des outils périphériques (data ingestion/intégration)\nLa mise en place des premières solutions d’Analytics (Business Intelligence, EPM,)\nSupport, extension et optimisation des solutions\nDans le cadre du développement de ces activités, nous recrutons un\nData Architect Senior (H/F)\nen Freelance pour une mission entre 2 à 3 mois.\nDescription du poste\nEn tant qu’Architecte Data vous intervenez dans le cadre de projets et missions qui répondent aux enjeux clients d’exploitation des données. Vous participez aux phases d’avant-vente, aux études d’architecture, et à la réalisation des solutions avec une responsabilité d’encadrement technique des projets (tant sur des forfaits que des missions clients). Vous aurez des missions avec de réelles responsabilités et très diversifiées (secteurs d’activités variés).\nVos principales missions s’articulent autour de :\nL’analyse et la qualification des besoins et problématiques « métiers » de nos clients\nAssurer la conception, le développement et la mise en oeuvre de l'architecture des données sur la plateforme Databricks\nLa définition et mise en œuvre des architectures Data adaptées aux contextes des projets : Modern Datawarehouse, LakeHouse, DataMesh etc.\nL’accompagnement des Consultants et des Ingénieurs spécialistes Data sur les projets. Vous œuvrez à qualité de leurs réalisations et des livrables.\nLa collaboration sur tous les domaines d’activités DATA : BI, Big Data, IoT, IA\nL’apport d’un regard critique et la capacité à conseiller sur le choix des technologies Data\nLa participation à la définition des bonnes pratiques de mises en œuvres techniques et la veille à leurs applications selon les méthodes en vigueur (Zero Trust Security, DataOps, Infra-as-Code, Tests automatisés etc.)\nQualifications\nTechniques :\nVous avez :\nTrès bonnes connaissances de Databricks\nLa capacité à réaliser la conception et l’implémentation de solutions d’analytique à l’échelle de l’entreprise ; SQL\nLa connaissance d’un ou plusieurs outils ETL (Azure Data Factory ou autres) et Data Visualisation (PowerBI par exemple)\nLa capacité à mettre en place une solution Data end-to-end La connaissances des typologies d’architectures (Modern Datawarehouse, LakeHouse ou DataMesh)\nVous connaissez l’environnement Azure, MSBI, SQL Server ou si vous avez des notions dans l’IA (Python, R, Machine Learning)\nMaitrise le traitement et l'analyse des données en Python (Expérience dans la conception et le développement de processus ETL/ELT)\nMaitrise d’outils de traitement et de stockage distribués parmi Hadoop, Spark, Databricks, Snowflake et/ou Kafka\nConnaissance des bonnes pratiques de conception d’architecture data (sécurité, disponibilité, scalabilité, confidentialité) et des principes d’une architecture Data Mesh.\nCapacité à concevoir des architectures basées sur les services d’une plateforme Cloud : AWS ou Azure\nSoft Skills\n:\nVous êtes proactif et appréciez travailler dans un environnement ambitieux et innovant.\nVous aimez ne pas rester sur vos acquis et toujours apprendre par le biais de formations, votre veille technologique ou encore par la participation aux événements communautaires.\nHabitué à travailler aussi bien de façon autonome qu’à collaborer en équipe\nConnaissance des méthodologies Agile (SCRUM ou autres)\nEnvie d’apprendre et de partager vos savoir-faire\nCuriosité\nLangues :\nFrançais (Courant)\nAnglais (A l’aise en communication orale et écrite)\nFormation\n:\nVéritable passionné par la DATA et diplômé d’une école d’ingénieur (Bac+3 minimum) ou d'une formation spécifique orientée Data avec une expérience significative en Data Engineering et architecture.\nVous avez une expérience de plus de 7 ans en environnement informatique, dont 3 à 4 ans minimum sur un poste senior en environnement Databricks (Team Lead, Architecte ou encore Consultant Senior).\nNous attacherons davantage d’importance à votre capacité à vouloir apprendre et progresser et votre motivation qu’à votre diplôme.\nInformations supplémentaires\nTeamWork, où votre épanouissement professionnel est clé. Récompensés par le label 'Great Place to Work 2023', nous plaçons l'humain au cœur de notre entreprise.\nAu-delà des compétences, nous valorisons les personnalités qui partagent nos valeurs de solidarité et d'esprit d'équipe.\nSi ces principes vous parlent, rejoignez-nous ! Nous sommes dédiés à l'équité et à la diversité, ouvrant nos portes à tous les talents, y compris aux personnes en situation de handicap.\nPostulez et devenez un acteur de notre réussite collective chez TeamWork.\nShow more\nShow less",
        "details": {
            "JobDetail": [
                "Senior"
            ],
            "TypeContract": "",
            "Salary": "",
            "Level": "Bac+3",
            "Experience": "7 an(s)"
        },
        "title": "data architect",
        "skills": {
            "ProgLanguage": [
                "R",
                "Python"
            ],
            "DataBase": [
                "SQL"
            ],
            "DataAnalytics": [
                "R"
            ],
            "BigData": [
                "Databricks",
                "Hadoop",
                "Spark"
            ],
            "CloudComputing": [
                "AWS",
                "Azure"
            ],
            "DBMS": [
                "SQL Server",
                "Snowflake"
            ],
            "Other": [
                "Machine Learning",
                "Cloud",
                "Big Data"
            ],
            "EnSoftSkils": [
                "Teamwork",
                "Communication",
                "Collaboration"
            ]
        }
    },
    {
        "source": "LinkedIn",
        "company": "Airbus",
        "location": "Saint-Nazaire",
        "link": "https://fr.linkedin.com/jobs/view/airbus-atlantic-architecte-data-all-gender-at-airbus-3916426275?position=7&pageNum=2&refId=s27%2F43wenQFDag2sabINKw%3D%3D&trackingId=bxP4EpffbA1eb29JFyQBdA%3D%3D&trk=public_jobs_jserp-result_search-card",
        "description": "Job Description\nEt si VOTRE aventure avec NOUS commençait ?!\nNous vous proposons de travailler chez Airbus Atlantic, nouveau champion de dimension mondiale, n°2 des aérostructures, n°1 des sièges pilotes et dans le Top 3 des fauteuils passagers Premium.\nNotre site Airbus Atlantic basé\nà Toulouse (possibilité de travailler à Montoir de Bretagne)\nrecherche son futur\nArchitecte Data (All Gender)\nLe poste d’architecte Data est rattaché au domaine « Architecture » au sein du département « Architecture Digital & Sécurité ».\nVous serez en interface avec les architectes du Système d'Information et les différents métiers consommateurs des architectures.\nVos Principales Missions Seront Les Suivantes\nFixer les orientations et définir des politiques concernant la modélisation des données, en collaboration avec les autres architectes,\nCréer des modèles de données logiques et physiques en utilisant les meilleures pratiques pour garantir une qualité élevée des données et une réduction de leur redondance,\nInstancier, implémenter, construire, tester et maintenir les architectures data définies\nAnalyser, évaluer, tester et recommander les briques technologiques nécessaires pour l’acquisition, l’analyse et l’implémentation des données,\nAnalyser les problèmes d'intégration des systèmes liés aux données et proposer des solutions appropriées,\nDéterminer les « Data set process » c’est à dire comment les données sont intégrées et transformées pour qu’elles soient prêtes à être analysées (ex : ETL)\nParticiper aux processus d'extraction performants et qualitatifs des données des sources requises afin de répondre aux besoins de l'entreprise\nMaintenir les modèles de données conceptuels, logiques et physiques ainsi que les métadonnées correspondantes (pour la data gouvernance).\nDévelopper les meilleures pratiques pour les conventions de dénomination standard et les pratiques de codage afin d'assurer la cohérence des modèles de données,\nRespecter les normes de sécurité des données, de contrôle des exportations et de protection des données.\nConstruire les pipelines qui permettront aux Data Scientist/Analysts/Developers de mettre leurs modèles en production\nEtre garant de la fiabilité, de la qualité et de l’efficacité du traitement des données\nMaintenir les modèles créés.\nParticiper aux idéations et proposer des innovations aux services.\nDocumenter ses activités et mettre à jour le référentiel documentaire.\nParlons de vous !\nVous disposez d'une\ne\nxp\nérience de minimum 5 ans en Data & Informatique sur un poste similaire.\nLes compétences techniques à détenir pour le poste :\nL’optimisation et les standards Qualité des données informatiques\nComprendre et savoir mettre en place les différentes Structure et stockage de données\nGestion des problèmes lié à la donnée, l'architecture\nIdéalement, l'expérience des technologies suivantes serait un plus : Ressources & services data MS Azure (Databricks, Azure ML …), SGBD (SQL, MongoDB, PostGreSQL, redis), Outils ETL (Qlik replicate, Alteryx, …), Outils BI (PowerBI, Qlik, Grafana ...),\nLangages de programmation (python, SCALA, R, DAX)\nLes certifications de Azure (DP-203, AZ-300, AZ-303, AZ-304, AZ-400, AI-900) seraient un plus,\nVotre Personnalité\nFort volonté de travailler en équipe\nBonnes habitudes de documentation\nNiveau avancé en Français et en Anglais (niveau minimum B1)\nFaire preuve d’innovation et être source de proposition\nSavoir exprimer ses idées de manière claire et concise\nEtre à l'écoute\nParlons de nous !\nEnvironnement & Conditions De Travail\nAirbus Atlantic c’est aussi :\nPrendre part à des projets ambitieux, à la pointe de la technologie pour construire l’avion de demain, en lien avec les enjeux environnementaux.\nUn environnement qui valorise la proximité et la dimension humaine, au sein d’un collectif engagé et solidaire.\nL’opportunité d’apprendre et d’évoluer tout au long de votre parcours, en étant accompagné dans votre développement pour une carrière sur-mesure.\nAvoir la liberté d’entreprendre et de laisser libre court à vos initiatives.\nSes conditions de travail attractives et ses avantages : restaurant d’entreprise sur site, CSE (avantages loisirs & famille), parking entreprise, mutuelle d’entreprise (famille).\nSa politique de diversité et d'inclusion : Airbus Atlantic s’engage en faveur de l’égalité des chances pour tous.\nSon plan d'actionnariat salarié et son plan d’épargne salariale.\nNotre Processus De Recrutement\nNous avons à cœur de mieux vous connaître et de comprendre ce qui vous motive à nous rejoindre. Aussi, notre process de recrutement se déroule en plusieurs étapes après analyse de votre candidature :\nEntretien vidéo différé via la plateforme Hirevue\nEntretien avec le Manager Recruteur\nEntretien avec le/la Chargé(e) de Recrutement qui peut être complété par un questionnaire de personnalité\nEntretien avec le/la Human Resources Business Partner.\nThis job requires an awareness of any potential compliance risks and a commitment to act with integrity, as the foundation for the Company’s success, reputation and sustainable growth.\nCompany\nAirbus Atlantic\nContract Type\nPermanent\nClasse Emploi (France): Classe G13\nExperience Level\nProfessional\nJob Family\nDigital\nBy submitting your CV or application you are consenting to Airbus using and storing information about you for monitoring purposes relating to your application or future employment. This information will only be used by Airbus.\nAirbus is committed to achieving workforce diversity and creating an inclusive working environment. We welcome all applications irrespective of social and cultural background, age, gender, disability, sexual orientation or religious belief.\nAirbus is, and always has been, committed to equal opportunities for all. As such, we will never ask for any type of monetary exchange in the frame of a recruitment process. Any impersonation of Airbus to do so should be reported to emsom@airbus.com.\nAt Airbus, we support you to work, connect and collaborate more easily and flexibly. Wherever possible, we foster flexible working arrangements to stimulate innovative thinking.\nShow more\nShow less",
        "details": {
            "JobDetail": [],
            "TypeContract": "",
            "Salary": "",
            "Level": "",
            "Experience": "5 an(s)"
        },
        "title": "data architect",
        "skills": {
            "ProgLanguage": [
                "R",
                "Scala",
                "Python"
            ],
            "DataBase": [
                "SQL",
                "MongoDB"
            ],
            "DataAnalytics": [
                "R"
            ],
            "BigData": [
                "Databricks"
            ],
            "CloudComputing": [
                "Azure"
            ],
            "DBMS": [
                "PostgreSQL"
            ],
            "Other": [
                "ML"
            ],
            "EnSoftSkils": [
                "Collaboration"
            ]
        }
    },
    {
        "source": "LinkedIn",
        "company": "Capgemini",
        "location": "Nantes, Pays de la Loire, France",
        "link": "https://fr.linkedin.com/jobs/view/architecte-technique-bi-big-data-nantes-at-capgemini-3803994992?position=8&pageNum=2&refId=s27%2F43wenQFDag2sabINKw%3D%3D&trackingId=7FHNSEfvjMmvL7Q5xmN9%2FQ%3D%3D&trk=public_jobs_jserp-result_search-card",
        "description": "Capgemini\nChoisir Capgemini, c'est choisir une entreprise où vous serez en mesure de façonner votre carrière selon vos aspirations, où vous serez soutenu et inspiré par une communauté d’experts dans le monde entier, où vous pourrez réécrire votre futur. Rejoignez-nous pour redéfinir les limites de ce qui est possible, contribuer à libérer la valeur de la technologie pour les plus grandes organisations et participez à la construction d’un monde plus durable et inclusif.\nVos missions :\nIntégré(e) au sein d'une équipe projets intervenant pour des clients dans des secteurs d'activités variées, vous serez notamment en charge des missions suivantes :\nInteragir avec nos clients, nos partenaires pour concevoir et mettre en œuvre des solutions/projets innovants et compétitifs\nRépondre aux problématiques de nos clients en proposant la meilleure plateforme data dans un environnement Agile\nAdapter chaque architecture en fonction du contexte grâce à votre maîtrise des caractéristiques fondamentales de chaque solution (catalogue des offres de services managés, performance, sécurité, déploiement des data centers …)\nUtiliser les solutions d’intégration associées et les solutions décisionnelles ainsi qu’analytiques qui viennent consommer les données manipulées\nEncadrer les équipes dans la mise en place des architectures préconisées et/ ou des plateformes Data\nVous avez acquis de l’expérience sur les cadres de référence et patterns d’architecture Data, DevOps.\nVotre profil :\nDiplôme d’ingénieur ou équivalent universitaire\nMinimum 6 ans d'expérience\nAnglais courant\nExpertise dans la conception d’architecture, la mise en œuvre et/ou le support d’applications hautement distribuées\nSensibilisation à la méthode devops et connaissance d’un outil de de Continuous Integration/Continuous Delivery (CI-CD)\nExpertise sur les services Cloud Data suivants (Azure, AWS, GCP)\nGrande aisance dans la communication orale et écrite, leadership afin de fédérer des équipes\n3 raisons de nous rejoindre :\nQualité de vie au travail : accord de télétravail en France et à l’international, accord sur l’égalité\nprofessionnelle, la parentalité, l’équilibre des temps et la mobilité durable.\nApprentissage en continu : certifications et formations en libre accès, accompagnement sur mesure avec votre carreer manager, parcours d’intégration sur 9 mois.\nAvantages groupe & CSE : plan actionnariat, activités à tarifs préférentiels, remboursement partiel\nvacances, remboursement de votre abonnement sportif ou culturel.\nNos engagements et priorités :\nLe groupe Capgemini encourage une culture inclusive dans un cadre multiculturel et handi-accueillant. En nous rejoignant, vous intégrez un collectif qui valorise la diversité, développe le potentiel de ses talents, s’engage dans des initiatives solidaires avec ses partenaires, et se mobilise pour réduire son impact environnemental sur tous ses sites et auprès de ses clients.\nCapgemini\nCapgemini est un leader mondial, responsable et multiculturel, regroupant près de 350 000 personnes dans plus de 50 pays. Fort de 55 ans d’expérience, nous sommes un partenaire stratégique des entreprises pour la transformation de leurs activités en tirant profit de toute la puissance de la technologie et des innovations dans les domaines en perpétuelle évolution tels que le cloud, la data, l’Intelligence Artificielle, la connectivité, les logiciels, l’ingénierie digitale ou les plateformes.\nGet The Future You Want* | www.capgemini.com/fr-fr\n*Capgemini, le futur que vous voulez\nShow more\nShow less",
        "details": {
            "JobDetail": [],
            "TypeContract": "",
            "Salary": "",
            "Level": "",
            "Experience": "6 an(s)"
        },
        "title": "data architect",
        "skills": {
            "CloudComputing": [
                "GCP",
                "AWS",
                "Azure"
            ],
            "Other": [
                "Cloud",
                "DevOps"
            ],
            "EnSoftSkils": [
                "Leadership",
                "Communication"
            ]
        }
    },
    {
        "source": "LinkedIn",
        "company": "EXAKIS NELITE",
        "location": "Grenoble, Auvergne-Rhône-Alpes, France",
        "link": "https://fr.linkedin.com/jobs/view/architecte-conseil-data-h-f-at-exakis-nelite-3813458944?position=9&pageNum=2&refId=s27%2F43wenQFDag2sabINKw%3D%3D&trackingId=sFkATwbM7Wt2uLFv7VyJuQ%3D%3D&trk=public_jobs_jserp-result_search-card",
        "description": "Exakis Nelite, entité du groupe\nMagellan Partners\n, est le\n1er partenaire pure-player Microsoft\nindépendant en France avec l’ambition de devenir le premier partenaire Européen et en Afrique Francophone avec sa forte présence au Maroc.\nNés du rapprochement de 2 leaders spécialistes de l’intégration des solutions Microsoft, nous allions expertise technique et fonctionnelle pour répondre concrètement aux enjeux de demain : accélération de la transformation digitale,\nCyberSécurité, Intelligence Artificielle, IoT, Data, transformation vers le cloud Azure, Services Cognitifs …\nEn rejoignant la communauté Exakis Nelite dans l’une de nos 12 agences (680 collaborateurs), vous intégrerez une équipe passionnée et impliquée dans les projets les plus innovants. Vous rejoindrez une structure construite autour de valeurs tournées vers ses collaborateurs : intelligence collective, convivialité et bienveillance.\nExakis Nelite a reçu la certification\nGreat Place to Work\net se place\n3ème de sa catégorie\nen 2024 parmi les entreprises où il fait bon travailler en France !\nÀ quoi ressembleront vos futures missions ?\nEn tant qu’Architecte et Conseil, dans les domaines Data et Business Intelligence, vous serez amené à travailler sur des projets d’envergure mettant à l’épreuve votre expérience des systèmes de données et votre ouverture vers les technologies de BI moderne et cloud.\nVotre rôle d’architecte et de conseil auprès de nos clients trouvera son sens dans la compétence que pourrez apporter autour des solutions Microsoft (Power BI, Azure…), et aussi dans la connaissance globale que vous aurez acquise par vos expériences variées. Cette combinaison compétence/expérience aura pour but d’orchestrer l’implémentation des technologies Microsoft dans des systèmes d’information et décisionnels technologiquement hétérogènes.\nVotre passion, votre curiosité et votre envie sont les maîtres mots pour réussir dans ce poste. Vous êtes motivé pour travailler dans un environnement dynamique où la donnée se décline autour de nos projets innovants (IoT, Industrie 4.0, IA…). Vous avez une vision claire des enjeux actuels autour de la donnée.\nDescription du poste\nSelon les missions vous serez amené à :\nAccompagner nos clients dans leur stratégie digitale\nAnimer des ateliers d’architecture technique\nAppréhender les besoins fonctionnels et les contraintes techniques du client\nPréconiser des architectures complexes pour répondre à une problématique ou un besoin métier\nDéfinir et améliorer les standards, patterns d’architecture et le catalogue de services\nSuperviser et mettre en œuvre, dans le cadre des projets, les préconisations techniques établies dans le cadre des cahiers des charges\nRéaliser l’architecture de données dans des environnements on Premise\nIntervenir sur l’architecture Azure data\nRédiger les documents associés (HLD, LLD, etc.)\nPiloter des projets et des hommes\nIntervenir en toute autonomie sur les phases de cadrage technique et/ou avant ventes\nAssurer une veille technologique\nProfil\nFort d’une expérience de 3 à 15 ans dans les domaines, Data, BI et Big Data, vous portez de l’intérêt aux technologies du Cloud, aux approches de BI moderne et à leur développement. Vous êtes un professionnel aguerri des environnements Data, de l’architecture et de l’utilisation des technologies Cloud.\nLa connaissance des environnements Microsoft (Power BI, SQL Server, Azure…) est un plus mais n’est pas une obligation. La diversité de vos expériences dans le champ d’activité Data/BI est le facteur clef de succès de ce poste.\nCurieux et dynamique, vous avez le gout du challenge et souhaitez prendre part au développement important d’Exakis Nelite et de Magellan Partners dans le domaine des Data-sciences.\nShow more\nShow less",
        "details": {
            "JobDetail": [],
            "TypeContract": "",
            "Salary": "",
            "Level": "",
            "Experience": "15 an(s)"
        },
        "title": "data architect",
        "skills": {
            "DataBase": [
                "SQL"
            ],
            "DataVisualisation": [
                "Power BI"
            ],
            "CloudComputing": [
                "Azure"
            ],
            "DBMS": [
                "SQL Server"
            ],
            "Other": [
                "Cloud",
                "Big Data"
            ]
        }
    },
    {
        "source": "LinkedIn",
        "company": "SIBIOS",
        "location": "Lyon, Auvergne-Rhône-Alpes, France",
        "link": "https://fr.linkedin.com/jobs/view/data-architect-manager-at-sibios-3881612188?position=10&pageNum=2&refId=s27%2F43wenQFDag2sabINKw%3D%3D&trackingId=VKlC%2FXFyXvWYWqlKEhzgWw%3D%3D&trk=public_jobs_jserp-result_search-card",
        "description": "SIBIOS recherche un consultant Senior DATA / ARCHITECT Manager avec minium 10 ans d'expérience pour un nouveau projet dans le secteur industriel.\nUne bonne connaissance d'architecture fonctionnelle et l'urbanisation data, ainsi que des règles de sécurité.\nVous avez une maîtrise de la gestion des données et des outils/langages correspondants (SQL, Power BI, modélisation et visualisation des données, ...)\nDiriger des projets Data sur divers domaines fonctionnels (Métier et IT) pour définir les feuilles de route.\nDéfinir la gouvernance de chaque projet et suivre le planning, le budget, la qualité et les risques sur chaque projet\nPiloter la gestion du changement et communiquer autour des projets\nIndustrialisation des innovations digitales : gouvernance, socle technique, documentation et support\nPour un entretien immédiat, merci de nous faire suivre votre cv mis á jour en word format ainsi que votre date de disponibilité et TJM.\nShow more\nShow less",
        "details": {
            "JobDetail": [
                "Senior"
            ],
            "TypeContract": "",
            "Salary": "",
            "Level": "",
            "Experience": "10 an(s)"
        },
        "title": "data architect",
        "skills": {
            "DataBase": [
                "SQL"
            ],
            "DataVisualisation": [
                "Power BI"
            ]
        }
    }
]