[
    {
        "source": "LinkedIn",
        "company": "Akademija Oxford",
        "location": "Boulogne-Billancourt, Île-de-France, France",
        "link": "https://fr.linkedin.com/jobs/view/data-analyst-at-akademija-oxford-3917868480?position=2&pageNum=0&refId=jBvsgtdGm8ta0dsilpa8wg%3D%3D&trackingId=2CwkzoUGCXsijBVJxieuIQ%3D%3D&trk=public_jobs_jserp-result_search-card",
        "description": "Nos collaborateurs travaillent au quotidien avec tous les métiers et avec notre réseau international. Et pour être au top de l’innovation, on a ce qui se fait de mieux en matière d’environnement de travail et d’outils technos : datalab, delta room, intelligence artificielle, machine learning…\nRésultats ? Une activité multipliée par 2 en 3 ans (et ce n’est pas fini), une expertise reconnue et une position de leader en France.\nBienvenue au cœur du big bang !\nShow more\nShow less",
        "details": {
            "JobDetail": [],
            "TypeContract": "",
            "Salary": "",
            "Level": "",
            "Experience": "3 an(s)"
        },
        "title": "data analyst",
        "skills": {
            "Other": [
                "Machine Learning"
            ]
        }
    },
    {
        "source": "LinkedIn",
        "company": "Akademija Oxford",
        "location": "Ille-et-Vilaine, Brittany, France",
        "link": "https://fr.linkedin.com/jobs/view/data-analyst-at-akademija-oxford-3917868488?position=3&pageNum=0&refId=jBvsgtdGm8ta0dsilpa8wg%3D%3D&trackingId=BNUusJQE4Ycib3V28fZ5xQ%3D%3D&trk=public_jobs_jserp-result_search-card",
        "description": "Diplômé(e) d’un bac+2 dans le secteur informatique et plus précisément dans le domaine du développement.\nDans le cadre d’un contrat d’apprentissage de 12 mois, nous recherchons pour l’un de nos partenaires, un Data Analyst qui souhaite apporter ses compétences techniques tout en faisant preuve d’un excellent savoir-être.\nShow more\nShow less",
        "details": {
            "JobDetail": [],
            "TypeContract": "",
            "Salary": "",
            "Level": "",
            "Experience": null
        },
        "title": "data analyst",
        "skills": {}
    },
    {
        "source": "LinkedIn",
        "company": "Akademija Oxford",
        "location": "Ille-et-Vilaine, Brittany, France",
        "link": "https://fr.linkedin.com/jobs/view/data-analyst-at-akademija-oxford-3917872056?position=4&pageNum=0&refId=jBvsgtdGm8ta0dsilpa8wg%3D%3D&trackingId=4oROEO4bVfHAu%2BQ%2FoSkdhg%3D%3D&trk=public_jobs_jserp-result_search-card",
        "description": "L’école Sup de Vinci, Rennes, accompagne l’une de ses entreprises partenaires dans son projet de recrutement d’un profil Big Data en alternance pour la rentrée de Septembre 2021.\nA noter : Sup de Vinci présentera à cette entreprise partenaire uniquement des candidats ayant passé les tests d’admission et qui seront admissibles dans son établissement.\nShow more\nShow less",
        "details": {
            "JobDetail": [],
            "TypeContract": "",
            "Salary": "",
            "Level": "",
            "Experience": null
        },
        "title": "data analyst",
        "skills": {
            "Other": [
                "Big Data"
            ]
        }
    },
    {
        "source": "LinkedIn",
        "company": "CHANEL",
        "location": "Neuilly-sur-Seine, Île-de-France, France",
        "link": "https://fr.linkedin.com/jobs/view/alternance-data-analyst-junior-anti-trafic-h-f-septembre-2024-at-chanel-3847615544?position=5&pageNum=0&refId=jBvsgtdGm8ta0dsilpa8wg%3D%3D&trackingId=4b3gXai5MwL697fpwKUrog%3D%3D&trk=public_jobs_jserp-result_search-card",
        "description": "Alternance Data Analyst Junior Anti-trafic (H/F) septembre 2024\nL'activité Parfums Beauté affirme sa singularité à travers une promesse : celle de révéler la beauté de chaque femme dans ce qu'elle a de plus singulier à travers son parfum, son maquillage et ses produits de soin. Cette philosophie est largement héritée de Mademoiselle Chanel, qui a toujours œuvré pour affirmer sa propre indépendance et celle de toutes les femmes.\nDescription de l'emploi :\nL’équipe Anti-trafic a pour mission de contribuer à protéger la marque CHANEL Parfums Beauté, ses consommateurs(rices) ainsi que ses distributeurs agréés en luttant au quotidien contre le marché gris.\nAu sein de cette équipe dynamique à taille humaine et dotée d’un scope mondial, rattaché(e) à la Chef de projet Amélioration continue, vous contribuerez au travail d’investigation, de consolidation et de qualification des informations et données du marché parallèle. Plongé(e) dans l’envers du décor d’une Maison de luxe, vous serez amené(e) à travailler en autonomie et à être force de proposition sur vos futures missions.\nÀ ce titre, vos missions sont les suivantes :\nGestion de la qualité des données de nos outils de pilotage et d’analyse :\nOutils internes :\nContrôle des informations saisies sur nos différentes bases de données\nRetraitement des données : garantir la fiabilité et la cohérence des données, réaliser les travaux de nettoyage correspondants avant transmission des rapports aux marchés\nAccompagnement de l’analyste produit dans la recherche/complétion des informations manquantes\nOutils externes :\nContrôle de l’intégrité et de la qualité des données fournies\nElaboration de propositions d'optimisation des jeux de données (format / structure des fichiers…)\nSuivi et développements BI\n:\nDéveloppement/Amélioration de rapports PBI en partenariat avec la chef de projet Data Junior\nAppui à l’amélioration des data set et de la data visualisation\nCréation et rédaction de guides utilisateurs à destination de l’équipe et de nos marchés\nSupport de l’équipe anti-trafic :\nAmélioration de la gestion documentaire en collaboration avec nos parties prenantes\nMission support auprès des chef de projet marchés pour l’aide au reporting\nParticipation à la vie de l’équipe\nPROFIL\nVous êtes en master et possédez les atouts nécessaires pour intégrer un environnement rigoureux et en constante évolution. Très organisée, la personnalité que nous recherchons est également curieuse et pro-active. Vous possédez une réelle appétence pour l’opérationnel et le croisement des données qualitatives et quantitatives. Excel et Power BI n’ont plus de secret pour vous et vous êtes à l’aise avec les autres modules de la suite Microsoft. Enfin, vous êtes à l’aise en anglais.\nLa connaissance du domaine et des enjeux de l’anti-trafic n’est pas nécessaire, vous serez formé(e) en interne par l’équipe avant de débuter vos missions.\nVous pouvez postuler en ligne sur Chanel.com, rubriques Carrières\nAlternance dès début septembre 2024 basée à Neuilly-sur-Seine.\nDe la singularité de chacun naît la richesse de nos équipes. CHANEL valorise la diversité sous toutes ses formes.\nShow more\nShow less",
        "details": {
            "JobDetail": [
                "Junior"
            ],
            "TypeContract": "",
            "Salary": "",
            "Level": "",
            "Experience": null
        },
        "title": "data analyst",
        "skills": {
            "DataVisualisation": [
                "Power BI"
            ],
            "Automation": [
                "Chef"
            ],
            "EnSoftSkils": [
                "Collaboration"
            ]
        }
    },
    {
        "source": "LinkedIn",
        "company": "Allianz France",
        "location": "Paris, Île-de-France, France",
        "link": "https://fr.linkedin.com/jobs/view/data-analyst-f-h-at-allianz-france-3909179361?position=6&pageNum=0&refId=jBvsgtdGm8ta0dsilpa8wg%3D%3D&trackingId=yrNle9v7%2FDyEOFZZYImtFg%3D%3D&trk=public_jobs_jserp-result_search-card",
        "description": "AIM Paris (Allianz Investment Management Paris), l’unité Investissement d’Allianz France, a la charge de la gestion des investissements des différentes entités d’Allianz France tant sur les portefeuilles d’actifs généraux qu’en unités de compte (UC), sur toute la chaîne de valeur des investissements, qui couvre la gestion actif-passif, la stratégie d'investissement, ainsi que la planification des revenus des investissements, le suivi des risques, le reporting et les opérations.\nLe rôle de l’équipe :\nPour soutenir ces activités, l’équipe AIM Finance & Opérations, en charge des données d’investissements, des reportings et du suivi des risques des investissements, est à la recherche d’un\nData Analyst\n. Ce dernier, rattaché hiérarchiquement à AIM Finance & Opérations, couvrira l’ensemble des besoins des différentes équipes d’AIM (AIM Investment Strategy, AIM Asset-Liability Management, AIM Finance) et interviendra de façon opérationnelle sur des projets de transformation locaux et Groupe.\nVoici vos principales missions :\n·\nL’automatisation\nde sourcing des données, des contrôles et des réconciliations entre différents systèmes d’informations\n·\nLe développement\nde macros/codes afin d’automatiser/optimiser les tâches\n·\nL’amélioration continue\ndes bases de données Investissements\n·\nLa fiabilisation et l’amélioration\ncontinue des bases de données\n·\nLa mise en place\nde nouveaux reportings (Power BI)\n·\nLe pilotage de projets\nen lien avec les initiatives groupes et locales\nVous travaillerez en lien étroit avec les autres équipes d'AIM France ainsi que les équipes AIM centrales à Munich. La maitrise de\nl’anglais\nest alors indispensable.\nVotre parcours :\nDiplômé(e) en informatique/gestion des données ou d’une école d’ingénieur (\nBAC +5),\nvous disposez d’une expérience significative dans la manipulation de données\n(5-10 ans).\nMaîtrise de plusieurs langages de développement du type\nPython, VBA, Access, SAS\nBonne maîtrise des outils bureautiques Powerpoint, Excel et VBA, et idéalement une première expérience significative dans l’utilisation d’outils de datavisualisation\n(Power BI)\nCapacité d’analyse et de synthèse, ouverture d’esprit, rigueur, organisation et autonomie,\nFrançais et\nanglais\nprofessionnel courants indispensables, à l’écrit comme à l’oral.\nVous aimez travailler en équipe dans une entreprise qui met ses collaborateurs au cœur de sa stratégie de développement ! Alors rejoignez-nous chez Allianz ! Toute l’équipe de Marwen NAJAR vous y attend !\nEn tant qu’entreprise reconnue et internationale, nous vous offrons des avantages attractifs tels qu’une flexibilité du temps de travail, le télétravail (3 jours par semaine), 9 semaines de congés, une restauration sur site, des taux préférentiels collaborateurs, des congés maternité et paternité élargis, des places en crèche et bien plus encore.\nEn tant qu’employeur, nous mettons tout en œuvre pour vous assurer un bien être propice à votre épanouissement.\nAllianz est la 1ère marque mondiale d'assurance présente dans 70 pays. Les #Allianzers, c'est 9.000 salariés en France qui accompagnent leurs clients tout au long de leur vie, des collaborateurs qui associent innovation, performance et agilité pour relever des défis permanents au quotidien. Parce qu'en nous préoccupant de l’avenir de nos collaborateurs, nous pouvons encore mieux nous préoccuper de l’avenir de tous nos clients. Pour cela, Allianz innove et met la technologie aux services des hommes pour préparer leur avenir, un avenir plus sûr.\nEn qualité d’employeur engagé, Allianz reconnaît que sa force se trouve dans la diversité de ses collaborateurs. Nous sommes fiers de promouvoir l’intégration et l’égalité des chances quel que soit le sexe, l’âge, l’origine, la nationalité, la religion, le handicap, ou l’orientation sexuelle de nos collaborateurs.\nAllianz, We secure your future !\nInformations complémentaires :\nPoste base à PARIS, La Défense, Métro Esplanade\nShow more\nShow less",
        "details": {
            "JobDetail": [],
            "TypeContract": "",
            "Salary": "",
            "Level": "",
            "Experience": "10 an(s)"
        },
        "title": "data analyst",
        "skills": {
            "ProgLanguage": [
                "Python"
            ],
            "DataVisualisation": [
                "Power BI"
            ]
        }
    },
    {
        "source": "LinkedIn",
        "company": "Akademija Oxford",
        "location": "Paris, Île-de-France, France",
        "link": "https://fr.linkedin.com/jobs/view/apprenti-e-data-analyst-at-akademija-oxford-3917871082?position=7&pageNum=0&refId=jBvsgtdGm8ta0dsilpa8wg%3D%3D&trackingId=wi9eB%2BVDDbZ4RDKHND%2BNug%3D%3D&trk=public_jobs_jserp-result_search-card",
        "description": "Un acteur du secteur voyage et tourisme basé à Paris recrute un.e Apprenti.e Data Analyst pour renforcer son équipe Développement & Business Stratégique. L’alternant.e sera positionné.e sur le suivi et le contrôle de l’activité de la direction. Le contrat commence en octobre 2021 pour une durée de 12 mois.\nShow more\nShow less",
        "details": {
            "JobDetail": [],
            "TypeContract": "",
            "Salary": "",
            "Level": "",
            "Experience": null
        },
        "title": "data analyst",
        "skills": {}
    },
    {
        "source": "LinkedIn",
        "company": "Akademija Oxford",
        "location": "Boulogne-Billancourt, Île-de-France, France",
        "link": "https://fr.linkedin.com/jobs/view/apprenti-data-analyst-h-f-at-akademija-oxford-3883289604?position=8&pageNum=0&refId=jBvsgtdGm8ta0dsilpa8wg%3D%3D&trackingId=zGSBVf05Ek5Tzxjbr54Bug%3D%3D&trk=public_jobs_jserp-result_search-card",
        "description": "Une de nos structures partenaires, acteur majeur du secteur des Télécommunications et situé dans les Hauts-De-Seine, recherche un Apprenti Data Analyst (H/F) préparant un bac +4/+5 spécialité Big Data à partir de Septembre 2021 et pour une durée d’un à deux ans.\nShow more\nShow less",
        "details": {
            "JobDetail": [],
            "TypeContract": "",
            "Salary": "",
            "Level": "",
            "Experience": null
        },
        "title": "data analyst",
        "skills": {
            "Other": [
                "Big Data"
            ]
        }
    },
    {
        "source": "LinkedIn",
        "company": "Unlimitail",
        "location": "Paris, Île-de-France, France",
        "link": "https://fr.linkedin.com/jobs/view/data-analyst-junior-at-unlimitail-3912999630?position=9&pageNum=0&refId=jBvsgtdGm8ta0dsilpa8wg%3D%3D&trackingId=ZjOVmytedKcnsKSQ0pQ%2FUQ%3D%3D&trk=public_jobs_jserp-result_search-card",
        "description": "Unlimitail\nis a joint venture between\nCarrefour\nGroup and\nPublicis\nGroup, intending to become the leader of the\nretail media market in Europe and Latin America\n. It combines the power of Carrefour Links' in-store and e-commerce assets and traffic with Publicis\nCitrus Ad and Epsilon's\non-site and off-site retail media technologies. The goal of Unlimitail is to become the premier retail media player in Continental Europe and South America for both in-store and digital channels.\nMissions\nWithin the Product team, your mission will be to participate in the development of Unlimitail’s analytics capabilities. Your environment will be millions of transactional data coming from major retailers on the market to analyze and improve the performance of online and offline marketing campaigns.\nAs we work with both retailers (providing media inventory) and brands (buying media inventory), you will have the opportunity to gain a deep understanding of the retail media ecosystem.\nYou will work with different teams (Ad Operations, Marketing, Sales) in different countries and on a wide variety of topics:\n- Perform e-commerce campaigns analysis to provide detailed insights\n- Conduct end-to-end ad hoc analysis to help retailers best monetize their inventory\n- Participate in the design and maintenance of databases, using SQL to store and manage data efficiently\n- Work on automating data analysis and data visualization capabilities\n- Work on Unlimitail’s customer lifetime value calculation capability\n- Participate in the development of new, cutting-edge abilities to create the best\nRequirements\n:\n· Master's degree in Data Analysis, business analytics, Computer Science, Statistics, Mathematics, Engineering, or a related field.\n· Data Analysis: Proven ability to analyze large datasets, identify trends, and extract actionable insights through using strong SQL skills for querying and data extraction.\n· Programming Languages: Python and SQL are mandatory. Any other is a plus\n· Data Visualization: previous experience in creating interactive and insightful visualizations, using tools like Power BI or Looker is a big plus\n· Knowledge of GCP or Azure environment is a plus\n· Problem-solving: Adept at approaching analytical problems and proposing effective solutions.\n· Good communication skills in English. Another language (Spanish, Portuguese) is a plus.\n· Strong team player with the ability to collaborate effectively\nBenefits\n:\n· 2 days of WFH\n· 90% reimbursement of public transportation fees\n· Office located in central Paris (Chatelet)\n· Swile card of 10€/working days\nShow more\nShow less",
        "details": {
            "JobDetail": [],
            "TypeContract": "",
            "Salary": "",
            "Level": "",
            "Experience": null
        },
        "title": "data analyst",
        "skills": {
            "ProgLanguage": [
                "Python"
            ],
            "DataBase": [
                "SQL"
            ],
            "DataVisualisation": [
                "Power BI"
            ],
            "CloudComputing": [
                "GCP",
                "Azure"
            ],
            "Collaboration": [
                "Teams"
            ],
            "EnSoftSkils": [
                "Communication"
            ]
        }
    },
    {
        "source": "LinkedIn",
        "company": "Orange Business",
        "location": "Lille",
        "link": "https://fr.linkedin.com/jobs/view/data-analyst-power-bi-f-h-at-orange-business-3916552634?position=10&pageNum=0&refId=jBvsgtdGm8ta0dsilpa8wg%3D%3D&trackingId=U4KAg6WLRoRLqVSKwDxsYw%3D%3D&trk=public_jobs_jserp-result_search-card",
        "description": "Missions\n:\nOrange Business, recherche pour son site de Lille, son futur Data Analyst Power BI pour rejoindre sa team Data.\nVotre quotidien ?\nEn intégrant Orange Business, vous pouvez participer à une grande diversité d’activités dans la Data. En voici un aperçu :\nAu démarrage du projet :\nRecueillir et analyser les besoins du client\nRédiger les spécifications fonctionnelles et techniques\nEstimer les charges\nPendant la phase de réalisation :\nConcevoir et développer des\nsolutions frontend BI à des fins analytics & dashboarding\nAccompagner les Métier dans la\ncompréhension des Analytics\net mise en oeuvre de solution \"data driven\"\nMettre en œuvre des solutions industrielles exploitables, mesurables et opérables\nCommuniquer et traduire les résultats complexes et leurs implications aux parties prenantes de l'entreprise\nCapitaliser sur les solutions pour créer de nouveaux produits, de nouveaux services et de nouvelles opportunités de digitalisation, de valorisation de la donnée\nCollaborer avec les data scientists et data ops dans la construction d'une culture axée sur les données\nEn fonction de votre évolution et de nos enjeux, vous pouvez aussi évoluer sur des missions transverses (conseil, coaching, avant-vente, formation, audit, etc.). La prise d’initiative est toujours la bienvenue !\nProfil\n:\nVous possédez 3 ans d'expérience ou plus autour d’écosystèmes BI. Vous maitrisez la chaîne de valeur du traitement de la donnée, vous savez intégrer les enjeux de sécurité des données\nVous\nmaîtrisez Power BI\non Cloud.\nVous avez acquis de l’expérience dans les outils BI et\ndata visualisation\n.\nAu-delà des connaissances techniques, nous recherchons quelqu’un de :\nDynamique et positif ;\nAyant soif d'apprendre et d'évoluer ;\nAimant relever les défis et être challengé pour progresser ;\nA l'écoute et aimant le travail collectif ;\nAimant partager avec l’équipe ses expertises et ses questions.\nShow more\nShow less",
        "details": {
            "JobDetail": [],
            "TypeContract": "",
            "Salary": "",
            "Level": "",
            "Experience": "3 an(s)"
        },
        "title": "data analyst",
        "skills": {
            "MachineLearning": [
                "Orange"
            ],
            "DataVisualisation": [
                "Power BI"
            ],
            "Other": [
                "Cloud"
            ],
            "EnSoftSkils": [
                "Initiative"
            ]
        }
    },
    {
        "source": "LinkedIn",
        "company": "Akademija Oxford",
        "location": "Ille-et-Vilaine, Brittany, France",
        "link": "https://fr.linkedin.com/jobs/view/data-analyst-en-alternance-at-akademija-oxford-3917867571?position=11&pageNum=0&refId=jBvsgtdGm8ta0dsilpa8wg%3D%3D&trackingId=n4ufLwBz1rqVmlUhHuwGWQ%3D%3D&trk=public_jobs_jserp-result_search-card",
        "description": "Vous avez envie d’intégrer une école à taille humaine ? Vous êtes intéressé.es par l’analyse et le traitement des données ? Sup de Vinci propose une formation complète, en bachelor Big Data.\nL’école Sup de Vinci, Rennes, accompagne l’une de ses entreprises partenaires dans son projet de recrutement d’un profil Big Data en alternance pour la rentrée de Septembre 2021.\nShow more\nShow less",
        "details": {
            "JobDetail": [],
            "TypeContract": "",
            "Salary": "",
            "Level": "",
            "Experience": null
        },
        "title": "data analyst",
        "skills": {
            "Other": [
                "Big Data"
            ]
        }
    },
    {
        "source": "LinkedIn",
        "company": "Technology & Strategy",
        "location": "Lyon, Auvergne-Rhône-Alpes, France",
        "link": "https://fr.linkedin.com/jobs/view/data-analyst-h-f-at-technology-strategy-3909691608?position=12&pageNum=0&refId=jBvsgtdGm8ta0dsilpa8wg%3D%3D&trackingId=rIGPfKv%2BBKfXZ19%2BAwYA7A%3D%3D&trk=public_jobs_jserp-result_search-card",
        "description": "Découvrez Novencia\n:\nExpert en Data et Intelligence Artificielle, nous aidons nos clients à exploiter et à valoriser leurs données sous toutes ses formes en les accompagnant sur des projets de Data Analyse, Data Gourvernance, Data Architecture, Data Science, et Data Engineering…\nVous avez une solide expérience de minimum 3 ans dans l'analyse des données et vous êtes à la recherche de nouveaux défis ? N'hésitez plus, la suite est pour vous !\nType de contrat : CDI\nDémarrage : Dès que possible\nLieu : Lyon\nDescription du poste\n:\nNous recherchons un Data Analyst expérimenté pour rejoindre notre équipe dynamique en région lyonnaise. Le candidat idéal devrait avoir une solide expérience dans l’analyse de données, ainsi que des compétences techniques en SQL, Python et Power BI (ou tout autre outil de visualisation de données).\nEn qualité de Data Anlayst (H/F)*, vous serez en charge de :\nCollecter, nettoyer et analyser des données commerciales provenant de différentes sources.\nCréer des rapports et des tableaux de bord pertinents pour les équipes opérationnelles et de gestion.\nIdentifier les tendances, les opportunités et les domaines d’amélioration à partir des données.\nCollaborer avec les équipes métier pour comprendre leurs besoins et fournir des analyses approfondies.\nPré-requis :\nExpérience professionnelle de minimum 3 ans en tant que Data Analyst.\nMaîtrise des langages SQL et Python pour l’extraction, la transformation et l’analyse des données.\nConnaissance approfondie de Power BI ou d’autres outils de visualisation de données.\nCapacité à travailler de manière autonome et à communiquer efficacement avec les parties prenantes.\nVous disposez des savoir-être suivants :\nAmbidextre : Agile à droite, Data à gauche\nCoordinateur.trice : manœuvre un projet et une équipe\nFin.e connaisseur.euse : alimente, reporte et conçoit des entrepôts de données\nDiplomate : résout les inévitables complexités de la réalisation d’un projet d’entreprise\nNégociateur.trice : met du tact dans chaque discussion\nTenace : un seul objectif, la satisfaction client\nNotre objectif commun est de co-construire votre carrière en fonction de vos aspirations et de vos compétences.\nContactez-moi en message privé ou par mail à s.ziki@technologyandstrategy.com !\nLet's make it possible #together\n*Nos postes sont ouverts aux personnes bénéficiant d’une Reconnaissance de la Qualité de Travailleur Handicapé (RQTH). T&S Groupe encourage la diversité et l’égalité sur le lieu de travail. Tous les candidats qualifiés H/F/* sont pris en considération pour un emploi sur un même pied d'égalité.\nShow more\nShow less",
        "details": {
            "JobDetail": [],
            "TypeContract": "CDI",
            "Salary": "",
            "Level": "",
            "Experience": "3 an(s)"
        },
        "title": "data analyst",
        "skills": {
            "ProgLanguage": [
                "Python"
            ],
            "DataBase": [
                "SQL"
            ],
            "DataVisualisation": [
                "Power BI"
            ]
        }
    },
    {
        "source": "LinkedIn",
        "company": "Avanty",
        "location": "Paris, Île-de-France, France",
        "link": "https://fr.linkedin.com/jobs/view/data-analyst-at-avanty-3908247423?position=13&pageNum=0&refId=jBvsgtdGm8ta0dsilpa8wg%3D%3D&trackingId=JB49bEdTFQzdJuewU%2BcDTA%3D%3D&trk=public_jobs_jserp-result_search-card",
        "description": "Avanty\nrecherche pour sa\nBusiness Unit\n–\nDigital & Technologique\n, des\nData Analyst\nspécialisés dans l’analyse de données, dont le rôle sera de comprendre les besoins de nos clients, les traduire via une spécification à l'attention des développeurs, les tester après développement pour finalement les valider avant mise en production.\nAvanty\nadresse l’ensemble des activités de banque, finance et assurance et propose un large périmètre de domaines d’intervention. Nos services s'articulent autour de\nl'expertise fonctionnelle métier\n, de\nl'apport\nméthodologique\n, de\nla\nmaîtrise\nde\nsolution\net de la\nréalisation\ntechnologique\n.\nAvanty\nemploie aujourd’hui\nune\ncentaine\nde\nconsultants\n. Nous intervenons auprès des plus grands comptes (BNP Paribas, Crédit Agricole, Société Générale, Natixis, …), pour les accompagner dans la réussite de leurs projets informatiques.\nNous rejoindre, c’est l’opportunité de grandir au quotidien au contact de votre consultant manager ou consultant directeur tout en étant acteur de votre carrière.\nVotre profil :\nDiplômé(e) Bac +3 à Bac +5 ayant un parcours ingénieur ou de formation Universitaire dans les domaines des statistiques, du traitement de l’information ou du big data, vous disposez d'une première expérience sur un similaire.\nVous disposez d’une expérience variée sur différents domaines et :\nVous êtes curieux et vous vous intéressez aux nouvelles tendances technologiques, à la digitalisation,\nVous avez d’excellentes capacités analytiques et de synthèse,\nFormation d’ingénieur complétée d’une formation data ou business intelligence,\nUne première expérience dans le domaine banque/finance est un véritable plus,\nVous avez un bon niveau d’anglais,\nVous êtes attiré par le dynamisme d’une structure en forte croissance,\nVous avez envie d’entreprendre, de construire et de transmettre auprès d’équipe et de clients à l’écoute.\nVous avez des compétences techniques sur un ou plusieurs domaines ci-dessous :\nExpertise en base de données et gestion de base de données (SQL/NoSQL)\nMaîtrise des tests et méthodes statistiques (segmentation, régression, forêt aléatoire)\nMaîtrise des langages de programmation (Python, R, C+)\nMaîtrise d’un outil de data visualisation (Tableau, Qlikview, PowerBI)\nMaîtrise des outils de fouille et analyse de données (Dataiku)\nNos missions :\nMise en place de datalake, datawarehouse, base de données relationnelles,\nExtraction des données\nMise en forme et structuration des données\nAnalyse et exploration des données\nInteraction avec les équipes métiers pour recueillir les besoins.\nAide le métier dans sa logique de prise de décision\nVeille technologique sur les outils d’analyse de données\nNos engagements :\nNous vous accompagnerons dans l'atteinte de vos objectifs professionnels en vous proposant un plan de carrière sur mesure, alliant mission et formation\nNos managers seront vos coachs pour vous accompagner vers cette transformation\nNos points forts :\nMissions intéressantes et diversité des comptes couverts.\nAbsence de commerciaux, management assuré par des consultants expérimentés\nTous les consultants en mission et sont en connexion avec la réalité mission.\nStructure à taille humaine et adossement aux forces du Groupe Ailancy.\nPlan de carrière personnalisé avec conseils de consultants expérimentés.\nFortes ambitions de croissance et opportunités de promotions internes.\nFormations sur mesure assurées par des consultants expérimentés.\nParticipation au développement du cabinet et promotion des initiatives.\nPossibilité d'être formateur et variété fonctionnelle.\nL’inter-staffing est une période idéale pour se former ou participer au rayonnement de la structure.\nPossibilité de renforcer son expertise et évoluer à un grade d’expert.\nSensibilisation à la RSE.\nShow more\nShow less",
        "details": {
            "JobDetail": [],
            "TypeContract": "",
            "Salary": "",
            "Level": "",
            "Experience": null
        },
        "title": "data analyst",
        "skills": {
            "ProgLanguage": [
                "R",
                "Python"
            ],
            "DataBase": [
                "SQL",
                "NoSQL"
            ],
            "DataAnalytics": [
                "R"
            ],
            "DataVisualisation": [
                "Tableau"
            ],
            "Other": [
                "Statistiques",
                "Big Data"
            ]
        }
    },
    {
        "source": "LinkedIn",
        "company": "Coders Connect",
        "location": "Paris, Île-de-France, France",
        "link": "https://fr.linkedin.com/jobs/view/data-analyst-at-coders-connect-3870416610?position=14&pageNum=0&refId=jBvsgtdGm8ta0dsilpa8wg%3D%3D&trackingId=jYpRadvx5qpmZlADXbNSKQ%3D%3D&trk=public_jobs_jserp-result_search-card",
        "description": "Coders Connect and Sanofi are joining forces to bring an electrifying twist to the biopharmaceutical world!\nWork with a rhythm that suits your style (2 days remote and 3 days onsite magic).\nLanguage:\nProficiency in English is required for this role to ensure effective communication within our diverse, global team.\nAbout Sanofi:\nWe're not just a company; we're a global movement, focused on human health and making a real difference. Our mission? To battle pain, ease suffering, and sprinkle a little bit of magic in the process by developing life-changing medicines and vaccines through breakthrough science and wizard-level technology.\nDigital & Data: The Pulse of Our Mission\nAt the heart of our quest lies our digital and data powerhouse. Think of us as the digital healthcare platform of your dreams, where innovation meets speed, and technology shakes hands with medicine. With our scale, deep-rooted connections in health ecosystems worldwide, and a knack for pushing boundaries, we're here to revolutionize medicine, one digital solution at a time.\nYour Quest as a Data Analyst:\nEmbark on an adventure where your data wizardry helps unlock new horizons in drug discovery and trial efficiency. Your role is pivotal—melding analysis with creativity to illuminate the path forward with insights gleaned from data. Your canvas? A world of complex data sets waiting for your exploratory magic and analytical prowess.\nRequirements\nYour Spellbook Includes:\nData Alchemy: Transform raw data into insights that shape future solutions. You're the master of extracting, cleaning, and interpreting data, finding stories in the numbers that others might miss.\nCollaboration Charms: Work your magic across realms, aligning stakeholders with the stardust of enterprise data models and definitions. Your mission is to weave consensus and drive the adoption of data management standards that resonate across Sanofi.\nVisionary Insight: Recommend KPIs, craft reports, and monitor the adoption of data practices that ensure Sanofi's data remains a beacon of quality, usability, and security.\nYour Arsenal:\nA robust understanding of the mystical arts of databases, data structures, and the tools that keep the data realm in order.\nProficiency in SQL, Python, and a knack for visual storytelling through Tableau, PowerBI, or other visual sorcery.\nA curious mind driven by the quest for knowledge and a passion for solving the puzzles of privacy laws and data compliance.\nThe Reward:\nA chance to play a crucial role in a collaboration that's redefining healthcare through digital transformation.\nA seat at the round table of diversity and inclusion, where different backgrounds and experiences conjure the richness of our culture.\nAn endless horizon of professional growth, learning opportunities, and the chance to contribute to a future where better health is a global reality.\nThe Call to Adventure:\nIf you're ready to join a quest for better – better treatments, better outcomes, and better science – and believe in the magic of bringing diverse talents together to make miracles happen, we want you. Let's embark on this journey together and transform the future of healthcare.\nBetter is out there. Are you ready to find it with us?\nShow more\nShow less",
        "details": {
            "JobDetail": [
                "Remote"
            ],
            "TypeContract": "",
            "Salary": "",
            "Level": "",
            "Experience": null
        },
        "title": "data analyst",
        "skills": {
            "ProgLanguage": [
                "Python"
            ],
            "DataBase": [
                "SQL"
            ],
            "DataVisualisation": [
                "Tableau"
            ],
            "EnSoftSkils": [
                "Creativity",
                "Communication",
                "Collaboration"
            ]
        }
    },
    {
        "source": "LinkedIn",
        "company": "Mobilize Financial Services",
        "location": "Paris, Île-de-France, France",
        "link": "https://fr.linkedin.com/jobs/view/business-data-analyst-h-f-at-mobilize-financial-services-3904096866?position=15&pageNum=0&refId=jBvsgtdGm8ta0dsilpa8wg%3D%3D&trackingId=wGmLWi9AJQuurhQ0iaRHwA%3D%3D&trk=public_jobs_jserp-result_search-card",
        "description": "🚗 En route vers Mobilize !\nA l’écoute de tous nos clients, nous créons des services financiers innovants pour construire une mobilité durable pour tous.\nRejoindre Mobilize Financial Services,\nc’est d’abord choisir d’intégrer un groupe international\n, filiale de Renault Group, une banque de financement solide, partenaire des constructeurs Renault–Mitsubishi (Renault, Dacia, Alpine, Renault Samsung Motors, Mobilize, Infiniti, Datsun, et Mitsubishi Motors) dans plusieurs pays. Nos 4 000 collaborateurs présents dans 36 pays, agissent ensemble au service de nos clients.\nNous proposons à nos clients - particuliers comme professionnels - les financements et les services les plus adaptés pour les véhicules neufs et d'occasion.\nNous finançons également l'\nactivité des réseaux de concessionnaires\ndes marques du groupe Renault et nous veillons à faciliter leur gestion au quotidien pour leur permettre de développer leurs ventes et assurer leur pérennité financière.\nEn 2022, le groupe a financé plus de\n1,2 millions de dossiers\n(véhicules neufs et véhicules d’occasion) et vendu\n3,8 millions de services\n. Nous proposons également des\noffres d’épargne\ndans 7 pays.\nNotre entreprise se \"MOBILIZE\" en faveur de la\ndiversité\nculturelle, l'égalité hommes-femmes et l'intégration de personnes en situation de Handicap, au travers notamment de notre Chartre. Nous favorisons un environnement de travail où les différences individuelles sont reconnues, appréciées, respectées et valorisées, de façon à développer les talents et les forces de chacun.\nEnfin, nous bénéficions au sein du groupe d’une forte\npolitique de mobilité\n: les possibilités d’évolution sont donc multiples et variées.\n🚘Prenez le volant ! Pas de routine, tous nos itinéraires sont différents !\nIn the Data Factory Team, reporting to the Data Management Director, the Business Analyst is the proxy Product Owner inside the Data Factory and internal Head of Project. He/She has to :\nSupport MFS internal clients (countries and corporate functions) in their data projects, help them express their needs, advise and guide them on possible solutions:\nCommunicate and promote Data Platform solutions in the different subsidiaries and in Corporate\nFoster the identification of Data Platform use-cases opportunities and added values for business\nEnsure the consistency of Data Platform projects, their alignment with strategy and their compliance (data privacy, data governance, security…)\nIdentify the potentials adherences between the Data platform projects and make propositions accordingly (grouping, carry over , prioritization...)\nTransform clients needs in functional requirements, produce the appropriate documentation for Go/No Go decision, prioritization and development\nSteer and follow Data projects, on QCD axis, from framing to go live, in Agile method\nEnsure compliance and its auditability with Data project methodology and delivery of project documentation\nEnsure, all along the projects, actions coordination between the different stakeholders, in Corporate and in Subsidiaries: Project Owner, Data Governance, Data Privacy, Data Factory (Data Engineering, Data Science, IT & Data Architecture) and the businesses involved such as marketing, digital, regulatory, financials & controlling\nDefine and follow the QCD KPI’s and report the progress of the projects he/she is in charge of\nEnsure the business validation of the finished products\nEnsure training and operational usage of the finished products\nGuarantee the finished products from delivery in production to serial life management\nDetailed responsibilities\nFrame the Data Platform use cases for the Go/No Go decision and prioritization\nEnsure that the projects prerequisites are met\nEnsure each project KPIs will be measurable and measured\nFormalize through the business requirements documentation, the business need and the different features to set up\nTake the project to Data Factory and Data Office\nChallenge, validate or invalidate the solution and the schedule proposed\nRoll out the different project phases he/she is in charge of, from framing to go live, on QCD axis, following the methodology applied to Data Factory project (agile method) and coordinating stakeholders actions\nSteer project committees and comitology\nPrepare projects reporting for steering committees to present QCD KPIs he has built and followed\nSet up test plans and follow their roll out\nEnsure the proper delivery in production of the finished product\nEnsure training and operational usage of the finished products\nEnsure the maintenance of the finished product\nEnsure that the project documentation has been created in accordance with Data Factory method\nPrepare all necessary presentation of the project\nPropose methodological modifications\nRequired skills / required experience\nFluent English\nBasic SQL Level : ability to perform simple requests\nData analysis skills\nProject management or Project owner support experience required\nExcellent written and verbal communication skills\nBusiness process analysis and data analysis appetence\nAnimation, coordination, and teamwork appetence\nSynthetic spirit, organization and pedagogy required\nKnowledge of the banking, insurance, automobile sectors appreciated\nKnowledge or appetence for Big Data technologies, AI, Data engineering and Data Science appreciated\nKnowledge or appetence for Agile method and related tools\nPack Office mastery\nPourquoi nous rejoindre ? Votre Pack confort est composé de nombreux avantages 😀 :\nUn environnement de travail moderne et convivial\n: locaux agréables, CSE dynamique avec de nombreuses offres (voyages, sport, famille) et, selon les sites, salle de sport, restaurant d’entreprise ou tickets restaurant, ainsi qu’un parking\nNous sommes mobilisés pour développer la qualité de vie au travail de nos collaborateurs en faisant évoluer nos façons de travailler (méthodes, outils, organisation du travail…) et nous sommes fiers d’être\ncertifiés ⭐Great Place To Work ⭐\nPossibilité de\ntélétravailler 2/3 jours par semaine\nRemboursement à hauteur de\n75% des frais d’abonnement aux transports publics\nou forfait de transport mensuel selon le mode de locomotion\nNos locaux sont situés à\nParis Grands Boulevards\n❗ Mobilize Financial Services déménage ❗ Les postes à pourvoir en région parisienne seront tous basés à Boulogne Billancourt en 2026.\nShow more\nShow less",
        "details": {
            "JobDetail": [],
            "TypeContract": "",
            "Salary": "",
            "Level": "",
            "Experience": null
        },
        "title": "data analyst",
        "skills": {
            "DataBase": [
                "SQL"
            ],
            "Other": [
                "Big Data"
            ],
            "EnSoftSkils": [
                "Teamwork",
                "Communication",
                "Organization"
            ]
        }
    },
    {
        "source": "LinkedIn",
        "company": "Technology & Strategy",
        "location": "Paris, Île-de-France, France",
        "link": "https://fr.linkedin.com/jobs/view/data-analyst-h-f-at-technology-strategy-3909686864?position=16&pageNum=0&refId=jBvsgtdGm8ta0dsilpa8wg%3D%3D&trackingId=opO%2B6UiSrxYNp3pGtR%2B0Ow%3D%3D&trk=public_jobs_jserp-result_search-card",
        "description": "Découvrez Novencia\n:\nExpert en Data et Intelligence Artificielle, nous aidons nos clients à exploiter et à valoriser leurs données sous toutes ses formes en les accompagnant sur des projets de Data Analyse, Data Gourvernance, Data Architecture, Data Science, et Data Engineering…\nVous avez une solide expérience de minimum 4 ans dans l'analyse des données et vous êtes à la recherche de nouveaux défis ? Bouclez votre ceinture, la suite est pour vous !\nType de contrat : CDI\nDémarrage : Dès que possible\nLieu : Paris\nDescription du poste :\nNous recherchons un Data Analyst expérimenté pour rejoindre notre équipe dynamique en région parisienne. Le candidat idéal devrait avoir une solide expérience dans l’analyse de données, ainsi que des compétences techniques en SQL, Python et Power BI (ou tout autre outil de visualisation de données).\nEn qualité de Data Anlayst (H/F)*, vous serez en charge de :\nCollecter, nettoyer et analyser des données commerciales provenant de différentes sources.\nCréer des rapports et des tableaux de bord pertinents pour les équipes opérationnelles et de gestion.\nIdentifier les tendances, les opportunités et les domaines d’amélioration à partir des données.\nCollaborer avec les équipes métier pour comprendre leurs besoins et fournir des analyses approfondies.\nPré-requis :\nExpérience professionnelle de 4 à 5 ans en tant que Data Analyst.\nMaîtrise des langages SQL et Python pour l’extraction, la transformation et l’analyse des données.\nConnaissance approfondie de Power BI ou d’autres outils de visualisation de données.\nCapacité à travailler de manière autonome et à communiquer efficacement avec les parties prenantes.\nVous disposez des savoir-être suivants :\nAmbidextre : Agile à droite, Data à gauche\nCoordinateur.trice : manœuvre un projet et une équipe\nFin.e connaisseur.euse : alimente, reporte et conçoit des entrepôts de données\nDiplomate : résout les inévitables complexités de la réalisation d’un projet d’entreprise\nNégociateur.trice : met du tact dans chaque discussion\nTenace : un seul objectif, la satisfaction client\nNotre objectif commun est de co-construire votre carrière en fonction de vos aspirations et de vos compétences.\nContactez-moi en message privé ou par mail à s.ziki@technologyandstrategy.com !\nLet's make it possible #together\n*Nos postes sont ouverts aux personnes bénéficiant d’une Reconnaissance de la Qualité de Travailleur Handicapé (RQTH). T&S Groupe encourage la diversité et l’égalité sur le lieu de travail. Tous les candidats qualifiés H/F/* sont pris en considération pour un emploi sur un même pied d'égalité.\nShow more\nShow less",
        "details": {
            "JobDetail": [],
            "TypeContract": "CDI",
            "Salary": "",
            "Level": "",
            "Experience": "4 an(s)"
        },
        "title": "data analyst",
        "skills": {
            "ProgLanguage": [
                "Python"
            ],
            "DataBase": [
                "SQL"
            ],
            "DataVisualisation": [
                "Power BI"
            ]
        }
    },
    {
        "source": "LinkedIn",
        "company": "Inetum",
        "location": "Lille, Hauts-de-France, France",
        "link": "https://fr.linkedin.com/jobs/view/data-analyst-h-f-at-inetum-3843955768?position=17&pageNum=0&refId=jBvsgtdGm8ta0dsilpa8wg%3D%3D&trackingId=WgqQmxF94rwdsVuRDQwLFQ%3D%3D&trk=public_jobs_jserp-result_search-card",
        "description": "Détail de l'offre\nInformations générales\nEntité de rattachement\nInetum est un leader européen des services numériques. Pour les entreprises, les acteurs publics et la société dans son ensemble, les 28 000 consultants et spécialistes du groupe visent chaque jour l'impact digital des solutions qui contribuent à la performance, à l'innovation et au bien commun.\nPrésent dans 19 pays au plus près des territoires, et avec ses grands partenaires éditeurs de logiciels, Inetum répond aux enjeux de la transformation digitale avec proximité et flexibilité.\nPorté par son ambition de croissance et d'industrialisation, Inetum a généré en 2023 un chiffre d'affaires de 2,5 milliards d'€.\nPour répondre à un marché en croissance continue depuis plus de 30ans, Inetum a fait le choix délibéré de se recentrer sur 4 métiers afin de gagner en puissance et proposer des solutions sur mesure, adaptées aux besoins spécifiques de ses clients le conseil (Inetum Consulting), la gestion des infrastructures et applications à façon (Inetum Technologies), l'implémentation de progiciels (Inetum Solutions) et sa propre activité d'éditeur de logiciels (Inetum Software). Inetum a conclu des partenariats stratégiques avec 4 grands éditeurs mondiaux - Salesforce, ServiceNow, Microsoft et SAP et poursuit une stratégie d'acquisitions dédiée afin d'entrer dans le top 5 européen sur ces technologies et proposer la meilleure expertise à ses clients.\nTous nos postes sont ouverts aux personnes en situation de handicap.\nDescription du poste\nMétier\nApplications Delivery - Software Development\nIntitulé du poste\nData Analyst H/F\nContrat\nCDI\nDescription De La Mission\nDans le cadre de la croissance de notre agence lilloise, nous développons notre Practice Data et recrutons des profils Data de divers horizons Data Analyst, Data Engineer, Data Scientist et Data Gouv. Les besoins métiers de nos clients et la multitude des technologies font qu'il nous faut nous appuyer sur une diversité de compétences. Vous pourriez être l’un d’eux et rejoindre Inetum.\nEn tant que Data Analyst, vos principales missions consistent à\nAnalyser et retranscrire le besoin client\nIdentifier, extraire et exploiter les sources d'acquisition de données les plus pertinentes\nValoriser de la donnée\nDévelopper l'outil de data visualisation pour accompagner les équipes métiers dans leurs aides à la décision\nÊtre le lien entre les équipes métier pour les accompagner dans la mise en œuvre des nouveaux outils\nProfil\nPour mener à bien votre rôle, il vous faut\nparler SQL couramment\nun niveau avancé sur Excel et/ou Google Spreadsheet\nune maîtrise d'un outil décisionnel comme PowerBI, Qlik, Tableau ou encore Google Data Studio\nVous vous reconnaissez dans ces quelques lignes, alors rencontrons-nous !\nNotre plus\nRejoindre la région Nord-Est, c’est bénéficier des avantages d’un Grand Groupe tout en gardant la proximité régionale.\nNous mettrons tout en œuvre pour vous apporter un équilibre vie perso / vie pro. C’est pourquoi nous vous proposons un rythme hybride (selon les contraintes clients)\nUne trajectoire de carrière personnalisée et adaptée à vos souhaits d'évolution grâce à une implantation à l’international (26 pays, 7 Fablab), des formations ciblées et des projets couvrant l’ensemble de la chaîne de valeur IT (+25 filières métiers)\nIntégrer un collectif d’experts partageant des valeurs de solidarité et d’excellence\nIntégrer une entreprise ayant une stratégie affirmée de certifications de ses collaborateurs\nLocalisation du poste\nLocalisation du poste\nFrance, Nord, 59 Nord\nVille\nLille\nCritères candidat\nNiveau d'études min. requis\nBac+5\nNiveau d'expérience min. requis\nPlus de 2 ans\nShow more\nShow less",
        "details": {
            "JobDetail": [
                "Hybride"
            ],
            "TypeContract": "CDI",
            "Salary": "",
            "Level": "Bac+5",
            "Experience": "30 an(s)"
        },
        "title": "data analyst",
        "skills": {
            "DataBase": [
                "SQL"
            ],
            "DataVisualisation": [
                "Tableau"
            ]
        }
    },
    {
        "source": "LinkedIn",
        "company": "CGI",
        "location": "Niort, Nouvelle-Aquitaine, France",
        "link": "https://fr.linkedin.com/jobs/view/data-analyst-f-h-at-cgi-3902408459?position=18&pageNum=0&refId=jBvsgtdGm8ta0dsilpa8wg%3D%3D&trackingId=M3XvIQC%2B%2F604IhMHyZgJxg%3D%3D&trk=public_jobs_jserp-result_search-card",
        "description": "Big Data, Data Science, Data analyse, Data architecture ... Ça n’a pas de secret pour vous ?\nQue vous commenciez votre carrière professionnelle ou que vous soyez spécialiste de l’une de ces disciplines, intégrer notre communauté Data, c’est l’assurance de progresser, innover, partager, vous certifier et rendre service à nos clients.\nSi vous souhaitez intégrer nos équipes à Niort et accompagner les plus grands acteurs du secteur des Assurances, cette annonce est susceptible de vous intéresser.\nEn tant que Data Analyst dans le secteur assurantiel, votre rôle principal sera d'analyser et d'interpréter des données pour fournir des informations stratégiques et opérationnelles permettant d'améliorer la prise de décision et la performance de l'entreprise.\nFonctions et responsabilités\nVos responsabilités seront les suivantes:\n-Collecter et Préparer les données provenant de diverses sources internes et externes.\n-Assurer la qualité et la fiabilité des données en nettoyant et en transformant les données brutes.\n-Analyser les données\n-Créer des Tableaux de Bord et Rapports\n-Effectuer des modélisation Prédictive\n-Analyser les Performances\n-Travailler en étroite collaboration avec les équipes actuarielles\n-Surveiller des Tendances du Marché\n-Veiller à ce que toutes les activités d'analyse de données soient conformes aux normes de sécurité des données et aux réglementations en vigueur, telles que le RGPD.\nEn rejoignant CGI, vous bénéficiez notamment d’une offre complète de formations (techniques, métiers, développement personnel,…), de flexibilité grâce à notre accord télétravail (jusqu’à 3 jours de télétravail par semaine), d’une politique de congés avantageuse (27 jours de congés payés, RTT, congés ancienneté et enfant malade,…) et d’un package d’avantages intéressant (régime d’achats d’actions, participation, CSE,...).\nQualités requises pour réussir dans ce rôle\nAyant une première expérience en Data, vous maitrisez les technologies suivantes:\n-Les langages de programmation et de requêtage tels que Python, R, SAS et SQL.\n-Solides compétences en analyse statistique et en modélisation de données, en particulier dans un environnement SAS.\n-Expérience avec des outils de Business Intelligence tels que Tableau, Power BI, QlikView, etc.\nConnaissance approfondie des techniques d'apprentissage automatique et de l'analyse.\nCGI est un employeur inclusif et attentif aux candidatures des personnes en situation de handicap, à l’évolution de carrières des hommes et des femmes et au bien-être de nos salariés LGBT+. Dans un souci d’accessibilité et de clarté, le point médian n’est pas utilisé dans cette annonce. Tous les termes employés se réfèrent aussi bien au genre féminin que masculin.\nShow more\nShow less",
        "details": {
            "JobDetail": [],
            "TypeContract": "",
            "Salary": "Package",
            "Level": "",
            "Experience": null
        },
        "title": "data analyst",
        "skills": {
            "ProgLanguage": [
                "R",
                "Python"
            ],
            "DataBase": [
                "SQL"
            ],
            "DataAnalytics": [
                "R"
            ],
            "DataVisualisation": [
                "Power BI",
                "Tableau"
            ],
            "Other": [
                "Big Data"
            ],
            "EnSoftSkils": [
                "Collaboration"
            ]
        }
    },
    {
        "source": "LinkedIn",
        "company": "Lagardère Travel Retail",
        "location": "Levallois-Perret, Île-de-France, France",
        "link": "https://fr.linkedin.com/jobs/view/junior-data-analyst-h-f-alternance-septembre-2024-at-lagard%C3%A8re-travel-retail-3909162343?position=19&pageNum=0&refId=jBvsgtdGm8ta0dsilpa8wg%3D%3D&trackingId=WN4Sw3FzYfhTb4FpadsoCw%3D%3D&trk=public_jobs_jserp-result_search-card",
        "description": "Lagardère Travel Retail est l’un des leaders mondiaux du Travel Retail, au service des passager.e.s dans les aéroports, les gares et autres concessions dans 42 pays. L'une des deux divisions du groupe Lagardère, Lagardère Travel Retail répond aux besoins des passager.e.s et des concédants de façon holistique à travers un réseau de plus de 5 000 points de vente Travel Essentials, Duty Free & Fashion et Foodservice. Le groupe s’est engagé à créer des expériences de voyage plus responsables dans le cadre de sa stratégie RSE (P.E.P.S) ainsi qu’à contribuer à la neutralité carbone globale d'ici fin 2023. En 2022, Lagardère Travel Retail a réalisé un chiffre d'affaires de 5.2 milliards d'euros.\nRattaché.e à la Direction Commercial Development & Transformation, vous intègrerez notre équipe de Supply-Chain Controller.\nA ce titre, vos principales missions seront les suivantes\n1/ Support sur le projet Datafactory\n- Réaliser les guides utilisateurs des dashboards;\n- Devenir le support technique aux utilisateurs;\n- Contrôler la qualité des données (versus BW / entre dashboards);\n- Gérer l’évolution de dashbaords suite à validation en comité key users.\n2/ Développement de nouveaux dashboards en support à l’équipe supply chain\n- Contribuer à la rédaction des cahiers des charges en fonction des besoins récoltés;\n- Être l’interface entre l’IT et la Supply Chain pour la constitution de nouveaux reportings;\n- Contribuer au développement des tableaux de bord avec une IHM adaptée aux utilisateurs;\n- Apporter un support à la conduite du changement pour l'appropriation de l'outil par les opérationnels (formation, accompagnement des utilisateurs);\n- Mettre à jour les modes opératoires et la documentation technique.\n3/ Data analytics/ Data science\n- Participer à des sujets exploratoires « big data » en R ou Python.\nProfil :\nActuellement en Master en école de commerce/d'ingénieur ou en université avec une spécialisation en data science, vous recherchez une alternance de deux ans dès septembre 2024. Vous justifiez idéalement d’une première expérience dans la data science.\nVous avez un niveau d’anglais courant à l'écrit comme à l'oral.\nVous maitrisez les outils de bureautiques (Pack office), la maitrise de SAP Hana/BI4/ Power BI est un plus.\nVous êtes autonome et rigoureux.se, motivé.e et organisé.e, avec un fort esprit d’analyse et de synthèse pour aborder des sujets très divers.\nNous croyons que l’inclusion et la diversité sont essentielles à la réussite des entreprises et des personnes. Chez Lagardère Travel Retail, nous nous engageons à créer un environnement de travail dans lequel nos collaborateur.rice.s peuvent réaliser leur potentiel et être eux.elles-mêmes, et à soutenir chacun.e d'entre eux.elles dans la réalisation de ses ambitions. Nous accueillons et prenons en considération toutes les candidatures, quel que soit leur profil, et garantissons un traitement juste et équitable à tou.te.s les candidat.e.s.\nShow more\nShow less",
        "details": {
            "JobDetail": [],
            "TypeContract": "",
            "Salary": "",
            "Level": "",
            "Experience": null
        },
        "title": "data analyst",
        "skills": {
            "ProgLanguage": [
                "R",
                "Python"
            ],
            "DataAnalytics": [
                "R"
            ],
            "DataVisualisation": [
                "Power BI"
            ],
            "Other": [
                "Big Data"
            ]
        }
    },
    {
        "source": "LinkedIn",
        "company": "Ayming",
        "location": "Lyon, Auvergne-Rhône-Alpes, France",
        "link": "https://fr.linkedin.com/jobs/view/data-analyst-h-f-at-ayming-3896616843?position=20&pageNum=0&refId=jBvsgtdGm8ta0dsilpa8wg%3D%3D&trackingId=%2FhGBgzTh07dgLybaGD38hA%3D%3D&trk=public_jobs_jserp-result_search-card",
        "description": "Votre job\nVotre job\nQuelles sont vos missions chez Ayming ?\nAu sein de notre activité de Conseil en Financement de l’Innovation, vous êtes en support aux équipes consulting Innovation France\nVous êtes membre du « CSP » : Centre de Services Partagés.\nVos missions seront les suivantes :\nEn tant que référent d’une équipe, vous gérez et contribuez à la fiabilisation des datas Equipe (affectation des ressources missions, préparation de la facturation, co-gestion des stocks (factu et CA)\nAssurer le support aux équipes sur les outils\nIntervenir sur le suivi de certains indicateurs\nVos talents et aspirations professionnelles\nVous avez :\nUne formation Bac ou Bac +2 dans la gestion (débutant accepté)\nUne très bonne maîtrise du VBA, python, SQL\nEnvie d’intégrer une entreprise dynamique et leader dans son secteur d’activité\nLe sens des priorités et le sens du service\nUne approche pédagogique\nL’esprit d’équipe et le goût du challenge\nUn bon relationnel client\nLa capacité à traiter diverses tâches annexes\nVous êtes :\nOrganisé, rigoureux, curieux et autonome\nEngagé et impliqué\nForce de proposition\nSi vous devenez un Aymer ?\nVous bénéficierez :\nBien-être au travail et carrière\nD’une diversité de projets et d’environnements métiers et géographiques\nBien-être au travail et carrière\nD’une politique de développement de votre potentiel au travers de notre Ayming Academy et Ayming Digital Academy\nUn programme d’évolution de carrière au travers de nos accompagnements RH « My Professionnal Journey »\nDe notre Nouvelle Vie au travail : flexibilité, espaces créativité et conviviaux, 108 jours de télétravail par an\nDes moments de rencontre lors d’événements tout au long de l‘année\nPackage de rémunération et avantages sociaux\nRémunération fixe et variable selon profil\nStatut employé\nSoutien à la parentalité\nVotre recruteur\nRachid BELHOCINE\nPostuler Envoyer à un(e) ami(e) ›\nPartager cette publication\nPostuler Envoyer à un(e) ami(e) ›\nNom *\nPrénom *\nEmail *\nJe suis intéressé par :\nTéléchargement de votre CV * Types de fichiers acceptés : pdf, doc, rtf, txt, docx, odt, jpg, Taille max. des fichiers : 24 MB.\n*\nJ'accepte qu'Ayming traite mes données personnelles pour gérer ma candidature dans les conditions détaillées au sein de la Politique RH .\nNous vous rappelons que vous disposez d'un droit d'accès, de rectification, de suppression, de limitation, de portabilité ainsi qu'un droit d'opposition au traitement de vos données. Pour exercer ces droits, vous pouvez adresser une demande à : contact@ayming.com.\nShow more\nShow less",
        "details": {
            "JobDetail": [],
            "TypeContract": "",
            "Salary": "24",
            "Level": "",
            "Experience": null
        },
        "title": "data analyst",
        "skills": {
            "ProgLanguage": [
                "Python"
            ],
            "DataBase": [
                "SQL"
            ]
        }
    },
    {
        "source": "LinkedIn",
        "company": "Ayming",
        "location": "Levallois-Perret, Île-de-France, France",
        "link": "https://fr.linkedin.com/jobs/view/data-analyst-h-f-at-ayming-3896616845?position=21&pageNum=0&refId=jBvsgtdGm8ta0dsilpa8wg%3D%3D&trackingId=pWjSk%2BK7uxcdfSBSld7cmg%3D%3D&trk=public_jobs_jserp-result_search-card",
        "description": "Votre job\nVotre job\nQuelles sont vos missions chez Ayming ?\nAu sein de notre activité de Conseil en Financement de l’Innovation, vous êtes en support aux équipes consulting Innovation France\nVous êtes membre du « CSP » : Centre de Services Partagés.\nVos missions seront les suivantes :\nEn tant que référent d’une équipe, vous gérez et contribuez à la fiabilisation des datas Equipe (affectation des ressources missions, préparation de la facturation, co-gestion des stocks (factu et CA)\nAssurer le support aux équipes sur les outils\nIntervenir sur le suivi de certains indicateurs\nVos talents et aspirations professionnelles\nVous avez :\nUne formation Bac ou Bac +2 dans la gestion (débutant accepté)\nUne très bonne maîtrise du VBA, python, SQL\nEnvie d’intégrer une entreprise dynamique et leader dans son secteur d’activité\nLe sens des priorités et le sens du service\nUne approche pédagogique\nL’esprit d’équipe et le goût du challenge\nUn bon relationnel client\nLa capacité à traiter diverses tâches annexes\nVous êtes :\nOrganisé, rigoureux, curieux et autonome\nEngagé et impliqué\nForce de proposition\nSi vous devenez un Aymer ?\nBien-être au travail et carrière\nD’une diversité de projets et d’environnements métiers et géographiques\nD’une politique de développement de votre potentiel au travers de notre Ayming Academy et Ayming Digital Academy\nUn programme d’évolution de carrière au travers de nos accompagnements RH « My Professionnal Journey »\nDe notre Nouvelle Vie au travail : flexibilité, espaces créativité et conviviaux, 108 jours de télétravail par an\nDes moments de rencontre lors d’événements tout au long de l‘année\nPackage de rémunération et avantages sociaux\nRémunération fixe et variable selon profil\nStatut employé\nSoutien à la parentalité\nVotre recruteur\nRachid BELHOCINE\nPostuler Envoyer à un(e) ami(e) ›\nPartager cette publication\nPostuler Envoyer à un(e) ami(e) ›\nNom *\nPrénom *\nEmail *\nJe suis intéressé par :\nTéléchargement de votre CV * Types de fichiers acceptés : pdf, doc, rtf, txt, docx, odt, jpg, Taille max. des fichiers : 24 MB.\n*\nJ'accepte qu'Ayming traite mes données personnelles pour gérer ma candidature dans les conditions détaillées au sein de la Politique RH .\nNous vous rappelons que vous disposez d'un droit d'accès, de rectification, de suppression, de limitation, de portabilité ainsi qu'un droit d'opposition au traitement de vos données. Pour exercer ces droits, vous pouvez adresser une demande à : contact@ayming.com.\nShow more\nShow less",
        "details": {
            "JobDetail": [],
            "TypeContract": "",
            "Salary": "24",
            "Level": "",
            "Experience": null
        },
        "title": "data analyst",
        "skills": {
            "ProgLanguage": [
                "Python"
            ],
            "DataBase": [
                "SQL"
            ]
        }
    },
    {
        "source": "LinkedIn",
        "company": "Akademija Oxford",
        "location": "Boulogne-Billancourt, Île-de-France, France",
        "link": "https://fr.linkedin.com/jobs/view/apprenti-e-data-analyst-at-akademija-oxford-3917867572?position=22&pageNum=0&refId=jBvsgtdGm8ta0dsilpa8wg%3D%3D&trackingId=lVaSmyHVxk74JYgGCwqu6Q%3D%3D&trk=public_jobs_jserp-result_search-card",
        "description": "Notre partenaire, acteur mondial des métiers des concessions et de la construction, recherche un.e apprenti.e Data Analyst dans le cadre d’une alternance de 12 à 24 mois débutant à la rentrée de Septembre 2021.\nShow more\nShow less",
        "details": {
            "JobDetail": [],
            "TypeContract": "",
            "Salary": "",
            "Level": "",
            "Experience": null
        },
        "title": "data analyst",
        "skills": {}
    },
    {
        "source": "LinkedIn",
        "company": "Akademija Oxford",
        "location": "Ille-et-Vilaine, Brittany, France",
        "link": "https://fr.linkedin.com/jobs/view/ing%C3%A9nieur-data-at-akademija-oxford-3912800588?position=23&pageNum=0&refId=jBvsgtdGm8ta0dsilpa8wg%3D%3D&trackingId=0TTXCFAk%2FLF32wfFcRuT1w%3D%3D&trk=public_jobs_jserp-result_search-card",
        "description": "Vous souhaitez intégrer une école à taille humaine ? Vous êtes intéressé.es par la donnée ? Sup de Vinci propose une formation complète, en Mastère Big Data & Intelligence Artificielle (2 années en alternance).\nL’école Sup de Vinci, Rennes, accompagne l’une de ses entreprises partenaires dans son projet de recrutement d’un profil ingénieur data, en alternance pour la rentrée 2022.\nShow more\nShow less",
        "details": {
            "JobDetail": [],
            "TypeContract": "",
            "Salary": "",
            "Level": "",
            "Experience": null
        },
        "title": "data engineer",
        "skills": {
            "Other": [
                "Big Data"
            ]
        }
    },
    {
        "source": "LinkedIn",
        "company": "Valeuriad",
        "location": "Nantes, Pays de la Loire, France",
        "link": "https://fr.linkedin.com/jobs/view/data-analyst-h-f-at-valeuriad-3741219622?position=24&pageNum=0&refId=jBvsgtdGm8ta0dsilpa8wg%3D%3D&trackingId=RedIFTSJZaEhGejEZRMlMg%3D%3D&trk=public_jobs_jserp-result_search-card",
        "description": "Rejoins la Team Data\ncréée par Nicolas Greffard,\nDocteur en Intelligence Artificielle\n, déjà composée de 20 Data Scientists et Data Engineer talentueux 😍\nNous recherchons de nouvelles pépites pour rejoindre notre équipe de choc et répondre aux multiples problématiques Data science de nos clients nantais mais également contribuer à nos projets de R&D et travailler sur des conférences incroyables (DevFest, Salon de la Data) 🤩\nTa future mission si tu l'acceptes 😉\nNous te proposons d'intervenir au sein de nos grandes DSI clientes, sur des sujets de collecte, d'alimentation et de transformation de données autour de l’intelligence artificielle.\nLe job en détail 🤩\nToutes Les Missions Ne Sont Pas Identiques, Mais Voici Des Exemples De Choses Sur Lesquelles Nos Data Analyst Sont Intervenus\nMettre en oeuvre des outils informatiques, des techniques et des méthodes statistiques pour permettre d'organiser, synthétiser et traduire efficacement des données ;\nFournir un appui analytique à la conduite d'exploration et à l'analyse complexe de données ;\nCréer des algorithmes de recherche de données qui permettent d'explorer les données utiles ;\nProcéder à l'industrialisation du procédé pour les données les plus intéressantes. Et organiser, synthétiser et traduire les informations pour faciliter la prise de décision ;\nGérer les opérations et l'administration, la modélisation et l'architecture des sources de données. Et s'assurer que les bases de données existantes soient opérationnelles et intègres ;\nDonner un sens aux données à l'aide de ses connaissances analytiques (SQL, analytics/BI, statistiques basiques) ;\nD’intégrer de nouveaux jeux de données (Open Data, crowd sourcing, API, fichiers, etc.).\nNous intervenons sur\ndes données Big Data\n(Hadoop, Hive, Spark, etc...), NoSQL (Neo4j, Redis Graph, Redis, mongo) avec toujours quelques bases de données Oracle indéboulonnables. Mais aussi régulièrement sur des environnements\nCloud\n(principalement AWS et GCP). Côté outillage et ETL, les missions récentes étaient principalement sur Informatica, Dataiku et Dig Dash. A retenir : nous faisons de tout !\nPourquoi choisir Valeuriad ? 😊\nEn plus d’être aujourd’hui un acteur nantais reconnu de l’expertise IT, nous nous inscrivons depuis notre création dans une démarche d'entreprise\nOpale\net\nHolacratique\n, où l'ensemble de nos prises de décisions et projets sont réalisés par et avec l'ensemble de nos 120 coéquipiers 💪\nRejoindre Valeuriad, c'est\npouvoir s'investir dans la co-construction\nde l'entreprise :\nPar un rôle, avec une fiche de poste et un temps dédié (gestionnaire des Ci’s, porteur des partenariats écoles, organisateur d’événements, PO des projets internes, gestion de l'Académie Valeuriad…).\nPar les projets stratégiques (200 jours mis à disposition pour les coéquipiers chaque année) pour créer et faire grandir des projets structurants (création de nouveaux avantages à l'ancienneté, création d'indicateurs mensuels pour être toujours plus transparents, mécénat de compétences pour des associations caritatives...).\nPar les projets cagnottes (150€ par coéquipiers et par an) pour réaliser des projets collaboratifs qui te tiennent à cœur avec d'autres Valeurieux (découverte du cécifoot, challenge écologique, challenges sportifs pour des dons à des associations humanitaires, borne photo...).\nPar les ateliers collaboratifs, chaque mois des brainstorming et ateliers de travail sont proposés par les différents porteurs de projets et sont ouverts à tous les volontaires.\nMais avant-tout nous sommes une\néquipe soudée\n, des collègues qui apprécient passer du temps ensemble lors de nos soirées hebdomadaires et se créer des souvenirs inoubliables 🤩 C'est pour ça que chez Valeuriad, le plus important pour nous reste le savoir-être : des passionnés, du dynamisme, des sourires, de l'écoute et le sens de la fête 😉\nShow more\nShow less",
        "details": {
            "JobDetail": [],
            "TypeContract": "",
            "Salary": "",
            "Level": "",
            "Experience": null
        },
        "title": "data analyst",
        "skills": {
            "ProgLanguage": [
                "R"
            ],
            "DataBase": [
                "SQL",
                "Neo4j",
                "NoSQL"
            ],
            "DataAnalytics": [
                "R"
            ],
            "BigData": [
                "Hadoop",
                "Spark"
            ],
            "CloudComputing": [
                "GCP",
                "AWS"
            ],
            "Other": [
                "Statistiques",
                "Cloud",
                "Big Data"
            ]
        }
    },
    {
        "source": "LinkedIn",
        "company": "Pluxee",
        "location": "Paris, Île-de-France, France",
        "link": "https://fr.linkedin.com/jobs/view/data-analyst-at-pluxee-3918821570?position=25&pageNum=0&refId=jBvsgtdGm8ta0dsilpa8wg%3D%3D&trackingId=XAtTme4fJeQAComt5IwV3Q%3D%3D&trk=public_jobs_jserp-result_search-card",
        "description": "Pluxee is a global player in\nemployee benefits and engagement\nthat operates in\n31 countries\n. Pluxee helps companies attract, engage, and retain talent thanks to a broad range of solutions across Meal & Food, Wellbeing, Lifestyle, Reward & Recognition, and Public Benefits.\nPowered by leading technology and more than\n5,000 engaged team members\n, Pluxee acts as a trusted partner within a highly interconnected B2B2C ecosystem made up of more than\n500,000 clients, 36 million consumers and 1.7 million merchants\n.\nConducting its business as a trusted partner for more than 45 years, Pluxee is committed to creating a positive impact on all its stakeholders, from driving business to local communities, to supporting wellbeing at work for employees while protecting the planet.\n🚀\nYour next challenge\nPluxee Data organization has chosen a decentralized Data Hub (central) & Data Spoke (local) organization where the Spokes are data factory teams covering multiple countries' Data needs and supporting business teams by delivering operations reporting, the ad-hoc analysis supporting decision making and advanced insights aiming at predicting clients, merchants, or consumers behaviors.\nTo support this objective, your responsibilities will encompass:\nData Analysis and interpretation:\ncollecting and analyzing data from various sources to identify trends and insights relevant for business improvement.\nVisualization and reporting:\ndeveloping clear and informative dashboards and reports using data visualization tools to effectively communicate findings to business teams.\nDecision support:\nproviding ad-hoc analyses and statistical modeling to assist business teams in making informed decisions and defining key performance indicators (KPIs) to measure progress.\n🌟\nYou’re a match\nTechnical Skills:\nSQL Proficiency:\ndemonstrated expertise in querying and managing data using SQL, with at least 3 years of experience as a Data Analyst.\nKPI Definition and Visualization:\nproficient in designing and developing dashboards using Power BI. Experience in defining and computing key performance indicators (KPIs) in DAX to measure business performance (finance or payment services will be a plus).\nStatistical and Machine Learning:\ngood understanding of\nstatistical analysis and machine learning techniques, enabling advanced data analysis.\nSoft Skills:\nEffective communication:\nstrong verbal and written communication skills in both French and English, adept at interacting with diverse stakeholders with varying cultural backgrounds and technical expertise.\nAnalytical thinking:\nhighly analytical and detail-oriented, with a knack for problem-solving and extracting insights from complex datasets.\nProactive and motivated:\nproactive attitude, hands-on approach, and a high level of motivation to learn quickly and adapt to new challenges in an ever-moving domain.\n🔎\nTo get this challenge\nVideocall with Talent Acquisition Expert.\nTechnical assessment.\nVideocall with Hiring Manager (Data Spoke Manager).\n🏅\nYour team\nReporting to Jean Francois Prince (Data Spoke Manager).\n📍\nYour Location\nCentral Paris, Paris.\nAbility to work in a hybrid mode (3 days at the office and 2 days at home).\n☀️ Happy at work\nA meaningful job:\nbuild the future of employee benefits and contribute to the quality of life at work for others, you will impact positively local communities too. It counts!\nA great culture:\nwe respect and care authentically about our people, we embrace work-life balance, new ideas and we have a lot of fun!\nEmployee experience is what we do. So, you can expect a comprehensive package including benefits and an annual bonus based on performance.\nAbout Pluxee\nWorking at Pluxee is joining a multicultural team that moves as one. It’s also a place where your individual ideas, perspectives, and input count. You’ll be given the freedom and autonomy you need to do impactful work, supported by a team that cares about your well-being, growth, and work/life balance.\nIt’s the agility you’d expect from a fast-growing small business, with the stability that only a globally renowned company with +45 years in the business can offer. Put a part of yourself into the future of employee benefits and meaningfully contribute to lives and communities worldwide.\nShow more\nShow less",
        "details": {
            "JobDetail": [
                "Full"
            ],
            "TypeContract": "",
            "Salary": "45",
            "Level": "",
            "Experience": null
        },
        "title": "data analyst",
        "skills": {
            "DataBase": [
                "SQL"
            ],
            "DataVisualisation": [
                "Power BI"
            ],
            "Collaboration": [
                "Teams"
            ],
            "Other": [
                "Machine Learning"
            ],
            "EnSoftSkils": [
                "Communication",
                "Organization"
            ]
        }
    },
    {
        "source": "LinkedIn",
        "company": "Aqualung Group",
        "location": "Valbonne, Provence-Alpes-Côte d'Azur, France",
        "link": "https://fr.linkedin.com/jobs/view/master-data-analyst-intern-at-aqualung-group-3908876542?position=26&pageNum=0&refId=jBvsgtdGm8ta0dsilpa8wg%3D%3D&trackingId=jzNiCZHh6TTb36amu82WbQ%3D%3D&trk=public_jobs_jserp-result_search-card",
        "description": "Aqualung Group pioneered the creation of modern diving equipment in 1943 when Captain Jacques-Yves Cousteau teamed with Émile Gagnan to develop the first “aqua-lung” that made underwater exploration possible. Today, Aqualung Group continues to be the leading global designer and manufacturer of dive and water sports gear. With a deep commitment to quality, research and testing, Aqualung Group has revolutionized the scuba diving experience by setting industry standards for scuba equipment in technology, comfort, safety and design.\nThe Aqualung Group consists of premium, innovative and inclusive brands such as Aqualung, Apeks, Aquasphere, Omer;\nSo, are you...\na sport enthusiast\ndo you love oceans and everything beyond\nare you an advocate of making a difference and protect our planet, a world where the ocean and all living creature are healthy and thriving\nor are you simply motivated and inspired to be a part of our passionate team that is always eager for a new challenge\nAqualung believes in the future, thus we invite you to strengthen and broaden your skills, pursue your passion by co-creating the future within an internship open positions.\nScope and Mission\nSupport the Aqualung Group in the daily management of Item master data.\nStart date:\nASAP\nDuration target:\nminimum 6 months\nLocation:\nSophia Antipolis\nKey duties and responsibilities\nSupport the master data team in the Item master data collection processes. (Creation/Update).\nHelp centralizing Master Data information in dedicated MDM tool (Product Hub/Oracle).\nHelp ensuring synchronization of the item master data in consuming systems.\nControl master data availability and quality through the publication of KPIs and implementation of data quality reports.\nEnsure master data collection environments are up to date.\nContribute in implementing data quality reports and corrective processes.\nContribute with the Master Data team in enhancing the existing item Core Model.\nYour qualifications\nLevel of studies:\nBAC + 4/5 minimum / master's degree in data science / data analysis.\nA first level of experience in Master data is preferred.\nSkills\nFluent English\nExcellent communication skills\nWorking effectively in a Team\nGood organizational skills, sense of prioritization\nYou are curious, dynamic, passionate about innovation\nStrong ability in manipulating data. (SQL)\nIf you are excited about this opportunity and joining the Aqua Lung team, please apply!\nWe look forward to receiving your application.\nShow more\nShow less",
        "details": {
            "JobDetail": [],
            "TypeContract": "",
            "Salary": "",
            "Level": "",
            "Experience": null
        },
        "title": "data analyst",
        "skills": {
            "DataBase": [
                "SQL"
            ],
            "EnSoftSkils": [
                "Communication"
            ]
        }
    },
    {
        "source": "LinkedIn",
        "company": "Astek",
        "location": "Paris, Île-de-France, France",
        "link": "https://fr.linkedin.com/jobs/view/data-analyst-%E2%80%93-paris-france-h-f-at-astek-3839098102?position=27&pageNum=0&refId=jBvsgtdGm8ta0dsilpa8wg%3D%3D&trackingId=BSmRQQfj3MaLcUFEyaTRiQ%3D%3D&trk=public_jobs_jserp-result_search-card",
        "description": "CDI\nParis - France\nPubliée il y a 2 mois\nLe Groupe Astek\nCe Que Nous Allons Accomplir Ensemble :\nNous rejoindre en tant que\nData Analyst (H/F),\nafin d’accompagner un opérateur télécoms, Leader en Europe dans la gestion de ses solutions robustes, efficientes et sécurisées à destination d’environnements variés.\nUn challenge portant sur des millions d’utilisateurs dans un environnement technique innovant, stratégique et où l’entraide et la bonne humeur priment !\nVotre Mission, Si Vous L’acceptez :\nEtude sur les données pour aide au cadrage du besoin Métier.\nForce de proposition sur des solutions analytiques adaptées aux besoins utilisateurs (avec nos équipes UX).\nAnalyse des besoins métiers, accompagnement à la formulation et à la définition de KPI métiers.\nModélisation des données.\nConception de Datasets Big Query.\nConception et Réalisation de Datamarts et de Dashboards (PowerBI / Looker)\nAnalyse de la qualité de la donnée source, pour challenger les équipes Digitales / Data Engineers.\nVotre Future Équipe :\nAu sein d’un environnement riche et complexe, vous évoluerez avec des experts passionnés à la fois techniques et fonctionnels (Ingénieurs spécialisés, chef de projet, scrum master, product owner …).\nL’équipe est en interaction avec des clients à la fois internes et externes.\nVotre stack de jeu\nSQL – Confirmé\nModélisation de Données – Confirmé\nOutils de Data Viz – Confirmé\nGCP – Junior\nAnglais – Professionnel\nLes Petits Plus Du Projet :\nVous interviendrez de A à Z sur des projets riches fonctionnellement et ambitieux techniquement. Un challenge portant sur des millions d’utilisateurs dans un environnement technique innovant et stratégique.\nVous ?\nDiplômé(e) d’une école d’ingénieur ou équivalent de niveau Bac+5.\nVous justifiez idéalement d’une expérience d’au moins 3 ans d’expériences sur un poste similaire ?\nVous faite preuve d’un bon relationnel et d’esprit d’équipe, êtes doté(e) d’un excellent sens de l’organisation et vous aimez les challenges et la résolution de problème ?\nAlors ce poste est fait pour vous, n’hésitez plus et rejoignez l’aventure ASTEK !\nAstek\nCréé en France en 1988, Astek est un acteur mondial de l’ingénierie et du conseil en technologies. Fort de son expertise dans de nombreux secteurs industriels et tertiaires, Astek accompagne ses clients internationaux dans le déploiement intelligent de leurs produits et de leurs services, et dans la mise en œuvre de leur transformation digitale.\nDepuis sa création, le Groupe a fondé son développement sur une forte culture d’entrepreneuriat et d’innovation, et sur l’accompagnement et la montée en compétence de\nses 7800 collaborateurs\nqui s’engagent chaque jour à promouvoir la complémentarité entre les technologies numériques et l’ingénierie des systèmes complexes.\nRejoignez un Groupe en fort développement en France et à travers le monde ayant réalisé un chiffre d’affaires de 600 M€ en 2023.\nTous les détails sur le Groupe sur le site https://astekgroup.fr. Et vous pouvez aussi nous suivre sur notre blog : https://blog.groupeastek.com.\nRencontrons-nous\nNotre projet commun vous plait ?\nPostulez à cette annonce, et soyez transparent !\nMaud, notre Talent Acquisition Referent, vous contactera pour un premier échange.\nPuis vous rencontrerez Martin, votre futur manager, avec lequel vous échangerez autour d’Astek, de votre parcours, de vos attentes et de votre future mission .\nEnfin, vous rencontrerez Jérémy, notre Directeur d’agence avec lequel vous pourrez valider votre intérêt et adéquation pour le poste et finaliser les éléments contractuels.\nNos Plus\nAstek est green et fait bénéficier ses salariés d’une indemnité kilométrique vélo\nUne politique CARE sur-mesure déployée par nos équipes RH pour nos collaborateurs (https://astekgroup.fr/engagements)\nNotre charte de la Diversité\nMots-clés :\ningénieur – ingénieure – consultant – consultante – data – analyst – modélisation – données\nCaractéristiques de l'emploi\nCatégorie Ingénieur\nJob Industry Télécom / Média\nPostuler en ligne\nNom *\nPrénom *\nEmail *\nUn email valide est requis.\nTéléphone *\nUn numéro de téléphone valide est requis.\nJoindre un CV *\nMots-clés :\ningénieur – ingénieure – consultant – consultante – data – analyst – modélisation – données\nShow more\nShow less",
        "details": {
            "JobDetail": [
                "Confirmé",
                "Junior"
            ],
            "TypeContract": "CDI",
            "Salary": "",
            "Level": "Bac+5",
            "Experience": "3 an(s)"
        },
        "title": "data analyst",
        "skills": {
            "DataBase": [
                "SQL"
            ],
            "CloudComputing": [
                "GCP"
            ],
            "DBMS": [
                "Big Query"
            ],
            "Automation": [
                "Chef"
            ]
        }
    },
    {
        "source": "LinkedIn",
        "company": "ACT-ON DATA",
        "location": "Courbevoie, Île-de-France, France",
        "link": "https://fr.linkedin.com/jobs/view/data-analyst-at-act-on-data-3912559652?position=28&pageNum=0&refId=jBvsgtdGm8ta0dsilpa8wg%3D%3D&trackingId=qqUvkDvbhZMk5pOMux4%2FCQ%3D%3D&trk=public_jobs_jserp-result_search-card",
        "description": "Description de l'entreprise\nSociété de conseil & de services, ACT-ON GROUP est l’acteur leader du #HumanTech.\nIl mobilise ses expertises variées et complémentaires en STRATEGY, HR & HRIS, DATA et TECHNOLOGY, ainsi que la connaissance de son écosystème partenaires pour accompagner ses clients dans la réussite de tous leurs projets de transformation qu’ils soient organisationnels, digitaux ou culturels…\nAvec plus de 20 ans d’existence, notre groupe compte aujourd’hui plus de 1 500 missions chez nos clients (ETI, SBF 120, CAC 40, secteur public, associatif et ONG).\nIl réunit une communauté de plus de 600 collaborateurs, pour un chiffre d’affaires de plus de 70 millions d’euros.\nHistoriquement présent sur le marché français, en Île-de-France, à Lille, Lyon et Nantes, il se développe désormais aussi à l’international.\nDescription du poste\nAu sein de notre entité innovante Act-On Data, vous êtes intégré(e) à une équipe d’experts métier en tant que Data analyst, potentiellement sur un projet international.\nVous participerez ainsi à des missions à forte valeur ajoutée auprès de nos clients en intervenant sur des problématiques métiers, tout en ayant la charge de problématiques opérationnelles :\nMettre à disposition des outils de pilotage d'activité à destination des équipes métier en définissant les principaux KPI à suivre,\nMener et présenter les analyses demandées par les Directions métiers ou la Direction nécessaire pour comprendre le business et transformer ces insights en plan d'action,\nVeiller à améliorer et mesurer la qualité des données afin de mettre à disposition des données fiables,\nParmi vos missions :\nCollaborer avec les métiers sur la définition des principaux KPI,\nRécolter des besoins métiers,\nRéalisation des analyses statistiques simples ou complexes en fonction de la demande,\nConception des monitorings de suivi de la qualité des données des différents domaines,\nIntervenir techniquement sur la partie aval de la chaîne de valeur Data.\nQualifications\nVous justifiez d’une expérience significative sur un poste similaire.\nVous avez un niveau d’anglais qui vous permet de piloter un projet à l’international.\nVous maîtrisez vos domaines de compétences (outils/modules ou fonctionnels) et démontrez votre légitimité par des expériences significatives sur un poste similaire.\nNous recherchons une personne organisée, volontaire, dynamique avec une bonne capacité d’adaptation.\nLe goût des chiffres et la maitrise d’Excel sont indispensables.\nVous avez une bonne appétence pour la data et sur les outils de reporting (SAP BI, PowerBI, Tableau, …) et connaissez les plates-formes Cloud (Azure, AWS, GCP)\nD’un tempérament passionné, vous aimez les challenges et vous souhaitez vous investir dans cette aventure ?\nAlors ce poste peut vous intéresser !\nInformations supplémentaires\nCe poste est ouvert au télétravail.\nCe poste est ouvert aux personnes recherchant un CDI uniquement.\nShow more\nShow less",
        "details": {
            "JobDetail": [],
            "TypeContract": "CDI",
            "Salary": "",
            "Level": "",
            "Experience": "20 an(s)"
        },
        "title": "data analyst",
        "skills": {
            "DataVisualisation": [
                "Tableau"
            ],
            "CloudComputing": [
                "GCP",
                "AWS",
                "Azure"
            ],
            "Other": [
                "Statistiques",
                "Cloud"
            ]
        }
    },
    {
        "source": "LinkedIn",
        "company": "Datatorii",
        "location": "Paris",
        "link": "https://fr.linkedin.com/jobs/view/data-analyst-at-datatorii-3916566708?position=29&pageNum=0&refId=jBvsgtdGm8ta0dsilpa8wg%3D%3D&trackingId=%2B56qG1wm41iP3stNV3mqmQ%3D%3D&trk=public_jobs_jserp-result_search-card",
        "description": "1. Présentation\nDatatorii est une société de conseil spécialisée en data.\nPartenaires des directions métiers et IT, nous accompagnons nos clients dans la mise en place de solutions techniques Microsoft ainsi que dans l’analyse de leurs données.\nLa R&D réalisée en interne (10% du temps, au Dojo) autour de la formation continue et du suivi des évolutions technologiques nous positionne comme un partenaire de choix, spécialisé Data Microsoft.\nOrganisme de formation, nous accompagnons également nos clients de la prise en main jusqu’à la maîtrise des outils et des méthodes autour de la data.\nNichés dans le 1er arrondissement de Paris, nos locaux vous offrent tout le confort pour vous former, échanger régulièrement avec vos pairs, participer aux ateliers internes et recevoir nos clients.\nDatatorii vous donne la possibilité de réaliser vos prochains défis !\n2. Mission\nLa communication en entreprise, interne ou externe, est de plus en plus influencée par la restitution de données, que ce soit via des dashboards, des rapports interactifs ou des présentations au Top Management.\nChez Datatorii, vous évoluerez au sein d’un dispositif pluridisciplinaire (Ingénieur, Data Scientist, Architecte, Chef de projet, Formateur, etc.) qui propose des solutions complètes data :\nLa récolte du besoin auprès des utilisateurs, la définition de personas, de maquettes et d’user-flow\nLa création de Style Guides Data et de thèmes clé-en-main pour les projets de visualisation de données\nL’accompagnement sur les réalisations (PowerBI, PowerApps, Microsoft Azure, Python, SQL, Modélisation, ...)\nLa conception d’offres innovantes et leur promotion (UX BI, BI Self-service, Low-code application, Data Management ...)\nLa réalisation de dashboards et rapports interactifs à fort enjeux\nLa formation interne ou externe au sein de notre organisme de formation\nGrâce à nos parcours de carrière gamifiés, nos training kit et notre dispositif d’accompagnement, Datatorii vous intègre dans un parcours certifiant et vous offre toutes les chances de réussir avec des perspectives de carrière claires et stimulantes.\n3. Profil\nFormation initiale\nBAC +5 Ecole de commerce (Data Analyst, Data Business) ou (Ingénieur, mathématiques, statistiques, informatique)\nConnaissances ou expériences\nVous possédez une première expérience significative en DataViz\nVous y avez développé des compétences de Business Analyst (DataViz, UX, Modélisation, etc. )\nQualités\nExcellent relationnel\nBon communicant\nProactif\nPédagogue\nCapacité d’analyse et de synthèse\nShow more\nShow less",
        "details": {
            "JobDetail": [],
            "TypeContract": "",
            "Salary": "",
            "Level": "",
            "Experience": null
        },
        "title": "data analyst",
        "skills": {
            "ProgLanguage": [
                "R",
                "Python"
            ],
            "DataBase": [
                "SQL"
            ],
            "DataAnalytics": [
                "R"
            ],
            "CloudComputing": [
                "Azure"
            ],
            "Automation": [
                "Chef"
            ],
            "Other": [
                "Statistiques"
            ],
            "EnSoftSkils": [
                "Communication"
            ]
        }
    },
    {
        "source": "LinkedIn",
        "company": "Iveco Group",
        "location": "Le Plessis-Belleville, Hauts-de-France, France",
        "link": "https://fr.linkedin.com/jobs/view/data-analysis-assistant-at-iveco-group-3907438232?position=30&pageNum=0&refId=jBvsgtdGm8ta0dsilpa8wg%3D%3D&trackingId=F5EWPCh8u9x3K4ieBNS%2F9A%3D%3D&trk=public_jobs_jserp-result_search-card",
        "description": "FPT Industrial est une marque d'Iveco Group (IVG: MI), dédiée à la conception, la production et la vente de groupes motopropulseurs et solutions destinés aux véhicules routiers et tout-terrain, ainsi qu'aux applications marines et de production d'énergie. Plus de 8000 salariés, répartis sur onze sites de production et onze centres de R&D travaillent pour FPT Industrial à travers le monde. Implantés dans près de 100 pays, le réseau mondial de vente et le Customer Service de FTP Industrial soutiennent tous les clients de la Marque.\nNous recherchons : Un(e) assistant(e) Data Analysis en alternance\nMissions :\n• Fournir les principaux rapports sur les ventes et les produits au niveau de Monde (Europe, Moyen Orient , Asie, Afrique, Amérique latine)\n• Collecter et compiler les données sur la concurrence et les données potentielles au niveau des produits\n• Analyser la performance des ventes par produit\n• Élaborer des rapports standards, un tableau de bord des produits et un suivi des indicateurs de performances clés.\n• Identifier les potentiels produits/ Running parks\nProfil :\nMaster marketing stratégique / Data analytics – Business analytics\n-Anglais opérationnel, l'italien est un plus\n-Compétences d'analyse requises\n-Ouvert d'esprit et curieux : vous ferez partie d'une équipe internationale située entre Le Plessis Belleville et Turin et vous travaillerez dans le département marketing Reman\n-Durée : à partir de septembre 2024 pendant 12 à 24 mois\nOutils :\n-Microsoft Office\n-Excel : très bonne maitrise\n-Powerpoint : bonne maitrise\n-La maitrise d’Access est un plus\n-Data Warehouse (SAP BW)\n-Qlik sense\n-Power BI est un plus\nShow more\nShow less",
        "details": {
            "JobDetail": [],
            "TypeContract": "",
            "Salary": "",
            "Level": "",
            "Experience": null
        },
        "title": "Other",
        "skills": {
            "ProgLanguage": [
                "R"
            ],
            "DataAnalytics": [
                "R"
            ],
            "DataVisualisation": [
                "Power BI",
                "Tableau"
            ]
        }
    },
    {
        "source": "LinkedIn",
        "company": "Mobiskill | WEFY Group",
        "location": "Paris",
        "link": "https://fr.linkedin.com/jobs/view/data-analyst-at-mobiskill-wefy-group-3900004007?position=31&pageNum=0&refId=jBvsgtdGm8ta0dsilpa8wg%3D%3D&trackingId=FfuHS0i2DjiQ05OHyrPcnQ%3D%3D&trk=public_jobs_jserp-result_search-card",
        "description": "L'entreprise?\nInsurTech récemment créée, elle s'impose comme référence sur son marché en proposant des produits d'assurance disruptif.\nIls travaillent avec des petites entreprises comme des grands noms de l'assurance et cumulent 1 millions de clients.\nTeam?\n40 personnes\nContexte?\nForte traction commerciale, ils ont besoin de structurer leur donnée afin de créer de la valeur en interne et de la délivrer à leurs clients aussi.\nLes missions?\n- Participer à la construction de la roadmap data sur le moyen et le long terme (en accord avec les Business units)\n- Leader la mise en former d'une grosse volumétrie de Data pour dégager de la valeur pour leurs partenaires existants\n- Réaliser des études exploratoires poussées pour apporter des recommandations stratégiques à l'entreprise\n- Co-construire les KPIs, OKR et dashboards, puis les automatiser\n- A/B testing sur de potentiels features\nTon profil?\n- Diplômé(e) Bac+5, vous justifiez d'une expérience de 3 ans minimum dans la Data analyse\n- Idéalement, vous êtes familier de l'univers de l'assurance\n- Doté(e) d'une forte capacité analytique, vous êtes aussi capable d'exprimer clairement vos à recommandations à l'oral\n- Tu maîtrises SQL et un outil de Data vizualisation (Tableau/PowerBI). Idéalement tu es aussi familier de Python\n- Fiabilité, proactivité et autonomie sont des compétences clés à ce poste\nLes++?\n- Société en pleine croissance (suite à leur levée de fonds, la roadmap 2024 est validée et ils sont prêts à scaler )\n- Organisation d’entreprise alliant flexibilité et structure (méthode de l’autonomie alignée)\n- Poste évolutif avec de fortes perspectives d'évolutions (dont management)\n- Package attractif\nShow more\nShow less",
        "details": {
            "JobDetail": [],
            "TypeContract": "",
            "Salary": "Package",
            "Level": "Bac+5",
            "Experience": "3 an(s)"
        },
        "title": "data analyst",
        "skills": {
            "ProgLanguage": [
                "Python"
            ],
            "DataBase": [
                "SQL"
            ],
            "DataVisualisation": [
                "Tableau"
            ]
        }
    },
    {
        "source": "LinkedIn",
        "company": "Astek",
        "location": "Lille, Hauts-de-France, France",
        "link": "https://fr.linkedin.com/jobs/view/data-analyst-%E2%80%93-lille-france-h-f-at-astek-3839093481?position=32&pageNum=0&refId=jBvsgtdGm8ta0dsilpa8wg%3D%3D&trackingId=MoPSjLmEdUkC3hffLr7yzg%3D%3D&trk=public_jobs_jserp-result_search-card",
        "description": "CDI\nLille - France\nPubliée il y a 2 mois\nLe Groupe Astek\nCe Que Nous Allons Accomplir Ensemble :\nNous rejoindre en tant que\nData Analyst (H/F),\nafin d’accompagner un opérateur télécoms, Leader en Europe dans la gestion de ses solutions robustes, efficientes et sécurisées à destination d’environnements variés.\nUn challenge portant sur des millions d’utilisateurs dans un environnement technique innovant, stratégique et où l’entraide et la bonne humeur priment !\nVotre Mission, Si Vous L’acceptez :\nEtude sur les données pour aide au cadrage du besoin Métier.\nForce de proposition sur des solutions analytiques adaptées aux besoins utilisateurs (avec nos équipes UX).\nAnalyse des besoins métiers, accompagnement à la formulation et à la définition de KPI métiers.\nModélisation des données.\nConception de Datasets Big Query.\nConception et Réalisation de Datamarts et de Dashboards (PowerBI / Looker)\nAnalyse de la qualité de la donnée source, pour challenger les équipes Digitales / Data Engineers.\nVotre Future Équipe :\nAu sein d’un environnement riche et complexe, vous évoluerez avec des experts passionnés à la fois techniques et fonctionnels (Ingénieurs spécialisés, chef de projet, scrum master, product owner …).\nL’équipe est en interaction avec des clients à la fois internes et externes.\nVotre stack de jeu\nSQL – Confirmé\nModélisation de Données – Confirmé\nOutils de Data Viz – Confirmé\nGCP – Junior\nAnglais – Professionnel\nLes Petits Plus Du Projet :\nVous interviendrez de A à Z sur des projets riches fonctionnellement et ambitieux techniquement. Un challenge portant sur des millions d’utilisateurs dans un environnement technique innovant et stratégique.\nVous ?\nDiplômé(e) d’une école d’ingénieur ou équivalent de niveau Bac+5.\nVous justifiez idéalement d’une expérience d’au moins 3 ans d’expériences sur un poste similaire ?\nVous faite preuve d’un bon relationnel et d’esprit d’équipe, êtes doté(e) d’un excellent sens de l’organisation et vous aimez les challenges et la résolution de problème ?\nAlors ce poste est fait pour vous, n’hésitez plus et rejoignez l’aventure ASTEK !\nAstek\nCréé en France en 1988, Astek est un acteur mondial de l’ingénierie et du conseil en technologies. Fort de son expertise dans de nombreux secteurs industriels et tertiaires, Astek accompagne ses clients internationaux dans le déploiement intelligent de leurs produits et de leurs services, et dans la mise en œuvre de leur transformation digitale.\nDepuis sa création, le Groupe a fondé son développement sur une forte culture d’entrepreneuriat et d’innovation, et sur l’accompagnement et la montée en compétence de\nses 7800 collaborateurs\nqui s’engagent chaque jour à promouvoir la complémentarité entre les technologies numériques et l’ingénierie des systèmes complexes.\nRejoignez un Groupe en fort développement en France et à travers le monde ayant réalisé un chiffre d’affaires de 600 M€ en 2023.\nTous les détails sur le Groupe sur le site https://astekgroup.fr. Et vous pouvez aussi nous suivre sur notre blog : https://blog.groupeastek.com.\nRencontrons-nous\nNotre projet commun vous plait ?\nPostulez à cette annonce, et soyez transparent !\nMaud, notre Talent Acquisition Referent, vous contactera pour un premier échange.\nPuis vous rencontrerez Martin, votre futur manager, avec lequel vous échangerez autour d’Astek, de votre parcours, de vos attentes et de votre future mission .\nEnfin, vous rencontrerez Jérémy, notre Directeur d’agence avec lequel vous pourrez valider votre intérêt et adéquation pour le poste et finaliser les éléments contractuels.\nNos Plus\nAstek est green et fait bénéficier ses salariés d’une indemnité kilométrique vélo\nUne politique CARE sur-mesure déployée par nos équipes RH pour nos collaborateurs (https://astekgroup.fr/engagements)\nNotre charte de la Diversité\nMots-clés :\ningénieur – ingénieure – consultant – consultante – data – analyst – modélisation – données\nCaractéristiques de l'emploi\nCatégorie Ingénieur\nJob Industry Télécom / Média\nPostuler en ligne\nNom *\nPrénom *\nEmail *\nUn email valide est requis.\nTéléphone *\nUn numéro de téléphone valide est requis.\nJoindre un CV *\nMots-clés :\ningénieur – ingénieure – consultant – consultante – data – analyst – modélisation – données\nShow more\nShow less",
        "details": {
            "JobDetail": [
                "Confirmé",
                "Junior"
            ],
            "TypeContract": "CDI",
            "Salary": "",
            "Level": "Bac+5",
            "Experience": "3 an(s)"
        },
        "title": "data analyst",
        "skills": {
            "DataBase": [
                "SQL"
            ],
            "CloudComputing": [
                "GCP"
            ],
            "DBMS": [
                "Big Query"
            ],
            "Automation": [
                "Chef"
            ]
        }
    },
    {
        "source": "LinkedIn",
        "company": "moOngy Digital Lab",
        "location": "Lille",
        "link": "https://fr.linkedin.com/jobs/view/data-analyst-h-f-at-moongy-digital-lab-3890974953?position=33&pageNum=0&refId=jBvsgtdGm8ta0dsilpa8wg%3D%3D&trackingId=L9xZtAwqXVojDTcbN2pv7g%3D%3D&trk=public_jobs_jserp-result_search-card",
        "description": "Web Transition, c’est qui ?\nFondée en 2011,\nWeb transition\nest une entreprise de services numériques opérant sur le marché de l’IT/Digital !\nConstituant une part essentielle de\nMoOngy Digital Lab\n, Web Transition accompagne ses clients grands comptes sur leurs projets de Webmarketing, de Design, Gestion de projet et également en Data !\nNotre objectif : nous implanter comme un acteur principal sur le marché de la Transformation Digitale en accompagnant et valorisant les compétences de nos collaborateurs !\nNous sommes convaincus que le succès de MoOngy Digital Lab réside dans la somme des potentiels de nos équipes 🤝\nTon équipe : La tribu Data\nParce qu’il est indispensable que tu puisses partager tes connaissances mais aussi en acquérir de nouvelles, tu feras partie de l’une de nos tribus : celle de la Data. De plus, cela te permettra d’être acteur dans le développement et la stratégie de Web Transition. Ce système de co-réflexion et co-construction est un fondement essentiel chez nous !\nDans cette aventure, tu :\nOptimises\nles requêtes SQL ;\nConstruis\nles modèles de régression ;\nAnalyses\nla rentabilité des actions marketing ;\nRéalises\ndes études ad hoc sur les comportements clients ;\nProduits\net\nautomatises\nle reporting.\nRejoins-nous si tu as :\nUne expérience de 3 ans minimum,\nUne maitrise technique de GCP / DBT / PowerBI,\nUne expérience similaire dans une startup ou dans l’industrie serait un plus !\nTon savoir-être :\nOuvert d’esprit\nRespectueux des différences de chacun\nCurieux\nProactif\nPar où on commence ?\nUn premier entretien RH d’1h pour comprendre ton parcours et tes aspirations\nUn second entretien de 45 minutes avec l’un de nos Business Manager afin de valider tes compétences et qu’il se projette sur l’une des missions qu’il pourrait te proposer\nUn troisième entretien de quelques minutes avec notre responsable d’agence pour te proposer d’intégrer notre superbe Team Web !\n3 entretiens en peu de temps, si ton profil correspond tu intègreras très vite nos équipes 😉\nPrêt pour embarquer dans notre grande aventure humaine ? Deviens notre futur Weber en postulant à cette offre ! Voici les avantages qui t’attendent en tant que Weber :\n🤩 Des collègues incroyables\n🏆 Certifiée Great Place to Work\n🎮 Des bureaux sympas (où vous serez toujours les bienvenus)\n🎉 Des teambuilding et évents tous les mois\n💻 Des tributs métiers pour échanger entre Weber du même métier\nDes missions chez le client qui sont accompagnées et coachées par ton manager\nUn accompagnement dans ton plan de carrière et tes envies de re skilling\n🤓 Un catalogue de formations certifiantes ouvert à tous les salariés\n🍽️ Une carte tickets restaurant MyEdenred\n❤️ Une mutuelle GrasSavoye\n🚎 Une prise en charge des frais de transport à 100%\nShow more\nShow less",
        "details": {
            "JobDetail": [],
            "TypeContract": "",
            "Salary": "",
            "Level": "",
            "Experience": "3 an(s)"
        },
        "title": "data analyst",
        "skills": {
            "DataBase": [
                "SQL"
            ],
            "CloudComputing": [
                "GCP"
            ]
        }
    },
    {
        "source": "LinkedIn",
        "company": "Novencia Group",
        "location": "Lyon, Auvergne-Rhône-Alpes, France",
        "link": "https://fr.linkedin.com/jobs/view/data-analyst-lyon-f-h-at-novencia-group-3842056375?position=34&pageNum=0&refId=jBvsgtdGm8ta0dsilpa8wg%3D%3D&trackingId=R7ljJszcODXjSIF%2F3My0tQ%3D%3D&trk=public_jobs_jserp-result_search-card",
        "description": "Carnet de route\nNovencia accompagne ses clients dans leurs projets de transformation digitale, technologique et data.\nExpert en Data et Intelligence Artificielle nous aidons nos clients à exploiter et valoriser leurs données sous toutes ses formes en les accompagnant sur des projets de Data Gouvernance, Data Architecture, Data Science, et Data Engineering.\nData Analyst\ndepuis au moins\n3 ans,\ntu es à la recherche de nouveaux défis. Boucle ta ceinture, la suite est pour toi !\nTon Rôle\nRattaché.e aux consultants de l’agence Lyonnaise, tu seras amené.e à travailler chez les clients finaux et/ou au sein de notre Datalab’.\nEn tant que Data Analyst, tu auras les missions suivantes :\nT’immerger dans le contexte client ;\nMener des ateliers avec les équipes métier pour recueillir/ définir leurs besoins ;\nChallenger leurs demandes ;\nParticiper au recueil et à la modélisation des données ;\nContrôler la fiabilité et la qualité des données ;\nStructurer et exploiter les données grâce à des outils de Data visualisation ;\nAnalyser ces données et partager les résultats ;\nFaire des recommandations au client.\nTon profil\nDe formation Bac+5 dans le domaine de la Data, tu as au moins 3 ans d’expérience sur un poste similaire.\nCompétences techniques recherchées :\nExpérience significative sur un outil de Data visualisation pour l’élaboration de rapports/tableaux de bord (Power BI/Tableau/QlikSense etc.)\nLangage SQL (Python est un plus)\nModélisation de données\nConnaissance des bases de données (e.g. Snowflake, Google BigQuery, SQL Server ou Oracle)\nUtilisation d’un ETL (e.g. Azure Data Factory, SSIS, Informatica, Talend, Matillion)\nUne expérience dans le fonctionnement d’une équipe agile.\nTu es passionné.e par la Data et souhaites évoluer au sein d’une communauté d’Experts de la Data, tu veux t’investir dans des projets data innovants au sein de notre Datalab’, tu aimes le travail en équipe mais sais être autonome sur tes sujets, tu es curieux.euse et force de proposition, tu es capable de chercher et trouver des solutions, tu as un bon niveau d’anglais.\nEnfin, tu souhaites intégrer une agence à taille humaine où la bienveillance n’est pas qu’un mot marketing.\nS’engager en faveur du handicap c’est garantir l’égalité des chances dès le recrutement. À compétences égales, nos postes sont ouverts aux personnes en situation de handicap.\nShow more\nShow less",
        "details": {
            "JobDetail": [],
            "TypeContract": "",
            "Salary": "",
            "Level": "Bac+5",
            "Experience": "3 an(s)"
        },
        "title": "data analyst",
        "skills": {
            "ProgLanguage": [
                "Python"
            ],
            "DataBase": [
                "SQL"
            ],
            "DataVisualisation": [
                "Power BI",
                "Tableau"
            ],
            "CloudComputing": [
                "Azure"
            ],
            "DBMS": [
                "SQL Server",
                "BigQuery",
                "Snowflake"
            ]
        }
    },
    {
        "source": "LinkedIn",
        "company": "LEADER S.A.S",
        "location": "Le Havre",
        "link": "https://fr.linkedin.com/jobs/view/data-analyst-h-f-at-leader-s-a-s-3909699484?position=35&pageNum=0&refId=jBvsgtdGm8ta0dsilpa8wg%3D%3D&trackingId=nx78yvS12QieiR91FCSxDQ%3D%3D&trk=public_jobs_jserp-result_search-card",
        "description": "Les sociétés de LEADER GROUP représentées par près de 170 salariés en France, Allemagne, Autriche, Chine et Etats-Unis, proposent à leurs clients du monde entier un ensemble de produits – émulseurs, équipements mousse, appareils de recherche de victimes, ventilateurs de désenfumage, lances, canons incendies, caméras thermiques, etc. – de haute technicité et fiables en toutes circonstances pour protéger et secourir les personnes et les biens.\nL'innovation est l'un des moteurs essentiels du Groupe, qui s'appuie également sur un système d'amélioration continue et de responsabilité sociétale et environnementale.\nRaison d’être de Leader Group : « Aider à sauver des vies »\nPour répondre à sa dynamique de croissance, LEADER renforce ses équipes et recherche son/sa futur(e)\nData Analyst H/F\nCDI – temps plein – Le Havre/Octeville sur mer (76)\nVos missions\nRattaché(e) au site de LEADER et sous la responsabilité du Directeur Commercial et Marketing, le/la Data Analyst se charge de l'analyse des données commerciales et marketing pour aider à la prise de décisions éclairées au sein des entités du groupe. A ce titre vos principales missions seront de :\nRéaliser des analyses approfondies des données de ventes internes, et du marché des équipements concernés, incluant les tendances, la demande, et les innovations technologiques.\nÉtudier la concurrence pour comprendre leurs produits, tarifications, et stratégies marketing.\nCollaborer étroitement avec les équipes de vente, et chefs produits pour partager les insights du marché et orienter le développement de produits et les stratégies commerciales.\nÉlaborer des rapports détaillés et des présentations pour la direction, avec des recommandations permettant de guider les décisions stratégiques, et soutenir l’équipe commerciale.\nEtudier chaque marché et connaitre le potentiel en chiffres et en volumes dans chaque pays pour les activités de Leader et différentes familles de produits.\nRechercher, référencer et suivre les appels d’offres\nVotre profil\nTitulaire d’un bac + 4/5 en marketing ou statistiques, vous justifiez d’une première expérience du secteur industriel, B2B et des produits techniques.\nOrienté(e) amélioration continue, vous avez une maîtrise parfaite des outils informatiques (Excel), CRM et ERP, de bonnes compétences analytiques et la capacité à communiquer des informations complexes de manière claire et compréhensible.\nLa curiosité, le souci du détail et une bonne aisance relationnelle sont des qualités qui vous caractérisent.\nVotre maitrise de l’anglais vous permet de communiquer aisément à l’écrit comme à l’oral.\nDes déplacements nationaux et internationaux ponctuels sont à prévoir.\nInformations complémentaires\nVotre futur bureau est basé à Octeville sur Mer, commune littorale limitrophe du Havre, au cœur du siège social du Groupe.\nA votre salaire de base (35K€ à 38K€/an), s’ajoutent une prime annuelle, RTT, mutuelle d’entreprise, télétravail partiel possible, conciergerie d’entreprise, et des titres restaurant.\nSi vous vous reconnaissez dans ce descriptif, et souhaitez relever de nouveaux défis au sein d'une entreprise innovante, en pleine évolution, rejoignez-nous en envoyant votre candidature\nNous avons hâte de vous rencontrer et de découvrir comment vous pouvez contribuer à notre équipe dynamique et à nos projets passionnants.\nLes équipes de LEADER innovent chaque jour pour protéger et secourir.\nPour en savoir plus, n’hésitez pas à consulter notre site https://www.leader-group.company/fr\nShow more\nShow less",
        "details": {
            "JobDetail": [
                "Temps plein"
            ],
            "TypeContract": "CDI",
            "Salary": "35K",
            "Level": "",
            "Experience": null
        },
        "title": "data analyst",
        "skills": {
            "Other": [
                "Statistiques"
            ]
        }
    },
    {
        "source": "LinkedIn",
        "company": "Volvo Group",
        "location": "Vénissieux, Auvergne-Rhône-Alpes, France",
        "link": "https://fr.linkedin.com/jobs/view/data-analyst-at-volvo-group-3860811035?position=36&pageNum=0&refId=jBvsgtdGm8ta0dsilpa8wg%3D%3D&trackingId=Pr5ZjV2XGcCz4zrvvT5ZTQ%3D%3D&trk=public_jobs_jserp-result_search-card",
        "description": "Transport is at the core of modern society. Imagine using your expertise to shape sustainable transport solutions for the future? If you seek to make a difference on a global scale, working with next-gen technologies and the sharpest collaborative teams, then we could be a perfect match.\nWhat You Will Do\nAt DIGITAL&IT DATA you will contribute to the transformation of our company, the transport industry and society at large. You will:\nDrive workshops with the business stakeholders to understand their business context and to collect their needs.\nBecome a Data expert on one or more business domains, to draw conclusions and to provide answers to business stakeholders questions.\nAccess, manipulate, query, and analyze data using different software, tools and techniques.\nBe part of the data modeling process (design and implementation) as well as in the definition of business rules that will ensure data consistency and quality.\nPre-process, clean and structure data to facilitate data exploration and advanced analytics activities.\nDesign and implement dashboards using advanced visualization tools.\nWork in cross functional agile teams to continuously experiment, iterate and deliver on new product objectives.\nBe an active member of the Data Analyst Chapter, sharing knowledge and best practices with your peers.\nBenefit from dedicated trainings to maintain and develop your Data Analyst skills.\nYour Future Team\nAs Data Analyst, you will be part of A&BI (Analytics & Business Intelligence) Trucks Dealer agile team. You will have opportunity to work on heterogenous topics such as (non exhaustive list):\nPaperless NLP: Support Paperless project thanks to NLP (Natural Language Processing) & AI (Artificial Intelligence) processes,\nDealer Quality program: Set of Key Performance Indicators on all Dealer processes to support Sales Area organization,\nSet up Data Product on Azure to support smart business services,\nBe part of the maintenance team to ensure business process continuity, ...\nWho are you?\nDo you dream big? We do too, and we are excited to grow together. Are you the one?\nHaving a master degree or equivalent in IT.\nData & Data Analysis has been your world for 3-5 years now.\nYou are an experienced Data Analyst looking for new challenges in the transport industry. You are proactive problem solver with innovative thinking with a strong sense of teamwork.\nWriting SQL and doing data modelling are natural activities for you.\nYou are experienced working on data manipulation and data modeling.\nYou are experienced designing and developing dashboard using at least one visualization tool (such as PowerBI for example).\nYou are familiar with Azure Data Analytics Stack (Storage accounts, Databricks, Azure Data Factory, SQL Server, SQL Data base, etc...).\nYou are familiar writing scripts on Python to do data preparation/cleaning.\nYou have excellent communication skills in French and English (C1 level)\nReady for the next move?\nAre you excited to bring your skills and disruptive ideas to the table? We can’t wait to hear from you. Apply today!\nWe value your data privacy and therefore do not accept applications via mail.\nWho We Are And What We Believe In\nOur focus on Inclusion, Diversity, and Equity allows each of us the opportunity to bring our full authentic self to work and thrive by providing a safe and supportive environment, free of harassment and discrimination. We are committed to removing the barriers to entry, which is why we ask that even if you feel you may not meet every qualification on the job description, please apply and let us decide.\nApplying to this job offers you the opportunity to join\nVolvo Group.\nEvery day, across the globe, our trucks, buses, engines, construction equipment, financial services, and solutions make modern life possible. We are almost 100,000 people empowered to shape the future landscape of efficient, safe and sustainable transport solutions. Fulfilling our mission creates countless career opportunities for talents with sharp minds and passion across the group’s leading brands and entities.\nGroup Digital & IT\nis the hub for digital development within Volvo Group. Imagine yourself working with cutting-edge technologies in a global team, represented in more than 30 countries. We are dedicated to leading the way of tomorrow’s transport solutions, guided by a strong customer mindset and high level of curiosity, both as individuals and as a team. Here, you will thrive in your career in an environment where your voice is heard and your ideas matter.\n‘\nData\n’ is a new function within Volvo Digital & IT with the goal to unlock the power of data for the whole Volvo Group to become a fully data-driven company! With data, the core component of our transformation journey, we will, together with our data talents, make the Volvo Group 2030 vision happen. We will take care of all the aspects of Data, how it is quality assured, documented, made available, prepared and consumed through BI, Analytics and Machine Learning. We have an ambitious transformation in front of us, with an implementation of the Data Layer in Azure as well as the reinforcement of Data Governance and Data Management in the full Group.\nThe ‘Data’ function is a large multi-cultural organization with 600+ employees and contractors located mainly in 7 countries - Sweden, Poland, India, Belgium, Brazil, USA, and France. In this role you will be joining the Data Analyst Chapter team in France.\nWe collaborate with other parts of the organization, both in Volvo Digital & IT, with Truck Divisions, Business Areas and Group Functions. We foster an environment where ideas, thoughts and opinions can be shared. We are team players with clear common ambitions, and we win together.\nShow more\nShow less",
        "details": {
            "JobDetail": [
                "Full"
            ],
            "TypeContract": "",
            "Salary": "",
            "Level": "",
            "Experience": null
        },
        "title": "data analyst",
        "skills": {
            "ProgLanguage": [
                "Python"
            ],
            "DataBase": [
                "SQL"
            ],
            "BigData": [
                "Databricks"
            ],
            "CloudComputing": [
                "Azure"
            ],
            "DBMS": [
                "SQL Server"
            ],
            "Collaboration": [
                "Teams"
            ],
            "Other": [
                "Machine Learning"
            ],
            "EnSoftSkils": [
                "Teamwork",
                "Communication",
                "Organization"
            ]
        }
    },
    {
        "source": "LinkedIn",
        "company": "Malt",
        "location": "Paris, Île-de-France, France",
        "link": "https://fr.linkedin.com/jobs/view/senior-data-analyst-at-malt-3916770897?position=37&pageNum=0&refId=jBvsgtdGm8ta0dsilpa8wg%3D%3D&trackingId=Jzp%2FN8TZv3I1hmLBJnA%2FGw%3D%3D&trk=public_jobs_jserp-result_search-card",
        "description": "Discover our galaxy 🪐\nSince 2013, when Malt was founded by Vincent Huguet and Hugo Lassiège, we have become Europe’s fastest-growing freelance marketplace.\nBy acquiring Comatch (the Berlin-based leading marketplace for top freelance management consultants and industry experts) in 2022, we’re now home to a dynamic community of 550k+ freelancers, 70k+ companies, and 700+ Malters.\nWe’ve built the industry’s leading freelance management solution — all on a powerful, data driven tech platform — to match companies with the right freelance talent.\nBut we’re more than just a connector. Our marketplace streamlines freelancer-client communications, simplifies administrative and legal tasks, expedites invoicing and payments, and so much more.\nToday, our company is growing fast! We need people like you to help us write this next chapter.\nWe Are a Tech Company With a Human Approach 👽\nStrong company culture fueled by 700+ Malters from 40 countries\nOffices and teams in France, Germany, Spain, Belgium, United Kingdom, the Netherlands, Switzerland and the Middle East\nCommitted to equality and diversity (50% of people managers are women)\nStrong career path policies allowing all Malters to develop and grow equally\nBacked by renowned investors including ISAI, Eurazeo Growth, Goldman Sachs and BPI France\nRecognized twice by LinkedIn as one of the best start-ups to work at\nExplore your future career 🔭\nYou would be part of Malt’s data team, an international team of about 30 people, with various profiles, including 7 data analysts, analytics engineers, data engineers, data scientists, and economists... The team is led by\nClaire Lebarz\n, Chief Data & AI Officer @ Malt, and former Head of Data @ Airbnb.\nJoin us and become part of the #FutureOfwork!\nKey Responsibilities ✨\nDevelop a deep understanding of our freelancers and clients and how they interact with each other and with our product\nBe a partner to product and business teams across the marketplace, helping them to better understand their performance through strategic analytics and structured thinking\nSupport our most strategic topics with deep-dive analytics, insights, recommendations\nEmpower the teams across Malt to answer data questions quickly and easily by building high-quality ground truth data sets, metrics and dashboards.\nContribute to the modelization of our databases and semantic layer along with analytics engineers\nBe a key member of the data team, helping spread the data and AI culture within Malt\nAbout You 🧑‍🚀\nYou have a Master’s degree in a quantitative field (e.g., Statistics, Econometrics, Computer Science, Engineering, Mathematics, Data Science, Operations Research) or in Business\nYou have +3 years of experience as a data analyst in a fast-paced and quantitative environment (start-up, scale-up, consulting…)\nYou consider yourself a full-stack data analyst: You write SQL perfectly, you know how to work with ETLs, you’ve been using data modelization tools such as dbt, you can write simple Python scripts… You are also very comfortable in using data visualization tools (e.g. Looker, Metabase, Tableau…)\nYou have strong communication (written and oral), presentation-building and storytelling skills\nYou are fluent in English\nYou are curious and eager to learn new things and grow\nWhat makes you different from others? 🫵\nYou have good business acumen, but you also have a “hacker” mindset, you enjoy leveraging technology to find solutions to problems\nYou have a growth mindset: you are comfortable in navigating and excelling in fast-paced environments with no playbook for success\nYou have an ability to influence people, but you are also a strong team player\nHow to join the mission? 🚀\nScreening with Alex, our Tech Talent Acquisition Manager, to better understand your background, aspirations and answer your questions (45 minutes)\nExperience discussion and technical assessment with the Data Director (Gautier Chenard, your future manager) (45mn)\nTake home assignment and restitution to the Data Director & a Data Analyst (1h)\nInterview with Claire, our Chief Data Officer (30mn)\nMalt is the perfect space to thrive personally and professionally 💫\nOnboarding: Before easing into your new role, you’ll spend your first week learning about our culture, products, and services with other onboardees at our office in Paris\nEquity: Every Malter is entitled to stock options\nLunch vouchers (legal benefit): €9/day on your Swile card\nTransportation (legal benefit): 50% reimbursement (any type of transport)\nRTT: From 8 to 12 days off\nSports: company participation to a Gymlib membership\nMalt sabbatical: After three years, every Malter is entitled to a one month paid sabbatical leave\nFree books: If you’re interested in learning more about any topic relevant to Malt’s business, just tell us the books you’d like to read, and we’ll order them for you—without any questions asked or approval processes to follow\nRemote work: Hybrid remote policy\nAnnual team building events\nReady? Get your ticket to Malt 🪐\nShow more\nShow less",
        "details": {
            "JobDetail": [
                "Remote",
                "Full"
            ],
            "TypeContract": "",
            "Salary": "",
            "Level": "",
            "Experience": null
        },
        "title": "data analyst",
        "skills": {
            "ProgLanguage": [
                "Python"
            ],
            "DataBase": [
                "SQL"
            ],
            "DataVisualisation": [
                "Tableau"
            ],
            "Collaboration": [
                "Teams"
            ],
            "EnSoftSkils": [
                "Communication"
            ]
        }
    },
    {
        "source": "LinkedIn",
        "company": "Getaround",
        "location": "Paris, Île-de-France, France",
        "link": "https://fr.linkedin.com/jobs/view/data-analyst-at-getaround-3913446628?position=38&pageNum=0&refId=jBvsgtdGm8ta0dsilpa8wg%3D%3D&trackingId=1fazPRFKmLVIT6qaPmVL5A%3D%3D&trk=public_jobs_jserp-result_search-card",
        "description": null,
        "details": {
            "JobDetail": [
                "Remote",
                "Full"
            ],
            "TypeContract": "",
            "Salary": "",
            "Level": "",
            "Experience": null
        },
        "title": "data analyst"
    },
    {
        "source": "LinkedIn",
        "company": "Richard Attias & Associates",
        "location": "Paris",
        "link": "https://fr.linkedin.com/jobs/view/junior-data-analyst-at-richard-attias-associates-3916877308?position=39&pageNum=0&refId=jBvsgtdGm8ta0dsilpa8wg%3D%3D&trackingId=eDRP4ZevCdv3sGQIe%2BPRiQ%3D%3D&trk=public_jobs_jserp-result_search-card",
        "description": "Description du poste :\nDans le cadre de son expansion et de son engagement à consolider ses ressources, Richard Attias & Associés souhaite renforcer ses équipes en améliorant et en étoffant sa base de données.\nNous recherchons 5 collaborateurs talentueux qui auront les principales missions suivantes :\nMise à jour, maintenance et enrichissement de la base de données existante, notamment en identifiant et en ajoutant de nouveaux contacts pertinents issus de la presse internationale (les domaines de l'économie et de la finance).\nResponsabilités :\n·       Tâches administratives quotidiennes :\n·       Mise à jour des contacts, maintien de l'exactitude et de la cohérence des informations de la base\n·       Identification de nouveaux contacts qualifiés en lisant la presse internationale, en mettant des alertes internet de suivi de contacts/ domaines importants prioritaires pour nos événements\n·       Collaborer avec d'autres départements pour assurer la cohérence et la qualité des données.\n·       Tâches liées à des projets :\n·       Établir et maintenir des listes de conférenciers et de participants pour des événements spécifiques\n·       Collaborer avec les équipes de projet pour développer des communautés innovantes d’influencers / experts mondiaux\n·       Identifier des tendances politiques, sociales, économiques et mondiales pertinentes pour les sujets qui positionnent RA&A en tant que leader en communication stratégique\nProfil recherché :\n·       Formation digitale / data management. 1ere expérience en tant qu'analyste de données.\n·       Excellente maîtrise de MS Office, Excel, Powerpoint et bonne connaissance de Salesforce.\n·       Bonne compréhension de l'économie et de la politique internationale, conscience des problèmes mondiaux, de l'innovation internationale\n·       Grande curiosité intellectuelle et proactivité\n·       Compétences organisationnelles exceptionnelles et capacité à effectuer plusieurs tâches à la fois.\n·       Rigueur, sens du détail et esprit d'analyse développé\n·       Flexibilité pour s'adapter à un environnement dynamique.\n·       Aptitude à travailler en équipe et à collaborer avec différents services.\n·       Anglais courant + maitrise d’une autre langue appréciée\nPour postuler :\nMerci d'envoyer votre CV et une lettre de motivation à laurence.ania@richardattiasassociates.com\nLa rémunération proposée sera discutée en fonction de l'expérience et des compétences du candidat retenu.\nShow more\nShow less",
        "details": {
            "JobDetail": [],
            "TypeContract": "",
            "Salary": "",
            "Level": "",
            "Experience": null
        },
        "title": "data analyst",
        "skills": {
            "EnSoftSkils": [
                "Communication"
            ]
        }
    },
    {
        "source": "LinkedIn",
        "company": "Wewyse",
        "location": "Paris, Île-de-France, France",
        "link": "https://fr.linkedin.com/jobs/view/data-analyst-h-f-at-wewyse-3811756415?position=40&pageNum=0&refId=jBvsgtdGm8ta0dsilpa8wg%3D%3D&trackingId=rMTYnswMxIJJ%2BPlDS7ZOnw%3D%3D&trk=public_jobs_jserp-result_search-card",
        "description": "Wewyse\nest un cabinet de conseil spécialisé en\nData et en Intelligence Artificielle\n. C'est aussi et surtout une communauté de passionnés partageant l'ambition de grandir ensemble et d'ouvrir le champ des possibles dans leurs domaines.\nSi vous pensez que la Data et l'Intelligence Artificielle ont beaucoup à offrir au monde de demain, et si vous souhaitez apporter votre contribution à ce monde, avec humilité et enthousiasme, alors vous êtes un Wyser en puissance.\nÊtre\nData Analyst\nchez Wewyse c'est :\nIntégrer une communauté d’experts Data passionnés,\nRecevoir et partager des connaissances, des savoirs-faire lors de nombreux évènements internes et acquérir constamment de nouvelles compétences,\nIntervenir sur des projets à la fois techniques et business, souvent dans un contexte international, avec des forts enjeux stratégiques auprès de nos clients dans tous les secteurs (retail, énergie, médias, transports, banque et assurance …)\nViser l’excellence dans la qualité et l’actionnabilité des analyses, grâce à la maîtrise technique des outils en Data Analytics (développement, notebooks, visualisation, techniques de statistiques avancées…) et la bonne compréhension des enjeux business de nos clients,\nParticiper à des projets innovants, impactants et positifs au sein de notre Datalab, en équipe, avec des partenaires académiques (CentraleSupelec, …) et parfois avec des starts up, afin de laisser exprimer vos valeurs et vos idées,\nAvoir la possibilité de s’impliquer dans le développement de Wewyse (participer au recrutement, concevoir des formations, donner des masterclass en école d’ingénieur, participer à l’avant-vente business, piloter des projets au sein du Datalab, développer de nouveaux partenariats …)\nÊtre encouragé, conseillé et accompagné dans un parcours de formation adapté à vos ambitions professionnelles et avec un budget dédié,\nFaire partie de la famille Wemanity, créer rapidement un réseau d’experts et de personnes reconnues dans leur domaine, participer aux évènements communs (voyage annuel, talks, afterworks ...) et bénéficier des multiples opportunités de carrière au sein du Groupe,\nAvoir l’opportunité de travailler avec une équipe dynamique, dans une ambiance start-up et à taille humaine dans le centre de Paris (Opéra 9ème arrondissement)\nCe que nous aimons :\nLes personnalités ouvertes, curieuses, ambitieuses\nUn excellent niveau en\nSQL\nUne première expérience en\nPython\nLa maîtrise d’un outil de Data Visualisation\n(PBI, Tableau, Qlik, Looker, Data Studio …)\nUne expérience dans l’utilisation de\nJupyter Notebook / Databricks Notebook\nest fortement appréciée\nL’aisance en communication\nL’esprit de synthèse\nL'anglais\nVous vous reconnaissez ? Alors n'hésitez pas à postuler !\nShow more\nShow less",
        "details": {
            "JobDetail": [],
            "TypeContract": "",
            "Salary": "",
            "Level": "",
            "Experience": null
        },
        "title": "data analyst",
        "skills": {
            "ProgLanguage": [
                "Python"
            ],
            "DataBase": [
                "SQL"
            ],
            "BigData": [
                "Databricks"
            ],
            "DataVisualisation": [
                "Tableau"
            ],
            "Other": [
                "Statistiques"
            ],
            "EnSoftSkils": [
                "Communication"
            ]
        }
    },
    {
        "source": "LinkedIn",
        "company": "Lincoln France",
        "location": "Hauts-de-France, France",
        "link": "https://fr.linkedin.com/jobs/view/data-analyst-h-f-at-lincoln-france-3827765148?position=41&pageNum=0&refId=jBvsgtdGm8ta0dsilpa8wg%3D%3D&trackingId=qxtFap4aZ1CurvlNOOEeEw%3D%3D&trk=public_jobs_jserp-result_search-card",
        "description": "DATA ANALYST H/F\nCDI\n3 ans minimum\nChez Lincoln\n, nous formons une communauté d'innovateurs passionnés qui redéfinissent l'analyse de données depuis\nplus de 30 ans\n. En tant que\nPure Player Data\n, notre expertise est reconnue dans les domaines\nde la Modern BI, du Big Data et de la Science des données\n.\nNotre mission ?\nTransformer les données en solutions concrètes pour nos clients grands comptes dans divers secteurs tels que la banque, le retail, les télécoms, l'industrie, la santé, etc.\nDescription de poste\nNous recherchons un\nData Analyst H/F\npour accompagner nos clients dans leurs projets stratégiques.\nVos missions\nCollecter, nettoyer et traiter les données provenant de différentes sources.\nAnalyser les données pour identifier des tendances, des corrélations et des anomalies.\nConcevoir et développer des tableaux de bord et des rapports pour présenter les résultats de manière claire et concise.\nCollaborer avec les équipes clients pour comprendre leurs besoins et recommander des solutions adaptées.\nPrérequis :\nMaîtrise avancée des langages de programmation\n(SQL, Python, R, etc.).\nConnaissance approfondie des bases de données relationnelles et non relationnelles.\nExpérience pratique avec des outils d'analyse de données\n(Tableau, Power BI, Looker, Qlik etc.).\nFortes compétences analytiques et capacité à transformer les données brutes en insights exploitables.\nExpérience de travail en\nméthode Agile\npour la gestion de projet et le développement de solutions.\nCapacité à travailler de manière autonome et en équipe.\nExcellentes compétences en communication et en présentation.\nLes plus du poste\nEnvironnement Collaboratif\n: projets innovants favorisant le partage des connaissances.\nAccompagnement individualisé et de proximité\n: formations certifiantes, attribution d’un Career Manager pour vous orienter dans votre trajectoire professionnelle, opportunités d’évolution de carrière.\nFlexibilité du Travail\n: Télétravail et horaires flexibles pour votre équilibre vie professionnelle-personnelle.\nRémunération Compétitive\n: Salaire compétitif avec des avantages sociaux attrayants.\nMobilité\n: Possibilité de mobilité à Paris, Lyon ou Aix-en-Provence offrant des expériences diversifiées au sein de Lincoln.\nNotre processus de recrutement :\nUn entretien RH (1h) et entretien technique (1h)\nCette annonce n’est pas faite pour vous si :\nVous êtes freelance et vous comptez le rester !\nToujours là ? Postulez et rejoignez nos\n400 experts en Data\n😉.\nShow more\nShow less",
        "details": {
            "JobDetail": [],
            "TypeContract": "CDI",
            "Salary": "400",
            "Level": "",
            "Experience": "3 an(s)"
        },
        "title": "data analyst",
        "skills": {
            "ProgLanguage": [
                "R",
                "Python"
            ],
            "DataBase": [
                "SQL"
            ],
            "DataAnalytics": [
                "R"
            ],
            "DataVisualisation": [
                "Power BI",
                "Tableau"
            ],
            "Other": [
                "Big Data"
            ],
            "EnSoftSkils": [
                "Communication"
            ]
        }
    },
    {
        "source": "LinkedIn",
        "company": "Akademija Oxford",
        "location": "Boulogne-Billancourt, Île-de-France, France",
        "link": "https://fr.linkedin.com/jobs/view/data-analyst-sas-et-qlik-at-akademija-oxford-3917871100?position=42&pageNum=0&refId=jBvsgtdGm8ta0dsilpa8wg%3D%3D&trackingId=NhudTSdpC%2FS%2ByPoPbky7aw%3D%3D&trk=public_jobs_jserp-result_search-card",
        "description": "Un des grands acteurs du secteur des assurances, situé dans les Hauts-De-Seine, recherche un.e Data Analyst SAS et QLIK, préparant un Mastère spécialisation Big Data, en alternance pour le mois de Septembre 2021.\nShow more\nShow less",
        "details": {
            "JobDetail": [],
            "TypeContract": "",
            "Salary": "",
            "Level": "",
            "Experience": null
        },
        "title": "data analyst",
        "skills": {
            "Other": [
                "Big Data"
            ]
        }
    },
    {
        "source": "LinkedIn",
        "company": "Credit Agricole Consumer Finance",
        "location": "Roubaix, Hauts-de-France, France",
        "link": "https://fr.linkedin.com/jobs/view/data-analyst-senior-at-credit-agricole-consumer-finance-3870530425?position=43&pageNum=0&refId=jBvsgtdGm8ta0dsilpa8wg%3D%3D&trackingId=K%2Bzy5zcPgSd8rR8rgIQ37Q%3D%3D&trk=public_jobs_jserp-result_search-card",
        "description": "Filiale spécialisée du Groupe Crédit Agricole en crédit à la consommation, Crédit Agricole Consumer Finance est l'un des leaders en Europe du crédit à la consommation et des solutions de financement. Il distribue une gamme complète de produits et services associés, en France et à l'international.\nEn qualité de Lead Data Analyst, vous rejoindrez l’équipe Etudes et Data Science dans leur mission d’éclairer l’entreprise et ses décideurs par des éléments de définition et de compréhension du business model et par des analyses stratégiques et opérationnelles. Plus qu’une aide à la décision, les membres de l’équipe ont surtout un objectif de conseil à l’égard des décideurs de Crédit Agricole Consumer Finance et de ses partenaires.\nVous aurez pour missions principales de :\nCollaborer en transverse avec plusieurs départements internes (Marketing Direct, Digital, Web, Commerces BtoC, BtoB, etc)\nDéfinir des stratégies d’analyse de données permettant de répondre de manière pertinente et pragmatique aux problématiques des clients internes\nParticiper à des projets d’entreprise et gérer des projets analytiques transverses de bout en bout\nCommuniquer efficacement les résultats de vos analyses aux parties prenantes clés pouvant aller des décideurs internes aux équipes opérationnelles\nGarantir la fiabilité et la pérennité (robustesse et pertinence) des analyses réalisées en veillant à la qualité de la donnée\nRéaliser des études approfondies sur nos clients directs et ceux recrutés via nos partenaires Retail/grandes distributions afin d’apporter à l’entreprise une vision globale de son portefeuille\nAssurer un management fonctionnel de plusieurs collaborateurs Data et être en capacité de prendre en charge des « Squads » ou plusieurs collaborateurs se réunissent afin de délivrer sur un objectif commun\nVotre profil :\nVous avez une expérience d’au moins trois ans sur un poste équivalent\nVous savez combiner une profondeur méthodologique avec une approche pragmatique de recherche de la valeur\nVous êtes en capacité à vous mettre au service du collectif, et êtes à l'aise avec la vulgarisation de votre savoir-faire et de vos compétences\nVous avez envie de rejoindre une équipe dynamique, bienveillante avec une trajectoire ambitieuse sur les deux prochaines années\nVous maîtrisez le langage SQL. Des expériences sur Snowflake, PowerBI et/ou SAS seraient des plus\nShow more\nShow less",
        "details": {
            "JobDetail": [],
            "TypeContract": "",
            "Salary": "",
            "Level": "",
            "Experience": null
        },
        "title": "data analyst",
        "skills": {
            "DataBase": [
                "SQL"
            ],
            "DBMS": [
                "Snowflake"
            ]
        }
    },
    {
        "source": "LinkedIn",
        "company": "EXOMIND",
        "location": "Île-de-France, France",
        "link": "https://fr.linkedin.com/jobs/view/data-analyst-h-f-at-exomind-3912508157?position=44&pageNum=0&refId=jBvsgtdGm8ta0dsilpa8wg%3D%3D&trackingId=j9uQZPtg0HquFycfbCZ46w%3D%3D&trk=public_jobs_jserp-result_search-card",
        "description": "Fusion entre le\ncabinet de conseil IT\net\nagence de développement\n, nous accompagnons les grandes entreprises et les pure players dans la conception et le développement de leurs solutions digitales.\nNous réalisons des applications web et mobiles sur mesure. Nos équipes composées de Tech Lead, Développeurs, Testeur, Product Owner et Designers maitrisent l’ensemble de la chaine de réalisation projet : conseil, design, développement, qualité et post production.\n30 clients\ngrands comptes et pure players présents sur différents secteurs (médias, e-commerce, industrie, bancaire, énergie et transport).\nCe que nous recherchons, ce que nos clients attendent de nos Data Analyst ?\nAssurer la collecte des données techniques en provenance du Datawarehouse\nTraiter et consolider les données techniques via\nDataiku\nDéfinir des indicateurs clés pour orienter les prises de décisions via\nPower BI\nPouvoir collaborer au sein d’une équipe structurée et mener les actions nécessaires avec les équipes techniques et les PO\nMaitrises des outils :\nExcel avancé, SQL, Base Oracle, JIRA\n,\nNiveau d'\nanglais\ncourant\nComment avancer ensemble ?\nNous faisons connaissance : Vous nous présentez votre parcours, votre projet, et vos valeurs et nous vous parlons de nous, de notre culture et de nos attentes\nNous évaluons votre expertise : L’évaluation qui concerne à la fois les compétences techniques/fonctionnelles, mais aussi les soft skills comme l’adaptabilité, le relationnel, le mindset...\nNous définissons les enjeux de notre collaboration : Nous organisons une rencontre avec le manager de votre future team pour valider le process, intégrer votre cercle et vous projeter sur votre prochain challenge\nShow more\nShow less",
        "details": {
            "JobDetail": [],
            "TypeContract": "",
            "Salary": "",
            "Level": "",
            "Experience": null
        },
        "title": "data analyst",
        "skills": {
            "DataBase": [
                "SQL"
            ],
            "DataVisualisation": [
                "Power BI"
            ],
            "Collaboration": [
                "JIRA"
            ],
            "EnSoftSkils": [
                "Collaboration"
            ]
        }
    },
    {
        "source": "LinkedIn",
        "company": "Inetum",
        "location": "Niort, Nouvelle-Aquitaine, France",
        "link": "https://fr.linkedin.com/jobs/view/data-analyst-h-f-at-inetum-3892405912?position=45&pageNum=0&refId=jBvsgtdGm8ta0dsilpa8wg%3D%3D&trackingId=CDvZEmy7aGs07kF5ZWkAJg%3D%3D&trk=public_jobs_jserp-result_search-card",
        "description": "Détail de l'offre\nInformations générales\nEntité de rattachement\nInetum est un leader européen des services numériques. Pour les entreprises, les acteurs publics et la société dans son ensemble, les 28 000 consultants et spécialistes du groupe visent chaque jour l'impact digital des solutions qui contribuent à la performance, à l'innovation et au bien commun.\nPrésent dans 19 pays au plus près des territoires, et avec ses grands partenaires éditeurs de logiciels, Inetum répond aux enjeux de la transformation digitale avec proximité et flexibilité.\nPorté par son ambition de croissance et d'industrialisation, Inetum a généré en 2023 un chiffre d'affaires de 2,5 milliards d'€.\nPour répondre à un marché en croissance continue depuis plus de 30ans, Inetum a fait le choix délibéré de se recentrer sur 4 métiers afin de gagner en puissance et proposer des solutions sur mesure, adaptées aux besoins spécifiques de ses clients le conseil (Inetum Consulting), la gestion des infrastructures et applications à façon (Inetum Technologies), l'implémentation de progiciels (Inetum Solutions) et sa propre activité d'éditeur de logiciels (Inetum Software). Inetum a conclu des partenariats stratégiques avec 4 grands éditeurs mondiaux - Salesforce, ServiceNow, Microsoft et SAP et poursuit une stratégie d'acquisitions dédiée afin d'entrer dans le top 5 européen sur ces technologies et proposer la meilleure expertise à ses clients.\nTous nos postes sont ouverts aux personnes en situation de handicap.\nDescription du poste\nMétier\nData - Data IT\nIntitulé du poste\nData Analyst H/F\nContrat\nCDI\nDescription De La Mission\nInetum Chauray, recherche un Consultant Data h/f, pour une mission en centre de service ou chez notre client, pour travailler sur des projets d'analyses de données Assurances.\nEn tant que Data Analyst, vous participerez à l'évolution du SI de\nnos clients et vos missions seront variées.\nCompétences requises\nMaîtrise d'un ETL - Talend OU Informatica.\nUne expérience en Analyse fonctionnelle et une compétence en résolution d'incident.\nVous êtes certifié(e) Google avec une connaissance d\nGCP, c'est IDEAL.Base de données Oracle, SQ\nOutils décisionnels de restitution BI Qliksense, Qlikview\nBITQUERY / GCP\nCe que nous offrons\nUn environnement de travail inclusif et respectueux.\nDes opportunités de formation et de développement professionnel.\nUne fourchette de rémunération allant de 38K et 42k selon votre niveau d'expertise\nProfil\nDe formation supérieure, vous possédez une expérience de 3 ans minimum dans le domaine de la data.\nLocalisation du poste\nLocalisation du poste\nFrance, Ouest, 79 Deux-Sèvres\nVille\nNiort\nCritères candidat\nNiveau d'études min. requis\nBac+2\nNiveau d'expérience min. requis\nPlus de 2 ans\nShow more\nShow less",
        "details": {
            "JobDetail": [],
            "TypeContract": "CDI",
            "Salary": "",
            "Level": "",
            "Experience": "30 an(s)"
        },
        "title": "data analyst",
        "skills": {
            "CloudComputing": [
                "GCP"
            ]
        }
    },
    {
        "source": "LinkedIn",
        "company": "Teads",
        "location": "Montpellier, Occitanie, France",
        "link": "https://fr.linkedin.com/jobs/view/product-data-analyst-at-teads-3860869090?position=46&pageNum=0&refId=jBvsgtdGm8ta0dsilpa8wg%3D%3D&trackingId=kUSSzQz%2Fu%2Fh89Vq3sDsh1g%3D%3D&trk=public_jobs_jserp-result_search-card",
        "description": "At Teads, we do quality and responsible advertising, at scale. We invented outstream video advertising and now have a reach of 1,9 billion unique users per month powered by an end-to-end proprietary platform. We foster a sustainable advertising and media ecosystem by funding quality journalism and respectfully connecting brands to consumers.\nTo innovate, we have created a strong company culture that empowers passionate people, gives them the right tools and trusts them to do their jobs as best they can. Teads roadmap is full of ambitious and strategic projects related to the evolution of our offering for both publishers and advertisers.\nOur company offers a\nhybrid work model\n, allowing two days in-office and the flexibility to work from home for the rest of the week. Additionally, we offer relocation packages for those who are interested in moving to one of our engineering offices.\n👉 Join a team of passionate people who build quality and responsible advertising, at scale!\nOur Business Intelligence Community\nWe want to empower everyone at Teads to take data-driven decisions. To achieve this, we federate a community of Data Analysts, distributed across our product areas. They infuse a data-driven culture within the entire company by driving proactive product analysis and building self-serve Business Intelligence tools. They also make sure everyone else within their product area is empowered to use these tools or run ad-hoc studies of any kind (business analysis, financial reporting, exec summary, growth analysis, etc.).\nWhat will you do?\nAs a\nData Analyst\nin the Product department, your goal is to help infuse a data-driven culture at Teads.\nTo develop BI within your product area, you will proactively:\nDrive the adoption of standard key product metrics, leveraging Teads BI stack (datamarts, data catalog, dashboards, etc.), by making them available in self-service to everyone in the company, with a standardized and accepted definition.\nAssess the success of each product release, by defining and monitoring relevant metrics (success, adoption, etc.), and reporting them regularly to key stakeholders.\nHelp shape the product roadmap, by working closely with Product Managers, and by owning yourself a part of the roadmap, in order to assess business opportunities and challenges.\nDrive ad-hoc studies and self-serve data exploration, by building self-serve BI tools, and providing documented business models developed in close collaboration with Software Engineers.\nSpread BI knowledge and best practices, by animating BI rituals (workshops, trainings, demos, etc.) and keeping a good relationship with data enthusiasts of your product area (business analysts, product managers, leadership, etc.)\nYou will also be part of a community to develop BI transversely. As a member of this community, you will:\nGovern a BI roadmap, around a unified vision and common objectives.\nWork on global BI initiatives, such as standardizing the UI/UX of dashboards, BI learning & knowledge, or consolidating a centralized Data Catalog.\nDefine and share BI best practices, to enforce consistency across the board.\nOwn the complete BI cycle, by developing your technical skills and your knowledge of the ad-tech industry.\nHelp onboarding Data Analysts, with adequate documentation and training.\nWhat will you bring to the team?\nYour Skills And Experience\nAt least 2 years of experience as a Data Analyst.\nBachelor or Master degree in BI, engineering, mathematics, or marketing.\nAdvanced knowledge of SQL and BI tools (warehouse, datamarts, dataviz, etc.).\nAbility to efficiently communicate and collaborate with cross-functional teams.\nData-driven mindset and proactive approach.\nPassionate, innovative, and fast learner.\nStrong problem solving and analytical skills.\nFluent in English.\nBonus Points\nExperience with BI platforms (Looker, Tableau, PowerBI, SiSense, Qlik, Domo, etc.).\nExperience with modern data warehousing solutions (BigQuery, SnowFlake, Redshift, etc.).\nExperience in the digital advertising industry.\nExperience in coding.\nProficient in French.\nWhy work at Teads?\nAt Teads, Product and Engineering work hand in hand and are aligned towards the same goal: to\nscale our business\nwhile continuing to create\nnew and exciting products\n.\nWe value team spirit, pragmatism, listening and we encourage initiatives.\nWe promote end-to-end development: “You build it, you run it, you monitor it”.\nWe share knowledge and support with each other beyond any organizational boundary.\nWe fix issues during a blameless postmortem and learn from it so that it doesn’t happen twice.\nWe are working together to create great engineering, but we are also supportive to promote a great work-life balance.\nWe Care About You\nSecurity & Savings: Attractive package providing financial peace of mind, including competitive compensation, profit-sharing, daily meal vouchers (Swile), family health insurance (Alan), and a personalized relocation package (if needed).\nCareer Development: Continuous investment in our employees' skills: in-house and external training, tech conference opportunities, internal mobility (individual contributor or management career ladder).\nLife Balance: A well-balanced work-life for our employees is one of our top priorities: 35+ days off per year, hybrid work (2-3 days remote work per week, more is open to discussion), fully covered parental leave, and reserved daycare places.\nWellness: Prioritizing employee well-being through premium work equipment, enjoyable work environment (work-life balance, team building events, summits), remote work subsidy, promoting Diversity & Inclusion with internal & external initiatives (women speaking groups, dedicated school partnerships), dedicated charitable time and sustainability actions (Eco Tree, subsidy for eco-mobility).\nDiscover more about our culture and benefits on our Engineering website.\nAbout Teads\nTeads operates a leading, cloud-based, omnichannel platform that enables programmatic digital advertising across a global ecosystem of quality digital media.\nAs an end-to-end solution, Teads’ modular platform allows partners to leverage buy-side, sell-side, creative, data and AI optimization technologies. For advertisers and their agencies, Teads offers a single access point to buy the inventory of many of the world’s best publishers and content providers.\nThrough exclusive global media partnerships, Teads enables advertisers and agencies to reach billions of unique monthly users in brand safe, responsible advertising environments, while improving the effectiveness and efficiency of digital ad transactions.\nTeads partners with the leading marketers, agencies and publishers through a team of 1,200+ people in 50 offices across more than 30 countries.\nWe're committed to creating a dynamic work environment that values diversity and inclusion, and represents employees across a variety of skill sets. We embrace contributions from all ages, sexes, races, ethnicities, religions, sexual orientations and gender identities.\nShow more\nShow less",
        "details": {
            "JobDetail": [
                "Remote",
                "Full"
            ],
            "TypeContract": "",
            "Salary": "2",
            "Level": "",
            "Experience": null
        },
        "title": "data analyst",
        "skills": {
            "DataBase": [
                "SQL"
            ],
            "DataVisualisation": [
                "Tableau"
            ],
            "DBMS": [
                "BigQuery",
                "Snowflake"
            ],
            "Collaboration": [
                "Teams"
            ],
            "Other": [
                "Cloud"
            ],
            "EnSoftSkils": [
                "Problem Solving",
                "Leadership",
                "Flexibility",
                "Collaboration"
            ]
        }
    },
    {
        "source": "LinkedIn",
        "company": "Wemanity Lille",
        "location": "Lille",
        "link": "https://fr.linkedin.com/jobs/view/data-analyst-h-f-at-wemanity-lille-3890979963?position=47&pageNum=0&refId=jBvsgtdGm8ta0dsilpa8wg%3D%3D&trackingId=PwWHag%2Fa6dUQUflJ8WCYCg%3D%3D&trk=public_jobs_jserp-result_search-card",
        "description": "Fondée en 2018, l’agence\nWemanity Lille\nse développe d’année en année grâce aux talents qui font de cette aventure une réussite ! 🌈​\n3 mots pour la décrire ? Pétillante, à taille humaine et audacieuse !\nPour suivre cette dynamique nous recherchons des talents ayant l'envie de progresser et de se lancer dans une belle aventure professionnelle et humaine à nos côtés. 🌳\nNous recherchons un(e)\nData Analyst (H/F)\navec un minimum d'expérience de 3/4 ans, qui a envie d'apprendre et de dévoiler tout son potentiel à nos côtés !\nQui sommes-nous\n?\n💡\n🎢 Cabinet de conseil spécialisé en\ntransformations digitales et agiles.\n🌍 Présent à l’international :\nParis, Lille, Belgique, Pays-bas, Maroc et Luxembourg.\n👥\n600\ncoopérateurs passionnés.\n🍃Un pôle RSE débordant d’idées qui propose des projets à\nimpact\nsociaux\net\nenvironnementaux.\n💼​ Présence du Wemanity Learning Center permettant\nformations & certifications.\n🦸 Ton profil :\nTu es Data Analyst (H/F)\n, tu as une expérience de plus de 3/4 ans et tu souhaites rejoindre une équipe de passionnés ambitieux?\nTu aimes mettre en valeur les bonnes pratiques, apprendre et partager ? Cette offre est faite pour toi !\n🚀 Tes missions* :\nMaîtrise des outils d'analyse de données.\nExpérience avec les outils de visualisation de données (Tableau, Power BI).\nConnaissance des techniques d'analyse statistique et des modèles de machine learning.\nUtilisation de méthodologies Agile/Scrum.\nCollaboration avec des équipes interfonctionnelles.\n*Liste non exhaustive\n🌈Pourquoi Wemanity ?\nUn salaire attractif et de nombreux avantages (RTT, formations & certifications, primes vacances, CE, carte Swile …) ☀️\nDes projets variés à forte valeur ajoutée 🎈\nUne vraie montée en compétences avec notre pôle formation (formations, certifications) 🪄\nL’opportunité d’intégrer une communauté d’agilistes soudée 🚀\nLa possibilité d’intégrer des squads agiles qui fonctionnent en mode startup pour intervenir sur des projets from scratch en interne ou chez nos clients 🤹‍\nLa possibilité de travailler en réelle autonomie (télétravail) ☀️\nUne carrière évolutive au sein d’une entreprise pleine de projets 💪\nUne entreprise avec un réel engagement RSE 🌳\n📌\nNotre processus de recrutement en 3 étapes :\n1ère étape, ton profil nous intéresse ! Premier échange avec l’un de nos recruteurs passionnés pour faire connaissance et en savoir plus sur tes souhaits d’évolution.\n2ème étape, l’entretien technique : c’est le moment d’échanges sur la partie technique avec un membre de Wemanity (coopérateurs).\nEntretien final : Tu rencontreras un commercial afin de déterminer le projet et le client chez qui tu pourras évoluer et t’épanouir ! Suite à ces 3 échanges, je te souhaite d’obtenir ton billet d’entrée pour rejoindre l’aventure Wemanity !\nShow more\nShow less",
        "details": {
            "JobDetail": [],
            "TypeContract": "",
            "Salary": "3",
            "Level": "",
            "Experience": "4 an(s)"
        },
        "title": "data analyst",
        "skills": {
            "DataVisualisation": [
                "Power BI",
                "Tableau"
            ],
            "Other": [
                "Machine Learning"
            ],
            "EnSoftSkils": [
                "Collaboration"
            ]
        }
    },
    {
        "source": "LinkedIn",
        "company": "Listen too",
        "location": "Nantes, Pays de la Loire, France",
        "link": "https://fr.linkedin.com/jobs/view/data-analyst-at-listen-too-3890444112?position=48&pageNum=0&refId=jBvsgtdGm8ta0dsilpa8wg%3D%3D&trackingId=oJ2u4kAJZaJicFUonn5q2w%3D%3D&trk=public_jobs_jserp-result_search-card",
        "description": "📢 Imaginez un lieu où votre voix compte autant que vos compétences…\nChez Listen too, nous sommes convaincus que l’écoute est indissociable du progrès. Cultivée au quotidien, elle devient un catalyseur de croissance et de réussite, tant pour l’entreprise que pour ses collaborateur·rice·s.\nListen too est une agence conseil spécialisée depuis 2013 dans la digitalisation de la Relation Client & Collaborateur. Grâce à la justesse de l’accompagnement offert à nos clients comme à nos consultant·e·s, nous nous sommes construits au fil des ans sur notre marché une réputation de véritables « horlogers du conseil ».\nNos domaines d’expertise ?\n🎯 Le Product Management : pour porter la vision Produit et maximiser la création de valeur.\n🎨 Le Product Design : pour une conception Produit centrée utilisateur.\n🔧 Le Product TechOps : pour déployer les meilleures solutions digitales.\n📢 Le Product Marketing : pour maximiser le succès d’un produit/service sur son marché.\n📊 Le Product Data : pour mettre la donnée au cœur de la stratégie de nos clients.\n🤝 La Gouvernance projet : pour optimiser le mode de management et le cadre organisationnel de nos clients.\nÊtre listenien·ne, c’est être au cœur d’une entreprise qui valorise votre voix, votre parcours, et votre évolution. Ici, nous appliquons les principes du design thinking à votre carrière, co-construisant avec vous une trajectoire où vos passions, vos aspirations, et vos forces sont au premier plan.\n💪 Vos futures missions\nVous êtes passionné·e par le domaine de la Data et vous souhaitez rejoindre une équipe client avec des projets challengeants ?\nConcrètement, vous aurez l'opportunité de :\nIdentification des besoins en données de l'entreprise et leurs objectifs d'analyse.\nCollecte des données à partir de différentes sources telles que des bases de données, des fichiers Excel, des API, etc.\nNettoyage et préparation des données.\nAnalyse des data grâce aux langages de programmation tels que Python, SQL ou Excel.\nCréation de tableaux de bord, de graphiques et de visualisations.\nÉlaboration de rapports et des recommandations.\nCollaboration avec d'autres membres de l'équipe, tels que les Data Scientists et les Data Engineers, pour résoudre des problèmes complexes.\n😎 Votre vie de listenien·ne\nCe qu’on vous propose ?\n🤜 Être membre d’une communauté : partager et enrichir vos compétences au sein d’une équipe soudée.\n🤝 Être accompagné.e : dans votre progression professionnelle et votre quotidien par votre Consultant Manager, votre Business Manager et notre Responsable Expérience collaborateur·rice.\n🎓 Être formé·e en continu : grâce à un plan de développement des compétences co-construit et nourri par nos solutions d’e-learning (Linkedin Learning & Babbel), nos formations certifiantes et celles de la Listen too Academy, designées par nos consultant·e·s pour nos consultant·e·s.\n🚀 Être intrapreneur.e : encouragé à innover, échanger, entreprendre et ainsi contribuer à l’épanouissement du cabinet.\n☘️ Être engagé.e : à nos côtés dans une démarche sociétale et environnementale responsable et durable.\n🤗 Être « bien » ! : parce que le bien-être physique et mental de nos collaborateur.rice.s est au cœur de notre réussite.\nConcrètement ?\n🎉 De multiples occasions de passer de bons moments avec notamment notre fameux sémineige, des afterworks et des teambuildings.\n🏋️‍♂️ Du sport et de la santé avec des évènements sportifs, nos partenaires Gymlib, Zenride, Moka.care et le programme Vitality.\n😎 Du confort avec du télétravail indémnisé.\n🤗 Toujours plus liens avec un onboarding aux petits oignons, notre programme de parrainage, nos newsletters, nos podcasts et nos webinaires.\n🫶 De l’engagement solidaire avec notre partenaire Vendredi, plateforme de mécénat de compétence et bénévolat\n👍 De nombreux avantages avec notre CSE, des tickets restaurant, une prime vacances, des primes de cooptation, de participation, de développement…\nProfil recherché\nVous avez minimum 5 ans d’expérience en tant que Data Analyst (ou sur des fonctions associées de Data scientist / Data engineer)\nVous maitrisez les différents outils indispensable au métier (SQL, Google Sheets, Python (Pandas/Numpy), Microsoft Power Query, outils de Data Visualisation)\nVous avez envie de progresser et d’évoluer au sein d’une société à taille humaine sur une expertise ou des responsabilités managériales\nVous rêvez de vous investir au sein d’une communauté soudée et passionnée\nDéroulement des entretiens\n🙋‍♀️ Un premier entretien téléphonique ou en visio avec notre chargée de recrutement\nJulie\npour voir si ça colle entre nous !\n💁🏻‍♀️ Un deuxième en visio avec\nConstance\n, notre Directrice Grand Ouest, pour valider notre première impression.\n🙋🏻‍♂️ Un dernier échange sur mesure avec\nFlorent\n, Co-fondateur du cabinet, pour confirmer ce que nous savions déjà ! 😉\nVous l’aurez compris, cette phase de recrutement est avant tout l’occasion de s’écouter et d’échanger. Chez Listen too, nous célébrons la diversité et l’inclusion, convaincus que chaque talent, quelle que soit son origine ou son parcours, est une richesse pour notre équipe et contribue à notre réussite commune.\nShow more\nShow less",
        "details": {
            "JobDetail": [],
            "TypeContract": "",
            "Salary": "",
            "Level": "",
            "Experience": "5 an(s)"
        },
        "title": "data analyst",
        "skills": {
            "ProgLanguage": [
                "Python"
            ],
            "DataBase": [
                "SQL"
            ],
            "DataAnalytics": [
                "NumPy",
                "Pandas"
            ],
            "EnSoftSkils": [
                "Collaboration"
            ]
        }
    },
    {
        "source": "LinkedIn",
        "company": "Lincoln France",
        "location": "Île-de-France, France",
        "link": "https://fr.linkedin.com/jobs/view/data-analyst-h-f-at-lincoln-france-3892483893?position=49&pageNum=0&refId=jBvsgtdGm8ta0dsilpa8wg%3D%3D&trackingId=BJrA9xzzEoljjqK0jjEP8w%3D%3D&trk=public_jobs_jserp-result_search-card",
        "description": "CDI\n📊\n3 ans minimum\nChez Lincoln\n, nous formons une communauté d'innovateurs passionnés qui redéfinissent l'analyse de données depuis\nplus de 30 ans\n. En tant que\nPure Player Data\n, notre expertise est reconnue dans les domaines\nde la Modern BI, du Big Data et de la Science des données\n.\nNotre mission ?\nTransformer les données en solutions concrètes pour nos clients grands comptes dans divers secteurs tels que la banque, le retail, les télécoms, l'industrie, la santé, etc.\nDescription du poste\nNous recherchons un\nData Analyst H/F\npour accompagner nos clients dans leurs projets stratégiques.\nVos missions\nCollecter, nettoyer et traiter les données provenant de différentes sources.\nAnalyser les données pour identifier des tendances, des corrélations et des anomalies.\nConcevoir et développer des tableaux de bord et des rapports pour présenter les résultats de manière claire et concise.\nCollaborer avec les équipes clients pour comprendre leurs besoins et recommander des solutions adaptées.\nPrérequis :\nMaîtrise avancée des langages de programmation (\nSQL, Python, R\n, etc.).\nConnaissance approfondie des bases de données relationnelles et non relationnelles.\nExpérience pratique avec des outils d'analyse de données (\nTableau, Power BI\n, etc.).\nFortes compétences analytiques et capacité à transformer les données brutes en insights exploitables.\nExpérience de travail en\nméthode Agile\npour la gestion de projet et le développement de solutions.\nCapacités à travailler de manière autonome et en équipe.\nExcellentes compétences en communication et en présentation.\nLes plus du poste\nEnvironnement Collaboratif\n: projets innovants favorisant le partage des connaissances.\nAccompagnement individualisé et de proximité\n: formations certifiantes, attribution d’un Career Manager pour vous orienter dans votre trajectoire professionnelle, opportunités d’évolution de carrière.\nFlexibilité du Travail\n: Télétravail et horaires flexibles pour votre équilibre vie professionnelle-personnelle.\nRémunération Compétitive\n: Salaire compétitif avec des avantages sociaux attrayants.\nMobilité\n: Possibilité de mobilité à Lille, Lyon ou Aix-en-Provence offrant des expériences diversifiées au sein de Lincoln.\nNotre processus de recrutement :\nUn entretien RH (1h) et entretien technique (1h)\nCette annonce n’est pas faite pour vous si :\nVous êtes freelance et vous comptez le rester !\nToujours là ? Postulez et rejoignez nos\n400 experts en Data\n😉.\nShow more\nShow less",
        "details": {
            "JobDetail": [],
            "TypeContract": "CDI",
            "Salary": "400",
            "Level": "",
            "Experience": "3 an(s)"
        },
        "title": "data analyst",
        "skills": {
            "ProgLanguage": [
                "R",
                "Python"
            ],
            "DataBase": [
                "SQL"
            ],
            "DataAnalytics": [
                "R"
            ],
            "DataVisualisation": [
                "Power BI",
                "Tableau"
            ],
            "Other": [
                "Big Data"
            ],
            "EnSoftSkils": [
                "Communication"
            ]
        }
    },
    {
        "source": "LinkedIn",
        "company": "Groupe TF1",
        "location": "Boulogne-Billancourt, Île-de-France, France",
        "link": "https://fr.linkedin.com/jobs/view/cdi-data-analyst-achats-f-h-at-groupe-tf1-3905896016?position=50&pageNum=0&refId=jBvsgtdGm8ta0dsilpa8wg%3D%3D&trackingId=kz1wOnU7VnpSCT96onAtYQ%3D%3D&trk=public_jobs_jserp-result_search-card",
        "description": "Faisons connaissance\nTF1, c’est bien sûr les grands programmes de divertissement, les séries exclusives, les films et les talk-shows qui nourrissent la culture populaire et réunissent le plus grand nombre. C’est aussi l’information, la plus suivie d’Europe, et les événements sportifs planétaires qui font vibrer tous les Français et les Françaises.\nTF1, c’est surtout une ambition : celle de développer la première plateforme de streaming gratuite en France, pour donner accès à tous et à toutes, à la demande, au meilleur du divertissement et de l’info. Envie d’inventer la télévision de demain ? C’est ici que ça se passe !\nVotre rôle au sein de l’équipe\nEn interface avec l’ensemble de la Direction Financière de TF1, le\nData Analyst Achats\naura un rôle central dans l’accompagnement de la Direction des Achats autour des différents sujets de reportings et de process.\nDe manière plus globale, il lui sera demandé de repenser la data comme étant au cœur de la stratégie de performance de la Direction et d’être force de proposition quant aux indicateurs, outils, et process mis en place.\nLes principales missions :\nVous serez conduit à :\nPiloter être force de proposition sur les besoins de reporting de la Direction des Achats\nCréer et automatiser les reportings sur Power BI, pour accompagner les acheteurs dans leurs besoins en analyses\nProposer des KPI de suivi\nAdministrer l’ensemble des campagnes d’évaluation RSE des fournisseurs\nSuivre l’avancement du processus RFA et optimiser le process\nFaire de la veille sur les outils d’IA au service des directions Achats.\nLe Data Analyst Achats pourra ponctuellement être amené à travailler sur des projets d’achats en collaboration avec la Directrice Achats.\nVos atouts pour faire la différence\nVous êtes issu d'une formation supérieure spécialisée dans les Achats et expérience professionnelle souhaitée dans le domaine de 3/4 ans minimum.\nVous connaissez la méthodologie de la conduite de projet et avez une excellente maitrise de Power Bi, ainsi qu'Excel.\nVous avez eu l'occasion de travailler sur de l'analyse financière.\nQUALITES REQUISES :\nSens du relationnel développé ainsi que des capacités reconnues d'écoute\nAutonomie et force de proposition (capacité à challenger l’existant)\nDynamique, rigoureux, organisé et réactif\nForce de conviction, capacité à faire adhérer et influencer\nBonnes capacités d'analyse, de rédaction, de synthèse et goût pour les chiffres\nGoût pour le travail en équipe\nAppétence pour la gestion de projet\nShow more\nShow less",
        "details": {
            "JobDetail": [],
            "TypeContract": "",
            "Salary": "",
            "Level": "",
            "Experience": "4 an(s)"
        },
        "title": "data analyst",
        "skills": {
            "DataVisualisation": [
                "Power BI"
            ],
            "EnSoftSkils": [
                "Collaboration"
            ]
        }
    },
    {
        "source": "LinkedIn",
        "company": "Lokad",
        "location": "Paris, Île-de-France, France",
        "link": "https://fr.linkedin.com/jobs/view/business-data-analyst-h-f-at-lokad-3915779840?position=51&pageNum=0&refId=jBvsgtdGm8ta0dsilpa8wg%3D%3D&trackingId=JMfb1YRIu3BpJuAecVg1%2FQ%3D%3D&trk=public_jobs_jserp-result_search-card",
        "description": "We’re looking for the right candidate to join our Business Data Analyst team and become part of a fast-growing company that is on always on the look for people that will demonstrate they’re able to grow with the company. As the role is our entry level, this is a great entry point for a career path at Lokad, either as a future technical expert or as manager.\nWe help companies in different verticals (aerospace, automotive, ecommerce…) to forecast and make decisions about their inventory. The vast majority of our clients are based outside of France, mainly in North America and Europe.\nAs a Business Data Analyst (or Supply Chain Scientist in Lokad's terminology), your role is to make sure our clients get the most from Lokad's technology. The role is a mix between technology, data crunching and supply chain expertise. You will address complex supply chain issues and craft quantitative strategies. Your goal is not only to advise your clients on strategies to adopt, but to craft and execute these strategies on a daily basis while leveraging the data available as much as possible. Your goal is also to keep refining these strategies over time to keep them aligned with the needs of our clients.\nAt Lokad, you will benefit from the extensive training and coaching of our expert team. You will gain skills in supply chain, predictive analysis and overall quantitative optimization for business. You will learn how to achieve measurable business results grounded on scientific analysis of data.\nAbout one quarter of your time is spent interacting with clients in order to better understand their business (mainly over the phone or by mail, with occasional travels). Note that, in order to benefit from your colleagues expertise, you won't be required to work on the customers' premises.\nThe rest of your time is spent on data analysis, including manipulating and cleaning data, setting up forecasts, economic optimization, reporting and data vizualisation. In order to do this, you'll learn to use our Differentiable Programming tools and a DSL (Envision) developped by Lokad.\nWe are looking for candidates with the following skills and qualities:\nA strong engineering background.\nA keen interest in data and quantitative analysis in general.\nGood Excel skills or programming skills (e.g. Python, VBA, SQL, etc.).\nImpeccable command of English\n( French is optional).\nExcellent communication skills and telephone manners.\nA well-made head, rather than a well-filled head.\nWe are not looking for someone who is already an expert in supply chain or programming. We’re looking for a fast learner, with an ability to quickly grasp technology and concepts, since our technology is by no means a simple and plug-and-play product. Knowledge or understanding of supply chain would be a bonus, but the ability to quickly assess and grasp a new situation or get a clear picture of how an organization works and what are the pain points is what we are really after.\nCandidates must be self-motivated, confident and highly driven to achieve results with a “hands on” attitude.\nThe role is predominantly office based, although some travel will be occasionally required to customers, partners or events. We are located in the very center of Paris, France (station Chevaleret).\nShow more\nShow less",
        "details": {
            "JobDetail": [],
            "TypeContract": "",
            "Salary": "",
            "Level": "",
            "Experience": null
        },
        "title": "data analyst",
        "skills": {
            "ProgLanguage": [
                "Python"
            ],
            "DataBase": [
                "SQL"
            ],
            "EnSoftSkils": [
                "Communication",
                "Organization"
            ]
        }
    },
    {
        "source": "LinkedIn",
        "company": "SOFTEAM",
        "location": "Paris, Île-de-France, France",
        "link": "https://fr.linkedin.com/jobs/view/data-analyst-f-h-at-softeam-3587086987?position=52&pageNum=0&refId=jBvsgtdGm8ta0dsilpa8wg%3D%3D&trackingId=FFP%2B2Q5b4yUJyWRjMDwkKg%3D%3D&trk=public_jobs_jserp-result_search-card",
        "description": "Vous évoluez dans le domaine de la Data et souhaitez intégrer\nun leader de la transformation numérique spécialisé dans les secteurs de la Banque, du Luxe, de l'Assurance, de la Finance, de l'Energie et la possibilité d'évoluer au sein du Groupe Docaposte !\nSofteam est labellisé \"HappyIndex® AtWork \" 2022 pour la 5ème année consécutive !\nNos collaborateurs\ntravaillent en « mode projet » et accompagnent de bout en bout nos clients sur des problématiques de Gouvernance.\nCE QUE NOUS RECHERCHONS\nData Analyst\npour intervenir sur nos projets et contribuer au développement de notre Practice « Augmented analytics »\nCE QUE NOUS ATTENDONS DE VOUS\nVos missions :\nMaîtriser les outils statistiques et les informations nécessaires à la mise en place d'une base de données,\nGérer parfaitement les différentes technologies spécifiques au big data,\nExtraire les données du système source,\nExtraire et traduire des données business en données statistiques,\nModéliser et assurer les mises à jour régulières de la base de données,\nContrôler la qualité des données,\nMettre en œuvre une data warehouse\nSynthétiser et vulgariser les informations pour les rendre accessibles aux utilisateurs.\nVOUS ETES\nIngénieur(e) de formation avec une spécialité Business Analytics, Big Data, Applications des Masses de Données (IAMD), Systèmes Décisionnels..\nvous disposez d'une expérience de\n3 ans minimum\nen tant que\nData Analyst/Data Miner\n..\nVous avez une expertise sur un ou plusieurs des outils d'alimentation et de traitement suivants :\nSQL, Alteryx, Dataiku, Python\n..\nVous avez une expertise sur un ou plusieurs des outils de data visualisation suivants :\nPower BI, Looker/GCP, Qlik, Tableau Software,\nBon(ne) communicant(e), curieux(se) et adaptable, v\nous êtes doté(e) d'une grande capacité d’analyse et de synthèse et d'un bon esprit d'équipe,\nVotre maîtrise de l'\nanglais\nvous permet d'évoluer dans un contexte international.\nNOUS VOUS OFFRONS\nDes\nmissions engageantes\nauprès des grands acteurs du marché.\nUn management de proximité avec\nGilles SALVADOR, Directeur du Centre d'Expertise Data\n, toujours bienveillant et à à l'écoute et avec qui vous pourrez échanger au quotidien sur les enjeux de votre mission et évoquer vos futurs projets afin que nous puissions vous aider à les réaliser.\nLa possibilité d’évoluer et de monter en compétences grâce à des\nformations et à des certifications auprès de nos clients et de nos consultants\n, des\n12@13\n, notre Entité\nSofteam Institute, Organisme de formation interne\nde renommé qui délivre des formations auprès de nos clients...\nQUI SOMMES-NOUS ?\nSOFTEAM DATA\nest une marque de\nDOCAPOSTE\nspécialisée dans l'informatique décisionnelle et les nouvelles technologies. Nous apportons notre expertise à nos clients, principalement des Grands Comptes de la place financière française, dans des projets de transformation digitale et cognitive.\n2000 Softeamien.nes\nsont dédié.es à la transformation métier et digitale de nos clients et ont généré 200 M€ de chiffre d’affaires en 2020.\nSOFTEAM SPIRIT\nDes\ncommunautés d'expertises sur les sujets de la Data\nDe\nsuper nouveaux locaux qui sont en plus accessibles facilement\nUne\nécole de formation intégrée\nDes\névènements : des soirées avec les consultants, des 12@13...\nUne entreprise\nlabellisée \"Happy at Work\" pour la 5ème année consécutive\n.\nN’attendez plus, rejoignez SOFTEAM et venez nous rencontrer dans nos nouveaux locaux situés à la Défense #DevenezSofteamien !\nShow more\nShow less",
        "details": {
            "JobDetail": [],
            "TypeContract": "",
            "Salary": "",
            "Level": "",
            "Experience": "3 an(s)"
        },
        "title": "data analyst",
        "skills": {
            "ProgLanguage": [
                "Python"
            ],
            "DataBase": [
                "SQL"
            ],
            "DataVisualisation": [
                "Power BI",
                "Tableau"
            ],
            "CloudComputing": [
                "GCP"
            ],
            "Other": [
                "Statistiques",
                "Big Data"
            ]
        }
    },
    {
        "source": "LinkedIn",
        "company": "Talent Disruptors",
        "location": "Paris, Île-de-France, France",
        "link": "https://fr.linkedin.com/jobs/view/data-analyst-at-talent-disruptors-3860725693?position=53&pageNum=0&refId=jBvsgtdGm8ta0dsilpa8wg%3D%3D&trackingId=0KBJ7Pd6KUtz1%2By4ulonkw%3D%3D&trk=public_jobs_jserp-result_search-card",
        "description": "We are on the lookout for a Data Analyst with a specialization in marketing analytics. In this critical role, you will harness the power of tools like Google Data Studio, BigQuery, and Power BI to derive actionable insights that drive our marketing decisions. Your expertise in analyzing complex datasets and turning them into understandable and strategic information will be essential in shaping our marketing strategies. This position is ideal for someone who thrives on data-driven challenges and has a passion for leveraging technology to inform business decisions.\nWhat You’ll Be Doing\nData Analysis and Interpretation: Utilize tools like Google Data Studio, BigQuery, and Power BI to analyze marketing data and extract meaningful insights.\nDeveloping Reporting Dashboards: Create dynamic dashboards and reports that provide real-time insights into marketing performance.\nCollaborating with Marketing Teams: Work closely with marketing teams to understand their data needs and provide insights that inform strategy and decision-making.\nData Integration and Management: Integrate data from various sources to provide a comprehensive view of marketing performance.\nPerformance Tracking: Monitor key performance indicators (KPIs) to measure the effectiveness of marketing campaigns and strategies.\nPredictive Analysis: Use data to predict trends and market movements, aiding in proactive strategy development.\nTraining and Support: Provide training and support to team members in using data analysis tools and understanding reports.\nWho You Are\nProficient in Data Analysis Tools: You have strong experience with tools such as Google Data Studio, BigQuery, and Power BI.\nAnalytical and Insightful: You possess the ability to analyze complex datasets and turn them into actionable insights.\nCollaborative in Nature: You work well with marketing teams, understanding their needs and communicating data insights effectively.\nSkilled in Data Integration: You are adept at integrating and managing data from various sources.\nDetail-Oriented: You have a keen eye for detail and accuracy in data analysis and reporting.\nProactive and Predictive: You are capable of conducting predictive analyses to inform future marketing strategies.\nExcellent Communicator: You can clearly convey data insights and their implications to non-technical team members.\nWhat Success Looks Like\n30 Days\nEstablish a comprehensive, organized online database in BigQuery to store all client and marketing data and integrate lead data from CRMs, digital advertising data, customer opt-ins, and purchasing data to provide meaningful insights that inform marketing decisions.\nCreate and maintain data dashboards in Looker Studio for easy data visualization, analysis, and automated reporting.\n60 Days\nDevelop statistical models for data analysis, including linear regression modeling and predictive lead scoring, that effectively guide marketing actions.\n90 Days\nAutomated the generation of actionable insights and trends over time from data analysis to inform our marketing strategy.\nShow more\nShow less",
        "details": {
            "JobDetail": [],
            "TypeContract": "",
            "Salary": "",
            "Level": "",
            "Experience": null
        },
        "title": "data analyst",
        "skills": {
            "DataVisualisation": [
                "Power BI"
            ],
            "DBMS": [
                "BigQuery"
            ],
            "Collaboration": [
                "Teams"
            ]
        }
    },
    {
        "source": "LinkedIn",
        "company": "Mazars",
        "location": "Paris, Île-de-France, France",
        "link": "https://fr.linkedin.com/jobs/view/data-analyst-junior-paris-2024-h-f-at-mazars-3838258695?position=54&pageNum=0&refId=jBvsgtdGm8ta0dsilpa8wg%3D%3D&trackingId=rJqp5EuCxwewlPfzUeQKvA%3D%3D&trk=public_jobs_jserp-result_search-card",
        "description": null,
        "details": {
            "JobDetail": [],
            "TypeContract": "",
            "Salary": "",
            "Level": "",
            "Experience": null
        },
        "title": "data analyst"
    },
    {
        "source": "LinkedIn",
        "company": "Stack Digital",
        "location": "Belfort, Bourgogne-Franche-Comté, France",
        "link": "https://fr.linkedin.com/jobs/view/data-analyst-at-stack-digital-3895910936?position=55&pageNum=0&refId=jBvsgtdGm8ta0dsilpa8wg%3D%3D&trackingId=WL17XxGJYCFg2llCVWkoOw%3D%3D&trk=public_jobs_jserp-result_search-card",
        "description": "Job Title:\nData Analyst\nType:\nContract\nLocation:\nBelfort, France\nImmediate Joining Required\nOverview:\nWe are currently seeking a dedicated Analyst with expertise in the Shopfloor/Manufacturing domain to join our team. This role requires a professional who is adept at learning existing application business functions and is capable of working independently on Oracle PL/SQL. The ideal candidate will be based out of our client's office in Belfort and must be willing to collaborate with geographically distributed teams across India and the Americas.\n​​​​​​​\nKey Responsibilities:\nLearn and understand the business functions of existing applications within the Shopfloor/Manufacturing domain.\nParticipate in the transition process, including documentation and internal transition to other teams.\nIndependently work on Oracle PL/SQL, including solving tickets related to PL/SQL issues.\nCoordinate with third-party application vendors to ensure tickets are resolved within the Service Level Agreement (SLA).\nParticipate in critical outage calls as required.\nPrepare high-quality status reports and present them to stakeholders if needed.\nRequirements:\nProven experience in the Shopfloor/Manufacturing domain.\nStrong capability in working independently on Oracle PL/SQL.\nExperience in coordinating with third-party vendors and managing ticket resolution within SLA.\nExcellent problem-solving skills and ability to participate in critical outage calls.\nNative level French language proficiency and strong business English language skills.\nAbility to work effectively with geographically distributed teams.\nExcellent documentation skills and experience in transition processes.\nWhy Join Us?\nThis is a fantastic opportunity to contribute to a critical role within a dynamic and challenging environment. You will have the chance to work with a diverse team and develop your skills in a global setting. If you are a motivated individual with a passion for the Shopfloor/Manufacturing domain and possess the required skills, we would love to hear from you.\nHow to Apply:\nPlease submit your application, including your CV and a cover letter, highlighting your relevant experience and why you are the best fit for this role. We are looking for immediate joiners, so please indicate your earliest availability.\nShow more\nShow less",
        "details": {
            "JobDetail": [],
            "TypeContract": "",
            "Salary": "",
            "Level": "",
            "Experience": null
        },
        "title": "data analyst",
        "skills": {
            "DataBase": [
                "SQL"
            ],
            "Collaboration": [
                "Teams"
            ]
        }
    },
    {
        "source": "LinkedIn",
        "company": "Allianz France",
        "location": "Paris, Île-de-France, France",
        "link": "https://fr.linkedin.com/jobs/view/data-analyst-h-f-at-allianz-france-3909795270?position=56&pageNum=0&refId=jBvsgtdGm8ta0dsilpa8wg%3D%3D&trackingId=reZ3nyL33Q3I5e3rpxYHOg%3D%3D&trk=public_jobs_jserp-result_search-card",
        "description": "Allianz\nLeader européen de l'assurance et des services financiers, Allianz propose une offre complète couvrant tous les besoins en assurance, assistance et services financiers des particuliers, professionnels, entreprises et collectivités. Allianz compte plus de 150.000 salariés dans le monde. Le groupe réalise 75% de ses activités en Europe et il est présent dans plus de 70 pays. Avec 80 millions de clients dans le monde, Allianz fait partie des 5 plus grands groupes financiers mondiaux et est n° 1 de l'assurance et des services financiers en Europe.\nL’Unité Investissements\nAIM Paris (Allianz Investment Management Paris), l’unité Investissement d’Allianz France, a la charge de la gestion des investissements des différentes entités d’Allianz France tant sur les portefeuilles d’actifs généraux qu’en unités de compte (UC), sur toute la chaîne de valeur des investissements, qui couvre la gestion actif-passif, la stratégie d'investissement, ainsi que la planification des revenus des investissements, le suivi des risques, le reporting et les opérations.\nDescriptif / Missions du poste\nPour soutenir ces activités l’équipe AIM Finance & Opérations, en charge des données d’investissements, des reportings et du suivi des risques des investissements, est à la recherche d’un « Data Analyst ». Ce dernier, rattaché hiérarchiquement à AIM Finance & Opérations, couvrira l’ensemble des besoins des différentes équipes d’AIM (AIM Investment Strategy, AIM Asset-Liability Management, AIM Finance) et interviendra de façon opérationnelle sur des projets de transformation locaux et Groupe.\nVotre mission sera d’intervenir plus particulièrement sur :\nL’automatisation de sourcing des données, des contrôles et des réconciliations entre différents systèmes d’informations\nLe développement de macros/codes afin d’automatiser/optimiser les tâches\nL’amélioration continue des bases de données Investissements\nLa fiabilisation et l’amélioration continue des bases de données\nLa mise en place de nouveaux reportings (Power BI)\nLe pilotage de projets en lien avec les initiatives groupes et locales\nVous travaillerez en lien étroit avec les autres équipes d'AIM France ainsi que les équipes AIM centrales à Munich. La maitrise de l’anglais est alors indispensable.\nProfil\nDiplômé(e) en informatique/gestion des données ou d’une école d’ingénieur (BAC +5), vous disposez d’une expérience significative dans la manipulation de données (5-10 ans).\nMaîtrise de plusieurs langages de développement du type Python, VBA, Access, SAS\nBonne maîtrise des outils bureautiques Powerpoint, Excel et VBA, et idéalement une première expérience significative dans l’utilisation d’outils de datavisualisation (Power BI)\nCapacité d’analyse et de synthèse, ouverture d’esprit, rigueur, organisation et autonomie,\nFrançais et anglais professionnel courants indispensables, à l’écrit comme à l’oral.\nDébut de la mission :\nMars 2024\nLocalisation :\nParis - La Défense – TAO\nContacts : t ransmettre votre candidature complète (CV + lettre de motivation)\nShow more\nShow less",
        "details": {
            "JobDetail": [],
            "TypeContract": "",
            "Salary": "",
            "Level": "",
            "Experience": "10 an(s)"
        },
        "title": "data analyst",
        "skills": {
            "ProgLanguage": [
                "Python"
            ],
            "DataVisualisation": [
                "Power BI"
            ]
        }
    },
    {
        "source": "LinkedIn",
        "company": "Groupe Qérys",
        "location": "Le Haillan, Nouvelle-Aquitaine, France",
        "link": "https://fr.linkedin.com/jobs/view/data-analyst-h-f-at-groupe-q%C3%A9rys-3912192127?position=57&pageNum=0&refId=jBvsgtdGm8ta0dsilpa8wg%3D%3D&trackingId=9TrfwOZb1wDej%2FDQEO3G%2BA%3D%3D&trk=public_jobs_jserp-result_search-card",
        "description": "Le Groupe QERYS, spécialiste de l’aménagement de l’habitat, a son siège social QERYS SAS à Le Haillan en Gironde.\nSes\nfonctions supports\naccompagnent les sociétés commerciales du Groupe (Bricodeal, Cazabox, Domotelec, Hydro Sud Direct, Midi Piles Services, Sider et Youpalo) dans leur fonctionnement, au travers de services mutualisés.\nLe Groupe QERYS propose une offre globale dans le domaine de l’aménagement et de l’habitat\n(890 collaborateurs - 299M€ CA en 2022)\nNous rejoindre c’est :\nL’assurance d’un\nGroupe solide\nUn système de\nmanagement participatif\nUn engagement\nRSE\n(Responsabilité sociétale des entreprises)\nUne attention particulière à la\nQVT\n(Qualité de vie au Travail)\nUn\nparcours d’intégration\n, des\nformations\net un\naccompagnement\ntout au long de votre carrière\nPour en savoir +, consultez notre site institutionnel\nhttps://www.groupe-qerys.com/\nQuel est notre contexte ?\nEn tant que Développeur Dataviz H/F, vous développez des outils d’aide à la décision utilisant la donnée consolidée du Groupe pour faciliter le quotidien des métiers.\nQuel sera votre quotidien ?\nRattaché au Responsable Informatique BI :\nFACILITER L’ACCES A L’INFORMATION\n• Créer, développer et adapter les applications à destination des différents services\n• Homogénéiser les indicateurs pour permettre une lecture analytique simple et optimale\nGARANTIR LA QUALITE DE LA DATA\n• Contrôler, corriger et fiabiliser toutes les données du Groupe\n• Enrichir le décisionnel des données des nouveaux entrants (Nouveaux outils / Nouvelles Das…)\nEn collaboration avec les Data Ingénieurs, trouver des solutions pour optimiser les performances système et assurer un confort de consultation\n• Soutenir la démarche data de la DSI\nFORMER ET ACCOMPAGNER LES UTILISATEURS SUR L’OUTIL DE DATAVIZ\n• Former les collaborateurs à l’outil de Dataviz\n• Accompagner le changement auprès des métiers\nMAINTENIR ET DEVELOPPER L’OUTIL DE DATAVIZ\n• Assurer la veille technologique de l’outil\n• Assurer la gestion administrative des accès et des licences\n• Comprendre les besoins d’analyse et y apporter les solutions en adéquation avec l’urgence.\nEnvironnement Technique :\nETL : Talend (OpenStudio) + ETLTools\nRestitution : Qliksense\nBase de données : SQLServer/Oracle/MySQL/AS400\nMéthodologie Traditionnel et Agile\nJira/Confluence\nCe que nous vous apportons pour assurer un bon équilibre vie pro/vie perso (sous conditions d’éligibilité) :\n32 jours\nde congés payés (25 + 7 jours ouvrés)\nLundi de pentecôte chômé et payé (Journée de solidarité offerte)\nDes\njours supplémentaires\nofferts :\nancienneté, déménagement, mariage/pacs…\nJusqu’à\n2 jours de télétravail par semaine selon le poste\nPartenariat Klaxit (favoriser le covoiturage)\nUne\nmutuelle gratuite\nUn\nintéressement\nPrévoyance\nRéduction\nPartenaires -\nDéjeuner\nUne prime de\ncooptation\npour tout collaborateur recruté suite à votre recommandation\nConditions du contrat :\nCDI - Temps plein\nSalaire et avantages :\nà partir 34K€brut/an + intéressement + mutuelle Groupe + partenariat déjeuner\nHoraires :\n38h45 du lundi au vendredi\nLocalisation du poste :\n29 rue Thomas Edison, 33612 Canéjan\nInformations complémentaires :\ndéplacements occasionnels sur nos différents sites à l'échelle nationale\ntélétravail possible jusqu’à deux jours/semaine\nVotre candidature retiendra notre attention si :\nVous justifiez d’une première expérience significative d’au moins 2 ans sur un poste similaire. Vous disposez d’un intérêt pour la data. Vous maîtrisez les outils de Dataviz, avez un forte capacité d’analyse et de synthèse. Vous êtes à l’écoute, bon communicant et respectez la confidentialité des données.\nRejoignez l’équipe de Benjamin !\nShow more\nShow less",
        "details": {
            "JobDetail": [
                "Temps plein"
            ],
            "TypeContract": "CDI",
            "Salary": "34K",
            "Level": "",
            "Experience": "2 an(s)"
        },
        "title": "data analyst",
        "skills": {
            "DBMS": [
                "MySQL"
            ],
            "Collaboration": [
                "Confluence",
                "JIRA"
            ],
            "EnSoftSkils": [
                "Collaboration"
            ]
        }
    },
    {
        "source": "LinkedIn",
        "company": "Catalina Marketing France",
        "location": "Boulogne-Billancourt, Île-de-France, France",
        "link": "https://fr.linkedin.com/jobs/view/data-analyst-python-f-h-cdi-boulogne-billancourt-at-catalina-marketing-france-3907391526?position=58&pageNum=0&refId=jBvsgtdGm8ta0dsilpa8wg%3D%3D&trackingId=zSgtYD1T%2BibeK21Tso9%2BRw%3D%3D&trk=public_jobs_jserp-result_search-card",
        "description": "Catalina est le seul acteur de la GMS à pouvoir déployer des plans marketing hyper-personnalisés avec autant de puissance ! Chez Catalina, on parle en milliards de données depuis des années.\nGrâce à de puissants outils en IA et Machine Learning, nous analysons les comportements d’achat des clients de la grande distribution pour mettre en place des stratégies de recrutement et de fidélisation via des plans marketing omnicanaux (couponing ciblé, couponing digital via Coupon Network, programmes de fidélité…). Nous élaborons des milliers de campagnes chaque année : Leclerc, Carrefour, Monoprix, Nestlé, Procter & Gamble, Heineken, Coca-Cola, Bjorg… Ce serait trop long de tous les citer.\nCatalina réunit 860 personnes dans le monde, et plus de 240 en France. Travaillant main dans la main, les Cataliniens ont un fort esprit collaboratif et la culture du résultat. Ici on a la gagne !\nDepuis toujours, le succès de Catalina, c'est le talent de nos équipes. Chez Catalina, on favorise la confiance, la pro-activité et le développement en investissant sur la formation continue. Et parce que nous avons tant de pépites talentueuses, nous misons sur elles tous les jours en prônant l’évolution. Les meilleurs atouts des grands groupes et des start-ups sont réunis en une seule entreprise : puissance et flexibilité !\nSoucieux de notre impact, la RSE est au cœur de nos actions depuis toujours. En 2022, nous avons reçu la médaille d’argent EcoVadis pour saluer nos engagements sociaux et environnementaux.\nMissions et Responsabilités :\nAu sein du pôle Analytics, et intégré(e) à une équipe de 8 personnes dédiée au support des industriels de la grande distribution à travers l’Europe (France, Italie et UK), tes missions consistent à :\n-Echanger régulièrement avec les équipes business en France ou en Italie pour prendre connaissance des enjeux et problématiques clients auprès des équipes commerciales\n-Proposer, mettre en place des optimisations/Automatisations de nos process statistiques actuels\n-Extraire, analyser et interpréter les résultats des campagnes de marketing direct\n-Participer à des sessions des brainstorming en interne avec l’équipe DataScience et les autres équipes Analytics sur la veille méthodologique de nos mesures\n-Réaliser des projets d’études statistiques (segmentations, algo AI/ML, etc.)\nEt si c’était toi ?\nDe formation supérieure en statistiques, tu bénéficies d’un minimum 2 ans d’expérience idéalement dans le domaine des études marketing, et d’une expérience de travail sur des bases de données à forte volumétrie.\nTu parles Anglais (courant)\nTu as une parfaite maîtrise du SQL.\nTu as une parfaite connaissance de Python, l’utilisation dans un environnement Cloud est un plus (Azure, Snowflake, Databricks, etc.)\nLa connaissance des outils de Data visualisation comme Power BI est un plus\nTu connais les techniques statistiques appliquées au Marketing Direct : échantillonnage, mise en place de témoins, analyse des résultats, bonne connaissance des techniques de segmentations et de scoring.\nTu es déjà familier avec les techniques de ML & AI.\nTu es capable de vulgariser votre discours auprès de tes interlocuteurs (équipe commerciale, équipe marketing, clients…)\nDynamique et curieux(se), ta rigueur, ton aisance relationnelle, ton sens de l’initiative ainsi que ton autonomie te permettra de t’intégrer rapidement dans notre structure.\nTu es un amoureux de la data, un fin connaisseur de la grande conso, un passionné d'innovations digitales ? Tu cherches une entreprise qui te fait confiance et valorise tes talents, une bonne ambiance de travail, un équilibre vie privée/ vie pro et une forte cohésion d'équipe avec un esprit entrepreneurial ?\nEn devenant toi aussi Catalinien, tu seras fier de participer à cette aventure humaine au côté d’experts passionnés et bons vivants !\nProcess de recrutement :\n1er entretien avec Natacha, Talent Acquisition Manager et test technique de 30 minutes\n2ème entretien avec Laurence Analytics Director et Murielle Manager Analytics.\nNos infos utiles :\nTon futur lieu de travail : Boulogne-Billancourt (Marcel Sembat)\nContrat: CDI\nTélétravail : 3 jours de télétravail possible / semaine\nAvantages : 1 RTT / mois, CE, participation, prime vacances, carte restaurant swile, prise en charge de 2/3 de la mutuelle, journée d’engagement associatif, mais aussi de nombreux team buildings, des apéros, des paniers de fruits, du café à volonté…\nCatalina, en tant que responsable de traitement, met en œuvre un traitement de données ayant pour finalités principales la gestion et le suivi des candidatures. Tu disposes d’un droit d’accès, d’effacement, de rectification et de portabilité de vos données, ainsi que d’un droit d’opposition et de limitation au traitement de ces données. L’exercice des droits s’effectue sur la plateforme OneTrust dédiée (choix de la langue en haut à droite) accessible depuis le site catalinamarketing.fr/politique-confidentialite « Vos droits, employé » ou par courrier adressé à : Catalina Marketing France, Privacy Recrutement, 58 Avenue Edouard Vaillant 92100 Boulogne Billancourt.\nSauf opposition de ta part, les candidatures reçues font l’objet d’une conservation pendant 2 ans.\nShow more\nShow less",
        "details": {
            "JobDetail": [],
            "TypeContract": "CDI",
            "Salary": "",
            "Level": "",
            "Experience": "2 an(s)"
        },
        "title": "data analyst",
        "skills": {
            "ProgLanguage": [
                "Python"
            ],
            "DataBase": [
                "SQL"
            ],
            "BigData": [
                "Databricks"
            ],
            "DataVisualisation": [
                "Power BI"
            ],
            "CloudComputing": [
                "Azure"
            ],
            "DBMS": [
                "Snowflake"
            ],
            "Other": [
                "Statistiques",
                "Machine Learning",
                "Cloud",
                "ML"
            ],
            "EnSoftSkils": [
                "Initiative"
            ]
        }
    },
    {
        "source": "LinkedIn",
        "company": "Checkout.com",
        "location": "Paris, Île-de-France, France",
        "link": "https://fr.linkedin.com/jobs/view/senior-data-analyst-at-checkout-com-3860155203?position=59&pageNum=0&refId=jBvsgtdGm8ta0dsilpa8wg%3D%3D&trackingId=F373RzA%2BYIbaLl1oE%2B3a9w%3D%3D&trk=public_jobs_jserp-result_search-card",
        "description": "Company Description\nWe're Checkout.com\nCheckout.com is one of the most exciting fintechs in the world. Our mission is to enable businesses and their communities to thrive in the digital economy. We’re the strategic payments partner for some of the best known fast-moving brands globally such as Wise, Hut Group, Sony Electronics, Homebase, Henkel, Binance, Klarna and many others. Purpose-built with performance and scalability in mind, our flexible cloud-based payments platform helps global enterprises launch new products and create experiences customers love. And it's not just what we build that makes us different. It's how.\nWe empower passionate problem-solvers to collaborate, innovate and do their best work. That’s why we’re number 9 on the Forbes Cloud 100 list and on Glassdoor’s list of Top 10 fintechs to work for. And we’re just getting started. We’re building diverse and inclusive teams around the world — because that’s how we create even better experiences for our merchants and our partners. And we need your help. So, join us to build tomorrow, today.\nJob Description\nYou will be joining the Identity Verification team, responsible to maintain and continuously improve a world-class online identity verification technology, based on real-time video recognition.\nAs a Senior Product Data Scientist, you'll work as part of a cross-functional team alongside product managers, designers, and software and analytics engineers, using data and your expertise to influence and drive the strategy of our products. You will have end-to-end ownership for all the data aspects for your ‘tribe’. You'll help define how we measure the success of our products, collaborate with engineers on how we collect data, build data pipelines to track the defined metrics, design and build reports/dashboards, and run analyses to find product improvement opportunities. You'll be a co-owner of a product, driving it to success in partnership with other cross-functional team members.\nYou'll also be part of the broader Analytics function, a team of Analytics Engineers, Data Scientists, and Data Product Managers.\nWe're a new but highly visible function within Checkout.com, so this is an exciting opportunity to drive a positive impact.\nHow you’ll make an impact\nBe responsible for a product domain and its metrics. You'll be accountable for defining, measuring, and presenting metrics.\nContribute product roadmaps through data-based recommendations and continuously define high-impact areas for improvement.\nSupporting product discovery, research, and experimentation\nWorking closely with Data Engineers to make sure we collect and model the right data to produce relevant business insights\nDesign and implement reusable and scalable data models for our data warehouse using dbt and Snowflake\nDesign and implement Looker structures (explores, views, etc) which will enable users across the organization to self-serve analytics\nFoster data culture across products and technology by actively sharing insights and ideas and building positive relationships with colleagues\nBuild experiments and analysis frameworks to quantify the ROI of product development.\nDrive by example your team and broader data community to apply best practices in analytics from data collection to analysis.\nQualifications\nWhat we’re looking for\nProven delivery experience as a data scientist or data analyst\nStrong communicator, you're able to explain complex technical topics to non-technical team members\nExperience conducting experiments, building measurement frameworks, and validating the results with relevant quantitative methods\nStrong analytical mind, proven experience in converting ambiguous problems into structured and data-informed solutions\nCuriosity and attention to detail: you like to explore and understand the trends and investigate unusual patterns\nProficiency in SQL for data interrogation and data transformation (ideally experience with Looker, Snowflake and dbt)\nKnowledge of applied statistics (e.g., hypothesis testing, regression)\nAdditional Information\nHybrid Working Model:\nAll of our offices globally are\nonsite 3 times per week\n(Tuesday, Wednesday, and Thursday). We’ve worked towards enabling teams to work collaboratively in the same space, while also being able to partner with colleagues globally. During your days at the office, we offer amazing snacks, breakfast, and lunch options in all of our locations.\nApply Without Meeting All Requirements Statement\nIf you don't meet all the requirements but think you might still be right for the role, please apply anyway. We're always keen to speak to people who connect with our mission and values.\nWe believe in equal opportunities\nWe work as one team. Wherever you come from. However you identify. And whichever payment method you use.\nOur clients come from all over the world — and so do we. Hiring hard-working people and giving them a community to thrive in is critical to our success.\nWhen you join our team, we’ll empower you to unlock your potential so you can do your best work. We’d love to hear how you think you could make a difference here with us.\nWe want to set you up for success and make our process as accessible as possible. So let us know in your application, or tell your recruiter directly, if you need anything to make your experience or working environment more comfortable. We’ll be happy to support you.\nTake a peek inside life at Checkout.com via\nOur Culture video https://youtu.be/BEwnpHuadSw\nOur careers page https://www.checkout.com/careers\nOur LinkedIn Life pages bit.ly/3OaoN1U\nOur Instagram https://www.instagram.com/checkout_com/\nShow more\nShow less",
        "details": {
            "JobDetail": [
                "Senior"
            ],
            "TypeContract": "",
            "Salary": "",
            "Level": "",
            "Experience": null
        },
        "title": "data analyst",
        "skills": {
            "DataBase": [
                "SQL"
            ],
            "DBMS": [
                "Snowflake"
            ],
            "Collaboration": [
                "Teams"
            ],
            "Other": [
                "Cloud"
            ],
            "EnSoftSkils": [
                "Organization"
            ]
        }
    },
    {
        "source": "LinkedIn",
        "company": "Mazars",
        "location": "Courbevoie, Île-de-France, France",
        "link": "https://fr.linkedin.com/jobs/view/data-analyst-junior-paris-2024-h-f-at-mazars-3904531206?position=60&pageNum=0&refId=jBvsgtdGm8ta0dsilpa8wg%3D%3D&trackingId=jM4CkYBw7lqjrrNiqERqpQ%3D%3D&trk=public_jobs_jserp-result_search-card",
        "description": "Description de l'entreprise\nMazars est un groupe international et intégré spécialisé dans l’audit, la fiscalité et le conseil ainsi que dans les services comptables et juridiques*. Présents dans plus de 95 pays et territoires à travers le monde, nous nous appuyons sur l’expertise de plus de 47 000 professionnels – plus de 30 000 au sein de notre partenariat intégré et plus de 17 000 via « Mazars North America Alliance » – pour accompagner les clients de toutes tailles à chaque étape de leur développement.\nDans les pays où les lois en vigueur l’autorisent\nDescription du poste\nMazars souhaite chaleureusement son équipe « Audit Data Analytics » au sein de ses équipes Data Services.\nAu sein d'une équipe à la frontière entre l'audit et la tech, vous développez ainsi une double compétence technique et fonctionnelle ; en véritable Business Analyst, vous concevez et déployez des solutions Analytics pour les clients Mazars.\nVous intervenez sur des missions variées dans plusieurs secteurs d'activité (industrie, services, secteur public, services financiers (banque et assurance)) et alimentez les compétences suivantes :\ndéveloppement de solutions innovantes sur des socles technologiques variés de data analytics, de data visualisation et de programmation : Alteryx, Qlik, SQL, PowerBI, Python, etc. ;\nparticipation à la conception de solutions fonctionnelles, de la phase de spécifications à la phase de mise à disposition ;\ncontribution au développement de nouvelles offres Mazars au service des enjeux Data de nos clients ;\nanalyser fonctionnellement les résultats produits par les solutions Analytics ;\nparticipation à la rédaction de rapports d'analyse et présentation des outils et résultats Analytics à nos clients.\nEn complément, vous êtes progressivement formés aux technologies de machine learning, à l'intelligence artificielle et à la science des données.\nQualifications\nDe formation Bac+5, vous êtes jeune diplômé(e) d'une école d'ingénieurs, école de commerce ou université et avez un goût prononcé pour les sujets Analytics et les nouvelles technologies de façon générale, avec une appétence pour les problématiques métier et finance :\nVous avez une spécialisation en Système d'Information et/ou en Data Science ;\nVous êtes passionné(e) par les nouvelles technologies liées à la Data ;\nVous avez idéalement une expérience de stage au cours de laquelle vous êtes intervenu(e) sur le domaine de la « Data » ;\nVous aimez innover, vous êtes curieux, dynamique et autonome et vous avez une certaine\naisance à développer vos connaissances sur de nouveaux outils ;\nVous avez un excellent sens du travail en équipe ;\nVous possédez les connaissances de base parmi les technologies suivantes : SQL, ACL, data studio, PowerBI, Qlik, Alteryx, Tableau softwareetc.)\nIntégration prévue à partir de septembre 2024\nInformations supplémentaires\nLes + du métier :\nDiversité des missions\nTravail d'équipe\nEquipe dynamique\nÉvolution de carrière rapide\nChez Mazars, nous plaçons le développement personnel au cœur de nos priorités. Vous êtes force de proposition ? Nous vous donnerons l'opportunité de porter et réussir vos idées. Vous souhaitez participer à la croissance du cabinet ? Nous vous intégrerons dans le développement ou le renforcement de nos offres. Enfin, les formations conçues par Mazars U Learn vous permettront de réinventer et de développer vos softs skills ainsi que de booster votre talent !\nShow more\nShow less",
        "details": {
            "JobDetail": [],
            "TypeContract": "",
            "Salary": "",
            "Level": "Bac+5",
            "Experience": null
        },
        "title": "data analyst",
        "skills": {
            "ProgLanguage": [
                "Python"
            ],
            "DataBase": [
                "SQL"
            ],
            "DataVisualisation": [
                "Tableau"
            ],
            "Other": [
                "Machine Learning"
            ]
        }
    },
    {
        "source": "LinkedIn",
        "company": "Aqualung Group",
        "location": "Valbonne, Provence-Alpes-Côte d'Azur, France",
        "link": "https://fr.linkedin.com/jobs/view/master-data-analyst-intern-at-aqualung-group-3908876542?position=1&pageNum=2&refId=qJ2foyHYFct0ss%2B3yaGaFw%3D%3D&trackingId=tyNyqO4YRk72iJZ1bycEkQ%3D%3D&trk=public_jobs_jserp-result_search-card",
        "description": "Aqualung Group pioneered the creation of modern diving equipment in 1943 when Captain Jacques-Yves Cousteau teamed with Émile Gagnan to develop the first “aqua-lung” that made underwater exploration possible. Today, Aqualung Group continues to be the leading global designer and manufacturer of dive and water sports gear. With a deep commitment to quality, research and testing, Aqualung Group has revolutionized the scuba diving experience by setting industry standards for scuba equipment in technology, comfort, safety and design.\nThe Aqualung Group consists of premium, innovative and inclusive brands such as Aqualung, Apeks, Aquasphere, Omer;\nSo, are you...\na sport enthusiast\ndo you love oceans and everything beyond\nare you an advocate of making a difference and protect our planet, a world where the ocean and all living creature are healthy and thriving\nor are you simply motivated and inspired to be a part of our passionate team that is always eager for a new challenge\nAqualung believes in the future, thus we invite you to strengthen and broaden your skills, pursue your passion by co-creating the future within an internship open positions.\nScope and Mission\nSupport the Aqualung Group in the daily management of Item master data.\nStart date:\nASAP\nDuration target:\nminimum 6 months\nLocation:\nSophia Antipolis\nKey duties and responsibilities\nSupport the master data team in the Item master data collection processes. (Creation/Update).\nHelp centralizing Master Data information in dedicated MDM tool (Product Hub/Oracle).\nHelp ensuring synchronization of the item master data in consuming systems.\nControl master data availability and quality through the publication of KPIs and implementation of data quality reports.\nEnsure master data collection environments are up to date.\nContribute in implementing data quality reports and corrective processes.\nContribute with the Master Data team in enhancing the existing item Core Model.\nYour qualifications\nLevel of studies:\nBAC + 4/5 minimum / master's degree in data science / data analysis.\nA first level of experience in Master data is preferred.\nSkills\nFluent English\nExcellent communication skills\nWorking effectively in a Team\nGood organizational skills, sense of prioritization\nYou are curious, dynamic, passionate about innovation\nStrong ability in manipulating data. (SQL)\nIf you are excited about this opportunity and joining the Aqua Lung team, please apply!\nWe look forward to receiving your application.\nShow more\nShow less",
        "details": {
            "JobDetail": [],
            "TypeContract": "",
            "Salary": "",
            "Level": "",
            "Experience": null
        },
        "title": "data analyst",
        "skills": {
            "DataBase": [
                "SQL"
            ],
            "EnSoftSkils": [
                "Communication"
            ]
        }
    },
    {
        "source": "LinkedIn",
        "company": "Astek",
        "location": "Paris, Île-de-France, France",
        "link": "https://fr.linkedin.com/jobs/view/data-analyst-%E2%80%93-paris-france-h-f-at-astek-3839098102?position=2&pageNum=2&refId=qJ2foyHYFct0ss%2B3yaGaFw%3D%3D&trackingId=4d3rgYcDQJw5rvsYeoh9ww%3D%3D&trk=public_jobs_jserp-result_search-card",
        "description": "CDI\nParis - France\nPubliée il y a 2 mois\nLe Groupe Astek\nCe Que Nous Allons Accomplir Ensemble :\nNous rejoindre en tant que\nData Analyst (H/F),\nafin d’accompagner un opérateur télécoms, Leader en Europe dans la gestion de ses solutions robustes, efficientes et sécurisées à destination d’environnements variés.\nUn challenge portant sur des millions d’utilisateurs dans un environnement technique innovant, stratégique et où l’entraide et la bonne humeur priment !\nVotre Mission, Si Vous L’acceptez :\nEtude sur les données pour aide au cadrage du besoin Métier.\nForce de proposition sur des solutions analytiques adaptées aux besoins utilisateurs (avec nos équipes UX).\nAnalyse des besoins métiers, accompagnement à la formulation et à la définition de KPI métiers.\nModélisation des données.\nConception de Datasets Big Query.\nConception et Réalisation de Datamarts et de Dashboards (PowerBI / Looker)\nAnalyse de la qualité de la donnée source, pour challenger les équipes Digitales / Data Engineers.\nVotre Future Équipe :\nAu sein d’un environnement riche et complexe, vous évoluerez avec des experts passionnés à la fois techniques et fonctionnels (Ingénieurs spécialisés, chef de projet, scrum master, product owner …).\nL’équipe est en interaction avec des clients à la fois internes et externes.\nVotre stack de jeu\nSQL – Confirmé\nModélisation de Données – Confirmé\nOutils de Data Viz – Confirmé\nGCP – Junior\nAnglais – Professionnel\nLes Petits Plus Du Projet :\nVous interviendrez de A à Z sur des projets riches fonctionnellement et ambitieux techniquement. Un challenge portant sur des millions d’utilisateurs dans un environnement technique innovant et stratégique.\nVous ?\nDiplômé(e) d’une école d’ingénieur ou équivalent de niveau Bac+5.\nVous justifiez idéalement d’une expérience d’au moins 3 ans d’expériences sur un poste similaire ?\nVous faite preuve d’un bon relationnel et d’esprit d’équipe, êtes doté(e) d’un excellent sens de l’organisation et vous aimez les challenges et la résolution de problème ?\nAlors ce poste est fait pour vous, n’hésitez plus et rejoignez l’aventure ASTEK !\nAstek\nCréé en France en 1988, Astek est un acteur mondial de l’ingénierie et du conseil en technologies. Fort de son expertise dans de nombreux secteurs industriels et tertiaires, Astek accompagne ses clients internationaux dans le déploiement intelligent de leurs produits et de leurs services, et dans la mise en œuvre de leur transformation digitale.\nDepuis sa création, le Groupe a fondé son développement sur une forte culture d’entrepreneuriat et d’innovation, et sur l’accompagnement et la montée en compétence de\nses 7800 collaborateurs\nqui s’engagent chaque jour à promouvoir la complémentarité entre les technologies numériques et l’ingénierie des systèmes complexes.\nRejoignez un Groupe en fort développement en France et à travers le monde ayant réalisé un chiffre d’affaires de 600 M€ en 2023.\nTous les détails sur le Groupe sur le site https://astekgroup.fr. Et vous pouvez aussi nous suivre sur notre blog : https://blog.groupeastek.com.\nRencontrons-nous\nNotre projet commun vous plait ?\nPostulez à cette annonce, et soyez transparent !\nMaud, notre Talent Acquisition Referent, vous contactera pour un premier échange.\nPuis vous rencontrerez Martin, votre futur manager, avec lequel vous échangerez autour d’Astek, de votre parcours, de vos attentes et de votre future mission .\nEnfin, vous rencontrerez Jérémy, notre Directeur d’agence avec lequel vous pourrez valider votre intérêt et adéquation pour le poste et finaliser les éléments contractuels.\nNos Plus\nAstek est green et fait bénéficier ses salariés d’une indemnité kilométrique vélo\nUne politique CARE sur-mesure déployée par nos équipes RH pour nos collaborateurs (https://astekgroup.fr/engagements)\nNotre charte de la Diversité\nMots-clés :\ningénieur – ingénieure – consultant – consultante – data – analyst – modélisation – données\nCaractéristiques de l'emploi\nCatégorie Ingénieur\nJob Industry Télécom / Média\nPostuler en ligne\nNom *\nPrénom *\nEmail *\nUn email valide est requis.\nTéléphone *\nUn numéro de téléphone valide est requis.\nJoindre un CV *\nMots-clés :\ningénieur – ingénieure – consultant – consultante – data – analyst – modélisation – données\nShow more\nShow less",
        "details": {
            "JobDetail": [
                "Confirmé",
                "Junior"
            ],
            "TypeContract": "CDI",
            "Salary": "",
            "Level": "Bac+5",
            "Experience": "3 an(s)"
        },
        "title": "data analyst",
        "skills": {
            "DataBase": [
                "SQL"
            ],
            "CloudComputing": [
                "GCP"
            ],
            "DBMS": [
                "Big Query"
            ],
            "Automation": [
                "Chef"
            ]
        }
    },
    {
        "source": "LinkedIn",
        "company": "ACT-ON DATA",
        "location": "Courbevoie, Île-de-France, France",
        "link": "https://fr.linkedin.com/jobs/view/data-analyst-at-act-on-data-3912559652?position=3&pageNum=2&refId=qJ2foyHYFct0ss%2B3yaGaFw%3D%3D&trackingId=cGKz7lqM1rjx%2BAvg%2FAK2LQ%3D%3D&trk=public_jobs_jserp-result_search-card",
        "description": "Description de l'entreprise\nSociété de conseil & de services, ACT-ON GROUP est l’acteur leader du #HumanTech.\nIl mobilise ses expertises variées et complémentaires en STRATEGY, HR & HRIS, DATA et TECHNOLOGY, ainsi que la connaissance de son écosystème partenaires pour accompagner ses clients dans la réussite de tous leurs projets de transformation qu’ils soient organisationnels, digitaux ou culturels…\nAvec plus de 20 ans d’existence, notre groupe compte aujourd’hui plus de 1 500 missions chez nos clients (ETI, SBF 120, CAC 40, secteur public, associatif et ONG).\nIl réunit une communauté de plus de 600 collaborateurs, pour un chiffre d’affaires de plus de 70 millions d’euros.\nHistoriquement présent sur le marché français, en Île-de-France, à Lille, Lyon et Nantes, il se développe désormais aussi à l’international.\nDescription du poste\nAu sein de notre entité innovante Act-On Data, vous êtes intégré(e) à une équipe d’experts métier en tant que Data analyst, potentiellement sur un projet international.\nVous participerez ainsi à des missions à forte valeur ajoutée auprès de nos clients en intervenant sur des problématiques métiers, tout en ayant la charge de problématiques opérationnelles :\nMettre à disposition des outils de pilotage d'activité à destination des équipes métier en définissant les principaux KPI à suivre,\nMener et présenter les analyses demandées par les Directions métiers ou la Direction nécessaire pour comprendre le business et transformer ces insights en plan d'action,\nVeiller à améliorer et mesurer la qualité des données afin de mettre à disposition des données fiables,\nParmi vos missions :\nCollaborer avec les métiers sur la définition des principaux KPI,\nRécolter des besoins métiers,\nRéalisation des analyses statistiques simples ou complexes en fonction de la demande,\nConception des monitorings de suivi de la qualité des données des différents domaines,\nIntervenir techniquement sur la partie aval de la chaîne de valeur Data.\nQualifications\nVous justifiez d’une expérience significative sur un poste similaire.\nVous avez un niveau d’anglais qui vous permet de piloter un projet à l’international.\nVous maîtrisez vos domaines de compétences (outils/modules ou fonctionnels) et démontrez votre légitimité par des expériences significatives sur un poste similaire.\nNous recherchons une personne organisée, volontaire, dynamique avec une bonne capacité d’adaptation.\nLe goût des chiffres et la maitrise d’Excel sont indispensables.\nVous avez une bonne appétence pour la data et sur les outils de reporting (SAP BI, PowerBI, Tableau, …) et connaissez les plates-formes Cloud (Azure, AWS, GCP)\nD’un tempérament passionné, vous aimez les challenges et vous souhaitez vous investir dans cette aventure ?\nAlors ce poste peut vous intéresser !\nInformations supplémentaires\nCe poste est ouvert au télétravail.\nCe poste est ouvert aux personnes recherchant un CDI uniquement.\nShow more\nShow less",
        "details": {
            "JobDetail": [],
            "TypeContract": "CDI",
            "Salary": "",
            "Level": "",
            "Experience": "20 an(s)"
        },
        "title": "data analyst",
        "skills": {
            "DataVisualisation": [
                "Tableau"
            ],
            "CloudComputing": [
                "GCP",
                "AWS",
                "Azure"
            ],
            "Other": [
                "Statistiques",
                "Cloud"
            ]
        }
    },
    {
        "source": "LinkedIn",
        "company": "Datatorii",
        "location": "Paris",
        "link": "https://fr.linkedin.com/jobs/view/data-analyst-at-datatorii-3916566708?position=4&pageNum=2&refId=qJ2foyHYFct0ss%2B3yaGaFw%3D%3D&trackingId=5JkTwJE8Av1TCDyTEdU5ZQ%3D%3D&trk=public_jobs_jserp-result_search-card",
        "description": "1. Présentation\nDatatorii est une société de conseil spécialisée en data.\nPartenaires des directions métiers et IT, nous accompagnons nos clients dans la mise en place de solutions techniques Microsoft ainsi que dans l’analyse de leurs données.\nLa R&D réalisée en interne (10% du temps, au Dojo) autour de la formation continue et du suivi des évolutions technologiques nous positionne comme un partenaire de choix, spécialisé Data Microsoft.\nOrganisme de formation, nous accompagnons également nos clients de la prise en main jusqu’à la maîtrise des outils et des méthodes autour de la data.\nNichés dans le 1er arrondissement de Paris, nos locaux vous offrent tout le confort pour vous former, échanger régulièrement avec vos pairs, participer aux ateliers internes et recevoir nos clients.\nDatatorii vous donne la possibilité de réaliser vos prochains défis !\n2. Mission\nLa communication en entreprise, interne ou externe, est de plus en plus influencée par la restitution de données, que ce soit via des dashboards, des rapports interactifs ou des présentations au Top Management.\nChez Datatorii, vous évoluerez au sein d’un dispositif pluridisciplinaire (Ingénieur, Data Scientist, Architecte, Chef de projet, Formateur, etc.) qui propose des solutions complètes data :\nLa récolte du besoin auprès des utilisateurs, la définition de personas, de maquettes et d’user-flow\nLa création de Style Guides Data et de thèmes clé-en-main pour les projets de visualisation de données\nL’accompagnement sur les réalisations (PowerBI, PowerApps, Microsoft Azure, Python, SQL, Modélisation, ...)\nLa conception d’offres innovantes et leur promotion (UX BI, BI Self-service, Low-code application, Data Management ...)\nLa réalisation de dashboards et rapports interactifs à fort enjeux\nLa formation interne ou externe au sein de notre organisme de formation\nGrâce à nos parcours de carrière gamifiés, nos training kit et notre dispositif d’accompagnement, Datatorii vous intègre dans un parcours certifiant et vous offre toutes les chances de réussir avec des perspectives de carrière claires et stimulantes.\n3. Profil\nFormation initiale\nBAC +5 Ecole de commerce (Data Analyst, Data Business) ou (Ingénieur, mathématiques, statistiques, informatique)\nConnaissances ou expériences\nVous possédez une première expérience significative en DataViz\nVous y avez développé des compétences de Business Analyst (DataViz, UX, Modélisation, etc. )\nQualités\nExcellent relationnel\nBon communicant\nProactif\nPédagogue\nCapacité d’analyse et de synthèse\nShow more\nShow less",
        "details": {
            "JobDetail": [],
            "TypeContract": "",
            "Salary": "",
            "Level": "",
            "Experience": null
        },
        "title": "data analyst",
        "skills": {
            "ProgLanguage": [
                "R",
                "Python"
            ],
            "DataBase": [
                "SQL"
            ],
            "DataAnalytics": [
                "R"
            ],
            "CloudComputing": [
                "Azure"
            ],
            "Automation": [
                "Chef"
            ],
            "Other": [
                "Statistiques"
            ],
            "EnSoftSkils": [
                "Communication"
            ]
        }
    },
    {
        "source": "LinkedIn",
        "company": "Iveco Group",
        "location": "Le Plessis-Belleville, Hauts-de-France, France",
        "link": "https://fr.linkedin.com/jobs/view/data-analysis-assistant-at-iveco-group-3907438232?position=5&pageNum=2&refId=qJ2foyHYFct0ss%2B3yaGaFw%3D%3D&trackingId=r5z1%2BEhnCgp1DgZHRsC0sA%3D%3D&trk=public_jobs_jserp-result_search-card",
        "description": "FPT Industrial est une marque d'Iveco Group (IVG: MI), dédiée à la conception, la production et la vente de groupes motopropulseurs et solutions destinés aux véhicules routiers et tout-terrain, ainsi qu'aux applications marines et de production d'énergie. Plus de 8000 salariés, répartis sur onze sites de production et onze centres de R&D travaillent pour FPT Industrial à travers le monde. Implantés dans près de 100 pays, le réseau mondial de vente et le Customer Service de FTP Industrial soutiennent tous les clients de la Marque.\nNous recherchons : Un(e) assistant(e) Data Analysis en alternance\nMissions :\n• Fournir les principaux rapports sur les ventes et les produits au niveau de Monde (Europe, Moyen Orient , Asie, Afrique, Amérique latine)\n• Collecter et compiler les données sur la concurrence et les données potentielles au niveau des produits\n• Analyser la performance des ventes par produit\n• Élaborer des rapports standards, un tableau de bord des produits et un suivi des indicateurs de performances clés.\n• Identifier les potentiels produits/ Running parks\nProfil :\nMaster marketing stratégique / Data analytics – Business analytics\n-Anglais opérationnel, l'italien est un plus\n-Compétences d'analyse requises\n-Ouvert d'esprit et curieux : vous ferez partie d'une équipe internationale située entre Le Plessis Belleville et Turin et vous travaillerez dans le département marketing Reman\n-Durée : à partir de septembre 2024 pendant 12 à 24 mois\nOutils :\n-Microsoft Office\n-Excel : très bonne maitrise\n-Powerpoint : bonne maitrise\n-La maitrise d’Access est un plus\n-Data Warehouse (SAP BW)\n-Qlik sense\n-Power BI est un plus\nShow more\nShow less",
        "details": {
            "JobDetail": [],
            "TypeContract": "",
            "Salary": "",
            "Level": "",
            "Experience": null
        },
        "title": "Other",
        "skills": {
            "ProgLanguage": [
                "R"
            ],
            "DataAnalytics": [
                "R"
            ],
            "DataVisualisation": [
                "Power BI",
                "Tableau"
            ]
        }
    },
    {
        "source": "LinkedIn",
        "company": "Mobiskill | WEFY Group",
        "location": "Paris",
        "link": "https://fr.linkedin.com/jobs/view/data-analyst-at-mobiskill-wefy-group-3900004007?position=6&pageNum=2&refId=qJ2foyHYFct0ss%2B3yaGaFw%3D%3D&trackingId=fm6wVtn%2BXTV741jyiPspHg%3D%3D&trk=public_jobs_jserp-result_search-card",
        "description": "L'entreprise?\nInsurTech récemment créée, elle s'impose comme référence sur son marché en proposant des produits d'assurance disruptif.\nIls travaillent avec des petites entreprises comme des grands noms de l'assurance et cumulent 1 millions de clients.\nTeam?\n40 personnes\nContexte?\nForte traction commerciale, ils ont besoin de structurer leur donnée afin de créer de la valeur en interne et de la délivrer à leurs clients aussi.\nLes missions?\n- Participer à la construction de la roadmap data sur le moyen et le long terme (en accord avec les Business units)\n- Leader la mise en former d'une grosse volumétrie de Data pour dégager de la valeur pour leurs partenaires existants\n- Réaliser des études exploratoires poussées pour apporter des recommandations stratégiques à l'entreprise\n- Co-construire les KPIs, OKR et dashboards, puis les automatiser\n- A/B testing sur de potentiels features\nTon profil?\n- Diplômé(e) Bac+5, vous justifiez d'une expérience de 3 ans minimum dans la Data analyse\n- Idéalement, vous êtes familier de l'univers de l'assurance\n- Doté(e) d'une forte capacité analytique, vous êtes aussi capable d'exprimer clairement vos à recommandations à l'oral\n- Tu maîtrises SQL et un outil de Data vizualisation (Tableau/PowerBI). Idéalement tu es aussi familier de Python\n- Fiabilité, proactivité et autonomie sont des compétences clés à ce poste\nLes++?\n- Société en pleine croissance (suite à leur levée de fonds, la roadmap 2024 est validée et ils sont prêts à scaler )\n- Organisation d’entreprise alliant flexibilité et structure (méthode de l’autonomie alignée)\n- Poste évolutif avec de fortes perspectives d'évolutions (dont management)\n- Package attractif\nShow more\nShow less",
        "details": {
            "JobDetail": [],
            "TypeContract": "",
            "Salary": "Package",
            "Level": "Bac+5",
            "Experience": "3 an(s)"
        },
        "title": "data analyst",
        "skills": {
            "ProgLanguage": [
                "Python"
            ],
            "DataBase": [
                "SQL"
            ],
            "DataVisualisation": [
                "Tableau"
            ]
        }
    },
    {
        "source": "LinkedIn",
        "company": "Astek",
        "location": "Lille, Hauts-de-France, France",
        "link": "https://fr.linkedin.com/jobs/view/data-analyst-%E2%80%93-lille-france-h-f-at-astek-3839093481?position=7&pageNum=2&refId=qJ2foyHYFct0ss%2B3yaGaFw%3D%3D&trackingId=CuGoTs8pGBQ2grHeXh6T9w%3D%3D&trk=public_jobs_jserp-result_search-card",
        "description": "CDI\nLille - France\nPubliée il y a 2 mois\nLe Groupe Astek\nCe Que Nous Allons Accomplir Ensemble :\nNous rejoindre en tant que\nData Analyst (H/F),\nafin d’accompagner un opérateur télécoms, Leader en Europe dans la gestion de ses solutions robustes, efficientes et sécurisées à destination d’environnements variés.\nUn challenge portant sur des millions d’utilisateurs dans un environnement technique innovant, stratégique et où l’entraide et la bonne humeur priment !\nVotre Mission, Si Vous L’acceptez :\nEtude sur les données pour aide au cadrage du besoin Métier.\nForce de proposition sur des solutions analytiques adaptées aux besoins utilisateurs (avec nos équipes UX).\nAnalyse des besoins métiers, accompagnement à la formulation et à la définition de KPI métiers.\nModélisation des données.\nConception de Datasets Big Query.\nConception et Réalisation de Datamarts et de Dashboards (PowerBI / Looker)\nAnalyse de la qualité de la donnée source, pour challenger les équipes Digitales / Data Engineers.\nVotre Future Équipe :\nAu sein d’un environnement riche et complexe, vous évoluerez avec des experts passionnés à la fois techniques et fonctionnels (Ingénieurs spécialisés, chef de projet, scrum master, product owner …).\nL’équipe est en interaction avec des clients à la fois internes et externes.\nVotre stack de jeu\nSQL – Confirmé\nModélisation de Données – Confirmé\nOutils de Data Viz – Confirmé\nGCP – Junior\nAnglais – Professionnel\nLes Petits Plus Du Projet :\nVous interviendrez de A à Z sur des projets riches fonctionnellement et ambitieux techniquement. Un challenge portant sur des millions d’utilisateurs dans un environnement technique innovant et stratégique.\nVous ?\nDiplômé(e) d’une école d’ingénieur ou équivalent de niveau Bac+5.\nVous justifiez idéalement d’une expérience d’au moins 3 ans d’expériences sur un poste similaire ?\nVous faite preuve d’un bon relationnel et d’esprit d’équipe, êtes doté(e) d’un excellent sens de l’organisation et vous aimez les challenges et la résolution de problème ?\nAlors ce poste est fait pour vous, n’hésitez plus et rejoignez l’aventure ASTEK !\nAstek\nCréé en France en 1988, Astek est un acteur mondial de l’ingénierie et du conseil en technologies. Fort de son expertise dans de nombreux secteurs industriels et tertiaires, Astek accompagne ses clients internationaux dans le déploiement intelligent de leurs produits et de leurs services, et dans la mise en œuvre de leur transformation digitale.\nDepuis sa création, le Groupe a fondé son développement sur une forte culture d’entrepreneuriat et d’innovation, et sur l’accompagnement et la montée en compétence de\nses 7800 collaborateurs\nqui s’engagent chaque jour à promouvoir la complémentarité entre les technologies numériques et l’ingénierie des systèmes complexes.\nRejoignez un Groupe en fort développement en France et à travers le monde ayant réalisé un chiffre d’affaires de 600 M€ en 2023.\nTous les détails sur le Groupe sur le site https://astekgroup.fr. Et vous pouvez aussi nous suivre sur notre blog : https://blog.groupeastek.com.\nRencontrons-nous\nNotre projet commun vous plait ?\nPostulez à cette annonce, et soyez transparent !\nMaud, notre Talent Acquisition Referent, vous contactera pour un premier échange.\nPuis vous rencontrerez Martin, votre futur manager, avec lequel vous échangerez autour d’Astek, de votre parcours, de vos attentes et de votre future mission .\nEnfin, vous rencontrerez Jérémy, notre Directeur d’agence avec lequel vous pourrez valider votre intérêt et adéquation pour le poste et finaliser les éléments contractuels.\nNos Plus\nAstek est green et fait bénéficier ses salariés d’une indemnité kilométrique vélo\nUne politique CARE sur-mesure déployée par nos équipes RH pour nos collaborateurs (https://astekgroup.fr/engagements)\nNotre charte de la Diversité\nMots-clés :\ningénieur – ingénieure – consultant – consultante – data – analyst – modélisation – données\nCaractéristiques de l'emploi\nCatégorie Ingénieur\nJob Industry Télécom / Média\nPostuler en ligne\nNom *\nPrénom *\nEmail *\nUn email valide est requis.\nTéléphone *\nUn numéro de téléphone valide est requis.\nJoindre un CV *\nMots-clés :\ningénieur – ingénieure – consultant – consultante – data – analyst – modélisation – données\nShow more\nShow less",
        "details": {
            "JobDetail": [
                "Confirmé",
                "Junior"
            ],
            "TypeContract": "CDI",
            "Salary": "",
            "Level": "Bac+5",
            "Experience": "3 an(s)"
        },
        "title": "data analyst",
        "skills": {
            "DataBase": [
                "SQL"
            ],
            "CloudComputing": [
                "GCP"
            ],
            "DBMS": [
                "Big Query"
            ],
            "Automation": [
                "Chef"
            ]
        }
    },
    {
        "source": "LinkedIn",
        "company": "moOngy Digital Lab",
        "location": "Lille",
        "link": "https://fr.linkedin.com/jobs/view/data-analyst-h-f-at-moongy-digital-lab-3890974953?position=8&pageNum=2&refId=qJ2foyHYFct0ss%2B3yaGaFw%3D%3D&trackingId=uf%2FTvTD%2FsimXjgz5Z6hkSQ%3D%3D&trk=public_jobs_jserp-result_search-card",
        "description": "Web Transition, c’est qui ?\nFondée en 2011,\nWeb transition\nest une entreprise de services numériques opérant sur le marché de l’IT/Digital !\nConstituant une part essentielle de\nMoOngy Digital Lab\n, Web Transition accompagne ses clients grands comptes sur leurs projets de Webmarketing, de Design, Gestion de projet et également en Data !\nNotre objectif : nous implanter comme un acteur principal sur le marché de la Transformation Digitale en accompagnant et valorisant les compétences de nos collaborateurs !\nNous sommes convaincus que le succès de MoOngy Digital Lab réside dans la somme des potentiels de nos équipes 🤝\nTon équipe : La tribu Data\nParce qu’il est indispensable que tu puisses partager tes connaissances mais aussi en acquérir de nouvelles, tu feras partie de l’une de nos tribus : celle de la Data. De plus, cela te permettra d’être acteur dans le développement et la stratégie de Web Transition. Ce système de co-réflexion et co-construction est un fondement essentiel chez nous !\nDans cette aventure, tu :\nOptimises\nles requêtes SQL ;\nConstruis\nles modèles de régression ;\nAnalyses\nla rentabilité des actions marketing ;\nRéalises\ndes études ad hoc sur les comportements clients ;\nProduits\net\nautomatises\nle reporting.\nRejoins-nous si tu as :\nUne expérience de 3 ans minimum,\nUne maitrise technique de GCP / DBT / PowerBI,\nUne expérience similaire dans une startup ou dans l’industrie serait un plus !\nTon savoir-être :\nOuvert d’esprit\nRespectueux des différences de chacun\nCurieux\nProactif\nPar où on commence ?\nUn premier entretien RH d’1h pour comprendre ton parcours et tes aspirations\nUn second entretien de 45 minutes avec l’un de nos Business Manager afin de valider tes compétences et qu’il se projette sur l’une des missions qu’il pourrait te proposer\nUn troisième entretien de quelques minutes avec notre responsable d’agence pour te proposer d’intégrer notre superbe Team Web !\n3 entretiens en peu de temps, si ton profil correspond tu intègreras très vite nos équipes 😉\nPrêt pour embarquer dans notre grande aventure humaine ? Deviens notre futur Weber en postulant à cette offre ! Voici les avantages qui t’attendent en tant que Weber :\n🤩 Des collègues incroyables\n🏆 Certifiée Great Place to Work\n🎮 Des bureaux sympas (où vous serez toujours les bienvenus)\n🎉 Des teambuilding et évents tous les mois\n💻 Des tributs métiers pour échanger entre Weber du même métier\nDes missions chez le client qui sont accompagnées et coachées par ton manager\nUn accompagnement dans ton plan de carrière et tes envies de re skilling\n🤓 Un catalogue de formations certifiantes ouvert à tous les salariés\n🍽️ Une carte tickets restaurant MyEdenred\n❤️ Une mutuelle GrasSavoye\n🚎 Une prise en charge des frais de transport à 100%\nShow more\nShow less",
        "details": {
            "JobDetail": [],
            "TypeContract": "",
            "Salary": "",
            "Level": "",
            "Experience": "3 an(s)"
        },
        "title": "data analyst",
        "skills": {
            "DataBase": [
                "SQL"
            ],
            "CloudComputing": [
                "GCP"
            ]
        }
    },
    {
        "source": "LinkedIn",
        "company": "Novencia Group",
        "location": "Lyon, Auvergne-Rhône-Alpes, France",
        "link": "https://fr.linkedin.com/jobs/view/data-analyst-lyon-f-h-at-novencia-group-3842056375?position=9&pageNum=2&refId=qJ2foyHYFct0ss%2B3yaGaFw%3D%3D&trackingId=bXmYtTRYeAYlcjy0MNiY3g%3D%3D&trk=public_jobs_jserp-result_search-card",
        "description": "Carnet de route\nNovencia accompagne ses clients dans leurs projets de transformation digitale, technologique et data.\nExpert en Data et Intelligence Artificielle nous aidons nos clients à exploiter et valoriser leurs données sous toutes ses formes en les accompagnant sur des projets de Data Gouvernance, Data Architecture, Data Science, et Data Engineering.\nData Analyst\ndepuis au moins\n3 ans,\ntu es à la recherche de nouveaux défis. Boucle ta ceinture, la suite est pour toi !\nTon Rôle\nRattaché.e aux consultants de l’agence Lyonnaise, tu seras amené.e à travailler chez les clients finaux et/ou au sein de notre Datalab’.\nEn tant que Data Analyst, tu auras les missions suivantes :\nT’immerger dans le contexte client ;\nMener des ateliers avec les équipes métier pour recueillir/ définir leurs besoins ;\nChallenger leurs demandes ;\nParticiper au recueil et à la modélisation des données ;\nContrôler la fiabilité et la qualité des données ;\nStructurer et exploiter les données grâce à des outils de Data visualisation ;\nAnalyser ces données et partager les résultats ;\nFaire des recommandations au client.\nTon profil\nDe formation Bac+5 dans le domaine de la Data, tu as au moins 3 ans d’expérience sur un poste similaire.\nCompétences techniques recherchées :\nExpérience significative sur un outil de Data visualisation pour l’élaboration de rapports/tableaux de bord (Power BI/Tableau/QlikSense etc.)\nLangage SQL (Python est un plus)\nModélisation de données\nConnaissance des bases de données (e.g. Snowflake, Google BigQuery, SQL Server ou Oracle)\nUtilisation d’un ETL (e.g. Azure Data Factory, SSIS, Informatica, Talend, Matillion)\nUne expérience dans le fonctionnement d’une équipe agile.\nTu es passionné.e par la Data et souhaites évoluer au sein d’une communauté d’Experts de la Data, tu veux t’investir dans des projets data innovants au sein de notre Datalab’, tu aimes le travail en équipe mais sais être autonome sur tes sujets, tu es curieux.euse et force de proposition, tu es capable de chercher et trouver des solutions, tu as un bon niveau d’anglais.\nEnfin, tu souhaites intégrer une agence à taille humaine où la bienveillance n’est pas qu’un mot marketing.\nS’engager en faveur du handicap c’est garantir l’égalité des chances dès le recrutement. À compétences égales, nos postes sont ouverts aux personnes en situation de handicap.\nShow more\nShow less",
        "details": {
            "JobDetail": [],
            "TypeContract": "",
            "Salary": "",
            "Level": "Bac+5",
            "Experience": "3 an(s)"
        },
        "title": "data analyst",
        "skills": {
            "ProgLanguage": [
                "Python"
            ],
            "DataBase": [
                "SQL"
            ],
            "DataVisualisation": [
                "Power BI",
                "Tableau"
            ],
            "CloudComputing": [
                "Azure"
            ],
            "DBMS": [
                "SQL Server",
                "BigQuery",
                "Snowflake"
            ]
        }
    },
    {
        "source": "LinkedIn",
        "company": "LEADER S.A.S",
        "location": "Le Havre",
        "link": "https://fr.linkedin.com/jobs/view/data-analyst-h-f-at-leader-s-a-s-3909699484?position=10&pageNum=2&refId=qJ2foyHYFct0ss%2B3yaGaFw%3D%3D&trackingId=%2B9je3t%2BltPtuFK7aqYiyvA%3D%3D&trk=public_jobs_jserp-result_search-card",
        "description": "Les sociétés de LEADER GROUP représentées par près de 170 salariés en France, Allemagne, Autriche, Chine et Etats-Unis, proposent à leurs clients du monde entier un ensemble de produits – émulseurs, équipements mousse, appareils de recherche de victimes, ventilateurs de désenfumage, lances, canons incendies, caméras thermiques, etc. – de haute technicité et fiables en toutes circonstances pour protéger et secourir les personnes et les biens.\nL'innovation est l'un des moteurs essentiels du Groupe, qui s'appuie également sur un système d'amélioration continue et de responsabilité sociétale et environnementale.\nRaison d’être de Leader Group : « Aider à sauver des vies »\nPour répondre à sa dynamique de croissance, LEADER renforce ses équipes et recherche son/sa futur(e)\nData Analyst H/F\nCDI – temps plein – Le Havre/Octeville sur mer (76)\nVos missions\nRattaché(e) au site de LEADER et sous la responsabilité du Directeur Commercial et Marketing, le/la Data Analyst se charge de l'analyse des données commerciales et marketing pour aider à la prise de décisions éclairées au sein des entités du groupe. A ce titre vos principales missions seront de :\nRéaliser des analyses approfondies des données de ventes internes, et du marché des équipements concernés, incluant les tendances, la demande, et les innovations technologiques.\nÉtudier la concurrence pour comprendre leurs produits, tarifications, et stratégies marketing.\nCollaborer étroitement avec les équipes de vente, et chefs produits pour partager les insights du marché et orienter le développement de produits et les stratégies commerciales.\nÉlaborer des rapports détaillés et des présentations pour la direction, avec des recommandations permettant de guider les décisions stratégiques, et soutenir l’équipe commerciale.\nEtudier chaque marché et connaitre le potentiel en chiffres et en volumes dans chaque pays pour les activités de Leader et différentes familles de produits.\nRechercher, référencer et suivre les appels d’offres\nVotre profil\nTitulaire d’un bac + 4/5 en marketing ou statistiques, vous justifiez d’une première expérience du secteur industriel, B2B et des produits techniques.\nOrienté(e) amélioration continue, vous avez une maîtrise parfaite des outils informatiques (Excel), CRM et ERP, de bonnes compétences analytiques et la capacité à communiquer des informations complexes de manière claire et compréhensible.\nLa curiosité, le souci du détail et une bonne aisance relationnelle sont des qualités qui vous caractérisent.\nVotre maitrise de l’anglais vous permet de communiquer aisément à l’écrit comme à l’oral.\nDes déplacements nationaux et internationaux ponctuels sont à prévoir.\nInformations complémentaires\nVotre futur bureau est basé à Octeville sur Mer, commune littorale limitrophe du Havre, au cœur du siège social du Groupe.\nA votre salaire de base (35K€ à 38K€/an), s’ajoutent une prime annuelle, RTT, mutuelle d’entreprise, télétravail partiel possible, conciergerie d’entreprise, et des titres restaurant.\nSi vous vous reconnaissez dans ce descriptif, et souhaitez relever de nouveaux défis au sein d'une entreprise innovante, en pleine évolution, rejoignez-nous en envoyant votre candidature\nNous avons hâte de vous rencontrer et de découvrir comment vous pouvez contribuer à notre équipe dynamique et à nos projets passionnants.\nLes équipes de LEADER innovent chaque jour pour protéger et secourir.\nPour en savoir plus, n’hésitez pas à consulter notre site https://www.leader-group.company/fr\nShow more\nShow less",
        "details": {
            "JobDetail": [
                "Temps plein"
            ],
            "TypeContract": "CDI",
            "Salary": "35K",
            "Level": "",
            "Experience": null
        },
        "title": "data analyst",
        "skills": {
            "Other": [
                "Statistiques"
            ]
        }
    },
    {
        "source": "LinkedIn",
        "company": "Lokad",
        "location": "Paris, Île-de-France, France",
        "link": "https://fr.linkedin.com/jobs/view/business-data-analyst-h-f-at-lokad-3915779840?position=1&pageNum=5&refId=9FNYDD6Vrcv1aW7UUJOd7A%3D%3D&trackingId=6nl2OtPTboNbxYMoxBOqGQ%3D%3D&trk=public_jobs_jserp-result_search-card",
        "description": "We’re looking for the right candidate to join our Business Data Analyst team and become part of a fast-growing company that is on always on the look for people that will demonstrate they’re able to grow with the company. As the role is our entry level, this is a great entry point for a career path at Lokad, either as a future technical expert or as manager.\nWe help companies in different verticals (aerospace, automotive, ecommerce…) to forecast and make decisions about their inventory. The vast majority of our clients are based outside of France, mainly in North America and Europe.\nAs a Business Data Analyst (or Supply Chain Scientist in Lokad's terminology), your role is to make sure our clients get the most from Lokad's technology. The role is a mix between technology, data crunching and supply chain expertise. You will address complex supply chain issues and craft quantitative strategies. Your goal is not only to advise your clients on strategies to adopt, but to craft and execute these strategies on a daily basis while leveraging the data available as much as possible. Your goal is also to keep refining these strategies over time to keep them aligned with the needs of our clients.\nAt Lokad, you will benefit from the extensive training and coaching of our expert team. You will gain skills in supply chain, predictive analysis and overall quantitative optimization for business. You will learn how to achieve measurable business results grounded on scientific analysis of data.\nAbout one quarter of your time is spent interacting with clients in order to better understand their business (mainly over the phone or by mail, with occasional travels). Note that, in order to benefit from your colleagues expertise, you won't be required to work on the customers' premises.\nThe rest of your time is spent on data analysis, including manipulating and cleaning data, setting up forecasts, economic optimization, reporting and data vizualisation. In order to do this, you'll learn to use our Differentiable Programming tools and a DSL (Envision) developped by Lokad.\nWe are looking for candidates with the following skills and qualities:\nA strong engineering background.\nA keen interest in data and quantitative analysis in general.\nGood Excel skills or programming skills (e.g. Python, VBA, SQL, etc.).\nImpeccable command of English\n( French is optional).\nExcellent communication skills and telephone manners.\nA well-made head, rather than a well-filled head.\nWe are not looking for someone who is already an expert in supply chain or programming. We’re looking for a fast learner, with an ability to quickly grasp technology and concepts, since our technology is by no means a simple and plug-and-play product. Knowledge or understanding of supply chain would be a bonus, but the ability to quickly assess and grasp a new situation or get a clear picture of how an organization works and what are the pain points is what we are really after.\nCandidates must be self-motivated, confident and highly driven to achieve results with a “hands on” attitude.\nThe role is predominantly office based, although some travel will be occasionally required to customers, partners or events. We are located in the very center of Paris, France (station Chevaleret).\nShow more\nShow less",
        "details": {
            "JobDetail": [],
            "TypeContract": "",
            "Salary": "",
            "Level": "",
            "Experience": null
        },
        "title": "data analyst",
        "skills": {
            "ProgLanguage": [
                "Python"
            ],
            "DataBase": [
                "SQL"
            ],
            "EnSoftSkils": [
                "Communication",
                "Organization"
            ]
        }
    },
    {
        "source": "LinkedIn",
        "company": "SOFTEAM",
        "location": "Paris, Île-de-France, France",
        "link": "https://fr.linkedin.com/jobs/view/data-analyst-f-h-at-softeam-3587086987?position=2&pageNum=5&refId=9FNYDD6Vrcv1aW7UUJOd7A%3D%3D&trackingId=BgrRUM%2Brzt0%2FFt%2BO31KNyA%3D%3D&trk=public_jobs_jserp-result_search-card",
        "description": "Vous évoluez dans le domaine de la Data et souhaitez intégrer\nun leader de la transformation numérique spécialisé dans les secteurs de la Banque, du Luxe, de l'Assurance, de la Finance, de l'Energie et la possibilité d'évoluer au sein du Groupe Docaposte !\nSofteam est labellisé \"HappyIndex® AtWork \" 2022 pour la 5ème année consécutive !\nNos collaborateurs\ntravaillent en « mode projet » et accompagnent de bout en bout nos clients sur des problématiques de Gouvernance.\nCE QUE NOUS RECHERCHONS\nData Analyst\npour intervenir sur nos projets et contribuer au développement de notre Practice « Augmented analytics »\nCE QUE NOUS ATTENDONS DE VOUS\nVos missions :\nMaîtriser les outils statistiques et les informations nécessaires à la mise en place d'une base de données,\nGérer parfaitement les différentes technologies spécifiques au big data,\nExtraire les données du système source,\nExtraire et traduire des données business en données statistiques,\nModéliser et assurer les mises à jour régulières de la base de données,\nContrôler la qualité des données,\nMettre en œuvre une data warehouse\nSynthétiser et vulgariser les informations pour les rendre accessibles aux utilisateurs.\nVOUS ETES\nIngénieur(e) de formation avec une spécialité Business Analytics, Big Data, Applications des Masses de Données (IAMD), Systèmes Décisionnels..\nvous disposez d'une expérience de\n3 ans minimum\nen tant que\nData Analyst/Data Miner\n..\nVous avez une expertise sur un ou plusieurs des outils d'alimentation et de traitement suivants :\nSQL, Alteryx, Dataiku, Python\n..\nVous avez une expertise sur un ou plusieurs des outils de data visualisation suivants :\nPower BI, Looker/GCP, Qlik, Tableau Software,\nBon(ne) communicant(e), curieux(se) et adaptable, v\nous êtes doté(e) d'une grande capacité d’analyse et de synthèse et d'un bon esprit d'équipe,\nVotre maîtrise de l'\nanglais\nvous permet d'évoluer dans un contexte international.\nNOUS VOUS OFFRONS\nDes\nmissions engageantes\nauprès des grands acteurs du marché.\nUn management de proximité avec\nGilles SALVADOR, Directeur du Centre d'Expertise Data\n, toujours bienveillant et à à l'écoute et avec qui vous pourrez échanger au quotidien sur les enjeux de votre mission et évoquer vos futurs projets afin que nous puissions vous aider à les réaliser.\nLa possibilité d’évoluer et de monter en compétences grâce à des\nformations et à des certifications auprès de nos clients et de nos consultants\n, des\n12@13\n, notre Entité\nSofteam Institute, Organisme de formation interne\nde renommé qui délivre des formations auprès de nos clients...\nQUI SOMMES-NOUS ?\nSOFTEAM DATA\nest une marque de\nDOCAPOSTE\nspécialisée dans l'informatique décisionnelle et les nouvelles technologies. Nous apportons notre expertise à nos clients, principalement des Grands Comptes de la place financière française, dans des projets de transformation digitale et cognitive.\n2000 Softeamien.nes\nsont dédié.es à la transformation métier et digitale de nos clients et ont généré 200 M€ de chiffre d’affaires en 2020.\nSOFTEAM SPIRIT\nDes\ncommunautés d'expertises sur les sujets de la Data\nDe\nsuper nouveaux locaux qui sont en plus accessibles facilement\nUne\nécole de formation intégrée\nDes\névènements : des soirées avec les consultants, des 12@13...\nUne entreprise\nlabellisée \"Happy at Work\" pour la 5ème année consécutive\n.\nN’attendez plus, rejoignez SOFTEAM et venez nous rencontrer dans nos nouveaux locaux situés à la Défense #DevenezSofteamien !\nShow more\nShow less",
        "details": {
            "JobDetail": [],
            "TypeContract": "",
            "Salary": "",
            "Level": "",
            "Experience": "3 an(s)"
        },
        "title": "data analyst",
        "skills": {
            "ProgLanguage": [
                "Python"
            ],
            "DataBase": [
                "SQL"
            ],
            "DataVisualisation": [
                "Power BI",
                "Tableau"
            ],
            "CloudComputing": [
                "GCP"
            ],
            "Other": [
                "Statistiques",
                "Big Data"
            ]
        }
    },
    {
        "source": "LinkedIn",
        "company": "Talent Disruptors",
        "location": "Paris, Île-de-France, France",
        "link": "https://fr.linkedin.com/jobs/view/data-analyst-at-talent-disruptors-3860725693?position=3&pageNum=5&refId=9FNYDD6Vrcv1aW7UUJOd7A%3D%3D&trackingId=umm8lmNVvTOV8qQw60QtlQ%3D%3D&trk=public_jobs_jserp-result_search-card",
        "description": "We are on the lookout for a Data Analyst with a specialization in marketing analytics. In this critical role, you will harness the power of tools like Google Data Studio, BigQuery, and Power BI to derive actionable insights that drive our marketing decisions. Your expertise in analyzing complex datasets and turning them into understandable and strategic information will be essential in shaping our marketing strategies. This position is ideal for someone who thrives on data-driven challenges and has a passion for leveraging technology to inform business decisions.\nWhat You’ll Be Doing\nData Analysis and Interpretation: Utilize tools like Google Data Studio, BigQuery, and Power BI to analyze marketing data and extract meaningful insights.\nDeveloping Reporting Dashboards: Create dynamic dashboards and reports that provide real-time insights into marketing performance.\nCollaborating with Marketing Teams: Work closely with marketing teams to understand their data needs and provide insights that inform strategy and decision-making.\nData Integration and Management: Integrate data from various sources to provide a comprehensive view of marketing performance.\nPerformance Tracking: Monitor key performance indicators (KPIs) to measure the effectiveness of marketing campaigns and strategies.\nPredictive Analysis: Use data to predict trends and market movements, aiding in proactive strategy development.\nTraining and Support: Provide training and support to team members in using data analysis tools and understanding reports.\nWho You Are\nProficient in Data Analysis Tools: You have strong experience with tools such as Google Data Studio, BigQuery, and Power BI.\nAnalytical and Insightful: You possess the ability to analyze complex datasets and turn them into actionable insights.\nCollaborative in Nature: You work well with marketing teams, understanding their needs and communicating data insights effectively.\nSkilled in Data Integration: You are adept at integrating and managing data from various sources.\nDetail-Oriented: You have a keen eye for detail and accuracy in data analysis and reporting.\nProactive and Predictive: You are capable of conducting predictive analyses to inform future marketing strategies.\nExcellent Communicator: You can clearly convey data insights and their implications to non-technical team members.\nWhat Success Looks Like\n30 Days\nEstablish a comprehensive, organized online database in BigQuery to store all client and marketing data and integrate lead data from CRMs, digital advertising data, customer opt-ins, and purchasing data to provide meaningful insights that inform marketing decisions.\nCreate and maintain data dashboards in Looker Studio for easy data visualization, analysis, and automated reporting.\n60 Days\nDevelop statistical models for data analysis, including linear regression modeling and predictive lead scoring, that effectively guide marketing actions.\n90 Days\nAutomated the generation of actionable insights and trends over time from data analysis to inform our marketing strategy.\nShow more\nShow less",
        "details": {
            "JobDetail": [],
            "TypeContract": "",
            "Salary": "",
            "Level": "",
            "Experience": null
        },
        "title": "data analyst",
        "skills": {
            "DataVisualisation": [
                "Power BI"
            ],
            "DBMS": [
                "BigQuery"
            ],
            "Collaboration": [
                "Teams"
            ]
        }
    },
    {
        "source": "LinkedIn",
        "company": "Mazars",
        "location": "Paris, Île-de-France, France",
        "link": "https://fr.linkedin.com/jobs/view/data-analyst-junior-paris-2024-h-f-at-mazars-3838258695?position=4&pageNum=5&refId=9FNYDD6Vrcv1aW7UUJOd7A%3D%3D&trackingId=AhU6IATg%2BZgeBQXN2ELG1A%3D%3D&trk=public_jobs_jserp-result_search-card",
        "description": "Votre poste\nMazars est un groupe international et intégré spécialisé dans l’audit, la fiscalité et le conseil ainsi que dans les services comptables et juridiques*. Présents dans plus de 95 pays et territoires à travers le monde, nous nous appuyons sur l’expertise de plus de 47 000 professionnels – plus de 30 000 au sein de notre partenariat intégré et plus de 17 000 via « Mazars North America Alliance » – pour accompagner les clients de toutes tailles à chaque étape de leur développement.\n*Dans les pays où les lois en vigueur l’autorisent\nVos principales missions\nMazars souhaite chaleureusement son équipe « Audit Data Analytics » au sein de ses équipes Data Services.\nAu sein d'une équipe à la frontière entre l'audit et la tech, vous développez ainsi une double compétence technique et fonctionnelle ; en véritable Business Analyst, vous concevez et déployez des solutions Analytics pour les clients Mazars.\nVous Intervenez Sur Des Missions Variées Dans Plusieurs Secteurs D'activité (industrie, Services, Secteur Public, Services Financiers (banque Et Assurance)) Et Alimentez Les Compétences Suivantes\ndéveloppement de solutions innovantes sur des socles technologiques variés de data analytics, de data visualisation et de programmation : Alteryx, Qlik, SQL, PowerBI, Python, etc. ;\nparticipation à la conception de solutions fonctionnelles, de la phase de spécifications à la phase de mise à disposition ;\ncontribution au développement de nouvelles offres Mazars au service des enjeux Data de nos clients ;\nanalyser fonctionnellement les résultats produits par les solutions Analytics ;\nparticipation à la rédaction de rapports d'analyse et présentation des outils et résultats Analytics à nos clients.\nEn complément, vous êtes progressivement formés aux technologies de machine learning, à l'intelligence artificielle et à la science des données.\nVotre profil\nDe Formation Bac+5, Vous Êtes Jeune Diplômé(e) D'une École D'ingénieurs, École De Commerce Ou Université Et Avez Un Goût Prononcé Pour Les Sujets Analytics Et Les Nouvelles Technologies De Façon Générale, Avec Une Appétence Pour Les Problématiques Métier Et Finance\nVous avez une spécialisation en Système d'Information et/ou en Data Science ;\nVous êtes passionné(e) par les nouvelles technologies liées à la Data ;\nVous avez idéalement une expérience de stage au cours de laquelle vous êtes intervenu(e) sur le domaine de la « Data » ;\nVous aimez innover, vous êtes curieux, dynamique et autonome et vous avez une certaine\naisance à développer vos connaissances sur de nouveaux outils ;\nVous avez un excellent sens du travail en équipe ;\nVous possédez les connaissances de base parmi les technologies suivantes : SQL, ACL, data studio, PowerBI, Qlik, Alteryx, Tableau softwareetc.)\nIntégration prévue à partir de septembre 2024\nShow more\nShow less",
        "details": {
            "JobDetail": [],
            "TypeContract": "",
            "Salary": "",
            "Level": "Bac+5",
            "Experience": null
        },
        "title": "data analyst",
        "skills": {
            "ProgLanguage": [
                "Python"
            ],
            "DataBase": [
                "SQL"
            ],
            "DataVisualisation": [
                "Tableau"
            ],
            "Other": [
                "Machine Learning"
            ]
        }
    },
    {
        "source": "LinkedIn",
        "company": "Stack Digital",
        "location": "Belfort, Bourgogne-Franche-Comté, France",
        "link": "https://fr.linkedin.com/jobs/view/data-analyst-at-stack-digital-3895910936?position=5&pageNum=5&refId=9FNYDD6Vrcv1aW7UUJOd7A%3D%3D&trackingId=vUmOApUSAzjlXJCoQmU7ww%3D%3D&trk=public_jobs_jserp-result_search-card",
        "description": "Job Title:\nData Analyst\nType:\nContract\nLocation:\nBelfort, France\nImmediate Joining Required\nOverview:\nWe are currently seeking a dedicated Analyst with expertise in the Shopfloor/Manufacturing domain to join our team. This role requires a professional who is adept at learning existing application business functions and is capable of working independently on Oracle PL/SQL. The ideal candidate will be based out of our client's office in Belfort and must be willing to collaborate with geographically distributed teams across India and the Americas.\n​​​​​​​\nKey Responsibilities:\nLearn and understand the business functions of existing applications within the Shopfloor/Manufacturing domain.\nParticipate in the transition process, including documentation and internal transition to other teams.\nIndependently work on Oracle PL/SQL, including solving tickets related to PL/SQL issues.\nCoordinate with third-party application vendors to ensure tickets are resolved within the Service Level Agreement (SLA).\nParticipate in critical outage calls as required.\nPrepare high-quality status reports and present them to stakeholders if needed.\nRequirements:\nProven experience in the Shopfloor/Manufacturing domain.\nStrong capability in working independently on Oracle PL/SQL.\nExperience in coordinating with third-party vendors and managing ticket resolution within SLA.\nExcellent problem-solving skills and ability to participate in critical outage calls.\nNative level French language proficiency and strong business English language skills.\nAbility to work effectively with geographically distributed teams.\nExcellent documentation skills and experience in transition processes.\nWhy Join Us?\nThis is a fantastic opportunity to contribute to a critical role within a dynamic and challenging environment. You will have the chance to work with a diverse team and develop your skills in a global setting. If you are a motivated individual with a passion for the Shopfloor/Manufacturing domain and possess the required skills, we would love to hear from you.\nHow to Apply:\nPlease submit your application, including your CV and a cover letter, highlighting your relevant experience and why you are the best fit for this role. We are looking for immediate joiners, so please indicate your earliest availability.\nShow more\nShow less",
        "details": {
            "JobDetail": [],
            "TypeContract": "",
            "Salary": "",
            "Level": "",
            "Experience": null
        },
        "title": "data analyst",
        "skills": {
            "DataBase": [
                "SQL"
            ],
            "Collaboration": [
                "Teams"
            ]
        }
    },
    {
        "source": "LinkedIn",
        "company": "Allianz France",
        "location": "Paris, Île-de-France, France",
        "link": "https://fr.linkedin.com/jobs/view/data-analyst-h-f-at-allianz-france-3909795270?position=6&pageNum=5&refId=9FNYDD6Vrcv1aW7UUJOd7A%3D%3D&trackingId=ojlNCfNepK96X%2BENBfD4Cg%3D%3D&trk=public_jobs_jserp-result_search-card",
        "description": "Allianz\nLeader européen de l'assurance et des services financiers, Allianz propose une offre complète couvrant tous les besoins en assurance, assistance et services financiers des particuliers, professionnels, entreprises et collectivités. Allianz compte plus de 150.000 salariés dans le monde. Le groupe réalise 75% de ses activités en Europe et il est présent dans plus de 70 pays. Avec 80 millions de clients dans le monde, Allianz fait partie des 5 plus grands groupes financiers mondiaux et est n° 1 de l'assurance et des services financiers en Europe.\nL’Unité Investissements\nAIM Paris (Allianz Investment Management Paris), l’unité Investissement d’Allianz France, a la charge de la gestion des investissements des différentes entités d’Allianz France tant sur les portefeuilles d’actifs généraux qu’en unités de compte (UC), sur toute la chaîne de valeur des investissements, qui couvre la gestion actif-passif, la stratégie d'investissement, ainsi que la planification des revenus des investissements, le suivi des risques, le reporting et les opérations.\nDescriptif / Missions du poste\nPour soutenir ces activités l’équipe AIM Finance & Opérations, en charge des données d’investissements, des reportings et du suivi des risques des investissements, est à la recherche d’un « Data Analyst ». Ce dernier, rattaché hiérarchiquement à AIM Finance & Opérations, couvrira l’ensemble des besoins des différentes équipes d’AIM (AIM Investment Strategy, AIM Asset-Liability Management, AIM Finance) et interviendra de façon opérationnelle sur des projets de transformation locaux et Groupe.\nVotre mission sera d’intervenir plus particulièrement sur :\nL’automatisation de sourcing des données, des contrôles et des réconciliations entre différents systèmes d’informations\nLe développement de macros/codes afin d’automatiser/optimiser les tâches\nL’amélioration continue des bases de données Investissements\nLa fiabilisation et l’amélioration continue des bases de données\nLa mise en place de nouveaux reportings (Power BI)\nLe pilotage de projets en lien avec les initiatives groupes et locales\nVous travaillerez en lien étroit avec les autres équipes d'AIM France ainsi que les équipes AIM centrales à Munich. La maitrise de l’anglais est alors indispensable.\nProfil\nDiplômé(e) en informatique/gestion des données ou d’une école d’ingénieur (BAC +5), vous disposez d’une expérience significative dans la manipulation de données (5-10 ans).\nMaîtrise de plusieurs langages de développement du type Python, VBA, Access, SAS\nBonne maîtrise des outils bureautiques Powerpoint, Excel et VBA, et idéalement une première expérience significative dans l’utilisation d’outils de datavisualisation (Power BI)\nCapacité d’analyse et de synthèse, ouverture d’esprit, rigueur, organisation et autonomie,\nFrançais et anglais professionnel courants indispensables, à l’écrit comme à l’oral.\nDébut de la mission :\nMars 2024\nLocalisation :\nParis - La Défense – TAO\nContacts : t ransmettre votre candidature complète (CV + lettre de motivation)\nShow more\nShow less",
        "details": {
            "JobDetail": [],
            "TypeContract": "",
            "Salary": "",
            "Level": "",
            "Experience": "10 an(s)"
        },
        "title": "data analyst",
        "skills": {
            "ProgLanguage": [
                "Python"
            ],
            "DataVisualisation": [
                "Power BI"
            ]
        }
    },
    {
        "source": "LinkedIn",
        "company": "Groupe Qérys",
        "location": "Le Haillan, Nouvelle-Aquitaine, France",
        "link": "https://fr.linkedin.com/jobs/view/data-analyst-h-f-at-groupe-q%C3%A9rys-3912192127?position=7&pageNum=5&refId=9FNYDD6Vrcv1aW7UUJOd7A%3D%3D&trackingId=AL6badOm1oi06lyjb5xCFQ%3D%3D&trk=public_jobs_jserp-result_search-card",
        "description": "Le Groupe QERYS, spécialiste de l’aménagement de l’habitat, a son siège social QERYS SAS à Le Haillan en Gironde.\nSes\nfonctions supports\naccompagnent les sociétés commerciales du Groupe (Bricodeal, Cazabox, Domotelec, Hydro Sud Direct, Midi Piles Services, Sider et Youpalo) dans leur fonctionnement, au travers de services mutualisés.\nLe Groupe QERYS propose une offre globale dans le domaine de l’aménagement et de l’habitat\n(890 collaborateurs - 299M€ CA en 2022)\nNous rejoindre c’est :\nL’assurance d’un\nGroupe solide\nUn système de\nmanagement participatif\nUn engagement\nRSE\n(Responsabilité sociétale des entreprises)\nUne attention particulière à la\nQVT\n(Qualité de vie au Travail)\nUn\nparcours d’intégration\n, des\nformations\net un\naccompagnement\ntout au long de votre carrière\nPour en savoir +, consultez notre site institutionnel\nhttps://www.groupe-qerys.com/\nQuel est notre contexte ?\nEn tant que Développeur Dataviz H/F, vous développez des outils d’aide à la décision utilisant la donnée consolidée du Groupe pour faciliter le quotidien des métiers.\nQuel sera votre quotidien ?\nRattaché au Responsable Informatique BI :\nFACILITER L’ACCES A L’INFORMATION\n• Créer, développer et adapter les applications à destination des différents services\n• Homogénéiser les indicateurs pour permettre une lecture analytique simple et optimale\nGARANTIR LA QUALITE DE LA DATA\n• Contrôler, corriger et fiabiliser toutes les données du Groupe\n• Enrichir le décisionnel des données des nouveaux entrants (Nouveaux outils / Nouvelles Das…)\nEn collaboration avec les Data Ingénieurs, trouver des solutions pour optimiser les performances système et assurer un confort de consultation\n• Soutenir la démarche data de la DSI\nFORMER ET ACCOMPAGNER LES UTILISATEURS SUR L’OUTIL DE DATAVIZ\n• Former les collaborateurs à l’outil de Dataviz\n• Accompagner le changement auprès des métiers\nMAINTENIR ET DEVELOPPER L’OUTIL DE DATAVIZ\n• Assurer la veille technologique de l’outil\n• Assurer la gestion administrative des accès et des licences\n• Comprendre les besoins d’analyse et y apporter les solutions en adéquation avec l’urgence.\nEnvironnement Technique :\nETL : Talend (OpenStudio) + ETLTools\nRestitution : Qliksense\nBase de données : SQLServer/Oracle/MySQL/AS400\nMéthodologie Traditionnel et Agile\nJira/Confluence\nCe que nous vous apportons pour assurer un bon équilibre vie pro/vie perso (sous conditions d’éligibilité) :\n32 jours\nde congés payés (25 + 7 jours ouvrés)\nLundi de pentecôte chômé et payé (Journée de solidarité offerte)\nDes\njours supplémentaires\nofferts :\nancienneté, déménagement, mariage/pacs…\nJusqu’à\n2 jours de télétravail par semaine selon le poste\nPartenariat Klaxit (favoriser le covoiturage)\nUne\nmutuelle gratuite\nUn\nintéressement\nPrévoyance\nRéduction\nPartenaires -\nDéjeuner\nUne prime de\ncooptation\npour tout collaborateur recruté suite à votre recommandation\nConditions du contrat :\nCDI - Temps plein\nSalaire et avantages :\nà partir 34K€brut/an + intéressement + mutuelle Groupe + partenariat déjeuner\nHoraires :\n38h45 du lundi au vendredi\nLocalisation du poste :\n29 rue Thomas Edison, 33612 Canéjan\nInformations complémentaires :\ndéplacements occasionnels sur nos différents sites à l'échelle nationale\ntélétravail possible jusqu’à deux jours/semaine\nVotre candidature retiendra notre attention si :\nVous justifiez d’une première expérience significative d’au moins 2 ans sur un poste similaire. Vous disposez d’un intérêt pour la data. Vous maîtrisez les outils de Dataviz, avez un forte capacité d’analyse et de synthèse. Vous êtes à l’écoute, bon communicant et respectez la confidentialité des données.\nRejoignez l’équipe de Benjamin !\nShow more\nShow less",
        "details": {
            "JobDetail": [
                "Temps plein"
            ],
            "TypeContract": "CDI",
            "Salary": "34K",
            "Level": "",
            "Experience": "2 an(s)"
        },
        "title": "data analyst",
        "skills": {
            "DBMS": [
                "MySQL"
            ],
            "Collaboration": [
                "Confluence",
                "JIRA"
            ],
            "EnSoftSkils": [
                "Collaboration"
            ]
        }
    },
    {
        "source": "LinkedIn",
        "company": "Catalina Marketing France",
        "location": "Boulogne-Billancourt, Île-de-France, France",
        "link": "https://fr.linkedin.com/jobs/view/data-analyst-python-f-h-cdi-boulogne-billancourt-at-catalina-marketing-france-3907391526?position=8&pageNum=5&refId=9FNYDD6Vrcv1aW7UUJOd7A%3D%3D&trackingId=4W0j8BPf8es2VkbZTqz6qg%3D%3D&trk=public_jobs_jserp-result_search-card",
        "description": "Catalina est le seul acteur de la GMS à pouvoir déployer des plans marketing hyper-personnalisés avec autant de puissance ! Chez Catalina, on parle en milliards de données depuis des années.\nGrâce à de puissants outils en IA et Machine Learning, nous analysons les comportements d’achat des clients de la grande distribution pour mettre en place des stratégies de recrutement et de fidélisation via des plans marketing omnicanaux (couponing ciblé, couponing digital via Coupon Network, programmes de fidélité…). Nous élaborons des milliers de campagnes chaque année : Leclerc, Carrefour, Monoprix, Nestlé, Procter & Gamble, Heineken, Coca-Cola, Bjorg… Ce serait trop long de tous les citer.\nCatalina réunit 860 personnes dans le monde, et plus de 240 en France. Travaillant main dans la main, les Cataliniens ont un fort esprit collaboratif et la culture du résultat. Ici on a la gagne !\nDepuis toujours, le succès de Catalina, c'est le talent de nos équipes. Chez Catalina, on favorise la confiance, la pro-activité et le développement en investissant sur la formation continue. Et parce que nous avons tant de pépites talentueuses, nous misons sur elles tous les jours en prônant l’évolution. Les meilleurs atouts des grands groupes et des start-ups sont réunis en une seule entreprise : puissance et flexibilité !\nSoucieux de notre impact, la RSE est au cœur de nos actions depuis toujours. En 2022, nous avons reçu la médaille d’argent EcoVadis pour saluer nos engagements sociaux et environnementaux.\nMissions et Responsabilités :\nAu sein du pôle Analytics, et intégré(e) à une équipe de 8 personnes dédiée au support des industriels de la grande distribution à travers l’Europe (France, Italie et UK), tes missions consistent à :\n-Echanger régulièrement avec les équipes business en France ou en Italie pour prendre connaissance des enjeux et problématiques clients auprès des équipes commerciales\n-Proposer, mettre en place des optimisations/Automatisations de nos process statistiques actuels\n-Extraire, analyser et interpréter les résultats des campagnes de marketing direct\n-Participer à des sessions des brainstorming en interne avec l’équipe DataScience et les autres équipes Analytics sur la veille méthodologique de nos mesures\n-Réaliser des projets d’études statistiques (segmentations, algo AI/ML, etc.)\nEt si c’était toi ?\nDe formation supérieure en statistiques, tu bénéficies d’un minimum 2 ans d’expérience idéalement dans le domaine des études marketing, et d’une expérience de travail sur des bases de données à forte volumétrie.\nTu parles Anglais (courant)\nTu as une parfaite maîtrise du SQL.\nTu as une parfaite connaissance de Python, l’utilisation dans un environnement Cloud est un plus (Azure, Snowflake, Databricks, etc.)\nLa connaissance des outils de Data visualisation comme Power BI est un plus\nTu connais les techniques statistiques appliquées au Marketing Direct : échantillonnage, mise en place de témoins, analyse des résultats, bonne connaissance des techniques de segmentations et de scoring.\nTu es déjà familier avec les techniques de ML & AI.\nTu es capable de vulgariser votre discours auprès de tes interlocuteurs (équipe commerciale, équipe marketing, clients…)\nDynamique et curieux(se), ta rigueur, ton aisance relationnelle, ton sens de l’initiative ainsi que ton autonomie te permettra de t’intégrer rapidement dans notre structure.\nTu es un amoureux de la data, un fin connaisseur de la grande conso, un passionné d'innovations digitales ? Tu cherches une entreprise qui te fait confiance et valorise tes talents, une bonne ambiance de travail, un équilibre vie privée/ vie pro et une forte cohésion d'équipe avec un esprit entrepreneurial ?\nEn devenant toi aussi Catalinien, tu seras fier de participer à cette aventure humaine au côté d’experts passionnés et bons vivants !\nProcess de recrutement :\n1er entretien avec Natacha, Talent Acquisition Manager et test technique de 30 minutes\n2ème entretien avec Laurence Analytics Director et Murielle Manager Analytics.\nNos infos utiles :\nTon futur lieu de travail : Boulogne-Billancourt (Marcel Sembat)\nContrat: CDI\nTélétravail : 3 jours de télétravail possible / semaine\nAvantages : 1 RTT / mois, CE, participation, prime vacances, carte restaurant swile, prise en charge de 2/3 de la mutuelle, journée d’engagement associatif, mais aussi de nombreux team buildings, des apéros, des paniers de fruits, du café à volonté…\nCatalina, en tant que responsable de traitement, met en œuvre un traitement de données ayant pour finalités principales la gestion et le suivi des candidatures. Tu disposes d’un droit d’accès, d’effacement, de rectification et de portabilité de vos données, ainsi que d’un droit d’opposition et de limitation au traitement de ces données. L’exercice des droits s’effectue sur la plateforme OneTrust dédiée (choix de la langue en haut à droite) accessible depuis le site catalinamarketing.fr/politique-confidentialite « Vos droits, employé » ou par courrier adressé à : Catalina Marketing France, Privacy Recrutement, 58 Avenue Edouard Vaillant 92100 Boulogne Billancourt.\nSauf opposition de ta part, les candidatures reçues font l’objet d’une conservation pendant 2 ans.\nShow more\nShow less",
        "details": {
            "JobDetail": [],
            "TypeContract": "CDI",
            "Salary": "",
            "Level": "",
            "Experience": "2 an(s)"
        },
        "title": "data analyst",
        "skills": {
            "ProgLanguage": [
                "Python"
            ],
            "DataBase": [
                "SQL"
            ],
            "BigData": [
                "Databricks"
            ],
            "DataVisualisation": [
                "Power BI"
            ],
            "CloudComputing": [
                "Azure"
            ],
            "DBMS": [
                "Snowflake"
            ],
            "Other": [
                "Statistiques",
                "Machine Learning",
                "Cloud",
                "ML"
            ],
            "EnSoftSkils": [
                "Initiative"
            ]
        }
    },
    {
        "source": "LinkedIn",
        "company": "Checkout.com",
        "location": "Paris, Île-de-France, France",
        "link": "https://fr.linkedin.com/jobs/view/senior-data-analyst-at-checkout-com-3860155203?position=9&pageNum=5&refId=9FNYDD6Vrcv1aW7UUJOd7A%3D%3D&trackingId=c%2FTawuU0%2Frn24Zsqr0ew8A%3D%3D&trk=public_jobs_jserp-result_search-card",
        "description": "Company Description\nWe're Checkout.com\nCheckout.com is one of the most exciting fintechs in the world. Our mission is to enable businesses and their communities to thrive in the digital economy. We’re the strategic payments partner for some of the best known fast-moving brands globally such as Wise, Hut Group, Sony Electronics, Homebase, Henkel, Binance, Klarna and many others. Purpose-built with performance and scalability in mind, our flexible cloud-based payments platform helps global enterprises launch new products and create experiences customers love. And it's not just what we build that makes us different. It's how.\nWe empower passionate problem-solvers to collaborate, innovate and do their best work. That’s why we’re number 9 on the Forbes Cloud 100 list and on Glassdoor’s list of Top 10 fintechs to work for. And we’re just getting started. We’re building diverse and inclusive teams around the world — because that’s how we create even better experiences for our merchants and our partners. And we need your help. So, join us to build tomorrow, today.\nJob Description\nYou will be joining the Identity Verification team, responsible to maintain and continuously improve a world-class online identity verification technology, based on real-time video recognition.\nAs a Senior Product Data Scientist, you'll work as part of a cross-functional team alongside product managers, designers, and software and analytics engineers, using data and your expertise to influence and drive the strategy of our products. You will have end-to-end ownership for all the data aspects for your ‘tribe’. You'll help define how we measure the success of our products, collaborate with engineers on how we collect data, build data pipelines to track the defined metrics, design and build reports/dashboards, and run analyses to find product improvement opportunities. You'll be a co-owner of a product, driving it to success in partnership with other cross-functional team members.\nYou'll also be part of the broader Analytics function, a team of Analytics Engineers, Data Scientists, and Data Product Managers.\nWe're a new but highly visible function within Checkout.com, so this is an exciting opportunity to drive a positive impact.\nHow you’ll make an impact\nBe responsible for a product domain and its metrics. You'll be accountable for defining, measuring, and presenting metrics.\nContribute product roadmaps through data-based recommendations and continuously define high-impact areas for improvement.\nSupporting product discovery, research, and experimentation\nWorking closely with Data Engineers to make sure we collect and model the right data to produce relevant business insights\nDesign and implement reusable and scalable data models for our data warehouse using dbt and Snowflake\nDesign and implement Looker structures (explores, views, etc) which will enable users across the organization to self-serve analytics\nFoster data culture across products and technology by actively sharing insights and ideas and building positive relationships with colleagues\nBuild experiments and analysis frameworks to quantify the ROI of product development.\nDrive by example your team and broader data community to apply best practices in analytics from data collection to analysis.\nQualifications\nWhat we’re looking for\nProven delivery experience as a data scientist or data analyst\nStrong communicator, you're able to explain complex technical topics to non-technical team members\nExperience conducting experiments, building measurement frameworks, and validating the results with relevant quantitative methods\nStrong analytical mind, proven experience in converting ambiguous problems into structured and data-informed solutions\nCuriosity and attention to detail: you like to explore and understand the trends and investigate unusual patterns\nProficiency in SQL for data interrogation and data transformation (ideally experience with Looker, Snowflake and dbt)\nKnowledge of applied statistics (e.g., hypothesis testing, regression)\nAdditional Information\nHybrid Working Model:\nAll of our offices globally are\nonsite 3 times per week\n(Tuesday, Wednesday, and Thursday). We’ve worked towards enabling teams to work collaboratively in the same space, while also being able to partner with colleagues globally. During your days at the office, we offer amazing snacks, breakfast, and lunch options in all of our locations.\nApply Without Meeting All Requirements Statement\nIf you don't meet all the requirements but think you might still be right for the role, please apply anyway. We're always keen to speak to people who connect with our mission and values.\nWe believe in equal opportunities\nWe work as one team. Wherever you come from. However you identify. And whichever payment method you use.\nOur clients come from all over the world — and so do we. Hiring hard-working people and giving them a community to thrive in is critical to our success.\nWhen you join our team, we’ll empower you to unlock your potential so you can do your best work. We’d love to hear how you think you could make a difference here with us.\nWe want to set you up for success and make our process as accessible as possible. So let us know in your application, or tell your recruiter directly, if you need anything to make your experience or working environment more comfortable. We’ll be happy to support you.\nTake a peek inside life at Checkout.com via\nOur Culture video https://youtu.be/BEwnpHuadSw\nOur careers page https://www.checkout.com/careers\nOur LinkedIn Life pages bit.ly/3OaoN1U\nOur Instagram https://www.instagram.com/checkout_com/\nShow more\nShow less",
        "details": {
            "JobDetail": [
                "Senior"
            ],
            "TypeContract": "",
            "Salary": "",
            "Level": "",
            "Experience": null
        },
        "title": "data analyst",
        "skills": {
            "DataBase": [
                "SQL"
            ],
            "DBMS": [
                "Snowflake"
            ],
            "Collaboration": [
                "Teams"
            ],
            "Other": [
                "Cloud"
            ],
            "EnSoftSkils": [
                "Organization"
            ]
        }
    },
    {
        "source": "LinkedIn",
        "company": "Mazars",
        "location": "Courbevoie, Île-de-France, France",
        "link": "https://fr.linkedin.com/jobs/view/data-analyst-junior-paris-2024-h-f-at-mazars-3904531206?position=10&pageNum=5&refId=9FNYDD6Vrcv1aW7UUJOd7A%3D%3D&trackingId=Jamm1MtpZy%2BS5vmsVMyqOA%3D%3D&trk=public_jobs_jserp-result_search-card",
        "description": "Description de l'entreprise\nMazars est un groupe international et intégré spécialisé dans l’audit, la fiscalité et le conseil ainsi que dans les services comptables et juridiques*. Présents dans plus de 95 pays et territoires à travers le monde, nous nous appuyons sur l’expertise de plus de 47 000 professionnels – plus de 30 000 au sein de notre partenariat intégré et plus de 17 000 via « Mazars North America Alliance » – pour accompagner les clients de toutes tailles à chaque étape de leur développement.\nDans les pays où les lois en vigueur l’autorisent\nDescription du poste\nMazars souhaite chaleureusement son équipe « Audit Data Analytics » au sein de ses équipes Data Services.\nAu sein d'une équipe à la frontière entre l'audit et la tech, vous développez ainsi une double compétence technique et fonctionnelle ; en véritable Business Analyst, vous concevez et déployez des solutions Analytics pour les clients Mazars.\nVous intervenez sur des missions variées dans plusieurs secteurs d'activité (industrie, services, secteur public, services financiers (banque et assurance)) et alimentez les compétences suivantes :\ndéveloppement de solutions innovantes sur des socles technologiques variés de data analytics, de data visualisation et de programmation : Alteryx, Qlik, SQL, PowerBI, Python, etc. ;\nparticipation à la conception de solutions fonctionnelles, de la phase de spécifications à la phase de mise à disposition ;\ncontribution au développement de nouvelles offres Mazars au service des enjeux Data de nos clients ;\nanalyser fonctionnellement les résultats produits par les solutions Analytics ;\nparticipation à la rédaction de rapports d'analyse et présentation des outils et résultats Analytics à nos clients.\nEn complément, vous êtes progressivement formés aux technologies de machine learning, à l'intelligence artificielle et à la science des données.\nQualifications\nDe formation Bac+5, vous êtes jeune diplômé(e) d'une école d'ingénieurs, école de commerce ou université et avez un goût prononcé pour les sujets Analytics et les nouvelles technologies de façon générale, avec une appétence pour les problématiques métier et finance :\nVous avez une spécialisation en Système d'Information et/ou en Data Science ;\nVous êtes passionné(e) par les nouvelles technologies liées à la Data ;\nVous avez idéalement une expérience de stage au cours de laquelle vous êtes intervenu(e) sur le domaine de la « Data » ;\nVous aimez innover, vous êtes curieux, dynamique et autonome et vous avez une certaine\naisance à développer vos connaissances sur de nouveaux outils ;\nVous avez un excellent sens du travail en équipe ;\nVous possédez les connaissances de base parmi les technologies suivantes : SQL, ACL, data studio, PowerBI, Qlik, Alteryx, Tableau softwareetc.)\nIntégration prévue à partir de septembre 2024\nInformations supplémentaires\nLes + du métier :\nDiversité des missions\nTravail d'équipe\nEquipe dynamique\nÉvolution de carrière rapide\nChez Mazars, nous plaçons le développement personnel au cœur de nos priorités. Vous êtes force de proposition ? Nous vous donnerons l'opportunité de porter et réussir vos idées. Vous souhaitez participer à la croissance du cabinet ? Nous vous intégrerons dans le développement ou le renforcement de nos offres. Enfin, les formations conçues par Mazars U Learn vous permettront de réinventer et de développer vos softs skills ainsi que de booster votre talent !\nShow more\nShow less",
        "details": {
            "JobDetail": [],
            "TypeContract": "",
            "Salary": "",
            "Level": "Bac+5",
            "Experience": null
        },
        "title": "data analyst",
        "skills": {
            "ProgLanguage": [
                "Python"
            ],
            "DataBase": [
                "SQL"
            ],
            "DataVisualisation": [
                "Tableau"
            ],
            "Other": [
                "Machine Learning"
            ]
        }
    },
    {
        "source": "LinkedIn",
        "company": "Disneyland Paris",
        "location": "Marne-la-Vallée, Île-de-France, France",
        "link": "https://fr.linkedin.com/jobs/view/alternance-%E2%80%93-data-analyst-junior-reporting-f-h-nb-at-disneyland-paris-3901105673?position=1&pageNum=7&refId=QYO6QFCk1HyZpy1IxSLXjw%3D%3D&trackingId=wJnmePfCYzhHCYd4vWttEw%3D%3D&trk=public_jobs_jserp-result_search-card",
        "description": "Le Sourcing à Disneyland® Paris :\nLe département division Sourcing et Environnement Produits Merchandise Food & Beverage est composée de 4 pôles : la coordination Environnementale produits, l’Administration des achats, le pôle Outils et Analyses et enfin le pôle Achat sourcing.\nLa mission principale de l’équipe est de négocier des coûts d'acquisition des produits merchandise ou food & beverage, dans le respect du cahier des charges produits, en veillant à la conformité réglementaire, environnementale et en pleine adéquation avec les objectifs commerciaux.\nVos missions :\nRattaché(e) au pôle Outils et Analyses, vos missions seront les suivantes :\nVous êtes garant(e) de la mise à jour des reportings existants et nécessaires au fonctionnement de l'activité ;\nVous assistez les analystes au quotidien (écriture des process, support sur les analyses…) ;\nVous participez au développement d'outils de reportings variés (Excel, Query, Power BI…) ;\nEnfin, vous collaborez en mode projet selon l’actualité du service.\nVos atouts pour ce poste :\nIl s'agit d'une alternance de 1 an ou 2 ans.\nVous préparez un diplôme d’un niveau Bac+3 au minimum spécialisé en analyse de données, informatique ou équivalent.\nVous avez idéalement une première expérience dans le domaine (stage/alternance).\nVous avez une bonne maîtrise du Pack Office (niveau avancé). La connaissance de Power BI, Tableau ou Business solution est un plus.\nVous justifiez d’un niveau d’anglais intermédiaire (B2).\nAu quotidien, vous faites preuve d’organisation et de rigueur. Vous appréciez évoluer dans un environnement collaboratif, échanger avec de multiples interlocuteurs et témoignez d’un bel esprit d’équipe.\nEnfin, vous êtes reconnu(e) pour votre esprit d’analyse.\nLa différence Disney\n✨\nLa diversité des interactions et donc les opportunités pour rencontrer une multitude de métiers autour des achats, de la supply chain ou du développement produit comme de la relation commerciale.\nQuelques avantages de notre entreprise :\nUn cadre de travail unique dans un contexte international aux nombreuses opportunités,\nUn logement à proximité de nos parcs (sous conditions),\nLe remboursement de 80% des abonnements pour les transports quotidiens domicile–travail,\nOffre diversifiée de restauration d’entreprise et subvention allouée,\nDes accès aux parcs pour vous et vos proches, et à la plateforme Disney+,\nDes réductions tarifaires dans les boutiques, restaurants et hôtels Disney toute l’année,\nDe nombreux avantages supplémentaires : temps de formation, programmes de reconnaissance, évènements exclusifs, aide à la parentalité, conciergerie d’entreprise, complémentaire santé…\nTélétravail possible lorsque la fonction ne nécessite pas une présence sur site.\nVous êtes prêt(e) à participer à une formidable aventure humaine et à rejoindre nos 18 000 collaborateurs (Cast Members) qui partagent tous la même ambition professionnelle : faire vivre la magie Disney et faire rêver des millions de visiteurs ? Nous sommes prêts à vous donner les moyens de faire rayonner vos talents ! #DLPCAMPUSGA24\n🏰\nShow more\nShow less",
        "details": {
            "JobDetail": [],
            "TypeContract": "",
            "Salary": "",
            "Level": "Bac+3",
            "Experience": "2 an(s)"
        },
        "title": "data analyst",
        "skills": {
            "DataVisualisation": [
                "Power BI",
                "Tableau"
            ]
        }
    },
    {
        "source": "LinkedIn",
        "company": "VINCI Airports",
        "location": "Lyon, Auvergne-Rhône-Alpes, France",
        "link": "https://fr.linkedin.com/jobs/view/data-analyst-f-h-at-vinci-airports-3918622032?position=3&pageNum=7&refId=QYO6QFCk1HyZpy1IxSLXjw%3D%3D&trackingId=Pn%2B%2BQas%2Bc6Wf6MzEIV%2Fr0w%3D%3D&trk=public_jobs_jserp-result_search-card",
        "description": "Lyon Aéroport, 1er aéroport du réseau VINCI Airports en France pilote l’exploitation des aéroports Lyon–Saint Exupéry et Lyon–Bron.\nRattaché(e) au responsable études et projets, le/la data analyst se positionne comme référent technique et fonctionnel sur le périmètre data de la DCM. Il organise et valorise les données pour délivrer des reportings et des analyses à valeur ajoutée.\nExpert technique, il/elle collabore avec les équipes informatiques pour construire les environnements et assurer le traitement de données. Expert analytique, il/elle capte les enjeux et besoins métiers et se positionne comme véritable « business partner ».\nMISSIONS\nCe poste nécessite une réelle double compétence technique et analytique, et la capacité à travailler en autonomie et transversalité :\nTechnique : data cleaning, data modeling et business intelligence\nSourcer, structurer, croiser, redresser, valider les données\nConstruire des univers de données orientés décisionnels\nProduire les KPIs et tableaux de bords sous Power BI (et Business Object)\nPréparer / collaborer à l’industrialisation des travaux\nFavoriser la self-BI dans les équipes métiers\nAnalytique : exploration, études et data mining\nConsolider les besoins métiers d’analyses et de reporting\nSchématiser les flux et modèles de données, et consigner les règles de gestion\nFaire émerger par vos propres recherches de nouveaux axes d’analyses / leviers de performance\nRéaliser les analyses : du tableau à plat au modèle statistique avancé (ex : prédictif)\nPrésenter les résultats : structuration de fichiers, tableaux, présentation power point\nTransverse : projets et gouvernance\nDocumenter les travaux : supports techniques et fonctionnels\nPromouvoir une démarche de gouvernance\nGarantir la qualité des données et améliorer les référentiels\nPiloter / contribuer à des projets orientés data et technologiques\nEnquêtes\nCollaborer avec les instituts d’études prestataires en charge de mener des enquêtes\nCadrer le besoin et valider les choix méthodologiques et l’échantillon\nProduire des rapports trimestriels et réaliser des analyses ad hoc\nIndustrialiser le recueil des données pour une exploitation automatisée\nBac +4/5, double compétence, expérience 3 à 5 ans\nVous disposez de compétences techniques vous permettant d’évoluer en complète autonomie, et vous êtes en capacité de mener des analyses percutantes. Vous faites donc preuve d’agilité pour collaborer avec des interlocuteurs aux profils variés. Et de résilience pour consacrer l’énergie suffisante à la préparation des données dans un environnement en mutation. Votre curiosité et votre sensibilité vous permettent d’appréhender les enjeux métiers, et vous savez y répondre par des livrables de qualité, orientés usages et résultats.\nVous serez amené à travailler en autonomie avec les environnements, outils et langages suivants : Google Cloud Plateform (GCP / Big - Power Query), Oracle (SQL), Power BI (PBI / DAX), Business Object (BO), Python.\nVous réaliserez des dashboards / analyses portant sur les parkings, le pricing, l’aéronautique, le retail, CRM…\nGestion de projet, autonomie, initiative, persévérance, rigueur, curiosité, enthousiasme, esprit d’équipe, anglais\nShow more\nShow less",
        "details": {
            "JobDetail": [],
            "TypeContract": "",
            "Salary": "",
            "Level": "",
            "Experience": "5 an(s)"
        },
        "title": "data analyst",
        "skills": {
            "ProgLanguage": [
                "Python"
            ],
            "DataBase": [
                "SQL"
            ],
            "DataVisualisation": [
                "Power BI",
                "Tableau"
            ],
            "CloudComputing": [
                "GCP"
            ],
            "Other": [
                "Cloud"
            ],
            "EnSoftSkils": [
                "Initiative"
            ]
        }
    },
    {
        "source": "LinkedIn",
        "company": "Accor",
        "location": "Issy-les-Moulineaux, Île-de-France, France",
        "link": "https://fr.linkedin.com/jobs/view/business-data-analyst-at-accor-3849451754?position=4&pageNum=7&refId=QYO6QFCk1HyZpy1IxSLXjw%3D%3D&trackingId=6WzHkxk%2FOyXxqQg8i7yv3g%3D%3D&trk=public_jobs_jserp-result_search-card",
        "description": "Company Description\nLeading the hospitality revolution, Accor is more than a hotel group. With luxury to economy, homestays to resorts, we are a holistic ecosystem of 40 brands in 110 countries, Talent and Solutions, ready to engage with the future’s endless possibilities. Accor has an offer to bring new life to the way you live, work, play and do business with a personalized guest experience.\nAstore is Accor’s Procurement Organization, that is revolutionizing the hospitality sector by offering all the products and services necessary to ensure the proper functioning of all hospitality businesses. With a team of 200 experts serving 5000 customers in 20 countries, Astore is able to negotiate some of the best prices and conditions on the market. With more than 7500 clients worldwide and about 2000 external partners, our ambition is to become the first choice for procurement solution for the hospitality sector.\nAstore Digital Factory leads all our Digital activities within the Procurement function. Its main responsibility is to develop the business thanks to best-in-class digital tools maximizing the impact (Revenue, EBITDA) of our Procurement business teams in the Paris HQ and in the different worldwide regions. The digital platforms are covering all Procurement business processes: (i) Hospitality supply chain at site (e-ordering through marketplace, Supplier directory, Pre-opening project management, Inventory & recipe management, Invoice to pay, Data, Customer Analytics & Procurement news) and (ii) Internal Procurement operations (Source to contract, CRM, Marketing & Sales automation, Ticketing, Customer Website, Full order to pay Revenue / Back end rebate Management, CSR, Finance process & Business performance analytics).\nThe Hotel Tools Product team is in charge of all tools at hotel level (e-ordering, inventory & recipe management, invoice to pay), out of which some are “custom” and others “SaaS” (Mirakl, Tradeshift, FutureLog).\nJob Description\nThe Business Data Analyst (BDA) is the interface between the Data and business teams. The BDA is in charge of understanding the demands of Procurement department and carefully providing and planning a solution. The BDA is a data-driven professional, uses the data analysis process to understand, interpret, and predict patterns in business, and then use those data-driven insights to enhance their business process and making decisions. The BDA aims to identify opportunities to grow, optimize, and improve an organization’s business processes. His function is on of vision and strategy implementation. The BDA also helps in making judgments that are aligned with corporate objectives.\nMain Activities\nHas experience in Data-driven Business Analysis on simple and complex problems\nIn charge of prioritization of business requirements according to the objectifs requested\nCollaborates with the users or business experts to define what it is expected\nAnalyses requirements and participates in the design of the solution with the technical team\nLies at the intersection of Data Analysis and Business Analysis\nCreates and modifies computer programs to extract information from company databases\nInteracts with data engineer and data scientists to understand how data needs to be converted, loaded and presented\nDevelops and deploys dashboards, reports, to collect data-backed insights\nInterprets key business data sets\nProvides insights on potential areas of growth, optimization, and improvements\nWorks cross-department on data-driven strategies that improve business processes and decision-making\nIs responsible of writing or providing US stories or/and Business Rules.\nQualifications\nSkills & profile\n:\nBS/BA Degree (MS preferred) preferably in Computer Science, Statistics, Math or equivalent combination of education and experience.)\n1-5 years of experience with data analysis and preparation, including experience with very large data sets\nExperience working with unstructured data sets is a plus\nMathematical skills to help collect, measure, organize and analyze data\nKnowledge of programming languages like SQL, R, Python\nTechnical proficiency regarding database design development, data models\nKnowledge of data visualization\nKnowledge of how to create and apply the most accurate algorithms to datasets in order to find solutions\nKnowledge of the project management process.\n3+ years in management/executive role\nExperience in Agile Development\nAdditional Information\nWhat benefits can Accor offer its employees?\nA real Work life balance\nRemote work / autnomous framework\nAttractive Finance Benefits\nProfit sharing bonus \"interessement participation\" compulsory and voluntary plans / 700 € per year Allowance Green transportation such as electrical bike, scooter / Pass Navigo subsidised max 75% / Referral bonus / meal ticket / free coffee\nLearning & development\nManagement talent at the earth our of HR Accor strategy.\nWe want you to feel free to dare and free to grow, by opening new doors to continuous learning and skills development. Challenge yourself and switch between jobs, brands, and career paths\nShow more\nShow less",
        "details": {
            "JobDetail": [
                "Remote",
                "Full"
            ],
            "TypeContract": "",
            "Salary": "",
            "Level": "",
            "Experience": null
        },
        "title": "data analyst",
        "skills": {
            "ProgLanguage": [
                "R",
                "Python"
            ],
            "DataBase": [
                "SQL"
            ],
            "DataAnalytics": [
                "R"
            ],
            "Collaboration": [
                "Teams"
            ],
            "EnSoftSkils": [
                "Organization"
            ]
        }
    },
    {
        "source": "LinkedIn",
        "company": "FBD Group",
        "location": "Tremblay-en-France, Île-de-France, France",
        "link": "https://fr.linkedin.com/jobs/view/data-analyst-f-h-at-fbd-group-3886652484?position=5&pageNum=7&refId=QYO6QFCk1HyZpy1IxSLXjw%3D%3D&trackingId=wzAHo5vhmHxpEaABJc8jHA%3D%3D&trk=public_jobs_jserp-result_search-card",
        "description": "Vous aimez :\nConduire le changement dans le secteur de la distribution\nPartager les challenges d’une entreprise agile en forte croissance\nL’esprit d’équipe et l’ambiance qui règnent dans un groupe à taille humaine (250 collaborateurs)\nL’innovation, le numérique et les nouvelles technologies au service de l’expérience client\nLa gestion de projet\nVous aimerez accompagner l’entreprise dans son évolution en étant un agitateur d'idées.\nRattaché(e) au Responsable Performance, vous aurez pour objectif principal le recueil, l’analyse et l’interprétation de la donnée de l’entreprise. Ces données peuvent être liées aux clients (CRM), aux produits et à leurs performances, ou même aux concurrents.\nEn collaboration étroite avec les autres pôles de la Direction Digitale, les équipes Commerce, les équipes Marketing, et les équipes IT, ainsi que les autres Directions support du Groupe, vous construirez, exploiterez et interpréterez les données pour en dégager des observations business utiles.\nMissions Principales :\nEchanger avec les différentes équipes internes concernées pour comprendre leurs besoins et leurs enjeux\nDéfinir les indicateurs clés de performance (KPI) avec les parties prenantes pour mesurer la tenue des objectifs\nMettre en place ou optimiser les outils de suivi et de prévision avec la DSI\nAnalyser les bases de données\nSynthétiser les résultats de ces analyses pour les communiquer aux bons interlocuteurs\nProposer des plans d’action (mise en place d’outils, définition des processus…)\nIdentifier les problèmes et proposer des solutions appropriées\nAssurer la qualité et la fiabilité des données\nEtablir une cartographie des données utilisées au sein des analyses pour une meilleure compréhension des interlocuteurs\nMissions Détaillées :\nRecueil des besoins\nEchanger avec les différentes équipes internes concernées pour comprendre leurs besoins et leurs enjeux\nDéfinir les indicateurs clés de performance (KPI) avec les parties prenantes pour mesurer la tenue des objectifs\nModéliser les données nécessaires à l’analyse\nCollecte des données\nRecueillir et extraire les sources de données pertinentes (savoir où les trouver) et de qualité, à traduire ensuite en données statistiques\nAssurer la qualité et la fiabilité des données\nIdentifier les problèmes (données manquantes, qualité insuffisante, stockage, centralisation, etc.) et proposer des solutions appropriées en exprimant le besoin associé aux équipes IT\nTraitement\nProposer des plans d’action :\nMettre en place des process/requêtes et des automatisations\nMettre en place ou optimiser les outils de suivi et de prévision avec la DSI\nTrouver de nouvelles façons de traiter la donnée avec l’appui de nouveaux outils, au vu de l’accroissement considérable du nombre de données\nAnalyse\nDéfinir et gérer des outils d’analyse et d’aide à la décision : prévisions et objectifs de vente, tableaux de bord, indicateurs de performance, analyse de la conjoncture et des marchés, suivi de la performance et appui aux équipes commerciales\nAnalyser les bases de données, produire des analyses métiers et proposer des recommandations aux managers\nS’assurer de la cohérence des résultats par rapport au commerce et à l’activité réelle en point de vente\nCommunication\nCréer des Dashboard, mettre en place des KPIs et des reportings de performance\nConstruire et faire évoluer les rapports issus de la Business Intelligence (BI) & Web Analytics\nSynthétiser les résultats de ces analyses pour les communiquer aux bons interlocuteurs\nEtablir une cartographie des données utilisées au sein des analyses pour une meilleure compréhension des interlocuteurs\nDiffuser et assurer la bonne interprétation et la bonne compréhension des rapports d’analyse\nTransverse\nFaire preuve de proactivité pour explorer les données disponibles et proposer des analyses non sollicitées\nRéaliser une veille marketing et commerciale sur la concurrence et proposer des analyses associées\nContribuer à l’analyse des parcours omnicanaux et à la recherche de leviers de croissance\nExplorer les opportunités d’application de l’IA dans la Data Analyse\nRéaliser des études qualitatives sur différentes problématiques business\nParticiper à la mesure économétrique des campagnes d’acquisition ainsi qu’à la mesure de l’attribution/contribution des différents leviers marketing actionnés\nExpérience : 5 ans minimum en Data analyse, avec des connaissances en data engineering idéalement dans le secteur du retail\nFormation : Bac+5, cursus en mathématiques, statistiques, économie, marketing ou en informatique (idéalement Master en statistiques / économétrie ou Master spécialisé en Big Data)\nLa maitrise de l’anglais courant est nécessaire\nSavoir-faire & compétences :\nMaîtrise des bases de données business (BigQuery, Snowflake, Redshift…) et du langage SQL\nMaitrise de la construction d’un Datawarehouse\nMaîtrise d’un outil d’orchestration (DBT, Airflow…) et du langage Python\nMaîtrise d’au moins un outil de dashboarding (Looker, Power BI, Tableau…)\nMaîtrise des librairies de manipulation de données en Python (NumPy, Pandas, Matplotlib, SciPy, Scikit-learn)\nUne connaissance des outils tels que Hadoop ou Spark serait un plus\nCompréhension des enjeux liés à la traçabilité des données (data lineage)\nUne connaissance métier, notamment en marketing et relation client est nécessaire\nSavoir être :\nGrande aisance écrite et orale pour optimiser la compréhension et la communication avec les équipes\nPassion pour les chiffres et les statistiques\nOrientation business pour faire des recommandations pertinentes et actionnables\nAisance relationnelle pour emporter l’adhésion des interlocuteurs\nEsprit de synthèse et analytique\nEsprit ouvert et compétences transverses pour appréhender les problématiques techniques et les restituer de façon compréhensible aux différents publics\nRigoureux, organisé et réactif\nForce de proposition\nPrise de recul\nPourquoi nous rejoindre ?\nLa brigade\nUne Direction qui accorde une attention particulière au bien être des collaborateurs : Nous sommes Great Place to Work !\nLes ingrédients\nVous aurez tous les ustensiles nécessaires pour votre recette (ordinateur, téléphone portable professionnel etc.)\nUne rémunération fixe + Prime annuelle liée à vos objectifs + Prime de participation\nLes assaisonnements\nUne mutuelle familiale prise en charge à 100% par le Groupe FBD\nL’accès à un Restaurant Interentreprises\n2 jours de télétravail par semaine sans condition d’ancienneté\nDes locaux à Roissy à 200m du RER B et une annexe à Paris 9ème\nUn réseau social Entreprise pour vous mettre au courant et participer à la vie d’entreprise\nLa carte\nNotre menu est composée d’ingrédients divers et variés, ce qui en fait la richesse de ses plats.\nNous accordons une attention particulière à lutter contre toute formes de discriminations, raison pour laquelle nous avons adhéré à l'association A Compétences Egales qui œuvre dans ce domaine.\nLa cerise sur le gâteau\nBoissons chaudes et fruits Bio à disposition pour bien commencer la journée !\nDes activités tous les mois pour les collaborateurs, préparés par notre service Com Interne + 2 évènements groupe par an.\nEn cuisine, le meilleur reste à inventer ! Nous vous attendons !\nShow more\nShow less",
        "details": {
            "JobDetail": [],
            "TypeContract": "",
            "Salary": "",
            "Level": "Bac+5",
            "Experience": "5 an(s)"
        },
        "title": "data analyst",
        "skills": {
            "ProgLanguage": [
                "Python"
            ],
            "DataBase": [
                "SQL"
            ],
            "DataAnalytics": [
                "NumPy",
                "Pandas"
            ],
            "BigData": [
                "Hadoop",
                "Spark"
            ],
            "MachineLearning": [
                "Scikit-Learn"
            ],
            "DataVisualisation": [
                "Power BI",
                "Matplotlib",
                "Tableau"
            ],
            "DBMS": [
                "BigQuery",
                "Snowflake"
            ],
            "Automation": [
                "Airflow"
            ],
            "Other": [
                "Statistiques",
                "Big Data"
            ],
            "EnSoftSkils": [
                "Communication",
                "Collaboration"
            ]
        }
    },
    {
        "source": "LinkedIn",
        "company": "eXalt",
        "location": "Paris, Île-de-France, France",
        "link": "https://fr.linkedin.com/jobs/view/data-analyst-at-exalt-3856622458?position=6&pageNum=7&refId=QYO6QFCk1HyZpy1IxSLXjw%3D%3D&trackingId=Iy5BukBI5QpMOdTFJaCkbw%3D%3D&trk=public_jobs_jserp-result_search-card",
        "description": "Descriptif du poste\nNous recherchons un.e\nData Analyst Confirmé H/F\npour rejoindre notre communauté sur le\npilier Data Performance & Analytics.\nVos missions:\nCollecter, nettoyer et traiter les données provenant des différentes sources de données de l’entreprise\nAnalyser les données pour identifier des tendances, des corrélations et des anomalies.\nConcevoir et développer des tableaux de bord et des rapports pour présenter les résultats de manière claire et concise.\nCollaborer avec les équipes clients pour comprendre leurs besoins et recommander des solutions adaptées.\nExplorer les résultats des analyses en utilisant la Data Visualisation\nProfil recherché\nMaîtrise avancée des langages de programmation (SQL, Python, R, etc.).\nBonnes connaissances en modélisation de données\nExpérience pratique en dashboarding (Tableau, Power BI, Dataiku, Qlikview,etc.).\nFortes compétences analytiques et capacité à transformer les données brutes en insights exploitables.\nExpérience de travail en méthode Agile\nCapacité à travailler de manière autonome et en équipe.\nExcellentes compétences en communication et en résolution de problèmes.\nMaîtrise de l’anglais (oral & écrit dans un contexte international professionnel).\nDéroulement des entretiens\nUn entretien RH avec Estelle, à la suite duquel vous saurez tout (ou presque) d’eXalt Value,\nUn entretien technique avec un Manager assorti d’un test technique sur un outil de Dataviz/Analyse de Données lors duquel vous aurez l’occasion de démontrer vos talents mais aussi d’apprendre avant même de dire oui,\nUn entretien final avec la Directrice Associée ou le Directeur Opérationnel, pour finir de vous convaincre de nous rejoindre 😊\nVotre environnement eXalté:\nRejoindre\neXalt Value\n, c’est également :\nUn environnement de travail Collaboratif favorisant les initiatives et projets transverses à la Practice Data & IA (Lab IA, Data Hub, etc)\nUn collectif de consultants passionnés, s’intéressant aux tendances innovantes du secteur\nUne Practice de proximité, privilégiant la montée en compétence de ses collaborateurs (formations, coachings, mentorats,etc)\nUn suivi individualisé et de proximité par un.e Data Sales Manager référent du compte client, un.e Chargé.e RH et un.e Practice Manager\nUne équipe sympa et dynamique, qui privilégie des moments de partage (séminaires, eXaltemps, meet-ups, déjeuners d’équipe,etc.)\nQui sont-ils ?\neXalt\nest un cabinet de conseil IT\nPure player Data\n& IA basé à Paris (1er arrondissement).\nNotre offre s’articule autour de 4 piliers réunis au sein d’une même communauté pour un accompagnement à 360° alliant une expertise technique et méthodologique à une approche conseil métier:\nData Gouvernance & Project\nData Engineering & Big Data\nData Performance & Analytics\nData Science & IA\nFiliale du groupe eXalt créé en 2018,\nregroupant plus de\n950 collaborateurs en France\n(Paris, Lyon, Bordeaux, Lille, Nantes, Marseille)\net à l’international\n(Colombie, Etats-Unis, Espagne, Belgique),\neXalt Value\ndémontre une\nexpertise approfondie\ndans le domaine de la Data & IA et conseille les entreprises dans le déploiement de leurs stratégies data-driven.\nBénéficiant de la renommée et des relations client du groupe eXalt\n(1er dans la catégorie Conseil & Audit au classement des Champions de la Croissance 2024), eXalt Value\nest en pleine croissance et regroupe aujourd’hui une communauté d’expertise de plus de 60 collaborateurs en région parisienne.\nNos consultants interviennent sur d\nes projets d’envergure stimulants\ndans divers secteurs d’activité, Banque & Assurance, Médias, Transports, Retail, Tourisme, etc.\nShow more\nShow less",
        "details": {
            "JobDetail": [
                "Confirmé"
            ],
            "TypeContract": "",
            "Salary": "",
            "Level": "",
            "Experience": null
        },
        "title": "data analyst",
        "skills": {
            "ProgLanguage": [
                "R",
                "Python"
            ],
            "DataBase": [
                "SQL"
            ],
            "DataAnalytics": [
                "R"
            ],
            "DataVisualisation": [
                "Power BI",
                "Tableau"
            ],
            "Other": [
                "Big Data"
            ],
            "EnSoftSkils": [
                "Communication"
            ]
        }
    },
    {
        "source": "LinkedIn",
        "company": "Allianz France",
        "location": "Paris, Île-de-France, France",
        "link": "https://fr.linkedin.com/jobs/view/alternance-data-analyst-h-f-at-allianz-france-3888470171?position=7&pageNum=7&refId=QYO6QFCk1HyZpy1IxSLXjw%3D%3D&trackingId=XOY6FwwxT2NZ2yuOdnAuFA%3D%3D&trk=public_jobs_jserp-result_search-card",
        "description": "Nous vous proposons une mission de Data Analyst au sein de l’Unité Data, Engagement Marketing, et Stratégie de la Direction Leads & Data.\nVos principales missions seront :\nContribution aux opérations récurrentes de collecte, analyse et exploration des données clients\nParticipation aux validation des données du datamart connaissance client\nExtraction et mise à disposition de données pour d’autres directions d’Allianz France\nPrise en charge d’études statistiques et notamment sur la qualité des données à partir du datamart\nCadre de la mission :\nVous serez intégré à l’équipe Data Client située à la Défense.\nVous serez accompagné par un encadrant, votre futur tuteur.\nVous disposerez de tous les outils de travail à distance et aurez la possibilité de faire un jour de télétravail par semaine, une fois que vous serez autonome.\nProfil / Compétences :\nIssu(e) d’une formation supérieure dans un domaine lié : Data/Mathématiques/Statistiques, vous êtes à la recherche d’une alternance pour un BAC+4 ou BAC+5\nVous avez de solides bases en développement SAS (SAS GUIDE) et en Python\nVous êtes de nature curieuse et aimez prendre découvrir / apprendre de nouvelles technologies\nVous avez une très bonne autonomie/rigueur/curiosité intellectuelle\nInformations pratiques :\nType de contrat : apprentissage ou contrat de professionnalisation.\nDate de démarrage : septembre 2024\nDurée : 12 mois\nLieu : La Défense (métro Esplanade de la Défense)\nÊtre stagiaire chez Allianz France, c'est aussi bénéficier de...\nUne journée de travail à distance par semaine\nUn remboursement des frais de transport à 50%\nUne rémunération attractive\nAllianz est la 1ère marque mondiale d’assurance présente dans 70 pays. Les #Allianzers, ce sont 9.000 salariés en France qui accompagnent leurs clients tout au long de leur vie, des collaborateurs qui associent innovation, performance et agilité pour relever des défis permanents au quotidien.\nSe soucier de nos employés, de leurs ambitions, de leurs rêves et de leurs défis, voilà ce qui fait de nous un employeur unique. Ensemble, nous pouvons construire un environnement où chacun se sent responsabilisé et a la confiance nécessaire pour explorer, se développer et façonner un meilleur avenir pour nos clients et le monde qui nous entoure.\nEn qualité d’employeur engagé, Allianz reconnaît que sa force se trouve dans la diversité de ses collaborateurs. Nous sommes fiers de promouvoir l’intégration et l’égalité des chances quel que soit le sexe, l’âge, l’origine, la nationalité, la religion, le handicap, ou l’orientation sexuelle de nos collaborateurs.\nAllianz, Let’s care for tomorrow !\nShow more\nShow less",
        "details": {
            "JobDetail": [],
            "TypeContract": "",
            "Salary": "",
            "Level": "Bac+5",
            "Experience": null
        },
        "title": "data analyst",
        "skills": {
            "ProgLanguage": [
                "Python"
            ],
            "Other": [
                "Statistiques"
            ]
        }
    },
    {
        "source": "LinkedIn",
        "company": "STATION F",
        "location": "Paris, Île-de-France, France",
        "link": "https://fr.linkedin.com/jobs/view/data-analyst-at-station-f-3818685290?position=8&pageNum=7&refId=QYO6QFCk1HyZpy1IxSLXjw%3D%3D&trackingId=iayrIDeQMFcxT%2BAQ7DTLrg%3D%3D&trk=public_jobs_jserp-result_search-card",
        "description": "Job Description\nThis position is remote-friendly.\n🧚🏻\nOur Data team\nThe Data team at Joko is turning mountains of data into actionable insights for all the teams! The Data team is part of our Operations department led by Quentin, our COO, and our mission is to empower the company to make informed decisions.\nMore Specifically, The Team's Responsibilities Are\nData for Business: We create top-notch reports and tools, making it easy for teams to dive into data and excel in their decision-making.\nHelp our stakeholders with the best data stack: We load and transform data, automate reports, and continuously improve our data stack. This allows teams to use valuable insights built on robust and scalable foundations.\nSpread the data culture: At Joko, we have a strong engineering and tech culture across all teams, making it an ideal environment for our Data team to have a significant impact. We provide support and training on data tools to our stakeholders, and by closely collaborating with them, we ensure that our solutions align perfectly with their operational needs.\n🎯 What You Will Do\nAs a Data Analyst, you will have a cross-functional role and collaborate closely with teams to understand our data and develop insights.\nDeep-dive analyses: You will explore and analyse data to uncover trends, patterns, and potential issues that will help in the decision-making processes across all teams.\nReporting and Data Visualization: You will participate in creating content, such as dashboards and charts, using our data visualization tool. You will be involved in defining the report's content and constructing dashboards and charts to effectively communicate data-driven findings to stakeholders.\nData loading and transformation: You will be involved in loading and transforming the data as we have a “full stack” approach in Data at Joko. Of course, you will get some help on Data Engineering parts but you will be involved in the entire lifecycle of our data.\nInteractions with stakeholders: You will work hand-in-hand with them to understand their needs, collect their feedback, and also evangelize data usage to help them make smarter choices.\nContinuous Learning and Improvement: As \"never stop learning\" is one of our values, you will grow along the way and learn how to use analytical methods and the different tools that we use (and will use) in our data stack.\nPreferred Experience\nExperience: You have 1-3y of professional experience in data analysis (relevant internships can count).\nEducation: You graduated from an engineering or business school (or equivalent).\nMindset: You have an entrepreneurial mindset, you like challenges, you welcome feedback and you are willing to get better everyday to reach excellence.\nProblem-solving & Analytical skills: You love solving complex problems and analyzing data.\nCoding knowledge: Mastering SQL and Python is not mandatory, as you can still learn when joining, but it's a plus.\nBusiness acumen: You can understand the needs of your business stakeholders and get the big picture of how the business is running.\nCommunication: You know how to present your conclusions clearly and synthetically (written and oral).\nLanguages: You are fluent in English, both written and spoken.\nRecruitment Process\n15-min call with the Hiring Manager\n45-min personality interview with two team members\nA case study followed by a 45-min debrief\n45-min Founders interview\nReference calls\nYou might also be invited to meet other team members at the office for a coffee or a drink!\nAdditional Information\nContract Type: Full-Time\nLocation: Paris\nPossible full remote\nShow more\nShow less",
        "details": {
            "JobDetail": [
                "Remote",
                "Full"
            ],
            "TypeContract": "",
            "Salary": "",
            "Level": "",
            "Experience": null
        },
        "title": "data analyst",
        "skills": {
            "ProgLanguage": [
                "Python"
            ],
            "DataBase": [
                "SQL"
            ],
            "Collaboration": [
                "Teams"
            ],
            "EnSoftSkils": [
                "Communication"
            ]
        }
    },
    {
        "source": "LinkedIn",
        "company": "Voodoo",
        "location": "Paris, Île-de-France, France",
        "link": "https://fr.linkedin.com/jobs/view/data-analyst-at-voodoo-3902465580?position=9&pageNum=7&refId=QYO6QFCk1HyZpy1IxSLXjw%3D%3D&trackingId=WW6m%2FNzPWPqSaavHT3oVxg%3D%3D&trk=public_jobs_jserp-result_search-card",
        "description": "Team\nThe Engineering & Data team builds innovative tech products and platforms to support the impressive growth of their gaming and consumer apps which allow Voodoo to stay at the forefront of the mobile industry. The Engineering & Data team plays a key role in Voodoo’s long-term strategy. It enables Voodoo to both accelerate product diversification and provide a state of the art growth-engine to distribute and scale our games. They create innovative solutions that drive growth with a pragmatic approach, ranging from simple searching to complex machine learning systems.\nWe are looking for a Data Analyst who is deeply passionate about data-driven decisions, transforming raw data into clear actionable business insights, and who is constantly driving themselves and the team towards completing the next challenge.\nBy joining this team, you will have a strong impact on the business and a unique opportunity to reach hundreds of millions of users with your insights and recommendations.\nThe Analytics Team works closely with Voodoo’s game studios. We specialize in crafting analytical tools that dissect gaming behavior, offering crucial insights to our studio game analysts. Our proficiency in analyzing gaming behavior equips us to devise and implement innovative solutions. These solutions fuel growth and fortify the success of Voodoo’s diverse gaming portfolio.\nRole\nWork on end-to-end data projects in collaboration with internal departments, aiming to enhance our games and boost both monetization and player retention.\nBuild and manage robust data pipelines to align with ever-evolving business needs, ensuring optimal architecture support.\nDevelop dashboards and reports to foster company-wide comprehension of key business metrics and player experiences.\nAnalyze large, complex datasets representing the behavior of millions of online and mobile game players, delivering actionable recommendations that shape game features, economies, and future product roadmaps.\nProfile\nYou possess substantial experience in analytical roles, ideally within a web or mobile company or the online gaming industry.\nYou are highly skilled in SQL and have a proven track record of building production-ready pipelines that handle large and complex data sets.\nYou have practical experience with Tableau, and can create dashboards that are shared company-wide, facilitating data-driven decision-making across departments.\nYou enjoy working in a fast-paced environment and are able to balance the tradeoff between time-consuming development and rapid results.\nA BA/B.Sc degree in Statistics, Math, Engineering, Economy, or other quantitative fields is mandatory for this role.\nAdvanced knowledge of statistical tools and models will be considered a significant advantage.\nBenefits\nCompetitive salary upon experience\nSwile Lunch voucher\nGymlib (100% borne by Voodoo)\nPremium healthcare coverage SideCare, for your family is 100% borne by Voodoo\nChild day care facilities (Les Petits Chaperons rouges)\nWellness activities in our Paris office\nUnlimited vacation policy\nRemote days\nVoodoo just won the award for Best Office Space in France\nShow more\nShow less",
        "details": {
            "JobDetail": [
                "Remote"
            ],
            "TypeContract": "",
            "Salary": "100",
            "Level": "",
            "Experience": null
        },
        "title": "data analyst",
        "skills": {
            "DataBase": [
                "SQL"
            ],
            "DataVisualisation": [
                "Tableau"
            ],
            "Other": [
                "Machine Learning"
            ],
            "EnSoftSkils": [
                "Collaboration"
            ]
        }
    },
    {
        "source": "LinkedIn",
        "company": "AccorInvest",
        "location": "Évry, Île-de-France, France",
        "link": "https://fr.linkedin.com/jobs/view/hr-data-analyst-h-f-cdd-at-accorinvest-3883853598?position=10&pageNum=7&refId=QYO6QFCk1HyZpy1IxSLXjw%3D%3D&trackingId=RcogLii3ygNT3HfutMbu9g%3D%3D&trk=public_jobs_jserp-result_search-card",
        "description": "Dans le cadre d'un remplacement partiel de congé maternité, dès juin 2024, vous ferez partie de\nl’équipe HR Data / Contrôle de Gestion Sociale. Vous aurez pour principales missions de collecter, analyser et synthétiser les données sociales. Pour réaliser un travail de qualité, vous devrez aussi contrôler la cohérence et la fiabilité de ces données.\nVos principales missions seront:\nAssurer la production et l’analyse du HR Dashboard Europe du Sud\nAssurer la production et l’analyse des rapports légaux France (BDES : Bilan Social, Index, SSCT, Rapport de Situation Comparée)\nRépondre aux demandes mensuelles, trimestrielles et ponctuelles des CSE et de tous les clients internes\nProduction et contrôle de l’ensemble des documents liées aux expertises CSE\nRéaliser des simulations de coûts liés à la politique sociale\nÊtre garant de la qualité des données et des process et alerter de toutes dérives sur les process data et résultats de KPIs\nÊtre capable de vulgariser les analyses et transmettre des informations compréhensibles pour aider à la prise de décision.\nGérer l’administration des accès et publication des données BDES\nVeiller à ce que les données numériques des collaborateurs soient protégées et utilisées en parfaite conformité avec les règlementations en vigueur\nPiloter une partie de l’automatisation des productions pour sécuriser et fiabiliser les rapports.\nProfil et Compétences:\nFormation :\nMaster 2 RH ou Contrôle de Gestion.\nExpérience professionnelle requise :\n3ans min. d’expérience en Contrôle de Gestion Sociale, HR data analyst, Data scientist.\nSavoir faire:\nExcel\nAppétence pour les chiffres\nAisance avec les systèmes d’informations\nRigueur dans la manipulation des données\nEsprit d’analyse et de synthèse\nGestion des priorités et des délais\nAnglais\nConnaissance GXP, HRI, Power BI et Oracle serait un plus\nSavoir être:\nAutonomie\nEsprit d’équipe\nRéactif\nIntérêt/Curiosité sur les sujets RH\nRespect de la confidentialité des données\nLe poste est à pourvoir dès juin 2024 en Contrat à Durée Déterminée.\nInformation sur le traitement des données personnelles\nLorsqu’une personne soumet sa candidature à SGHI, cette société SGHI traite certaines de ses données pour évaluer et gérer la candidature. En notre qualité de responsable de traitement de vos données personnelles, nous veillons à nous conformer à la législation relative à la protection des données personnelles (notamment à la loi du 6 janvier 1978 modifiée relative à l'informatique, aux fichiers et aux libertés ainsi qu’au règlement européen n°2016-679 du 27/04/2016 sur la protection des données (Règlement Général sur la Protection des Données ou « RGPD »)). Par ailleurs, nous pouvons être amenés à contacter un ou plusieurs des anciens employeurs du candidat. Nous pouvons également proposer au candidat de procéder à un questionnaire de personnalité ; il est précisé que les réponses à ce questionnaire n’entraineront pas de décision automatisée concernant le recrutement.L’ensemble des informations relatives au traitement des données personnelles des candidats et notamment à l’exercice de leurs droits d’accès, d’opposition, de rectification, de suppression, est disponible dans notre\nPolitique deprotection des données personnelles des collaborateurs\n.\nShow more\nShow less",
        "details": {
            "JobDetail": [],
            "TypeContract": "",
            "Salary": "",
            "Level": "",
            "Experience": "3 an(s)"
        },
        "title": "data analyst",
        "skills": {
            "DataVisualisation": [
                "Power BI"
            ]
        }
    },
    {
        "source": "LinkedIn",
        "company": "Aubay",
        "location": "Paris, Île-de-France, France",
        "link": "https://fr.linkedin.com/jobs/view/consultant-data-power-bi-f-h-at-aubay-3621584441?position=1&pageNum=10&refId=tn2QJQESk9ttg00nH%2FdA7g%3D%3D&trackingId=wnFdgAH1t6J9nGP4Lb8VpQ%3D%3D&trk=public_jobs_jserp-result_search-card",
        "description": "Rejoins une Team Data du tonnerre ⚡ et une communauté Data driven d’expérience avec des experts qui analysent, créent des outils de pilotage, valorisent les visuels et accompagnent des clients de tous secteurs d’activité pour booster leurs performances en Modern Business Intelligence (BI) et en Data Viz.\nAubay renforce ses équipes Data et recherche des consultants Power BI pour intervenir sur des projets de développement ou de refonte de rapports et de tableaux de bords basés sur des solutions BI legacy.\nTon quotidien en tant que Consultant Data Power BI :\nParticipation aux ateliers de cadrage et d’expression de besoins avec les métiers\nPréparation des données avec Power Query et Power BI Dataflow\nModélisation de données performants\nProduction et mise à disposition de rapports avec Power BI Desktop et Service\nAccompagnement des métiers au cours de la phase de recette des rapports et dans l'adoption des principes de Data Viz et de la solution Power BI\nTes qualifications :\nSoft skills :\nTu disposes d’une formation niveau BAC+5 (Master 2 ou école d’ingénieur) spécialisée en informatique (idéalement d’une filière orientée BI / Data Analytics) et tu as déjà une première expérience significative (2 ans ou plus) dans la mise en œuvre de la solution Power BI\nTu sais ce qu’implique l’expression « garbage in – garbage out » dans un contexte Data. Tu es donc vigilant à la qualité des données que tu manipules et force de proposition pour identifier et mettre en œuvre des actions curatives / correctives pérennes\nTes qualités de communication orale et écrite te permettent d’échanger et collaborer de manière efficace aussi bien avec des profils métiers / fonctionnels qu’avec des profils techniques\nTu es soucieux de la qualité visuelle de tes livrables (documents, tableaux de bords, etc.) afin de garantir une expérience utilisateur réussie\nHard skills :\nTu connais les langages SQL, DAX, M et Python\nTu maîtrises les concepts de modélisation de données\nLes plus qui te feront sortir du lot :\nTu as obtenu la certification « Microsoft Power BI Data Analyst Associate » (DA-100 / PL-300)\nConnaissance des autres solutions de la Power Platform de Microsoft et notamment Power Automate\nTu as déjà eu une expérience un service cloud type Azure, AWS ou GCP\nTu sais gérer un projet en mode agile\nTu es à l’aise en anglais à l’oral comme à l’écrit\nTu crois aux valeurs d’excellence, d’efficacité, de bienveillance, d’intraprenariat et de responsabilité.\nPourquoi nous rejoindre ?\nDes missions et projets dans le domaine Modern BI & Analytics en nombre et dans des secteurs variés (Banque, Assurance, Telecom, Industrie, …) qui permettent à nos collaborateurs de monter en compétences et de devenir des experts Data reconnus\nDe l’apprentissage en continu avec des formations et des certifications sur les technologies Data de pointe\nDes experts Data mobilisables pour accompagner et soutenir techniquement les collaborateurs sur leurs projets\nDes communautés de savoir-faire Data proposant de manière régulière aux collaborateurs d’Aubay du contenu et des évènements de partage (webinar, meetup/afterwork, BBL, …) sur les thématiques suivantes : Data Engineering, Modern BI & Analytics, Data Science/IA, Data Platform & Architecture, …\nTa carrière chez Aubay\nTu auras la possibilité de certifier tes compétences et de développer tes connaissances sur différentes solutions Modern BI & Data Viz comme Power BI, Tableau, QlikSense ou Preset.io\nTu rejoindras la BU d’excellence Data et évolueras au sein d’un environnement humain et professionnel de haut niveau. Tu profiteras d’un management sur-mesure pour t’accompagner dans ta trajectoire de carrière\nAu sein de la BU d’excellence, de multiples perspectives s’offriront à toi, de devenir :\nLead en étant un référent auprès de nos clients et des collaborateurs de la communauté Modern BI & Analytics\nChampion en représentant Aubay auprès de nos partenaires\nHead en prenant la tête d’une practice (développement business, recrutement, management de collaborateurs, définition de la stratégie et animation de la communauté au sein du groupe Aubay, etc.)\nBesoin d’en savoir plus sur le processus de recrutement ?\nUn échange macro\nau niveau RH\navec\nDoriane\nUn entretien\ntechnique\navec\nClaudio\n, un de nos référents techniques\nUn échange\nmanagérial\navec\nle Directeur de la BU Modern BI & Data\nA savoir que l’ordre des étapes peut varier selon tes envies (ex : échange managérial avec l’échange technique)\nAubay encourage la diversité sous toutes ses formes et garantit l'égalité des chances à tous les candidats. Tous nos postes sont ouverts aux personnes en situation de handicap et nous proposons tous les aménagements nécessaires.\nShow more\nShow less",
        "details": {
            "JobDetail": [],
            "TypeContract": "",
            "Salary": "",
            "Level": "Bac+5",
            "Experience": "2 an(s)"
        },
        "title": "consultant data",
        "skills": {
            "ProgLanguage": [
                "Python"
            ],
            "DataBase": [
                "SQL"
            ],
            "DataVisualisation": [
                "Power BI",
                "Tableau"
            ],
            "CloudComputing": [
                "GCP",
                "AWS",
                "Azure"
            ],
            "Other": [
                "Cloud"
            ],
            "EnSoftSkils": [
                "Communication"
            ]
        }
    },
    {
        "source": "LinkedIn",
        "company": "Artefact",
        "location": "Paris, Île-de-France, France",
        "link": "https://fr.linkedin.com/jobs/view/senior-data-analyst-paris-at-artefact-3435228972?position=2&pageNum=10&refId=tn2QJQESk9ttg00nH%2FdA7g%3D%3D&trackingId=Gb3m8CHu%2BrgF70zxy%2FCNYQ%3D%3D&trk=public_jobs_jserp-result_search-card",
        "description": "Who We Are\nArtefact is a new generation of data service provider, specialised in data consulting and data-driven digital marketing.\nOur purpose?\nEvery day we boost our clients’ data transformation into business impact across the entire value chain of organisations.\nOur strength?\nOur data services stand on double expertise: the combination of Artificial Intelligence and the business prowess acquired from our customers around the world, such as AccorHotels, Orange, Carrefour, Engie, Samsung, L'Oréal, Nissan...\nArtefact’s success comes from a unique mix of company assets: cutting-edge data technologies, agile methodologies for fast delivery, cohesive teams assembling the finest business consultants, data analysts, data scientists, data engineers, and digital marketing experts.\nArtefact Is\n13 offices in Paris, London, Shanghai, Dubai...\n900 employees\n4 practices: Data Consulting, Data Marketing, Activation and Creation\nWhat you will be doing: Key responsibilities\nAs a Senior Data Analyst, Your Role Will Encompass\nConducting projects to accompany the transformation of your clients’ businesses through the effective collection, processing, and visualisation of data\nExtracting valuable insights from our clients’ marketing-related data sources.\nDesigning dashboards for marketing decision-making while taking into account the business needs\nAccompanying our clients in the conception and implementation of data architectures and data pipelines, from collection to monitoring.\nActively contributing to the expertise level and competencies of the Data & Analytics team\nClosely collaborate with the other divisions (Media & Activation, Creation, Consulting, Data Science and Data Engineer) to provide comprehensive services to your clients\nBeing a great tech role model\nDemonstrating the skill and credibility required to ensure the success of our clients’ initiatives\nResearching and developing new technical approaches to address problems efficiently\nStaying up-to-date on developments within the industry, sharing best practices and actively contributing to Artefact’s institutional knowledge\nEmbodying Artefact’s values and inspiring others to do the same\nQualifications: Education & experience required\nHaving an academic level of education (Bachelor or Master), in a data-driven working environment, you have experience or have knowledge in :\nA minimum of 3 year of work experience in a data-driven working environment\n1 or more data collection (Google Analytics, Adobe Analytics, SQL database, CRM database, transactional data)\n1 or 2 programming languages among SQL, Python and/or R.\n1 or more Data visualisation tool (Tableau, Data Studio, Dataviz, R / Python dataviz libraries, ...)\nIn addition, you have the knowledge in one or more of the following technologies:\nGoogle Cloud Platform resources (Big Query, Google Cloud Storage) or its equivalent in Azure or AWS\nYou know how to connect to an API through the knowledge of the different authentication method (OAuth, HTTP Basic, API key)\nAdvertising tool, linked to tracking and/or analytics in a marketing context (Google Analytics, Adobe Analytics, DMP, DSP, Adservers, DV 360...)\nETL tool (Airflow, Dataiku, Dataflow, Dataprep...)\nWeb application (R-Shiny, Python Flask) that you have industrialized\nIdeally You Have\nKnowledge of statistics\nKnowledge of machine learning and data engineering\nWhat We Are Looking For\nA Doer: you get things done and inspire your team to do the same\nAn Analyst: you LOVE data and think every company should take their decisions based on facts\nA Pragmatist: you have a no-nonsense mindset that seeks for practical and realistic solutions\nA Mentor: your clients and colleagues naturally seek you out for advice\nAn Adventurer: you’re an entrepreneur constantly looking for business opportunities\nWhy you should join us\nArtefact is the place to be: come and build the future of marketing\nProgress: every day offers new challenges and new opportunities to learn\nCulture: join the best team you could ever imagine\nEntrepreneurship: you will be joining a team of driven entrepreneurs. We won’t give up until we make a huge dent in this industry!\nCome join us!\nShow more\nShow less",
        "details": {
            "JobDetail": [
                "Senior"
            ],
            "TypeContract": "",
            "Salary": "",
            "Level": "",
            "Experience": null
        },
        "title": "data analyst",
        "skills": {
            "ProgLanguage": [
                "R",
                "Python"
            ],
            "DataBase": [
                "SQL"
            ],
            "DataAnalytics": [
                "R"
            ],
            "MachineLearning": [
                "Orange"
            ],
            "DataVisualisation": [
                "Tableau"
            ],
            "CloudComputing": [
                "AWS",
                "Google Cloud Platform",
                "Azure"
            ],
            "DBMS": [
                "Big Query"
            ],
            "Automation": [
                "Airflow"
            ],
            "Collaboration": [
                "Teams"
            ],
            "Other": [
                "Machine Learning",
                "Cloud"
            ]
        }
    },
    {
        "source": "LinkedIn",
        "company": "Artefact",
        "location": "Paris, Île-de-France, France",
        "link": "https://fr.linkedin.com/jobs/view/data-analyst-specialist-entry-level-at-artefact-3072340205?position=3&pageNum=10&refId=tn2QJQESk9ttg00nH%2FdA7g%3D%3D&trackingId=%2F%2BAExzq8YRDeWurxr8thNg%3D%3D&trk=public_jobs_jserp-result_search-card",
        "description": "Who We Are\nArtefact is a new generation of a data service provider, specialised in data consulting and data-driven digital marketing.\nOur purpose?\nEvery day we boost our clients’ data transformation into business impact across the entire value chain of organisations.\nOur strength?\nOur data services stand on a double expertise: the combination of Artificial Intelligence and the business prowess acquired from our customers around the world, such as AccorHotels, Orange, Carrefour, Engie, Samsung, L'Oréal, Nissan...\nArtefact’s success comes from a unique mix of company assets: cutting-edge data technologies, agile methodologies for fast delivery, cohesive teams assembling the finest business consultants, data analysts, data scientists, data engineers, and digital marketing experts.\nArtefact is looking for a Data Analyst Specialist for our clients, in order to reinforce our multiple data marketing offers.\nArtefact Is\n13 offices in Paris, London, Shanghai, Dubai...\n900 employees\n4 practices: Data Consulting, Data Marketing, Activation and Creation\nWhat you will be doing: Key responsibilities\nAs a Data Analyst Specialist, Your Role Will Encompass\nCreating and implementing a tagging plan, using analytics tools according to the template and basic configuration\nPerforming audit reports and creating web analysis studies (client journey, landing page, channels ROI) by defining and monitoring different KPIs and PIs\nMonitoring different activities that can be impacted by web analytics (Activation, UX/CRO, tracking, trafficking).\nActively contributing to the expertise level and competencies of the Data & Analytics team\nClosely collaborate with the other divisions (Media & Activation, Creation, Consulting, Data Science and Data Infrastructure) to provide data-driven marketing services to your clients\nQualifications: Education & experience required\nWith 1-2 years of experience in the digital marketing environment, preferably with big client accounts, you have:\nAcademic level of education (Bachelor or Master)\nKnowledge in working with a tagging plan, either by optimising an existing setup by solving problems and challenging existing tagging plan, or draft and set-up a tagging plan according to the template.\nKnowledge of web analytics platforms like Google Analytics, Adobe Analytics, etc.\nFamiliarity with tag management systems like Google Tag Manager, Tag Commander, Tealium IQ Tag Management, Launch/DTM etc.\nPreferably, You Also Have\nGood knowledge of web-related technologies (JavaScript, CSS and HTML)\nOptionally, familiarity with the Data Management Platforms like BlueKai, Krux, Ysance, Weborama, Adobe Audience Manager, Tealium Audience Streams, etc.\nKnowledge in a website optimization tools like hotjar, Google Optimize360, Content Square, AB Tasty etc. is appreciated.\nKnowledge in customer journey optimization / CRO is appreciated.\nWhat We Are Looking For\nA Doer: you get things done and inspire your colleagues to do the same\nAn Analyst: you LOVE data and think every company should take their decisions based on facts\nA Pragmatist: you have a no-nonsense mindset that seeks for practical and realistic solutions\nA Mentor: your clients and teams naturally seek you out for advice\nAn Adventurer: you’re an entrepreneur constantly looking for business opportunities\nWhy you should join us\nArtefact is the place to be: come and build the future of marketing\nProgress: every day offers new challenges and new opportunities to learn\nCulture: join the best team you could ever imagine\nEntrepreneurship: you will be joining a team of driven entrepreneurs. We won’t give up until we make a huge dent in this industry!\nCome join us!\n#fr\nShow more\nShow less",
        "details": {
            "JobDetail": [],
            "TypeContract": "",
            "Salary": "",
            "Level": "",
            "Experience": null
        },
        "title": "data analyst",
        "skills": {
            "MachineLearning": [
                "Orange"
            ],
            "Collaboration": [
                "Teams"
            ]
        }
    },
    {
        "source": "LinkedIn",
        "company": "GROUPE ADF",
        "location": "Vitrolles, Provence-Alpes-Côte d'Azur, France",
        "link": "https://fr.linkedin.com/jobs/view/data-analyst-f-h-at-groupe-adf-3906894523?position=4&pageNum=10&refId=tn2QJQESk9ttg00nH%2FdA7g%3D%3D&trackingId=nvEl2SXyoFq0DHIN7d1rIw%3D%3D&trk=public_jobs_jserp-result_search-card",
        "description": "Description\nActeur majeur en prestations de maintenance et services connexes aux industries et fortement implanté à l’international, le Groupe ADF (3900 collaborateurs / 540 millions de CA) propose à ses clients des solutions de maintenance axées sur l'amélioration continue et l'optimisation de ses équipements, ainsi que des installations industrielles clés en main.\nDans le cadre de son développement la Direction des Achats du Groupe ADF, recrute son/sa futur(e) Analyste Achat (F/H).\nMission\nAnalyse, reporting et suivi des KPI\nÉlaborer et suivre les indicateurs clés de performance (KPI) pour évaluer la performance de la Direction des Achats\nAnalyser et communiquer par des tableaux de bord visuels pour présenter les résultats aux différents responsables achats\nApprofondir certaines dérives constatées avec des reportings périodiques sur des sujets ciblés\nSuivre, animer et co piloter les plans d’actions initiés dans le cadre de la stratégie Achat du Groupe\nOptimisation des processus & applications\nCollaborer avec les équipes internes pour identifier des possibilités d'efficacité et de réduction des coûts\nProposer des recommandations basées sur les données pour améliorer les processus existants\nAssurer un rôle de référent pour certains projets transverses impliquant l’environnement applicatif achat.\nProfil\nDiplômé(e) d’une école de Commerce, vous disposez d’une première expérience dans l’analyse des processus achats d’un Groupe ainsi que dans la gestion d’applications.\nLa maitrise d’Excel est requise.\nLa connaissance d’outils de gestion de base de données (Access) et de reporting (Power BI) sera un plus à votre candidature.\nLe développement du Groupe à l’international impliquera certains échanges en Anglais.\nVotre polyvalence et votre autonomie ainsi que votre appétence à la prise d’initiative seront des qualités indispensables pour la réussite de votre mission !\nAvantages\nAccord intéressement / participation\nConvention collective Métallurgie / Syntec\nAvantages CSE (chèques cadeaux, tarifs préférentiels, chèques vacances, etc)\nAccord QVT\nMutuelle\nPossibilité de télétravail en fonction du poste\nPasserelle métiers (mobilité interne et internationale, cooptation, etc)\nPrime de cooptation\nApplication de covoiturage, Klaxit\nCentre de formation interne, OTI\nTitre Restaurant\nIntéressé(e) par notre proposition ?\nTransmettez-nous votre candidature !\nNotre service recrutement et nos experts techniques l'étudieront avec attention.\nSi elle est retenue, nous vous contacterons pour un premier échange téléphonique puis pour un entretien avec un expert technique.\nDans le cadre de sa politique diversité, Groupe ADF étudie, à compétences égales, toutes candidatures dont celles de personnes en situation de handicap.\nShow more\nShow less",
        "details": {
            "JobDetail": [],
            "TypeContract": "",
            "Salary": "",
            "Level": "",
            "Experience": null
        },
        "title": "data analyst",
        "skills": {
            "DataVisualisation": [
                "Power BI"
            ],
            "EnSoftSkils": [
                "Initiative"
            ]
        }
    },
    {
        "source": "LinkedIn",
        "company": "CubeRH",
        "location": "Tourcoing, Hauts-de-France, France",
        "link": "https://fr.linkedin.com/jobs/view/data-analyst-h-f-cdi-at-cuberh-3840635774?position=5&pageNum=10&refId=tn2QJQESk9ttg00nH%2FdA7g%3D%3D&trackingId=wVZSg%2FbQFHyd%2BXSVzxZMLQ%3D%3D&trk=public_jobs_jserp-result_search-card",
        "description": "La société :\nNotre client est une entreprise de services spécialisée dans le domaine de la Data, à échelle humaine, qui se distingue par son expertise développée autour de trois axes principaux : la Data généraliste, l'outil de reporting Power BI et la solution cloud Microsoft Azure.\nAu cœur de sa mission, l'éco-responsabilité constitue un pilier essentiel. En adoptant cette approche, elle offre une vision complète et intégrée de la gestion des données. Grâce à une équipe de consultants experts, elle simplifie les opérations, optimise les données et les valorise, offrant ainsi à ses clients une opportunité de progression.\nEn pleine croissance, l'entreprise recherche à agrandir son équipe avec un Data Analyst H/F.\nSi vous recherchez une équipe qui met en avant votre développement professionnel et votre épanouissement, vous êtes au bon endroit !\nL'objectif de la mission :\nAnalyser les problématiques métier et les synthétiser\nManipuler la donnée, l'exploiter et l'interpréter pour en dégager des observations business utiles\nCréer des dashboards et rapports afin d'obtenir des éléments de décision\nMettre en place des kpis de performances permettant de donner une vision cohérente des résultats aux différentes équipes métiers\nDevenir un référent technique sur l'outil de reporting Power BI\nPrendre part au développement de la startup avec tes idées innovantes\nLes conditions de travail :\nUne mutuelle avantageuse et des tickets restaurants\nRemboursement intégral de vos frais de transports en commun\nDes trottinettes électrique et des vélos à disposition\nPrimes (notamment de cooptation)\nTélétravail\nVotre profil :\nMaitrise du SQL\nConnaissance analytiques et statistiques\nBonne maitrise de Power BI\nConnaissance du cloud\nConnaissance d'outils d'analyse de données (SAS, R, etc.) ainsi que de python qui serait un plus.\nProcess entretien :\nDeux premiers échanges avec le cabinet Cube RH;\nEntretiens avec le client (RH et avec le manager).\nShow more\nShow less",
        "details": {
            "JobDetail": [],
            "TypeContract": "",
            "Salary": "",
            "Level": "",
            "Experience": null
        },
        "title": "data analyst",
        "skills": {
            "ProgLanguage": [
                "R",
                "Python"
            ],
            "DataBase": [
                "SQL"
            ],
            "DataAnalytics": [
                "R"
            ],
            "DataVisualisation": [
                "Power BI"
            ],
            "CloudComputing": [
                "Azure"
            ],
            "Other": [
                "Statistiques",
                "Cloud"
            ]
        }
    },
    {
        "source": "LinkedIn",
        "company": "Boursorama",
        "location": "Boulogne-Billancourt, Île-de-France, France",
        "link": "https://fr.linkedin.com/jobs/view/data-analyst-marketing-boursorama-h-f-at-boursorama-3854191406?position=6&pageNum=10&refId=tn2QJQESk9ttg00nH%2FdA7g%3D%3D&trackingId=%2FMChFsGgtUuLBs7azXCy5w%3D%3D&trk=public_jobs_jserp-result_search-card",
        "description": "23000UHD\nVos missions au quotidien\nAu sein de la Direction Marketing Epargne, et en binôme avec un autre Data Analyst, votre mission sera de suivre l’activité Marketing et Commerciale en exploitant les différentes sources de données.\nPour mener votre mission à bien, vous pourrez vous appuyer sur l’expertise des autres Data Analysts de la communauté Data Marketing.\nExpertise en Dashboarding :\nConcevoir, produire et faire évoluer les tableaux de bord de l’activité commerciale et marketing en Datavisualisation (Tableau)\nProduire des insights pertinents pour tirer des enseignements, lever des alertes dans le cadre de certains reportings d’activités à forte valeur ajoutée\nInterpréter les résultats en regard des actualités Business\nSuivre des actions commerciales :\nRéaliser le ciblage dans le cadre d’actions commerciales/ campagnes marketing en lien avec les autres équipes marketing : appropriation du contexte et des enjeux, challenge des demandeurs métier\nEffectuer des bilans des campagnes marketing / d’opérations et produire des enseignements sur la performance des campagnes et des recommandations pour des futures actions marketing\nConnaissance clients :\nRéaliser des études statistiques adhoc sur des problématiques marketing (acquisition, fidélisation, lancement de produits/services …)\nComprendre les enjeux business et l’impact de son travail sur la prise de décision\nContribuer à la construction et l’évolution des outils de fidélisation : segmentation client, relances automatisées, gestion des moments de vie …\nEtudier la performance de notre recrutement pour optimisation (analyse des tunnels de transformation, analyse des canaux d’acquisition …)\nRéaliser des analyses liées à des problématiques d’autres Directions\nEt si c’était vous ?\nDe formation Bac +4/5 en statistiques, vous justifiez d’une première expérience réussie dans ce domaine – alternance y compris.\nVous avez une bonne compréhension des problématiques marketing et de l‘écosystème data dans le digital (DMP, web analytics, ...)\nVous maîtrisez SAS (langage macro), Excel, Powerpoint et un outil de DataVisualisation (idéalement Tableau). La connaissance du langage Python est un plus.\nVotre capacité d’analyse, votre bon relationnel et votre capacité à gérer des projets Data en travaillant de façon transverse avec d’autres Directions seront de réels atouts\nPourquoi nous choisir ?\nBoursorama est un acteur pionner et leader sur ses trois activités principales : la banque en ligne, le courtage en ligne et l’information financière sur Internet.\nPrécurseur d’une nouvelle génération de banque depuis 2005, Boursorama, filiale de la Société Générale est aujourd’hui plébiscitée et recommandée par 85% de ses clients.\nAccessible à tous et classée banque la moins chère depuis 15 ans, Boursorama a doublé le nombre de ses clients ces trois dernières années.\nL’entreprise conforte chaque année sa position d’acteur majeur du secteur et compte aujourd’hui plus de 5 millions de clients.\nEnvie de prendre part à cette aventure professionnelle enrichissante et construire un projet professionnel solide, venez rejoindre vos 930 futurs collègues dans nos locaux de Boulogne Billancourt (92) et Nancy (54).\nBoursorama est certifiée B CorpTM et rejoint le mouvement mondial des sociétés engagées en matière d’impact social et environnemental, de transparence et de responsabilité.En tant qu’acteur engagé, Boursorama au cœur de ses valeurs les thématiques RSE. Nous avons notamment mis en place des actions visant à réduire notre impact écologique : accord inédit sur le télétravail, proposition de moyen de locomotion électrique, zéro déchet….\nNous avons aussi à cœur d’assurer le bien-être de nos équipes en proposant des avantages notamment 2 jours de télétravail hebdomadaires et un accord d’intéressement motivant.\nEn intégrant la Direction Marketing et Communication\nvous conforterez chaque jour la position de leader de Boursorama.\nNous sommes un\nemployeur garantissant l'égalité des chances\net nous sommes fiers de faire de la diversité une force pour notre entreprise. Le groupe s’engage à reconnaître et à\npromouvoir tous les talents\n, quels que soient leurs croyances, âge, handicap, parentalité, origine ethnique, nationalité, identité de genre, orientation sexuelle, appartenance à une organisation politique, religieuse, syndicale ou à une minorité, ou toute autre caractéristique qui pourrait faire l’objet d’une discrimination.\nShow more\nShow less",
        "details": {
            "JobDetail": [],
            "TypeContract": "",
            "Salary": "",
            "Level": "",
            "Experience": "15 an(s)"
        },
        "title": "data analyst",
        "skills": {
            "ProgLanguage": [
                "Python"
            ],
            "DataVisualisation": [
                "Tableau"
            ],
            "Other": [
                "Statistiques"
            ],
            "EnSoftSkils": [
                "Communication"
            ]
        }
    },
    {
        "source": "LinkedIn",
        "company": "Bpifrance",
        "location": "Maisons-Alfort, Île-de-France, France",
        "link": "https://fr.linkedin.com/jobs/view/data-analyst-f-h-at-bpifrance-3911935389?position=7&pageNum=10&refId=tn2QJQESk9ttg00nH%2FdA7g%3D%3D&trackingId=IEzuL7VfCUjSl0J%2FRyb%2BBQ%3D%3D&trk=public_jobs_jserp-result_search-card",
        "description": "Vos missions au service de l’économie française\nNous recherchons un.e Data Analyste.\nVous travaillez au sein des équipes en charge du socle Data Gouvernance, en étroite collaboration avec les équipes de la Gouvernance des données.\nVous jouerez un rôle clé dans la transformation Data Centric de notre système d’information Bpifrance au service de toutes les directions métiers.\nVous contribuez activement aux enjeux du socle data gouvernance pour positionner le dictionnaire de données au cœur des process du SI et améliorerez les services pour assurer la data quality tout au long de son cycle de vie.\nVos activités principales au sein de l’équipe socle Data Gouvernance :\nAccompagner au quotidien les équipes agiles et les métiers dans la prise en main des outils du socle.\nAnimer la communauté du socle au travers de communications\nAnimer le club utilisateurs du socle\nMettre en œuvre des e-learning\nMettre en place des indicateurs de mesure et de pilotage du socle,\nSuperviser, mesurer, suivre l’évolution des indicateurs de mesure et de pilotage du socle au travers de tableaux de bord que vous produirez pour des comités de supervision,\nDévelopper des tableaux de bords à destination de différentes instances et métiers,\nSuivre les éditeurs (demandes d’évolutions, releases, incidents,..)\nVotre environnement technique sera le suivant :\nNotre dictionnaire de données est la solution DataGalaxy.\nNos outils de mesure de la qualité de données sont Informatica Data Quality (Informatica) et Cloud Data Quality (Informatica).\nNotre outil de Dataviz est Qlik Sense.\nNous interagissons avec l’ensemble des métiers de la banque !\nProfil recherché\nPrêts à rejoindre notre équipe ?\nVotre profil :\nVous disposez d’une première expérience autour des outils de la gouvernance des données et en comprenez les enjeux.\nVous êtes doté d’un excellent relationnel, vous permettant de sensibiliser vos différents interlocuteurs Métiers, Data & IT\nVous êtes à la fois rigoureux et analytique\nVous aimez travailler en équipe, vous êtes curieux, proactif et responsable\nVous êtes diplômé.e Bac+5 et parlez couramment anglais\nLes + du poste :\nDes challenges tech à relever et des événements tech futuristes auxquels vous serez acteur.trice et convié.e\nVivre au rythme d’une culture Tech affirmée au cœur d’une équipe soudée\nVibrer au son d’un podcast hebdo\nAssister à des Town Hall (événements virtuels & soirées) trimestriels\nLe poste est localisé soit au siège de Maisons-Alfort, soit là où vous êtes en France.\nLes bonnes raisons de rejoindre l’aventure Bpifrance !\nUn travail avec du sens : Vous contribuerez à une mission unique d’utilité publique au service de l’économie française et au sein d’une banque engagée sur des sujets de société (climat, jeunesse, égalité des chances…).\nUn environnement dans lequel il fait bon vivre : Vous intégrerez des équipes dynamiques et bienveillantes, au sein d’une entreprise attentive à la Qualité de Vie au Travail de ses collaborateurs. Nos certifications Happy Trainees et Meilleurs Employeurs France par Glassdoor en témoignent !\nDes conditions avantageuses : Vous bénéficierez des nombreux avantages qu’offre le groupe pour ses collaborateurs : télétravail, congés payés supérieurs au minimum légal, épargne salariale attractive, CSE, dispositifs de Qualité de Vie au Travail…\nUn tremplin pour votre carrière : Vous profiterez des meilleures conditions mises en place chez Bpifrance pour développer vos compétences et construire votre parcours de carrière, grâce à un accompagnement sur-mesure et des parcours de formation complets et personnalisés.\nTravailler chez Bpifrance, c’est intégrer une banque pas comme les autres, un projet d’entreprise ambitieux et tourné vers l’avenir. C’est plus qu’un métier : c’est une mission, une équipe, un réseau et un écosystème.\nPour découvrir nos autres opportunités et tout savoir de la vie au sein du groupe, rendez-vous sur notre site carrière !\nBpifrance est une banque citoyenne dotée d’un code de déontologie et d’une politique anti-corruption.\nAvant de postuler, nous vous invitons à consulter notre politique relative à la gestion des données à caractère personnel disponible sur notre site.\nShow more\nShow less",
        "details": {
            "JobDetail": [],
            "TypeContract": "",
            "Salary": "",
            "Level": "Bac+5",
            "Experience": null
        },
        "title": "data analyst",
        "skills": {
            "Other": [
                "Cloud"
            ],
            "EnSoftSkils": [
                "Collaboration"
            ]
        }
    },
    {
        "source": "LinkedIn",
        "company": "Scalian",
        "location": "Toulouse, Occitanie, France",
        "link": "https://fr.linkedin.com/jobs/view/hr-data-analyst-f-h-at-scalian-3841931151?position=8&pageNum=10&refId=tn2QJQESk9ttg00nH%2FdA7g%3D%3D&trackingId=Ah2hjwDXMTkyq32AW8A0Jw%3D%3D&trk=public_jobs_jserp-result_search-card",
        "description": "TOULOUSE\nVous êtes HR Data Analyst (F/H) ou vous souhaitez le devenir !\nCDI à Toulouse /Télétravail partiel possible\nAu moins 5 ans d'expérience dans l'analyse de données.\nRémunération selon votre expérience et vos compétences.\nVous êtes intéressé·e par l’analyse de données RH ?\nVous savez prendre du recul et analyser votre production ?\nVous avez une appétence pour les chiffres et l’amélioration continue ?\nRejoignez notre équipe !\nQuel sera votre rôle ?\nAu sein de la Direction des Affaires sociales et sous la responsabilité du Directeur des Affaires Sociales Groupe, vous aurez pour mission\nl’élaboration et l’analyse des datas sociales\nrécurrentes sur des process industrialisés et ponctuelles :\nProposer des process d’élaboration des outils reporting permettant une productivité, fiabilité, et agilité pour des résultats attendus précis, rigoureux et adaptables selon l’évolution du nombre de sociétés du groupe,\nEtablir des zones de vérifications et de contrôles de cohérences pour assurer la véracité des données transmises,\nDéterminer et formaliser les règles et processus devant être mis en œuvre avec rigueur par vos clients internes,\nAssurer un back up opérationnel pouvant être pris en charge en cas d’absence par la personne en charge des rapports sociaux,\nEnrichir les KPI actuels d’éléments plus qualitatifs RH permettant une lecture plus précise de l’état des Ressources Humaines du Groupe.\nD'autres missions concerneront les rémunérations internationales :\nMener ponctuellement des comparaisons inter sociétés sur leurs éléments de rémunérations prenant en compte le salaire fixe, le variable individuel et/ou collectif, les régimes de santé, et tous autres périphériques de rémunération,\nAdapter des automatismes de reportings mensuels (Effectifs et niveaux de salaires) suffisamment fiables et flexibles permettant d’éclairer le management,\nRépondre à toute analyse souhaitée par le traitement des données sociales internationales et françaises.\nCe que cette expérience va vous apporter\nVous intègrerez notre équipe Social Affairs, au sein de la\nHolding Scalian\nafin d’occuper un poste alliant la technique de votre métier, ainsi que l’analyse et la mise en perspective de votre travail quotidien, le tout sur un périmètre France et international.\nNotre contexte local :\nUne partie de la Direction des Ressources Humaines basée à Toulouse, dont la Direction des Affaires Sociales, composée de 5 personnes,\nDes interlocuteurs internes et externes.\nCe que nous recherchons chez vous\nMaster 2 ou Ingénieur·e de formation,\nExpérience certaine en analyse de données dans un contexte d'entreprise complexe et multi-filiales,\nAvoir travaillé sur des données RH et savoir faire des analyses pertinentes,\nRechercher une performance sur la production des rapports et leur fiabilité,\nAnglais courant : écrit et oral,\nÊtre autonome sur l’évolution des systèmes,\nAvoir le souci du détail, être rigoureux·se.\nÊtre dynamique, curieux·se, avoir le sens de l'adaptabilité.\nPourquoi feriez-vous le grand saut ?\nParce que Scalian vous accompagne dans le développement de votre carrière :\nProgramme d'onboarding complet sur 1 an avec votre manager et votre RH\nProgramme de formation (Scalian Academy, e-learning, webinaires et formations externes)\nCommunautés techniques (Squads, Practices) afin de valoriser et développer votre expertise\nÉvénements internes (Afterworks, Awards Dinner, Kick Off, Live Event du COMEX, Stand Up) et externes (participation à des salons et forums spécialisés dans nos domaines d’activités…)\nDispositif d’accélération d’accès à la mobilité interne et à des échanges internationaux type Erasmus\nParce que Scalian favorise la Qualité de Vie au Travail :\nCertifications Great Place to Work® et Best Workplaces for Women®\nPrime de cooptation, prime vacances, prise en charge par l’employeur de 60% des titres-restaurant, Accord télétravail (jusqu’à 2,5 jours par semaine indemnisés), RTT (dont une partie monétisable), CSE (activités ludiques, chèques-cadeaux, chèques vacances)\nBerceaux en crèches inter-entreprises\nDon ou réception de jours de congés en cas de difficultés personnelles\nParce que Scalian développe une politique RSE concrète et ambitieuse :\nMobilité durable (indemnité kilométrique vélo, leasing de vélos à assistance électrique)\nActions environnementales (Fresque du Climat, Reforest'Action, Clean Up Day, mécénat ONF)\nPostes ouverts aux personnes en situation de Handicap\nDiverses politiques de diversité, d’inclusion et d’intégration mises en place\nScalian c’est aussi :\nUne entreprise en très forte croissance qui, créée en 1989, compte aujourd’hui plus de 5500 personnes\nDes références clients à forte valeur ajoutée auprès de grands industriels français (du CAC40) et internationaux\nUn terrain de jeu où l’expertise se conjugue avec audace, liberté d’entreprendre et convivialité\nSi vous aspirez à un environnement de travail qui valorise autant votre bien-être que votre développement professionnel,\nrejoignez-nous et exprimez pleinement votre talent !\nQuelles seront les prochaines étapes ?\nEchange en visio avec Janice, Talent Acquisition Officer,\n1er entretien avec Éric, Social Affairs Director,\n2nd entretien avec Caroline, Head of Human Ressources.\nShow more\nShow less",
        "details": {
            "JobDetail": [],
            "TypeContract": "CDI",
            "Salary": "5",
            "Level": "",
            "Experience": "5 an(s)"
        },
        "title": "data analyst",
        "skills": {}
    },
    {
        "source": "LinkedIn",
        "company": "METEOJOB by CleverConnect",
        "location": "Marseille, Provence-Alpes-Côte d'Azur, France",
        "link": "https://fr.linkedin.com/jobs/view/data-analyst-power-bi-h-f-at-meteojob-by-cleverconnect-3915208737?position=9&pageNum=10&refId=tn2QJQESk9ttg00nH%2FdA7g%3D%3D&trackingId=8PDR2hc7py4NvsCCa%2FGa%2Fg%3D%3D&trk=public_jobs_jserp-result_search-card",
        "description": "Entreprise\nJob Link est un groupe de recrutement CDD/CDI et intérim existant depuis 2005 et en pleine croissance.\nNous sommes implantés sur 14 bureaux (Lille, Paris et Ile-de-France, Lyon, Marseille, Aix-en-Provence, Aubagne, Nantes, Bordeaux, Toulon et Toulouse).\nNos 80 collaborateurs passionnés par leur métier sont animés par la même ambition : accompagner les candidats et les clients au plus près de leurs besoins. Pour cela, nous proposons un service de recrutement très sélectif et performant, optimisé par un sourcing multicanal, un processus d'évaluation métier par mise en situation et des tests de sélections spécifiques.\nEn 2022, nos équipes ont proposé un entretien à plus de 8000 candidats et 4500 d'entre eux ont pu décrocher l'emploi souhaité.\nDescription Du Poste\nJob Link, spécialisé en recrutement CDD/CDI recherche pour un de ses clients cabinet d'expertise et de conseils un DATA ANALYST expert POWER BI H/F pour un CDI sur Marseille.\nPour Poursuivre Son Développement Et Accompagner Au Mieux Ses Clients Dans L'analyse De Leurs Données, Le Cabinet Recherche Un Consultant.e Data Analyst Spécialisé.e Sur Power BI\ndéploiement de Power BI en interne et auprès des clients du cabinet\ndéveloppement de tableaux de bord en fonction des attentes clients\namélioration des solutions de BI\nFormation auprès de utilisateurs\ncontrat CDI\nsalaire en fonction de l'expérience\nDescription Du Profil\nFormation informatique ou data analyst\nExpertise Power BI\nBon communiquant\nUne première expérience réussie sur ce type de poste d'au moins 2 ans souhaitée\nShow more\nShow less",
        "details": {
            "JobDetail": [],
            "TypeContract": "CDI, CDD",
            "Salary": "2",
            "Level": "",
            "Experience": "2 an(s)"
        },
        "title": "data analyst",
        "skills": {
            "DataVisualisation": [
                "Power BI"
            ]
        }
    },
    {
        "source": "LinkedIn",
        "company": "Relais Colis",
        "location": "Créteil, Île-de-France, France",
        "link": "https://fr.linkedin.com/jobs/view/data-analyst-h-f-at-relais-colis-3901520746?position=10&pageNum=10&refId=tn2QJQESk9ttg00nH%2FdA7g%3D%3D&trackingId=3v0tpbE58kFJ%2FqiriMliuw%3D%3D&trk=public_jobs_jserp-result_search-card",
        "description": "Inventeur du concept de la livraison en Relais, riche de plus de\n54 ans d'expérience\n,\nRelais Colis\nlivre aujourd'hui plus de\n40 millions de colis par an\nen Relais et à Domicile, pour les grands noms du e-commerce, de plus en plus nombreux à lui faire confiance.\nPartenaire n°1 du Top 10 e-commerce avec des grandes enseignes comme\nLA REDOUTE, CDISCOUNT, VEEPEE, AMAZON, SHOWROOMPRIVE, BOUYGUES TELECOM, CONFORAMA, VINTED...\nRelais Colis compte plus de 450 collaborateurs. Entreprise citoyenne, Relais Colis mène une politique volontariste en faveur de l’insertion des personnes en situation de handicap.\nRejoignez Relais Colis en tant que :\nData Analyst (F/H)\nLa Direction data accompagne les différentes directions de Walden Express International (Relais Colis et Ciblex) et ses parties prenantes dans la mise en place du pilotage de leurs activités par la data.\nElle participe activement à l’élaboration, à la valorisation et la restitution de la data pour éclairer les décisions.\nEn collaboration avec les équipes commerciales, relation client et opérationnelles, le(la) data analyst contribue à la mise en œuvre d’un pilotage orienté data chez Relais Colis et Ciblex.\nRattaché(e) au Directeur data, vous assumez les missions suivantes :\nRecueillir les besoins Data et contribuer à l’élaboration des indicateurs et dashboards sur le périmètre.\nIdentifier les axes d’amélioration.\nApporter votre support et votre expertise dans les échanges avec nos clients et les autres directions.\nContribuer au suivi qualitatif de notre performance\nMettre en place les routines de Data Quality afin d’atteindre l’objectif d’une entreprise Data Driven\nIssu(e) d'une formation supérieure, vous êtes \"dataphile\", orienté(e) business et métiers, et surtout doté(e) d'un fort esprit d'entreprise et plein d'enthousiasme\nVous savez coder en SQL et Python\nVous êtes autonome, orienté(e) client et connaissez les métiers du transport et de la logistique.\nVous disposez d'une première expérience réussie et êtes curieux(se), appréciez de travailler en équipe transverse et disposez d'excellente qualités relationnelles et d'organisation, vous avez un réel sens client\nLa base de vos missions se fera par le biais de SAS Visual Analytics et Power BI : une connaissance de ces outils serait un plus.\nUn niveau d’anglais professionnel est nécessaire.\nShow more\nShow less",
        "details": {
            "JobDetail": [],
            "TypeContract": "CDI",
            "Salary": "",
            "Level": "",
            "Experience": "54 an(s)"
        },
        "title": "data analyst",
        "skills": {
            "ProgLanguage": [
                "Python"
            ],
            "DataBase": [
                "SQL"
            ],
            "DataVisualisation": [
                "Power BI"
            ],
            "EnSoftSkils": [
                "Collaboration"
            ]
        }
    },
    {
        "source": "LinkedIn",
        "company": "Foxintelligence",
        "location": "Paris, Île-de-France, France",
        "link": "https://fr.linkedin.com/jobs/view/business-data-analyst-stage-at-foxintelligence-3828937325?position=1&pageNum=12&refId=3UAduJ9EGa9s5reXg%2Ffruw%3D%3D&trackingId=S21H3lOORpE6U7m7zStesQ%3D%3D&trk=public_jobs_jserp-result_search-card",
        "description": "Chez Foxintelligence, nous sommes des amoureux de la data. 🤓\nNotre mission est de rendre les consommateurs et les marques plus intelligents, grâce à une donnée de marché révolutionnaire issue de l'intelligence collective. Pour les consommateurs, Foxintelligence rend accessibles et utiles leurs données transactionnelles issues de leurs boîtes mail ou comptes bancaires. En les anonymisant, nous créons des statistiques uniques qui permettent aux marques de rester en phase avec les produits qui se vendent le mieux et les attentes des consommateurs.\nNous publions une application grand public aimée par des millions de personnes (Cleanfox, 5m+ de téléchargements, 4.8/5 💖 sur l'app store et le play store) et préparons le lancement d'une app de bilan carbone à l'expérience radicalement nouvelle. Grâce à notre plateforme data, elle va rendre possible une prise de conscience massive des enjeux du changement climatique 🌍 et des actions individuelles possibles pour le combattre. Nous pensons que l'information est une force de changement puissante, lorsqu'elle s'appuie sur la data.\nUtilisant ces données personnelles totalement anonymisées, notre plateforme SaaS foxintelligence.io est devenue la référence de la market intelligence digitale en Europe avec des dizaines de grands groupes clients. Le point commun entre Deliveroo, Just Eat, Mano Mano, BackMarket ou The Boston Consulting Group ? Ils vont très vite (on ne s'ennuie pas avec eux !) et ils nous font tous confiance !\nSoutenus par des investisseurs de premier plan (17m levés auprès de Daphni, Partech, GFC et eFounders) et récemment intégré au groupe NielsenIQ nous sommes maintenant à la conquête de l'Europe et en phase d'hyper-croissance.\nSi notre FoxHQ reste à Paris, notre équipe de plus de 140 talents pluridisciplinaires (tech, data et business) travaille depuis partout en France et même en dehors (ex. Turquie). Nous pensons que notre politique remote-first, notre culture forte (bienveillance, exigence, résilience et data-first) et notre innovation permanente en termes de modes de travail (ex. grille de salaire transparente, formation au changement climatique, transparence sur la stratégie) sont les clés de notre réussite collective.... et de ta réussite avec nous !\nJob Description\nFoxintelligence recherche un\nstagiaire analyst full-stack data & business.\nTu seras rattaché(e) à l'équipe\nDigital & New Verticals\n, responsable de l'intégralité du dataflow sur nos verticales digitales (food delivery et ride hailing) et du lancement de nouvelles industries innovantes telles que le gaming, le Buy-Now-Pay-Later ou les hedge funds.\nTes responsabilités au quotidien:\nParticiper activement au lancement de nouveaux produits (via Tableau, ou la construction d'applications SaaS natives) et contribuer au développement de nouveaux enrichissements de données (par exemple pour notre dataset mobile apps, l'identification de l'application liée à chaque transaction, via du matching de logos)\nContribuer à notre expansion internationale via le développement de nouveaux pays sur les 5 continents, des Etats-Unis au Canada, en passant par l'Inde et le Japon\nParticiper à la gestion de partenariats stratégiques avec des clients globaux et clés pour Foxintelligence, en comprenant leurs besoins et en développant des nouvelles analyses (sous Tableau, ou Google Big Query) qui y répondent\nExplorer et mettre en oeuvre des projets data à fort potentiel stratégique et commercial, tels que le redressement et l'extrapolation de notre panel, ou l'automatisation de nos process de qualité\nRequirements\nCompétences nécessaires (ce qu'il te faut pour réussir sur ce poste):\nSoft Skills\nEsprit analytique et structuré\nPassionné(e) par les défis et à l'aise face à des problèmes nouveaux et complexes\nEnvie d'apprendre, de contribuer spontanément à son environnement et d'aider l'équipe à s'améliorer\nHard Skills\nCapacité à comprendre rapidement le fonctionnement de produits techniques complexes: soit par une expérience pertinente (auto formation, projet perso, etc), soit par une formation adaptée (grande école d'ingénieur ou équivalent à l'étranger, école de commerce avec parcours avancée en data)\nCompétences en code suffisantes pour manipuler de la data (R ou Python)\nExpérience\nTu as une première expérience d'au moins 6 mois en data, opération ou produit dans des startups tech, ou en cabinets de conseil\nCompétences bonus\nHard skills\nMaitrise de Tableau, SQL (idéalement BigQuery), Github, Airflow, Google Cloud Platform\nExpérience\nRôle précédent dans un environnement tech où on passe à l'échelle\nTu as déjà monté un projet entrepreneurial ou personnel\nLadies\nLes études montrent que les femmes ont moins tendance à postuler à une offre d'emploi quand elles n'ont pas toutes les qualifications. Ladies, ne vous mettez pas de barrière et donnez nous la chance de nous faire notre propre avis, nous serons toujours ravis d'échanger avec vous ! Si notre raison d'être vous parle, postulez !\nSelf made data lovers\nLes diplômes c'est bien, les skills c'est mieux et l'expérience t'en donne. Aucun diplôme n'est requis chez nous, ce sont les compétences et l'énergie qui comptent !\nBenefits\nAvantages/ce que nous offrons:\nRémunération compétitive\nRemote friendly mais notre bureau dans le 10e arrondissement à Paris est ouvert si tu veux venir !\nTitres restaurants (swile) : pris en charge à 60% par Fox\nCulture forte et pratiques de management à la pointe (stratégie et résultats financiers transparents, feedback360, grille de salaire innovante et transparente etc.)\nDéroulement des entretiens\nRound 0 : entretien (fit) avec un membre de l'équipe HR\nRound 1 : entretiens (expérience et fit) avec deux leads data analystes de l'équipe\nEtude de cas\nDecision Round : Entretien (fit et vision) avec la manager de l'équipe\nShow more\nShow less",
        "details": {
            "JobDetail": [
                "Remote",
                "Full"
            ],
            "TypeContract": "",
            "Salary": "5",
            "Level": "",
            "Experience": null
        },
        "title": "data analyst",
        "skills": {
            "ProgLanguage": [
                "R",
                "Python"
            ],
            "DataBase": [
                "SQL"
            ],
            "DataAnalytics": [
                "R"
            ],
            "DataVisualisation": [
                "Tableau"
            ],
            "CloudComputing": [
                "Google Cloud Platform"
            ],
            "DBMS": [
                "Big Query",
                "BigQuery"
            ],
            "Automation": [
                "Airflow"
            ],
            "Other": [
                "Statistiques",
                "Cloud"
            ]
        }
    },
    {
        "source": "LinkedIn",
        "company": "Zoomalia",
        "location": "Castets, Nouvelle-Aquitaine, France",
        "link": "https://fr.linkedin.com/jobs/view/data-analyst-h-f-at-zoomalia-3898519325?position=2&pageNum=12&refId=3UAduJ9EGa9s5reXg%2Ffruw%3D%3D&trackingId=oave2oZ4XEuLqQRvWdHkyQ%3D%3D&trk=public_jobs_jserp-result_search-card",
        "description": "Cette offre d’emploi est fournie par Pôle emploi\nDescription\nAnalyse des données (économiques, statistiques, ...) et les restitue en une information opérationnelle et stratégique d'aide à la décision pour la structure, l'entreprise. Peut réaliser et mettre en oeuvre le recueil de données. Peut coordonner une équipe ou diriger un service.\nPROFIL SOUHAITÉ\nExpérience\nDébutant accepté\nSource: Pole emploi (https://www.pole-emploi.fr)\nShow more\nShow less",
        "details": {
            "JobDetail": [],
            "TypeContract": "",
            "Salary": "",
            "Level": "",
            "Experience": null
        },
        "title": "data analyst",
        "skills": {
            "Other": [
                "Statistiques"
            ]
        }
    },
    {
        "source": "LinkedIn",
        "company": "LVMH",
        "location": "Paris, Île-de-France, France",
        "link": "https://fr.linkedin.com/jobs/view/data-analyst-global-travel-retail-assistant-internship-at-lvmh-3904852662?position=3&pageNum=12&refId=3UAduJ9EGa9s5reXg%2Ffruw%3D%3D&trackingId=laxu6ugtThE2OKruQl5j2A%3D%3D&trk=public_jobs_jserp-result_search-card",
        "description": "Moët Hennessy, No. 1 worldwide in Luxury Wines & Spirits, owns prestigious brands such as Moët & Chandon, Dom Pérignon, Hennessy, Glenmorangie, Ruinart and Veuve Clicquot... As a part of LVMH, luxury sector leader, Moët Hennessy is recognized for the quality of its products, its constant search for excellence and innovation. Moët Hennessy realizes more than 90% of its turnover in the export and embodies the French Art de vivre.\nThe Travel Retail works in close relationship with its main customers to deliver unique brand experiences in the biggest Airports and Cruises Lines across the world. In the highly dynamic environment of Travel Retail, our team is dedicated to sharing and promote with passion the excellence of our Wines & Spirits portfolio.\nAs part of the Travel Retail division team based in Paris, you will work closely along the business controllers, with a key focus on business intelligence. You will oversee the existing BI tools we are using, maintaining and developing them. You will directly impact the top-level decisions by providing key analysis. You will be the data expert for all the departments (Finance, Marketing, Sales).\nThis internship is the perfect opportunity to understand and experience the role of the finance function within a highly dynamic Business environment.\nHOW YOU WILL CONTRIBUTE TO MH TR’S SUCCESS\nData management\nEnsure a good maintenance of our data systems (Power BI, Anaplan)\nProvide data reports, analytic insights and clear data visualizations for different stakeholders (Finance, Marketing, Sales)\nTransform the data to deliver insights to the top management\nOrganize trainings for your key users\nMake recommendations on best practices / technological watch\nKey point of contact with our internal business users and external Power BI consultant\nSupport GTR consolidation\nAssist GTR controller on all analysis (Monthly Sell-in, Sell-out, P&L, MMF etc)\nParticipate to all reporting phases of Global Travel Retail (budget, LE1, LE2 and Actuals)\nAd-hoc analysis for top management (Business reviews, customers / product analysis etc)\nWE THINK YOU WILL FIT IN GREAT WITH US IF\nYou are doing business or engineering studies (master level or bac +5)\nExcel has no secret for you, a first experience with Power BI is a must\nYou are problem solving oriented\nYou are a team player\nYou know how to deal with complexity and thrive in a dynamic working environment\nYou speak French and English\nYou show strong analytical skills, with an ability to use multiple data sources to extract the best insights from it\nYou are autonomous, proactive\nWHAT WE OFFER IN RETURN\nWorking with the world-leading luxury company\nEmbrace diversity, equity, and inclusion as core values, fostering an inclusive culture\nWill join a vibrant and creative global community at MH/LVMH\nOffer a hybrid working arrangement and a collaborative environment\nCareer growth opportunities with mobility options within LVMH Group\nStaff enjoy exclusive discounts on Moët Hennessy and other LVMH brands\nInternship of 6 months starting July 2024\nShow more\nShow less",
        "details": {
            "JobDetail": [],
            "TypeContract": "",
            "Salary": "",
            "Level": "",
            "Experience": null
        },
        "title": "data analyst",
        "skills": {
            "DataVisualisation": [
                "Power BI"
            ],
            "EnSoftSkils": [
                "Problem Solving"
            ]
        }
    },
    {
        "source": "LinkedIn",
        "company": "eXalt",
        "location": "Lille, Hauts-de-France, France",
        "link": "https://fr.linkedin.com/jobs/view/data-analyst-h-f-%40exalt-lille-at-exalt-3842174165?position=4&pageNum=12&refId=3UAduJ9EGa9s5reXg%2Ffruw%3D%3D&trackingId=vXxmvLhqT6a0f%2Bpeq4Ma%2Fg%3D%3D&trk=public_jobs_jserp-result_search-card",
        "description": "Descriptif du poste\neXalt Lille recherche son/sa nouveau/elle\nData Analyst\npour aller à la conquête de nouveaux projets ! Vous évoluerez dans un contexte multi sociétés et challengeant.\nVous serez rattaché(e) à notre bureau Lillois.\nVos principales missions seront de :\nComprendre les problématiques métiers et les traduire de manières analytiques\nExtraire les données nécessaires à l’analyse\nDéfinir et réaliser le nettoyage de la base de données\nS’assurer la qualité des données tout au long de leur traitement\nAnalyser et exploiter les données\nCréer des dashboards via des outils de visualisations\nEffectuer une veille sur les nouvelles technologies et solutions logicielles d’analyse des données\nPourquoi nous rejoindre ?\nLa force d’eXalt consiste à s’organiser en interne comme une organisation produit et à cultiver. Nous avons à cœur de vous accompagner tout au long de votre carrière grâce à nos formations et à notre accompagnement au passage de certifications. Animés par nos valeurs que sont la cocréation, la do-ocratie et le permanent bêta, nous vous permettrons de vous épanouir dans un environnement dynamique et favorisons votre proactivité et esprit d’initiative !\nProfil recherché\nNous recherchons avant tout une personne animée par l’esprit et l’ADN d’eXalt ☀️ ayant l’envie de prendre part à un superbe challenge et à notre aventure !\nVous êtes diplômé(e) d’un Bac+5\nVous bénéficiez d’une expérience d’au moins 3 ans en tant que Data Analyst\nVous avez une expertise en base de données et gestion de base de données (SQL/ NoSQL)\nVous maitrisez des outils de data visualisation (Tableau, Qlikview, PowerBI) et/ou des outils de fouille et analyse de données (Dataiku)\nVous avez une aisance rédactionnelle & relationnelle\nVous avez une passion pour les chiffres et le goût pour l’innovation\nVous êtes reconnu(e) pour votre rigueur, votre organisation et votre adaptabilité\nDéroulement des entretiens\nUn premier entretien avec un/e Digital Sales Manager pour se découvrir mutuellement\nUn second entretien avec un/e associé/e co-fondateur/rice pour aller plus loin dans les problématiques abordées en mission et les enjeux maîtrisés\nUn dernier entretien avec un Consultant Senior, pour faire le point sur votre positionnement et vos compétences\nNous sommes agiles !\nCes entretiens peuvent se faire en visio et/ou en présentiel !\nVenez nous rencontrer autour d’un café dans nos locaux, situés: 57 rue Nationale, 59 800 Lille ☕\nQui sont-ils ?\nCabinet de conseil en Transformation Digitale, eXalt est avant tout une formidable aventure humaine, et une communauté de plus de 950 collaborateurs, basés à Paris, Lyon, Lille, Nantes, Rennes, Bordeaux, Aix-en-Provence, Bogota, New-York et Madrid.\nFondée en juillet 2018 autour des valeurs d’intrapreneuriat, de co-apprentissage et de co-construction, eXalt inscrit son développement dans un engagement fort auprès de ses clients et de ses équipes. Multi-spécialiste, le groupe décline son modèle dans différents domaines à travers ses filiales dédiées :\nLe Product Management & la Gestion de Projet au sein d’eXalt Flow\nLa Finance de Marché au sein d’eXalt Fi,\nLa Tech au sein d’eXalt IT,\nLa Cybersécurité au sein d’eXalt Shield\nLa Data au sein d’eXalt Value\neXalt Lille, filiale du groupe spécialisée sur les métiers du Product & Project Management, recherche son/sa nouveau/elle\nData Analyst\npour aller à la conquête de nouveaux projets ! Vous évoluerez dans un contexte multi sociétés et challengeant.\nVous serez rattaché(e) à notre bureau lillois.\nShow more\nShow less",
        "details": {
            "JobDetail": [
                "Senior"
            ],
            "TypeContract": "",
            "Salary": "",
            "Level": "Bac+5",
            "Experience": "3 an(s)"
        },
        "title": "data analyst",
        "skills": {
            "DataBase": [
                "SQL",
                "NoSQL"
            ],
            "DataVisualisation": [
                "Tableau"
            ],
            "EnSoftSkils": [
                "Initiative"
            ]
        }
    },
    {
        "source": "LinkedIn",
        "company": "Notariat Services",
        "location": "Arnac-Pompadour, Nouvelle-Aquitaine, France",
        "link": "https://fr.linkedin.com/jobs/view/data-analyst-h-f-at-notariat-services-3910209780?position=5&pageNum=12&refId=3UAduJ9EGa9s5reXg%2Ffruw%3D%3D&trackingId=JVHqa3jl4WfnUViVon5Ecw%3D%3D&trk=public_jobs_jserp-result_search-card",
        "description": "Cette offre d’emploi est fournie par Pôle emploi\nDescription\nLe Groupe Notariat Services, fort de 55 ans d'expérience en communication immobilière notariale, recrute une.e Data Analyst. Ce poste est basé à POMPADOUR, à 45 min de Limoges et de Brive. Vous aurez pour mission d'analyser et interpréter des données complexes, de formuler des insights pertinents, et de contribuer à la prise de décision stratégique au sein de l'entreprise. Vous participerez activement à l'extraction, au traitement, à l'analyse et à la visualisation des données. Responsabilités Principales : 1. Collecte de Données : - Identifier et collecter les données nécessaires à l'analyse. - Collaborer avec les équipes concernées pour assurer une collecte de données efficace. 2. Traitement des Données : - Transformer les données brutes en formats exploitables pour l'analyse. 3. Analyse Statistique : - Utiliser des techniques statistiques pour analyser les tendances, les corrélations et les modèles dans les données. - Effectuer des analyses descriptives et prédictives. 4. Visualisation des Données : - Créer des visualisations claires et informatives pour faciliter la compréhension des résultats. - Utiliser des outils de visualisation tels que Tableau, Power BI, etc. 5. Rapports et Présentations : - Préparer des rapports réguliers sur les analyses effectuées. - Présenter les résultats de manière compréhensible aux parties prenantes. 6. Collaboration Interfonctionnelle : - Collaborer avec les équipes métier pour comprendre leurs besoins et fournir des solutions adaptées. - Travailler en étroite collaboration avec les équipes informatiques pour assurer l'intégration des données. 7. (En plus : Modélisation et Machine Learning ) - Développer des modèles prédictifs en utilisant des algorithmes de machine learning. - Évaluer et améliorer la performance des modèles existants. Compétences Requises : - Compétences en programmation (Python, R, etc.). - Maîtrise des outils et langages liés à la manipulation de données (SQL, etc.). - Connaissance des techniques d'analyse statistique (et de machine learning). - Expérience dans la création de visualisations de données. - Excellentes compétences en communication et capacité à présenter des résultats de manière compréhensible. - Capacité à travailler de manière autonome et en équipe. VOTRE CV DOIT ÊTRE ACCOMPAGNÉ D'UNE LETTRE DE MOTIVATION\nPROFIL SOUHAITÉ\nExpérience\n2 An(s)\nSavoirs et savoir-faire\nAdapter les outils de traitement statistique de données\nRédiger l'information produite\nPrésenter et diffuser les résultats des études réalisées\nRéaliser une étude\nDéfinir et faire évoluer des procédés de traitement de l'information\nSavoir-être professionnels\nFaire preuve de rigueur et de précision\nPrendre des initiatives et être force de proposition\nTravailler en équipe\nSource: Pole emploi (https://www.pole-emploi.fr)\nShow more\nShow less",
        "details": {
            "JobDetail": [],
            "TypeContract": "",
            "Salary": "",
            "Level": "",
            "Experience": "55 an(s)"
        },
        "title": "data analyst",
        "skills": {
            "ProgLanguage": [
                "R",
                "Python"
            ],
            "DataBase": [
                "SQL"
            ],
            "DataAnalytics": [
                "R"
            ],
            "DataVisualisation": [
                "Power BI",
                "Tableau"
            ],
            "Other": [
                "Statistiques",
                "Machine Learning"
            ],
            "EnSoftSkils": [
                "Communication",
                "Collaboration"
            ]
        }
    },
    {
        "source": "LinkedIn",
        "company": "Envu",
        "location": "Lyon, Auvergne-Rhône-Alpes, France",
        "link": "https://fr.linkedin.com/jobs/view/senior-data-analyst-at-envu-3913350840?position=6&pageNum=12&refId=3UAduJ9EGa9s5reXg%2Ffruw%3D%3D&trackingId=c2M3Q0VRNkAz32ebgDZ86g%3D%3D&trk=public_jobs_jserp-result_search-card",
        "description": "We’re Hiring!\nSenior Data Analyst (all genders)\nAt Envu, we partner with our customers to design world-class, forward-thinking innovations that protect and enhance the health of environments around the world. We offer dedicated services in: Professional Pest Management, Forestry, Ornamentals, Golf, Industrial Vegetation Management, Lawn & Landscape, Mosquito Management, and Range & Pasture.\nEnvu brings together diverse points of view to look beyond chemistry and dare to explore new paths forward. Guided by our inclusive culture, we embrace change and flexibility, tackling our customers’ toughest challenges proactively, passionately and with an entrepreneurial spirit.\nWe pursue our ambitions collaboratively because we know that a unified and empowered team is an unstoppable force, allowing us to achieve our vision of healthy environments for everyone, everywhere. Join Us.\nFUNCTION\n: Senior Data Analyst\nLOCATION\n: Lyon, France\nJOB\nTYPE\n: Permanent\nROLE\nSENIORITY\n: Manager\nGET TO KNOW YOUR AREA:\nJoin the Finance Data Analytics team to enhance data analysis and visualization tools to drive financial strategy, enhance forecasting accuracy, and provide critical insights that support key business decisions.\nFocus on leveraging the capabilities of our Azure Data lake and the Microsoft Power Platform (Power BI, PowerApps, and Power Automate) to enhance our reports, process automation, and custom business applications.\nYOUR MISSION WILL BE TO:\nDesign, develop and maintain complex Power BI dashboards for decision-making while taking into account the needs from the different stakeholders (Finance, Business, Marketing)\nPerform data modeling, transformation, and analytics using SQL and DAX\nContinuously evaluate and improve existing processes and systems using insights derived from data analysis and automation projects\nDevelop custom business applications using Power Platform, integrating with various data sources and APIs to fulfill unique business requirements\nActively contributing to the expertise level and competencies of the Finance Data & Analytics team\nCollaborate with other departments to identify opportunities for process improvement and automation in reporting workflows\nARE YOU READY FOR THE ROLE?\nMain requirements:\nMaster's degree in a relevant field such as Computer Science, Statistics, or Data Analytics. Experience in Finance is required\nMinimum of 5 years of experience in a data analyst role, with a proven experience in data visualization using Power BI\nExperience in writing scripts, and queries using SQL\nExpertise in Power Platform is a strong plus\nSolid understanding of data governance, data management, and data visualization best practices\nExcellent analytical and problem-solving skills, with the ability to translate complex data into actionable insights\nEnvu is committed to diversity in all aspects for all employees and candidates, regardless of ethnicity, color, race, religion, origin, age, gender, gender identity or expression, sexual orientation, or other conditions. And all opportunities are open to people with disabilities.\nBy applying for this position, you agree that your personal data are going to be processed and recorded by Envu for recruitment purposes only. For candidates who are not selected for this position, personal data will be kept for a period of two years and then permanently deleted.\nWe will soon be in touch to let you know the next steps to be taken!\nShow more\nShow less",
        "details": {
            "JobDetail": [
                "Senior"
            ],
            "TypeContract": "",
            "Salary": "",
            "Level": "",
            "Experience": null
        },
        "title": "data analyst",
        "skills": {
            "DataBase": [
                "SQL"
            ],
            "DataVisualisation": [
                "Power BI"
            ],
            "CloudComputing": [
                "Azure"
            ],
            "EnSoftSkils": [
                "Flexibility"
            ]
        }
    },
    {
        "source": "LinkedIn",
        "company": "Capgemini",
        "location": "Nantes, Pays de la Loire, France",
        "link": "https://fr.linkedin.com/jobs/view/business-analyst-data-nantes-at-capgemini-3803937789?position=7&pageNum=12&refId=3UAduJ9EGa9s5reXg%2Ffruw%3D%3D&trackingId=hhi3cfaxZ94Cn0pSipWkhw%3D%3D&trk=public_jobs_jserp-result_search-card",
        "description": "Capgemini\nChoisir Capgemini, c'est choisir une entreprise où vous serez en mesure de façonner votre carrière selon vos aspirations, où vous serez soutenu et inspiré par une communauté d’experts dans le monde entier, où vous pourrez réécrire votre futur. Rejoignez-nous pour redéfinir les limites de ce qui est possible, contribuer à libérer la valeur de la technologie pour les plus grandes organisations et participez à la construction d’un monde plus durable et inclusif.\nVos missions :\nIntégré(e) au sein d’une équipe projet BI, Big Data ou Data Gouvernance pour des clients intervenant dans des secteurs d'activités divers, vous serez notamment en charge des missions suivantes :\nDéfinir les besoins réels de nos clients, et déterminer la meilleure manière d’y répondre en utilisant la Data\nConduire des ateliers avec le client sur les aspects fonctionnels et techniques\nRédaction des User Stories et/ou les spécifications fonctionnelles , Rédaction de spécifications détaillées\nSupport à la recette métier\nCoordination d’équipes pluri disciplinaire\nPilotage et gestion de projets.\nVotre profil :\nDiplôme d’ingénieur ou équivalent universitaire\nMinimum 3 ans d’expérience\nEncadrement d'équipe\nAnglais courant\nExcellentes qualités d’écoute et d’analyse,\nMaîtrise de la rédaction de documentation fonctionnelle, de la méthodologie projet (Scrum),\nConnaissances de la modélisation de données, du langage SQL et d'un ou de plusieurs outils de reporting tels que Power BI, Tableau ou Qlik Sense.\n3 raisons de nous rejoindre :\nQualité de vie au travail : accord de télétravail en France et à l’international, accord sur l’égalité\nprofessionnelle, la parentalité, l’équilibre des temps et la mobilité durable.\nApprentissage en continu : certifications et formations en libre accès, accompagnement sur mesure avec votre carreer manager, parcours d’intégration sur 9 mois.\nAvantages groupe & CSE : plan actionnariat, activités à tarifs préférentiels, remboursement partiel\nvacances, remboursement de votre abonnement sportif ou culturel.\nNos engagements et priorités :\nLe groupe Capgemini encourage une culture inclusive dans un cadre multiculturel et handi-accueillant. En nous rejoignant, vous intégrez un collectif qui valorise la diversité, développe le potentiel de ses talents, s’engage dans des initiatives solidaires avec ses partenaires, et se mobilise pour réduire son impact environnemental sur tous ses sites et auprès de ses clients.\nCapgemini\nCapgemini est un leader mondial, responsable et multiculturel, regroupant près de 350 000 personnes dans plus de 50 pays. Fort de 55 ans d’expérience, nous sommes un partenaire stratégique des entreprises pour la transformation de leurs activités en tirant profit de toute la puissance de la technologie et des innovations dans les domaines en perpétuelle évolution tels que le cloud, la data, l’Intelligence Artificielle, la connectivité, les logiciels, l’ingénierie digitale ou les plateformes.\nGet The Future You Want* | www.capgemini.com/fr-fr\n*Capgemini, le futur que vous voulez\nShow more\nShow less",
        "details": {
            "JobDetail": [],
            "TypeContract": "",
            "Salary": "",
            "Level": "",
            "Experience": "3 an(s)"
        },
        "title": "data analyst",
        "skills": {
            "DataBase": [
                "SQL"
            ],
            "DataVisualisation": [
                "Power BI",
                "Tableau"
            ],
            "Other": [
                "Cloud",
                "Big Data"
            ]
        }
    },
    {
        "source": "LinkedIn",
        "company": "Prisma Media",
        "location": "Île-de-France, France",
        "link": "https://fr.linkedin.com/jobs/view/data-analyst-yield-f-h-cdi-at-prisma-media-3918307053?position=9&pageNum=12&refId=3UAduJ9EGa9s5reXg%2Ffruw%3D%3D&trackingId=zyBZt5P2r%2BuaJ8TiMuZTWw%3D%3D&trk=public_jobs_jserp-result_search-card",
        "description": "Vos Missions ?\nAu sein de la cellule digitale de Prisma Media Solutions, votre objectif est de traiter et d’analyser l'ensemble des données d'inventaire et de revenus, sur les formats publicitaires et sur les partenaires.\nPoussé par la volonté d'être toujours à la pointe, nous testons énormément d’innovations marché afin d’avoir l’environnement le plus performant.\nVos missions seront les suivantes :\nAnalyse des KPI clé de la performance (Visibilité, CPM, …)\nConstruction et développement d’outils d’aide à la décision et suivi des performances\nMaintien et développement des différents dashboard métier\nEchange avec les équipes Adops, IT et Traffic acquisition pour l’orientation de la stratégie monétisation et acquisition\nSuivi et analyse des A/B Test\nAide à l'optimisation des remplissages, des revenus et des mesures de performances\nD'autres missions pourront être confiées en fonction de l'activité du service.\nVotre Profil ?\nCe poste est fait pout vous si :\nDiplômé.e d’université ou d’école supérieure (BAC+5), vous avez une forte appétence pour l'analyse de données.\nDynamique, vous apprécierez évoluer dans un environnement passionnant en pleine transformation\nVous êtes autonome et savez être force de proposition\nExcel n'a aucun secret pour vous\nLa connaissance du langage SQL ou de l’univers de la publicité seraient un plus.\nVotre future entreprise ?\nLe groupe Prisma Media accompagne le quotidien des Français depuis plus de 40 ans pour les divertir et les informer. Il est aujourd’hui le leader de la presse magazine et des médias en ligne. Chaque mois, 2 Français sur 3 consultent une marque de Prisma Media. Avec un portefeuille de 35 marques de référence, le groupe est présent sur les principaux segments grand public et luxe. Prisma Media a pour ambition de devenir le leader européen des marques médias désirables.\nPrisma Media est aussi un groupe qui s’engage :\nDes marques engagées auprès d’associations pour faire la différence :\nLe Rire Médecin, La Maison des Femmes ou encore la collecte de nos magazines pour l’APHP\nDes référents handicap et LGBTQIA+ pour que tous se sentent accompagné\n100% des papiers de nos magazines sont issus de forêts éco-gérées\nEt tellement d’autres actions à découvrir !\nLes petits plus chez nous ?\nNos chiffres et nos marques ne sont pas des arguments suffisants pour attirer votre attention ? Ne vous en faites pas, nous en avons d’autres !\nRémunération selon profil\n6 semaines de congés + 3 semaines de RTT\nDu télétravail\nUne conciergerie : pressing, coiffeur, boutique…\nCafé et thé gratuits, cantine de qualité avec des produits de saisons cuisinés sur place\nDes formations & conférences mensuelles sur des thématiques diverses : réseaux sociaux, développement personnel, intelligence artificielle…\nDes events annuels : Garden party, journée, Vis ma vie, afterworks…\nShow more\nShow less",
        "details": {
            "JobDetail": [],
            "TypeContract": "",
            "Salary": "",
            "Level": "Bac+5",
            "Experience": "40 an(s)"
        },
        "title": "data analyst",
        "skills": {
            "DataBase": [
                "SQL"
            ]
        }
    },
    {
        "source": "LinkedIn",
        "company": "GN Group",
        "location": "Villeneuve-d’Ascq, Hauts-de-France, France",
        "link": "https://fr.linkedin.com/jobs/view/data-analyst-at-gn-group-3887257536?position=10&pageNum=12&refId=3UAduJ9EGa9s5reXg%2Ffruw%3D%3D&trackingId=HH6kspxd23vDpZ4edAKA4g%3D%3D&trk=public_jobs_jserp-result_search-card",
        "description": "Lille\nSteelSeries\nest un groupe danois, leader mondial spécialisé dans les équipements de jeu vidéo haute performance utilisés par les joueurs professionnels.\nPionniers des compétitions de jeux vidéo et eSports, nous améliorons les performances grâce à des innovations et des technologies de premier ordre.\nSteelSeries France\n, anciennement\nNahimic\n, fait partie depuis 3 ans de la division Software de\nSteelSeries\n. Notre équipe de spécialistes en traitement audio et génie logiciel est basée en France, à Singapour et à Taiwan. Nous développons la prochaine génération de logiciels audio, combinant technologies de pointe et innovations pour booster l’expérience de jeu des gamers. Nous équipons les PC et périphériques des plus grandes marques telles que MSI, Dell, Asus, Huawei et Lenovo.\nNotre site français, basé à Villeneuve d’Ascq, compte 40 collaborateurs dont 15 Développeurs.\nNous avons des bureaux mondiaux en Amérique du Nord, en Europe et en Asie, offrant une gamme complète de produits conçus pour les jeux.\nSteelSeries\nconnaît une croissance rapide et, en janvier 2022, nous avons intégré le Groupe\nGN Store Nord.\nLa forte croissance du marché du jeu vidéo et le développement du télétravail sont autant de boosters pour notre activité : Aujourd’hui il nous faut renforcer nos équipes pour pouvoir continuer à satisfaire les demandes de nos clients !\nNotre Poste:\nNous recrutons notre futur Data Analyst. En tant que partenaire du business et expert en analyse de données, vous avez un rôle clé, dans la transformation digitale de notre offre de Software & Products (Business Unit). Software & Products de SteelSeries se concentre sur la construction d’un écosystème de produits et services logiciels pour la communauté des gamers du monde entier.\nNotre logiciel GG incluant Engine, Sonar, Moments & 3D Aim Trainer, est aujourd’hui utilisé par des millions de gamers. Nous souhaitons continuer d’améliorer nos produits et nos logiciels afin de fidéliser et acquérir de nouveaux utilisateurs.\nPersuadés que la Data est un élément clé dans cette amélioration, nous sommes à la recherche d’un Data Analyst, afin de nous accompagner sur la compréhension de nos produits et sur l’acquisition, l’activation et la conversion de nouveaux utilisateurs.\nAu sein de l’équipe Data, et en étroite collaboration avec notre Lead Data Engineer, vous aurez comme principales responsabilités :\nRencontrer les parties prenantes de la gestion et de la conception de produits, de l’ingénierie et de SteelSeries afin de comprendre les besoins inter fonctionnels des équipes et de prioriser les analyses et metrics des produits ;\nAccompagner les équipes Produits & Marketing afin de les aider à améliorer l’expérience Produit pour développer notre base clients ;\nTraduire et transformer les questions business en cas d'étude analytiques en questionnant, challengeant, et accompagnant les métiers dans la compréhension et l’exploitation des données ;\nTravailler de manière proactive et collaborative avec les équipes Produits et Marketing pour s’assurer, valider que les mesures, les KPIs et les analyses répondent aux exigences du produit, du marketing et de SteelSeries ;\nUtiliser votre expertise Data afin de valoriser nos Data internes vers un objectif de croissance produit dans une dimension client.\nLa dimension interculturelle est important dans cette équipe (échanges quotidiens avec nos équipes basées aux USA, en Europe et en Asie), nous sommes des collaborateurs impliqués et proactifs et très passionnés par les jeux vidéo et la technologie grand public.\nVous êtes expérimenté, adaptable, énergique et avait l’envie de participer activement à l’analyse et la consolidation de notre portefeuille produits pour proposer les meilleurs produits aux joueurs avec un impact commercial direct énorme et fédérer de plus en plus de joueurs autour de SteelSeries.\nNos Data Stack:\nSnowflake/ Data warehouse & Amazon S3 / Data Lake\nDbt pour notre ETL\nSegment pour notre Customer Data Platform\nSQL & Python pour notre data stack applicatif\nRedash et Power BI pour la dataviz\nLe profil que nous recherchons :\nVous êtes un véritable passionné de la Data et au-delà de votre niveau de formation :\nVous êtes issu(e) d’une formation supérieure de niveau BAC +5 en école d’ingénieur ou de commerce et bénéficiez d'une expérience de 5 ans minimum dans la Data Analyse\nVous avez en partie construit votre expérience dans des problématiques d’acquisition et de croissance client dans des domaines digitaux (idéalement produits Logiciels),\nCapacité d’analyse croisée sur différents domaines : Logiciels, e-Commerce et produits,\nExpérience en SQL & Python (ou similaire) ,\nExpérience avec les outils de Dataviz ,\nBonne compréhension des structures, des principes, des théories et des meilleures pratiques des bases de données,\nExpérience avec des méthodes marketing digitales (A/B testing, groupe témoin, clustering, …)\nAnglais nécessaire pour échanger avec nos collègues aux USA, Asie & Europe : La collaboration est le maître mot de notre façon de travailler !\nVous êtes curieux et agile dans votre fonctionnement,\nBon communicant, vous savez adapter votre discours en fonction de vos interlocuteurs et avez un sens aigu du service client (interne / externe),\nVous avez le sens de l’excellence, du partage,\nVous avez envie de travailler dans l’univers du Gaming,\nVous êtes ambitieux et avez envie de faire partie d’une aventure qui repousse les limites du gaming et du développement produits.\nC’est un +: Si vous avez déjà travaillé dans des équipes de Software grand public, Web ou e-commerce,de préférence avec des équipes produit et / ou marketing et si vous avez connaissance des packages d'analyse et de modélisation de la science des données en Python et / ou R !\n« Steelseries s'engage en faveur de la diversité culturelle, l'égalité hommes-femmes et l'emploi des travailleurs handicapés. »\nNous vous proposons de rejoindre une équipe de talents à taille humaine qui vous attend déjà ! Où les choses bougent rapidement Et qui bénéficie de l’appui d’un groupe solide et reconnu et nous ouvre de nombreuses perspectives.\nCe que nous proposons :\nUn cadre de travail moderne et innovant avec des locaux à côté de Lille et des conditions de travail plus qu’agréables (horaires aménagés, télétravail, salle de jeux video, salle de sport..) :\nsalaire attractif\nRTT\nmutuelle (familiale) prise en charge à 100%\ndes tickets restos\ndes primes sur objectifs (jusqu’à 2 mois de salaire)\nPossibilité de travailler en remote (3 j/hebdo)\nEn vélo, en métro ou en voiture : Venez nous rejoindre à la\nPilaterie de Villeneuve d’Ascq\n(à 6 minutes du centre ville de Lille et tout à côté des embranchements routiers)\nShow more\nShow less",
        "details": {
            "JobDetail": [
                "Remote"
            ],
            "TypeContract": "",
            "Salary": "100, 100",
            "Level": "",
            "Experience": "3 an(s)"
        },
        "title": "data analyst",
        "skills": {
            "ProgLanguage": [
                "R",
                "Python"
            ],
            "DataBase": [
                "SQL"
            ],
            "DataAnalytics": [
                "R"
            ],
            "DataVisualisation": [
                "Power BI"
            ],
            "DBMS": [
                "Snowflake"
            ],
            "EnSoftSkils": [
                "Collaboration"
            ]
        }
    },
    {
        "source": "LinkedIn",
        "company": "euRHasi",
        "location": "Paris, Île-de-France, France",
        "link": "https://fr.linkedin.com/jobs/view/data-analyst-h-f-at-eurhasi-3919187688?position=1&pageNum=15&refId=nmjl8wtZkD%2F%2FLwpmcHztLg%3D%3D&trackingId=tf2e1FWGJSer%2B7hChtmpaQ%3D%3D&trk=public_jobs_jserp-result_search-card",
        "description": "EURHASI recrute pour son client un\nData Analyst (H/F)\nNotre client est un groupe de production d’artistes\nLe client n’accepte pas de candidatures nécessitant des démarches administratives pour une autorisation de travail (permis de séjour, permis de travail, autorisations diverses ...)\nMission\nSous la responsabilité de la Directrice du Service Billetterie, le Data Analyst (H/F) aura les missions suivantes, sans que celles-ci ne soient exhaustives :\nOptimisation et analyses business\nAnalyses régulières de la performance billetterie et site web de nos artistes et salles durant la vie commerciale des manifestations\nOptimisation des canaux de ventes selon les performances de chacun\nRecommandations d’action billetterie en fonction des résultats obtenus\nAnalyses Adhoc selon les demandes du département ou Groupe.\nGestion de l’outil dédié au reporting et à l’analyse des ventes\nFinalisation, évolution et optimisation de l’outil dédié mis en œuvre au sein du service\nIntégration progressive de sources de données externes à la billetterie\nIntégration progressive de l’outil auprès des divers interlocuteurs et accompagnement dans l’adoption de cet outil\nCollaboration avec les divers services pour création et optimisation des dashboards et suivi des Kpi de chaque activité\nMise en place de grilles tarifaires et optimisation des revenus durant la vie commerciale des manifestations selon plusieurs critères :\nAnalyse du potentiel de l’artiste, du spectacle ou de la salle.\nAnalyse de l’historique billetterie d’une précédente tournée ou spectacle similaire\nBenchmark d’artistes ou spectacles similaires, de notoriété équivalente ou de spectacles similaires\nMise en place de grilles tarifaires évolutives durant la vie commerciale des manifestations afin de mieux coller à la demande et au remplissage par catégorie.\nFaire découler de ces grilles tarifaires des budgets billetteries et points d’atterrissage potentiels.\nProfil\nProfil recherché\nIssu(e) d’une formation BAC+4 minimum,\nVous maitrisez la suite Office (Word / Excel / Outlook)\nVous maitrisez Tableau ou un outil similaire d’analyse de données\nVous avez un bon esprit de synthèse et d’analyse\nVous êtes rigoureux(se), réactif(ve), organisé(e), précis(e)\nVous avez un bon relationnel et vous savez faire preuve d’initiatives\nVous aimez le travail en équipe\nCompétences minimum attendues :\nExpérience de 3 ans en tant que Data Analyst et non pas \"développeur\" ( en dehors de stage et alternance )\nExcellent esprit synthétique/d'analyse et très à l'aise avec les chiffres\nTrès bon relationnel\nArrive à vulgariser facilement des données complexes\nProfil qui connait le secteur du divertissement ou du moins qui démontre un vrai intérêt\nProfil qui a déjà travaillé dans un secteur complexe, rythme soutenu (divertissement, grande distribution, etc)\nA noter : poste en lien direct avec la Directrice Billetterie (données complexes à traiter) + lien en direct avec le DG\nInformations contractuelles\nLes avantages\nCongés additionnels\nTélétravail 1 jour de TT ( lundi - avant la validation de la période d’essai ) / 2 jours de TT après la validation de période d’essai de TT\nMutuelle d'entreprise\nTickets restaurant\nRemboursement de transport à 70%\nShow more\nShow less",
        "details": {
            "JobDetail": [],
            "TypeContract": "",
            "Salary": "",
            "Level": "",
            "Experience": "3 an(s)"
        },
        "title": "data analyst",
        "skills": {
            "DataVisualisation": [
                "Tableau"
            ],
            "EnSoftSkils": [
                "Collaboration"
            ]
        }
    },
    {
        "source": "LinkedIn",
        "company": "Plus que PRO ⭐⭐⭐⭐⭐",
        "location": "Schiltigheim, Grand Est, France",
        "link": "https://fr.linkedin.com/jobs/view/data-analyst-h-f-at-plus-que-pro-%E2%AD%90%E2%AD%90%E2%AD%90%E2%AD%90%E2%AD%90-3910218289?position=2&pageNum=15&refId=nmjl8wtZkD%2F%2FLwpmcHztLg%3D%3D&trackingId=IxHmf727HJhWsO%2B09HCsxQ%3D%3D&trk=public_jobs_jserp-result_search-card",
        "description": "À propos de nous\nDevenez acteur du changement et rejoignez un Leader sur son marché :\nProtégez les consommateurs,\nValorisez le savoir-faire des TPME Françaises !\nConstruisons ensemble un monde plus sûr pour les Consommateurs et plus valorisant pour les Entrepreneurs.\nDécouvrez un secteur en pleine expansion et vivez avec nous une histoire pleine de succès !\nMission\nTu as la passion de la data et des chiffres en général ?\nTu aimes observer, décrire, analyser et décortiquer de l’info, des tableaux et des flux de données ?\nTu aimerais participer à la création et l’optimisation d’un système d’information au service de la performance de Plus que PRO ?\nBienvenue chez Plus que PRO !\n« Un environnement de travail qu’il est chouette »\nIntégrer Plus que PRO, c’est avoir l’opportunité d’évoluer au sein d’une entreprise « fun & serious ». Concrètement, cela signifie que pas une journée ne se passe sans que nous puissions échanger dans la bonne humeur et le second degré.\nMais cela veut aussi dire qu’il y a des choses que nous prenons très à cœur, parmi lesquelles : l’atteinte de nos objectifs, le goût du challenge, la qualité de la collaboration et la confiance que nous portent nos différents interlocuteurs.\nTu participeras à l’analyse de l’activité des différents pôles d’activité de Plus que PRO.\nTu participeras à la création d’outil de mesure de la performance et d’aide à la décision au bénéfice de chaque responsable de pôle.\nTu soutiendras les responsables de pôle à la mise à jour des tableaux de bord et à la construction des remontées d’information aux dirigeants.\nTu auras l’opportunité de mener diverses analyses ad-hoc en fonction des besoin des équipes et formuler des recommandations & des alertes à destination des BU & de la direction.\nProfil\nDe formation initiale : École d’ingénieur / École de commerce dominante Finance / Gestion et/ ou en préparation d’un diplôme master en data management.\nTu recherches une expérience dans les métiers de la Gestion, des Analytics & de l’Innovation.\nTu fais preuve de curiosité, d’une bonne culture technologique et d’un intérêt pour le développement de solutions de traitement de données.\nTu as une forte appétence pour l’analyse et la manipulation de données.\nIdéalement, tu bénéficies d’une expérience professionnelle préalable dans un environnement demandant une forte capacité d’adaptation et d’analyse.\nTu as une bonne capacité à traduire les analyses dans des outils de mesure et de communication afin de les diffuser pour aider le pilotage et la prise de décision.\nRéférence de l'offre : g5fwk6y375\nShow more\nShow less",
        "details": {
            "JobDetail": [],
            "TypeContract": "",
            "Salary": "",
            "Level": "",
            "Experience": null
        },
        "title": "data analyst",
        "skills": {
            "EnSoftSkils": [
                "Communication",
                "Collaboration"
            ]
        }
    },
    {
        "source": "LinkedIn",
        "company": "Equativ",
        "location": "Paris, Île-de-France, France",
        "link": "https://fr.linkedin.com/jobs/view/data-analyst-at-equativ-3910669096?position=3&pageNum=15&refId=nmjl8wtZkD%2F%2FLwpmcHztLg%3D%3D&trackingId=R7JjLGn7MOEFymtoEts6nA%3D%3D&trk=public_jobs_jserp-result_search-card",
        "description": "👫 About the team\nHelping the company be fully data-driven is not just a buzzword, it is our mission at Equativ. We, the Data Analytics team at Equativ, maximize Equativ’s efficiency by enabling easy and permanent access to quality data, valuable insights & rigorous thinking. Our responsibility is to ensure our local and central teams, clients and partners, make informed business decisions. To do so, we leverage huge volumes of data (Equativ handles 150Bn Auctions per day) in a state-of-the-art tech stack (AirFlow, Snowflake, Tableau…) in order to provide actionable insights to all teams at Equativ!\n✏️ What you'll do\nCollaborate with the Product Analytics Manager and a dynamic team of 15 analysts within the Analytics team\nSupport the product team in solving challenges through advanced analyses, providing actionable insights and sanity checks on new features, and prioritizing roadmap topics based on estimated business value\nCreate and maintain performance dashboards used by product and service teams, enabling them to better understand their customers’ performance and achieve their objectives\nDevelop your technical knowledge of our product, growing to proactively identify areas of concern, and propose corrective actions to optimize client setups and buying strategies and ultimately drive Equativ’s revenue growth\nDepending on your interests and skills, you may also:\nDevelop and maintain data tools tailored to specific use cases\nParticipate in sourcing, continuously enriching our databases with new internal data\n🤝 Collaboration\nEngage with Product, Product Marketing, and R&D leaders and teams to align on recent deliverables, understand upcoming needs, and prioritize effectively\nWork closely with cross-functional teams serving our B2B Marketplace, driving actions based on data-driven insights\nEnsure widespread adoption of metrics and reports through effective internal go-to-market strategies (beta-testing, communication, training, and continuous optimization)\n🤩 Why You Should Join Us:\nOpportunity to work with modern data tools (Snowflake, Tableau, Airflow, Python, Google BigQuery) and technologies in an intellectually stimulating environment\nCollaborative culture that encourages professional growth and development\nImpactful role with opportunities to drive tangible results and contribute to company growth\n💪 About you\nYou are curious, love solving problems, and want to develop your autonomy and expertise\nExcellent communication skills and ability to form recommendations and present insights to both technical and non-technical audiences\nMaster’s degree or higher in a quantitative or business field (Statistics, Mathematics, Econometrics, Economics, Finance, etc.)\nYou are fluent in English\nTechnical knowledge of SQL is a must\nBasic knowledge of reporting software (Tableau)\nPython and other programming languages are a plus\n👋 About us\nEquativ is the new single name for Smart Adserver, DynAdmic, LiquidM and Nowtilus — four proven innovators in advertising technology. The vertically integrated company provides brand and privacy-safe solutions that empower its clients to achieve maximum impact while respecting the rights of consumers. The union combines client expertise and engineering excellence to serve the interests of both the supply- side and demand-side with equal professionalism and technical sophistication.\nHeadquartered in Paris and New York, Equativ operates globally with a team of more than 550 people in 20 offices. Equativ offers the market its own independent ad server, SSP, buyer tools, and media services to fulfill the promise of advertising technology. Learn more at Equativ.com.\nThe company is ranked on the Deloitte Technology Fast 500 EMEA and in the Financial Times’ FT 1000: Europe’s Fastest-Growing Companies.\nEquativ (formerly Smart AdServer) has been awarded the HappyIndex@Work label and is proud to be among the best companies in the ChooseMyCompany ranking, recognized for its flexible working environment.\nCome and lead the charge with us in building a transparent ecosystem based on quality!\nEquativ is an equal opportunity employer. Equal access to employment, services, and programs are available to everyone, regardless of race, color, ancestry, religion, sex, national origin, sexual orientation, age, citizenship, marital status, disability, gender identity, or Veteran status. If you require reasonable accommodation throughout the application and/or interview process, please contact the recruitment team at ta-team@equativ.com\nShow more\nShow less",
        "details": {
            "JobDetail": [
                "Full"
            ],
            "TypeContract": "",
            "Salary": "",
            "Level": "",
            "Experience": null
        },
        "title": "data analyst",
        "skills": {
            "ProgLanguage": [
                "R",
                "Python"
            ],
            "DataBase": [
                "SQL"
            ],
            "DataAnalytics": [
                "R"
            ],
            "DataVisualisation": [
                "Tableau"
            ],
            "DBMS": [
                "BigQuery",
                "Snowflake"
            ],
            "Automation": [
                "Airflow"
            ],
            "Collaboration": [
                "Teams"
            ],
            "EnSoftSkils": [
                "Communication",
                "Collaboration"
            ]
        }
    },
    {
        "source": "LinkedIn",
        "company": "Treezor",
        "location": "Paris, Île-de-France, France",
        "link": "https://fr.linkedin.com/jobs/view/data-analyst-h-f-at-treezor-3882828889?position=4&pageNum=15&refId=nmjl8wtZkD%2F%2FLwpmcHztLg%3D%3D&trackingId=7DektiSvMTNL96mO8i%2FmFQ%3D%3D&trk=public_jobs_jserp-result_search-card",
        "description": "Fondée en 2015 et acquise en 2019 par le groupe Société Générale, Treezor est un Établissement de Monnaie Électronique, agréé par l’ACPR, autorisé à opérer dans 25 pays et membre principal du réseau Mastercard.\nTreezor est le précurseur du “Banking as a Service” et intègre dans son offre les dimensions technologiques, réglementaire et sécuritaire pour proposer en API l’accès à l’ensemble des services de la chaîne de paiements, en acquisition et émission. Treezor consacre une partie importante de ses ressources au développement de nouvelles technologies afin de soutenir l’innovation et la stratégie de croissance de ses clients.\n💶 80 milliards+ d'euros de flux gérés depuis notre lancement\n💳 5 millions+ cartes de paiement émises\n🤝 150+ clients (néobanques, néobanques professionnelles, marketplaces...)\n🌍 25 pays couverts\n👥 250+ collaborateurs\n💬 20+ nationalités\nPour accompagner sa croissance, Treezor recherche un(e) Data Analyst (H/F).\nL’équipe Data a pour mission de démocratiser l’usage de la Data à tous les niveaux de l'entreprise.\nLe Data Analyst joue un rôle clé pour permettre une large adoption de la Data sous ses différents aspects au sein de Treezor. Il accompagne les équipes métiers pour affiner leurs besoins et définir la meilleure façon de représenter la donnée.\nVous aurez pour principales missions :\nExtraire divers indicateurs de notre Data Lake\nConstruire des Dashboards pour les équipes métiers et les conseiller sur le meilleure manière d’exploiter la donnée\nExploiter des sources de données variées (fichiers CSV, Google Docs, etc.) pour enrichir les données du Data Lake\nComprendre précisément les problématiques métiers et les traduire de manière analytique\nVoici les prérequis pour ce poste :\nBac+3/5 dans les domaines suivants : Technicien/Ingénieur informatique avec une spécialisation ou bien une forte appétence Data\nMaîtrise du langage SQL, idéalement sur plusieurs types de bases de données\nConnaissance d'un outil de visualisation de données (Quicksight est un plus)\nCompréhension de la modélisation de données dans des bases de données relationnelles\nAppétence pour les interactions avec les équipes métiers\nConnaissance de l’environnement AWS\nCapacité à comprendre rapidement les environnements techniques complexes\nQualité de présentation et de rédaction en français et en anglais\nAutonomie\nMaîtrise du langage Python dans un contexte Data serait un plus\nRejoindre l’aventure TREEZOR c’est aussi :\n💥 Un environnement agile, dynamique et en pleine croissance et des bureaux en plein cœur de Paris (près de l’Arc de Triomphe) et de Rennes (près de la gare)\n📖 Des opportunités d'apprentissage constantes\n🤝 Une culture collaborative où la créativité est encouragée\n💰 Une rémunération compétitive\n🏠 Organisation de travail hybride avec une participation financière pour vous équiper à la maison\n🚀 Des avantages pour les salariés (des subventions, des cartes cadeaux etc.) et des événements créés par le CSE (loterie, sorties de groupe dans des parcs d'attractions, grands événements mondiaux comme Roland Garros et Rolex Paris Master, etc.)\nAu travers de ses recrutements, Treezor cultive une politique en faveur de la diversité, de l’égalité professionnelle et de l’emploi des travailleurs handicapés.\nShow more\nShow less",
        "details": {
            "JobDetail": [
                "Hybride"
            ],
            "TypeContract": "",
            "Salary": "",
            "Level": "Bac+3",
            "Experience": null
        },
        "title": "data analyst",
        "skills": {
            "ProgLanguage": [
                "Python"
            ],
            "DataBase": [
                "SQL"
            ],
            "CloudComputing": [
                "AWS"
            ]
        }
    },
    {
        "source": "LinkedIn",
        "company": "RAJA",
        "location": "Roissy-en-France, Île-de-France, France",
        "link": "https://fr.linkedin.com/jobs/view/business-data-analyst-at-raja-3916636230?position=5&pageNum=15&refId=nmjl8wtZkD%2F%2FLwpmcHztLg%3D%3D&trackingId=sLuBYUBqtui9ZBHFtOsmcQ%3D%3D&trk=public_jobs_jserp-result_search-card",
        "description": "Description Du Poste\nAu sein du pole achat, vos missions seront:\nRecueillir et analyser l’ensemble des données autour des produits sur la base des extractions MDM, ERP ou autres applicatifs pour contribuer à la construction et la mise en œuvre du modèle de données cible\nEtudier, recouper, retraiter et nettoyer des données pour les transformer en informations exploitables\nProposer et créer des KPI et des Dashboard pertinents\nParticiper aux réunions d’équipe MDM et toute autre instance projet nécessaire\nContribuer au chantier de refonte de la BI produit : expression des besoins propres à la BDDP\nContribuer à la définition fonctionnelle du monitoring de la donnée produit\nMonter en compétence sur la gouvernance et la maintenance de la donnée produit Groupe Pilotage des analyses en Run\nExtraire les données à partir des sources de données pertinentes\nContrôler la qualité de données\nAnalyser et exploiter les données du MDM post mise en œuvre du nouveau data model\nAssurer une mise à jour régulière\nProposer et créer des KPI et des Dashboard pertinents\nVulgariser et synthétiser visuellement des données pour les rendre accessibles aux décideurs et à sa hiérarchie\nMettre en place des process de requêtes automatiques afin de faciliter l’extraction de données\nProduire des analyses en fonction des attentes de sa Direction\nAssurer la création/modification des articles pour les sociétés Office (JPG / Mondoffice et Kalamazoo)\nAssurer le rôle de référent data MDM pour les sociétés Office\nProfil recherché\nDe formation supérieure (Bac +4/5) en ingénierie informatique / statistique, ou mastère spécialisé Big Data, avec une expérience de 2 ans sur un emploi similaire.\nVous Avez\nDe la rigueur\nUn esprit analytique et de synthèse\nUne forte appétence pour les statistiques\nLe sens du service\nShow more\nShow less",
        "details": {
            "JobDetail": [],
            "TypeContract": "",
            "Salary": "",
            "Level": "",
            "Experience": "2 an(s)"
        },
        "title": "data analyst",
        "skills": {
            "Other": [
                "Statistiques",
                "Big Data"
            ]
        }
    },
    {
        "source": "LinkedIn",
        "company": "TotalEnergies",
        "location": "Courbevoie, Île-de-France, France",
        "link": "https://fr.linkedin.com/jobs/view/data-analyst-rh-d%C3%A9butant-e-h-f-at-totalenergies-3920520940?position=6&pageNum=15&refId=nmjl8wtZkD%2F%2FLwpmcHztLg%3D%3D&trackingId=qUkbsze2oibJsQwPoMp5WQ%3D%3D&trk=public_jobs_jserp-result_search-card",
        "description": "Profil du candidat\nVous êtes récemment diplômé.e d'un Bac+5/Master 2 et recherchez une expérience stimulante dans le domaine des RH et Data RH, au cœur d’équipes internationales, engagées dans la transition énergétique !\nNous vous proposons un contrat de professionnalisation temps plein qualifiant de 12 mois incluant 15% de formation interne (métier, linguistique, outils…). Ces formations sont dispensées en interne par des organismes sélectionnés par TotalEnergies. Ce contrat vous permettra d’acquérir une année d’expérience professionnelle tout en étant formé aux spécificités de votre métier en lien avec les activités de la Compagnie. Un réel atout pour booster votre employabilité !\nPour postuler à cette offre, vous devez impérativement posséder, à la date d’embauche, un titre de séjour valide pour la période couverte par cette offre (attention, la conclusion de ce contrat de professionnalisation ne permet pas la délivrance d’un titre de séjour (article R.52221-6 du Code du travail).\nATTENTION CE POSTE NE S'ADRESSE PAS AUX PERSONNES RECHERCHANT UNE ALTERNANCE AVEC UNE ECOLE OU UNE FORMATION DIPLOMANTE MAIS AUX PERSONNES RECEMMENT DIPLOMEES A LA RECHERCHE D’UNE PREMIERE EXPERIENCE\nConnaissances techniques et informatiques :\nAnalyse et gestion de bases de données\nMode gestion de projet\nExcel (Excellent niveau)\nPower BI (Navigation assurée dans l'outil pour montée en compétence des équipes en place)\nBO Business Object (utile)\nAnglais\nSavoir-être :\nRigueur\nOrganisation\nGoût du travail en équipe\nTotalEnergies recherche avant tout des compétences et des personnalités et s’ouvre à tous les talents représentant la diversité et la richesse des profils. Depuis de nombreuses années, nous menons une politique volontariste favorisant l’insertion professionnelle et l’accompagnement dans l’emploi de nos salariés en situation de handicap tout au long de leur carrière.\nSi cette offre vous intéresse alors n'attendez plus... Postulez chez TotalEnergies !\nActivités\nNous recherchons un spécialiste Power Bi pour accompagner nos recherches, envisager des automatisations et simplifications, lancer des développements, améliorer nos reportings, les faire évoluer tout en gagnant du temps à répondre aux demandes ponctuelles qui interviennent au fil de l’eau (listes de diffusion, études, populations).\nLe temps de travail sera réparti entre un véritable back-office de l'équipe Data et le travail direct avec la fonction RH et les équipes qui utilisent les données RH de la branche.Le candidat retenu devra suivre l'équipe dans ce qu'elle produit quotidiennement ou périodiquement, maitriser les sujets dans la pratique et devenir aussi un potentiel back up ou relais possible selon les périodes et les demandes. Faire, comprendre et connaitre est la meilleure passerelle pour construire, orienter et améliorer les process.\nSur l'aspect Technique de l'outil, un cahier des charges sera constitué au fur et à mesure pour tenter de simplifier certaines études, de diminuer le délai de réalisation des livrables (aujourd'hui sous excel), d'assurer la maintenance des dashboards déjà réalisés sur PowerBI et utilisant le codage sous Power Query et et de trouver les astuces pour monitorer au mieux les données et rendre les visuels les plus attractifs possibles.\nContexte et environnement\nAccompagné de son tuteur et de ses futurs collègues data analystes, le candidat retenu intègrera un open space bienveillant, agréable et dynamique de +/- 15 personnes, qui travaille en mode \"projet\". Entre les systèmes d’information RH et la partie développement, la passerelle est quasi invisible et l’entraide un point fort .\nShow more\nShow less",
        "details": {
            "JobDetail": [
                "Temps plein"
            ],
            "TypeContract": "",
            "Salary": "",
            "Level": "Bac+5",
            "Experience": null
        },
        "title": "data analyst",
        "skills": {
            "ProgLanguage": [
                "R"
            ],
            "DataAnalytics": [
                "R"
            ],
            "DataVisualisation": [
                "Power BI"
            ]
        }
    },
    {
        "source": "LinkedIn",
        "company": "Balzac Paris",
        "location": "Paris, Île-de-France, France",
        "link": "https://fr.linkedin.com/jobs/view/data-analyst-h-f-alternance-at-balzac-paris-3920291908?position=7&pageNum=15&refId=nmjl8wtZkD%2F%2FLwpmcHztLg%3D%3D&trackingId=3NSSzEYWCpKlpLJFbU7ZWA%3D%3D&trk=public_jobs_jserp-result_search-card",
        "description": "Balzac Paris est à la recherche d'un.e\nData Analyst H/F\nen alternance !\nRattaché.e au RAF, vous serez garant.e de la modélisation et de l'exploitation de la base de données pour accroitre les performances de l'entreprise.\nA Ce Titre, Vous Aurez Les Missions Suivantes\nModélisation de la base de données\nIdentifier les besoins en travaillant avec les équipes métiers pour construire les différents modèles et analyses\nCollecter, organiser, et modéliser les données (données business)\nExploitation de la donnée\nProduire des analyses métiers et faire des recommandations aux équipes\nFluidifier les échanges avec nos partenaires (filtrer les demandes, co-construire les solutions)\nAccompagnement des équipes\nParticiper à répandre la culture data chez Balzac Paris en mettant la donnée au centre de chaque prise de décision\nAccompagner les équipes pour les rendre le plus indépendantes possibles dans leur consommation de donnée (document de formation, tuto)\n✨Profil Recherché\nFormation : bac +4/5\nAptitude : Maîtriser le stockage de données\nTrès forte capacité en Excel (VBA a minima)\nConnaître les outils de Web Analytics : Google Analytics, Power BI, Biron…\nCompétences en mathématiques/statistiques\nEsprit d’analyse et de synthèse\nCapacité d’écoute\nRigueur\nOrganisation\nSens de la pédagogie\n❤️Ce Que Nous Vous Offrons\nDes bureaux en plein cœur de Paris avec des espaces de travail agréables\nDes collègues enthousiastes et de bonne humeur au quotidien\nLe remboursement à hauteur de 50% de votre titre de transports\nUne mutuelle 100% prise en charge\nUne carte restaurant Swile\nDes réductions sur notre site Balzac Paris et un accès à nos ventes privées du personnel ! 🎁\nVous souhaitez nous rejoindre et être un acteur incontournable dans une entreprise en pleine croissance? N’hésitez plus et postulez dès maintenant !\n« Le génie a cela de beau qu’il ressemble à tout le monde et que personne ne lui ressemble. »\nSur les traces d’Honoré de Balzac et parce que chacun d’entre vous est unique, nous nous engageons en faveur de la diversité au sein de nos équipes.\nShow more\nShow less",
        "details": {
            "JobDetail": [],
            "TypeContract": "",
            "Salary": "",
            "Level": "",
            "Experience": null
        },
        "title": "data analyst",
        "skills": {
            "DataVisualisation": [
                "Power BI"
            ],
            "Other": [
                "Statistiques"
            ]
        }
    },
    {
        "source": "LinkedIn",
        "company": "Onatera",
        "location": "Aix-en-Provence, Provence-Alpes-Côte d'Azur, France",
        "link": "https://fr.linkedin.com/jobs/view/alternance-data-analyst-h-f-at-onatera-3872986165?position=8&pageNum=15&refId=nmjl8wtZkD%2F%2FLwpmcHztLg%3D%3D&trackingId=2%2FdoWWFGXCwnyAxCyhWebQ%3D%3D&trk=public_jobs_jserp-result_search-card",
        "description": "Chez Onatera, depuis plus de 12 ans, la nature nous inspire, nous guide, nous comble.\nNotre mission est simple : proposer un choix le plus large de produits et d’ingrédients naturels, efficaces et sensoriels à nos clients pour qu’ils prennent soin d’eux, de leur corps et de leur esprit.\nCette approche holistique, nous pousse à sans cesse développer nos univers afin que nos clients puissent trouver en un seul et même endroit tout ce dont ils ont besoin pour prendre soin d'eux plus naturellement et plus durablement. Forts de notre expérience, et convaincus que nous pouvons offrir à nos clients des produits encore meilleurs et au meilleur prix, nous sommes devenus fabricant, et avons ouvert notre usine à Salon de Provence.\nUn grand pas qui permet aujourd'hui de proposer plus de 1500 produits, 300 plantes, 200 actifs naturels et 120 huiles essentielles pour que chaque client s’occupe de son corps, de son esprit et de son cœur.\nIntégrer Onatera c'est rejoindre un projet collectif, avec des équipes passionnées et unies par l’envie de rendre le bien-être au naturel accessible à tous.\nVous êtes à la recherche d’une alternance responsabilisante et vous avez envie de rejoindre une aventure dans laquelle chaque effort contribue au développement d’Onatera ?\nRejoignez nos équipes pour une alternance en tant que Data Analyst (h/f) à Aix en Provence. Au sein de la direction e-commerce, vous contribuez à l’analyse de la data pour optimiser le pilotage de l’ensemble des leviers d’acquisition online dans une logique d’acquisition à la fois performante et qualitative.\nVos missions :\nParticiper au déploiement du plan d’acquisition Web (plan d’acquisition et de fidélisation des clients pertinent) avec notre agence et la direction e-commerce pour accompagner la croissance, dans le respect d’un cadre budgétaire préalablement défini.\nCollecter, mesurer, optimiser, tester, mesurer encore la data…pour contribuer à l’augmentation du volume de conversion et pour suivre les performances des actions mises en place en acquisition.\nVeille active sur les tendances et compilation des best practices.\nPour ce projet, nous recherchons un étudiant qui a une bonne compréhension globale du fonctionnement du digital, des leviers pour acquérir du trafic, et, avec une sensibilité aux environnements BtoC. Les must have :\nVous possédez d’excellentes capacités analytiques pour évaluer et restituer les performances des actions.\nVous êtes curieux et faites preuve de pro-activité et de rigueur pour piloter vos projets efficacement.\nVotre esprit d’équipe sera un atout pour collaborer avec les équipes Marketing/ CRM/ Communication ou encore Tech.\nVous maîtrisez Excel à un niveau avancé.\nCe poste est ouvert aux personnes en situation de handicap.\nDécouvrez nos dernières actualités sur notre page LinkedIn & abonnez vous -> Onatera\nShow more\nShow less",
        "details": {
            "JobDetail": [],
            "TypeContract": "",
            "Salary": "",
            "Level": "",
            "Experience": "12 an(s)"
        },
        "title": "data analyst",
        "skills": {
            "EnSoftSkils": [
                "Communication"
            ]
        }
    },
    {
        "source": "LinkedIn",
        "company": "Foxintelligence",
        "location": "Paris, Île-de-France, France",
        "link": "https://fr.linkedin.com/jobs/view/lead-data-analyst-at-foxintelligence-3835174526?position=9&pageNum=15&refId=nmjl8wtZkD%2F%2FLwpmcHztLg%3D%3D&trackingId=J43OIwMa5fITBnT1J74P6w%3D%3D&trk=public_jobs_jserp-result_search-card",
        "description": "Chez Foxintelligence, nous sommes des amoureux de la data. 🤓\nNotre mission est de rendre les consommateurs et les marques plus intelligents, grâce à une donnée de marché révolutionnaire issue de l'intelligence collective. Pour les consommateurs, Foxintelligence rend accessibles et utiles leurs données transactionnelles issues de leurs boîtes mail. En les anonymisant, nous créons des statistiques uniques qui permettent aux marques de rester en phase avec les produits qui se vendent le mieux et les attentes des consommateurs.\nNous publions une application grand public aimée par des millions de personnes (Cleanfox, 15m+ de téléchargements, 4.8/5 💖 sur l'app store et le play store) et préparons le lancement d'une app de bilan carbone à l'expérience radicalement nouvelle. Grâce à notre plateforme data, elle va rendre possible une prise de conscience massive des enjeux du changement climatique 🌍 et des actions individuelles possibles pour le combattre. Nous pensons que l'information est une force de changement puissante, lorsqu'elle s'appuie sur la data.\nUtilisant ces données personnelles totalement anonymisées, notre plateforme SaaS foxintelligence.io est devenue la référence de la market intelligence digitale en Europe avec des dizaines de grands groupes clients. Le point commun entre Deliveroo, Just Eat, BackMarket ou The Boston Consulting Group ? Ils vont très vite (on ne s'ennuie pas avec eux !) et ils nous font tous confiance !\nSoutenus par des investisseurs de premier plan et récemment intégrés au groupe NielsenIQ (17m levés auprès de Daphni, Partech, GFC et eFounders), nous sommes maintenant à la conquête de l'Europe et en phase d'hyper-croissance\nSi notre FoxHQ reste à Paris, notre équipe de plus de 120 talents pluridisciplinaires (tech, data et business) travaille depuis partout en France. Nous pensons que notre politique de remote, notre culture forte (bienveillance, exigence, résilience et data-first) et notre innovation permanente en termes de modes de travail (ex. grille de salaire transparente, formation au changement climatique, transparence sur la stratégie) sont les clés de notre réussite collective.... et de ta réussite avec nous !\nJob Description\nFoxintelligence recherche un(e)\nLead Data Analyst.\nTes responsabilités au quotidien :\nData Analysis/Engineering\nAutomatisation & scale : Construire des outils de productivité à destination des équipes Métiers pour leur permettre de gagner en efficacité (définition de process transverses, automatisation de tâches avec Python, mise à disposition de dashboards Tableau d'investigations etc...)\nExpertise technique : Avoir une parfaite maîtrise de notre pipeline Data et être le/la référent(e) technique auprès des équipes Métiers. Les accompagner au quotidien, les former et les rendre autonomes\nAnalyses : Faire des analyses approfondies sur une variété d'enrichissements comme l'âge des consommateurs ou la géolocalisation des commandes. Remettre en question ces enrichissements, identifier les améliorations nécessaires et construire la roadmap qui nous permettra de scaler à l'international\nManagement : Superviser et faire grandir les data analysts de l'équipe\nProduct Management Data\nProjets stratégiques : Orchestrer les initiatives majeures et à fort potentiel pour Fox sur le plan Data. Etre l'interlocuteur/trice des équipes internes et externes (NielsenIQ, partenaires stratégiques) et piloter les projets de A à Z : définition de la roadmap, structuration et exécution. A titre d'exemple, l'un de nos challenges actuels est l'intégration avec NielsenIQ pour rendre possibles des analyses omnicanales (online/offline)\nProduct Owner de nos applications internes :\nDéfinir les besoins avec les équipes Métiers\nConcevoir de nouveaux outils et fonctionnalités, et accompagner les équipes dans leur prise en main\nConstruire la roadmap, la décomposer en tickets, tester et communiquer auprès de l'ensemble des équipes\nRequirements\nCompétences nécessaires (ce qu'il te faut pour réussir sur ce poste) :\nSoft Skills\nEsprit analytique et structuré\nMotivé(e) par les défis et à l'aise face à des problèmes nouveaux et complexes\nCapacité à collaborer avec des clients de séniorité diverses et différents interlocuteurs internes (Marketing & Sales, Produits & Tech, R&D data)\nEnvie d'apprendre, de contribuer spontanément à son environnement et d'aider l'équipe à s'améliorer\nHard Skills\nCapacité à comprendre et challenger rapidement le fonctionnement de produits techniques complexes : soit par une expérience pertinente (auto-formation, projet perso), soit par une formation adaptée (grande école d'ingénieur ou équivalent à l'étranger, école de commerce avec parcours avancé en data)\nCapacité à gérer simultanément de multiples projets et à prendre des décisions rapidement au regard des enjeux techniques mais aussi business, y compris à divers niveaux de risque ou d'incertitude\nMaîtrise de Tableau, SQL (idéalement BigQuery), Github, Airflow, Google Cloud Platform\nAvancé en R ou en Python\nExpérience\n3-5 ans d'expérience en data, opération ou produit dans des startups/environnements tech, ou en cabinet de conseil\nCompétences bonus\nExpérience passée dans un environnement tech où on passe à l'échelle, ou au lancement d'un produit data/tech de zéro\nConnaissances en IA/LLM\nLadies\nLes études montrent que les femmes ont moins tendance à postuler à une offre d'emploi quand elles n'ont pas toutes les qualifications requises. Ladies, ne vous mettez pas de barrière et donnez-nous la chance de nous faire notre propre avis, nous serons toujours ravis d'échanger avec vous ! Si notre raison d'être vous parle, postulez !\nSelf-made data lovers\nLes diplômes c'est bien, les skills c'est mieux et l'expérience t'en donne. Aucun diplôme n'est requis chez nous, c'est les compétences et l'énergie qui comptent !\nRecruitment process\nRound 0 : entretien (fit) avec notre Head of People\nRound 1 : entretien (expérience et fit) avec notre Head of Data Management\nTest technique\nRound 2: entretiens avec le/la manager de l'équipe\nDecision round: entretien avec deux membres de l'équipe\nBenefits\nAvantages/ce que nous offrons :\nSalaire et variable compétitifs\nRemote friendly (+ budget aménagement de l'espace de travail @Home)\nBonus Cooptation\nBonne assurance santé (Alan)\nTitres restaurants (swile) : pris en charge à 60% par Fox\nSystème de crèche subventionné par Fox\nCulture forte et pratiques de management à la pointe (stratégie et résultats financiers transparents, feedback 360, grille de salaire innovante et transparente etc.)\n4 jours par an offert pour faire du bénévolat (partenariat avec la plateforme vendredi)\nShow more\nShow less",
        "details": {
            "JobDetail": [
                "Remote"
            ],
            "TypeContract": "",
            "Salary": "3",
            "Level": "",
            "Experience": "5 an(s)"
        },
        "title": "data analyst",
        "skills": {
            "ProgLanguage": [
                "R",
                "Python"
            ],
            "DataBase": [
                "SQL"
            ],
            "DataAnalytics": [
                "R"
            ],
            "DataVisualisation": [
                "Tableau"
            ],
            "CloudComputing": [
                "Google Cloud Platform"
            ],
            "DBMS": [
                "BigQuery"
            ],
            "Automation": [
                "Airflow"
            ],
            "Other": [
                "Statistiques",
                "Cloud"
            ]
        }
    },
    {
        "source": "LinkedIn",
        "company": "Terres d'Aventure",
        "location": "Paris, Île-de-France, France",
        "link": "https://fr.linkedin.com/jobs/view/data-analyst-at-terres-d-aventure-3866774439?position=10&pageNum=15&refId=nmjl8wtZkD%2F%2FLwpmcHztLg%3D%3D&trackingId=V1LeoVp4H%2Bl1pmy2ppkJfQ%3D%3D&trk=public_jobs_jserp-result_search-card",
        "description": "À propos de nous\nOsez l'aventure et transformez votre passion en carrière !\nDepuis plus de 45 ans, nous explorons le monde avec une curiosité insatiable et une passion intacte pour organiser des voyages inoubliables ! Spécialiste de la randonnée, du trekking et du voyage à vélo,\nTerres d’aventure est le numéro 1 du voyage d’aventure\nfaisant ainsi voyager chaque année des milliers d’aventuriers dans le monde entier. Engagés dans le tourisme durable nous proposons des voyages respectueux des pays dans lesquels nous allons et 100% carbone absorbés.\nVous êtes passionné·e par les voyages et la randonnée ? Vous souhaitez intégrer une entreprise\ndynamique et innovante\navec des\nvaleurs fortes\net investie dans le\ntourisme durable\n? Rejoignez l’équipe Terdav ! www.terdav.com\nMission\nLe service Business Analyst est un service stratégique pour l’ensemble de l’entreprise.\nVos Missions Sont Les Suivantes\nLa réalisation d’études marketing, commerciales et d’analyses de données\nDéfinition, élaboration et déploiement de reportings marketing et commerciaux périodiques sur l’activité de la société, à la demande de la direction ou des différents services de l’entreprise\nAnalyses ad hoc sur des sujets spécifiques à la demande de la direction ou des différents services de l’entreprise\nLa Gestion Des Process\nAnalyse des process internes et externes en fonction des projets et à la demande des directions de la société\nDéfinition, élaboration et proposition de plans d’action pour améliorer les process\nProposition d’évolution des outils pour suivre les modifications de process\nDéploiement des nouveaux process et accompagnements des équipes dans leur mise en œuvre\nLe Bilan Carbone\nRéalisation du bilan carbone de Terres d’Aventure\nCalcul des émissions carbone des trajets aériens des clients du groupe Voyageurs du Monde\nProfil\nIssu·e d’une grande école de commerce vous bénéficiez d’une expérience d’au moins 3 ans dans un poste similaire.\nDoté·e de très bonnes capacités d’analyse et de synthèse vous possédez un vif intérêt pour le marketing et l’analyse de données. Vous avez une très bonne connaissance des outils d’analyse dont Excel (notamment Power Query), Power BI ou autre outil similaire et êtes très à l’aise avec la manipulation de base de données métier (compréhension, modélisation, traitement et analyse). Enfin, vous avez de grandes capacités rédactionnelles.\nOrganisé·e, rigoureux·se et méthodique, vous aimez travailler en équipe.\nDe nature dynamique, curieux·se et proactive, vous savez vous adapter et possédez une bonne écoute et un très bon sens relationnel.\nVous avez le goût du challenge ? Vous vous reconnaissez dans ce poste ? Rejoignez-nous et aidez nos client·e·s à vivre des aventures uniques et inoubliables à travers le monde.\nRejoindre Terres D'Aventure C'est\nBénéficier de supers avantages et en plus ils sont nombreux ! :\n6 semaines de congés payés\nJusqu’à 2 jours de télétravail par semaine,\nUn système d’intéressement et de participation pouvant aller jusqu’à 3 mois de salaire,\nUne mutuelle prise en charge à 85% par l'entreprise,\nDes tickets restaurant d’une valeur de 10€ pris en charge à 60%,\nUne prise en charge des indemnités kilométriques vélo et de 50% des abonnements aux transports en commun\nDes prix réduits sur nos voyages\nDes avantages divers avec notre CSE comme des cours de sport ou des massages à l’heure du déjeuner, des weekends, des tarifs préférentiels pour divers évènements et le cinéma...\nTravailler dans des locaux accueillants situés en centre-ville sur un poste intégrant de nombreuses formations, polyvalent et évolutif à destination d'une clientèle de voyageur·se·s passionné·e·s.\nIntégrer une équipe passionnée, soudée, bienveillante, conviviale et sportive. Chez Terres d'Aventure, nous croyons en la force de l'équipe. On aime relever des défis dans le travail ou en dehors comme le Marathon des Sables, un semi-marathon ou des projets caritatifs. Et comme nous sommes convaincus qu’on travaille mieux dans une ambiance conviviale on aime également se retrouver autour d’un café, d’un déjeuner ou au cours d’évènements d’entreprise.\nRejoindre une entreprise avec des valeurs fortes qui ne cesse d'innover, de se développer et qui s'engage dans le tourisme responsable avec des engagements environnementaux et le soutien d’ONG et d’associations au travers de sa fondation.\nFaire partie d’un groupe international et profiter de possibilités d’évolution.\nConditions\nLe poste est à pourvoir dès que possible en CDI.\nLocalisation\n: Dans nos locaux de Paris.\nRémunération\nUn salaire fixe sur 12 mois selon profil,\nUn système d’intéressement et de participation pouvant aller jusqu’à 3 mois de salaire.\nRéférence de l'offre : 39b71s4u4n\nShow more\nShow less",
        "details": {
            "JobDetail": [],
            "TypeContract": "CDI",
            "Salary": "85",
            "Level": "",
            "Experience": "45 an(s)"
        },
        "title": "data analyst",
        "skills": {
            "DataVisualisation": [
                "Power BI"
            ]
        }
    }
]