[
    {
        "source": "LinkedIn",
        "title": "Data Architect",
        "company": "La Javaness",
        "location": "Paris, \u00cele-de-France, France",
        "link": "https://fr.linkedin.com/jobs/view/data-architect-at-la-javaness-3646114499?position=2&pageNum=0&refId=a5rwPua%2FMvx%2F2M%2FPSF0oPA%3D%3D&trackingId=Yk0NP1kjoSKWXhEqbeXfPA%3D%3D&trk=public_jobs_jserp-result_search-card",
        "description": "En 5 ans, La Javaness s'est impos\u00e9e comme leader fran\u00e7ais de l'IA pour les entreprises (BtoB). Sans tambour ni trompettes (mais avec beaucoup de R&D !), nous avons concentr\u00e9 nos forces \u00e0 d\u00e9ployer l'Intelligence Artificielle \u00e0 grande \u00e9chelle au sein d'organisations publiques et priv\u00e9es en France et en Europe.\nMais pas n'importe comment ! Nous croyons en une IA \u00e9thique, responsable, au service des salari\u00e9s et des citoyens europ\u00e9ens. Nous militons pour la souverainet\u00e9 des donn\u00e9es et l'ind\u00e9pendance des entreprises europ\u00e9ennes.\nPragmatiques et rationnels, nous d\u00e9ployons quotidiennement nos solutions \u00ab pr\u00eat-IA-porter \u00bb \u00e0 un niveau industriel. Nous faisons aussi de la haute couture en d\u00e9veloppant des solutions IA sur-mesure pour r\u00e9pondre aux d\u00e9fis de certains de nos clients. Notre R&D bout sans rel\u00e2che pour inventer, tester et d\u00e9ployer l'IA de demain.\nEn d'autres termes, dans la boutique de La Javaness, tu trouveras : Conseil data & IA, acc\u00e9l\u00e9ration par le design, d\u00e9veloppement front & back de pointe, d\u00e9fis business dans un joyeux mix exigeant d'intelligences. Avec ce super cocktail d'expertises et de cr\u00e9ativit\u00e9, nous intervenons sur tous les secteurs d'activit\u00e9 pour cracker les probl\u00e8mes de nos clients !\nNous sommes le partenaire Data et IA de r\u00e9f\u00e9rence pour l'AMF, LCL, la Banque de France ou encore P\u00f4le Emploi. Nous acc\u00e9l\u00e9rons \u00e9galement des projets d'innovation digitale pour la Soci\u00e9t\u00e9 G\u00e9n\u00e9rale, Facebook, Enedis, Saint Gobain, Louvre H\u00f4tels Group...\nComment \u00e7a marche au quotidien ?\nNos expertises Design, IT, Data, Delivery & Business, travaillent ensemble sur tous les projets afin de concevoir et d\u00e9ployer des solutions compl\u00e8tes et innovantes r\u00e9pondant aux besoins de nos clients.\nFort d'un collectif unique, la Javaness investit sans cesse dans des talents pointus, atypiques et compl\u00e9mentaires qui lui conf\u00e8rent une force de frappe hors norme. Et parce qu'on est pas que des machines, la \"Fullstackerie\" s'exprime aussi joyeusement lors de nos fameux ap\u00e9ros au d\u00e9bott\u00e9 et de notre s\u00e9minaire annuel.\nSi \u00e7a te semble une aventure \u00e0 ta mesure, c'est par ici pour nous rejoindre !\nDescriptif du poste:\nVos missions:\nAnalyser les \u00e9tapes du cycle de vie des donn\u00e9es manipul\u00e9es par les processus m\u00e9tier de nos clients\nConcevoir, ou transformer apr\u00e8s analyse pr\u00e9liminaire, les processus et outillages technologiques qui sous-tendent les processus m\u00e9tier, en fonction des besoins et contraintes m\u00e9tier et techniques\nCommuniquer les d\u00e9cisions d'architecture aux \u00e9quipes\nParticiper \u00e0 l'\u00e9laboration du r\u00e9f\u00e9rentiel de technologies, outils, proc\u00e9dures, normes, vocabulaire, s\u00e9curit\u00e9 des syst\u00e8mes d'information\nParticiper \u00e0 l'effort de veille technologique\nParticiper aux phases d'avant-vente par des \u00e9tudes de faisabilit\u00e9 et d'impact, d'architecture, de choix technologiques et d'estimations de charges\nEtre en support de la phase de delivery des projets\nCollaborer avec les autres comp\u00e9tences Data science, D\u00e9veloppeurs, Op\u00e9rations, UX/UI, PM/PO, Business, de La Javaness\nParticiper au d\u00e9veloppement de La Javaness via le recrutement, la structuration et animation interne, le networking, l'\u00e9v\u00e9nementiel, ..\nRequirements\nVous poss\u00e9dez une solide exp\u00e9rience:\nde l'appr\u00e9hension du cycle de vie de la donn\u00e9e et des processus m\u00e9tier associ\u00e9s,\nde l'\u00e9laboration d'architectures de donn\u00e9es et de l'industrialisation de solutions de data management par leur int\u00e9gration dans un SI complexe et s\u00e9curis\u00e9,\ndes technologies de data management et data engineering (ETL/ELT, DQM, portail de donn\u00e9es, data preparation, data virtualization, data catalog, data lineage, BI),\ndes architectures de donn\u00e9es et de leurs syst\u00e8mes de gestion (Datawarehouse, Data Lake),\ndes exigences que font peser les architectures de donn\u00e9es sur les infrastructures syst\u00e8me et r\u00e9seau\nde data science et machine learning (frameworks, librairies),\nde veille technologique. Vous \u00eates p\u00e9dagogue, avez un bon relationnel et surtout, un esprit entrepreneurial !\nVous pouvez justifier d'expe\u0301riences significatives (7 - 10 ans) dans ce type de poste, et en particulier en gestion de projets et accompagnements de solutions Big Data et IA.\nAnglais requis.\nBenefits\nAmbition et innovation\nPackage attractif : compl\u00e9mentaire sant\u00e9, prime d\u00e9jeuner 98\u20ac/mois, Navigo 100%, 25 jours de cong\u00e9s pay\u00e9s par an, RTT\nParis Bonne Nouvelle\nShow more\nShow less",
        "skills": {
            "ProgLanguage": [
                "Java",
                "R",
                "Go"
            ],
            "DataBase": [],
            "DataAnalytics": [
                "R"
            ],
            "BigData": [],
            "MachingLearning": [],
            "DataSerialization": [],
            "DataVisualization": [],
            "Statistics": [],
            "CloudComputing": [],
            "DevTools": [
                "Git"
            ],
            "Os": [],
            "DBMS": [],
            "SoftBigDataProcessing": [],
            "Automation": [],
            "InfrastructureAsCode": [],
            "NetworkSecurty": [],
            "Virtualisation": [],
            "Containers": [],
            "Collaboration": [],
            "Other": [
                "Big Data",
                "Machine Learning"
            ],
            "FrSoftSkills": [
                "Cr\u00e9ativit\u00e9",
                "Organisation"
            ],
            "EnSoftSkils": []
        },
        "details": {
            "JobDetail": [
                "Full"
            ],
            "TypeContract": [],
            "Salary": [
                "98"
            ],
            "Level": [],
            "Experience": [
                "a",
                "n",
                "s",
                "5",
                "5",
                "5"
            ]
        }
    },
    {
        "source": "LinkedIn",
        "title": "Architecte Data",
        "company": "Ippon Technologies",
        "location": "Paris, \u00cele-de-France, France",
        "link": "https://fr.linkedin.com/jobs/view/architecte-data-at-ippon-technologies-3851530940?position=3&pageNum=0&refId=a5rwPua%2FMvx%2F2M%2FPSF0oPA%3D%3D&trackingId=WUE05ZbK1%2BRSQiee2Y2X%2BA%3D%3D&trk=public_jobs_jserp-result_search-card",
        "description": "Ippon : cabinet de conseil et d'expertise en technologie, international et ind\u00e9pendant.\nVous int\u00e9grerez notre communaut\u00e9 data\n, compos\u00e9e d\u2019une \u00e9quipe de\n70 experts sur 9 agences en France.\nNotre sp\u00e9cialit\u00e9 est de\nconstruire des data platforms dans le cloud public avec les meilleures technos du moment.\nLa data chez Ippon, c\u2019est d\u00e9j\u00e0 plus de\n250 certifications AWS, GCP et AZURE,\ndes\nspeakers \u00e0 l\u2019AWS Summit, des partenariats avec Snowflake, Databricks, DBT, un blog technique\navec des publications r\u00e9guli\u00e8res.\nDescriptif du poste :\nCe poste est un vrai challenge aussi bien en termes de\nd\u00e9fis techniques que de gestion d\u2019\u00e9quipe.\nLa r\u00e9ussite de vos projets sera port\u00e9e par votre capacit\u00e9 \u00e0 vous adapter et \u00e0 monopoliser un large panel de comp\u00e9tences techniques.\nVous devrez \u00eatre le/la leader de votre \u00e9quipe en gardant \u00e0 l\u2019esprit l\u2019ensemble des\nbonnes pratiques d'architectes\n, de s\u00e9curit\u00e9 et d\u2019automatisation n\u00e9cessaires \u00e0 la r\u00e9ussite du projet.\nEn tant que\nrepr\u00e9sentant(e) de l\u2019engagement d\u2019Ippon\nsur les sujets qui vous seront confi\u00e9s, vous serez amen\u00e9(e) \u00e0\ntravailler avec notre \u00e9quipe commerciale\nd\u00e8s les phases de qualification\net lors de la validation de jalons de la roadmap que vous aurez pr\u00e9alablement valid\u00e9 avec le client. Vous interviendrez \u00e9galement dans la s\u00e9lection de l\u2019\u00e9quipe qui sera affect\u00e9e \u00e0 votre projet.\nVotre r\u00f4le :\nGr\u00e2ce \u00e0 votre position d\u2019architecte vous avez une vision experte et syst\u00e9mique de l\u2019ensemble des composants d\u2019une Modern Data Platform.\nVous ma\u00eetrisez le panel des exigences fonctionnelles et non fonctionnelles \u00e0 collecter afin d\u2019assurer l\u2019efficience op\u00e9rationnelle et la p\u00e9rennit\u00e9 de la data platform.\nVous \u00eates expert(e) et ma\u00eetrisez tous les outils et services d\u2019au moins un \u00e9cosyst\u00e8me parmi les 3 principaux leaders du march\u00e9 (AWS, Azure et GCP) et avez des facilit\u00e9s pour \u00e9tendre votre champ de comp\u00e9tences.\nVous \u00eates proactif/ve sur la veille technique et la capitalisation et veillez \u00e0 garder toujours un temps d\u2019avance sur l\u2019\u00e9tat de l\u2019art du secteur afin de pouvoir guider vos clients.\nEn tant qu\u2019architecte exp\u00e9riment\u00e9(e) vous pouvez indiff\u00e9remment intervenir sur des missions de delivery pour concevoir la solution cible ou en phase de cadrage amont pour guider les choix et construire les roadmaps.\nVous \u00eates p\u00e9dagogue et savez communiquer et vulgariser des r\u00e9flexions complexes pour les rendre accessibles \u00e0 tous.\nNotre \u00e9co-syst\u00e8me technique :\nCloud : AWS, GCP, Azure\nLangage de programmation data : Python, SQL, Scala\nApproche Data Warehouse : Redshift, Snowflake, BigQuery\nApproche Data Lakehouse : Databricks, Starburst, Glue-Athena-S3\nIngestion : AWS Glue, Airbyte, dbt\nStockage : AWS S3, Google Cloud Storage, Azure Blob Storage\nOrchestration : Airflow, AWS Step function\nGouvernance : cataloging, s\u00e9curit\u00e9, scope d'acc\u00e8s\nBatch et Streaming : Kafka, Amazon Kinesis, Google DataFlow\nOutil de visualisation : Tableau, Power BI, Metabase, Superset\nVotre \u00e9volution chez Ippon :\nVous serez accompagn\u00e9(e) dans votre mont\u00e9e en comp\u00e9tences aussi bien technique que leadership gr\u00e2ce \u00e0\nnotre programme BlackBelt\n(programme de formation continue : mentoring, formations, certifications).\nEn tant que membre d\u2019une communaut\u00e9,\nvous pouvez avoir diff\u00e9rents r\u00f4les :\nCelui de manager technique (MT) : manager d\u2019une \u00e9quipe de 7 ing\u00e9nieur(e)s Ippon (onboarding, suivis, accompagnement, mise en place d\u2019objectifs\u2026). Vous conduirez les entretiens techniques en bin\u00f4me\nResponsable de l\u2019accomplissement d\u2019une ou plusieurs actions strat\u00e9giques de la Core Team Data\nDevenir speaker lors de Meetup, Summit, Talks internes, aupr\u00e8s des \u00e9coles \u2026\nDevenir formateur(trice) et accompagner la nouvelle g\u00e9n\u00e9ration d\u2019Ippon dans leur mont\u00e9e en comp\u00e9tences\nVous avez d\u2019autres souhaits, pas de soucis, nous en discuterons durant notre \u00e9change et r\u00e9pondrons \u00e0 toutes vos questions.\nPr\u00e9sentiel ou t\u00e9l\u00e9-travail ?\nLes deux !\nLa plupart de nos clients sont en hybride et notre politique de t\u00e9l\u00e9travail est classique : 3 jours pr\u00e9sentiel / 2 jours TT.\nNotre processus de recrutement :\nUn call RH (20 min)\nPuis un entretien RH et Commerce pour que nous puissions \u00e9changer sur ce que vous recherchez et ce que nous pouvons vous proposer (1h)\nEnfin, un entretien technique avec un r\u00e9f\u00e9rent technique (1h)\nSi vous \u00eates int\u00e9ress\u00e9(e) mais que vous avez encore des questions, n'h\u00e9sitez pas \u00e0 nous contacter sur LinkedIn\nSinon il ne vous reste plus qu\u2019\u00e0 cliquer sur\nPostuler\nShow more\nShow less",
        "skills": {
            "ProgLanguage": [
                "Python",
                "Scala",
                "R",
                "Go"
            ],
            "DataBase": [
                "SQL"
            ],
            "DataAnalytics": [
                "R"
            ],
            "BigData": [
                "Databricks"
            ],
            "MachingLearning": [],
            "DataSerialization": [],
            "DataVisualization": [
                "Tableau",
                "Power BI"
            ],
            "Statistics": [],
            "CloudComputing": [
                "AWS",
                "Azure"
            ],
            "DevTools": [],
            "Os": [],
            "DBMS": [
                "Snowflake",
                "Snowflake",
                "BigQuery"
            ],
            "SoftBigDataProcessing": [],
            "Automation": [
                "Airflow"
            ],
            "InfrastructureAsCode": [],
            "NetworkSecurty": [],
            "Virtualisation": [],
            "Containers": [],
            "Collaboration": [],
            "Other": [
                "Cloud"
            ],
            "FrSoftSkills": [
                "Leadership"
            ],
            "EnSoftSkils": [
                "Leadership"
            ]
        },
        "details": {
            "JobDetail": [
                "Hybride"
            ],
            "TypeContract": [],
            "Salary": [],
            "Level": [],
            "Experience": [
                "a",
                "n",
                "s"
            ]
        }
    },
    {
        "source": "LinkedIn",
        "title": "Data Architect",
        "company": "MCA",
        "location": "Marseille, Provence-Alpes-C\u00f4te d'Azur, France",
        "link": "https://fr.linkedin.com/jobs/view/data-architect-at-mca-3907802841?position=4&pageNum=0&refId=a5rwPua%2FMvx%2F2M%2FPSF0oPA%3D%3D&trackingId=AqBqXAtI3a6pEmFBU%2Bm1cQ%3D%3D&trk=public_jobs_jserp-result_search-card",
        "description": "MCA est un Groupe de Conseil en Ing\u00e9nierie et Hautes Technologies qui compte 1500 collaborateurs en France et \u00e0 l\u2019International.\nFort de nos 30 ans d\u2019exp\u00e9rience, nous accompagnons nos clients dans la r\u00e9alisation de leurs projets.\nNous rejoindre, c'est int\u00e9grer une entreprise dynamique qui a \u00e0 c\u0153ur d\u2019accompagner ses collaborateurs.\nVous b\u00e9n\u00e9ficiez d'un suivi personnalis\u00e9 et r\u00e9gulier ainsi que de nombreuses formations qui participeront \u00e0 votre mont\u00e9e en comp\u00e9tences.\nD\u00e9tail projet :\nDate de d\u00e9marrage :\nASAP\nExp\u00e9rience n\u00e9cessaire :\n6 - 9 ans\nLangue :\nfran\u00e7ais et anglais\n(Niveau C1)\nContexte de la mission\n:\nNous cherchons un Data Architect qui aura la responsabilit\u00e9 compl\u00e8te de l'architecture.\nNous recherchons une personne ayant une bonne compr\u00e9hension globale des services disponibles d\u2019Azure Analytics.\nCette personne travaillera en collaboration avec plusieurs \u00e9quipes Produits. Il aura en charge l\u2019architecture des donn\u00e9es, et viendra en soutien aux \u00e9quipes dans l\u2019int\u00e9gralit\u00e9 du cycle de vie de la gestion des donn\u00e9es.\nLe consultant devra par ailleurs avoir une exp\u00e9rience op\u00e9rationnelle afin d\u2019\u00eatre en mesure de configurer diff\u00e9rents environnements et services.\nIl/Elle devra faire preuve de leadership dans le but d'endosser le r\u00f4le de Leader Technique, et point d\u2019entr\u00e9e avec les parties prenantes de l\u2019entreprise\nUsage quotidien de l\u2019anglais comme langue de communication dans la fonction\nT\u00e2ches \u00e0 r\u00e9aliser\n:\nVous assurez le leadership technique, participez au d\u00e9veloppement, et repr\u00e9sentez les ressources internes et externes de la plateforme\nVous serez un membre actif de l\u2019\u00e9quipe des architectes, afin de superviser le processus de gestion des donn\u00e9es et fournir des conseils et orientations aux \u00e9quipes de d\u00e9veloppement\nVous serez responsable de la conception, et de la documentation de la solution dans votre domaine\nComp\u00e9tences recherch\u00e9es :\nObligatoires\n:\nExp\u00e9rience dans le d\u00e9veloppement, la documentation et la maintenance de mod\u00e8les de donn\u00e9es logiques et physiques\nExp\u00e9rience sur Databricks, ADLS storage, SQL DB, ADF et Power BI\nExp\u00e9rience dans la d\u00e9finition et la ma\u00eetrise d'une architecture de donn\u00e9es \u00e9volutive de bout en bout, en tenant compte de l'architecture de l'entreprise et des normes industrielles.\nParticipation \u00e0 l'\u00e9laboration d'architectures, strat\u00e9gies et politiques en mati\u00e8re de donn\u00e9es, y compris la s\u00e9curit\u00e9 des donn\u00e9es\nLangage SQL Writing et mod\u00e9lisation de donn\u00e9es\nData Architecture\nPower BI\nAzure ADFv2, Databricks, Synapse, Delta Lake\nEnvironnement et technologie Azure Advanced Analytics\nPython, Pyspark\nMicrosoft cloud bas\u00e9 sur mod\u00e8le Delivery\nData Management, Data Governance et Data Quality\nD\u00e9ploiement d\u2019APIs et micro-services\nDevSecOps\nAgile\nExp\u00e9rience professionnelle dans un environnement international\nOptionnelles :\nExp\u00e9rience dans le secteur automobile\nVos perspectives d\u2019\u00e9volution :\nNotre objectif premier est de vous donner toutes les cl\u00e9s pour r\u00e9ussir et ainsi acc\u00e9der aux diff\u00e9rentes \u00e9volutions que nous proposons.\n\u00c0 terme, vous pourrez \u00e9voluer sur d'autres secteurs d'activit\u00e9s, mais aussi vous projeter en interne sur des postes en France ou \u00e0 l'international.\nCe poste est ouvert aux personnes en situation de handicap.\nShow more\nShow less",
        "skills": {
            "ProgLanguage": [
                "Python",
                "R",
                "Go"
            ],
            "DataBase": [
                "SQL"
            ],
            "DataAnalytics": [
                "R"
            ],
            "BigData": [
                "Spark",
                "Databricks"
            ],
            "MachingLearning": [],
            "DataSerialization": [],
            "DataVisualization": [
                "Power BI"
            ],
            "Statistics": [],
            "CloudComputing": [
                "Azure"
            ],
            "DevTools": [],
            "Os": [],
            "DBMS": [],
            "SoftBigDataProcessing": [],
            "Automation": [],
            "InfrastructureAsCode": [],
            "NetworkSecurty": [],
            "Virtualisation": [],
            "Containers": [],
            "Collaboration": [],
            "Other": [
                "Cloud"
            ],
            "FrSoftSkills": [
                "Communication",
                "Leadership",
                "Collaboration"
            ],
            "EnSoftSkils": [
                "Communication",
                "Leadership",
                "Collaboration"
            ]
        },
        "details": {
            "JobDetail": [],
            "TypeContract": [],
            "Salary": [],
            "Level": [],
            "Experience": [
                "a",
                "n",
                "s",
                "30",
                "30",
                "30"
            ]
        }
    },
    {
        "source": "LinkedIn",
        "title": "Senior Data Architect",
        "company": "CEVA Logistics",
        "location": "Marseille, Provence-Alpes-C\u00f4te d'Azur, France",
        "link": "https://fr.linkedin.com/jobs/view/senior-data-architect-at-ceva-logistics-3919628481?position=5&pageNum=0&refId=a5rwPua%2FMvx%2F2M%2FPSF0oPA%3D%3D&trackingId=0HGOhEn7s5L%2BPwRgFdatBw%3D%3D&trk=public_jobs_jserp-result_search-card",
        "description": "DATA FACTORY MANAGER / SENIOR DATA ARCHITECT\nBased in France (Marseille or Puteaux).\nWHAT ARE YOU GOING TO DO?\nThe Senior Data Architect will join the Global IT Data and Digital organization at CEVA Logistics within the Global CIO organization and will report to the Head of the CEVA Global Data Factory.\nThis role operates in complex decision-making environments impacting the CEVA enterprise, works with senior management from IT, BD and Operations to ensure the best possible global solutions are available for our customers and CEVA employees alike.\nThe data architect will operate in the context of the set of the new Cloud Data Platform of CEVA and will contribute to its set up, development and growth and built up of the internal teams and resources of data architects and data analysts.\nMain Responsabilities:\n\u00b7 Developing and implementing an overall organizational data strategy in line with business processes. The strategy includes data model designs, database development standards, implementation and management of data warehouses and data analytics systems.\n\u00b7 Identifying data sources, both internal and external, and working out a plan for data management that is aligned with organizational data strategy.\n\u00b7 Coordinating and collaborating with cross-functional teams, stakeholders, and vendors for the smooth functioning of the enterprise data system.\n\u00b7 Managing end-to-end data architecture, from selecting the platform, designing the technical architecture, and developing the application to finally testing and implementing the proposed solution.\n\u00b7 Planning and execution of big data solutions using appropriate technologies and ensure their full lifecycle and interoperability.\n\u00b7 Defining and managing the flow of data and dissemination of information within the organization.\n\u00b7 Integrating technical functionality, ensuring data accessibility, accuracy, and security.\n\u00b7 Conducting a continuous audit of data management system performance, refine whenever required, and report immediately any breach or loopholes to the stakeholders.\nWHAT ARE WE LOOKING FOR?\nMaster's degree in computer science or equivalent work experience\nMinimum of 10 years of experience in IT systems design or development.\nMinimum 5 years of experience gained in data architecture and delivering large scale analytics data platforms environments.\nKnowledge of systems development, including system development life cycle, project management approaches and requirements, design and testing techniques\nProven experience in design and building data models, data domains and understanding business data products (proficiency in data modeling and design, including SQL development and database administration).\nUnderstanding of predictive modeling, AI models and technologies, Data mining, visualization and Machine Learning\nAbility to implement common data management and reporting technologies, as well as the basics of columnar and NoSQL databases, data visualization, unstructured data, and predictive analytics.\nStrong and broad knowledge of latest technology stacks and trends, cloud-based data platforms and data lakes (preferably AWS and Snowflake technologies)\nExperience with data integration methods and technologies (e.g., ETL, Data Virtualization, Master Data Management, Data Warehouse/Lakehouse).\nUnderstanding of business strategy and ability to deliver recommendations in sync with key objectives and experience in developing and driving IT roadmaps.\nCapacity to coordinate and collaborate with users, system designers, and developers in their day-to-day functions. As such, soft skills like effective communication, team management, problem-solving, and leadership are highly desirable.\nStrong analytical skills and business acumen, ideally in the logistics sector.\nFluent English and proven practice.\nWHAT DO WE HAVE TO OFFER?\nPermanent contract.\nHybrid work: 4 days at the office and 1 remote.\nCompetitive salary.\nYou will work for one of the world 's leading logistics operators that will help you in your career development by offering you multiple opportunities.\nYou will receive on the job training that help you to better understand operational processes.\nABOUT TOMORROW\nWe offer professional opportunities for you to develop in CEVA. We value your professional and personal growth.\nJoin CEVA for a challenging carrer.\nCEVA Iberia is committed to attracting, acquiring and retaining the best possible candidates in an equitable and inclusive manner that is consistent with labor laws and best practices.\n#LI-SP1\nShow more\nShow less",
        "skills": {
            "ProgLanguage": [
                "R",
                "Go"
            ],
            "DataBase": [
                "SQL",
                "NoSQL"
            ],
            "DataAnalytics": [
                "R"
            ],
            "BigData": [],
            "MachingLearning": [],
            "DataSerialization": [],
            "DataVisualization": [],
            "Statistics": [],
            "CloudComputing": [
                "AWS"
            ],
            "DevTools": [
                "Git"
            ],
            "Os": [],
            "DBMS": [
                "Snowflake",
                "Snowflake"
            ],
            "SoftBigDataProcessing": [],
            "Automation": [],
            "InfrastructureAsCode": [],
            "NetworkSecurty": [],
            "Virtualisation": [],
            "Containers": [],
            "Collaboration": [
                "Teams"
            ],
            "Other": [
                "Big Data",
                "Machine Learning",
                "Cloud"
            ],
            "FrSoftSkills": [
                "Communication",
                "Leadership"
            ],
            "EnSoftSkils": [
                "Communication",
                "Leadership",
                "Organization"
            ]
        },
        "details": {
            "JobDetail": [
                "Remote",
                "Full",
                "Senior"
            ],
            "TypeContract": [],
            "Salary": [
                "Salary"
            ],
            "Level": [],
            "Experience": [
                "a",
                "n",
                "s"
            ]
        }
    },
    {
        "source": "LinkedIn",
        "title": "Solutions Architect",
        "company": "Airswift",
        "location": "Greater Paris Metropolitan Region",
        "link": "https://fr.linkedin.com/jobs/view/solutions-architect-at-airswift-3919714188?position=6&pageNum=0&refId=a5rwPua%2FMvx%2F2M%2FPSF0oPA%3D%3D&trackingId=b3MGM2D190q9EWNC%2FP5I3A%3D%3D&trk=public_jobs_jserp-result_search-card",
        "description": "\ud83d\ude80\nNow Hiring: Data-Cloud Solution Architect - FREELANCE\n\ud83d\udccd Location: On-site near Paris (3 days a week)\nAre you ready to join a cutting-edge Data Transformation initiative? We are seeking a talented\nData-Cloud Solution Architect\nto play a pivotal role in shaping the future of our client's data capabilities. This role offers an exciting opportunity to work on a complete set of data functionalities, from architecture and engineering to visualization and warehousing.\nRole & Responsibilities:\nProvide technical guidance and establish best practices for Snowflake account setup and configuration.\nManage Infrastructure-as-code and maximize automation.\nLead enhancements and deployments to support a fully federated Platform.\nAct as a Subject Matter Expert (SME) for all Snowflake-related queries.\nOwn platform-specific Snowflake documentation, including decisions and best practices.\nDesign the cloud environment holistically to meet all functional and non-functional requirements.\nExecute deployment, maintenance, monitoring, and management tasks.\nOversee cloud security for the account.\nComplete the integration of new applications into the cloud environment.\nRequirements:\nHigher education completed, preferably with a degree in Computer Sciences.\n5 to 10 years of experience in implementing Data Platforms in a cloud environment.\nFluent in French & English (must).\nDeep expertise in Snowflake.\nStrong skills in platform architecture, DBA, and cloud database administration.\nProficiency in AWS Architecture and cloud networking.\nExcellent communication, coordination, and collaboration skills.\nAbility to manage stakeholders, mitigate risks, and demonstrate leadership.\nOpen-mindedness and willingness to take on challenges.\nHighly motivated, adaptable, and flexible.\nThis is a contract position lasting until the end of 2024, with the possibility of extension. Join us in driving innovation and shaping the future of data! #DataArchitect #Snowflake #AWS #CloudComputing #ParisJobs #TechJobs\nShow more\nShow less",
        "skills": {
            "ProgLanguage": [
                "R"
            ],
            "DataBase": [],
            "DataAnalytics": [
                "R"
            ],
            "BigData": [],
            "MachingLearning": [],
            "DataSerialization": [],
            "DataVisualization": [],
            "Statistics": [],
            "CloudComputing": [
                "AWS"
            ],
            "DevTools": [],
            "Os": [],
            "DBMS": [
                "Snowflake",
                "Snowflake"
            ],
            "SoftBigDataProcessing": [],
            "Automation": [],
            "InfrastructureAsCode": [],
            "NetworkSecurty": [],
            "Virtualisation": [],
            "Containers": [],
            "Collaboration": [],
            "Other": [
                "Cloud"
            ],
            "FrSoftSkills": [
                "Communication",
                "Leadership",
                "Collaboration"
            ],
            "EnSoftSkils": [
                "Communication",
                "Leadership",
                "Collaboration",
                "Initiative"
            ]
        },
        "details": {
            "JobDetail": [
                "Full"
            ],
            "TypeContract": [],
            "Salary": [],
            "Level": [],
            "Experience": [
                "a",
                "n",
                "s"
            ]
        }
    },
    {
        "source": "LinkedIn",
        "title": "Data Architect (F/H)",
        "company": "Micropole",
        "location": "Levallois-Perret, \u00cele-de-France, France",
        "link": "https://fr.linkedin.com/jobs/view/data-architect-f-h-at-micropole-3652819338?position=7&pageNum=0&refId=a5rwPua%2FMvx%2F2M%2FPSF0oPA%3D%3D&trackingId=yzPwOD7STCK0AuX%2BJ6fjKg%3D%3D&trk=public_jobs_jserp-result_search-card",
        "description": "Rejoignez le Groupe Micropole. Devenez un #InnovativePeople !\nMission\nEn R\u00e9sum\u00e9\nLocalit\u00e9 : Levallois-Perret\nType de contrat : CDI\nNiveau d\u2019exp\u00e9rience : au moins 7 ans\nAccord de t\u00e9l\u00e9travail & Flex office\nVous \u00eates\npassionn\u00e9(e) par la data\n? Vous \u00eates convaincus que l\u2019optimisation du\npatrimoine data des entreprises\nest la cl\u00e9 de leur performance ? Vous voulez\nrendre les entreprises data intelligentes\net les aider \u00e0 se transformer pour pr\u00e9parer d\u00e8s \u00e0 pr\u00e9sent leur futur ?\nVous souhaitez rejoindre un groupe pionnier des grandes innovations data et digitales ?\nSi vous avez\nr\u00e9pondu \u00ab\u202fOui\u202f\u00bb\n\u00e0 chacune de ces questions alors devenez Data Architect pour l\u2019un de\nnos clients grands-comptes.\nPr\u00eat(e) \u00e0 rejoindre l\u2019aventure Micropole ? N\u2019attendez plus !\nAu sein de Micropole, nous vous proposons de rejoindre notre practice \u00ab Data Governance et Architecture \u00bb, compos\u00e9e de 80 #InnovativePeople et reconnue comme leader europ\u00e9en de la Gouvernance des donn\u00e9es.\nEn Tant Qu' Architect\nLes donn\u00e9es en entreprise sont trop souvent organis\u00e9es en silos ne laissant aux m\u00e9tiers qu'une vision parcellaire de l'information.\nAfin d'amener une plus grande valeur et de l'efficacit\u00e9 au niveau des processus op\u00e9rationnels et d\u00e9cisionnels de l'entreprise, nous accompagnons nos clients dans la gouvernance de leurs donn\u00e9es en les hi\u00e9rarchisant au sein du syst\u00e8me d'information. Nous abordons ainsi, le cycle de vie de la donn\u00e9e produit depuis la R&D jusqu'au Digital.\nAu sein de Micropole, nous vous proposons de rejoindre notre practice \u00ab Data Gouvernance et Architecture \u00bb bas\u00e9e \u00e0 Levallois-Perret, compos\u00e9e de 80 #InnovativePeople et reconnue comme leader europ\u00e9en de la Gouvernance des donn\u00e9es.\nDans Vos Missions Quotidiennes, Vous \u00cates Amen\u00e9(e)s \u00e0\n\u00catre l\u2019interface entre le client et l\u2019\u00e9quipe projet :\nPrise en compte des enjeux m\u00e9tier afin d\u2019aligner l\u2019architecture sur la strat\u00e9gie de l\u2019entreprise notamment vis-\u00e0-vis de la transformation digitale des entreprises et des enjeux r\u00e9glementaires ;\nD\u00e9finir la roadmap de mise en \u0153uvre ;\nD\u00e9finir les principes d\u2019urbanisation autour des donn\u00e9es ;\nCadrer les projets : r\u00e9f\u00e9rentiels (MDM), Data Hub, Big Data, gouvernance des donn\u00e9es, \u00e9change (ETL/ESB/IPaaS) ;\nAuditer les architectures existantes sur les axes qualit\u00e9, et urbanisation des donn\u00e9es ;\nAnimer les workshops de conception dans le cadre de projets d\u2019impl\u00e9mentation ;\nAccompagner sur les phases de cadrage \u00e0 la d\u00e9finition des mod\u00e8les de donn\u00e9es et des processus de gouvernance op\u00e9rationnelle ;\nR\u00e9aliser la conception technique et fonctionnelle des interfaces d\u2019\u00e9change.\nParticiper activement aux avant-ventes et d\u00e9marche de validation de concepts :\nParticipation aux phases de r\u00e9ponses \u00e0 appel d\u2019offre ;\nParticipation sur la production de d\u00e9monstrateur en lien avec nos partenaires \u00e9diteurs ;\nAnimation de s\u00e9minaires d\u2019acculturation \u00e0 la data.\nProfil\nVos Comp\u00e9tences Techniques\nVous maitrisez au moins une solution du march\u00e9 li\u00e9e \u00e0 la gouvernance des donn\u00e9es (MDM, Data Catalogue, DQM, Data Fabric, IPaaS, ETL/ESB).\nVos Atouts\nVous avez au moins 7 ans d\u2019exp\u00e9rience professionnelle sur la d\u00e9finition d\u2019architecture data ;\nVous ma\u00eetrisez les concepts de la gouvernance des donn\u00e9es, et disposez d\u2019une d\u2019exp\u00e9rience projet sur une des solutions leaders du march\u00e9 ;\nV\u00e9ritable co\u00e9quipier(e), vous avez \u00e0 c\u0153ur de contribuer \u00e0 la mont\u00e9e en comp\u00e9tence de votre \u00e9quipe ;\nVous disposez d\u2019un bon niveau de fran\u00e7ais et d\u2019anglais, \u00e0 l\u2019oral comme \u00e0 l\u2019\u00e9crit.\nLa Vie Chez Micropole, C\u2019est\nUne vie interne rythm\u00e9e pour se familiariser \u00e0 la culture d\u2019entreprise et aux valeurs de Micropole ;\nDes \u00e9v\u00e8nements internes r\u00e9guliers pour partager les connaissances aussi bien techniques que fonctionnelles ;\nUne politique de formation attractive et \u00e9clectique ;\nUn travail en \u00e9quipe valoris\u00e9 pour une meilleure coh\u00e9sion ;\nLa participation \u00e0 des projets internes sur la base du volontariat.\nDevenir #INNOVATIVEPEOPLE, c\u2019est :\nInt\u00e9grer une communaut\u00e9 de 1100 experts passionn\u00e9s r\u00e9partis entre la France, la Belgique, le Luxembourg, la Suisse, l\u2019Espagne et la Chine ;\nConstruire ensemble les solutions strat\u00e9giques et innovantes de demain pour accompagner nos clients dans leur transformation data et digitale ;\nParticiper au d\u00e9veloppement de nos 4 centres d\u2019excellences cloud : AWS, Microsoft Azure, Salesforce, GCP ;\nEvoluer continuellement au travers de formations et de certifications sur les plus grandes technologies gr\u00e2ce \u00e0 Micropole Campus ;\nS\u2019assurer d\u2019une innovation continue gr\u00e2ce \u00e0 : notre \u00e9cosyst\u00e8me de partenaires technologiques ; notre acc\u00e9l\u00e9rateur de start\u2019up databoost\u2019R ; nos lieux d\u2019innovations \u00ab innovativeSpaces \u00bb et de co-construction avec les clients ; notre management par les talents naturels.\nProcessus De Recrutement\nChez Micropole, le processus de recrutement est r\u00e9actif et transparent.\nEtape 1 \u2013 Si votre profil correspond \u00e0 nos besoins, vous \u00eates recontact\u00e9s dans les 72 heures qui suivent votre candidature par Victoria notre Talent Business Partner d\u00e9di\u00e9e \u00e0 Data Gouvernance & Architecture pour une qualification t\u00e9l\u00e9phonique ainsi qu'un premier entretien en visio ;\nEtape 2 \u2013 Vous rencontrez un manager avec l\u2019un de nos experts comme Aur\u00e9lien, R\u00e9gis ou Jofrey.\nEn fonction du poste, vous pouvez passer des \u00e9tapes suppl\u00e9mentaires (entretien ou test technique).\n\u00c0 PROPOS DU GROUPE MICROPOLE\nGroupe international de conseil et technologies innovantes, MICROPOLE est sp\u00e9cialis\u00e9 dans les domaines de la Data & Digital. Depuis ses 14 agences situ\u00e9es en Europe et en Chine, les 1200 #INNOVATIVE PEOPLE du Groupe (consultants, Data scientists, architectes IT, experts m\u00e9tiers, ing\u00e9nieurs, UX designers\u2026) accompagnent leurs clients partout dans le monde sur l'ensemble des phases de leurs projets, du conseil \u00e0 leur r\u00e9alisation, et sur la conduite du changement.\nMICROPOLE r\u00e9alise 35% de son chiffre d\u2019affaires \u00e0 l\u2019international et est cot\u00e9 sur le march\u00e9 Eurolist compartiment C d\u2019Euronext Paris, segment Next Economy.\nPour en savoir plus : https://www.linkedin.com/company/micropole/\nInfos pratiques\nA 200m, le m\u00e9tro Anatole France (Ligne 3) et un acc\u00e8s \u00e0 l'ensemble des commerce du centre ville de Levallois-Perret \u00e0 moins de 2 min \u00e0 pied.\nMot du Manager\nFace \u00e0 des enjeux de compliance toujours plus exigeants et rigoureux, la gouvernance des donn\u00e9es devient absolument indispensable pour garantir la coh\u00e9rence, maitriser la qualit\u00e9 et la connaissance du socle des donn\u00e9es des entreprises et assurer leur bonne mise en conformit\u00e9.\nShow more\nShow less",
        "skills": {
            "ProgLanguage": [
                "R",
                "Go"
            ],
            "DataBase": [],
            "DataAnalytics": [
                "R"
            ],
            "BigData": [],
            "MachingLearning": [],
            "DataSerialization": [],
            "DataVisualization": [],
            "Statistics": [],
            "CloudComputing": [
                "AWS",
                "Azure"
            ],
            "DevTools": [
                "Git"
            ],
            "Os": [],
            "DBMS": [],
            "SoftBigDataProcessing": [],
            "Automation": [],
            "InfrastructureAsCode": [],
            "NetworkSecurty": [],
            "Virtualisation": [],
            "Containers": [],
            "Collaboration": [],
            "Other": [
                "Big Data",
                "Cloud"
            ],
            "FrSoftSkills": [],
            "EnSoftSkils": []
        },
        "details": {
            "JobDetail": [],
            "TypeContract": [
                "CDI"
            ],
            "Salary": [],
            "Level": [],
            "Experience": [
                "a",
                "n",
                "s",
                "7",
                "7",
                "7"
            ]
        }
    },
    {
        "source": "LinkedIn",
        "title": "Enterprise Architect - Digital Workplace",
        "company": "AXA",
        "location": "Greater Paris Metropolitan Region",
        "link": "https://fr.linkedin.com/jobs/view/enterprise-architect-digital-workplace-at-axa-3845642526?position=8&pageNum=0&refId=a5rwPua%2FMvx%2F2M%2FPSF0oPA%3D%3D&trackingId=1QxAWv6oNOBK0QHumiAgPA%3D%3D&trk=public_jobs_jserp-result_search-card",
        "description": "AXA GROUP OPERATIONS\nAXA is becoming a sustainable tech-led company and at AXA Group Operations we are one of the major catalysts for this transformation.\nWe set the tone by triggering and empowering the evolution of our insurance business model through technology and innovation, driving its concrete implementation globally at speed, with a high quality of advisory and execution.\nWe are present across 17 countries with committed, highly qualified teams. We leverage technology, data, sourcing, security and investment allocation in a global way, but also achieve economies of scale and synergies when necessary.\nAt\nAXA Group Operations\n, we want to be recognized in three fields of action:\nState-of-the-art Data Technology to drive customer experience\nState-of-the-art Procurement & Sourcing to drive efficiency and better manage risks\nHigh-Performing Global Team for stronger partnerships with AXA entities\nWorking as part the Group\u2019s Technology Office, the\nDigital Workplace Entrerprise Architect,\nis responsible for providing architecture, vision, governance, problem anticipation and solving for IT on a transversal architectural level. This transversal scope of the architecture covers business, security, data, application and technology architecture.\nHe manages and coordinates, for his areas of responsibility \u2013 here transversal Workplace topics \u2013 , the work carried out by the other Architects cross-domains and Chief Architects / Chief Technology Officers from AXA Group Operations and AXA entities in close collaboration with GO departments for the global assets, with Group Security for the Security part, and with Business Partnership and the Markets/Entities for the entities related part.\nTransversal\nWorkplace topics\nscope will cover this non exhaustive list:\nDevice Management\nApplication delivery\nCollaboration & Productivity\nUX / QoS Monitoring\nWorkplace interaction with other domains (Security, IAM, Network, Cloud, Compliance\u2026)\nThe\nDigital Workplace Entrerprise Architect\n's role is to\nsteer the Architecture evolution\nacross AXA to ensure the\nproper implementation\nof the IT Strategy and to be able to adopt new technologies and new market solutions in line with the business priorities, the foundations of the products structure and with the aim support AXA to become a Tech Led Company.\nThe individual in this position understands the Group business strategy, the Information Systems (IS) of the Group and anticipates future directions of the IT industry to relate them to future business needs and initiatives. The Lead Architect Expert produces\nkey architecture deliverables\n, leads international workgroups and studies to\nestablish IT directions\nfor the Group and is responsible for the architecture review of projects related to technologies in his domain of responsibility.\nMAIN MISSIONS :\nThe objective of architecture is to ensure that we build sustainable, robust and secured Information Systems at the right cost and that bring business value to support the corporate business and lines of business strategies.\nThe Digital Workplace Entrerprise Architect main activity is to craft the IT Strategy of the Group and act as a change agent to implement this IT Strategy through the Target Enterprise Architecture of the Group, and of individual countries within the Group. He may also be called upon to directly support PMs on some key projects.\nThe core activities of the Lead Architect Expert include the following for his own area of responsibility :\n1- Vision and Strategy\nSupport the definition and management of the company Technology vision, strategies and plans with focus on domains related to his role\n2- Contribute to Technology/Architecture CTO Community and Technology Governance of the Group:\nTo cover global and local dimensions, which includes ensuring design and solution choices made in the entities are conform to Group Strategy in order to secure Group interests over the long-term (Architecture boards\u2026)\nTo share technological visions, opportunities, and risks company-wide, and in particular interact with senior business and IT executives\n3- Define, build and maintain architecture & design patterns, jointly with Product engineering teams aiming to minimize technical complexity and leverage convergence opportunities:\nArchitecture landscape\nArchitecture Model & Maturity\nArchitecture evolution and product design blueprints, HLD\nSupporting LLD delivery with Product teams\n4- Market Watch:\nParticipate to forums of leading companies (cross-industries) and vendors in order to use and/or influence technology evolutions\nIn particular, study industry trends and technologies in close collaboration with Group Data & Technology Innovation\nManage evaluation, development, and deployment of relevant technologies (technology lifecycle & roadmaps)\n5- Provide support to all Group IT supporting functions, in particular for Procurement and Finance for large negotiations or assets\nPROFILE\nExperience :\nStrong experience in IT Strategy, enterprise and solution architecture (10+ years)\nExperience on solutions architecture designs for very large projects/environments in particular in Workplace (both Device management and Collaboration)\nStrong change management skills with practical experience of transformation in an international environment\nFinancials (princiles, business cases, budgeting, business-planning, savings)\nStrives for excellence with deliverables of high quality and ability to work in sometimes tight planning\nDemonstrates to be a strong team member with an open and collaborative mind-set.\nSoft skills :\nThe person will have to interact and collaborate with multiple global and local stakeholders and different levels (peers, managers, experts, C-Levels\u2026). To succeed in his role, this can be achieved through:\nLeadership \u2013 Exhibits strong results orientation, change leadership, adaptability and the ability to drive collaborative behaviour.\nOpenness and reaching out \u2013 Strong human relationship skills, exhibit curiosity and can see opportunities in situations, not just problems.\nCommunication skills \u2013 Exhibits strong skills in listening, spoken and written communication, collaboration and the ability to work in a global team. Lead Architect Experts are expected to have the ability to understand and discuss with both senior managers and IT, and explain in clear language complicated architectural concepts and strategies.\nVision \u2013 Lead Architecture Expert demonstrates architectural vision and beliefs and is able to express them clearly, champion them, and debate his point of view in on-line forums or in-person workshops.\nEmbracing of the new AXA values and new ways of working with courage to promote them against tradition\nOpenness to different opinions and creation of consensus\nProblem solving orientation and strong analytical, logical and interpretive ability to interpret scenarios, express concepts or models with several dimensions: architecture, business value, procurement, program approach \u2026\nHas a deep understanding of the organizational structures, in order to be in a position to better identify improvement points\nInternational profile \u2013 A proven ability to work effectively in an international environment. In addition, exhibits a strong proficiency in English.\nTechnical skills :\nExpert knowledge in IT strategy focusing on Workplace Architecture with related infrastructure good practices\nExpertise in Workplace with critical thinking and decision making, information systems knowledge, innovation, knowledge of emerging technology, planning, risk management, systems thinking, application rationalization/TCO, IT Security and technical problem solving.\nGood expertise in the practice of Architecture (frameworks) to deliver a holistic view (architecture model)\nShow more\nShow less",
        "skills": {
            "ProgLanguage": [
                "R",
                "Go"
            ],
            "DataBase": [],
            "DataAnalytics": [
                "R"
            ],
            "BigData": [],
            "MachingLearning": [],
            "DataSerialization": [],
            "DataVisualization": [],
            "Statistics": [],
            "CloudComputing": [],
            "DevTools": [
                "Git"
            ],
            "Os": [],
            "DBMS": [],
            "SoftBigDataProcessing": [],
            "Automation": [],
            "InfrastructureAsCode": [],
            "NetworkSecurty": [],
            "Virtualisation": [],
            "Containers": [],
            "Collaboration": [
                "Teams"
            ],
            "Other": [
                "Cloud"
            ],
            "FrSoftSkills": [
                "Communication",
                "Leadership",
                "Collaboration"
            ],
            "EnSoftSkils": [
                "Communication",
                "Adaptability",
                "Problem Solving",
                "Leadership",
                "Collaboration",
                "Organization",
                "Initiative",
                "Critical Thinking"
            ]
        },
        "details": {
            "JobDetail": [
                "Senior"
            ],
            "TypeContract": [],
            "Salary": [],
            "Level": [],
            "Experience": [
                "a",
                "n",
                "s"
            ]
        }
    },
    {
        "source": "LinkedIn",
        "title": "Data Architect Cloud F/H",
        "company": "VISEO",
        "location": "Boulogne-Billancourt, \u00cele-de-France, France",
        "link": "https://fr.linkedin.com/jobs/view/data-architect-cloud-f-h-at-viseo-3904217803?position=9&pageNum=0&refId=a5rwPua%2FMvx%2F2M%2FPSF0oPA%3D%3D&trackingId=267fBpZ5knn1TQJTgrSw8g%3D%3D&trk=public_jobs_jserp-result_search-card",
        "description": "Rejoignez\nVISEO\net explorez un univers de possibilit\u00e9s o\u00f9\nl'Humain\n, le\nCollectif\net le\nChallenge\nsont au c\u0153ur de notre ADN.\nQui \u00eates-vous ?\nSi pour vous \u00eatre\nArchitecte Cloud & Data\n, c'est :\nInt\u00e9grer une \u00e9quipe d'experts en solutions cloud et en gestion de donn\u00e9es ;\nConcevoir et d\u00e9ployer des architectures cloud scalables et s\u00e9curis\u00e9es sur Google Cloud Platform et/ou Azure ;\nMa\u00eetriser les services GCP (BigQuery, Cloud Composer, Cloud Functions , Cloud Run) et/ou Azure (Synapse , Data Factory , ADLS , SQL Database)\nMaitriser les pratiques DevOps (CI/CD, monitoring, logging) ;\nMaitriser Python et ses biblioth\u00e8ques data\nD\u00e9couvrir et tester les nouvelles plateformes data (Exemple : Microsoft Fabric)\nOptimiser les co\u00fbts et les performances des solutions cloud pour garantir une efficacit\u00e9 maximale ;\nCollaborer avec les \u00e9quipes de d\u00e9veloppement pour int\u00e9grer les meilleures pratiques de gestion des donn\u00e9es et d'analytique...\nAlors, vous \u00eates la personne que nous recherchons !\nSi vous avez une exp\u00e9rience significative en\narchitecture cloud et data\net que vous \u00eates pr\u00eat \u00e0 relever de nouveaux\nd\u00e9fis\net \u00e0 enrichir votre parcours professionnel, c'est le moment id\u00e9al pour nous rejoindre.\nCe que nous allons faire ensemble ?\nD\u00e9couvrez comment votre quotidien sera r\u00e9volutionn\u00e9 en int\u00e9grant notre \u00e9quipe bas\u00e9e \u00e0 Paris. Vous pourrez :\n\u00catre acteur dans la conception des solutions cloud et data, en apportant votre expertise technique ;\nAssurer la qualit\u00e9 et la s\u00e9curit\u00e9 des infrastructures cloud (conformit\u00e9, r\u00e9silience, performance) ;\nPartager vos connaissances et innover au sein d'un collectif passionn\u00e9 par les technologies de pointe.\nCe que nous avons \u00e0 vous offrir ?\nDes formations avanc\u00e9es, des certifications GCP et un accompagnement personnalis\u00e9 pour votre d\u00e9veloppement professionnel ;\nUn cadre de travail dynamique, flexible et agile pour une carri\u00e8re sans fronti\u00e8res ;\nUn engagement profond pour l'environnement, la soci\u00e9t\u00e9, l'\u00e9galit\u00e9 et l'inclusion ;\nUn accord t\u00e9l\u00e9travail pour une harmonie parfaite entre vie professionnelle et personnelle.\nCe qui nous diff\u00e9rencie ?\nUne communaut\u00e9 active d'experts en cloud et data : des ateliers r\u00e9guliers, la participation \u00e0 des conf\u00e9rences sp\u00e9cialis\u00e9es ;\nDes dispositifs d'\u00e9pargne salariale attractifs (PEE et PERECO) et l'opportunit\u00e9 de devenir actionnaire de VISEO ;\nUn partenariat \u00e9troit avec Google & Microsoft, offrant un acc\u00e8s privil\u00e9gi\u00e9 aux derni\u00e8res innovations et technologies cloud.\nEnvie de nous rejoindre ? Contactez-nous et adoptez le #VISEOspirit\nEn tant qu'employeur, VISEO s'engage en faveur de la diversit\u00e9 et de l'inclusion.\n\u00c0 propos de VISEO\nAvec 3 000 collaborateurs pr\u00e9sents sur 5 continents, VISEO combine agilit\u00e9 et expertise pour transformer le num\u00e9rique en un v\u00e9ritable levier de comp\u00e9titivit\u00e9 et de performance.\n#PositiveDigitalMakers\nGDPR MESSAGE:\nOur privacy policy has been updated to comply with the new regulations. We invite you to consult it by clicking here: https://www.viseo.com/fr/politique-de-confidentialite. The VISEO Group uses the data collected as part of your application to assess your suitability for the job in question. We use the Jazz HR tool to help us in our recruitment process. This tool complies with current regulations on the protection of personal data. The tool is hosted in the United States and is PrivacyShield certified for HR data. In all cases, we may keep your file for 5 years so that we can contact you again if another position matches your profile. You may, of course, object to this. To find out more about how your data is used and how you can exercise your rights, please consult our privacy policy https://www.viseo.com/fr/politique-de-confidentialite.\nShow more\nShow less",
        "skills": {
            "ProgLanguage": [
                "Python",
                "Scala",
                "R",
                "Go"
            ],
            "DataBase": [
                "SQL"
            ],
            "DataAnalytics": [
                "R"
            ],
            "BigData": [],
            "MachingLearning": [],
            "DataSerialization": [],
            "DataVisualization": [],
            "Statistics": [],
            "CloudComputing": [
                "Azure",
                "Google Cloud Platform"
            ],
            "DevTools": [
                "Git"
            ],
            "Os": [],
            "DBMS": [
                "BigQuery"
            ],
            "SoftBigDataProcessing": [],
            "Automation": [],
            "InfrastructureAsCode": [],
            "NetworkSecurty": [],
            "Virtualisation": [],
            "Containers": [],
            "Collaboration": [],
            "Other": [
                "DevOps",
                "Cloud",
                "CI/CD"
            ],
            "FrSoftSkills": [],
            "EnSoftSkils": []
        },
        "details": {
            "JobDetail": [],
            "TypeContract": [],
            "Salary": [],
            "Level": [],
            "Experience": [
                "a",
                "n",
                "s"
            ]
        }
    },
    {
        "source": "LinkedIn",
        "title": "Data Architect (H/F)",
        "company": "PROXIAD",
        "location": "Lyon, Auvergne-Rh\u00f4ne-Alpes, France",
        "link": "https://fr.linkedin.com/jobs/view/data-architect-h-f-at-proxiad-3908705011?position=10&pageNum=0&refId=a5rwPua%2FMvx%2F2M%2FPSF0oPA%3D%3D&trackingId=5T%2Ftx9Gs0LAlbOyht9BGDw%3D%3D&trk=public_jobs_jserp-result_search-card",
        "description": "Dans le cadre de notre d\u00e9veloppement, nous recrutons pour int\u00e9grer notre \u00e9quipe sur Lyon (69) :\nData Architect (H/F)\nVos missions, si vous les acceptez :\nVous assurez le leadership technique, participez au d\u00e9veloppement, et repr\u00e9sentez les ressources internes et externes de la plateforme\nVous serez un membre actif de l\u2019\u00e9quipe des architectes, afin de superviser le processus de gestion des donn\u00e9es et fournir des conseils et orientations aux \u00e9quipes de d\u00e9veloppement\nVous serez responsable de la conception, et de la documentation de la solution dans votre domaine\nVous aurez la responsabilit\u00e9 compl\u00e8te de l\u2019architecture\nVous serez support aux \u00e9quipes techniques dans l\u2019int\u00e9gralit\u00e9 du cycle de vie de la gestion des donn\u00e9es.\nEnvironnement Technique :\nExp\u00e9rience dans le d\u00e9veloppement, la documentation et la maintenance de mod\u00e8les de donn\u00e9es logiques et physiques\nExp\u00e9rience sur Databricks, ADLS storage, SQL DB, ADF et Power BI\nExp\u00e9rience dans la d\u00e9finition et la ma\u00eetrise d'une architecture de donn\u00e9es \u00e9volutive de bout en bout, en tenant compte de l'architecture de l'entreprise et des normes industrielles.\nParticipation \u00e0 l'\u00e9laboration d'architectures, strat\u00e9gies et politiques en mati\u00e8re de donn\u00e9es, y compris la s\u00e9curit\u00e9 des donn\u00e9es\nLangage SQL Writing et mod\u00e9lisation de donn\u00e9es\nData Architecture\nPower BI\nAzure ADFv2, Databricks, Synapse, Delta Lake\nEnvironnement et technologie Azure Advanced Analytics\nPython, Pyspark\nMicrosoft cloud bas\u00e9 sur mod\u00e8le Delivery\nData Management, Data Governance et Data Quality\nD\u00e9ploiement d\u2019APIs et micro-services\nDevSecOps\nAgile\nExp\u00e9rience professionnelle dans un environnement international\nLe profil que nous recherchons :\nDe formation informatique, vous poss\u00e9dez une exp\u00e9rience significative d\u2019au moins 4 ans minimum en tant que Data Architect.\nVous avez le sens de l\u2019\u00e9coute, une bonne gestion des priorit\u00e9s, vous avez un bon relationnel et de la rigueur.\nVous disposez d\u2019une excellente communication.\nVous vous reconnaissez dans cette description ? Echangeons !\nPourquoi nous rejoindre ?\nL\u2019innovation, la qualit\u00e9 et l\u2019agilit\u00e9 sont au c\u0153ur du d\u00e9veloppement de nos activit\u00e9s IT, encadr\u00e9es et assur\u00e9es par nos 850 collaborateurs et collaboratrices fran\u00e7ais(es) et bulgares !\nNotre savoir-faire ?\nConseil, D\u00e9veloppement, Analyse et Expertise Informatique pour accompagner nos clients dans l'\u00e9volution et la transformation de leur SI.\nEn plus de notre ma\u00eetrise des technologies PHP, JavaEE et .Net qui sont des composantes fortes de notre savoir-faire, nous mettons en avant une expertise d\u00e9di\u00e9e aux applications mobiles et XNet (Inter, Intra et Extranet) et au d\u00e9veloppement de notre offre infrastructure (syst\u00e8mes, r\u00e9seaux, cybers\u00e9curit\u00e9\u2026).\nNos valeurs ?\nL\u2019engagement, le pragmatisme, la proximit\u00e9, l\u2019\u00e9volution et le partage. Aussi bien avec nos clients qu\u2019avec nos collaborateurs (F/H).\nR\u00e9sultats ?\nUne entreprise en pleine croissance avec des collaborateurs (F/H) \u00e9panouis et reconnus au quotidien ! Des clients fid\u00e8les et reconnaissants de la qualit\u00e9 des prestations fournies !\nNos collaborateurs \u0153uvrent chaque jour \u00e0 satisfaire et concr\u00e9tiser les id\u00e9es les plus folles et innovantes de nos clients !... N\u2019attendez plus et tentez l\u2019exp\u00e9rience PROXIAD !\nToutes les demandes seront trait\u00e9es avec la plus stricte confidentialit\u00e9. Seuls les candidats retenus seront contact\u00e9s.\nShow more\nShow less",
        "skills": {
            "ProgLanguage": [
                "Python",
                "Java",
                "R",
                "Go"
            ],
            "DataBase": [
                "SQL"
            ],
            "DataAnalytics": [
                "R"
            ],
            "BigData": [
                "Spark",
                "Databricks"
            ],
            "MachingLearning": [],
            "DataSerialization": [],
            "DataVisualization": [
                "Power BI"
            ],
            "Statistics": [],
            "CloudComputing": [
                "Azure"
            ],
            "DevTools": [],
            "Os": [],
            "DBMS": [],
            "SoftBigDataProcessing": [],
            "Automation": [],
            "InfrastructureAsCode": [],
            "NetworkSecurty": [],
            "Virtualisation": [],
            "Containers": [],
            "Collaboration": [],
            "Other": [
                "Cloud"
            ],
            "FrSoftSkills": [
                "Communication",
                "Leadership"
            ],
            "EnSoftSkils": [
                "Communication",
                "Leadership"
            ]
        },
        "details": {
            "JobDetail": [],
            "TypeContract": [],
            "Salary": [],
            "Level": [],
            "Experience": [
                "a",
                "n",
                "s",
                "4",
                "4",
                "4"
            ]
        }
    },
    {
        "source": "LinkedIn",
        "title": "Solutions Architect (Digital & Data)",
        "company": "Coders Connect",
        "location": "Paris, \u00cele-de-France, France",
        "link": "https://fr.linkedin.com/jobs/view/solutions-architect-digital-data-at-coders-connect-3889484245?position=11&pageNum=0&refId=a5rwPua%2FMvx%2F2M%2FPSF0oPA%3D%3D&trackingId=wYBT2jbq5kAyS9RkDIEUCw%3D%3D&trk=public_jobs_jserp-result_search-card",
        "description": "Coders Connect\nand\nSanofi\nare joining forces to bring an electrifying twist to the biopharmaceutical world!\nWork with a rhythm that suits your style (2 days remote and 3 days onsite magic).\nLanguage:\nProficiency in English is required for this role to ensure effective communication within our diverse, global team.\nAbout Sanofi:\nWe're not just a company; we're a global movement, focused on human health and making a real difference. Our mission? To battle pain, ease suffering, and sprinkle a little bit of magic in the process by developing life-changing medicines and vaccines through breakthrough science and wizard-level technology.\nDigital & Data: The Pulse of Our Mission\nAt the heart of our quest lies our digital and data powerhouse. Think of us as the digital healthcare platform of your dreams, where innovation meets speed, and technology shakes hands with medicine. With our scale, deep-rooted connections in health ecosystems worldwide, and a knack for pushing boundaries, we're here to revolutionize medicine, one digital solution at a time.\nYour Mission as a Solution Architect:\n\u200b\nAs our Solution Architect, you're the master planner of our digital architecture, crafting scalable and sustainable solutions that power advanced analytics, AI, and ML initiatives. You'll design the blueprint for our data platforms and technology stacks, ensuring they align with our strategic goals and adhere to the highest standards of quality and innovation.\nRequirements\nCloud Mastery:\nDeep expertise in cloud-based services, particularly AWS managed services, to architect scalable and resilient solutions.\nAgile and DevOps:\nA solid foundation in Agile development processes and DevOps principles, including proficiency with GIT (GitHub), CI/CD practices (GitHub Actions), and Infrastructure as Code (Terraform).\nTech Stack Expertise\n: Hands-on experience with Linux, containers (Kubernetes), serverless architectures, and programming skills in JavaScript, Node.js, React, and Flutter.\nData Engineering:\nKnowledge of SQL, relational databases (AWS RDS), and familiarity with data warehousing solutions like Snowflake and AWS Redshift. Integration Services experience (Informatica Cloud, Airflow) is a significant plus.\nMessaging and Integration:\nCompetency in messaging solutions (EventBridge, SNS, SQS, Rabbit MQ, Kafka) to ensure seamless data flow and integration across systems.\nCompliance and Security:\nAwareness of compliance and cybersecurity requirements in the healthcare industry, with experience in navigating quality, regulatory data privacy (GxP, SOX) standards.\nCertifications:\nRelevant cloud certifications (AWS, Azure, Snowflake) are highly regarded, reflecting a commitment to staying at the forefront of technology.\nThe Reward:\nA chance to play a crucial role in a collaboration that's redefining healthcare through digital transformation.\nA seat at the round table of diversity and inclusion, where different backgrounds and experiences conjure the richness of our culture.\nAn endless horizon of professional growth, learning opportunities, and the chance to contribute to a future where better health is a global reality.\nThe Call to Adventure:\nIf you're ready to join a quest for better \u2013 better treatments, better outcomes, and better science \u2013 and believe in the magic of bringing diverse talents together to make miracles happen, we want you. Let's embark on this journey together and transform the future of healthcare.\nBetter is out there. Are you ready to find it with us?\nShow more\nShow less",
        "skills": {
            "ProgLanguage": [
                "Java",
                "Scala",
                "R",
                "Go",
                "JavaScript"
            ],
            "DataBase": [
                "SQL"
            ],
            "DataAnalytics": [
                "R"
            ],
            "BigData": [],
            "MachingLearning": [],
            "DataSerialization": [],
            "DataVisualization": [],
            "Statistics": [],
            "CloudComputing": [
                "AWS",
                "Azure"
            ],
            "DevTools": [
                "Git"
            ],
            "Os": [
                "Linux"
            ],
            "DBMS": [
                "Snowflake",
                "Snowflake"
            ],
            "SoftBigDataProcessing": [],
            "Automation": [
                "Kubernetes",
                "Airflow"
            ],
            "InfrastructureAsCode": [
                "Terraform"
            ],
            "NetworkSecurty": [],
            "Virtualisation": [],
            "Containers": [
                "Kubernetes"
            ],
            "Collaboration": [],
            "Other": [
                "DevOps",
                "ML",
                "Cloud",
                "CI/CD"
            ],
            "FrSoftSkills": [
                "Communication",
                "Collaboration"
            ],
            "EnSoftSkils": [
                "Communication",
                "Collaboration",
                "Initiative"
            ]
        },
        "details": {
            "JobDetail": [
                "Remote"
            ],
            "TypeContract": [],
            "Salary": [],
            "Level": [],
            "Experience": [
                "a",
                "n",
                "s"
            ]
        }
    },
    {
        "source": "LinkedIn",
        "title": "Architecte Big Data & Cloud - Lyon",
        "company": "Capgemini",
        "location": "Greater Lyon Area",
        "link": "https://fr.linkedin.com/jobs/view/architecte-big-data-cloud-lyon-at-capgemini-3907764355?position=12&pageNum=0&refId=a5rwPua%2FMvx%2F2M%2FPSF0oPA%3D%3D&trackingId=7dtgcERGKyLxdC5FPR81ng%3D%3D&trk=public_jobs_jserp-result_search-card",
        "description": "\u00c0 propos de l\u2019offre d\u2019emploi\nCapgemini en quelques mots\nChoisir Capgemini, c'est choisir une entreprise o\u00f9 vous serez en mesure de fa\u00e7onner votre carri\u00e8re selon vos aspirations, o\u00f9 vous serez soutenu et inspir\u00e9 par une communaut\u00e9 d\u2019experts dans le monde entier, o\u00f9 vous pourrez r\u00e9\u00e9crire votre futur. Rejoignez-nous pour red\u00e9finir les limites de ce qui est possible, contribuer \u00e0 lib\u00e9rer la valeur de la technologie pour les plus grandes organisations et participez \u00e0 la construction d\u2019un monde plus durable et inclusif.\nVos missions :\nVous r\u00e9pondez aux probl\u00e9matiques de nos clients en proposant des\nsolutions big data \u00ab on premise \u00bb et/ou dans le cloud (MS Azure, AWS et GCP).\nVous adaptez chaque architecture en fonction du contexte gr\u00e2ce \u00e0 votre maitrise des caract\u00e9ristiques fondamentales de chaque solution (catalogue des offres de services manag\u00e9s, performance, s\u00e9curit\u00e9, d\u00e9ploiement des data centers \u2026).\nVous utilisez les solutions d\u2019int\u00e9gration associ\u00e9es et les solutions d\u00e9cisionnelles ainsi qu\u2019analytiques qui viennent consommer les donn\u00e9es manipul\u00e9es.\nVous \u00eates en mesure d\u2019encadrer les \u00e9quipes de data engineers dans la mise en place des architectures pr\u00e9conis\u00e9es et/ ou des plateformes Big Data.\nVous \u00eates en mesure d\u2019appuyer les \u00e9quipes commerciales dans les r\u00e9ponses aux appels d\u2019offres Big Data.\nVotre profil :\nFormation Bac + 5 en \u00e9cole d\u2019ing\u00e9nieur ou \u00e9quivalent universitaire avec une sp\u00e9cialisation Big Data,\nA partir de 7 ans d\u2019exp\u00e9rience,\nVous \u00eates un(e) passionn\u00e9(e) de la Data et maitrisez aussi bien Linux et Spark que Script shell\nHadoop (cloudera/Hortonworks/MapR) n'a pas de secret pour vous mais vous avez pris le virage du cloud (AWS, GCP, MS Azure ),\nEnglish speaker, because we are French but also international.\n3 raisons de nous rejoindre :\nQualit\u00e9 de vie au travail :\naccord de t\u00e9l\u00e9travail en France et \u00e0 l\u2019international, accord sur l\u2019\u00e9galit\u00e9 professionnelle, la parentalit\u00e9, l\u2019\u00e9quilibre des temps et la mobilit\u00e9 durable.\nApprentissage en continu :\ncertifications et formations en libre acc\u00e8s, accompagnement sur mesure avec votre carreer manager, parcours d\u2019int\u00e9gration sur 9 mois.\nAvantages groupe & CSE :\nplan actionnariat, activit\u00e9s \u00e0 tarifs pr\u00e9f\u00e9rentiels, remboursement partiel vacances, remboursement de votre abonnement sportif ou culturel.\nNos engagements et priorit\u00e9s :\nLe groupe Capgemini encourage une\nculture inclusive dans un cadre multiculturel et handi-accueillant.\nEn nous rejoignant, vous int\u00e9grez un collectif qui valorise la diversit\u00e9, d\u00e9veloppe le potentiel de ses talents, s\u2019engage dans des\ninitiatives solidaires avec ses partenaires, et se mobilise pour r\u00e9duire son impact environnemental sur tous ses sites et aupr\u00e8s de ses clients.\nCapgemini\nest un\nleader mondial,\nresponsable et multiculturel, regroupant pr\u00e8s de 350 000 personnes dans plus de 50 pays. Fort de\n55 ans d\u2019exp\u00e9rience\n, nous sommes un partenaire strat\u00e9gique des entreprises pour la transformation de leurs activit\u00e9s en tirant profit de toute la puissance de la technologie et des innovations dans les domaines en perp\u00e9tuelle \u00e9volution tels que\nle cloud, la data, l\u2019Intelligence Artificielle, la connectivit\u00e9, les logiciels, l\u2019ing\u00e9nierie digitale ou les plateformes.\nGet The Future You Want* | www.capgemini.com/fr-fr\n*Capgemini, le futur que vous voulez\nShow more\nShow less",
        "skills": {
            "ProgLanguage": [
                "R"
            ],
            "DataBase": [],
            "DataAnalytics": [
                "R"
            ],
            "BigData": [
                "Hadoop",
                "Spark"
            ],
            "MachingLearning": [],
            "DataSerialization": [],
            "DataVisualization": [],
            "Statistics": [],
            "CloudComputing": [
                "AWS",
                "Azure"
            ],
            "DevTools": [
                "Git"
            ],
            "Os": [
                "Linux"
            ],
            "DBMS": [],
            "SoftBigDataProcessing": [],
            "Automation": [],
            "InfrastructureAsCode": [],
            "NetworkSecurty": [],
            "Virtualisation": [],
            "Containers": [],
            "Collaboration": [],
            "Other": [
                "Big Data",
                "Cloud"
            ],
            "FrSoftSkills": [
                "Organisation"
            ],
            "EnSoftSkils": [
                "Initiative"
            ]
        },
        "details": {
            "JobDetail": [],
            "TypeContract": [],
            "Salary": [],
            "Level": [],
            "Experience": [
                "a",
                "n",
                "s",
                "7",
                "7",
                "7"
            ]
        }
    },
    {
        "source": "LinkedIn",
        "title": "Architecte Data",
        "company": "ANFSI - Agence du num\u00e9rique des forces de s\u00e9curit\u00e9 int\u00e9rieure",
        "location": "Issy-les-Moulineaux, \u00cele-de-France, France",
        "link": "https://fr.linkedin.com/jobs/view/architecte-data-at-anfsi-agence-du-num%C3%A9rique-des-forces-de-s%C3%A9curit%C3%A9-int%C3%A9rieure-3907477086?position=13&pageNum=0&refId=a5rwPua%2FMvx%2F2M%2FPSF0oPA%3D%3D&trackingId=Y3Rnq%2BGRbOfIeubfaQbhvg%3D%3D&trk=public_jobs_jserp-result_search-card",
        "description": "Vos activit\u00e9s principales\nConception et Strat\u00e9gie\n\u2022 Analyse des besoins m\u00e9tiers pour les syst\u00e8mes de collecte et de stockage de donn\u00e9es \u00e0 un niveau strat\u00e9gique.\n\u2022 Conception des architectures globales de donn\u00e9es pour la collecte et le stockage de donn\u00e9es, y compris l'int\u00e9gration via des API au travers de solutions on-premise et cloud.\n\u2022 Supervision des tests et de l'int\u00e9gration pour garantir l'efficacit\u00e9 et la fiabilit\u00e9 des syst\u00e8mes.\n\u2022 Strat\u00e9gie globales d'automatisation pour l'automatisation des traitements.\nGouvernance\n\u2022 Politiques de nettoyage de donn\u00e9es en s'alignant sur les objectifs de l'administration.\n\u2022 Gestion strat\u00e9gique des bases de donn\u00e9es incluant des strat\u00e9gies pour l'int\u00e9gration de donn\u00e9es diverses.\n\u2022 Conformit\u00e9 et s\u00e9curit\u00e9 des donn\u00e9es dans le respect de normes comme le RGPD.\n\u2022 Planification de la maintenance et du suivi des syst\u00e8mes de donn\u00e9es.\nDirection des Projets\n\u2022 D\u00e9finition des standards techniques et des meilleures pratiques pour les projets de d\u00e9veloppement de donn\u00e9es.\n\u2022 Coordination et reporting : se coordonner avec les chefs de projet et les \u00e9quipes techniques en vue de l'alignement architectural des projets.\n\u2022Accompagner et coacher les autres experts et d\u00e9veloppeurs, afin qu'ils\nmontent en comp\u00e9tences sur les sujets li\u00e9s \u00e0 l'int\u00e9gration et \u00e0 la\ngouvernance des donn\u00e9es.\nLeadership et Innovation\n\u2022 Veille strat\u00e9gique.\n\u2022 Leadership en documentation : D\u00e9finir les standards pour la documentation technique, incluant la gestion des connaissances et le partage des meilleures pratiques.\nVotre environnement professionnel\nActivit\u00e9s du service\nL\u2019Agence du Num\u00e9rique des Forces de S\u00e9curit\u00e9 Int\u00e9rieure (ANFSI) est charg\u00e9e de piloter et de conduire les projets de syst\u00e8mes d\u2019information, de communication, de commandement et des moyens technologiques connexes d\u00e9di\u00e9s aux utilisateurs de la s\u00e9curit\u00e9 int\u00e9rieure.\nComposition et effectifs du service\nL\u2019ANFSI est compos\u00e9e de six directions : la Direction des Supports Op\u00e9rationnels (DSO), la Direction de la s\u00e9curit\u00e9 et de l\u2019architecture (DSA), la Direction de l\u2019appui \u00e0 l\u2019investigation (DAI), la Direction des applications d\u2019appui au commandement (DAAC), la Direction des communications tactiques (DCT), et la Direction de la proximit\u00e9 et de l\u2019appui \u00e0 l\u2019innovation (DPAI). Son effectif est compos\u00e9de personnels de la police et de la gendarmerie nationales ainsi que de contractuels.\nLa Section de mise \u00e0 disposition des donn\u00e9es, o\u00f9 le poste est ouvert, est compos\u00e9e de 9 personnes. Vous serez l\u2019adjoint du chef de section qui est un ing\u00e9nieur officier de gendarmerie. L\u2019activit\u00e9 principale de la section consiste \u00e0 r\u00e9cup\u00e9rer les donn\u00e9es m\u00e9tier des logiciels de r\u00e9daction de proc\u00e9dures des FSI et \u00e0 les mettre \u00e0 disposition d\u2019applications tierces, comme le fichier des personnes recherch\u00e9es, le fichier des objets et v\u00e9hicules vol\u00e9s, ou le traitement des ant\u00e9c\u00e9dents judiciaires. L\u2019architecte apporte son exp\u00e9rience dans la mise en \u0153uvre d\u2019ETL et/ou d\u2019ESB, et API manager.\nVos comp\u00e9tences principales mises en \u0153uvre :\nConnaissances techniques\nAvoir des comp\u00e9tences en informatique - bureautique niveau ma\u00eetrise requis\nConna\u00eetre l'environnement professionnel niveau ma\u00eetrise \u00e0 acqu\u00e9rir\nSavoir-faire\nSavoir analyser niveau expert requis\nSavoir manager niveau ma\u00eetrise requis\nSavoir r\u00e9diger niveau pratique requis\nAvoir l'esprit de synth\u00e8se niveau ma\u00eetrise requis\nSavoir s'organiser niveau ma\u00eetrise requis\nSavoir travailler en \u00e9quipe niveau ma\u00eetrise requis\nSavoir-\u00eatre\navoir le sens des relations humaines niveau ma\u00eetrise requis\nsavoir s'adapter niveau expert requis\nsavoir communiquer niveau ma\u00eetrise \u00e0 acqu\u00e9rir\nsavoir s'exprimer oralement niveau ma\u00eetrise \u00e0 acqu\u00e9rir\nProfil recherch\u00e9 :\nTitulaire d'un dipl\u00f4me d'ing\u00e9nieur (Bac +5) ou \u00e9quivalent, votre passion pour la technologie vous rend apte \u00e0 r\u00e9soudre des d\u00e9fis complexes li\u00e9s \u00e0 la Data. Avec au moins cinq ans d'exp\u00e9rience en technologies ETL/ESB, message broker et API management, vous ma\u00eetrisez ces domaines. Une exp\u00e9rience approfondie dans la conception d'architectures de plateformes d'\u00e9changes est essentielle. Une connaissance de la plateforme Mulesoft est un plus.\nVos perspectives\n:\nDans un contexte d\u2019acc\u00e9l\u00e9ration de l'\u00e9volution du num\u00e9rique et des besoins de r\u00e9activit\u00e9 associ\u00e9s : enrichissement du r\u00e9seau professionnel, approfondissement des connaissances et exp\u00e9rience professionnelles, ma\u00eetrise des proc\u00e9dures et comp\u00e9tences \u00ab m\u00e9tier \u00bb de la GN/PN. Implication dans la mise en place de projets innovants (PN/GN) et transverses. S\u2019ouvrir aux nouvelles m\u00e9thodologies de conduite de projet.\nDur\u00e9e attendue sur le poste\n:\n3 ans\nSp\u00e9cificit\u00e9s du poste / Contraintes / Suj\u00e9tions :\n39 heures hebdomadaires - 25 jours CA -22 jours de RTT\nLes candidat.e.s pourront \u00eatre soumis \u00e0 une enqu\u00eate administrative de s\u00e9curit\u00e9 sur le fondement de l'article L.114-1 du code de la s\u00e9curit\u00e9 int\u00e9rieure.\nLocalisation g\u00e9ographique :\n4, rue Claude Bernard \u2013 92130 Issy-les-Moulineaux\nShow more\nShow less",
        "skills": {
            "ProgLanguage": [
                "R",
                "Go"
            ],
            "DataBase": [],
            "DataAnalytics": [
                "R"
            ],
            "BigData": [],
            "MachingLearning": [],
            "DataSerialization": [],
            "DataVisualization": [],
            "Statistics": [],
            "CloudComputing": [],
            "DevTools": [],
            "Os": [],
            "DBMS": [],
            "SoftBigDataProcessing": [],
            "Automation": [
                "Chef"
            ],
            "InfrastructureAsCode": [],
            "NetworkSecurty": [],
            "Virtualisation": [],
            "Containers": [],
            "Collaboration": [],
            "Other": [
                "Cloud"
            ],
            "FrSoftSkills": [
                "Communication",
                "Leadership"
            ],
            "EnSoftSkils": [
                "Communication",
                "Leadership"
            ]
        },
        "details": {
            "JobDetail": [],
            "TypeContract": [],
            "Salary": [],
            "Level": [],
            "Experience": [
                "a",
                "n",
                "s",
                "3",
                "3",
                "3"
            ]
        }
    },
    {
        "source": "LinkedIn",
        "title": "Architecte Big Data & Cloud",
        "company": "Capgemini",
        "location": "Issy-les-Moulineaux, \u00cele-de-France, France",
        "link": "https://fr.linkedin.com/jobs/view/architecte-big-data-cloud-at-capgemini-3902965293?position=14&pageNum=0&refId=a5rwPua%2FMvx%2F2M%2FPSF0oPA%3D%3D&trackingId=AwEXZKzHyJPYvt0z8HzQVw%3D%3D&trk=public_jobs_jserp-result_search-card",
        "description": "Capgemini en quelques mots\nChoisir Capgemini, c'est choisir une entreprise o\u00f9 vous serez en mesure de fa\u00e7onner votre carri\u00e8re selon vos aspirations, o\u00f9 vous serez soutenu et inspir\u00e9 par une communaut\u00e9 d\u2019experts dans le monde entier, o\u00f9 vous pourrez r\u00e9\u00e9crire votre futur. Rejoignez-nous pour red\u00e9finir les limites de ce qui est possible, contribuer \u00e0 lib\u00e9rer la valeur de la technologie pour les plus grandes organisations et participez \u00e0 la construction d\u2019un monde plus durable et inclusif.\nVos missions :\nVous r\u00e9pondez aux probl\u00e9matiques de nos clients en proposant des\nsolutions big data \u00ab on premise \u00bb et/ou dans le cloud (MS Azure, AWS et GCP).\nVous adaptez chaque architecture en fonction du contexte gr\u00e2ce \u00e0 votre maitrise des caract\u00e9ristiques fondamentales de chaque solution (catalogue des offres de services manag\u00e9s, performance, s\u00e9curit\u00e9, d\u00e9ploiement des data centers \u2026).\nVous utilisez les solutions d\u2019int\u00e9gration associ\u00e9es et les solutions d\u00e9cisionnelles ainsi qu\u2019analytiques qui viennent consommer les donn\u00e9es manipul\u00e9es.\nVous \u00eates en mesure d\u2019encadrer les \u00e9quipes de data engineers dans la mise en place des architectures pr\u00e9conis\u00e9es et/ ou des plateformes Big Data.\nVous \u00eates en mesure d\u2019appuyer les \u00e9quipes commerciales dans les r\u00e9ponses aux appels d\u2019offres Big Data.\nVotre profil :\nFormation Bac + 5 en \u00e9cole d\u2019ing\u00e9nieur ou \u00e9quivalent universitaire avec une sp\u00e9cialisation Big Data,\nA partir de 7 ans d\u2019exp\u00e9rience,\nVous \u00eates un(e) passionn\u00e9(e) de la Data et maitrisez aussi bien Linux et Spark que Script shell\nHadoop (cloudera/Hortonworks/MapR) n'a pas de secret pour vous mais vous avez pris le virage du cloud (AWS, GCP, MS Azure ),\nEnglish speaker, because we are French but also international.\n3 raisons de nous rejoindre :\nQualit\u00e9 de vie au travail :\naccord de t\u00e9l\u00e9travail en France et \u00e0 l\u2019international, accord sur l\u2019\u00e9galit\u00e9 professionnelle, la parentalit\u00e9, l\u2019\u00e9quilibre des temps et la mobilit\u00e9 durable.\nApprentissage en continu :\ncertifications et formations en libre acc\u00e8s, accompagnement sur mesure avec votre carreer manager, parcours d\u2019int\u00e9gration sur 9 mois.\nAvantages groupe & CSE :\nplan actionnariat, activit\u00e9s \u00e0 tarifs pr\u00e9f\u00e9rentiels, remboursement partiel vacances, remboursement de votre abonnement sportif ou culturel.\nNos engagements et priorit\u00e9s :\nLe groupe Capgemini encourage une\nculture inclusive dans un cadre multiculturel et handi-accueillant.\nEn nous rejoignant, vous int\u00e9grez un collectif qui valorise la diversit\u00e9, d\u00e9veloppe le potentiel de ses talents, s\u2019engage dans des\ninitiatives solidaires avec ses partenaires, et se mobilise pour r\u00e9duire son impact environnemental sur tous ses sites et aupr\u00e8s de ses clients.\nCapgemini\nest un\nleader mondial,\nresponsable et multiculturel, regroupant pr\u00e8s de 350 000 personnes dans plus de 50 pays. Fort de\n55 ans d\u2019exp\u00e9rience\n, nous sommes un partenaire strat\u00e9gique des entreprises pour la transformation de leurs activit\u00e9s en tirant profit de toute la puissance de la technologie et des innovations dans les domaines en perp\u00e9tuelle \u00e9volution tels que\nle cloud, la data, l\u2019Intelligence Artificielle, la connectivit\u00e9, les logiciels, l\u2019ing\u00e9nierie digitale ou les plateformes.\nGet The Future You Want* | www.capgemini.com/fr-fr\n*Capgemini, le futur que vous voulez\nShow more\nShow less",
        "skills": {
            "ProgLanguage": [
                "R"
            ],
            "DataBase": [],
            "DataAnalytics": [
                "R"
            ],
            "BigData": [
                "Hadoop",
                "Spark"
            ],
            "MachingLearning": [],
            "DataSerialization": [],
            "DataVisualization": [],
            "Statistics": [],
            "CloudComputing": [
                "AWS",
                "Azure"
            ],
            "DevTools": [
                "Git"
            ],
            "Os": [
                "Linux"
            ],
            "DBMS": [],
            "SoftBigDataProcessing": [],
            "Automation": [],
            "InfrastructureAsCode": [],
            "NetworkSecurty": [],
            "Virtualisation": [],
            "Containers": [],
            "Collaboration": [],
            "Other": [
                "Big Data",
                "Cloud"
            ],
            "FrSoftSkills": [
                "Organisation"
            ],
            "EnSoftSkils": [
                "Initiative"
            ]
        },
        "details": {
            "JobDetail": [],
            "TypeContract": [],
            "Salary": [],
            "Level": [],
            "Experience": [
                "a",
                "n",
                "s",
                "7",
                "7",
                "7"
            ]
        }
    },
    {
        "source": "LinkedIn",
        "title": "Data Architect",
        "company": "Harnham",
        "location": "Paris, \u00cele-de-France, France",
        "link": "https://fr.linkedin.com/jobs/view/data-architect-at-harnham-3907820245?position=15&pageNum=0&refId=a5rwPua%2FMvx%2F2M%2FPSF0oPA%3D%3D&trackingId=safltM8yfEOH1tQrs0R5zw%3D%3D&trk=public_jobs_jserp-result_search-card",
        "description": "DATA ARCHITECT\nPARIS (75) / LILLE (59)\n50-55K EUR\nUne nouvelle opportunit\u00e9 s\u2019ouvre pour un Data Architecte dans le domaine de l\u2019assurance. Une entreprise qui combine l\u2019expertise des grands groupes et l\u2019agilit\u00e9 d\u2019une start-up, qui vous permettra d\u2019innover ! Si vous recherchez un d\u00e9fi stimulant dans un environnement qui encourage les nouvelles id\u00e9es, cette opportunit\u00e9 est faite pour vous.\nVOTRE MISSION :\nElaborer et Concevoir l\u2019architecture des donn\u00e9es en r\u00e9ponse aux besoins m\u00e9tiers\nCollaboration pour comprendre les exigences des parties prenantes et les traduire en solutions architecturales\nConcevoir et impl\u00e9menter des mod\u00e8les de donn\u00e9es efficaces et \u00e9volutifs\nAssurer la coh\u00e9rence et l\u2019int\u00e9grit\u00e9 des donn\u00e9es \u00e0 travers tout le syst\u00e8me.\nFournir des recommandations pour assurer une gestion efficace des donn\u00e9es\nVOTRE PROFIL :\n4 ans d\u2019exp\u00e9rience dans un r\u00f4le similaire\nComp\u00e9tences solides en Python, Cloud AWS, Tableau\nComp\u00e9tencesavec le Machine Learning\nAnglais: Fluent obligatoire\nN\u2019h\u00e9sitez plus pour postuler !\nShow more\nShow less",
        "skills": {
            "ProgLanguage": [
                "Python",
                "R"
            ],
            "DataBase": [],
            "DataAnalytics": [
                "R"
            ],
            "BigData": [],
            "MachingLearning": [],
            "DataSerialization": [],
            "DataVisualization": [
                "Tableau"
            ],
            "Statistics": [],
            "CloudComputing": [
                "AWS"
            ],
            "DevTools": [],
            "Os": [],
            "DBMS": [],
            "SoftBigDataProcessing": [],
            "Automation": [],
            "InfrastructureAsCode": [],
            "NetworkSecurty": [],
            "Virtualisation": [],
            "Containers": [],
            "Collaboration": [],
            "Other": [
                "Machine Learning",
                "Cloud"
            ],
            "FrSoftSkills": [
                "Collaboration"
            ],
            "EnSoftSkils": [
                "Collaboration"
            ]
        },
        "details": {
            "JobDetail": [],
            "TypeContract": [],
            "Salary": [],
            "Level": [],
            "Experience": [
                "a",
                "n",
                "s",
                "4",
                "4",
                "4"
            ]
        }
    },
    {
        "source": "LinkedIn",
        "title": "Data Cloud Solution Architect",
        "company": "Vallum Associates",
        "location": "Paris, \u00cele-de-France, France",
        "link": "https://fr.linkedin.com/jobs/view/data-cloud-solution-architect-at-vallum-associates-3916589273?position=16&pageNum=0&refId=a5rwPua%2FMvx%2F2M%2FPSF0oPA%3D%3D&trackingId=4Zq3y89MIEfOPdGqnw0nGg%3D%3D&trk=public_jobs_jserp-result_search-card",
        "description": "Skills:\nFluent in French & English\n(must)\nDeep Snowflake expertise\nPlatform architecture\nDBA experience\nCloud database admin\nAWS Architecture\nCloud networking specialist\nExcellence in communication, coordination & collaboration, stakeholder & risk management and especially with drive & leadership\nOpen minded and accepting challenges\nHighly motivated, adaptable and flexible. Willing to integrate an existing environment and an existing project team\nShow more\nShow less",
        "skills": {
            "ProgLanguage": [
                "R"
            ],
            "DataBase": [],
            "DataAnalytics": [
                "R"
            ],
            "BigData": [],
            "MachingLearning": [],
            "DataSerialization": [],
            "DataVisualization": [],
            "Statistics": [],
            "CloudComputing": [
                "AWS"
            ],
            "DevTools": [],
            "Os": [],
            "DBMS": [
                "Snowflake",
                "Snowflake"
            ],
            "SoftBigDataProcessing": [],
            "Automation": [],
            "InfrastructureAsCode": [],
            "NetworkSecurty": [],
            "Virtualisation": [],
            "Containers": [],
            "Collaboration": [],
            "Other": [
                "Cloud"
            ],
            "FrSoftSkills": [
                "Communication",
                "Leadership",
                "Collaboration"
            ],
            "EnSoftSkils": [
                "Communication",
                "Leadership",
                "Collaboration"
            ]
        },
        "details": {
            "JobDetail": [],
            "TypeContract": [],
            "Salary": [],
            "Level": [],
            "Experience": [
                "a",
                "n",
                "s"
            ]
        }
    },
    {
        "source": "LinkedIn",
        "title": "Data Architect H/F",
        "company": "Agyla.Cloud",
        "location": "France",
        "link": "https://fr.linkedin.com/jobs/view/data-architect-h-f-at-agyla-cloud-3885512739?position=17&pageNum=0&refId=a5rwPua%2FMvx%2F2M%2FPSF0oPA%3D%3D&trackingId=iq1NzP0cg3me9Ol5f2LP2A%3D%3D&trk=public_jobs_jserp-result_search-card",
        "description": "Agyla est depuis le 1er Juillet, LA r\u00e9f\u00e9rence en cloud public du groupe IBM Consulting.\nNous sommes un cabinet de conseil informatique sp\u00e9cialis\u00e9 en Cloud & DevOps. Ce sont 90 experts qui interviennent au c\u0153ur de la transformation technologique de nos clients, de la conception \u00e0 la s\u00e9curisation en production.\nNos technologies cl\u00e9s: AWS, Azure, GCP/Kubernetes, HashiCorp, tout sur la CICD, Cloud Security, cloud native developpement.\nFaire partie d\u2019Agyla c\u2019est booster sa carri\u00e8re et rejoindre notre communaut\u00e9 d\u2019experts, recrut\u00e9s pour leurs talents.\nNos experts sont accompagn\u00e9s dans leur carri\u00e8re et renforcent leurs expertises \u00e0 travers des certifications techniques pour une mont\u00e9e en comp\u00e9tence constante. Ils participent au collectif en partageant leur savoir et en faisant grandir l\u2019entreprise aupr\u00e8s de ses clients.\nNous recrutons notre futur(e) Data Architect ! Vous souhaitez rejoindre une mission passionnante dans le secteur du retail ? Alors c'est par ici que \u00e7a se passe :\nVos t\u00e2ches :\nAccompagner et conseiller l'\u00e9quipe notamment dans le cadre de mod\u00e9lisation de donn\u00e9es\n\u00c9tablir et faciliter un forum d'architecture des donn\u00e9es, o\u00f9 les options d'architecture des donn\u00e9es sont examin\u00e9es et discut\u00e9es avec l'\u00e9quipe.\nVeiller \u00e0 ce que la documentation appropri\u00e9e soit cr\u00e9\u00e9e au fil du temps (suivi des d\u00e9cisions du forum d'architecture des donn\u00e9es, v\u00e9rification que l'architecture des donn\u00e9es pour chaque livraison r\u00e9alis\u00e9e par les \u00e9quipes soit correctement document\u00e9e).\nRepr\u00e9senter les int\u00e9r\u00eats de l'\u00e9quipe dans certains projets men\u00e9s par d'autres \u00e9quipes\nVos qualifications :\nExp\u00e9rience en mod\u00e9lisation de donn\u00e9es.\nCapacit\u00e9 \u00e0 influencer les autres (pour soutenir mais aussi remettre en question les conceptions des produits de donn\u00e9es r\u00e9alis\u00e9es).\nApp\u00e9tence pour les processus/documentation, car l'id\u00e9e est de renforcer la mani\u00e8re de documenter et de gouverner l'architecture des donn\u00e9es.\nMa\u00eetrise d'un cloud public (Azure ou GCP)\nNB : La mission se d\u00e9roule en full remote.\nAgyla.cloud a b\u00e2ti sa croissance sur la puissance de son \u00e9quipe. Vous deviendrez un membre actif du succ\u00e8s collectif.\nVous avez l\u2019attitude d\u2019un consultant : \u00e0 l\u2019\u00e9coute, bienveillant, vous partagez votre exp\u00e9rience et faites grandir le client. Vous savez prendre des initiatives et avec une excellente communication orale et \u00e9crite.\nAgyla-D\u00e9claration sp\u00e9cifique de confidentialit\u00e9\nAgyla est une filiale IBM qui a \u00e9t\u00e9 acquise par IBM et qui sera int\u00e9gr\u00e9e \u00e0 l'organisation IBM. Agyla sera l'entit\u00e9 d'embauche. En proc\u00e9dant \u00e0 cette candidature, vous comprenez qu'Agyla partagera vos informations personnelles avec IBM et d'autres filiales IBM impliqu\u00e9es dans votre processus de recrutement, o\u00f9 qu'elles se trouvent. Plus d'informations sur la fa\u00e7on dont IBM prot\u00e8ge vos informations personnelles, y compris les garanties en cas de transfert de donn\u00e9es transfronti\u00e8re, sont disponibles ici:\nhttps://www.ibm.com/fr-fr/privacy\nShow more\nShow less",
        "skills": {
            "ProgLanguage": [
                "R",
                "Go"
            ],
            "DataBase": [],
            "DataAnalytics": [
                "R"
            ],
            "BigData": [],
            "MachingLearning": [],
            "DataSerialization": [],
            "DataVisualization": [],
            "Statistics": [],
            "CloudComputing": [
                "AWS",
                "Azure"
            ],
            "DevTools": [],
            "Os": [],
            "DBMS": [],
            "SoftBigDataProcessing": [],
            "Automation": [
                "Kubernetes"
            ],
            "InfrastructureAsCode": [],
            "NetworkSecurty": [],
            "Virtualisation": [],
            "Containers": [
                "Kubernetes"
            ],
            "Collaboration": [],
            "Other": [
                "DevOps",
                "Cloud"
            ],
            "FrSoftSkills": [
                "Communication",
                "Organisation"
            ],
            "EnSoftSkils": [
                "Communication",
                "Initiative"
            ]
        },
        "details": {
            "JobDetail": [
                "Remote",
                "Full"
            ],
            "TypeContract": [],
            "Salary": [],
            "Level": [],
            "Experience": [
                "a",
                "n",
                "s"
            ]
        }
    },
    {
        "source": "LinkedIn",
        "title": "Solution Architect",
        "company": "INSEAD",
        "location": "Fontainebleau, \u00cele-de-France, France",
        "link": "https://fr.linkedin.com/jobs/view/solution-architect-at-insead-3868439514?position=18&pageNum=0&refId=a5rwPua%2FMvx%2F2M%2FPSF0oPA%3D%3D&trackingId=Y%2F3BfUWMhpQ%2Bmh97Cx%2FrVA%3D%3D&trk=public_jobs_jserp-result_search-card",
        "description": "INSEAD brings together people, cultures and ideas from around the world to educate leaders who transform business and society. As a mission-driven school, INSEAD focuses on three values: open, rigorous, and entrepreneurial. As one of the world\u2019s leading and largest graduate business schools, With campuses in Europe (France), Asia (Singapore), Middle East (Abu Dhabi) and an American Hub (San Francisco), INSEAD\u2019s business and research spans four continents.\nWe are currently looking for a\nSolution Architect\nto join our Data & Enterprise Architecture team in the IT department. This is a permanent and full-time position, based either on our\nAsia Campus in Singapore\nor on our\nEurope Campus in Fontainebleau, France\n. A hybrid working model is in place \u2013 3 days on campus, 2 days from home.\nThe Solution Architect will analyse the current state of the enterprise environment from a technical and functional point of view. He/she will develop and design the future state architecture and the roadmap to reach it, balancing risks in terms of timeline and costs while meeting business requirements and enabling capability. The Solution Architect will devise technical or functional solutions to achieve enterprise and business objectives, this effort will consistently align with the IT strategy.\nKey Responsibilities include:\n\u2022 Support large project implementation: (1) Formulate the solutions in which business and IT viewpoints are synthesised into a solution. (2) Develop the digital interoperability for new platforms to embed the INSEAD eco-system (3) Setup the plan for state-of-the-art operationalisation and maintenance of the new platform.\n\u2022 Develop continuous integration & delivery practices in IT. Work out the best possible optimisation and automation of tasks and process(es), costing time and energy to the organisation.\n\u2022 Formulate the architecture strategy and govern it: (1) Develop and communicate architectural standards (2) Add architecture consideration into business discussions to develop roadmaps and implementation plans considering a sustainable IT portfolio. (T.I.M.E from Gartner)\n\u2022 Understand the enterprise needs and anticipate a major technology shift from the industry. This encompasses the need to educate/ inform the IT and school senior leadership about it so they can better prepare for the near future. It means driving the cost versus benefits, risks, impact, and technology priorities.\nWe are looking for a hands-on candidate who meets the following profile:\n\u2022 A minimum of 5 years of professional experience with application development.\n\u2022 Expert with DevSecOps practices. Hand\u2019s on with suite of CI/CD platforms and utilities.\n\u2022 Track record of enterprise architecture application (certify TOGAF is a plus).\n\u2022 Expertise in process design as well as Data modelling (certify ArchiMate is a plus).\n\u2022 Knowledge of Salesforce, Oracle Cloud and ServiceNow is a plus.\n\u2022 Demonstrated polished consulting skills with a keen awareness of sensitive client topics, and the ability to navigate client messaging and recommendations tactfully.\n\u2022 Proven ability to establish credibility with Senior Executives, team members and external partners, with excellent analytical and problem-solving skills for managing large and small projects.\n\u2022 Strong prioritization skills with attention to detail, and the capability to quickly define dependencies, issues, and mitigation plans against risks.\n\u2022 Effective communication skills bridging technology and business communities, with a consistent track record of business-building successes.\n\u2022 Fluency in English, with proficiency in French is advantageous.\n\u2022 Enthusiasm for exploring unknown technological territories and a strong technical curiosity to understand how things work.\nWe are happy to receive your resume and cover letter for this exciting opportunity. Please send your application to Talent Acquisition Europe talent.acquisition@insead.edu\nDiversity is one of INSEAD\u2019s founding values and as such we commit to cultivating a community that pursues equity, exemplifies inclusion and cherishes diversity in all its dimensions. Our jobs are open to all talents, so apply and join us!\nWe regret that only shortlisted candidates will be contacted.\nShow more\nShow less",
        "skills": {
            "ProgLanguage": [
                "R",
                "Go"
            ],
            "DataBase": [],
            "DataAnalytics": [
                "R"
            ],
            "BigData": [],
            "MachingLearning": [],
            "DataSerialization": [],
            "DataVisualization": [],
            "Statistics": [],
            "CloudComputing": [],
            "DevTools": [
                "Git"
            ],
            "Os": [],
            "DBMS": [
                "Oracle"
            ],
            "SoftBigDataProcessing": [],
            "Automation": [],
            "InfrastructureAsCode": [],
            "NetworkSecurty": [],
            "Virtualisation": [],
            "Containers": [],
            "Collaboration": [],
            "Other": [
                "Cloud",
                "CI/CD"
            ],
            "FrSoftSkills": [
                "Communication",
                "Leadership",
                "Organisation"
            ],
            "EnSoftSkils": [
                "Communication",
                "Leadership"
            ]
        },
        "details": {
            "JobDetail": [
                "Full",
                "Senior"
            ],
            "TypeContract": [],
            "Salary": [],
            "Level": [],
            "Experience": [
                "a",
                "n",
                "s"
            ]
        }
    },
    {
        "source": "LinkedIn",
        "title": "Architecte Big Data & Cloud - Lille",
        "company": "Capgemini",
        "location": "Lille, Hauts-de-France, France",
        "link": "https://fr.linkedin.com/jobs/view/architecte-big-data-cloud-lille-at-capgemini-3861939159?position=19&pageNum=0&refId=a5rwPua%2FMvx%2F2M%2FPSF0oPA%3D%3D&trackingId=Rii39Sm%2BCo0XrM2FDDa1DA%3D%3D&trk=public_jobs_jserp-result_search-card",
        "description": "Capgemini en quelques mots\nChoisir Capgemini, c'est choisir une entreprise o\u00f9 vous serez en mesure de fa\u00e7onner votre carri\u00e8re selon vos aspirations, o\u00f9 vous serez soutenu et inspir\u00e9 par une communaut\u00e9 d\u2019experts dans le monde entier, o\u00f9 vous pourrez r\u00e9\u00e9crire votre futur. Rejoignez-nous pour red\u00e9finir les limites de ce qui est possible, contribuer \u00e0 lib\u00e9rer la valeur de la technologie pour les plus grandes organisations et participez \u00e0 la construction d\u2019un monde plus durable et inclusif.\nVos missions\nInteragir au plus proche de nos clients, des partenaires pour concevoir et mettre en \u0153uvre des solutions/projets innovants et comp\u00e9titifs\nR\u00e9pondre aux probl\u00e9matiques de nos clients en proposant la meilleure plateforme data dans un environnement Agile\nAdapter chaque architecture en fonction du contexte gr\u00e2ce \u00e0 votre maitrise des caract\u00e9ristiques fondamentales de chaque solution (catalogue des offres de services manag\u00e9s, performance, s\u00e9curit\u00e9, d\u00e9ploiement des data centers \u2026)\nUtiliser les solutions d\u2019int\u00e9gration associ\u00e9es et les solutions d\u00e9cisionnelles ainsi qu\u2019analytiques qui viennent consommer les donn\u00e9es manipul\u00e9es\nEncadrer les \u00e9quipes dans la mise en place des architectures pr\u00e9conis\u00e9es et/ ou des plateformes Data.\nVotre profil\nAu moins 6 ans d\u2019exp\u00e9rience (au sein d\u2019une ESN ou chez un int\u00e9grateur) en conseil client\u00e8le\nUne solide culture technologique\nUn bon niveau d\u2019anglais\nDes qualit\u00e9s de p\u00e9dagogue et un int\u00e9r\u00eat pour la phase d\u2019avant-vente.\n3 raisons de nous rejoindre\nQualit\u00e9 de vie au travail :\naccord de t\u00e9l\u00e9travail en France et \u00e0 l\u2019international, accord sur l\u2019\u00e9galit\u00e9\nprofessionnelle, la parentalit\u00e9, l\u2019\u00e9quilibre des temps et la mobilit\u00e9 durable.\nApprentissage en continu :\ncertifications et formations en libre acc\u00e8s, accompagnement sur mesure avec\nvotre carreer manager, parcours d\u2019int\u00e9gration sur 9 mois.\nAvantages groupe & CSE :\nplan actionnariat, activit\u00e9s \u00e0 tarifs pr\u00e9f\u00e9rentiels, remboursement partiel\nvacances, remboursement de votre abonnement sportif ou culturel\nNos engagements et priorit\u00e9s\nLe groupe Capgemini encourage une\nculture inclusive dans un cadre multiculturel et handi-accueillant.\nEn nous rejoignant, vous int\u00e9grez un collectif qui valorise la diversit\u00e9, d\u00e9veloppe le potentiel de ses talents, s\u2019engage dans des\ninitiatives solidaires avec ses partenaires, et se mobilise pour r\u00e9duire son impact environnemental sur tous ses sites et aupr\u00e8s de ses clients.\nCapgemini\nest un\nleader mondial\n, responsable et multiculturel, regroupant pr\u00e8s de 350 000 personnes dans plus de 50 pays. Fort de\n55 ans d\u2019exp\u00e9rience,\nnous sommes un partenaire strat\u00e9gique des entreprises pour la transformation de leurs activit\u00e9s en tirant profit de toute la puissance de la technologie et des innovations dans les domaines en perp\u00e9tuelle \u00e9volution tels que le\ncloud, la data, l\u2019Intelligence Artificielle, la connectivit\u00e9, les logiciels, l\u2019ing\u00e9nierie digitale ou les plateformes.\nGet The Future You Want* | www.capgemini.com/fr-fr\n*Capgemini, le futur que vous voulez\nShow more\nShow less",
        "skills": {
            "ProgLanguage": [
                "R",
                "Go"
            ],
            "DataBase": [],
            "DataAnalytics": [
                "R"
            ],
            "BigData": [],
            "MachingLearning": [],
            "DataSerialization": [],
            "DataVisualization": [],
            "Statistics": [],
            "CloudComputing": [],
            "DevTools": [
                "Git"
            ],
            "Os": [],
            "DBMS": [],
            "SoftBigDataProcessing": [],
            "Automation": [],
            "InfrastructureAsCode": [],
            "NetworkSecurty": [],
            "Virtualisation": [],
            "Containers": [],
            "Collaboration": [],
            "Other": [
                "Cloud"
            ],
            "FrSoftSkills": [
                "Organisation"
            ],
            "EnSoftSkils": [
                "Initiative"
            ]
        },
        "details": {
            "JobDetail": [],
            "TypeContract": [],
            "Salary": [],
            "Level": [],
            "Experience": [
                "a",
                "n",
                "s",
                "6",
                "6",
                "6"
            ]
        }
    },
    {
        "source": "LinkedIn",
        "title": "IT DATA architect",
        "company": "LEM",
        "location": "Lyon, Auvergne-Rh\u00f4ne-Alpes, France",
        "link": "https://fr.linkedin.com/jobs/view/it-data-architect-at-lem-3916801738?position=20&pageNum=0&refId=a5rwPua%2FMvx%2F2M%2FPSF0oPA%3D%3D&trackingId=KptAY1vG1vOswIxM2PaP3Q%3D%3D&trk=public_jobs_jserp-result_search-card",
        "description": "LEM \u2013 Life Energy Motion\nAt LEM, we help our customers and society accelerate the transition to a sustainable future.\nOur global team of 1,700 professionals which spans over 15 countries is dedicated to converting technology potential into powerful solutions, which enable the decarbonization of the world.\nA leading company in electrical measurement, LEM engineers the best solutions for energy efficiency and electrical mobility, ensuring our customers, systems are optimized, reliable and safe.\nLEM is listed on the SIX Swiss Exchange since 1986, with the ticker symbol LEHN.\nThe future needs our ingenuity, we need your Spark.\n#BringYourSpar\nIn order to build the analytic team, we are looking for an IT DATA architect.\nThis is an exciting new opportunity working as part of the Corporate IT team to develop new capabilities and establish a supportable model of platform and applications, growing the companies use of modern technologies.\nThe IT Data architect is responsible for defining policies, procedures, models, and technologies that will be used to collect, organize, store, and retrieve information for the organization.\nHe / she understands how data drives the development of applications and business requirements through appropriate design principles, methodologies, and tools.\nHe / she sets the rules and structure for the data strategy, choosing the ETL approach and setting additional requirements.\nThe main tasks will be related to:\nApplication Design\nData model definition: Define the data architecture, data contract interfaces, data quality into the systems, best practices,\nData flow overview: Take the ownership of the current and future data flows. Take responsibilities for data quality and timeliness,\n& ensure the evolution of data flows, using the global data standards and business rules to input data into the systems,\nQuality assurance: Perform data quality checks for correctness and completeness according to defined business rules,\nMaster Data System: maintain accurate & up to date data for assigned business processes,\nto continuous improvements of systems and processes. Ensure data alignment between contract documentation and customer master data,\nup to date process documentation and training material,\nSupport: Ensure issues are identified, tracked, reported on and resolved in a timely manner.\nDevelopment & maintenance\nRole of expert for the designated product or product domain.\nDeals with user requests, service tickets, incidents, modifications\nAssume the 3rd level support activities\nWrites and maintains the documentation\nParticipates in creating user guides\nEnsures that knowhow of domain is transferred to team members.\nEnsures compliance with data security at all times.\nEvaluates applications and databases performance and enhances when possible\nCarry out or supervise development and system integration activities.\nProject management\nLead data related projects as IT representative\nDefines scope of the project, plans and follows project developments and deployments of applications.\nSupervise external resources during project phase.\nSkills required:\nCustomer driven approach\nExperience working in azure DF, Synapse, AWS, or other\nworking with Agile methodologies\nproblem solving, ability to work under pressure and able to prioritise\nand ability to work independently with limited supervision\ncommunication and interpersonal skills, ability to work effectively with remote teams\ngood oral and written communication\nin English\nDate of Employment: ASAP\nShow more\nShow less",
        "skills": {
            "ProgLanguage": [
                "R",
                "Go"
            ],
            "DataBase": [],
            "DataAnalytics": [
                "R"
            ],
            "BigData": [
                "Spark"
            ],
            "MachingLearning": [],
            "DataSerialization": [],
            "DataVisualization": [],
            "Statistics": [],
            "CloudComputing": [
                "AWS",
                "Azure"
            ],
            "DevTools": [],
            "Os": [],
            "DBMS": [],
            "SoftBigDataProcessing": [],
            "Automation": [],
            "InfrastructureAsCode": [],
            "NetworkSecurty": [],
            "Virtualisation": [],
            "Containers": [],
            "Collaboration": [
                "Teams"
            ],
            "Other": [],
            "FrSoftSkills": [
                "Communication"
            ],
            "EnSoftSkils": [
                "Communication",
                "Problem Solving",
                "Organization",
                "Interpersonal Skills"
            ]
        },
        "details": {
            "JobDetail": [
                "Remote"
            ],
            "TypeContract": [],
            "Salary": [],
            "Level": [],
            "Experience": [
                "a",
                "n",
                "s"
            ]
        }
    },
    {
        "source": "LinkedIn",
        "title": "Senior Data Architect / Consultant",
        "company": "JSS ASSOCIATES",
        "location": "Paris, \u00cele-de-France, France",
        "link": "https://fr.linkedin.com/jobs/view/senior-data-architect-consultant-at-jss-associates-3912573427?position=21&pageNum=0&refId=a5rwPua%2FMvx%2F2M%2FPSF0oPA%3D%3D&trackingId=ksX%2FYtGaX9xFT9xx8JPlNw%3D%3D&trk=public_jobs_jserp-result_search-card",
        "description": "Senior Data Architect / Consultant\nFor one of my leading clients focused in data advisory, we are looking for an experienced Data Architect / Consultant to join their dynamic team based in an affluent and upscale suburb west of Paris.\nMy client is renowned by industry experts for its commitment to empowering its clients in establishing robust data frameworks. Offering bespoke solutions span from fostering cultural shifts and technological empowerment to ensuring data consistency, security, and precision. With expertise in Data Advisory, Architecture, Academy, and Green Data, as well as proficiency in implementing Platform Data solutions such as Data Preparation and Integration. My client caters to diverse clients across the world. Driven by core values, they strive for sustainable consulting services, leveraging innovation and pragmatism in their data-centric approach.\nRole Overview:\nReporting to either the Data Advisory Manager or the Director of the Data Advisory Business Line, you will collaborate with clients on multifaceted missions. You will participate in pre-sales activities, response to calls for tenders and support and participate in internal projects related to the development of my clients business interests.\nCommercial aspect:\nParticipate in pre-sales activities, response to calls for tenders and support, all of the entrusted activities are carried out in compliance with my clients quality level. Participate in internal projects related to the development of my clients business interests.\nManagement responsibilities:\nSupervise and develop the skills of consultants within your scope.\nEnsure the skills development of junior/confirmed consultants, coaching and monitoring\nData Architecture section:\nSupport audit or urbanization missions of data platforms and tools responding to the company's new challenges: definition of the scope, estimation of costs, planning and organization, promotion of the methodology.\nBe responsible for the quality of project deliverables/documentation;\nLead meetings and write reports;\nSupport and advise the client in defining their data architectures;\nValidate the company's expectations in terms of functionality and functional and non-functional coverage of the solutions;\nLead and arbitrate debates defining architectural orientations;\nConduct individual interviews with the various mission contacts for Coaching or Audit;\nProject management: lead a project independently from start to finish under the supervision of your project director;\nDefinition of feedback, self-criticism and retrospectives of milestones.\nIn addition you will support a project to set up a \u201cData Academy\u201d organization: definition of the scope, estimation of costs, planning and organization, promotion of the methodology.\nBe responsible for the quality of project deliverables;\nLead meetings and write reports;\nSupport and advise the client in managing change in their organization to support implementation;\nValidate the company's expectations in terms of acculturation and maturity around data;\nLead and arbitrate debates defining strategic orientations;\nConduct individual interviews with the various project stakeholders for Coaching or Audit;\nProject management: lead a project independently from start to finish under the supervision of your project director;\nDefinition of feedback, self-criticism and retrospectives of milestones.\nData governance component:\nFramework a governance initiative: identification of use cases, customer needs in terms of data governance, and the appropriate methodology;\nDesign and implement a data governance solution: glossary, business, metadata, processes, roles and responsibilities, lineage.\nDefine the roadmap to improve governance.\nYour profile:\nRequired skills:\nA Data Architect profile with a functional/technical background capable of:\nParticipate in pre-sales/proposals and the definition and audit of the architecture;\nPrepare and lead various Workshop committees;\nSupport Architects and Data Advisors;\nHave solid experience in enterprise architecture and consulting activities, be able to advise the best typical model according to needs.\nMinimum of Bac+5 training within a major engineering or IT school, you have at least 5 years of experience in this type of role;\nYou have worked in the field of information management in the company, data governance, or the implementation of Data solutions (MDM, DQM, Data Catalog Data Science, Data Preparation);\nDynamic and enthusiastic, you like teamwork and you want to actively participate in the development of our company and the training of consultants. Your thirst for entrepreneurship and your desire to participate in our development will be determining elements;\nThanks to your good level of English, you will participate with ease in international missions;\nYou will work in a very motivating and friendly context and you will benefit from significant freedom over the missions you will have to accomplish.\nShow more\nShow less",
        "skills": {
            "ProgLanguage": [
                "R",
                "Go"
            ],
            "DataBase": [],
            "DataAnalytics": [
                "R"
            ],
            "BigData": [],
            "MachingLearning": [],
            "DataSerialization": [],
            "DataVisualization": [],
            "Statistics": [],
            "CloudComputing": [],
            "DevTools": [],
            "Os": [],
            "DBMS": [],
            "SoftBigDataProcessing": [],
            "Automation": [],
            "InfrastructureAsCode": [],
            "NetworkSecurty": [],
            "Virtualisation": [],
            "Containers": [],
            "Collaboration": [],
            "Other": [],
            "FrSoftSkills": [],
            "EnSoftSkils": [
                "Teamwork",
                "Organization",
                "Initiative"
            ]
        },
        "details": {
            "JobDetail": [
                "Confirmed",
                "Junior",
                "Senior"
            ],
            "TypeContract": [],
            "Salary": [],
            "Level": [
                "Bac+5"
            ],
            "Experience": [
                "a",
                "n",
                "s"
            ]
        }
    },
    {
        "source": "LinkedIn",
        "title": "Data Architect Senior - H/F",
        "company": "Lincoln France",
        "location": "Boulogne-Billancourt, \u00cele-de-France, France",
        "link": "https://fr.linkedin.com/jobs/view/data-architect-senior-h-f-at-lincoln-france-3909573086?position=22&pageNum=0&refId=a5rwPua%2FMvx%2F2M%2FPSF0oPA%3D%3D&trackingId=e90%2FpCVUztPl3zl6iZg0KA%3D%3D&trk=public_jobs_jserp-result_search-card",
        "description": "Poste CDI : Data Architect Senior - H/F\n\ud83d\udcca 8 ans minimum\nLincoln Pure Player Data\n\ud83d\udca1: R\u00e9inventant l'analyse\ndepuis 30 ans\n. Experts en Modern BI, Big Data et Science des donn\u00e9es \ud83d\udcca. Nous transformons vos donn\u00e9es en solutions pour les grands comptes, des secteurs bancaire, retail, t\u00e9l\u00e9coms, industriel, sant\u00e9, et plus encore \ud83d\udcbc.\nDescription du poste :\nNous recherchons un\nData Architect\nexp\u00e9riment\u00e9 pour rejoindre notre \u00e9quipe dynamique. Vous int\u00e9grerez\nla direction Conseil Innovation et D\u00e9veloppement de Lincoln\nau sein de laquelle vous pourrez d\u00e9velopper tout votre savoir\n\ud83c\udfaf\nMissions\n:\nConcevoir et d\u00e9velopper\nl'architecture de donn\u00e9es\n, en alignant les besoins de l'entreprise avec les meilleures pratiques du secteur. (Savoir utiliser les services cloud / outils pour r\u00e9pondre aux besoin de l\u2019entreprise)\nCollaborer avec\nles \u00e9quipes techniques et m\u00e9tiers\npour d\u00e9finir les exigences et les objectifs en mati\u00e8re de donn\u00e9es.\nD\u00e9finir et maintenir\nles normes et les directives de gouvernance des donn\u00e9es\n.\nConcevoir et mettre en \u0153uvre des\nsolutions de s\u00e9curit\u00e9 des donn\u00e9es pour prot\u00e9ger l'int\u00e9grit\u00e9 et la confidentialit\u00e9 des informations sensibles\n.\nG\u00e9rer les\nprocessus d'int\u00e9gration, de transformation et de migration\ndes donn\u00e9es.\n\u00c9valuer et s\u00e9lectionner les outils et les technologies adapt\u00e9s \u00e0 l'architecture de donn\u00e9es de l'entreprise.\nParticiper \u00e0\nl'\u00e9valuation des risques et \u00e0 la planification de la continuit\u00e9 des activit\u00e9s\nli\u00e9es aux donn\u00e9es.\nParticiper \u00e0 la r\u00e9alisation de missions de conseil\n(audit, \u00e9tude de migration de plateforme, design d\u2019architecture DATA\u2026)\nConcevoir et superviser l'architecture de donn\u00e9es du client\n, en veillant \u00e0 ce qu'elle r\u00e9ponde aux besoins actuels et futurs de l'organisation\nParticiper aux r\u00e9ponses aux\nappels d\u2019offre\nSupport technique\nau partenariat \u00e9diteur de Lincoln\nR\u00e9aliser de\nla veille technologiques\n(solution DATA, cloud/on premise)\n\ud83d\udd0d\nPr\u00e9requis\n:\nExp\u00e9rience av\u00e9r\u00e9e en tant que Data Architect ou dans un r\u00f4le similaire.\nConnaissance approfondie des concepts et des principes de l'architecture de donn\u00e9es.\nTr\u00e8s bonne connaissance des environnements de cloud (sp\u00e9cialiste sur au moins une technologie \u2013 GCP, Azure, Aws, Snowflake, Databricks\u2026)\nMa\u00eetrise des technologies et des outils de gestion de donn\u00e9es, tels que les bases de donn\u00e9es relationnelles, les entrep\u00f4ts de donn\u00e9es, les outils ETL, etc.\nSolide compr\u00e9hension des principes de s\u00e9curit\u00e9 des donn\u00e9es et de la conformit\u00e9 aux r\u00e9glementations en vigueur.\nExcellentes comp\u00e9tences analytiques et de r\u00e9solution de probl\u00e8mes.\nCapacit\u00e9 \u00e0 travailler efficacement en \u00e9quipe et \u00e0 communiquer clairement avec des interlocuteurs techniques et non techniques.\nDipl\u00f4me d\u2019ing\u00e9nieur ou universitaire en informatique, en science des donn\u00e9es ou dans un domaine connexe (un atout).\nConnaissance de mod\u00e9lisation des donn\u00e9es (3FN, \u00e9toile, flocon)\nEnvironnements techniques :\nEnvironnement de cloud (GCP, Azure, AWS) vs On premises (Hadoop, Cloudera)\nBases de donn\u00e9es relationnelles et base de donn\u00e9es NoSql (MySQL, Oracle, SQL Server, PostgreSQL, Mango DB, Cassandra, GCP Big query, Snowflake, Redshift)\nLangage : Python, Pyspark, SQL\nOutils ETL / ELT: Informatica, Talend, IBM DataStage, DBT\n\ud83c\udf1f\nAvantages :\nEnvironnement collaboratif et innovant\nFormations certifiantes et accompagnement individualis\u00e9\nT\u00e9l\u00e9travail et horaires flexibles\nR\u00e9mun\u00e9ration comp\u00e9titive avec avantages sociaux attrayants\nPossibilit\u00e9 de mobilit\u00e9 \u00e0 Lille, Lyon ou Aix-en-Provence\n\u2728\nProcessus de recrutement\n: 2 entretiens (RH et technique)\nSi vous \u00eates passionn\u00e9 par les d\u00e9fis de la Data et que vous souhaitez rejoindre une \u00e9quipe dynamique et innovante,\npostulez d\u00e8s maintenant et contribuez \u00e0 red\u00e9finir l'avenir de l'analyse de donn\u00e9es chez Lincoln! \ud83d\ude09\nShow more\nShow less",
        "skills": {
            "ProgLanguage": [
                "Python",
                "R",
                "Go"
            ],
            "DataBase": [
                "SQL",
                "NoSQL",
                "Cassandra"
            ],
            "DataAnalytics": [
                "R"
            ],
            "BigData": [
                "Hadoop",
                "Spark",
                "Databricks"
            ],
            "MachingLearning": [],
            "DataSerialization": [],
            "DataVisualization": [],
            "Statistics": [],
            "CloudComputing": [
                "AWS",
                "Azure"
            ],
            "DevTools": [],
            "Os": [],
            "DBMS": [
                "MySQL",
                "PostgreSQL",
                "Oracle",
                "SQL Server",
                "Snowflake",
                "Snowflake",
                "Big Query"
            ],
            "SoftBigDataProcessing": [],
            "Automation": [],
            "InfrastructureAsCode": [],
            "NetworkSecurty": [],
            "Virtualisation": [],
            "Containers": [],
            "Collaboration": [],
            "Other": [
                "Big Data",
                "Cloud"
            ],
            "FrSoftSkills": [
                "R\u00e9solution de probl\u00e8mes",
                "Organisation"
            ],
            "EnSoftSkils": []
        },
        "details": {
            "JobDetail": [
                "Senior"
            ],
            "TypeContract": [
                "CDI"
            ],
            "Salary": [],
            "Level": [],
            "Experience": [
                "a",
                "n",
                "s",
                "8",
                "8",
                "8"
            ]
        }
    },
    {
        "source": "LinkedIn",
        "title": "Data Architect H/F",
        "company": "Akkodis",
        "location": "France",
        "link": "https://fr.linkedin.com/jobs/view/data-architect-h-f-at-akkodis-3894683359?position=23&pageNum=0&refId=a5rwPua%2FMvx%2F2M%2FPSF0oPA%3D%3D&trackingId=I9eYsNqP6O%2FDAy8ljoEwxA%3D%3D&trk=public_jobs_jserp-result_search-card",
        "description": "La ligne de service Consulting & Solutions d Akkodis France renforce ses \u00e9quipes et recrute\nun Data Architect H/F\nen CDI dans l\u2019un de nos sites principaux en Ile de France ou en Province.\nDescription de la mission :\nL\u2019offre data intelligence d\u2019AKKODIS fait partie des 7 expertises internationales du Groupe. Elle adresse aujourd\u2019hui des projets sur de nombreux secteurs d\u2019activit\u00e9 : A\u00e9ronautique, Transport, Energie, Banque & Assurance, D\u00e9fense.\nSon objectif est d\u2019aider nos clients \u00e0 am\u00e9liorer leurs processus op\u00e9rationnels, leur time-to-market et leur prise de d\u00e9cision en permettant :\n- la mise en place de la continuit\u00e9 digitale\n- de gagner en maturit\u00e9 dans l\u2019utilisation et la valorisation des donn\u00e9es\nvia la mise en \u0153uvre de technologies et plateformes data et l\u2019utilisation data sciences et de l\u2019IA.\nNotre strat\u00e9gie de croissance nous am\u00e8ne aujourd\u2019hui \u00e0 renforcer nos comp\u00e9tences m\u00e9tier dans le domaine de la Data Intelligence et dans ce cadre nous recherchons un(e) Data Architect capable d\u2019apporter son expertise sur les projets pr\u00e9sents dans notre portefeuille actuel et aupr\u00e8s des consultants Akkodis tout en travaillant sur les sujets d\u2019avant-vente et de construction d\u2019offre afin d\u2019\u00e9largir notre scope d\u2019intervention.\nInt\u00e9gr\u00e9(e) \u00e0 l\u2019\u00e9quipe Data Intelligence, vous travaillerez en collaboration avec une \u00e9quipe d\u2019une trentaine de personnes et participerez au d\u00e9veloppement de projets innovants (Jumeau num\u00e9rique, Industrie 4.0, maintenance pr\u00e9dictive, IA g\u00e9n\u00e9rative,..)\nVous vous verrez confier les missions suivantes :\n\u00b7 Participer \u00e0 la conception de l'architecture de notre plateforme Data ainsi qu\u2019\u00e0 celles de nos clients (On Premise, Cloud, Hybride)\n\u00b7 Participer \u00e0 la veille technologique et prendre en charge l'exp\u00e9rimentation de nouvelles solutions du march\u00e9\n\u00b7 R\u00e9aliser des missions d\u2019audit et conseil en architecture pour nos clients ; impl\u00e9mentation de projets data\nDipl\u00f4m\u00e9(e) d'un Bac + 3/+5 en informatique, vous justifiez d\u2019une exp\u00e9rience de 10 ans minimum dans les domaines de la Data et maitrisez les technologies Python, PySpark, Kafla, Spark et l\u2019environnement Linux.\nVous disposez exp\u00e9riences probantes dans l\u2019impl\u00e9mentation de projets data au sein de cloud providers (MS Azure, GCP ou AWS) et \u00eates en capacit\u00e9 de benchmarker les solutions propos\u00e9es, de conseiller nos clients sur les architectures et outils \u00e0 mettre en place. Vous avez de bonnes capacit\u00e9s de synth\u00e8se et savez convaincre. Vous avez le sens du relationnel et faites preuve d'adaptabilit\u00e9 et de flexibilit\u00e9. Vous \u00eates curieux et imaginatif pour trouver des solutions adapt\u00e9es.\nAlors n'h\u00e9sitez plus, rejoignez-nous en nous transmettant votre CV !\nA comp\u00e9tences \u00e9gales, le poste est ouvert aux personnes en situation de handicap.\nEn int\u00e9grant AKKODIS vous rejoindrez une entreprise dans laquelle votre savoir-\u00eatre et votre savoir-faire feront la diff\u00e9rence pour inventer le futur de nos clients. Votre r\u00f4le s\u2019inscrit dans un v\u00e9ritable projet d'entreprise.\nAkkodis accompagne ses clients dans la mondialisation de leurs projets, aussi un anglais courant est requis pour l ensemble de nos collaborateurs.\nChez Akkodis nous sommes convaincus que de l\u2019intelligence collective na\u00eet le succ\u00e8s. Il n\u2019existe pas qu\u2019un mod\u00e8le, nous valorisons l\u2019agilit\u00e9 et l\u2019excellence, l\u2019audace et la cr\u00e9ativit\u00e9.\nEt si nous parlions ensemble de vos ambitions pour les prochaines ann\u00e9es ?\nAkkodis est une entreprise handi-engag\u00e9e et inclusive. Tous nos postes sont ouverts aux handicaps et \u00e0 la diversit\u00e9. Tous diff\u00e9rents, tous comp\u00e9tents !\nAkkodis, est un acteur mondial de l\u2019ing\u00e9nierie et de l\u2019IT et un leader dans la smart industrie. Nous accompagnons nos clients dans leurs projets de transformation digitale via 4 lignes de service : Consulting, Solutions, Talent et Academy. Akkodis est un partenaire technologique de confiance pour ses clients \u00e0 l\u2019\u00e9chelle internationale. Nous co-cr\u00e9ons et nous imaginons des solutions de pointe pour r\u00e9pondre aux d\u00e9fis majeurs de notre soci\u00e9t\u00e9, qu'il s'agisse d'acc\u00e9l\u00e9rer la transition \u00e9nerg\u00e9tique et de d\u00e9velopper la mobilit\u00e9 verte, ou encore de construire des approches centr\u00e9es sur les utilisateurs.\nDot\u00e9s d\u2019une forte culture de l\u2019inclusion et de la diversit\u00e9, nos 50 000 experts en IT et en ing\u00e9nierie, pr\u00e9sents dans 30 pays, allient les meilleures comp\u00e9tences technologiques \u00e0 une connaissance transverse de toutes les industries pour fa\u00e7onner un futur plus durable. Nous sommes passionn\u00e9s par l\u2019id\u00e9e d\u2019inventer ensemble un avenir meilleur.\nAkkodis en France, ce sont pr\u00e8s de 9.000 experts en IT et en ing\u00e9nierie r\u00e9partis sur l'ensemble du territoire, des collaborateurs partageant des valeurs fortes d'honn\u00eatet\u00e9, de respect, d'\u00e9quit\u00e9 et d'inclusion. Notre engagement : leur permettre au quotidien d'\u00eatre eux-m\u00eames au travail, et acteurs de leur vie et de leur d\u00e9veloppement au sein d'Akkodis..\nAkkodis est la marque technologique de The Adecco Group\n*Akkodis est une marque commerciale sous laquelle les entit\u00e9s AKKA et Modis op\u00e8rent\nShow more\nShow less",
        "skills": {
            "ProgLanguage": [
                "Python",
                "R"
            ],
            "DataBase": [],
            "DataAnalytics": [
                "R"
            ],
            "BigData": [
                "Spark"
            ],
            "MachingLearning": [],
            "DataSerialization": [],
            "DataVisualization": [],
            "Statistics": [],
            "CloudComputing": [
                "AWS",
                "Azure"
            ],
            "DevTools": [
                "Git"
            ],
            "Os": [
                "Linux"
            ],
            "DBMS": [],
            "SoftBigDataProcessing": [],
            "Automation": [],
            "InfrastructureAsCode": [],
            "NetworkSecurty": [],
            "Virtualisation": [],
            "Containers": [],
            "Collaboration": [],
            "Other": [
                "Cloud"
            ],
            "FrSoftSkills": [
                "Adaptabilit\u00e9",
                "Cr\u00e9ativit\u00e9",
                "Collaboration",
                "Flexibilit\u00e9"
            ],
            "EnSoftSkils": [
                "Collaboration"
            ]
        },
        "details": {
            "JobDetail": [
                "Hybride"
            ],
            "TypeContract": [
                "CDI"
            ],
            "Salary": [],
            "Level": [],
            "Experience": [
                "a",
                "n",
                "s",
                "10",
                "10",
                "10"
            ]
        }
    },
    {
        "source": "LinkedIn",
        "title": "Data Model Architect F/H",
        "company": "Schneider Electric",
        "location": "Lattes, Occitanie, France",
        "link": "https://fr.linkedin.com/jobs/view/data-model-architect-f-h-at-schneider-electric-3864654667?position=24&pageNum=0&refId=a5rwPua%2FMvx%2F2M%2FPSF0oPA%3D%3D&trackingId=v3%2F141hz7OHIAN2jbFJZAA%3D%3D&trk=public_jobs_jserp-result_search-card",
        "description": "Missions\nAs a Data Architect, you will play a crucial role in shaping and optimizing our product's data infrastructure. You will be responsible for designing, implementing, and maintaining scalable and efficient data solutions that meet business needs. This role requires a deep understanding of data management and a strategic mindset to align data architecture with overall business strategies:\nData Modeling and Design:\nEnsure compliance with industry standards such as IEC61850\nDevelop and maintain conceptual, logical, and physical data models\nDesign data structures and relationships that support business requirements and enable efficient data retrieval\nData Governance:\nEstablish and enforce data governance policies and procedures\nDefine data standards, naming conventions, and data quality rules\nData Integration:\nDesign and implement data integration solutions to ensure seamless flow of information across systems\nCollaborate with other IT teams to integrate data sources and maintain data consistency\nCollaboration and Communication:\nWork closely with business stakeholders to understand their data needs and translate them into effective data solutions\nCollaborate with cross-functional teams including analysts and developers\nSecurity and Compliance:\nImplement data security measures to protect sensitive information\nProvide leadership, analysis, and design tasks related to the development or upgrade of a solution to ensure the application provides expected business value. Provide architecture guidance and support on activities performed to maintain, improve, or support applications.\nProfile\nBachelor's or Master's degree in Computer Science, Information Technology, or a related field\nMinimum of 5 years of experience as a Data Architect or in a similar role\nKnowledge of IEC61850\nStrong knowledge of database management systems and data modeling techniques\nUnderstanding of agile methods and processes, and the capability of supporting agile project teams\nAnalytical and strategic thinking\nExcellent communication and collaboration skills\nProblem-solving and troubleshooting abilities\nStay updated on emerging trends and technologies in data management\nWhy us?\nSchneider Electric is leading the digital transformation of energy management and automation. Our technologies enable the world to use energy in a safe, efficient and sustainable manner. We strive to promote a global economy that is both ecologically viable and highly productive.\n\u20ac34bn global revenue\n128 000+ employees in 100+ countries\n45% of revenue from IoT\n5% of revenue devoted for R&D\nYou must submit an online application to be considered for any position with us. This position will be posted until filled\nIt is the policy of Schneider Electric to provide equal employment and advancement opportunities in the areas of recruiting, hiring, training, transferring, and promoting all qualified individuals regardless of race, religion, color, gender, disability, national origin, ancestry, age, military status, sexual orientation, marital status, or any other legally protected characteristic or conduct. Concerning agencies: Schneider Electric does not accept unsolicited resumes and will not be responsible for fees related to such.\nShow more\nShow less",
        "skills": {
            "ProgLanguage": [
                "Scala",
                "R",
                "Go"
            ],
            "DataBase": [],
            "DataAnalytics": [
                "R"
            ],
            "BigData": [],
            "MachingLearning": [],
            "DataSerialization": [],
            "DataVisualization": [],
            "Statistics": [],
            "CloudComputing": [],
            "DevTools": [
                "Git"
            ],
            "Os": [],
            "DBMS": [],
            "SoftBigDataProcessing": [],
            "Automation": [],
            "InfrastructureAsCode": [],
            "NetworkSecurty": [],
            "Virtualisation": [],
            "Containers": [],
            "Collaboration": [
                "Teams"
            ],
            "Other": [
                "ML"
            ],
            "FrSoftSkills": [
                "Communication",
                "Leadership",
                "Collaboration"
            ],
            "EnSoftSkils": [
                "Communication",
                "Leadership",
                "Collaboration"
            ]
        },
        "details": {
            "JobDetail": [],
            "TypeContract": [],
            "Salary": [],
            "Level": [],
            "Experience": [
                "a",
                "n",
                "s"
            ]
        }
    },
    {
        "source": "LinkedIn",
        "title": "Data architect",
        "company": "Harnham",
        "location": "Greater Paris Metropolitan Region",
        "link": "https://fr.linkedin.com/jobs/view/data-architect-at-harnham-3911912252?position=25&pageNum=0&refId=a5rwPua%2FMvx%2F2M%2FPSF0oPA%3D%3D&trackingId=%2BTxN4OcYZuigrD5W0hnoCQ%3D%3D&trk=public_jobs_jserp-result_search-card",
        "description": "DATA ARCHITECT\nPARIS (75)\nUP TO 65K\u20ac FIXE\nAWS - Tableau - Pyspark - Data Modeling\nVous \u00eates \u00e0 la recherche d'un nouveau challenge de Data Architect dans le domaine de l'assurance ? Ne cherchez plus, voici l'opportunit\u00e9 de vos r\u00eaves ! Une entreprise sp\u00e9cialis\u00e9e dans l'assurance automobile des particuliers, recherche un Data Architect dans le cadre de la cr\u00e9ation d'une nouvelle plateforme data en Europe.\nLE POSTE\nEn tant que Data Architect, vous allez d\u00e9finir les architectures et les normes pour la strat\u00e9gie de donn\u00e9es. Vous d\u00e9finirez la vision et les lignes directrices pour la livraison des produits de donn\u00e9es.\nVoici vos responsabilit\u00e9s au quotidien :\nD\u00e9finir l'architecture cible\nCommuniquer avec les Product Owner pour atteindre l'objectif du wagon\nTravailler en \u00e9troite collaboration avec les data scientists pour op\u00e9rationnaliser les mod\u00e8les ML au sein de la plateforme de donn\u00e9es\nTravailler en \u00e9troite collaboration avec les data engineer et data ops pour le suivi de l'architecture cible\nTravailler en mode agile au quotidien\nVOTRE PROFIL\nDipl\u00f4me d'ing\u00e9nieur en computer engineering ou math\u00e9matiques\n5 ans d'exp\u00e9rience en architecture data\nConnaissance des architectures de plateformes de donn\u00e9es op\u00e9rationnelles\nConnaissance de la mod\u00e9lisation de donn\u00e9es et bases de donn\u00e9es\nConnaissance du cloud AWS\nConnaissance d'outils BI principalement Tableau\nBilingue (fan\u00e7ais et anglais)\nNice to have : connaissance en Machine Learning\nPOUR POSTULER\nMerci de me faire part de votre CV et je vous recontacterai au plus vite.\nShow more\nShow less",
        "skills": {
            "ProgLanguage": [
                "R",
                "Go"
            ],
            "DataBase": [],
            "DataAnalytics": [
                "R"
            ],
            "BigData": [
                "Spark"
            ],
            "MachingLearning": [],
            "DataSerialization": [],
            "DataVisualization": [
                "Tableau"
            ],
            "Statistics": [],
            "CloudComputing": [
                "AWS"
            ],
            "DevTools": [],
            "Os": [],
            "DBMS": [],
            "SoftBigDataProcessing": [],
            "Automation": [],
            "InfrastructureAsCode": [],
            "NetworkSecurty": [],
            "Virtualisation": [],
            "Containers": [],
            "Collaboration": [],
            "Other": [
                "ML",
                "Machine Learning",
                "Cloud"
            ],
            "FrSoftSkills": [
                "Collaboration"
            ],
            "EnSoftSkils": [
                "Collaboration"
            ]
        },
        "details": {
            "JobDetail": [],
            "TypeContract": [],
            "Salary": [],
            "Level": [],
            "Experience": [
                "a",
                "n",
                "s",
                "5",
                "5",
                "5"
            ]
        }
    },
    {
        "source": "LinkedIn",
        "title": "Architecte Data",
        "company": "FRG Technology Consulting",
        "location": "Paris, \u00cele-de-France, France",
        "link": "https://fr.linkedin.com/jobs/view/architecte-data-at-frg-technology-consulting-3917370845?position=26&pageNum=0&refId=a5rwPua%2FMvx%2F2M%2FPSF0oPA%3D%3D&trackingId=mFbs%2FJJcyFdi2JyuXmjTDA%3D%3D&trk=public_jobs_jserp-result_search-card",
        "description": "Notre client, entreprise renomm\u00e9e dans le secteur du luxe et des cosm\u00e9tiques, bas\u00e9 sur Paris, est \u00e0 la recherche de son/sa futur(e) Architecte Data.\nEn tant que membre de la DSI, votre r\u00f4le est de participer \u00e0 la transformation digitale de l\u2019entreprise, par une meilleure capture, analyse et exploitation des donn\u00e9es clients.\nPrincipales missions :\nAnalyse et r\u00e9ponses aux besoins des m\u00e9tiers (BI, analyses externes, etc.),\nConception de nouveaux mod\u00e8les de donn\u00e9es\nConstruction des pipelines de donn\u00e9es\nTransformation de donn\u00e9es (Pyspark) et le stockage de donn\u00e9es dans le Data Lake / Data Warehouse du Groupe\nRun et le suivi de la TMA\nDescription du profil :\nTitulaire Bac +5 informatique ou dipl\u00f4me ing\u00e9nieur\n6 ann\u00e9es minimum en expertise Data\nUne bonne ma\u00eetrise des outils suivants : Azure, SQL, Snowflake, Databricks, Spark, Python, ELK,..\nUne bonne affinit\u00e9 avec les best practices DevOps, CI/CD, unit-testing et m\u00e9thodologies de travail agile\nDes notions en data science sur l\u2019entra\u00eenement, la validation et le d\u00e9ploiement de mod\u00e8les ML supervis\u00e9s et non-supervis\u00e9s serait un plus.\nQualit\u00e9s requises : Bon esprit analytique et de synth\u00e8se, rigoureux, autonome, bonne communication, curieux, force de proposition, vulgarisation des probl\u00e9matiques techniques aupr\u00e8s du m\u00e9tier\nAvantages :\nPackage (variable / participation / int\u00e9ressement) + avantages attractifs\n\u00c9quipe Data \u00e0 taille humaine (tr\u00e8s bon accompagnement en interne)\nForte valeur ajout\u00e9e des projets\nT\u00e9l\u00e9travail\nCandidatures confidentielles\nShow more\nShow less",
        "skills": {
            "ProgLanguage": [
                "Python",
                "R",
                "Go"
            ],
            "DataBase": [
                "SQL"
            ],
            "DataAnalytics": [
                "R"
            ],
            "BigData": [
                "Spark",
                "Databricks"
            ],
            "MachingLearning": [],
            "DataSerialization": [],
            "DataVisualization": [],
            "Statistics": [],
            "CloudComputing": [
                "Azure"
            ],
            "DevTools": [
                "Git"
            ],
            "Os": [],
            "DBMS": [
                "Snowflake",
                "Snowflake"
            ],
            "SoftBigDataProcessing": [],
            "Automation": [],
            "InfrastructureAsCode": [],
            "NetworkSecurty": [],
            "Virtualisation": [],
            "Containers": [],
            "Collaboration": [],
            "Other": [
                "DevOps",
                "ML",
                "CI/CD"
            ],
            "FrSoftSkills": [
                "Communication"
            ],
            "EnSoftSkils": [
                "Communication"
            ]
        },
        "details": {
            "JobDetail": [],
            "TypeContract": [],
            "Salary": [
                "Package"
            ],
            "Level": [],
            "Experience": [
                "a",
                "n",
                "s"
            ]
        }
    },
    {
        "source": "LinkedIn",
        "title": "Architecte Data F/H",
        "company": "Ippon Technologies",
        "location": "Greater Lyon Area",
        "link": "https://fr.linkedin.com/jobs/view/architecte-data-f-h-at-ippon-technologies-3893256404?position=27&pageNum=0&refId=a5rwPua%2FMvx%2F2M%2FPSF0oPA%3D%3D&trackingId=6CvjRcGeId%2FV7kMGgeTUyg%3D%3D&trk=public_jobs_jserp-result_search-card",
        "description": "Qui sommes-nous ?\nIppon\n, c'est l\u2019\u00e9nergie du collectif au service de la technologie ! Nous sommes un cabinet de conseil et d\u2019expertise technique. Nos \u00e9quipes ont pour leitmotive de transformer des id\u00e9es innovantes en solutions logicielles de haute qualit\u00e9 avec un focus particulier sur la valeur apport\u00e9e aux utilisateurs.\nCr\u00e9\u00e9e en 2017, l\u2019agence de Lyon, ce sont des passionn\u00e9s intervenant sur des projets \u00e0 forte technicit\u00e9 ou en conseil et architecture : Fullstack, Data, DevOps, Cloud, Agile, Design et ne compte pas s\u2019arr\u00eater en si bon chemin !\nLa pluridisciplinarit\u00e9, l\u2019expertise, l\u2019\u00e9coute, l\u2019adaptabilit\u00e9 mais aussi le partage de connaissances fondent notre engagement au service de nos partenariats.\nVous int\u00e9grerez notre Communaut\u00e9 Data\n, compos\u00e9e d\u2019une \u00e9quipe de\n80 experts sur 10 agences en France.\nNotre sp\u00e9cialit\u00e9 est de\nconstruire des data platforms dans le Cloud public avec les meilleures technos du moment.\nLa\nData chez Ippon, c\u2019est d\u00e9j\u00e0 plus de\n250 certifications AWS, GCP et AZURE,\ndes\nspeakers \u00e0 l\u2019AWS Summit, des partenariats avec Snowflake, Databricks, DBT, un blog technique\navec des publications r\u00e9guli\u00e8res.\nCe poste est un vrai challenge aussi bien en termes de\nd\u00e9fis techniques que de gestion d'\u00e9quipe.\nLa\nr\u00e9ussite de vos projets sera port\u00e9e par votre capacit\u00e9 \u00e0 vous adapter et \u00e0 monopoliser un large panel de comp\u00e9tences techniques. Vous devrez \u00eatre le/la leader de votre \u00e9quipe en gardant \u00e0 l\u2019esprit l\u2019ensemble des\nbonnes pratiques d'architectes\n, de s\u00e9curit\u00e9 et d\u2019automatisation n\u00e9cessaires \u00e0 la r\u00e9ussite du projet. En tant que\nrepr\u00e9sentant(e) de l\u2019engagement d\u2019Ippon\nsur les sujets qui vous seront confi\u00e9s, vous serez amen\u00e9(e) \u00e0\ntravailler avec notre \u00e9quipe Commerce d\u00e8s les phases de qualification\net lors de la validation de jalons de la roadmap que vous aurez pr\u00e9alablement valid\u00e9 avec le client. Vous interviendrez \u00e9galement dans la s\u00e9lection de l\u2019\u00e9quipe qui sera affect\u00e9e \u00e0 votre projet.\nVotre r\u00f4le :\n- Gr\u00e2ce \u00e0 votre position d\u2019architecte vous avez une vision experte et syst\u00e9mique de l\u2019ensemble des composants d\u2019une Modern Data Platform.\n- Vous ma\u00eetrisez le panel des exigences fonctionnelles et non fonctionnelles \u00e0 collecter afin d\u2019assurer l\u2019efficience op\u00e9rationnelle et la p\u00e9rennit\u00e9 de la data platform.\n- Vous \u00eates expert(e) et ma\u00eetrisez tous les outils et services d\u2019au moins un \u00e9cosyst\u00e8me parmi les 3 principaux leaders du march\u00e9 (AWS, Azure et GCP) et avez des facilit\u00e9s pour \u00e9tendre votre champ de comp\u00e9tences.\n- Vous \u00eates proactif/ve sur la veille technique et la capitalisation et veillez \u00e0 garder toujours un temps d\u2019avance sur l\u2019\u00e9tat de l\u2019art du secteur afin de pouvoir guider vos clients.\n- En tant qu\u2019architecte exp\u00e9riment\u00e9(e) vous pouvez indiff\u00e9remment intervenir sur des missions de delivery pour concevoir la solution cible ou en phase de cadrage amont pour guider les choix et construire les roadmaps.\n- Vous \u00eates p\u00e9dagogue et savez communiquer et vulgariser des r\u00e9flexions complexes pour les rendre accessibles \u00e0 tous.\nNotre \u00e9co-syst\u00e8me technique :\n- Cloud : AWS, GCP, Azure\n- Langage de programmation data : Python, SQL, Scala\n- Approche Data Warehouse : Redshift, Snowflake, BigQuery\n- Approche Data Lakehouse : Databricks, Starburst, Glue-Athena-S3Ingestion : AWS Glue, Airbyte, dbt Stockage : AWS S3, Google Cloud Storage, Azure Blob Storage\n- Orchestration : Airflow, AWS Step function\n- Gouvernance : cataloging, s\u00e9curit\u00e9, scope d'acc\u00e8sBatch et Streaming : Kafka, Amazon Kinesis, Google DataFlow\n- Outil de visualisation : Tableau, Power BI, Metabase, Superset\nVotre \u00e9volution chez Ippon :\nVous serez accompagn\u00e9(e) dans votre mont\u00e9e en comp\u00e9tences aussi bien technique que leadership gr\u00e2ce \u00e0\nnotre programme BlackBelt\n(programme de formation continue : mentoring, formations, certifications).\nEn tant que membre d\u2019une communaut\u00e9,\nvous pouvez avoir diff\u00e9rents r\u00f4les :\n- Celui de Manager Technique (MT) : manager d\u2019une \u00e9quipe de 7 ing\u00e9nieur(e)s Ippon (onboarding, suivis, accompagnement, mise en place d\u2019objectifs\u2026). Vous conduirez les entretiens techniques en bin\u00f4me\n- Responsable de l\u2019accomplissement d\u2019une ou plusieurs actions strat\u00e9giques de la CoreTeam Data\n- Devenir speaker lors de Meetup, Summit, Talks internes, aupr\u00e8s des \u00e9coles \u2026\n- Devenir formateur(trice) et accompagner la nouvelle g\u00e9n\u00e9ration d\u2019Ippon dans leur mont\u00e9e en comp\u00e9tencesVous avez d\u2019autres souhaits, pas de soucis, nous en discuterons durant notre \u00e9change et r\u00e9pondrons \u00e0 toutes vos questions.\nLes Next Steps :\n1 Echange RH\n1 Echange Technique\n1 Echange avec la Direction\nSi le match est bon des deux c\u00f4t\u00e9s : Vous vous lancerez sur le tatami Ippon !\nShow more\nShow less",
        "skills": {
            "ProgLanguage": [
                "Python",
                "Scala",
                "R",
                "Go"
            ],
            "DataBase": [
                "SQL"
            ],
            "DataAnalytics": [
                "R"
            ],
            "BigData": [
                "Databricks"
            ],
            "MachingLearning": [],
            "DataSerialization": [],
            "DataVisualization": [
                "Tableau",
                "Power BI"
            ],
            "Statistics": [],
            "CloudComputing": [
                "AWS",
                "Azure"
            ],
            "DevTools": [],
            "Os": [],
            "DBMS": [
                "Snowflake",
                "Snowflake",
                "BigQuery"
            ],
            "SoftBigDataProcessing": [],
            "Automation": [
                "Airflow"
            ],
            "InfrastructureAsCode": [],
            "NetworkSecurty": [],
            "Virtualisation": [],
            "Containers": [],
            "Collaboration": [],
            "Other": [
                "DevOps",
                "Cloud"
            ],
            "FrSoftSkills": [
                "Adaptabilit\u00e9",
                "Leadership"
            ],
            "EnSoftSkils": [
                "Leadership"
            ]
        },
        "details": {
            "JobDetail": [
                "Full"
            ],
            "TypeContract": [],
            "Salary": [],
            "Level": [],
            "Experience": [
                "a",
                "n",
                "s"
            ]
        }
    },
    {
        "source": "LinkedIn",
        "title": "DATA ANALYST JUNIOR (H/F)",
        "company": "Akademija Oxford",
        "location": "Boulogne-Billancourt, \u00cele-de-France, France",
        "link": "https://fr.linkedin.com/jobs/view/data-analyst-junior-h-f-at-akademija-oxford-3917871112?position=28&pageNum=0&refId=a5rwPua%2FMvx%2F2M%2FPSF0oPA%3D%3D&trackingId=f1yl%2BuAsrVAr6V%2FZJ%2F13UQ%3D%3D&trk=public_jobs_jserp-result_search-card",
        "description": "Notre entreprise partenaire, sp\u00e9cialiste de la vente de m\u00e9dicaments et produits de sant\u00e9, recherche un apprenti Data Analyst (H/F) pr\u00e9parant un bac +4/+5 en fili\u00e8re Big Data pour la rentr\u00e9e de Septembre 2021.\nShow more\nShow less",
        "skills": {
            "ProgLanguage": [
                "R"
            ],
            "DataBase": [],
            "DataAnalytics": [
                "R"
            ],
            "BigData": [],
            "MachingLearning": [],
            "DataSerialization": [],
            "DataVisualization": [],
            "Statistics": [],
            "CloudComputing": [],
            "DevTools": [],
            "Os": [],
            "DBMS": [],
            "SoftBigDataProcessing": [],
            "Automation": [],
            "InfrastructureAsCode": [],
            "NetworkSecurty": [],
            "Virtualisation": [],
            "Containers": [],
            "Collaboration": [],
            "Other": [
                "Big Data"
            ],
            "FrSoftSkills": [],
            "EnSoftSkils": []
        },
        "details": {
            "JobDetail": [],
            "TypeContract": [],
            "Salary": [],
            "Level": [],
            "Experience": [
                "a",
                "n",
                "s"
            ]
        }
    },
    {
        "source": "LinkedIn",
        "title": "Data Architect Azure",
        "company": "FRG Technology Consulting",
        "location": "Paris, \u00cele-de-France, France",
        "link": "https://fr.linkedin.com/jobs/view/data-architect-azure-at-frg-technology-consulting-3902057360?position=29&pageNum=0&refId=a5rwPua%2FMvx%2F2M%2FPSF0oPA%3D%3D&trackingId=zMsO%2FBb3IByPj0twNDoAAQ%3D%3D&trk=public_jobs_jserp-result_search-card",
        "description": "FRG Consulting recrute pour l'un de ses clients, une soci\u00e9t\u00e9 finale renomm\u00e9e dans le secteur du luxe et des cosm\u00e9tiques, un Data Architect expert en Azure. Nich\u00e9 au c\u0153ur de Paris, vous aurez l'opportunit\u00e9 de travailler au sein d'une \u00e9quipe passionn\u00e9e par la recherche et l'innovation, \u00e9voluant dans un environnement stimulant et cr\u00e9atif.\nVos missions captivantes :\nContribuer \u00e0 l'\u00e9volution de nos syst\u00e8mes en d\u00e9veloppant de nouveaux connecteurs et pipelines pour l'extraction de donn\u00e9es, qu'il s'agisse de batch (utilisant Sqoop, scripts bash, Java ou des API) ou de streaming (via Kafka, ELK).\nParticiper activement \u00e0 la transformation des donn\u00e9es \u00e0 l'aide de Pyspark, ainsi qu'au stockage dans notre Data Lake et notre Data Warehouse.\nConcevoir de nouveaux mod\u00e8les de donn\u00e9es et mettre \u00e0 disposition des tables ad-hoc sur Snowflake et Impala, r\u00e9pondant ainsi aux besoins m\u00e9tier en termes de BI et d'analyses externes.\nAssurer le bon fonctionnement et le suivi de la TMA du Data Lake, garantissant ainsi la fiabilit\u00e9 et la performance de nos syst\u00e8mes.\nProfil recherch\u00e9 :\nVous b\u00e9n\u00e9ficiez d'au moins 8 ans d'exp\u00e9rience dans le domaine.\nVous ma\u00eetrisez les outils et frameworks de notre stack technique Big Data : Azure, SQL, Snowflake, Databricks, Spark, Python, ELK.\nVous \u00eates familier des best practices DevOps, CI/CD, et des m\u00e9thodologies de travail agile.\nDes comp\u00e9tences en data science, notamment sur l'entra\u00eenement, la validation et le d\u00e9ploiement de mod\u00e8les ML supervis\u00e9s et non-supervis\u00e9s, seraient grandement appr\u00e9ci\u00e9es.\nLa ma\u00eetrise de l'anglais est indispensable pour \u00e9voluer dans un environnement international et dynamique.\nShow more\nShow less",
        "skills": {
            "ProgLanguage": [
                "Python",
                "Java",
                "R",
                "Bash"
            ],
            "DataBase": [
                "SQL"
            ],
            "DataAnalytics": [
                "R"
            ],
            "BigData": [
                "Spark",
                "Databricks"
            ],
            "MachingLearning": [],
            "DataSerialization": [],
            "DataVisualization": [],
            "Statistics": [],
            "CloudComputing": [
                "Azure"
            ],
            "DevTools": [],
            "Os": [],
            "DBMS": [
                "Snowflake",
                "Snowflake"
            ],
            "SoftBigDataProcessing": [],
            "Automation": [],
            "InfrastructureAsCode": [],
            "NetworkSecurty": [],
            "Virtualisation": [],
            "Containers": [],
            "Collaboration": [],
            "Other": [
                "DevOps",
                "Big Data",
                "ML",
                "CI/CD"
            ],
            "FrSoftSkills": [],
            "EnSoftSkils": []
        },
        "details": {
            "JobDetail": [],
            "TypeContract": [],
            "Salary": [],
            "Level": [],
            "Experience": [
                "a",
                "n",
                "s",
                "8",
                "8",
                "8"
            ]
        }
    },
    {
        "source": "LinkedIn",
        "title": "Data Architect Senior - Freelance (H/F)",
        "company": "TeamWork Corporate",
        "location": "Saint-Priest, Auvergne-Rh\u00f4ne-Alpes, France",
        "link": "https://fr.linkedin.com/jobs/view/data-architect-senior-freelance-h-f-at-teamwork-corporate-3916528778?position=30&pageNum=0&refId=a5rwPua%2FMvx%2F2M%2FPSF0oPA%3D%3D&trackingId=K%2BcSw9XhUoNNd0%2BsEaReTg%3D%3D&trk=public_jobs_jserp-result_search-card",
        "description": "Description de l'entreprise\nTeamWork est un acteur majeur du conseil, de l\u2019int\u00e9gration technologique et de l\u2019innovation, implant\u00e9 en Europe, en Asie et en Am\u00e9rique du Nord.\nAu travers de ses univers, SAP Business Solutions, Data Analytics, Technology Platform et Salesforce, nous sommes reconnus par nos clients pour accro\u00eetre leur performance op\u00e9rationnelle.\nLa transformation digitale est un enjeu majeur pour toute organisation.\nLa n\u00e9cessit\u00e9 de digitaliser ses processus, d\u2019imaginer de nouvelles fa\u00e7ons d\u2019interagir avec ses clients, d\u2019en conqu\u00e9rir de nouveaux et de proposer de nouveaux outils pour anticiper les besoins de pilotage\u202fn\u2019a jamais \u00e9t\u00e9 aussi forte.\nL\u2019univers Data Analytics de TeamWork accompagne les organisations autour de :\nLa r\u00e9flexion et identification de cas d\u2019usage pour les transformer en trajectoires moyen et long terme\nLe design et l\u2019impl\u00e9mentation de plateforme de donn\u00e9es et des outils p\u00e9riph\u00e9riques (data ingestion/int\u00e9gration)\nLa mise en place des premi\u00e8res solutions\u202fd\u2019Analytics (Business Intelligence, EPM,)\nSupport, extension et optimisation des solutions\nDans le cadre du d\u00e9veloppement de ces activit\u00e9s, nous recrutons un\nData Architect Senior (H/F)\nen Freelance pour une mission entre 2 \u00e0 3 mois.\nDescription du poste\nEn tant qu\u2019Architecte Data vous intervenez dans le cadre de projets et missions qui r\u00e9pondent aux enjeux clients d\u2019exploitation des donn\u00e9es. Vous participez aux phases d\u2019avant-vente, aux \u00e9tudes d\u2019architecture, et \u00e0 la r\u00e9alisation des solutions avec une responsabilit\u00e9 d\u2019encadrement technique des projets (tant sur des forfaits que des missions clients). Vous aurez des missions avec de r\u00e9elles responsabilit\u00e9s et tr\u00e8s diversifi\u00e9es (secteurs d\u2019activit\u00e9s vari\u00e9s).\nVos principales missions s\u2019articulent autour de :\nL\u2019analyse et la qualification des besoins et probl\u00e9matiques \u00ab m\u00e9tiers \u00bb de nos clients\nAssurer la conception, le d\u00e9veloppement et la mise en oeuvre de l'architecture des donn\u00e9es sur la plateforme Databricks\nLa d\u00e9finition et mise en \u0153uvre des architectures Data adapt\u00e9es aux contextes des projets : Modern Datawarehouse, LakeHouse, DataMesh etc.\nL\u2019accompagnement des Consultants et des Ing\u00e9nieurs sp\u00e9cialistes Data sur les projets. Vous \u0153uvrez \u00e0 qualit\u00e9 de leurs r\u00e9alisations et des livrables.\nLa collaboration sur tous les domaines d\u2019activit\u00e9s DATA : BI, Big Data, IoT, IA\nL\u2019apport d\u2019un regard critique et la capacit\u00e9 \u00e0 conseiller sur le choix des technologies Data\nLa participation \u00e0 la d\u00e9finition des bonnes pratiques de mises en \u0153uvres techniques et la veille \u00e0 leurs applications selon les m\u00e9thodes en vigueur (Zero Trust Security, DataOps, Infra-as-Code, Tests automatis\u00e9s etc.)\nQualifications\nTechniques :\nVous avez :\nTr\u00e8s bonnes connaissances de Databricks\nLa capacit\u00e9 \u00e0 r\u00e9aliser la conception et l\u2019impl\u00e9mentation de solutions d\u2019analytique \u00e0 l\u2019\u00e9chelle de l\u2019entreprise ; SQL\nLa connaissance d\u2019un ou plusieurs outils ETL (Azure Data Factory ou autres) et Data Visualisation (PowerBI par exemple)\nLa capacit\u00e9 \u00e0 mettre en place une solution Data end-to-end La connaissances des typologies d\u2019architectures (Modern Datawarehouse, LakeHouse ou DataMesh)\nVous connaissez l\u2019environnement Azure, MSBI, SQL Server ou si vous avez des notions dans l\u2019IA (Python, R, Machine Learning)\nMaitrise le traitement et l'analyse des donn\u00e9es en Python (Exp\u00e9rience dans la conception et le d\u00e9veloppement de processus ETL/ELT)\nMaitrise d\u2019outils de traitement et de stockage distribu\u00e9s parmi Hadoop, Spark, Databricks, Snowflake et/ou Kafka\nConnaissance des bonnes pratiques de conception d\u2019architecture data (s\u00e9curit\u00e9, disponibilit\u00e9, scalabilit\u00e9, confidentialit\u00e9) et des principes d\u2019une architecture Data Mesh.\nCapacit\u00e9 \u00e0 concevoir des architectures bas\u00e9es sur les services d\u2019une plateforme Cloud : AWS ou Azure\nSoft Skills\n:\nVous \u00eates proactif et appr\u00e9ciez travailler dans un environnement ambitieux et innovant.\nVous aimez ne pas rester sur vos acquis et toujours apprendre par le biais de formations, votre veille technologique ou encore par la participation aux \u00e9v\u00e9nements communautaires.\nHabitu\u00e9 \u00e0 travailler aussi bien de fa\u00e7on autonome qu\u2019\u00e0 collaborer en \u00e9quipe\nConnaissance des m\u00e9thodologies Agile (SCRUM ou autres)\nEnvie d\u2019apprendre et de partager vos savoir-faire\nCuriosit\u00e9\nLangues :\nFran\u00e7ais (Courant)\nAnglais (A l\u2019aise en communication orale et \u00e9crite)\nFormation\n:\nV\u00e9ritable passionn\u00e9 par la DATA et dipl\u00f4m\u00e9 d\u2019une \u00e9cole d\u2019ing\u00e9nieur (Bac+3 minimum) ou d'une formation sp\u00e9cifique orient\u00e9e Data avec une exp\u00e9rience significative en Data Engineering et architecture.\nVous avez une exp\u00e9rience de plus de 7 ans en environnement informatique, dont 3 \u00e0 4 ans minimum sur un poste senior en environnement Databricks (Team Lead, Architecte ou encore Consultant Senior).\nNous attacherons davantage d\u2019importance \u00e0 votre capacit\u00e9 \u00e0 vouloir apprendre et progresser et votre motivation qu\u2019\u00e0 votre dipl\u00f4me.\nInformations suppl\u00e9mentaires\nTeamWork, o\u00f9 votre \u00e9panouissement professionnel est cl\u00e9. R\u00e9compens\u00e9s par le label 'Great Place to Work 2023', nous pla\u00e7ons l'humain au c\u0153ur de notre entreprise.\nAu-del\u00e0 des comp\u00e9tences, nous valorisons les personnalit\u00e9s qui partagent nos valeurs de solidarit\u00e9 et d'esprit d'\u00e9quipe.\nSi ces principes vous parlent, rejoignez-nous ! Nous sommes d\u00e9di\u00e9s \u00e0 l'\u00e9quit\u00e9 et \u00e0 la diversit\u00e9, ouvrant nos portes \u00e0 tous les talents, y compris aux personnes en situation de handicap.\nPostulez et devenez un acteur de notre r\u00e9ussite collective chez TeamWork.\nShow more\nShow less",
        "skills": {
            "ProgLanguage": [
                "Python",
                "Scala",
                "R"
            ],
            "DataBase": [
                "SQL"
            ],
            "DataAnalytics": [
                "R"
            ],
            "BigData": [
                "Hadoop",
                "Spark",
                "Databricks"
            ],
            "MachingLearning": [],
            "DataSerialization": [],
            "DataVisualization": [
                "PowerBI"
            ],
            "Statistics": [],
            "CloudComputing": [
                "AWS",
                "Azure"
            ],
            "DevTools": [
                "Git"
            ],
            "Os": [],
            "DBMS": [
                "SQL Server",
                "Snowflake",
                "Snowflake"
            ],
            "SoftBigDataProcessing": [],
            "Automation": [],
            "InfrastructureAsCode": [],
            "NetworkSecurty": [],
            "Virtualisation": [],
            "Containers": [],
            "Collaboration": [],
            "Other": [
                "Big Data",
                "Machine Learning",
                "Cloud"
            ],
            "FrSoftSkills": [
                "Communication",
                "Collaboration",
                "Organisation"
            ],
            "EnSoftSkils": [
                "Communication",
                "Teamwork",
                "Collaboration"
            ]
        },
        "details": {
            "JobDetail": [
                "Senior"
            ],
            "TypeContract": [],
            "Salary": [],
            "Level": [
                "Bac+3"
            ],
            "Experience": [
                "a",
                "n",
                "s",
                "7",
                "7",
                "7"
            ]
        }
    },
    {
        "source": "LinkedIn",
        "title": "Airbus Atlantic - Architecte Data (All Gender)",
        "company": "Airbus",
        "location": "Greater Saint-Nazaire Area",
        "link": "https://fr.linkedin.com/jobs/view/airbus-atlantic-architecte-data-all-gender-at-airbus-3916426275?position=31&pageNum=0&refId=a5rwPua%2FMvx%2F2M%2FPSF0oPA%3D%3D&trackingId=gQfwmP6313P%2BMZbEabRRXA%3D%3D&trk=public_jobs_jserp-result_search-card",
        "description": "Job Description\nEt si VOTRE aventure avec NOUS commen\u00e7ait ?!\nNous vous proposons de travailler chez Airbus Atlantic, nouveau champion de dimension mondiale, n\u00b02 des a\u00e9rostructures, n\u00b01 des si\u00e8ges pilotes et dans le Top 3 des fauteuils passagers Premium.\nNotre site Airbus Atlantic bas\u00e9\n\u00e0 Toulouse (possibilit\u00e9 de travailler \u00e0 Montoir de Bretagne)\nrecherche son futur\nArchitecte Data (All Gender)\nLe poste d\u2019architecte Data est rattach\u00e9 au domaine \u00ab Architecture \u00bb au sein du d\u00e9partement \u00ab Architecture Digital & S\u00e9curit\u00e9 \u00bb.\nVous serez en interface avec les architectes du Syst\u00e8me d'Information et les diff\u00e9rents m\u00e9tiers consommateurs des architectures.\nVos Principales Missions Seront Les Suivantes\nFixer les orientations et d\u00e9finir des politiques concernant la mod\u00e9lisation des donn\u00e9es, en collaboration avec les autres architectes,\nCr\u00e9er des mod\u00e8les de donn\u00e9es logiques et physiques en utilisant les meilleures pratiques pour garantir une qualit\u00e9 \u00e9lev\u00e9e des donn\u00e9es et une r\u00e9duction de leur redondance,\nInstancier, impl\u00e9menter, construire, tester et maintenir les architectures data d\u00e9finies\nAnalyser, \u00e9valuer, tester et recommander les briques technologiques n\u00e9cessaires pour l\u2019acquisition, l\u2019analyse et l\u2019impl\u00e9mentation des donn\u00e9es,\nAnalyser les probl\u00e8mes d'int\u00e9gration des syst\u00e8mes li\u00e9s aux donn\u00e9es et proposer des solutions appropri\u00e9es,\nD\u00e9terminer les \u00ab Data set process \u00bb c\u2019est \u00e0 dire comment les donn\u00e9es sont int\u00e9gr\u00e9es et transform\u00e9es pour qu\u2019elles soient pr\u00eates \u00e0 \u00eatre analys\u00e9es (ex : ETL)\nParticiper aux processus d'extraction performants et qualitatifs des donn\u00e9es des sources requises afin de r\u00e9pondre aux besoins de l'entreprise\nMaintenir les mod\u00e8les de donn\u00e9es conceptuels, logiques et physiques ainsi que les m\u00e9tadonn\u00e9es correspondantes (pour la data gouvernance).\nD\u00e9velopper les meilleures pratiques pour les conventions de d\u00e9nomination standard et les pratiques de codage afin d'assurer la coh\u00e9rence des mod\u00e8les de donn\u00e9es,\nRespecter les normes de s\u00e9curit\u00e9 des donn\u00e9es, de contr\u00f4le des exportations et de protection des donn\u00e9es.\nConstruire les pipelines qui permettront aux Data Scientist/Analysts/Developers de mettre leurs mod\u00e8les en production\nEtre garant de la fiabilit\u00e9, de la qualit\u00e9 et de l\u2019efficacit\u00e9 du traitement des donn\u00e9es\nMaintenir les mod\u00e8les cr\u00e9\u00e9s.\nParticiper aux id\u00e9ations et proposer des innovations aux services.\nDocumenter ses activit\u00e9s et mettre \u00e0 jour le r\u00e9f\u00e9rentiel documentaire.\nParlons de vous !\nVous disposez d'une\ne\nxp\n\u00e9rience de minimum 5 ans en Data & Informatique sur un poste similaire.\nLes comp\u00e9tences techniques \u00e0 d\u00e9tenir pour le poste :\nL\u2019optimisation et les standards Qualit\u00e9 des donn\u00e9es informatiques\nComprendre et savoir mettre en place les diff\u00e9rentes Structure et stockage de donn\u00e9es\nGestion des probl\u00e8mes li\u00e9 \u00e0 la donn\u00e9e, l'architecture\nId\u00e9alement, l'exp\u00e9rience des technologies suivantes serait un plus : Ressources & services data MS Azure (Databricks, Azure ML \u2026), SGBD (SQL, MongoDB, PostGreSQL, redis), Outils ETL (Qlik replicate, Alteryx, \u2026), Outils BI (PowerBI, Qlik, Grafana ...),\nLangages de programmation (python, SCALA, R, DAX)\nLes certifications de Azure (DP-203, AZ-300, AZ-303, AZ-304, AZ-400, AI-900) seraient un plus,\nVotre Personnalit\u00e9\nFort volont\u00e9 de travailler en \u00e9quipe\nBonnes habitudes de documentation\nNiveau avanc\u00e9 en Fran\u00e7ais et en Anglais (niveau minimum B1)\nFaire preuve d\u2019innovation et \u00eatre source de proposition\nSavoir exprimer ses id\u00e9es de mani\u00e8re claire et concise\nEtre \u00e0 l'\u00e9coute\nParlons de nous !\nEnvironnement & Conditions De Travail\nAirbus Atlantic c\u2019est aussi :\nPrendre part \u00e0 des projets ambitieux, \u00e0 la pointe de la technologie pour construire l\u2019avion de demain, en lien avec les enjeux environnementaux.\nUn environnement qui valorise la proximit\u00e9 et la dimension humaine, au sein d\u2019un collectif engag\u00e9 et solidaire.\nL\u2019opportunit\u00e9 d\u2019apprendre et d\u2019\u00e9voluer tout au long de votre parcours, en \u00e9tant accompagn\u00e9 dans votre d\u00e9veloppement pour une carri\u00e8re sur-mesure.\nAvoir la libert\u00e9 d\u2019entreprendre et de laisser libre court \u00e0 vos initiatives.\nSes conditions de travail attractives et ses avantages : restaurant d\u2019entreprise sur site, CSE (avantages loisirs & famille), parking entreprise, mutuelle d\u2019entreprise (famille).\nSa politique de diversit\u00e9 et d'inclusion : Airbus Atlantic s\u2019engage en faveur de l\u2019\u00e9galit\u00e9 des chances pour tous.\nSon plan d'actionnariat salari\u00e9 et son plan d\u2019\u00e9pargne salariale.\nNotre Processus De Recrutement\nNous avons \u00e0 c\u0153ur de mieux vous conna\u00eetre et de comprendre ce qui vous motive \u00e0 nous rejoindre. Aussi, notre process de recrutement se d\u00e9roule en plusieurs \u00e9tapes apr\u00e8s analyse de votre candidature :\nEntretien vid\u00e9o diff\u00e9r\u00e9 via la plateforme Hirevue\nEntretien avec le Manager Recruteur\nEntretien avec le/la Charg\u00e9(e) de Recrutement qui peut \u00eatre compl\u00e9t\u00e9 par un questionnaire de personnalit\u00e9\nEntretien avec le/la Human Resources Business Partner.\nThis job requires an awareness of any potential compliance risks and a commitment to act with integrity, as the foundation for the Company\u2019s success, reputation and sustainable growth.\nCompany\nAirbus Atlantic\nContract Type\nPermanent\nClasse Emploi (France): Classe G13\nExperience Level\nProfessional\nJob Family\nDigital\nBy submitting your CV or application you are consenting to Airbus using and storing information about you for monitoring purposes relating to your application or future employment. This information will only be used by Airbus.\nAirbus is committed to achieving workforce diversity and creating an inclusive working environment. We welcome all applications irrespective of social and cultural background, age, gender, disability, sexual orientation or religious belief.\nAirbus is, and always has been, committed to equal opportunities for all. As such, we will never ask for any type of monetary exchange in the frame of a recruitment process. Any impersonation of Airbus to do so should be reported to emsom@airbus.com.\nAt Airbus, we support you to work, connect and collaborate more easily and flexibly. Wherever possible, we foster flexible working arrangements to stimulate innovative thinking.\nShow more\nShow less",
        "skills": {
            "ProgLanguage": [
                "Python",
                "Scala",
                "R",
                "Go"
            ],
            "DataBase": [
                "SQL",
                " MongoDB"
            ],
            "DataAnalytics": [
                "R"
            ],
            "BigData": [
                "Databricks"
            ],
            "MachingLearning": [],
            "DataSerialization": [],
            "DataVisualization": [
                "PowerBI"
            ],
            "Statistics": [],
            "CloudComputing": [
                "Azure"
            ],
            "DevTools": [
                "Git"
            ],
            "Os": [],
            "DBMS": [
                "PostgreSQL"
            ],
            "SoftBigDataProcessing": [],
            "Automation": [],
            "InfrastructureAsCode": [],
            "NetworkSecurty": [],
            "Virtualisation": [],
            "Containers": [],
            "Collaboration": [],
            "Other": [
                "ML"
            ],
            "FrSoftSkills": [
                "Collaboration"
            ],
            "EnSoftSkils": [
                "Collaboration",
                "Initiative"
            ]
        },
        "details": {
            "JobDetail": [],
            "TypeContract": [],
            "Salary": [],
            "Level": [],
            "Experience": [
                "a",
                "n",
                "s",
                "5",
                "5",
                "5"
            ]
        }
    },
    {
        "source": "LinkedIn",
        "title": "Architecte Technique BI/Big Data -Nantes",
        "company": "Capgemini",
        "location": "Nantes, Pays de la Loire, France",
        "link": "https://fr.linkedin.com/jobs/view/architecte-technique-bi-big-data-nantes-at-capgemini-3803994992?position=32&pageNum=0&refId=a5rwPua%2FMvx%2F2M%2FPSF0oPA%3D%3D&trackingId=fUq1PzQau5f0BciSOTZc7A%3D%3D&trk=public_jobs_jserp-result_search-card",
        "description": "Capgemini\nChoisir Capgemini, c'est choisir une entreprise o\u00f9 vous serez en mesure de fa\u00e7onner votre carri\u00e8re selon vos aspirations, o\u00f9 vous serez soutenu et inspir\u00e9 par une communaut\u00e9 d\u2019experts dans le monde entier, o\u00f9 vous pourrez r\u00e9\u00e9crire votre futur. Rejoignez-nous pour red\u00e9finir les limites de ce qui est possible, contribuer \u00e0 lib\u00e9rer la valeur de la technologie pour les plus grandes organisations et participez \u00e0 la construction d\u2019un monde plus durable et inclusif.\nVos missions :\nInt\u00e9gr\u00e9(e) au sein d'une \u00e9quipe projets intervenant pour des clients dans des secteurs d'activit\u00e9s vari\u00e9es, vous serez notamment en charge des missions suivantes :\nInteragir avec nos clients, nos partenaires pour concevoir et mettre en \u0153uvre des solutions/projets innovants et comp\u00e9titifs\nR\u00e9pondre aux probl\u00e9matiques de nos clients en proposant la meilleure plateforme data dans un environnement Agile\nAdapter chaque architecture en fonction du contexte gr\u00e2ce \u00e0 votre ma\u00eetrise des caract\u00e9ristiques fondamentales de chaque solution (catalogue des offres de services manag\u00e9s, performance, s\u00e9curit\u00e9, d\u00e9ploiement des data centers \u2026)\nUtiliser les solutions d\u2019int\u00e9gration associ\u00e9es et les solutions d\u00e9cisionnelles ainsi qu\u2019analytiques qui viennent consommer les donn\u00e9es manipul\u00e9es\nEncadrer les \u00e9quipes dans la mise en place des architectures pr\u00e9conis\u00e9es et/ ou des plateformes Data\nVous avez acquis de l\u2019exp\u00e9rience sur les cadres de r\u00e9f\u00e9rence et patterns d\u2019architecture Data, DevOps.\nVotre profil :\nDipl\u00f4me d\u2019ing\u00e9nieur ou \u00e9quivalent universitaire\nMinimum 6 ans d'exp\u00e9rience\nAnglais courant\nExpertise dans la conception d\u2019architecture, la mise en \u0153uvre et/ou le support d\u2019applications hautement distribu\u00e9es\nSensibilisation \u00e0 la m\u00e9thode devops et connaissance d\u2019un outil de de Continuous Integration/Continuous Delivery (CI-CD)\nExpertise sur les services Cloud Data suivants (Azure, AWS, GCP)\nGrande aisance dans la communication orale et \u00e9crite, leadership afin de f\u00e9d\u00e9rer des \u00e9quipes\n3 raisons de nous rejoindre :\nQualit\u00e9 de vie au travail : accord de t\u00e9l\u00e9travail en France et \u00e0 l\u2019international, accord sur l\u2019\u00e9galit\u00e9\nprofessionnelle, la parentalit\u00e9, l\u2019\u00e9quilibre des temps et la mobilit\u00e9 durable.\nApprentissage en continu : certifications et formations en libre acc\u00e8s, accompagnement sur mesure avec votre carreer manager, parcours d\u2019int\u00e9gration sur 9 mois.\nAvantages groupe & CSE : plan actionnariat, activit\u00e9s \u00e0 tarifs pr\u00e9f\u00e9rentiels, remboursement partiel\nvacances, remboursement de votre abonnement sportif ou culturel.\nNos engagements et priorit\u00e9s :\nLe groupe Capgemini encourage une culture inclusive dans un cadre multiculturel et handi-accueillant. En nous rejoignant, vous int\u00e9grez un collectif qui valorise la diversit\u00e9, d\u00e9veloppe le potentiel de ses talents, s\u2019engage dans des initiatives solidaires avec ses partenaires, et se mobilise pour r\u00e9duire son impact environnemental sur tous ses sites et aupr\u00e8s de ses clients.\nCapgemini\nCapgemini est un leader mondial, responsable et multiculturel, regroupant pr\u00e8s de 350 000 personnes dans plus de 50 pays. Fort de 55 ans d\u2019exp\u00e9rience, nous sommes un partenaire strat\u00e9gique des entreprises pour la transformation de leurs activit\u00e9s en tirant profit de toute la puissance de la technologie et des innovations dans les domaines en perp\u00e9tuelle \u00e9volution tels que le cloud, la data, l\u2019Intelligence Artificielle, la connectivit\u00e9, les logiciels, l\u2019ing\u00e9nierie digitale ou les plateformes.\nGet The Future You Want* | www.capgemini.com/fr-fr\n*Capgemini, le futur que vous voulez\nShow more\nShow less",
        "skills": {
            "ProgLanguage": [
                "R"
            ],
            "DataBase": [],
            "DataAnalytics": [
                "R"
            ],
            "BigData": [],
            "MachingLearning": [],
            "DataSerialization": [],
            "DataVisualization": [],
            "Statistics": [],
            "CloudComputing": [
                "AWS",
                "Azure"
            ],
            "DevTools": [
                "Git"
            ],
            "Os": [],
            "DBMS": [],
            "SoftBigDataProcessing": [],
            "Automation": [],
            "InfrastructureAsCode": [],
            "NetworkSecurty": [],
            "Virtualisation": [],
            "Containers": [],
            "Collaboration": [],
            "Other": [
                "DevOps",
                "Cloud"
            ],
            "FrSoftSkills": [
                "Communication",
                "Leadership",
                "Organisation"
            ],
            "EnSoftSkils": [
                "Communication",
                "Leadership",
                "Initiative"
            ]
        },
        "details": {
            "JobDetail": [],
            "TypeContract": [],
            "Salary": [],
            "Level": [],
            "Experience": [
                "a",
                "n",
                "s",
                "6",
                "6",
                "6"
            ]
        }
    },
    {
        "source": "LinkedIn",
        "title": "Architecte / Conseil Data H/F",
        "company": "EXAKIS NELITE",
        "location": "Grenoble, Auvergne-Rh\u00f4ne-Alpes, France",
        "link": "https://fr.linkedin.com/jobs/view/architecte-conseil-data-h-f-at-exakis-nelite-3813458944?position=33&pageNum=0&refId=a5rwPua%2FMvx%2F2M%2FPSF0oPA%3D%3D&trackingId=hL5G3DbYXckmlMW9KGBYrA%3D%3D&trk=public_jobs_jserp-result_search-card",
        "description": "Exakis Nelite, entit\u00e9 du groupe\nMagellan Partners\n, est le\n1er partenaire pure-player Microsoft\nind\u00e9pendant en France avec l\u2019ambition de devenir le premier partenaire Europ\u00e9en et en Afrique Francophone avec sa forte pr\u00e9sence au Maroc.\nN\u00e9s du rapprochement de 2 leaders sp\u00e9cialistes de l\u2019int\u00e9gration des solutions Microsoft, nous allions expertise technique et fonctionnelle pour r\u00e9pondre concr\u00e8tement aux enjeux de demain : acc\u00e9l\u00e9ration de la transformation digitale,\nCyberS\u00e9curit\u00e9, Intelligence Artificielle, IoT, Data, transformation vers le cloud Azure, Services Cognitifs \u2026\nEn rejoignant la communaut\u00e9 Exakis Nelite dans l\u2019une de nos 12 agences (680 collaborateurs), vous int\u00e9grerez une \u00e9quipe passionn\u00e9e et impliqu\u00e9e dans les projets les plus innovants. Vous rejoindrez une structure construite autour de valeurs tourn\u00e9es vers ses collaborateurs : intelligence collective, convivialit\u00e9 et bienveillance.\nExakis Nelite a re\u00e7u la certification\nGreat Place to Work\net se place\n3\u00e8me de sa cat\u00e9gorie\nen 2024 parmi les entreprises o\u00f9 il fait bon travailler en France !\n\u00c0 quoi ressembleront vos futures missions ?\nEn tant qu\u2019Architecte et Conseil, dans les domaines Data et Business Intelligence, vous serez amen\u00e9 \u00e0 travailler sur des projets d\u2019envergure mettant \u00e0 l\u2019\u00e9preuve votre exp\u00e9rience des syst\u00e8mes de donn\u00e9es et votre ouverture vers les technologies de BI moderne et cloud.\nVotre r\u00f4le d\u2019architecte et de conseil aupr\u00e8s de nos clients trouvera son sens dans la comp\u00e9tence que pourrez apporter autour des solutions Microsoft (Power BI, Azure\u2026), et aussi dans la connaissance globale que vous aurez acquise par vos exp\u00e9riences vari\u00e9es. Cette combinaison comp\u00e9tence/exp\u00e9rience aura pour but d\u2019orchestrer l\u2019impl\u00e9mentation des technologies Microsoft dans des syst\u00e8mes d\u2019information et d\u00e9cisionnels technologiquement h\u00e9t\u00e9rog\u00e8nes.\nVotre passion, votre curiosit\u00e9 et votre envie sont les ma\u00eetres mots pour r\u00e9ussir dans ce poste. Vous \u00eates motiv\u00e9 pour travailler dans un environnement dynamique o\u00f9 la donn\u00e9e se d\u00e9cline autour de nos projets innovants (IoT, Industrie 4.0, IA\u2026). Vous avez une vision claire des enjeux actuels autour de la donn\u00e9e.\nDescription du poste\nSelon les missions vous serez amen\u00e9 \u00e0 :\nAccompagner nos clients dans leur strat\u00e9gie digitale\nAnimer des ateliers d\u2019architecture technique\nAppr\u00e9hender les besoins fonctionnels et les contraintes techniques du client\nPr\u00e9coniser des architectures complexes pour r\u00e9pondre \u00e0 une probl\u00e9matique ou un besoin m\u00e9tier\nD\u00e9finir et am\u00e9liorer les standards, patterns d\u2019architecture et le catalogue de services\nSuperviser et mettre en \u0153uvre, dans le cadre des projets, les pr\u00e9conisations techniques \u00e9tablies dans le cadre des cahiers des charges\nR\u00e9aliser l\u2019architecture de donn\u00e9es dans des environnements on Premise\nIntervenir sur l\u2019architecture Azure data\nR\u00e9diger les documents associ\u00e9s (HLD, LLD, etc.)\nPiloter des projets et des hommes\nIntervenir en toute autonomie sur les phases de cadrage technique et/ou avant ventes\nAssurer une veille technologique\nProfil\nFort d\u2019une exp\u00e9rience de 3 \u00e0 15 ans dans les domaines, Data, BI et Big Data, vous portez de l\u2019int\u00e9r\u00eat aux technologies du Cloud, aux approches de BI moderne et \u00e0 leur d\u00e9veloppement. Vous \u00eates un professionnel aguerri des environnements Data, de l\u2019architecture et de l\u2019utilisation des technologies Cloud.\nLa connaissance des environnements Microsoft (Power BI, SQL Server, Azure\u2026) est un plus mais n\u2019est pas une obligation. La diversit\u00e9 de vos exp\u00e9riences dans le champ d\u2019activit\u00e9 Data/BI est le facteur clef de succ\u00e8s de ce poste.\nCurieux et dynamique, vous avez le gout du challenge et souhaitez prendre part au d\u00e9veloppement important d\u2019Exakis Nelite et de Magellan Partners dans le domaine des Data-sciences.\nShow more\nShow less",
        "skills": {
            "ProgLanguage": [
                "R",
                "Go"
            ],
            "DataBase": [
                "SQL"
            ],
            "DataAnalytics": [
                "R"
            ],
            "BigData": [],
            "MachingLearning": [],
            "DataSerialization": [],
            "DataVisualization": [
                "Power BI"
            ],
            "Statistics": [],
            "CloudComputing": [
                "Azure"
            ],
            "DevTools": [
                "Git"
            ],
            "Os": [],
            "DBMS": [
                "SQL Server"
            ],
            "SoftBigDataProcessing": [],
            "Automation": [],
            "InfrastructureAsCode": [],
            "NetworkSecurty": [],
            "Virtualisation": [],
            "Containers": [],
            "Collaboration": [],
            "Other": [
                "Big Data",
                "Cloud"
            ],
            "FrSoftSkills": [],
            "EnSoftSkils": []
        },
        "details": {
            "JobDetail": [],
            "TypeContract": [],
            "Salary": [],
            "Level": [],
            "Experience": [
                "a",
                "n",
                "s",
                "15",
                "15",
                "15"
            ]
        }
    },
    {
        "source": "LinkedIn",
        "title": "DATA / ARCHITECT Manager",
        "company": "SIBIOS",
        "location": "Lyon, Auvergne-Rh\u00f4ne-Alpes, France",
        "link": "https://fr.linkedin.com/jobs/view/data-architect-manager-at-sibios-3881612188?position=34&pageNum=0&refId=a5rwPua%2FMvx%2F2M%2FPSF0oPA%3D%3D&trackingId=BeZElBp3vNJZRE6yKafYDg%3D%3D&trk=public_jobs_jserp-result_search-card",
        "description": "SIBIOS recherche un consultant Senior DATA / ARCHITECT Manager avec minium 10 ans d'exp\u00e9rience pour un nouveau projet dans le secteur industriel.\nUne bonne connaissance d'architecture fonctionnelle et l'urbanisation data, ainsi que des r\u00e8gles de s\u00e9curit\u00e9.\nVous avez une ma\u00eetrise de la gestion des donn\u00e9es et des outils/langages correspondants (SQL, Power BI, mod\u00e9lisation et visualisation des donn\u00e9es, ...)\nDiriger des projets Data sur divers domaines fonctionnels (M\u00e9tier et IT) pour d\u00e9finir les feuilles de route.\nD\u00e9finir la gouvernance de chaque projet et suivre le planning, le budget, la qualit\u00e9 et les risques sur chaque projet\nPiloter la gestion du changement et communiquer autour des projets\nIndustrialisation des innovations digitales : gouvernance, socle technique, documentation et support\nPour un entretien imm\u00e9diat, merci de nous faire suivre votre cv mis \u00e1 jour en word format ainsi que votre date de disponibilit\u00e9 et TJM.\nShow more\nShow less",
        "skills": {
            "ProgLanguage": [
                "R",
                "Go"
            ],
            "DataBase": [
                "SQL"
            ],
            "DataAnalytics": [
                "R"
            ],
            "BigData": [],
            "MachingLearning": [],
            "DataSerialization": [],
            "DataVisualization": [
                "Power BI"
            ],
            "Statistics": [],
            "CloudComputing": [],
            "DevTools": [
                "Git"
            ],
            "Os": [],
            "DBMS": [],
            "SoftBigDataProcessing": [],
            "Automation": [],
            "InfrastructureAsCode": [],
            "NetworkSecurty": [],
            "Virtualisation": [],
            "Containers": [],
            "Collaboration": [],
            "Other": [],
            "FrSoftSkills": [],
            "EnSoftSkils": []
        },
        "details": {
            "JobDetail": [
                "Senior"
            ],
            "TypeContract": [],
            "Salary": [],
            "Level": [],
            "Experience": [
                "a",
                "n",
                "s",
                "10",
                "10",
                "10"
            ]
        }
    },
    {
        "source": "LinkedIn",
        "title": "AWS Full Stack Solution Architect",
        "company": "Darwin Recruitment",
        "location": "Paris, \u00cele-de-France, France",
        "link": "https://fr.linkedin.com/jobs/view/aws-full-stack-solution-architect-at-darwin-recruitment-3918853578?position=35&pageNum=0&refId=a5rwPua%2FMvx%2F2M%2FPSF0oPA%3D%3D&trackingId=VNRlrafCbgn7Z%2FzxGie1uQ%3D%3D&trk=public_jobs_jserp-result_search-card",
        "description": "Data Cloud Full Stack Solution Architect - 9 Months + extensions\nJob:\nData Cloud Full Stack Solution Architect\nClient Location:\nParis, France\nHybrid structure:\n3 days per week onsite with 2 days remote.\nContract Length:\n9 months + possibility for extensions\nRole and responsibilities:\nAs part of a significant Data Transformation initiative encompassing our entire spectrum of data capabilities-from Data Architecture and Engineering to Data Modelling, Storage for Data & Analytics, Data Visualization, Data Science, Data Integration, Metadata Management, and Data Storage and Warehousing-this role will support the future technical architecture activities of our Data Foundation platform. Key responsibilities include:\nProviding technical guidance and establishing best practices for Snowflake account setup and configuration.\nManaging Infrastructure-as-code to maximize automation and efficiency.\nOverseeing enhancements and deployments to bolster a fully federated Platform.\nServing as the Subject Matter Expert (SME) for all Snowflake-related queries on the project.\nMaintaining platform-specific Snowflake documentation, including decisions, best practices, and features.\nCommunicating and demonstrating new features to relevant stakeholders.\nDesigning the cloud environment comprehensively to ensure alignment with functional and non-functional requirements.\nConducting deployment, maintenance, monitoring, and management tasks.\nOverseeing cloud security for the account.\nFacilitating the integration of new applications into the cloud environment.\nRequirements:\nEducation: Completion of higher education with a degree in Computer Sciences or related field.\nExperience: 5 to 10 years of experience, including a proven track record in implementing Data Platforms in a cloud environment.\nSkills:\nFluency in both French and English (mandatory).\nDeep expertise in Snowflake.\nStrong understanding of platform architecture.\nExperience as a Database Administrator (DBA) and Cloud Database Administrator.\nProficiency in AWS Architecture and cloud networking.\nExcellent communication, coordination, collaboration, stakeholder management, and risk management skills, coupled with strong leadership abilities.\nOpen-mindedness and willingness to tackle challenges.\nHigh motivation, adaptability, and flexibility, with a readiness to integrate into existing environments and project teams.\nIf this role is of interest, please send an up to date CV to\ntaylor.lewis@darwinrecruitment.com\nDarwin Recruitment AG is a Zurich based, SECO licensed, privately owned subsidiary of Darwin Professional Staffing Group Ltd (a Global IT Recruitment Consultancy).\nDarwin Recruitment AG manages client relationships whilst also utilising Darwin Professional Staffing Group databases and networks to source Candidates and fulfil client requests.\nWe do not ask for a placement fee from Candidates/Employees.\nIf you wish to contact a specialist regarding this role, or your job search in general, please contact +41 (0)43 456 29 09\nShow more\nShow less",
        "skills": {
            "ProgLanguage": [
                "R"
            ],
            "DataBase": [],
            "DataAnalytics": [
                "R"
            ],
            "BigData": [],
            "MachingLearning": [],
            "DataSerialization": [],
            "DataVisualization": [],
            "Statistics": [],
            "CloudComputing": [
                "AWS"
            ],
            "DevTools": [],
            "Os": [],
            "DBMS": [
                "Snowflake",
                "Snowflake"
            ],
            "SoftBigDataProcessing": [],
            "Automation": [],
            "InfrastructureAsCode": [],
            "NetworkSecurty": [],
            "Virtualisation": [],
            "Containers": [],
            "Collaboration": [
                "Teams"
            ],
            "Other": [
                "Cloud"
            ],
            "FrSoftSkills": [
                "Communication",
                "Leadership",
                "Collaboration"
            ],
            "EnSoftSkils": [
                "Communication",
                "Adaptability",
                "Leadership",
                "Collaboration",
                "Flexibility",
                "Initiative"
            ]
        },
        "details": {
            "JobDetail": [
                "Remote",
                "Full"
            ],
            "TypeContract": [],
            "Salary": [],
            "Level": [],
            "Experience": [
                "a",
                "n",
                "s"
            ]
        }
    },
    {
        "source": "LinkedIn",
        "title": "Architecte Data",
        "company": "Sibylone",
        "location": "Paris, \u00cele-de-France, France",
        "link": "https://fr.linkedin.com/jobs/view/architecte-data-at-sibylone-3888828561?position=36&pageNum=0&refId=a5rwPua%2FMvx%2F2M%2FPSF0oPA%3D%3D&trackingId=2yYnTKdQk5RoeQD6oXhgJw%3D%3D&trk=public_jobs_jserp-result_search-card",
        "description": "SIBYLONE, soci\u00e9t\u00e9 de conseil sp\u00e9cialis\u00e9e dans les syst\u00e8mes d\u2019information de synth\u00e8se et de pilotage, aide ses clients \u00e0 tirer toute la valeur de leur patrimoine de donn\u00e9es, levier strat\u00e9gique majeur de d\u00e9veloppement et de rentabilit\u00e9.\nNotre ambition : rendre les diff\u00e9rents acteurs de l\u2019entreprise autonomes dans l\u2019exploitation des donn\u00e9es, lib\u00e9rer les usages M\u00e9tier, pour qu\u2019ils soient en mesure de relever les d\u00e9fis de performance, de couverture de risque, de financement, de conqu\u00eate client, de RSE\u2026 qui s\u2019imposent \u00e0 eux.\nSp\u00e9cialistes reconnus, nos consultants s\u2019appuient pour cela sur une connaissance approfondie de l\u2019activit\u00e9 business de nos clients, en lien avec nos trois piliers que sont le M\u00e9tier, la Data et le Projet.\nVos missions\nR\u00e9aliser\nles \u00e9tudes de faisabilit\u00e9 technique et proposer une\nmigration vers le Cloud.\nAssister et conseiller\nles \u00e9quipes dans les diff\u00e9rentes \u00e9tapes des projets\nPrendre en charge\nles instructions d\u2019\u00e9tudes techniques (r\u00e9alisation des livrables correspondant, coordination des contributeurs techniques)\nConstruire\nl\u2019architecture technique et de s\u00e9curit\u00e9 des applications concern\u00e9s\nD\u00e9finir et concevoir\nles architectures techniques des projets m\u00e9tiers\nGarantir\nl\u2019exploitabilit\u00e9, l\u2019\u00e9volutivit\u00e9 et la performance des architectures propos\u00e9es\nCollaborer et animer\nla communaut\u00e9 d\u2019experts techniques pour d\u00e9finir les bonnes pratiques d\u2019architecture et d\u2019exploitabilit\u00e9 des solutions\nDocumenter et partager\nles modes op\u00e9ratoires suite aux migrations effectu\u00e9es.\nR\u00e9diger et pr\u00e9senter\nles dossiers d\u2019architecture devant les diff\u00e9rents comit\u00e9s de validation\nR\u00e9aliser la veille technologique\nsur les outils et pratiques de d\u00e9veloppement\nAssurer\nla coh\u00e9rence et l\u2019industrialisation du SI\nOptimiser\nle design de l\u2019architecture et le dimensionnement des infrastructures en fonction des \u00e9volutions des besoins\nVous \u00e9voluerez dans un environnement technique n\u00e9cessitant une\nbonne ma\u00eetrise des architectures n-tiers, des probl\u00e9matiques li\u00e9es au Cloud, des API (Management, REST) et webservices.\nPourquoi pas vous ?\nFormation sup\u00e9rieure Bac +5 en informatique\nExp\u00e9rience r\u00e9ussie de migration de workflow on premise vers le Cloud.\nConnaissances techniques dans certains des domaines suivants : design de blueprint Cloud, architecture de bases de donn\u00e9es, technologies Big Data Analytics, Machine Learning, virtualisation, architecture de stockage, s\u00e9curit\u00e9.\nPremi\u00e8re bonne exp\u00e9rience r\u00e9ussie dans un ou des projets de transformation et de transitions vers le Cloud.\nExp\u00e9rience > 6 ans en conception d\u2019applications au sens large\nUne exp\u00e9rience dans un environnement agile est un plus\nLes + Sibylone !\nEvoluer au sein d\u2019une soci\u00e9t\u00e9 qui exige le meilleur de ses collaborateurs tout en cultivant la coh\u00e9sion et l\u2019esprit d\u2019\u00e9quipe !\nS\u2019engager dans une politique RSE exigeante : labellisation Ecovadis\nAvoir un Partenariat EcoTree France : 1 recrutement = 1 arbre plant\u00e9 !\nUn Lab RSE ouvert \u00e0 tous, pour am\u00e9liorer la qualit\u00e9 de vie au travail des collaborateurs et nos engagements environnementaux au sein de SIBYLONE\nContribuer activement au bien-\u00eatre de ses collaborateurs : participation aux frais d\u2019abonnements activit\u00e9s ou achat 2 roues\nAvoir de nombreux moments de convivialit\u00e9s : s\u00e9minaires, afterworks, conf\u00e9rences et petits d\u00e9jeuners, sports en groupe via l\u2019application Gymlib\nLes actions et missions solidaires : notre partenariat avec la start-up sp\u00e9cialis\u00e9e en RSE Vendredi permet \u00e0 nos collaborateurs de r\u00e9aliser des missions aupr\u00e8s d\u2019associations\nDonner une offre de formation innovante et \u00e0 la pointe des nouvelles technologies\nAccord de t\u00e9l\u00e9travail en vigueur\nVous vous reconnaissez dans la description du poste ?\nVous souhaitez travailler dans un environnement stimulant et dynamique ?\nVous souhaitez rejoindre une soci\u00e9t\u00e9 ambitieuse ?\nVous souhaitez comprendre l\u2019origine de Sibylone ?\nVenez-nous rencontrer : Notre Team Talent Acquisition\nsera ravie d\u2019\u00e9changer avec vous !\nCe poste est ouvert aux personnes en situation de handicap.\nShow more\nShow less",
        "skills": {
            "ProgLanguage": [
                "R"
            ],
            "DataBase": [],
            "DataAnalytics": [
                "R"
            ],
            "BigData": [],
            "MachingLearning": [],
            "DataSerialization": [],
            "DataVisualization": [],
            "Statistics": [],
            "CloudComputing": [],
            "DevTools": [],
            "Os": [],
            "DBMS": [],
            "SoftBigDataProcessing": [],
            "Automation": [],
            "InfrastructureAsCode": [],
            "NetworkSecurty": [],
            "Virtualisation": [],
            "Containers": [],
            "Collaboration": [],
            "Other": [
                "Big Data",
                "ML",
                "Machine Learning",
                "Cloud"
            ],
            "FrSoftSkills": [],
            "EnSoftSkils": []
        },
        "details": {
            "JobDetail": [],
            "TypeContract": [],
            "Salary": [],
            "Level": [],
            "Experience": [
                "a",
                "n",
                "s",
                "6",
                "6",
                "6"
            ]
        }
    },
    {
        "source": "LinkedIn",
        "title": "Airbus Atlantic - Architecte Data (All Gender)",
        "company": "Airbus",
        "location": "Toulouse, Occitanie, France",
        "link": "https://fr.linkedin.com/jobs/view/airbus-atlantic-architecte-data-all-gender-at-airbus-3916426276?position=37&pageNum=0&refId=a5rwPua%2FMvx%2F2M%2FPSF0oPA%3D%3D&trackingId=qkxCD4D6DkGDb8EneBG3mw%3D%3D&trk=public_jobs_jserp-result_search-card",
        "description": "Job Description\nEt si VOTRE aventure avec NOUS commen\u00e7ait ?!\nNous vous proposons de travailler chez Airbus Atlantic, nouveau champion de dimension mondiale, n\u00b02 des a\u00e9rostructures, n\u00b01 des si\u00e8ges pilotes et dans le Top 3 des fauteuils passagers Premium.\nNotre site Airbus Atlantic bas\u00e9\n\u00e0 Toulouse (possibilit\u00e9 de travailler \u00e0 Montoir de Bretagne)\nrecherche son futur\nArchitecte Data (All Gender)\nLe poste d\u2019architecte Data est rattach\u00e9 au domaine \u00ab Architecture \u00bb au sein du d\u00e9partement \u00ab Architecture Digital & S\u00e9curit\u00e9 \u00bb.\nVous serez en interface avec les architectes du Syst\u00e8me d'Information et les diff\u00e9rents m\u00e9tiers consommateurs des architectures.\nVos Principales Missions Seront Les Suivantes\nFixer les orientations et d\u00e9finir des politiques concernant la mod\u00e9lisation des donn\u00e9es, en collaboration avec les autres architectes,\nCr\u00e9er des mod\u00e8les de donn\u00e9es logiques et physiques en utilisant les meilleures pratiques pour garantir une qualit\u00e9 \u00e9lev\u00e9e des donn\u00e9es et une r\u00e9duction de leur redondance,\nInstancier, impl\u00e9menter, construire, tester et maintenir les architectures data d\u00e9finies\nAnalyser, \u00e9valuer, tester et recommander les briques technologiques n\u00e9cessaires pour l\u2019acquisition, l\u2019analyse et l\u2019impl\u00e9mentation des donn\u00e9es,\nAnalyser les probl\u00e8mes d'int\u00e9gration des syst\u00e8mes li\u00e9s aux donn\u00e9es et proposer des solutions appropri\u00e9es,\nD\u00e9terminer les \u00ab Data set process \u00bb c\u2019est \u00e0 dire comment les donn\u00e9es sont int\u00e9gr\u00e9es et transform\u00e9es pour qu\u2019elles soient pr\u00eates \u00e0 \u00eatre analys\u00e9es (ex : ETL)\nParticiper aux processus d'extraction performants et qualitatifs des donn\u00e9es des sources requises afin de r\u00e9pondre aux besoins de l'entreprise\nMaintenir les mod\u00e8les de donn\u00e9es conceptuels, logiques et physiques ainsi que les m\u00e9tadonn\u00e9es correspondantes (pour la data gouvernance).\nD\u00e9velopper les meilleures pratiques pour les conventions de d\u00e9nomination standard et les pratiques de codage afin d'assurer la coh\u00e9rence des mod\u00e8les de donn\u00e9es,\nRespecter les normes de s\u00e9curit\u00e9 des donn\u00e9es, de contr\u00f4le des exportations et de protection des donn\u00e9es.\nConstruire les pipelines qui permettront aux Data Scientist/Analysts/Developers de mettre leurs mod\u00e8les en production\nEtre garant de la fiabilit\u00e9, de la qualit\u00e9 et de l\u2019efficacit\u00e9 du traitement des donn\u00e9es\nMaintenir les mod\u00e8les cr\u00e9\u00e9s.\nParticiper aux id\u00e9ations et proposer des innovations aux services.\nDocumenter ses activit\u00e9s et mettre \u00e0 jour le r\u00e9f\u00e9rentiel documentaire.\nParlons de vous !\nVous disposez d'une\ne\nxp\n\u00e9rience de minimum 5 ans en Data & Informatique sur un poste similaire.\nLes comp\u00e9tences techniques \u00e0 d\u00e9tenir pour le poste :\nL\u2019optimisation et les standards Qualit\u00e9 des donn\u00e9es informatiques\nComprendre et savoir mettre en place les diff\u00e9rentes Structure et stockage de donn\u00e9es\nGestion des probl\u00e8mes li\u00e9 \u00e0 la donn\u00e9e, l'architecture\nId\u00e9alement, l'exp\u00e9rience des technologies suivantes serait un plus : Ressources & services data MS Azure (Databricks, Azure ML \u2026), SGBD (SQL, MongoDB, PostGreSQL, redis), Outils ETL (Qlik replicate, Alteryx, \u2026), Outils BI (PowerBI, Qlik, Grafana ...),\nLangages de programmation (python, SCALA, R, DAX)\nLes certifications de Azure (DP-203, AZ-300, AZ-303, AZ-304, AZ-400, AI-900) seraient un plus,\nVotre Personnalit\u00e9\nFort volont\u00e9 de travailler en \u00e9quipe\nBonnes habitudes de documentation\nNiveau avanc\u00e9 en Fran\u00e7ais et en Anglais (niveau minimum B1)\nFaire preuve d\u2019innovation et \u00eatre source de proposition\nSavoir exprimer ses id\u00e9es de mani\u00e8re claire et concise\nEtre \u00e0 l'\u00e9coute\nParlons de nous !\nEnvironnement & Conditions De Travail\nAirbus Atlantic c\u2019est aussi :\nPrendre part \u00e0 des projets ambitieux, \u00e0 la pointe de la technologie pour construire l\u2019avion de demain, en lien avec les enjeux environnementaux.\nUn environnement qui valorise la proximit\u00e9 et la dimension humaine, au sein d\u2019un collectif engag\u00e9 et solidaire.\nL\u2019opportunit\u00e9 d\u2019apprendre et d\u2019\u00e9voluer tout au long de votre parcours, en \u00e9tant accompagn\u00e9 dans votre d\u00e9veloppement pour une carri\u00e8re sur-mesure.\nAvoir la libert\u00e9 d\u2019entreprendre et de laisser libre court \u00e0 vos initiatives.\nSes conditions de travail attractives et ses avantages : restaurant d\u2019entreprise sur site, CSE (avantages loisirs & famille), parking entreprise, mutuelle d\u2019entreprise (famille).\nSa politique de diversit\u00e9 et d'inclusion : Airbus Atlantic s\u2019engage en faveur de l\u2019\u00e9galit\u00e9 des chances pour tous.\nSon plan d'actionnariat salari\u00e9 et son plan d\u2019\u00e9pargne salariale.\nNotre Processus De Recrutement\nNous avons \u00e0 c\u0153ur de mieux vous conna\u00eetre et de comprendre ce qui vous motive \u00e0 nous rejoindre. Aussi, notre process de recrutement se d\u00e9roule en plusieurs \u00e9tapes apr\u00e8s analyse de votre candidature :\nEntretien vid\u00e9o diff\u00e9r\u00e9 via la plateforme Hirevue\nEntretien avec le Manager Recruteur\nEntretien avec le/la Charg\u00e9(e) de Recrutement qui peut \u00eatre compl\u00e9t\u00e9 par un questionnaire de personnalit\u00e9\nEntretien avec le/la Human Resources Business Partner.\nThis job requires an awareness of any potential compliance risks and a commitment to act with integrity, as the foundation for the Company\u2019s success, reputation and sustainable growth.\nCompany\nAirbus Atlantic\nContract Type\nPermanent\nClasse Emploi (France): Classe G13\nExperience Level\nProfessional\nJob Family\nDigital\nBy submitting your CV or application you are consenting to Airbus using and storing information about you for monitoring purposes relating to your application or future employment. This information will only be used by Airbus.\nAirbus is committed to achieving workforce diversity and creating an inclusive working environment. We welcome all applications irrespective of social and cultural background, age, gender, disability, sexual orientation or religious belief.\nAirbus is, and always has been, committed to equal opportunities for all. As such, we will never ask for any type of monetary exchange in the frame of a recruitment process. Any impersonation of Airbus to do so should be reported to emsom@airbus.com.\nAt Airbus, we support you to work, connect and collaborate more easily and flexibly. Wherever possible, we foster flexible working arrangements to stimulate innovative thinking.\nShow more\nShow less",
        "skills": {
            "ProgLanguage": [
                "Python",
                "Scala",
                "R",
                "Go"
            ],
            "DataBase": [
                "SQL",
                " MongoDB"
            ],
            "DataAnalytics": [
                "R"
            ],
            "BigData": [
                "Databricks"
            ],
            "MachingLearning": [],
            "DataSerialization": [],
            "DataVisualization": [
                "PowerBI"
            ],
            "Statistics": [],
            "CloudComputing": [
                "Azure"
            ],
            "DevTools": [
                "Git"
            ],
            "Os": [],
            "DBMS": [
                "PostgreSQL"
            ],
            "SoftBigDataProcessing": [],
            "Automation": [],
            "InfrastructureAsCode": [],
            "NetworkSecurty": [],
            "Virtualisation": [],
            "Containers": [],
            "Collaboration": [],
            "Other": [
                "ML"
            ],
            "FrSoftSkills": [
                "Collaboration"
            ],
            "EnSoftSkils": [
                "Collaboration",
                "Initiative"
            ]
        },
        "details": {
            "JobDetail": [],
            "TypeContract": [],
            "Salary": [],
            "Level": [],
            "Experience": [
                "a",
                "n",
                "s",
                "5",
                "5",
                "5"
            ]
        }
    },
    {
        "source": "LinkedIn",
        "title": "Lead Data Architect - H/F",
        "company": "E.Leclerc",
        "location": "Ivry-sur-Seine, \u00cele-de-France, France",
        "link": "https://fr.linkedin.com/jobs/view/lead-data-architect-h-f-at-e-leclerc-3688059702?position=38&pageNum=0&refId=a5rwPua%2FMvx%2F2M%2FPSF0oPA%3D%3D&trackingId=m6aEKnUwuFaLecnTTcpZRA%3D%3D&trk=public_jobs_jserp-result_search-card",
        "description": "Description\nAu sein de la Direction Support et Organisation, la DSI est compos\u00e9e de 5 services :\nService Solutions Finance & Qualit\u00e9,\nService Solutions Client,\nService Solutions Offre,\nService Support Utilisateurs,\nService TECH,\nLe Service TECH a Pour Mission\nD\u2019animer les constructions strat\u00e9giques SI et technologies,\nD\u2019explorer et d\u2019innover en technologie,\nDe fournir et d\u2019op\u00e9rer des infrastructures s\u00e9curis\u00e9es,\nD\u2019apporter de l\u2019expertise aux d\u00e9veloppeurs,\nD\u2019op\u00e9rer la s\u00e9curit\u00e9,\nNous recherchons pour le Service Tech un(e) Lead Data Architect.\nLe Lead Data Architect est responsable de la conception et de la gestion de l'architecture des donn\u00e9es sur la plateforme GCP. Son r\u00f4le consiste \u00e0 d\u00e9finir l'architecture des donn\u00e9es, \u00e0 \u00e9tablir les normes, standards et les bonnes pratiques de d\u00e9veloppement des traitements de donn\u00e9es. Il/elle collabore aussi \u00e9troitement avec les \u00e9quipes de Data Architects et de Data Engineers de l\u2019int\u00e9grateur ainsi qu\u2019avec les architectes Cloud GCP afin de s\u2019assurer que les solutions de traitement des donn\u00e9es mises en place sur la plateforme soient robustes, scalables et s\u00e9curis\u00e9es. Enfin, il/elle encadre fonctionnellement une \u00e9quipe interne constitu\u00e9e d\u2019un Data Architect et de deux Data Engineers.\nRattach\u00e9(e) au Responsable D\u00e9veloppement, vos responsabilit\u00e9s sont les suivantes :\nConception de l'architecture des donn\u00e9es : D\u00e9finir l'architecture des donn\u00e9es et des traitements de donn\u00e9es en tenant compte des besoins fonctionnels et non fonctionnels, des exigences de performance, de scalabilit\u00e9, de s\u00e9curit\u00e9 et de conformit\u00e9. Concevoir des mod\u00e8les et des pipelines de donn\u00e9es en s\u2019appuyant sur DBT ;\nS\u00e9lection et configuration des services GCP : \u00c9valuer et s\u00e9lectionner les services et les outils de GCP tels que BigQuery, Cloud Storage, Composer, Pub/Sub, etc. les mieux adapt\u00e9s aux besoins de chaque usage m\u00e9tier.\nGestion des donn\u00e9es : Concevoir les solutions pour la gestion des donn\u00e9es en streaming et en batch. \u00c9tablir et maintenir les normes, les standards et les bonnes pratiques de d\u00e9veloppement en s\u2019appuyant sur l\u2019int\u00e9grateur. Contribuer \u00e0 la mise en place et \u00e0 la maintenance des pipelines de donn\u00e9es pour la collecte, le traitement et l'analyse des donn\u00e9es. Assister et supporter les Data Engineers dans cette t\u00e2che ;\nS\u00e9curit\u00e9 et gouvernance des donn\u00e9es : D\u00e9finir des m\u00e9canismes de s\u00e9curit\u00e9 et de gouvernance des donn\u00e9es sur GCP pour garantir la confidentialit\u00e9, l'int\u00e9grit\u00e9 et la conformit\u00e9 r\u00e9glementaire (RGPD). D\u00e9finir les contr\u00f4les d'acc\u00e8s, les politiques de s\u00e9curit\u00e9 des donn\u00e9es et les m\u00e9canismes de tra\u00e7abilit\u00e9 \u00e0 mettre en \u0153uvre ;\nIndustrialisation et d\u00e9ploiement : Mettre en place des pipelines CI/CD pour automatiser le d\u00e9ploiement, les tests, et la gestion des d\u00e9veloppements. Automatiser la cr\u00e9ation et la configuration des ressources sur GCP n\u00e9cessaires en utilisant l\u2019IaC/Terraform pour d\u00e9finir et g\u00e9rer l'infrastructure de mani\u00e8re programmable et reproductible ;\nCollaboration avec les \u00e9quipes : Travailler en \u00e9troite collaboration avec les \u00e9quipes de l\u2019int\u00e9grateur (Data Architects et Data Engineers), les squads big data pour proposer les solutions techniques adapt\u00e9es aux besoins des m\u00e9tiers et assurer la mise en \u0153uvre r\u00e9ussie des projets data sur GCP ;\nVeille technologique : Rester \u00e0 jour sur les derni\u00e8res avanc\u00e9es technologiques et les tendances du march\u00e9 sur GCP et autres. \u00c9valuer et recommander de nouvelles solutions ou des am\u00e9liorations aux solutions existantes.\nProfil\nVous \u00eates issu(e) de formation sup\u00e9rieure en statistiques/marketing/informatique et vous justifiez d'une exp\u00e9rience significative en tant que data architect sur Google Cloud Platform (GCP). Vous avez de solides comp\u00e9tences en conception de pipelines de donn\u00e9es et en mod\u00e9lisation de bases de donn\u00e9es structur\u00e9es et non structur\u00e9es. Vous avez une connaissance approfondie des services GCP, tels que BigQuery, Cloud Storage, Cloud Composer, Pub/Sub, etc et des frameworks de d\u00e9veloppement tels que DBT.\nVous avez une exp\u00e9rience pratique en DevOps, CI/CD, avec une bonne compr\u00e9hension des principes et des pratiques de g\u00e9nie logiciel (Azure DevOps, Jenkins, GitLab,..). Vous avez une connaissance de l'IaC (Infrastructure as Code) et utilisation d'outils tels que Terraform. Vous avez une compr\u00e9hension des r\u00e9glementations relatives \u00e0 la protection des donn\u00e9es et de la confidentialit\u00e9, telles que le RGPD.\nVous avez une exp\u00e9rience en encadrement d\u2019\u00e9quipes techniques.\nDot\u00e9(e) d'une grande aisance relationnelle, vous avez le sens de l'\u00e9coute et de la diplomatie. Vous \u00eates rigoureux(se), vous avez un bon sens relationnel, une bonne capacit\u00e9 de communication et r\u00e9dactionnelle.\nEnfin, vous avez une capacit\u00e9 \u00e0 vous maintenir \u00e0 jour sur les technologies data.\nNous recherchons des personnalit\u00e9s dynamiques, sachant prendre des initiatives et qui souhaitent s\u2019impliquer dans les \u00e9volutions de notre secteur et du mouvement. Il est important que nos candidats d\u00e9montrent un r\u00e9el engagement, des valeurs communes aux valeurs fortes port\u00e9es par le mouvement Leclerc depuis sa fondation.\nEn rejoignant le Galec, vous pourrez valoriser et d\u00e9montrer votre potentiel, d\u00e9velopper vos comp\u00e9tences et acqu\u00e9rir une exp\u00e9rience enrichissante, \u00e0 travers des passerelles entre les diff\u00e9rents march\u00e9s et entit\u00e9s du Mouvement !\nEnvie de challenge ? Vous souhaitez tenter l'aventure dans un univers dynamique, enrichissant, au plus pr\u00e8s des entrepreneurs ?\nMieux nous connaitre\nLe Mouvement E.LECLERC est un groupement coop\u00e9ratif dont les adh\u00e9rents sont les propri\u00e9taires de magasins, soit 592 entrepreneurs, dont Michel-Edouard Leclerc est le porte-parole. Le Mouvement E.leclerc compte 133 000 collaborateurs, qui travaillent collectivement \u00e0 la r\u00e9ussite de nos 721 magasins (hypers, supers et express), 690 Drives et 2 541 enseignes sp\u00e9cialis\u00e9es.\nLe Galec est l'entit\u00e9 au c\u0153ur du syst\u00e8me, c'est m\u00eame le r\u00e9acteur ! Le Galec conjugue les talents d\u2019une \u00e9quipe de plus de 824 collaborateurs qui travaillent ensemble au service du front de vente omnicanal de l\u2019Enseigne, c\u2019est-\u00e0-dire les hyper/supermarch\u00e9s, les magasins sp\u00e9cialis\u00e9s, le drive, le site marchand E.Leclerc et E.Leclerc relais.\nShow more\nShow less",
        "skills": {
            "ProgLanguage": [
                "Scala",
                "R",
                "Go"
            ],
            "DataBase": [],
            "DataAnalytics": [
                "R"
            ],
            "BigData": [],
            "MachingLearning": [],
            "DataSerialization": [],
            "DataVisualization": [],
            "Statistics": [
                "Statistiques"
            ],
            "CloudComputing": [
                "Azure",
                "Google Cloud Platform"
            ],
            "DevTools": [
                "Git",
                "Jenkins"
            ],
            "Os": [],
            "DBMS": [
                "BigQuery"
            ],
            "SoftBigDataProcessing": [],
            "Automation": [],
            "InfrastructureAsCode": [
                "Terraform"
            ],
            "NetworkSecurty": [],
            "Virtualisation": [],
            "Containers": [],
            "Collaboration": [],
            "Other": [
                "DevOps",
                "Big Data",
                "Statistiques",
                "Cloud",
                "CI/CD"
            ],
            "FrSoftSkills": [
                "Communication",
                "Collaboration",
                "Organisation"
            ],
            "EnSoftSkils": [
                "Communication",
                "Collaboration",
                "Initiative"
            ]
        },
        "details": {
            "JobDetail": [],
            "TypeContract": [],
            "Salary": [],
            "Level": [],
            "Experience": [
                "a",
                "n",
                "s"
            ]
        }
    },
    {
        "source": "LinkedIn",
        "title": "ARCHITECTE DATA / POWER BI & AZURE",
        "company": "PROPULSE IT",
        "location": "Massy, \u00cele-de-France, France",
        "link": "https://fr.linkedin.com/jobs/view/architecte-data-power-bi-azure-at-propulse-it-3902536487?position=39&pageNum=0&refId=a5rwPua%2FMvx%2F2M%2FPSF0oPA%3D%3D&trackingId=XOow3ZIRcrdBggn90nLaPw%3D%3D&trk=public_jobs_jserp-result_search-card",
        "description": "PROPULSE IT accompagne ses clients grands comptes et PME dans la mise en \u0153uvre des projets It et digitaux.\nPROPULSE IT est un r\u00e9seau de consultants \u00e0 forte valeur ajout\u00e9e, compl\u00e8tement associ\u00e9 \u00e0 notre d\u00e9marche qualit\u00e9 de suivi des besoins et projets de nos clients.\nA ce jour, le r\u00e9seau de freelance PROPULSE IT comporte plus de 18000 consultants sur toute la France, et couvre l'ensemble des besoins IT et digitaux.\nEn constituant ce r\u00e9seau par cooptation de clients ou de consultants, nous avons privil\u00e9gi\u00e9 la constance dans le savoir-faire technique et le savoir-\u00eatre, pour devenir un v\u00e9ritable partenaire privil\u00e9gi\u00e9 de nos clients.\nParall\u00e8lement, nous avons d\u00e9velopp\u00e9 un r\u00e9seau de partenaires s\u00e9lectionn\u00e9es pour leur expertise technique, et l'adh\u00e9sion aux valeurs de notre entreprise.\nAujourd'hui PROPULSE IT est une soci\u00e9t\u00e9 en pleine croissance organique, Champion de la Croissance du journal Les Echos 4 ann\u00e9es cons\u00e9cutives.\nCe d\u00e9veloppement s'appuie sur la qualit\u00e9 et la p\u00e9rennit\u00e9 des missions r\u00e9alis\u00e9es.\nLa satisfaction client est ainsi li\u00e9e \u00e0 l'\u00e9panouissement des consultants !\nAlors, n'h\u00e9sitez pas \u00e0 postuler !\nLe Poste\nNous recherchons un(e) DATA ARCHITECTE POWER BI / AZURE\nDans le respect de la strat\u00e9gie IT \u00e9tablie par le DSI, votre mission consiste \u00e0 :\nResponsabilit\u00e9s\nAnalyser les besoins fonctionnels.\nLocaliser les donn\u00e9es de production.\nD\u00e9terminer les sp\u00e9cifications techniques.\nD\u00e9finir l'architecture.\nMod\u00e9liser les datawarehouse (entrep\u00f4ts de donn\u00e9es) et les datamarts (magasins de donn\u00e9es) d\u00e9di\u00e9s \u00e0 une fonction particuli\u00e8re dans l'entreprise.\nAccompagner le client dans la r\u00e9alisation du projet.\nMaintenir les sources de donn\u00e9es \u00e0 jour\nMettre \u00e0 disposition les donn\u00e9es aux m\u00e9tiers\nSuperviser les flux de donn\u00e9es et en contr\u00f4ler l'int\u00e9grit\u00e9\nProfil\nStack Technique :\nPower BI / DAX / Langage M\nAzure Data Factory\nAzure Synapse\nData Lake, Logical Datawarehouse\nMicrosoft Fabric\nInt\u00e9gration et la livraison continue (CI/CD)\nSavoir-faire\nRigueur\nShow more\nShow less",
        "skills": {
            "ProgLanguage": [
                "R"
            ],
            "DataBase": [],
            "DataAnalytics": [
                "R"
            ],
            "BigData": [],
            "MachingLearning": [],
            "DataSerialization": [],
            "DataVisualization": [
                "Power BI"
            ],
            "Statistics": [],
            "CloudComputing": [
                "Azure"
            ],
            "DevTools": [
                "Git"
            ],
            "Os": [],
            "DBMS": [],
            "SoftBigDataProcessing": [],
            "Automation": [],
            "InfrastructureAsCode": [],
            "NetworkSecurty": [],
            "Virtualisation": [],
            "Containers": [],
            "Collaboration": [],
            "Other": [
                "CI/CD"
            ],
            "FrSoftSkills": [],
            "EnSoftSkils": []
        },
        "details": {
            "JobDetail": [],
            "TypeContract": [],
            "Salary": [],
            "Level": [],
            "Experience": [
                "a",
                "n",
                "s"
            ]
        }
    },
    {
        "source": "LinkedIn",
        "title": "Cloud Solution Architect - Paris / Bordeaux / Remote",
        "company": "Fieldbox",
        "location": "Bordeaux, Nouvelle-Aquitaine, France",
        "link": "https://fr.linkedin.com/jobs/view/cloud-solution-architect-paris-bordeaux-remote-at-fieldbox-3881559118?position=40&pageNum=0&refId=a5rwPua%2FMvx%2F2M%2FPSF0oPA%3D%3D&trackingId=BfoYE0VTuCfRtXGAWXoRVg%3D%3D&trk=public_jobs_jserp-result_search-card",
        "description": "Our business:\nWe help industrial companies to accelerate their digital transformation and dramatically improve their operational efficiency and competitiveness with data, software and AI. Our clients include CAC 40 companies, as well as small and medium-sized companies on five continents and over 150 industrial sites.\nWhat makes us special:\nWe offer a complete range of services, combined with the use of latest technologies, covering the entire lifecycle of data-driven solutions, from ideation, business value assessment, industrialized solution development, to deployment, run and scale.\nOur positioning:\nWe seek long term partnership-relation with our clients. We can help them define their digital strategy and AI roadmap, build & run a solution, train, and transfer skills, set up and professionalize R&D or innovation units or digital & AI factories.\nOur teams:\nA virtuous combination of three areas of expertise:\nBusiness expertise: industrial operations & engineering.\nTechnical expertise: data science, software engineering & devops.\nDelivery management expertise: managing digital projects and setting digital factories.\nYour missions:\nAs a Cloud Architect,you will design and participate in the implementation of cloud solutions to support the digital transformation of our clients. You will work in agile mode, in an international context, on industrial projects.\nYour main missions :\nSupport pre-sales technical activities by translating client\u2019s requirements into state-of-the-art architectures, while guiding customers through their digital transformation journey in the cloud :\nLead workshops to study and define customer requirements\nImagine and define the architecture that would best meet the specifications provided while taking in account the financial and security constraints of the client.\nHandle and resolve technical questions and challenges encountered by clients during the first phases of their projects\nDefine deployment methodologies and integration of the solution into the existing client\u2019s ecosystem.\nParticipate in pre-sales meeting with clients to present the envisioned architectures\nLead end-to-end architecture projects (web applications, data engineering & processing pipelines) involving intensive use of industrial data, with a focus on performance, scalability and security issues\nSupervise the deployment and industrialization of the target architectures\nEnsure the security and reliability of deployed environments\nWork in collaboration with multidisciplinary teams, including DevOps, back-end, front-end, data, product and business skills to make every project a success.\nExperience and skills required:\nAt least 2 years' experience in Architect or tech lead full stack role\nYou have experience with the following technologies:\nCloud: Azure, Google Cloud, AWS, OVH\nDatabases & storage : PostgreSQL, TimeScaleDB, Redis, InfluxDB, S3 and alike\nProcessing and scheduling: Azure Data Factory, Azure Functions, Azure Synapse, Airflow, Argo, AWS Batch, AWS Step\nStreaming: Kafka, RabbitMQ, Kinesis, SQS\nDevops: Docker, Kubernetes\nMoreover :\nYou have proven experience in cloud or hybrid architectures\nYou love architecture diagrams ! (Excalidraw, Draw.io)\nYou demonstrate technical leadership and are able to communicate complex ideas effectively.\nYou know how to challenge customer requirements and Fieldbox objectives in order to optimize the proposed architecture.\nYou successfully manage the complex constraints of a production application through analysis and resolution.\nYou are customer and solution-oriented and have excellent interpersonal skills.\nFluency in English\nKnowledge of an industrial sector is a plus\nKnowledge in python is a plus\nAdvantage and benefits:\nFull remote possible (Metropolitan France only)\nWhat about our offices\nBordeaux: meet with your colleagues in a peaceful and calm space with an amazing view on \u201cLes bassins \u00e0 flots\u201d\nParis: enjoy a coworking space on the top of the Montparnasse tower with a 360 view of Paris\nWhat about our values :\nJoin a company which values care where everyone is in position to reach their full potential\nYou will work within an energetic team with a strong technical skill. Weekly engineering are organized every week to present and discuss technical topics\nCreate immediate impact on the company\nA quiz is sent every month in order to improve your comfort at work\nFun Activity:\nAfterwork every month with different theme ( bowling , board game , darts, beers bar, etc. )\nLunch break : outside lunchs, board game parties, and sport! (running, badminton, darts, yoga)\nCTFs\nTypical process includes 3 steps :\nHR interview\nInterview with operational team, aiming at testing your fit to the specific job,\nInterview with one or several founders to validate the application\nShow more\nShow less",
        "skills": {
            "ProgLanguage": [
                "Python",
                "Scala",
                "R",
                "Go"
            ],
            "DataBase": [
                "SQL"
            ],
            "DataAnalytics": [
                "R"
            ],
            "BigData": [],
            "MachingLearning": [],
            "DataSerialization": [],
            "DataVisualization": [],
            "Statistics": [],
            "CloudComputing": [
                "AWS",
                "Azure"
            ],
            "DevTools": [
                "Git",
                "Docker"
            ],
            "Os": [],
            "DBMS": [
                "PostgreSQL"
            ],
            "SoftBigDataProcessing": [],
            "Automation": [
                "Kubernetes",
                "Airflow"
            ],
            "InfrastructureAsCode": [],
            "NetworkSecurty": [],
            "Virtualisation": [],
            "Containers": [
                "Docker",
                "Kubernetes"
            ],
            "Collaboration": [
                "Teams"
            ],
            "Other": [
                "DevOps",
                "Cloud"
            ],
            "FrSoftSkills": [
                "Leadership",
                "Collaboration"
            ],
            "EnSoftSkils": [
                "Leadership",
                "Collaboration",
                "Interpersonal Skills"
            ]
        },
        "details": {
            "JobDetail": [
                "Remote",
                "Full"
            ],
            "TypeContract": [],
            "Salary": [],
            "Level": [],
            "Experience": [
                "a",
                "n",
                "s"
            ]
        }
    },
    {
        "source": "LinkedIn",
        "title": "Data Architect",
        "company": "Amadeus",
        "location": "Nice, Provence-Alpes-C\u00f4te d'Azur, France",
        "link": "https://fr.linkedin.com/jobs/view/data-architect-at-amadeus-3796958716?position=41&pageNum=0&refId=a5rwPua%2FMvx%2F2M%2FPSF0oPA%3D%3D&trackingId=ljKoPwTz1epZhroaEEkg%2Fw%3D%3D&trk=public_jobs_jserp-result_search-card",
        "description": "Job Title\nData Architect\nDigital Transformation Services (DTS) Is Committed To Drive Positive Change In Amadeus By Assembling, Leveraging, And Managing Digital And Transformation Services To Internal Customers Along Two Service Areas, Business Transformation Services And Enterprise Digital Services, Aiming To\nSpeed up and simplify business agility, value perception and compliance.\nGrow business value guided by the Amadeus Evolution Principles.\nDeliver end-to-end services and transformation programs to Amadeus.\nEngage, empower and develop a global team, proficient and engaged and nurturing our culture.\nDTS Solutions Architects and IBS Engineering Principal Specialists drive activities of developing a direction for managing a suit of solutions -including systems (applications and underlying IT stacks), processes and information, shared infrastructure services, and shared application services and components- in order to better match business requirements.\nAs such, DTS Solutions Architects act as leaders, with deep understanding of business goals, processes and enterprise architecture, to conceptualize and assemble technology solution architecture\u2019s designs. These designs optimize the response to business needs (i.e.: cost, time to market, usability, continuity, etc.), while ensuring and improving architecture consistency.\nIn This Role You\u2019ll / Your Main Responsibilities\nAs a Data Architect, you will play a crucial role in shaping and optimizing our organization's data infrastructure. You will be responsible for designing, implementing, and maintaining scalable and efficient data solutions that meet business needs. This role requires a deep understanding of data management, database technologies, and a strategic mindset to align data architecture with overall business strategies.\nKey Responsibilities\nData Modeling and Design:\nDevelop and maintain conceptual, logical, and physical data models.\nDesign data structures and relationships that support business requirements and enable efficient data retrieval.\nDatabase Management:\nSelect and implement appropriate database technologies based on project requirements.\nOptimize database performance and ensure data integrity.\nData Governance:\nEstablish and enforce data governance policies and procedures.\nDefine data standards, naming conventions, and data quality rules.\nData Integration:\nDesign and implement data integration solutions to ensure seamless flow of information across systems.\nCollaborate with other IT teams to integrate data sources and maintain data consistency.\nCollaboration and Communication:\nWork closely with business stakeholders to understand their data needs and translate them into effective data solutions.\nCollaborate with cross-functional teams including data scientists, analysts, and developers.\nSecurity and Compliance:\nImplement data security measures to protect sensitive information.\nEnsure compliance with data privacy regulations and industry standards.\nUse and leverage new technology solutions, to enable the organization's future-state business capabilities, facilitating and orchestrating the delivery of targeted business outcomes.\nProvide leadership, analysis and design tasks related to the development or upgrade of a solution to ensure application provides expected business value.\nProvide architecture guidance and support on activities performed to maintain, improve or support applications.\nAbout The Ideal Candidate\nBachelor's or Master's degree in Computer Science, Information Technology, or related field.\nProven experience as a Data Architect or in a similar role.\nStrong knowledge of database management systems, data warehousing, and data modeling techniques.\nProficiency in SQL and other query languages.\nFamiliarity with middleware, cloud-based data platforms and big data technologies.\nUnderstanding of agile methods and processes, and capability of supporting agile project teams.\nAnalytical and strategic thinking.\nExcellent communication and collaboration skills.\nProblem-solving and troubleshooting abilities.\nStay updated on emerging trends and technologies in data management.\nWhat we can offer you\nAn Extensive Range Of Benefits Including\nYou will be part of a multi-cultural team with international scope.\nYou will benefit from a permanent contract and a competitive employee benefits package such as pension plan, travel, life and healthcare insurance as well as lunch allowance.\nSkill development and career path.\nExperience in one of the world\u2019s top IT companies.\nYou will be based in our Nice office (Hybrid Model, 3 days office 2 days work from home).\nApplication process\nThe application process takes no longer than 10 minutes! Create your candidate profile, upload your CV and apply. Once we\u2019ve received your application, one of our recruiters may get in touch with you to arrange a telephone interview.\nAre you the one we\u2019re looking for? Apply now!\nDiversity & Inclusion\nWe are an Equal Opportunity Employer and seek to hire the best candidate regardless of age, beliefs, disability, ethnicity, gender or sexual orientation.\nShow more\nShow less",
        "skills": {
            "ProgLanguage": [
                "Scala",
                "R",
                "Go"
            ],
            "DataBase": [
                "SQL"
            ],
            "DataAnalytics": [
                "R"
            ],
            "BigData": [],
            "MachingLearning": [],
            "DataSerialization": [],
            "DataVisualization": [],
            "Statistics": [],
            "CloudComputing": [],
            "DevTools": [
                "Git"
            ],
            "Os": [],
            "DBMS": [],
            "SoftBigDataProcessing": [],
            "Automation": [],
            "InfrastructureAsCode": [],
            "NetworkSecurty": [],
            "Virtualisation": [],
            "Containers": [],
            "Collaboration": [
                "Teams"
            ],
            "Other": [
                "Big Data",
                "ML",
                "Cloud"
            ],
            "FrSoftSkills": [
                "Communication",
                "Leadership",
                "Collaboration"
            ],
            "EnSoftSkils": [
                "Communication",
                "Leadership",
                "Collaboration",
                "Organization"
            ]
        },
        "details": {
            "JobDetail": [],
            "TypeContract": [],
            "Salary": [
                "3"
            ],
            "Level": [],
            "Experience": [
                "a",
                "n",
                "s"
            ]
        }
    },
    {
        "source": "LinkedIn",
        "title": "Architecte Big Data & Cloud - Toulouse",
        "company": "Capgemini",
        "location": "Toulouse, Occitanie, France",
        "link": "https://fr.linkedin.com/jobs/view/architecte-big-data-cloud-toulouse-at-capgemini-3810332150?position=42&pageNum=0&refId=a5rwPua%2FMvx%2F2M%2FPSF0oPA%3D%3D&trackingId=d9gP0d9GUsgTzuxm6aSX1w%3D%3D&trk=public_jobs_jserp-result_search-card",
        "description": "Capgemini en quelques mots\nChoisir Capgemini, c'est choisir une entreprise o\u00f9 vous serez en mesure de fa\u00e7onner votre carri\u00e8re selon vos aspirations, o\u00f9 vous serez soutenu et inspir\u00e9 par une communaut\u00e9 d\u2019experts dans le monde entier, o\u00f9 vous pourrez r\u00e9\u00e9crire votre futur. Rejoignez-nous pour red\u00e9finir les limites de ce qui est possible, contribuer \u00e0 lib\u00e9rer la valeur de la technologie pour les plus grandes organisations et participez \u00e0 la construction d\u2019un monde plus durable et inclusif.\nVos missions\nVous int\u00e9grez une communaut\u00e9 d\u2019experts passionn\u00e9s reconnus par nos clients sur des technologies de pointe (Google Cloud Platform, Azure, AWS)\nVous interagissez au plus proche de nos clients, des partenaires pour concevoir et mettre en \u0153uvre des solutions/projets innovants et comp\u00e9titifs\nVous r\u00e9pondez aux probl\u00e9matiques de nos clients en proposant la meilleure plateforme data dans un environnement Agile\nVous avez acquis de l\u2019exp\u00e9rience sur les cadres de r\u00e9f\u00e9rence et patterns d\u2019architecture Data, DevOps\nVous adaptez chaque architecture en fonction du contexte gr\u00e2ce \u00e0 votre maitrise des caract\u00e9ristiques fondamentales de chaque solution (catalogue des offres de services manag\u00e9s, performance, s\u00e9curit\u00e9, d\u00e9ploiement des data centers \u2026)\nVous utilisez les solutions d\u2019int\u00e9gration associ\u00e9es et les solutions d\u00e9cisionnelles ainsi qu\u2019analytiques qui viennent consommer les donn\u00e9es manipul\u00e9es\nVous \u00eates en mesure d\u2019encadrer les \u00e9quipes dans la mise en place des architectures pr\u00e9conis\u00e9es et/ ou des plateformes Data\nVotre profil\nDe formation Bac + 5 en \u00e9cole d\u2019ing\u00e9nieur ou \u00e9quivalent universitaire\nAu moins 6 ans d\u2019exp\u00e9rience\nBon niveau d'anglais\nQualit\u00e9s de p\u00e9dagogue, transmission de comp\u00e9tences\nLa phase d'avant-vente vous int\u00e9resse\n3 raisons de nous rejoindre\nQualit\u00e9 de vie au travail :\naccord de t\u00e9l\u00e9travail en France et \u00e0 l\u2019international, accord sur l\u2019\u00e9galit\u00e9\nprofessionnelle, la parentalit\u00e9, l\u2019\u00e9quilibre des temps et la mobilit\u00e9 durable.\nApprentissage en continu :\ncertifications et formations en libre acc\u00e8s, accompagnement sur mesure avec\nvotre carreer manager, parcours d\u2019int\u00e9gration sur 9 mois.\nAvantages groupe & CSE :\nplan actionnariat, activit\u00e9s \u00e0 tarifs pr\u00e9f\u00e9rentiels, remboursement partiel\nvacances, remboursement de votre abonnement sportif ou culturel\nNos engagements et priorit\u00e9s\nLe groupe Capgemini encourage une\nculture inclusive dans un cadre multiculturel et handi-accueillant.\nEn nous rejoignant, vous int\u00e9grez un collectif qui valorise la diversit\u00e9, d\u00e9veloppe le potentiel de ses talents, s\u2019engage dans des\ninitiatives solidaires avec ses partenaires, et se mobilise pour r\u00e9duire son impact environnemental sur tous ses sites et aupr\u00e8s de ses clients.\nCapgemini\nest un\nleader mondial\n, responsable et multiculturel, regroupant pr\u00e8s de 350 000 personnes dans plus de 50 pays. Fort de\n55 ans d\u2019exp\u00e9rience\n, nous sommes un partenaire strat\u00e9gique des entreprises pour la transformation de leurs activit\u00e9s en tirant profit de toute la puissance de la technologie et des innovations dans les domaines en perp\u00e9tuelle \u00e9volution tels que\nle cloud, la data, l\u2019Intelligence Artificielle, la connectivit\u00e9, les logiciels, l\u2019ing\u00e9nierie digitale ou les plateformes.\nGet The Future You Want* | www.capgemini.com/fr-fr\n*Capgemini, le futur que vous voulez\nShow more\nShow less",
        "skills": {
            "ProgLanguage": [
                "R",
                "Go"
            ],
            "DataBase": [],
            "DataAnalytics": [
                "R"
            ],
            "BigData": [],
            "MachingLearning": [],
            "DataSerialization": [],
            "DataVisualization": [],
            "Statistics": [],
            "CloudComputing": [
                "AWS",
                "Azure",
                "Google Cloud Platform"
            ],
            "DevTools": [
                "Git"
            ],
            "Os": [],
            "DBMS": [],
            "SoftBigDataProcessing": [],
            "Automation": [],
            "InfrastructureAsCode": [],
            "NetworkSecurty": [],
            "Virtualisation": [],
            "Containers": [],
            "Collaboration": [],
            "Other": [
                "DevOps",
                "Cloud"
            ],
            "FrSoftSkills": [
                "Organisation"
            ],
            "EnSoftSkils": [
                "Initiative"
            ]
        },
        "details": {
            "JobDetail": [],
            "TypeContract": [],
            "Salary": [],
            "Level": [],
            "Experience": [
                "a",
                "n",
                "s",
                "6",
                "6",
                "6"
            ]
        }
    },
    {
        "source": "LinkedIn",
        "title": "Data Architect AGILE",
        "company": "Cyborg Intelligence",
        "location": "Lyon, Auvergne-Rh\u00f4ne-Alpes, France",
        "link": "https://fr.linkedin.com/jobs/view/data-architect-agile-at-cyborg-intelligence-3913820683?position=43&pageNum=0&refId=a5rwPua%2FMvx%2F2M%2FPSF0oPA%3D%3D&trackingId=QfZxY%2F2KgP%2BSZeHlfhURMA%3D%3D&trk=public_jobs_jserp-result_search-card",
        "description": "Pour l'un de nos clients suisses de prestige - L'anglais et le fran\u00e7ais sont des imp\u00e9ratifs incontournables pour ce poste en CDI\nResponsabilit\u00e9s\nL'architecte des donn\u00e9es informatiques est responsable de la d\u00e9finition des politiques, des proc\u00e9dures, des mod\u00e8les et\ntechnologies qui seront utilis\u00e9es pour collecter, organiser, stocker et r\u00e9cup\u00e9rer des informations pour\nl'organisation.\nIl/elle comprend comment les donn\u00e9es d\u00e9terminent le d\u00e9veloppement d'applications et\nexigences commerciales gr\u00e2ce \u00e0 des principes de conception, des m\u00e9thodologies et des\noutils.\nIl/elle fixe les r\u00e8gles et la structure de la strat\u00e9gie data, en choisissant l'ETL\napproche et d\u00e9finition d\u2019exigences suppl\u00e9mentaires\nD\u00e9finition du mod\u00e8le de donn\u00e9es\u00a0: d\u00e9finir l'architecture des donn\u00e9es, les interfaces des contrats de donn\u00e9es, les donn\u00e9es\nqualit\u00e9 dans les syst\u00e8mes, les meilleures pratiques,\nAper\u00e7u des flux de donn\u00e9es : devenez propri\u00e9taire des flux de donn\u00e9es actuels et futurs.\nAssumer la responsabilit\u00e9 de la qualit\u00e9 et de l'actualit\u00e9 des donn\u00e9es,\nMaintenir et assurer l'\u00e9volution des flux de donn\u00e9es, en utilisant les standards mondiaux de donn\u00e9es\net des r\u00e8gles m\u00e9tier pour saisir les donn\u00e9es dans les syst\u00e8mes,\nAssurance qualit\u00e9\u00a0: effectuer des contr\u00f4les de qualit\u00e9 des donn\u00e9es pour v\u00e9rifier leur exactitude et\nl'exhaustivit\u00e9 selon des r\u00e8gles m\u00e9tier d\u00e9finies,\nSyst\u00e8me de donn\u00e9es principal\u00a0: maintenir des donn\u00e9es pr\u00e9cises et \u00e0 jour pour les activit\u00e9s assign\u00e9es\nprocessus,\nContribuer \u00e0 l\u2019am\u00e9lioration continue des syst\u00e8mes et des processus. Garantir les donn\u00e9es\nalignement entre la documentation contractuelle et les donn\u00e9es de base client,\nMaintenir \u00e0 jour la documentation des processus et le mat\u00e9riel de formation,\nAssistance\u00a0: assurez-vous que les probl\u00e8mes sont identifi\u00e9s, suivis, signal\u00e9s et r\u00e9solus de mani\u00e8re rapide.\nen temps opportun.\nD\u00e9veloppement & maintenance\nR\u00f4le d'expert pour le produit ou le domaine de produit d\u00e9sign\u00e9.\n1. Traite les demandes des utilisateurs, les tickets de service, les incidents, les modifications\n2. Assumer les activit\u00e9s de support de 3\u00e8me niveau\n3. R\u00e9dige et maintient la documentation\n4. Participe \u00e0 la cr\u00e9ation des guides d'utilisation\nS'assure que le savoir-faire du domaine est transf\u00e9r\u00e9 aux membres de l'\u00e9quipe.\n5. Assure le respect de la s\u00e9curit\u00e9 des donn\u00e9es \u00e0 tout moment.\n6. \u00c9value les performances des applications et des bases de donn\u00e9es et les am\u00e9liore lorsque cela est possible\n7. R\u00e9aliser ou superviser les activit\u00e9s de d\u00e9veloppement et d'int\u00e9gration de syst\u00e8mes.\nGestion de projet\n1. Diriger des projets li\u00e9s aux donn\u00e9es en tant que repr\u00e9sentant informatique\n2. D\u00e9finit la port\u00e9e du projet, planifie et suit les d\u00e9veloppements du projet et\nd\u00e9ploiements d'applications.\n3. Superviser les ressources externes pendant la phase du projet.\nQualifications\nApproche ax\u00e9e sur le client\n\u2022 Exp\u00e9rience de travail dans Azure DF, Synapse, AWS ou autre\n\u2022 Exp\u00e9rience de travail avec les m\u00e9thodologies Agile\n\u2022 Forte r\u00e9solution de probl\u00e8mes, capacit\u00e9 \u00e0 travailler sous pression et capacit\u00e9 \u00e0 \u00e9tablir des priorit\u00e9s.\n\u2022 Autogestion et capacit\u00e9 \u00e0 travailler de mani\u00e8re ind\u00e9pendante avec une supervision limit\u00e9e\n\u2022 Bonnes comp\u00e9tences en communication et en relations interpersonnelles, capacit\u00e9 \u00e0 travailler efficacement avec\n\u00e9quipes \u00e0 distance\n\u2022 Tr\u00e8s bonne communication orale et \u00e9crite\n\u2022 Anglais courant\nShow more\nShow less",
        "skills": {
            "ProgLanguage": [
                "R"
            ],
            "DataBase": [],
            "DataAnalytics": [
                "R"
            ],
            "BigData": [],
            "MachingLearning": [],
            "DataSerialization": [],
            "DataVisualization": [],
            "Statistics": [],
            "CloudComputing": [
                "AWS",
                "Azure"
            ],
            "DevTools": [],
            "Os": [],
            "DBMS": [],
            "SoftBigDataProcessing": [],
            "Automation": [],
            "InfrastructureAsCode": [],
            "NetworkSecurty": [],
            "Virtualisation": [],
            "Containers": [],
            "Collaboration": [],
            "Other": [],
            "FrSoftSkills": [
                "Communication",
                "R\u00e9solution de probl\u00e8mes",
                "Organisation",
                "Relations interpersonnelles"
            ],
            "EnSoftSkils": [
                "Communication"
            ]
        },
        "details": {
            "JobDetail": [],
            "TypeContract": [
                "CDI"
            ],
            "Salary": [],
            "Level": [],
            "Experience": [
                "a",
                "n",
                "s"
            ]
        }
    },
    {
        "source": "LinkedIn",
        "title": "GET Data Architect (M/F)",
        "company": "ENGIE",
        "location": "Courbevoie, \u00cele-de-France, France",
        "link": "https://fr.linkedin.com/jobs/view/get-data-architect-m-f-at-engie-3596026403?position=44&pageNum=0&refId=a5rwPua%2FMvx%2F2M%2FPSF0oPA%3D%3D&trackingId=5EGkaG7PyxLRHfA4k%2BzyOw%3D%3D&trk=public_jobs_jserp-result_search-card",
        "description": "Come join one of the most ambitious Transformation Program of Engie\nENGIE's strategy to drive the energy transition and to industrialize the company, making it simpler,\nfaster, and more integrated, is set.\nGET, Global Enterprise Transformation\n, is the Program decided by ENGIE to accelerate and standardize the ERP system as well as the effectiveness of processes, embarking the Company on a centrally steered and business-led transformation focused on making ENGIE an integrated industrial company.\nTherefore, GET Program is among the top 5 ENGIE priorities with genuine ExCom sponsorship.\nBe part of the Change and come build the Future at one of the most ambitious Transformation Program of the moment.\nWith a view to harmonization, ENGIE has embarked on a major program to transform its processes and IT tools. This project, which extends over several years, concerns all the entities of the group and requires a sustained support.\nTo implement this support, we are looking to recruit a :\nGET \u2013\nData Architect (M/F)\nThe head office is based in Courbevoie (La D\u00e9fense), but the physical presence on the head office is not mandatory. We are also looking for international profiles.\nThe GET program aims to deliver the future business and IT core model with a central \u201cone ERP / One ARIBA\u201d platform. The functional context of the program covers a set of functional areas including accounting, controlling and procurement as main areas.\nThe GET program offers a unique opportunity to onboard on one of the most ambitious and strategic Enterprise transformation programs with a very high IT footprint with S/4 & SAP ARIBA as central IT components. Innovation is at the heart of GET Program with an ambition to implement a best in class processes & solution.\nThe\nGET Data Architect\nrole is proposed to reinforce the internal team supporting the core model delivery and coordinating the pilots/rollouts.\nThis role will be N-2 to GET IT Lead and directly reporting to the core model IT lead.\nJob Responsibilities:\nBring high level expertise on MDM and especially SAP MDG\nHelp the business teams in business requirement definition and ensure coherence with the SAP capabilities\nResponsible for reviewing the integrator delivery and challenge the proposed solutions\nAlign with the business team to ensure the proposed solution is aligned with the core model and the program guidelines\nWork with the integrator teams and SAP teams to secure design authority presentations for arbitrations\nSecure testing phases and ensure quality of test delivery by the IT integrator\nDrive discussions in multi-cultural / global context with multiple stakeholders\nPosition Requirements\nVery good knowledge of the SAP MDG and overall the MDM area.\nUnderstanding the process of translating business requirements and processes into data collection and usage principles in MDG.\nAt least 5 years experience in similar position\nGood references in the previous experiences with other customers\nFluent English (oral/written)\nMay require national & international mobility.\n\"Priority position reserved for ENGIE SA Corporate employees whose position is removed and for DTR employees\".\nShow more\nShow less",
        "skills": {
            "ProgLanguage": [
                "R",
                "Go"
            ],
            "DataBase": [],
            "DataAnalytics": [
                "R"
            ],
            "BigData": [],
            "MachingLearning": [],
            "DataSerialization": [],
            "DataVisualization": [],
            "Statistics": [],
            "CloudComputing": [],
            "DevTools": [],
            "Os": [],
            "DBMS": [],
            "SoftBigDataProcessing": [],
            "Automation": [],
            "InfrastructureAsCode": [],
            "NetworkSecurty": [],
            "Virtualisation": [],
            "Containers": [],
            "Collaboration": [
                "Teams"
            ],
            "Other": [],
            "FrSoftSkills": [],
            "EnSoftSkils": []
        },
        "details": {
            "JobDetail": [],
            "TypeContract": [],
            "Salary": [],
            "Level": [],
            "Experience": [
                "a",
                "n",
                "s"
            ]
        }
    },
    {
        "source": "LinkedIn",
        "title": "DATA Architect Solution Azure F/H",
        "company": "SOFTEAM",
        "location": "\u00cele-de-France, France",
        "link": "https://fr.linkedin.com/jobs/view/data-architect-solution-azure-f-h-at-softeam-3839977121?position=45&pageNum=0&refId=a5rwPua%2FMvx%2F2M%2FPSF0oPA%3D%3D&trackingId=nJC8wyzoJbZwI7vYjHDuaw%3D%3D&trk=public_jobs_jserp-result_search-card",
        "description": "Vous \u00e9voluez dans le domaine de la\nData\net souhaitez int\u00e9grer un leader de la transformation num\u00e9rique sp\u00e9cialis\u00e9 dans les secteurs de la\nBanque, du Luxe, de l'Assurance, de la Finance, de l'Energie\net la possibilit\u00e9 d'\u00e9voluer au sein du\nGroupe Docaposte\n!\nSofteam\nest labellis\u00e9 \"\nHappyIndex\u00ae AtWork\n\" 2022 pour la\n5\u00e8me\nann\u00e9e cons\u00e9cutive !\nNos collaborateurs travaillent en \u00ab mode projet \u00bb autour des\nModern DATA Platform\n\u2601 et\ntechnologies Big Data AWS Cloud / On premise\net autre \"playeur\" du march\u00e9. Nous accompagnons de bout en bout nos clients sur des probl\u00e9matiques de\nGouvernance, d\u2019Int\u00e9gration, de Visualisation et d\u2019IA.\nCE QUE NOUS RECHERCHONS\nData Architect Solution Azure\nF/H, disposant de l\u2019exp\u00e9rience dans la mise en place des\nModern Data Platform\ndans\nAzure\n.\nCE QUE NOUS ATTENDONS DE VOUS\nEn tant que\nData Architect Solution Azure\nF/H, vous intervenez sur nos projets et contribuer au d\u00e9veloppement de notre activit\u00e9.\nVOS MISSIONS DETAILLEES\nAccompagner et conseiller le client dans son adoption des Modern Data Platform dans Azure (Etude d\u2019architecture, pr\u00e9paration des DAT, FinOps, DevOps)\nConcevoir des architectures Cloud Data exploitant efficacement les services de donn\u00e9es manag\u00e9s d'Azure\nConduire des projets de d\u00e9ploiement des Modern Data Platform (Applications Cloud Native, Migration d\u2019applications existantes) et participer \u00e0 la mise en \u0153uvre\nEtablir des relations de confiance avec les d\u00e9cisionnaires techniques et m\u00e9tiers afin de favoriser l\u2019adoption du Cloud Azure \u00e0 long terme au sein de l\u2019entreprise.\nFournir une expertise technique approfondie aux \u00e9quipes projets\nAssister et former le client sur les usages et outils Data du Cloud Azure\nR\u00e9aliser une veille technologique permanente sur les tendances du march\u00e9 et les perspectives concurrentielles\nVOUS ETES\nIng\u00e9nieur(e) de formation, vous disposez d'une expertise reconnue et d'une exp\u00e9rience de 5 ans dans un r\u00f4le d\u2019\ud835\udc00\ud835\udc2b\ud835\udc1c\ud835\udc21\ud835\udc22\ud835\udc2d\ud835\udc1e\ud835\udc1c\ud835\udc2d\ud835\udc1e \ud835\udc12\ud835\udc28\ud835\udc25\ud835\udc2e\ud835\udc2d\ud835\udc22\ud835\udc28\ud835\udc27 \ud835\udc02\ud835\udc25\ud835\udc28\ud835\udc2e\ud835\udc1d \ud835\udc03\ud835\udc1a\ud835\udc2d\ud835\udc1a ou \ud835\udc13\ud835\udc1e\ud835\udc1c\ud835\udc21 \ud835\udc0b\ud835\udc1e\ud835\udc1a\ud835\udc1d \ud835\udc03\ud835\udc1a\ud835\udc2d\ud835\udc1a, avec une exp\u00e9rience significative sur Azure.\nVous avez des comp\u00e9tences approfondies dans un ou plusieurs de ces domaines : Op\u00e9rations / Gestion des syst\u00e8mes, Conception ou d\u00e9veloppement de logiciels, Processus DevOps et outillage, Strat\u00e9gie d'entreprise, Infrastructure Cloud (virtualisation, mise en r\u00e9seau, stockage, base de donn\u00e9es), S\u00e9curit\u00e9 et conformit\u00e9.\nVous \u00eates sensibilis\u00e9 \u00e0 la d\u00e9marche DevOps et connaissez au moins un outil pour la mise en \u0153uvre de Continuous Integration/Continuous Delivery (CI-CD)\nLa possession de certifications sur des services Azure est un plus.\nNOUS VOUS OFFRONS\nDes missions engageantes aupr\u00e8s des grands acteurs du march\u00e9.\nUn management de proximit\u00e9 avec Gilles SALVADOR, Directeur du Centre d'Expertise Data, toujours bienveillant et \u00e0 l'\u00e9coute et avec qui vous pourrez \u00e9changer au quotidien sur les enjeux de votre mission et \u00e9voquer vos futurs projets afin que nous puissions vous aider \u00e0 les r\u00e9aliser.\nLa possibilit\u00e9 d\u2019\u00e9voluer et de monter en comp\u00e9tences gr\u00e2ce \u00e0 des formations et \u00e0 des certifications aupr\u00e8s de nos clients et de nos consultants, des 12@13, notre Entit\u00e9 Softeam Institute, Organisme de formation interne de renomm\u00e9 qui d\u00e9livre des formations aupr\u00e8s de nos clients...\nQUI SOMMES-NOUS ?\nSOFTEAM DATA est une marque de DOCAPOSTE sp\u00e9cialis\u00e9e dans l'informatique d\u00e9cisionnelle et les nouvelles technologies. Nous apportons notre expertise \u00e0 nos clients, principalement des Grands Comptes de la place financi\u00e8re fran\u00e7aise, dans des projets de transformation digitale et cognitive.\n2000 Softeamien.nes sont d\u00e9di\u00e9.es \u00e0 la transformation m\u00e9tier et digitale de nos clients et ont g\u00e9n\u00e9r\u00e9 200 M\u20ac de chiffre d\u2019affaires en 2020.\nSOFTEAM SPIRIT\nDes communaut\u00e9s d'expertises sur les sujets de la Data ;\nDe super nouveaux locaux qui sont en plus accessibles facilement ;\nUne \u00e9cole de formation int\u00e9gr\u00e9e ;\nDes \u00e9v\u00e8nements : des soir\u00e9es avec les consultants, des 12@13... ;\nUne entreprise labellis\u00e9e \"Happy at Work\" pour la 5\u00e8me ann\u00e9e cons\u00e9cutive.\nN\u2019attendez plus, rejoignez SOFTEAM et venez nous rencontrer dans nos nouveaux locaux situ\u00e9s \u00e0 la D\u00e9fense #DevenezSofteamien !\nShow more\nShow less",
        "skills": {
            "ProgLanguage": [
                "R",
                "Go"
            ],
            "DataBase": [],
            "DataAnalytics": [
                "R"
            ],
            "BigData": [],
            "MachingLearning": [],
            "DataSerialization": [],
            "DataVisualization": [],
            "Statistics": [],
            "CloudComputing": [
                "AWS",
                "Azure"
            ],
            "DevTools": [
                "Git"
            ],
            "Os": [],
            "DBMS": [],
            "SoftBigDataProcessing": [],
            "Automation": [],
            "InfrastructureAsCode": [],
            "NetworkSecurty": [],
            "Virtualisation": [],
            "Containers": [],
            "Collaboration": [],
            "Other": [
                "DevOps",
                "Big Data",
                "Cloud"
            ],
            "FrSoftSkills": [],
            "EnSoftSkils": []
        },
        "details": {
            "JobDetail": [],
            "TypeContract": [],
            "Salary": [],
            "Level": [],
            "Experience": [
                "a",
                "n",
                "s",
                "5",
                "5",
                "5"
            ]
        }
    },
    {
        "source": "LinkedIn",
        "title": "Principal Data Architect",
        "company": "HP",
        "location": "Hauts de Bienne, France",
        "link": "https://fr.linkedin.com/jobs/view/principal-data-architect-at-hp-3902461217?position=46&pageNum=0&refId=a5rwPua%2FMvx%2F2M%2FPSF0oPA%3D%3D&trackingId=oNBWg9krxvuDIl9%2BoJg16A%3D%3D&trk=public_jobs_jserp-result_search-card",
        "description": "HP is a Fortune 100 technology company with $58+ Billion in revenue, with over 50,000 employees operating in more than 170 countries around the world. We provide technology and services that help people and companies address their problems and challenges, and realize their possibilities, aspirations, and dreams. We apply new thinking and ideas to create simpler, more valuable, and trusted experiences with technology, continuously improving the way our customers live and work.\nIn the GTM advanced analytics COE, our mission is to deliver impact by building machine learning (ML) products to optimize pricing, marketing investments and provide guidance to sales and other HP teams.\nWe're looking for a principal data architect to join our data engineering team.\nQualifications\nTypically 5+ years of experience in software or data engineering.\nExtensive experience in data modeling, data integration and processing of structured and unstructured data.\nHighly proficient in one or more programming languages (Python preferred).\nStrong SQL proficiency (experience with NoSQL \u2013 advantage).\nHighly experienced with Apache Spark / pyspark\nExcellent communication skills; mastery in English and local language.\nAbility to effectively communicate product architectures, design and change proposals.\nFamiliar with best practices of the data and software engineering lifecycle and/or best practices of the above platforms and tools.\nAdditional Preferred Qualifications / Advantages\nDatabricks\nPandas\nDataiku DSS\nShow more\nShow less",
        "skills": {
            "ProgLanguage": [
                "Python",
                "R"
            ],
            "DataBase": [
                "SQL",
                "NoSQL"
            ],
            "DataAnalytics": [
                "Pandas",
                "R"
            ],
            "BigData": [
                "Spark",
                "Databricks"
            ],
            "MachingLearning": [],
            "DataSerialization": [],
            "DataVisualization": [],
            "Statistics": [],
            "CloudComputing": [],
            "DevTools": [],
            "Os": [],
            "DBMS": [],
            "SoftBigDataProcessing": [],
            "Automation": [],
            "InfrastructureAsCode": [],
            "NetworkSecurty": [],
            "Virtualisation": [],
            "Containers": [],
            "Collaboration": [
                "Teams"
            ],
            "Other": [
                "ML",
                "Machine Learning"
            ],
            "FrSoftSkills": [
                "Communication"
            ],
            "EnSoftSkils": [
                "Communication"
            ]
        },
        "details": {
            "JobDetail": [],
            "TypeContract": [],
            "Salary": [],
            "Level": [],
            "Experience": [
                "a",
                "n",
                "s"
            ]
        }
    },
    {
        "source": "LinkedIn",
        "title": "Architecte Cloud Azure Data (H/F)",
        "company": "EXAKIS NELITE",
        "location": "Aix-en-Provence, Provence-Alpes-C\u00f4te d'Azur, France",
        "link": "https://fr.linkedin.com/jobs/view/architecte-cloud-azure-data-h-f-at-exakis-nelite-3904805434?position=47&pageNum=0&refId=a5rwPua%2FMvx%2F2M%2FPSF0oPA%3D%3D&trackingId=%2Fb%2F4oxKpQrWu%2F5dO2fGNpg%3D%3D&trk=public_jobs_jserp-result_search-card",
        "description": "Exakis Nelite, entit\u00e9 du groupe Magellan Partners, est le premier partenaire pure-player Microsoft ind\u00e9pendant en France avec l\u2019ambition de devenir le premier partenaire Europ\u00e9en et en Afrique Francophone avec sa forte pr\u00e9sence au Maroc.\nN\u00e9s du rapprochement de 2 leaders sp\u00e9cialistes de l\u2019int\u00e9gration des solutions Microsoft, nous allions expertise technique et fonctionnelle pour r\u00e9pondre concr\u00e8tement aux enjeux de demain : acc\u00e9l\u00e9ration de la transformation digitale, CyberS\u00e9curit\u00e9, Intelligence Artificielle, IoT, Data, transformation vers le cloud Azure, Services Cognitifs et Intelligence Artificielle\u2026\nEn rejoignant la communaut\u00e9 Exakis Nelite dans l\u2019une de nos 15 agences, vous int\u00e9grerez une \u00e9quipe passionn\u00e9e et impliqu\u00e9e dans les projets les plus innovants. Vous rejoindrez une structure construite autour de valeurs tourn\u00e9es vers ses collaborateurs : intelligence collective, convivialit\u00e9 et bienveillance.\nA la pointe des nouvelles technologies, vous int\u00e9grerez la communaut\u00e9 Modern Apps pour accompagner les grands comptes d'Aix-en-Provence dans leur strat\u00e9gie digitale et l\u2019adoption du cloud qui en d\u00e9coule.\nPoste et missions:\nEn tant qu\u2019Architecte Cloud Azure H/F, votre autonomie et votre force de proposition prendront toute leur ampleur en prenant en charge des missions d\u2019expertise ou des projets de plusieurs centaines de jours.\nVous travaillerez dans une ambiance conviviale, constructive, sereine, laissant une grande place \u00e0 l\u2019initiative et au d\u00e9veloppement personnel.\nSelon les missions vous serez amen\u00e9(e) \u00e0 :\nAccompagner nos clients dans leur strat\u00e9gie digitale\nAnimer des ateliers d\u2019architecture technique\nAppr\u00e9hender les besoins fonctionnels et les contraintes techniques du client\nPr\u00e9coniser des architectures complexes pour r\u00e9pondre \u00e0 une probl\u00e9matique ou un besoin m\u00e9tier\nD\u00e9finir et am\u00e9liorer les standards, patterns d\u2019architecture et le catalogue de services\nSuperviser et mettre en \u0153uvre, dans le cadre des projets, les pr\u00e9conisations techniques \u00e9tablies dans le cadre des cahiers des charges\nR\u00e9diger les documents associ\u00e9s (HLD, LLD, etc.)\nPiloter des projets et des hommes\nIntervenir en toute autonomie sur les phases de cadrage technique et/ou avant ventes\nAssurer une veille technologique\nComp\u00e9tences techniques attendues :\nBonne connaissance de la plateforme Azure dans son ensemble et de l\u2019\u00e9cosyst\u00e8me associ\u00e9.\nPlut\u00f4t DATA ?\nConnaissances requises :\nServices DATA dans Azure (DataFactory, Azure Synapse, Spark, Hadoop, etc.)\nBases de donn\u00e9es (SQL, MYSQL,\nDes probl\u00e9matiques de stockage et traitement de la donn\u00e9e dans Azure (Storage Account, Datalake store, Data Factory, Logic App)\n\u00ab Securit\u00e9 \u00bb de la donn\u00e9e dans Azure\nLa connaissance de la gestion des donn\u00e9es li\u00e9es \u00e0 l\u2019IOT dans Azure est un plus\nProfil :\nDe formation BAC+5, vous justifiez d'une exp\u00e9rience significative dans l'infrastructure informatique en cloud et notamment sur la plateforme Azure.\nBon(ne) communicant(e), vous \u00eates capable de vous adapter \u00e0 la fois au travail en \u00e9quipe et aux projets de nos clients.\nUne certaine aisance orale est indispensable. Un r\u00e9dactionnel de qualit\u00e9 est obligatoire. Une bonne maitrise de l\u2019anglais est obligatoire.\nExp\u00e9rience: minimum 5 ans\nAvantages :\nMutuelle prise en charge \u00e0 100%, t\u00e9l\u00e9travail, remboursement du titre de transport \u00e0 100%, primes de cong\u00e9s d'\u00e9t\u00e9, participation/int\u00e9ressement, avantages CSE.\nVous vous reconnaissez dans cette annonce? N'h\u00e9sitez pas \u00e0 postuler! Nous avons h\u00e2te de vous rencontrer!\nShow more\nShow less",
        "skills": {
            "ProgLanguage": [
                "R"
            ],
            "DataBase": [
                "SQL"
            ],
            "DataAnalytics": [
                "R"
            ],
            "BigData": [
                "Hadoop",
                "Spark"
            ],
            "MachingLearning": [],
            "DataSerialization": [],
            "DataVisualization": [],
            "Statistics": [],
            "CloudComputing": [
                "Azure"
            ],
            "DevTools": [
                "Git"
            ],
            "Os": [],
            "DBMS": [
                "MySQL"
            ],
            "SoftBigDataProcessing": [],
            "Automation": [],
            "InfrastructureAsCode": [],
            "NetworkSecurty": [],
            "Virtualisation": [],
            "Containers": [],
            "Collaboration": [],
            "Other": [
                "Cloud"
            ],
            "FrSoftSkills": [],
            "EnSoftSkils": [
                "Initiative"
            ]
        },
        "details": {
            "JobDetail": [],
            "TypeContract": [],
            "Salary": [],
            "Level": [
                "Bac+5"
            ],
            "Experience": [
                "a",
                "n",
                "s",
                "5",
                "5",
                "5"
            ]
        }
    },
    {
        "source": "LinkedIn",
        "title": "ARCHITECTE DATA (H/F)",
        "company": "Groupement des Mousquetaires",
        "location": "Vitr\u00e9, Brittany, France",
        "link": "https://fr.linkedin.com/jobs/view/architecte-data-h-f-at-groupement-des-mousquetaires-3889132514?position=48&pageNum=0&refId=a5rwPua%2FMvx%2F2M%2FPSF0oPA%3D%3D&trackingId=cmkYqYRJ7JbipE08px2xQQ%3D%3D&trk=public_jobs_jserp-result_search-card",
        "description": "Description De L'entreprise\nLe Groupement Les Mousquetaires, ce sont 7 enseignes de la grande distribution port\u00e9es haut et fort par plus de 3 000 chefs d\u2019entreprise ind\u00e9pendants ! Ce sont aussi 150 000 collaborateurs mobilis\u00e9s autour de notre mod\u00e8le \u00ab Producteurs et commer\u00e7ants \u00bb.\nDans toutes les fonctions au service des points de vente, de la logistique \u00e0 l\u2019immobilier, en passant par l\u2019industrie agroalimentaire ou l\u2019informatique, nos \u00e9quipes font nos succ\u00e8s.\nAgromousquetaires est le p\u00f4le industriel du Groupement Les Mousquetaires. Premier fabricant de marques de distributeurs en France.\nAgromousquetaires c'est avant tout 11 000 hommes et femmes aux sensibilit\u00e9s diverses, regroup\u00e9s au sein de 70 sites industriels et logistiques, dont une cinquantaine d'usines, et 6 P\u00f4les de Performance.\nNous rejoindre, c'est partager une culture commune, celle de l'entrepreneuriat et de l'engagement c\u2019est \u00eatre \u00ab Producteurs et Commer\u00e7ants \u00bb !\nAlors, pr\u00eat \u00e0 vous lancer au service du \u00ab Mieux Produire pour Mieux Vivre \u00bb ?\nAgroM Services h\u00e9berge \u00e0 l'AgroHub (35), \u00e0 Lanester (56) et au Parc de Tr\u00e9ville (91), l'ensemble des m\u00e9tiers transverses ayant vocation \u00e0 accompagner et r\u00e9pondre aux besoins op\u00e9rationnels de nos 6 p\u00f4les.\nVous souhaitez participer au d\u00e9veloppement d'un acteur majeur de la Grande Distribution en Europe sur un poste qui offre une forte exposition pour l'avenir du Groupe ? Alors cette opportunit\u00e9 pourrait vous int\u00e9resser. Seul distributeur \u00e0 \u00eatre \u00e0 la fois \u00ab Producteurs et Commer\u00e7ants \u00bb avec des gammes de produits de qualit\u00e9, dans des secteurs vari\u00e9s et 100% made in France.\nDescription Du Poste\nNous recherchons\nun(e) Architecte Data (H/F)\nPoste \u00e0 pourvoir en CDI sur notre site bas\u00e9 \u00e0 Vitr\u00e9 (35)\nRattach\u00e9(e) au Responsable D\u00e9partement Data & Analytics, vous serez en charge de concevoir, d\u00e9velopper et maintenir notre architecture de donn\u00e9es, en veillant \u00e0 garantir l\u2019int\u00e9grit\u00e9, la disponibilit\u00e9 et la confidentialit\u00e9 des donn\u00e9es.\nVos missions seront les suivantes :\nD\u00e9finir notre strat\u00e9gie d\u2019architecture des donn\u00e9es sur l\u2019alimentation, la transformation, la mod\u00e9lisation, jusqu\u2019\u00e0 l\u2019exposition des donn\u00e9es pour les usages tiers (BI notamment)\n\u00catre garant de la mod\u00e9lisation de notre patrimoine de donn\u00e9es au sein de la plateforme data Cloud\nAdministrer notre plateforme de donn\u00e9es sous GCP\nD\u00e9finir et mettre en \u0153uvre une strat\u00e9gie FinOps\nD\u00e9velopper ou faire d\u00e9velopper \u00e0 l\u2019\u00e9quipe Flux Inter-Applicatifs les jobs ETL d\u2019alimentation et de transformation de donn\u00e9es sous Talend\nD\u00e9finir les missions et piloter les Prestataires informatiques intervenant sur notre plateforme de donn\u00e9es\nCommuniquer notre strat\u00e9gie data au sein de l\u2019entreprise\nDocumenter ou s\u2019assurer que la documentation a \u00e9t\u00e9 r\u00e9alis\u00e9e\nCollaborer sur les diff\u00e9rents projets applicatifs n\u00e9cessitant de stocker de la donn\u00e9e\nContribuer au plan de transformation sur la gouvernance de la donn\u00e9e, comprenant le traitement de la qualit\u00e9 des donn\u00e9es\nPrendre en compte les contraintes cybers\u00e9curit\u00e9 et de conformit\u00e9 r\u00e9glementaire (RGPD) dans la conception des architectures\nS\u2019assurer que toute solution mise en \u0153uvre respecte la strat\u00e9gie du d\u00e9partement Data & Analytics, et plus g\u00e9n\u00e9ralement de la DSI\nRespecter les m\u00e9thodologies projet en vigueur et \u00e9tablies par le d\u00e9partement SI Gouvernance\nAssurer une veille technologique autour des sujets traitant de la donn\u00e9e et \u00eatre force de proposition sur la transformation de nos usages data\nQualifications\nVous avez :\nUne formation sup\u00e9rieure de niveau Bac +5 en informatique ou sciences des donn\u00e9es, de type Master ou Dipl\u00f4me d'Ing\u00e9nieur.\nVous disposez d'une exp\u00e9rience similaire de minimum 3 ans.\nVous devrez :\nAvoir de solides connaissances sur la plateforme Google Cloud Platform (Big Query, GCS notamment)\nMa\u00eetriser des outils et technologies li\u00e9s \u00e0 la gestion des donn\u00e9es, tels que les bases de donn\u00e9es, les entrep\u00f4ts de donn\u00e9es, les outils ETL (Talend de pr\u00e9f\u00e9rence), \u2026\nUtiliser des m\u00e9thodes de mod\u00e9lisations (UML, BPMN ou \u00e9quivalent).\nSavoir travailler en \u00e9quipe, et collaboration avec les parties prenantes,\nR\u00e9diger de mani\u00e8re claire et concise,\nAvoir une bonne communication orale et \u00e9crite\nVotre rigueur, votre adaptabilit\u00e9, votre sens de l\u2019\u00e9coute, votre relationnel et votre proactivit\u00e9 (et oui rien que \u00e7a \ud83d\ude0a), vous permettront de mener \u00e0 bien ces missions !\nInformations suppl\u00e9mentaires\nVous vous reconnaissez sur ce poste ?\nAlors postulez et discutons de votre avenir !\nVous devrez r\u00e9aliser votre travail dans une ambiance agr\u00e9able, accompagn\u00e9s de coll\u00e8gues sympathiques et \u00e7a en seulement 3 jours de pr\u00e9sence obligatoire sur site (2 jours de t\u00e9l\u00e9travail possible apr\u00e8s 2 mois d\u2019anciennet\u00e9 dans le groupe).\nAGROMOUSQUETAIRES s'engage \u00e0 promouvoir la diversit\u00e9, notamment en favorisant l'emploi de Travailleurs en situation de Handicap.\nAGROMOUSQUETAIRESRECRUTE\nShow more\nShow less",
        "skills": {
            "ProgLanguage": [
                "R",
                "Go"
            ],
            "DataBase": [],
            "DataAnalytics": [
                "R"
            ],
            "BigData": [],
            "MachingLearning": [],
            "DataSerialization": [],
            "DataVisualization": [],
            "Statistics": [],
            "CloudComputing": [
                "Google Cloud Platform"
            ],
            "DevTools": [],
            "Os": [],
            "DBMS": [
                "Big Query"
            ],
            "SoftBigDataProcessing": [],
            "Automation": [
                "Chef"
            ],
            "InfrastructureAsCode": [],
            "NetworkSecurty": [],
            "Virtualisation": [],
            "Containers": [],
            "Collaboration": [],
            "Other": [
                "ML",
                "Cloud"
            ],
            "FrSoftSkills": [
                "Communication",
                "Adaptabilit\u00e9",
                "Collaboration"
            ],
            "EnSoftSkils": [
                "Communication",
                "Collaboration"
            ]
        },
        "details": {
            "JobDetail": [],
            "TypeContract": [
                "CDI"
            ],
            "Salary": [],
            "Level": [],
            "Experience": [
                "a",
                "n",
                "s",
                "3",
                "3",
                "3"
            ]
        }
    },
    {
        "source": "LinkedIn",
        "title": "Architecte Data - Aix-en-provence",
        "company": "Capgemini",
        "location": "Aix-en-Provence, Provence-Alpes-C\u00f4te d'Azur, France",
        "link": "https://fr.linkedin.com/jobs/view/architecte-data-aix-en-provence-at-capgemini-3822433643?position=49&pageNum=0&refId=a5rwPua%2FMvx%2F2M%2FPSF0oPA%3D%3D&trackingId=ljqGAvYAe8YRObUU%2FcFj8A%3D%3D&trk=public_jobs_jserp-result_search-card",
        "description": "Choisir Capgemini, c'est choisir une entreprise o\u00f9 vous serez en mesure de fa\u00e7onner votre carri\u00e8re selon vos aspirations. Avec le soutien et l'inspiration d\u2019une communaut\u00e9 d\u2019experts dans le monde entier, o\u00f9 vous pourrez r\u00e9\u00e9crire votre futur. Rejoignez-nous pour red\u00e9finir les limites de ce qui est possible, contribuer \u00e0 lib\u00e9rer la valeur de la technologie pour les plus grandes organisations et participer \u00e0 la construction d\u2019un monde plus durable et inclusif.\nVOS MISSIONS\n\u2022 Pr\u00e9coniser une architecture et des technologies\n\u2022 Elaborer des standards technologies internes\n\u2022 Garantir la coh\u00e9rence technique de la solution et son \u00e9volution\n\u2022 Prototyper les solutions techniques pr\u00e9conis\u00e9es\n\u2022 Assister l'\u00e9quipe de d\u00e9veloppement dans la mise en \u0153uvre des solutions techniques pr\u00e9conis\u00e9es \u2022 D\u00e9velopper des composants techniques\n\u2022 Encadrer les \u00e9quipes de consultants gr\u00e2ce \u00e0 la formation et le coaching\nDans votre quotidien, vous contribuerez au partage et \u00e0 la capitalisation des savoirs et des pratiques au sein de la Communaut\u00e9 des Architectes de Capgemini.\nVous participerez \u00e0 la construction de points de vue par l'exp\u00e9rience et le savoir-faire reconnu dans un domaine technique\nL\u2019ENVIRONNEMENT TECHNIQUE\nDataHub :\n\u2022 ETL (Talend, Informatica ou SSIS),\n\u2022 Traitement de donn\u00e9es Spark, Python, Scala\u2026\n\u2022 Bases de donn\u00e9es (Oracle, SQL Server, Postgres),\n\u2022 Datalake / Big Data : Horton Works, Cloudera, ELK,\u2026\nData Viz & IA / Machine Learning :\n\u2022 Qlik, Tableau\n\u2022 Python, R\u2026\nVOTRE PROFIL\n\u2022 De formation sup\u00e9rieure, vous justifiez d'une exp\u00e9rience reconnue (6 \u00e0 10 ans) sur des projets de cadrage ou de mise en \u0153uvre d\u2019applications / d\u2019architectures visant \u00e0 collecter, stocker, raffiner et valoriser les donn\u00e9es ;\n\u2022 Vous \u00eates habitu\u00e9 \u00e0 travailler dans des contextes Agile et DevOps.Vous avez c\u00f4toy\u00e9 une/des d\u00e9marches de transformation SI (SOA, CLOUD, BigData, CLIENT/SERVEUR, EIM, \u2026) et une/des m\u00e9thodologies d'architecture des SI (TOGAF, IAF)\n\u2022 Vous ma\u00eetrisez l'anglais \u00e0 l'oral et \u00e0 l'\u00e9crit\n3 RAISONS DE NOUS REJOINDRE :\nQualit\u00e9 de vie au travail\n: accord de t\u00e9l\u00e9travail en France et \u00e0 l\u2019international, accord sur l\u2019\u00e9galit\u00e9 professionnelle, la parentalit\u00e9, l\u2019\u00e9quilibre des temps et la mobilit\u00e9 durable.\nApprentissage en continu\n: certifications et formations en libre acc\u00e8s, accompagnement sur mesure avec votre career manager, parcours d\u2019int\u00e9gration sur 9 mois.\nAvantages groupe & CSE\n: plan actionnariat, tarif pr\u00e9f\u00e9rentiels, remboursement partiel vacances, remboursement de votre abonnement sportif ou culturel.\nNOS ENGAGEMENTS ET PRIORITES :\nLe groupe Capgemini encourage une culture inclusive dans un cadre multiculturel et handi-accueillant. En nous rejoignant, vous int\u00e9grez un collectif qui valorise la diversit\u00e9, d\u00e9veloppe le potentiel de ses talents, s\u2019engage dans des initiatives solidaires avec ses partenaires, et se mobilise pour r\u00e9duire son impact environnemental sur tous ses sites et aupr\u00e8s de ses clients.\nA PROPOS DE CAPGEMINI :\nCapgemini est un leader mondial, responsable et multiculturel, regroupant pr\u00e8s de 350 000 personnes dans plus de 50 pays. Fort de 55 ans d\u2019exp\u00e9rience, nous sommes un partenaire strat\u00e9gique des entreprises pour la transformation de leurs activit\u00e9s en tirant profit de toute la puissance de la technologie et des innovations dans les domaines en perp\u00e9tuelle \u00e9volution tels que le cloud, la data, l\u2019Intelligence Artificielle, la connectivit\u00e9, les logiciels, l\u2019ing\u00e9nierie digitale ou les plateformes.\nGet The Future You Want* | www.capgemini.com/fr-fr\n*Capgemini, le futur que vous voulez\nShow more\nShow less",
        "skills": {
            "ProgLanguage": [
                "Python",
                "Scala",
                "R"
            ],
            "DataBase": [
                "SQL"
            ],
            "DataAnalytics": [
                "R"
            ],
            "BigData": [
                "Spark"
            ],
            "MachingLearning": [],
            "DataSerialization": [],
            "DataVisualization": [
                "Tableau"
            ],
            "Statistics": [],
            "CloudComputing": [],
            "DevTools": [
                "Git"
            ],
            "Os": [],
            "DBMS": [
                "Oracle",
                "SQL Server"
            ],
            "SoftBigDataProcessing": [],
            "Automation": [],
            "InfrastructureAsCode": [],
            "NetworkSecurty": [],
            "Virtualisation": [],
            "Containers": [],
            "Collaboration": [],
            "Other": [
                "DevOps",
                "Big Data",
                "Machine Learning",
                "Cloud"
            ],
            "FrSoftSkills": [
                "Organisation"
            ],
            "EnSoftSkils": [
                "Initiative"
            ]
        },
        "details": {
            "JobDetail": [],
            "TypeContract": [],
            "Salary": [],
            "Level": [],
            "Experience": [
                "a",
                "n",
                "s",
                "10",
                "10",
                "10"
            ]
        }
    },
    {
        "source": "LinkedIn",
        "title": "Data Architect m/f",
        "company": "HP",
        "location": "Grenoble, Auvergne-Rh\u00f4ne-Alpes, France",
        "link": "https://fr.linkedin.com/jobs/view/data-architect-m-f-at-hp-3903406324?position=50&pageNum=0&refId=a5rwPua%2FMvx%2F2M%2FPSF0oPA%3D%3D&trackingId=40S%2FgOr47a%2BHSzAk7zUjAw%3D%3D&trk=public_jobs_jserp-result_search-card",
        "description": "Who we are?\nHP creates new possibilities for technology to have a meaningful impact on people, businesses, governments and society. The world\u2019s largest technology company and ranked 10 on the Fortune 500 list for 2012, HP brings together a portfolio that spans printing, personal computing, software, services and IT infrastructure to serve more than 1 billion customers in over 170 countries on six continents.\nHP invents, engineers, and delivers technology solutions that drive business value, create social value, and improve the lives of our clients. At HP, we know that our people and values are the most important elements in this success. And we want you to add your voice and imagination to our mission.\nDiversity drives our innovation engine\nDiverse teams create transformative solutions that better serve our customers and advance how the world works and lives.\nWe\u2019re reinventing the standard for diversity and inclusion \u2014 in how we operate as a company and impact society. Diversity is embedded in all we do, and every HP employee at every level plays a part. By valuing differences, we engage top industry talent to drive our company\u2019s long-term success.\nWhat can we do together?\nIn the GTM advanced analytics COE, our mission is to deliver impact by building machine learning (ML) products to optimize pricing, marketing investments and provide guidance to sales and other HP teams.\nWe are looking for a Data Architect / Senior Data Engineer to join our data engineering team. If you are passionate about solving problems and making improvements through data and technology, we are eager to talk to you. The ideal candidate has both a willingness and desire to work in a dynamic environment, is able to apply Agile methodologies in day-to-day activities, and is a self-motivated developer who also enjoys working in a team environment. Our people have a creative, innovative, fun, and collaborative attitude, and are dedicated to creating new and valuable solutions for HP.\nThe data engineering architect applies developed subject matter knowledge to solve common and complex business issues within established guidelines and recommends appropriate alternatives.\nWorks on problems of diverse complexity and scope.\nMay act as a team or project leader providing direction to team activities and facilitates information validation and team decision making process.\nExercises independent judgment within generally defined policies and practices to identify and select a solution.\nAbility to handle most unique situations.\nMay seek advice in order to make decisions on complex business issues.\nWho you are?\n3+ years of experience in software or data engineering architecture.\nProficient in data modeling, data integration and processing of structured and unstructured data.\nProficient in one or more programming languages (Python preferred).\nStrong SQL proficiency (experience with NoSQL \u2013 advantage).\nExperienced with Apache Spark / pyspark\nExcellent communication skills; mastery in English and local language.\nAbility to effectively communicate product architectures, design and change proposals.\nAdditional Preferred Qualifications Advantages\nDatabricks\nPandas\nFamiliar with best practices of the data and software engineering lifecycle and/or best practices of the above platforms and tools.\nDataiku DSS\nWhy joining HP France?\nAt HP France, you will be immersed in an inspiring workplace where all our people love to be, collaborate well together and where they can learn, grow and develop professionally as well as personally. We offer empowering responsibilities. You will have the opportunity to evolve through your commitment, your skills and your sense of initiative! This position can be the 1st step in a great career within our teams!\nJoining us also means a great work-life balance and benefits such as meal vouchers, discounts on HP products and more! Driven by a strong corporate culture, our employees are involved in numerous initiatives through internal networks (Next Gen, Women@hp, workplace well-being team, ect.) and external volunteering (Nos Quartiers ont du Talent, Hour of Code).\nHP is also committed to an equal opportunities policy, from recruitment to career development. Job offers are open to all, including people with disabilities.\nOur promise: To create a diverse and inclusive working environment! So, what are you waiting for?\nThis role is based in Grenoble (38) within our international skills and expertise center. We offer a collaborative, stimulating and ultra-connected working environment in the heart of the mountains and just a 10 minute walk from the train station.\nShow more\nShow less",
        "skills": {
            "ProgLanguage": [
                "Python",
                "R",
                "Go"
            ],
            "DataBase": [
                "SQL",
                "NoSQL"
            ],
            "DataAnalytics": [
                "Pandas",
                "R"
            ],
            "BigData": [
                "Spark",
                "Databricks"
            ],
            "MachingLearning": [],
            "DataSerialization": [],
            "DataVisualization": [],
            "Statistics": [],
            "CloudComputing": [],
            "DevTools": [],
            "Os": [],
            "DBMS": [],
            "SoftBigDataProcessing": [],
            "Automation": [],
            "InfrastructureAsCode": [],
            "NetworkSecurty": [],
            "Virtualisation": [],
            "Containers": [],
            "Collaboration": [
                "Teams"
            ],
            "Other": [
                "ML",
                "Machine Learning"
            ],
            "FrSoftSkills": [
                "Communication"
            ],
            "EnSoftSkils": [
                "Communication",
                "Initiative"
            ]
        },
        "details": {
            "JobDetail": [
                "Senior"
            ],
            "TypeContract": [],
            "Salary": [],
            "Level": [],
            "Experience": [
                "a",
                "n",
                "s"
            ]
        }
    },
    {
        "source": "LinkedIn",
        "title": "Frontend Architect F/M/X",
        "company": "Mars",
        "location": "Aimargues, Occitanie, France",
        "link": "https://fr.linkedin.com/jobs/view/frontend-architect-f-m-x-at-mars-3914282604?position=51&pageNum=0&refId=a5rwPua%2FMvx%2F2M%2FPSF0oPA%3D%3D&trackingId=4YR1fYkda7creVM7OiFI5Q%3D%3D&trk=public_jobs_jserp-result_search-card",
        "description": "Job Description\nLocalisation:\nAimargues (30 minutes from Montpellier)\nType of contract:\npermanent contract\nTo achieve its ambition to be the reference in pet health through nutrition, Royal Canin wants to continue to push the barriers of nutrition and individualization.\nThe digital transformation is driving both new opportunities to serve more pets but also new challenges for our existing business models. Join the Royal Canin Digital Factory to participate to this transformation. You will join a multi-cultural, dynamic and caring team working all together and closely on all the digital projects of the brand. Royal Canin's Digital Factory is key in achieving this strategy through the multiplicity of its practices: UX/UI, Development, Product Ownership, Market deployment, Architecture, Governance...\nWhile the team will develop new digitally enabled business models that will shape the future of Royal Canin and Eukanuba, they also support the transformation of our existing business models.\nIn This Digital Acceleration Context, Royal Canin Needs To Reinforce Its Internal Strengths With Digital, User Centric And Data Capabilities. Based In Aimargues, This Job Will Sit In Our Digital Factory, Which Mission Are To\nDevelop our Service-driven and digital platforms supporting \u201cPet Health Guardians\u201d\nDevelop our key capabilities on Design Thinking, UX, Agile Management, Mobile/Web/Ecommerce development, Digital Platform deployment and Data-driven transformation.\nLeverage those capabilities to design and build our future Business Models\nHelp in acquiring data and driving traffic to our owned assets, which will help transform data collected into digital performance metrics and business insights.\nPush from global to deploy@ scale and pull from local to global synergy\nThe Digital factory, as part of the Direct to Pet Owner organization, works in strong partnership with Marketing and sales team and Innovation team.\nReporting to the Develop Factory Lead, we are hiring a\nFrontend Architect\n, who will define and drive the frontend technology strategy across the Digital Factory to support the organization ambitions.\nWhat are we looking for ?\n7 to 15 years' experience in Frontend Development for digital environment\nManagement of complex technical projects on an international level & in Agile methodology (Scrum, Kanban, SAFe)\nAbility to work with different teams and various team dynamics to achieve challenging delivery objectives\nLead of technical teams with external and internal actors\nFast Learner, Influencing and negotiations skills\nFluent in English\nWhat will be your key responsibilities ?\nThe role of\nFrontend Architect\nfor Supervision Angular/React Developers entails leading, guiding, and supervising multiple development teams working on projects utilizing Node.js, Angular, and/or React technologies. The\nFrontend Architect\nplays a crucial role in designing and implementing robust and scalable technical solutions, ensuring the quality, performance, and consistency of the developed applications.\nLeadership\nAs\nFrontend Architect\n, you will have to:\nHe/she can establish the software architecture of his/her project or steer it in a different direction, in alignment with the technical direction of the project.\nHe/she oversees the quality of what is produced by his/her team.\nHe/she communicates on technical matters, leveraging his/her expertise and contributing to the visibility of his/her team's expertise.\nThe Architect is the technical lead of the project. He/she ensures internal coordination between his teams and other teams involved in the project.\nHe/she ensures the flow of information and validates, if necessary, the various technical actions to be taken.\nHe/she can propose the right design based on functional and business challenges, and he advocates for his choices in front of the stakeholders.\nTechnical Leadership: Lead and mentor multiple development teams in designing, implementing, and maintaining software solutions based on Angular, and/or React.\nSystem Architecture: Design and define the technical architecture of applications, ensuring scalability, security, and performance.\nCollaboration: Collaborate closely with development teams, Delivery Leads, and PO to understand business requirements and define appropriate technical solutions.\nStandards and Best Practices: Establish and enforce coding standards, best practices, and development conventions within the teams.\nRisk Management: Identify and mitigate technical risks throughout the development lifecycle.\nMeetings\nSynchronization with frontend lead devs of all product squads\nTechnical retrospective: Once per sprint, exchange with the entire DEV team on technical improvements => Deliverables are technical tickets to be included in sprints (optional guest), leads must document decisions with CRs\nBack and Front Design Authority (weekly)\nSynchronization with front and back teams (sharing new topics, roadmaps, ..)\nSynchronization with DevOps\nWhat can you expect from Mars?\nAt Mars, we believe in a relationship of mutual trust, dignity and respect between our company and Associates that is more meaningful than the standard employer/employee relationship.\nAs Associates, we can expect to be respected, supported and valued as individuals, to be treated fairly and equitably.\nAn environment where you are empowered to be proactive and to take initiatives to make a difference.\nYou will work in a multicultural environment (more than 40 nationalities) and where your dog will be welcomed by more than 100 other Associates\u2019 dogs at the office!\nA unique and ideal work environment to become the leader in health through nutrition for cats and dogs!\nMars is an equal opportunity employer and all qualified applicants will receive consideration for employment without regard to race, color, religion, sex, sexual orientation, gender identity, national origin, disability status, protected veteran status, or any other characteristic protected by law. If you need assistance or an accommodation during the application process because of a disability, it is available upon request. The company is pleased to provide such assistance, and no applicant will be penalized as a result of such a request.\nShow more\nShow less",
        "skills": {
            "ProgLanguage": [
                "Scala",
                "R",
                "Go"
            ],
            "DataBase": [],
            "DataAnalytics": [
                "R"
            ],
            "BigData": [],
            "MachingLearning": [],
            "DataSerialization": [],
            "DataVisualization": [],
            "Statistics": [],
            "CloudComputing": [],
            "DevTools": [
                "Git"
            ],
            "Os": [],
            "DBMS": [],
            "SoftBigDataProcessing": [],
            "Automation": [],
            "InfrastructureAsCode": [],
            "NetworkSecurty": [],
            "Virtualisation": [],
            "Containers": [],
            "Collaboration": [
                "Teams"
            ],
            "Other": [
                "DevOps"
            ],
            "FrSoftSkills": [
                "Leadership",
                "Collaboration"
            ],
            "EnSoftSkils": [
                "Leadership",
                "Collaboration",
                "Organization",
                "Initiative"
            ]
        },
        "details": {
            "JobDetail": [],
            "TypeContract": [],
            "Salary": [],
            "Level": [],
            "Experience": [
                "a",
                "n",
                "s"
            ]
        }
    },
    {
        "source": "LinkedIn",
        "title": "Architecte data F/H - Syst\u00e8me, r\u00e9seaux, donn\u00e9es (H/F)",
        "company": "University of Strasbourg",
        "location": "Strasbourg, Grand Est, France",
        "link": "https://fr.linkedin.com/jobs/view/architecte-data-f-h-syst%C3%A8me-r%C3%A9seaux-donn%C3%A9es-h-f-at-university-of-strasbourg-3912809071?position=52&pageNum=0&refId=a5rwPua%2FMvx%2F2M%2FPSF0oPA%3D%3D&trackingId=RVJPCVX4Zg3%2B7sxclxk9CQ%3D%3D&trk=public_jobs_jserp-result_search-card",
        "description": "Cette offre d\u2019emploi est fournie par P\u00f4le emploi\nDescription\nDescriptif du poste: Emploi ouvert aux agents contractuels uniquement CDD de projet de 3 ans \u00e0 compter du 10/06/2024 Cat\u00e9gorie : A Corps : Ing\u00e9nieur d'\u00e9tudes R\u00e9mun\u00e9ration selon grille de la Fonction Publique La fiche de poste d\u00e9taill\u00e9e est disponible sur le site de l'Universit\u00e9. Mission : L'architecte data aura pour principale mission d'optimiser les process de collecte de donn\u00e9es issues des syst\u00e8mes d'information des partenaires du P\u00f4le Universitaire d'Innovation Alsace (PUI-A) et les bases de donn\u00e9es disponibles en \u00ab open data \u00bb, en vue d'assurer le d\u00e9ploiement de la d\u00e9marche de pilotage strat\u00e9gique et op\u00e9rationnel par la donn\u00e9e mise en \u0153uvre dans le cadre du projet PUI-A. Activit\u00e9s principales : * Cartographier les donn\u00e9es disponibles au sein des syst\u00e8mes d'informations des membres fondateurs du PUI-A et des bases de donn\u00e9es utiles aux activit\u00e9s du PUI-A notamment accessibles en \u00ab open data \u00bb * D\u00e9finir et mettre en place les normes, m\u00e9thodes, proc\u00e9dures, outils et r\u00e9f\u00e9rentiels de collecte et de gestion de donn\u00e9es * Concevoir une approche de regroupement et d'organisation des donn\u00e9es collect\u00e9es. Activit\u00e9s associ\u00e9es : * Contribuer aux travaux d'exploitation des donn\u00e9es * Contribuer \u00e0 l'\u00e9laboration des outils de pilotage strat\u00e9gique et op\u00e9rationnel par la donn\u00e9e du PUI-A. Contact pour renseignements sur le poste : David-Alexandre BONNE, Responsable du P\u00f4le Universitaire d'Innovation Alsace Profil recherch\u00e9: Profil recherch\u00e9 : Formation Bac+5 \u00e0 Bac+8 dans un des domaines en lien avec le poste (statistique, \u00e9conom\u00e9trie, math\u00e9matiques, informatique, traitement de l'information). Connaissances : * Architecture et environnement technique d'un syst\u00e8me d'information * Outils de gestion (ex. SQL, ETL) et d'exploitation (ex. R, Python) de bases de donn\u00e9es * Techniques statistiques et informatiques de collecte et de traitement de donn\u00e9es * M\u00e9thodes, outils, normes et proc\u00e9dures de la qualit\u00e9 * M\u00e9thodologie de conduite de projet * Organisation et fonctionnement de l'enseignement sup\u00e9rieur et de la recherche, ainsi que des \u00e9cosyst\u00e8mes de recherche et d'innovation (en Alsace ou dans d'autres territoires) * Langue anglaise : B2 \u00e0 C1 (cadre europ\u00e9en commun de r\u00e9f\u00e9rence pour les langues). Comp\u00e9tences op\u00e9rationnelles : * Piloter un projet * Construire et g\u00e9rer une base de donn\u00e9es * R\u00e9diger la documentation fonctionnelle et technique pour les utilisateurs * G\u00e9rer la s\u00e9curit\u00e9 de l'information * Mettre au point ou adapter des techniques nouvelles, notamment d'automatisation * Apporter des r\u00e9ponses \u00e0 des besoins sp\u00e9cifiques * Accompagner et conseiller * Communiquer et faire preuve de p\u00e9dagogie * Travailler en \u00e9quipe. Comp\u00e9tences comportementales : * Capacit\u00e9 de conceptualisation * Cr\u00e9ativit\u00e9 : sens de l'innovation * Sens de l'initiative * Rigueur * Curiosit\u00e9 intellectuelle et ouverture d'esprit * Pers\u00e9v\u00e9rance * Capacit\u00e9 d'adaptation * Sens de l'organisation * Sens relationnel * Capacit\u00e9 d'\u00e9coute.\nPROFIL SOUHAIT\u00c9\nExp\u00e9rience\nD\u00e9butant accept\u00e9\nSource: Pole emploi (https://www.pole-emploi.fr)\nShow more\nShow less",
        "skills": {
            "ProgLanguage": [
                "Python",
                "R",
                "Go"
            ],
            "DataBase": [
                "SQL"
            ],
            "DataAnalytics": [
                "R"
            ],
            "BigData": [],
            "MachingLearning": [],
            "DataSerialization": [],
            "DataVisualization": [],
            "Statistics": [
                "Statistiques"
            ],
            "CloudComputing": [],
            "DevTools": [],
            "Os": [],
            "DBMS": [],
            "SoftBigDataProcessing": [],
            "Automation": [],
            "InfrastructureAsCode": [],
            "NetworkSecurty": [],
            "Virtualisation": [],
            "Containers": [],
            "Collaboration": [],
            "Other": [
                "Statistiques"
            ],
            "FrSoftSkills": [
                "Cr\u00e9ativit\u00e9",
                "Organisation"
            ],
            "EnSoftSkils": [
                "Initiative"
            ]
        },
        "details": {
            "JobDetail": [],
            "TypeContract": [
                "CDD"
            ],
            "Salary": [],
            "Level": [
                "Bac+5"
            ],
            "Experience": [
                "a",
                "n",
                "s",
                "3",
                "3",
                "3"
            ]
        }
    },
    {
        "source": "LinkedIn",
        "title": "Data Architect Talend / BI",
        "company": "FRG Technology Consulting",
        "location": "Paris, \u00cele-de-France, France",
        "link": "https://fr.linkedin.com/jobs/view/data-architect-talend-bi-at-frg-technology-consulting-3908855754?position=53&pageNum=0&refId=a5rwPua%2FMvx%2F2M%2FPSF0oPA%3D%3D&trackingId=mF7ZBqw31ah5zMA856l4cg%3D%3D&trk=public_jobs_jserp-result_search-card",
        "description": "FRG Consulting est \u00e0 la recherche d'un Data Architect BI / Talend avec une solide ma\u00eetrise de Java pour rejoindre une \u00e9quipe bas\u00e9e dans le sud de Paris. Dans ce r\u00f4le, vous serez responsable de l'\u00e9valuation de l'architecture des donn\u00e9es et des bases de donn\u00e9es actuelles, ainsi que de la collecte, de l'organisation et de l'agr\u00e9gation des donn\u00e9es internes et externes pour les rendre accessibles.\nResponsabilit\u00e9s :\n\u00c9valuer l'architecture des donn\u00e9es et les bases de donn\u00e9es actuelles, y compris DataWarehouse, Datamart et les bases de donn\u00e9es tampons.\nCollecter, organiser et agr\u00e9ger les donn\u00e9es internes et externes en utilisant les meilleures pratiques ETL pour l'alimentation du DataWarehouse.\nD\u00e9finir et maintenir la cartographie des donn\u00e9es (applications, flux de donn\u00e9es) et assurer la coh\u00e9rence des donn\u00e9es.\nOptimiser l'utilisation, par les m\u00e9tiers, des services et solutions mis \u00e0 disposition par la DSI, en identifiant les opportunit\u00e9s de proposer de nouveaux produits ou services et en participant \u00e0 leur d\u00e9finition.\nParticiper \u00e0 la mise en place des projets en collectant les besoins exprim\u00e9s par les m\u00e9tiers, en traduisant ces besoins en sp\u00e9cifications techniques, mod\u00e8les de donn\u00e9es et user stories (avec une ma\u00eetrise des concepts Agile), et en accompagnant les projets dans la d\u00e9finition des besoins, la description et l'usage des donn\u00e9es en collaboration avec les \u00e9quipes DSI.\nS'assurer que les projets d\u00e9ploy\u00e9s par la DSI s'inscrivent dans la roadmap data et assurer un r\u00f4le de conseil aupr\u00e8s des \u00e9quipes DSI et m\u00e9tiers.\nR\u00e9aliser un suivi quotidien des performances et de l'efficacit\u00e9 des bases de donn\u00e9es.\nQualifications :\nExp\u00e9rience significative dans un poste similaire, avec une solide expertise en Java et Talend.\nConnaissance approfondie des bases de donn\u00e9es, des architectures de donn\u00e9es et des meilleures pratiques ETL.\nComp\u00e9tences avanc\u00e9es en analyse et mod\u00e9lisation de donn\u00e9es.\nExcellentes comp\u00e9tences en communication et en collaboration, avec la capacit\u00e9 de travailler efficacement avec des \u00e9quipes interfonctionnelles.\nMa\u00eetrise des concepts Agile et capacit\u00e9 \u00e0 travailler dans un environnement Agile.\nCapacit\u00e9 d\u00e9montr\u00e9e \u00e0 r\u00e9soudre des probl\u00e8mes complexes et \u00e0 prendre des d\u00e9cisions \u00e9clair\u00e9es.\nAutonomie, proactivit\u00e9 et capacit\u00e9 \u00e0 travailler de mani\u00e8re autonome tout en faisant partie d'une \u00e9quipe.\nShow more\nShow less",
        "skills": {
            "ProgLanguage": [
                "Java",
                "R"
            ],
            "DataBase": [],
            "DataAnalytics": [
                "R"
            ],
            "BigData": [],
            "MachingLearning": [],
            "DataSerialization": [],
            "DataVisualization": [],
            "Statistics": [],
            "CloudComputing": [],
            "DevTools": [],
            "Os": [],
            "DBMS": [],
            "SoftBigDataProcessing": [],
            "Automation": [],
            "InfrastructureAsCode": [],
            "NetworkSecurty": [],
            "Virtualisation": [],
            "Containers": [],
            "Collaboration": [],
            "Other": [],
            "FrSoftSkills": [
                "Communication",
                "Collaboration",
                "Organisation"
            ],
            "EnSoftSkils": [
                "Communication",
                "Collaboration"
            ]
        },
        "details": {
            "JobDetail": [],
            "TypeContract": [],
            "Salary": [],
            "Level": [],
            "Experience": [
                "a",
                "n",
                "s"
            ]
        }
    },
    {
        "source": "LinkedIn",
        "title": "Architecte Data-Model F/H",
        "company": "Schneider Electric",
        "location": "Lattes, Occitanie, France",
        "link": "https://fr.linkedin.com/jobs/view/architecte-data-model-f-h-at-schneider-electric-3864653832?position=54&pageNum=0&refId=a5rwPua%2FMvx%2F2M%2FPSF0oPA%3D%3D&trackingId=FuZ7MUBxPrGA%2B6wwUn0FZQ%3D%3D&trk=public_jobs_jserp-result_search-card",
        "description": "Missions\nEn tant qu\u2019 Architecte Data-Model, vous jouerez un r\u00f4le crucial dans le fa\u00e7onnement et l'optimisation de l'infrastructure de donn\u00e9es de notre produit. Vous serez responsable de la conception, de la mise en \u0153uvre et de la maintenance de solutions de donn\u00e9es \u00e9volutives et efficaces r\u00e9pondant aux besoins de l'entreprise. Ce r\u00f4le n\u00e9cessite une compr\u00e9hension approfondie de la gestion des donn\u00e9es et une vision strat\u00e9gique pour aligner l'architecture des donn\u00e9es avec les strat\u00e9gies commerciales globales :\nMod\u00e9lisation et Conception de Donn\u00e9es :\nVeiller \u00e0 la conformit\u00e9 de normes telles que l'IEC61850\nD\u00e9velopper et maintenir des mod\u00e8les de donn\u00e9es conceptuels, logiques et physiques\nConcevoir des structures de donn\u00e9es et des relations qui soutiennent les exigences commerciales et permettent une r\u00e9cup\u00e9ration efficace des donn\u00e9es\nGouvernance des Donn\u00e9es :\n\u00c9tablir et appliquer des politiques et proc\u00e9dures de gouvernance des donn\u00e9es\nD\u00e9finir les normes de donn\u00e9es, les conventions de d\u00e9nomination et les r\u00e8gles de qualit\u00e9 des donn\u00e9es\nInt\u00e9gration des Donn\u00e9es :\nConcevoir et mettre en \u0153uvre des solutions d'int\u00e9gration de donn\u00e9es pour assurer un flux d'informations transparent \u00e0 travers les syst\u00e8mes\nCollaborer avec d'autres \u00e9quipes informatiques pour int\u00e9grer les sources de donn\u00e9es\nCollaboration et Communication :\nTravailler en \u00e9troite collaboration avec les parties prenantes m\u00e9tier pour comprendre leurs besoins et les traduire en solutions de donn\u00e9es efficaces\nCollaborer avec des \u00e9quipes pluridisciplinaires, y compris des Analystes et des D\u00e9veloppeurs\nS\u00e9curit\u00e9 et Conformit\u00e9 :\nMettre en \u0153uvre des mesures de s\u00e9curit\u00e9 des donn\u00e9es pour prot\u00e9ger les informations sensibles\nFournir un leadership, des analyses et des t\u00e2ches de conception afin de garantir une application en phase avec la valeur commerciale attendue. Fournir des conseils en architecture et un soutien sur les activit\u00e9s r\u00e9alis\u00e9es pour maintenir et am\u00e9liorer les applications.\nProfil\nBac+5 minimum de type Ecole d\u2019Ing\u00e9nieur ou \u00e9quivalent en informatique, technologie de l'information ou domaine connexe\nAu moins 5 ans d'exp\u00e9rience en tant qu'Architecte de Donn\u00e9es ou dans un r\u00f4le similaire\nConnaissance de l'IEC61850\nSolide connaissance des syst\u00e8mes de gestion de bases de donn\u00e9es et des techniques de mod\u00e9lisation de donn\u00e9es\nCompr\u00e9hension des m\u00e9thodes et processus agiles, et capacit\u00e9 \u00e0 soutenir des \u00e9quipes de projet agiles\nCapacit\u00e9 d\u2019analyse et de synth\u00e8se, bon sens de la communication et de la collaboration\nCapacit\u00e9s de r\u00e9solution de probl\u00e8mes et de d\u00e9pannage\nRester en veille concernant les tendances \u00e9mergentes et technologies en gestion des donn\u00e9es\nPourquoi nous?\nSchneider Electric est la r\u00e9f\u00e9rence en mati\u00e8re de transformation num\u00e9rique de la gestion de l'\u00e9nergie et de l'automatisation. Nos technologies permettent au monde d'utiliser l'\u00e9nergie de mani\u00e8re s\u00fbre, efficace et durable. Nous nous effor\u00e7ons de promouvoir une \u00e9conomie mondiale \u00e0 la fois viable sur le plan \u00e9cologique et hautement productive.\n34 milliards d'euros de chiffre d'affaires global\n128 000+ employ\u00e9s dans plus de 100 pays\n45 % du chiffre d'affaires de l'IoT\n5 % du chiffre d'affaires consacr\u00e9 \u00e0 la R&D\nVous devez soumettre une demande en ligne pour que votre profil soit pris en consid\u00e9ration pour un poste chez nous. Ce poste sera visible jusqu'\u00e0 ce qu'il soit pourvu.\nSchneider Electric a pour politique de fournir des possibilit\u00e9s d'emploi et d'avancement \u00e9gales dans les domaines du recrutement, de l'embauche, de la formation, du transfert et de la promotion de toutes les personnes qualifi\u00e9es, quelle que soit leur race, religion, couleur, sexe, handicap, origine nationale, ascendance, \u00e2ge, statut militaire, orientation sexuelle, \u00e9tat matrimonial ou toute autre caract\u00e9ristique ou conduite l\u00e9galement prot\u00e9g\u00e9e. Agences concern\u00e9es : Schneider Electric n\u2019accepte pas de curriculum vit\u00e6 soumis de fa\u00e7on spontan\u00e9e et ne sera pas responsable des frais occasionn\u00e9s par de tels envois.\nShow more\nShow less",
        "skills": {
            "ProgLanguage": [
                "R",
                "Go"
            ],
            "DataBase": [],
            "DataAnalytics": [
                "R"
            ],
            "BigData": [],
            "MachingLearning": [],
            "DataSerialization": [],
            "DataVisualization": [],
            "Statistics": [],
            "CloudComputing": [],
            "DevTools": [],
            "Os": [],
            "DBMS": [],
            "SoftBigDataProcessing": [],
            "Automation": [],
            "InfrastructureAsCode": [],
            "NetworkSecurty": [],
            "Virtualisation": [],
            "Containers": [],
            "Collaboration": [],
            "Other": [],
            "FrSoftSkills": [
                "Communication",
                "R\u00e9solution de probl\u00e8mes",
                "Leadership",
                "Collaboration"
            ],
            "EnSoftSkils": [
                "Communication",
                "Leadership",
                "Collaboration"
            ]
        },
        "details": {
            "JobDetail": [],
            "TypeContract": [],
            "Salary": [],
            "Level": [
                "Bac+5"
            ],
            "Experience": [
                "a",
                "n",
                "s",
                "5",
                "5",
                "5"
            ]
        }
    },
    {
        "source": "LinkedIn",
        "title": "Frontend Architect F/M/X",
        "company": "Mars",
        "location": "Haguenau, Grand Est, France",
        "link": "https://fr.linkedin.com/jobs/view/frontend-architect-f-m-x-at-mars-3914284362?position=55&pageNum=0&refId=a5rwPua%2FMvx%2F2M%2FPSF0oPA%3D%3D&trackingId=GlRyZYi%2FaDs%2F1w84FA7kOw%3D%3D&trk=public_jobs_jserp-result_search-card",
        "description": "Job Description\nLocalisation:\nAimargues (30 minutes from Montpellier)\nType of contract:\npermanent contract\nTo achieve its ambition to be the reference in pet health through nutrition, Royal Canin wants to continue to push the barriers of nutrition and individualization.\nThe digital transformation is driving both new opportunities to serve more pets but also new challenges for our existing business models. Join the Royal Canin Digital Factory to participate to this transformation. You will join a multi-cultural, dynamic and caring team working all together and closely on all the digital projects of the brand. Royal Canin's Digital Factory is key in achieving this strategy through the multiplicity of its practices: UX/UI, Development, Product Ownership, Market deployment, Architecture, Governance...\nWhile the team will develop new digitally enabled business models that will shape the future of Royal Canin and Eukanuba, they also support the transformation of our existing business models.\nIn This Digital Acceleration Context, Royal Canin Needs To Reinforce Its Internal Strengths With Digital, User Centric And Data Capabilities. Based In Aimargues, This Job Will Sit In Our Digital Factory, Which Mission Are To\nDevelop our Service-driven and digital platforms supporting \u201cPet Health Guardians\u201d\nDevelop our key capabilities on Design Thinking, UX, Agile Management, Mobile/Web/Ecommerce development, Digital Platform deployment and Data-driven transformation.\nLeverage those capabilities to design and build our future Business Models\nHelp in acquiring data and driving traffic to our owned assets, which will help transform data collected into digital performance metrics and business insights.\nPush from global to deploy@ scale and pull from local to global synergy\nThe Digital factory, as part of the Direct to Pet Owner organization, works in strong partnership with Marketing and sales team and Innovation team.\nReporting to the Develop Factory Lead, we are hiring a\nFrontend Architect\n, who will define and drive the frontend technology strategy across the Digital Factory to support the organization ambitions.\nWhat are we looking for ?\n7 to 15 years' experience in Frontend Development for digital environment\nManagement of complex technical projects on an international level & in Agile methodology (Scrum, Kanban, SAFe)\nAbility to work with different teams and various team dynamics to achieve challenging delivery objectives\nLead of technical teams with external and internal actors\nFast Learner, Influencing and negotiations skills\nFluent in English\nWhat will be your key responsibilities ?\nThe role of\nFrontend Architect\nfor Supervision Angular/React Developers entails leading, guiding, and supervising multiple development teams working on projects utilizing Node.js, Angular, and/or React technologies. The\nFrontend Architect\nplays a crucial role in designing and implementing robust and scalable technical solutions, ensuring the quality, performance, and consistency of the developed applications.\nLeadership\nAs\nFrontend Architect\n, you will have to:\nHe/she can establish the software architecture of his/her project or steer it in a different direction, in alignment with the technical direction of the project.\nHe/she oversees the quality of what is produced by his/her team.\nHe/she communicates on technical matters, leveraging his/her expertise and contributing to the visibility of his/her team's expertise.\nThe Architect is the technical lead of the project. He/she ensures internal coordination between his teams and other teams involved in the project.\nHe/she ensures the flow of information and validates, if necessary, the various technical actions to be taken.\nHe/she can propose the right design based on functional and business challenges, and he advocates for his choices in front of the stakeholders.\nTechnical Leadership: Lead and mentor multiple development teams in designing, implementing, and maintaining software solutions based on Angular, and/or React.\nSystem Architecture: Design and define the technical architecture of applications, ensuring scalability, security, and performance.\nCollaboration: Collaborate closely with development teams, Delivery Leads, and PO to understand business requirements and define appropriate technical solutions.\nStandards and Best Practices: Establish and enforce coding standards, best practices, and development conventions within the teams.\nRisk Management: Identify and mitigate technical risks throughout the development lifecycle.\nMeetings\nSynchronization with frontend lead devs of all product squads\nTechnical retrospective: Once per sprint, exchange with the entire DEV team on technical improvements => Deliverables are technical tickets to be included in sprints (optional guest), leads must document decisions with CRs\nBack and Front Design Authority (weekly)\nSynchronization with front and back teams (sharing new topics, roadmaps, ..)\nSynchronization with DevOps\nWhat can you expect from Mars?\nAt Mars, we believe in a relationship of mutual trust, dignity and respect between our company and Associates that is more meaningful than the standard employer/employee relationship.\nAs Associates, we can expect to be respected, supported and valued as individuals, to be treated fairly and equitably.\nAn environment where you are empowered to be proactive and to take initiatives to make a difference.\nYou will work in a multicultural environment (more than 40 nationalities) and where your dog will be welcomed by more than 100 other Associates\u2019 dogs at the office!\nA unique and ideal work environment to become the leader in health through nutrition for cats and dogs!\nMars is an equal opportunity employer and all qualified applicants will receive consideration for employment without regard to race, color, religion, sex, sexual orientation, gender identity, national origin, disability status, protected veteran status, or any other characteristic protected by law. If you need assistance or an accommodation during the application process because of a disability, it is available upon request. The company is pleased to provide such assistance, and no applicant will be penalized as a result of such a request.\nShow more\nShow less",
        "skills": {
            "ProgLanguage": [
                "Scala",
                "R",
                "Go"
            ],
            "DataBase": [],
            "DataAnalytics": [
                "R"
            ],
            "BigData": [],
            "MachingLearning": [],
            "DataSerialization": [],
            "DataVisualization": [],
            "Statistics": [],
            "CloudComputing": [],
            "DevTools": [
                "Git"
            ],
            "Os": [],
            "DBMS": [],
            "SoftBigDataProcessing": [],
            "Automation": [],
            "InfrastructureAsCode": [],
            "NetworkSecurty": [],
            "Virtualisation": [],
            "Containers": [],
            "Collaboration": [
                "Teams"
            ],
            "Other": [
                "DevOps"
            ],
            "FrSoftSkills": [
                "Leadership",
                "Collaboration"
            ],
            "EnSoftSkils": [
                "Leadership",
                "Collaboration",
                "Organization",
                "Initiative"
            ]
        },
        "details": {
            "JobDetail": [],
            "TypeContract": [],
            "Salary": [],
            "Level": [],
            "Experience": [
                "a",
                "n",
                "s"
            ]
        }
    },
    {
        "source": "LinkedIn",
        "title": "Data Architect",
        "company": "FRG Technology Consulting",
        "location": "Paris, \u00cele-de-France, France",
        "link": "https://fr.linkedin.com/jobs/view/data-architect-at-frg-technology-consulting-3837380867?position=56&pageNum=0&refId=a5rwPua%2FMvx%2F2M%2FPSF0oPA%3D%3D&trackingId=kJraF7KaJQuIzQUTGcV6pw%3D%3D&trk=public_jobs_jserp-result_search-card",
        "description": "FRG recrute, pour l'un de ses clients un Data Architect. Notre client est une soci\u00e9t\u00e9 de conseil \u00e0 taille humaine, en pleine croissance, qui accompagne ses clients dans leur transformation num\u00e9rique.\nMissions principales\nConcevoir et mettre en \u0153uvre les plateformes Data\nD\u00e9velopper et maintenir l'architecture pour garantir une gestion efficace et s\u00e9curis\u00e9e des informations chez les clients\nMise en \u0153uvre des strat\u00e9gies de la plateforme Data\nElaboration et mise en \u0153uvre d'architecture Data\nAutomatisation et optimisation des op\u00e9rations de maintenance pour veiller \u00e0 l'am\u00e9lioration continue de l'efficacit\u00e9 des ressources sur les plateformes\nContribuer aux missions d'avant-vente : \u00e9tude de faisabilit\u00e9, \u00e9valuation d'impact\nProfil\n8 \u00e0 10 d'exp\u00e9rience dans l'IT dont 5 ans d'exp\u00e9rience sur l'un des Cloud Providers (AWS ; Azure ; GCP)\nExp\u00e9rience confirm\u00e9e dans l'impl\u00e9mentation des pratiques DevOps, la gestion de l'infrastructure et le d\u00e9ploiement de services dans le cloud\nMa\u00eetrise des technologies de gestion des donn\u00e9es (ETL...) et de la virtualisation des donn\u00e9es\nCertifications fortement appr\u00e9ci\u00e9es\nBonne communication \u00e0 l'oral et \u00e0 l'\u00e9crit, anglais courant\nShow more\nShow less",
        "skills": {
            "ProgLanguage": [
                "R"
            ],
            "DataBase": [],
            "DataAnalytics": [
                "R"
            ],
            "BigData": [],
            "MachingLearning": [],
            "DataSerialization": [],
            "DataVisualization": [],
            "Statistics": [],
            "CloudComputing": [
                "AWS",
                "Azure"
            ],
            "DevTools": [],
            "Os": [],
            "DBMS": [],
            "SoftBigDataProcessing": [],
            "Automation": [],
            "InfrastructureAsCode": [],
            "NetworkSecurty": [],
            "Virtualisation": [],
            "Containers": [],
            "Collaboration": [],
            "Other": [
                "DevOps",
                "Cloud"
            ],
            "FrSoftSkills": [
                "Communication"
            ],
            "EnSoftSkils": [
                "Communication"
            ]
        },
        "details": {
            "JobDetail": [
                "Confirm\u00e9"
            ],
            "TypeContract": [],
            "Salary": [],
            "Level": [],
            "Experience": [
                "a",
                "n",
                "s",
                "5",
                "5",
                "5"
            ]
        }
    },
    {
        "source": "LinkedIn",
        "title": "Architecte Avant-Vente Cloud Application, Data & Innovation (H/F)",
        "company": "EXAKIS NELITE",
        "location": "Aix-en-Provence, Provence-Alpes-C\u00f4te d'Azur, France",
        "link": "https://fr.linkedin.com/jobs/view/architecte-avant-vente-cloud-application-data-innovation-h-f-at-exakis-nelite-3904807120?position=57&pageNum=0&refId=a5rwPua%2FMvx%2F2M%2FPSF0oPA%3D%3D&trackingId=aX0ftkgaybh2MNefSEJg9A%3D%3D&trk=public_jobs_jserp-result_search-card",
        "description": "Exakis Nelite, entit\u00e9 du groupe Magellan Partners, est le premier partenaire pure-player Microsoft ind\u00e9pendant en France avec l\u2019ambition de devenir le premier partenaire Europ\u00e9en et en Afrique Francophone avec sa forte pr\u00e9sence au Maroc.\nN\u00e9s du rapprochement de 2 leaders sp\u00e9cialistes de l\u2019int\u00e9gration des solutions Microsoft, nous allions expertise technique et fonctionnelle pour r\u00e9pondre concr\u00e8tement aux enjeux de demain : acc\u00e9l\u00e9ration de la transformation digitale, transformation vers le cloud Azure, Services Cognitifs et Intelligence Artificielle\u2026\nEn rejoignant la communaut\u00e9 Exakis Nelite dans l\u2019une de nos 15 agences, vous int\u00e9grerez une \u00e9quipe passionn\u00e9e et impliqu\u00e9e dans les projets les plus innovants. Vous rejoindrez une structure construite autour de valeurs tourn\u00e9es vers ses collaborateurs : intelligence collective, convivialit\u00e9 et bienveillance.\nPoste et missions:\nVous \u00e9voluerez au sein de l\u2019Enterprise Solution Center (ESC) de la r\u00e9gion SUD pour relever de nouveaux d\u00e9fis autour des enjeux de d\u00e9veloppement Cloud et Digital.\nEn tant que Business Architect and Analyst, vous serez amen\u00e9 \u00e0 suivre et accompagner nos clients grands comptes sur leurs sujets de transformation digitale des processus m\u00e9tiers et sur la valorisation de leurs donn\u00e9es #Data. Vous les accompagnerez \u00e9galement lors des projets de migration vers ces nouvelles plateformes.\nVous accompagnerez le d\u00e9veloppement de la R\u00e9gion SUD sur ces enjeux en d\u00e9finissant les orientations, les offres, et les projets innovants.\nSelon les missions vous serez amen\u00e9 \u00e0 :\nAborder une posture de conseil pour accompagner nos clients strat\u00e9giques,\nD\u00e9finir les offres et propositions de valeurs qui feront le portefeuille de services autour de la transformation digitale vers le Cloud.\nAssurer le Bid Management des r\u00e9ponses commerciales au client,\nD\u00e9finir, choisir et argumenter des architectures applicatives et techniques,\nImaginer des sc\u00e9narios de valorisation des donn\u00e9es,\nConcevoir une architecture en ad\u00e9quation avec les besoins m\u00e9tier,\nPrendre en consid\u00e9ration les probl\u00e9matiques de performance et de s\u00e9curit\u00e9,\nAccompagner l\u2019int\u00e9gration des solutions dans le syst\u00e8me d\u2019information,\nR\u00e9aliser de la veille technologique sur les solutions et les innovations.\nAccompagner nos \u00e9quipes de Delivery et nos experts dans la prise en compte des nouveaux enjeux, des projets, et des solutions.\nParticiper et piloter les phases critiques des projets innovants,\nMettre en place des partenariats avec les acteurs cl\u00e9s du march\u00e9.\nProfil:\nDe formation BAC+5 id\u00e9alement en ing\u00e9nierie, vous justifiez d\u2019une exp\u00e9rience significative dans le d\u00e9veloppement de l\u2019infrastructure informatique en cloud et notamment sur la plateforme Azure \u00e0 forte valeur ajout\u00e9e.\nVous avez la capacit\u00e9 de :\nLeader les avant ventes structurantes\nProposer des orientations strat\u00e9giques autour des applications \u00e0 destination du Cloud public et de la gouvernance de la Data\nRelever des d\u00e9fis pour r\u00e9pondre aux enjeux des clients\n\u00catre force de proposition\nCoacher, animer, et suivre des consultants passionn\u00e9s\nBonne connaissance de la plateforme Azure dans son ensemble et de l\u2019\u00e9cosyst\u00e8me associ\u00e9.\nConnaissances requises :\nServices r\u00e9seaux dans Azure (VNet / Subnet, VPN S2S, ExpressRoute, Azure Firewall, Load Balancer, Application Gateway, Traffic Manager)\nAzure AD\nService machine virtuelle\nAutomatisation (mod\u00e8le de d\u00e9ploiement ARM et / ou Terraform, Ansible)\nConteneurisation (docker, Azure Container Instance, Azure Kubernetes Service)\nGouvernance dans Azure (Azure Policy, Azure tags, Azure Cost Management, etc.)\nAspects haute disponibilit\u00e9 et reprise d\u2019activit\u00e9 apr\u00e8s sinistre\nDou\u00e9(e) d\u2019un bon r\u00e9dactionnel, vous maitrisez l\u2019anglais \u00e0 l\u2019oral comme \u00e0 l\u2019\u00e9crit.\nUne exp\u00e9rience en ESN est indispensable !\nAvantages :\nMutuelle prise en charge \u00e0 100%, t\u00e9l\u00e9travail, remboursement du titre de transport \u00e0 100%, primes de cong\u00e9s d'\u00e9t\u00e9, participation/int\u00e9ressement, avantages CSE.\nVous vous reconnaissez dans cette annonce? N'h\u00e9sitez pas \u00e0 postuler! Nous avons h\u00e2te de vous rencontrer!\nShow more\nShow less",
        "skills": {
            "ProgLanguage": [
                "R",
                "Go"
            ],
            "DataBase": [],
            "DataAnalytics": [
                "R"
            ],
            "BigData": [],
            "MachingLearning": [],
            "DataSerialization": [],
            "DataVisualization": [],
            "Statistics": [],
            "CloudComputing": [
                "Azure"
            ],
            "DevTools": [
                "Git",
                "Docker"
            ],
            "Os": [],
            "DBMS": [],
            "SoftBigDataProcessing": [],
            "Automation": [
                "Ansible",
                "Kubernetes"
            ],
            "InfrastructureAsCode": [
                "Terraform"
            ],
            "NetworkSecurty": [
                "VPN",
                "Firewall"
            ],
            "Virtualisation": [],
            "Containers": [
                "Docker",
                "Kubernetes"
            ],
            "Collaboration": [],
            "Other": [
                "Cloud"
            ],
            "FrSoftSkills": [],
            "EnSoftSkils": []
        },
        "details": {
            "JobDetail": [],
            "TypeContract": [],
            "Salary": [],
            "Level": [
                "Bac+5"
            ],
            "Experience": [
                "a",
                "n",
                "s"
            ]
        }
    },
    {
        "source": "LinkedIn",
        "title": "DATA ARCHITECT - TOTALENERGIES DIGITAL FACTORY",
        "company": "TotalEnergies",
        "location": "Paris, \u00cele-de-France, France",
        "link": "https://fr.linkedin.com/jobs/view/data-architect-totalenergies-digital-factory-at-totalenergies-3915417534?position=58&pageNum=0&refId=a5rwPua%2FMvx%2F2M%2FPSF0oPA%3D%3D&trackingId=u97hBoyKUyuCRt2bDzyVOA%3D%3D&trk=public_jobs_jserp-result_search-card",
        "description": "TotalEnergies est une\ncompagnie multi-\u00e9nergies mondiale\nde production et de fourniture d'\u00e9nergies : p\u00e9trole et biocarburants, gaz naturel et gaz verts, renouvelables et \u00e9lectricit\u00e9.\nLa Digital Factory de TotalEnergies est compos\u00e9e de 300 personnes, 30 Squads, 39% de femmes et 25 nationalit\u00e9s. Elle offre un environnement de travail international et interculturel en plein c\u0153ur de Paris, engag\u00e9 dans la diversit\u00e9 et l'inclusion. Elle permet d'\nacc\u00e9l\u00e9rer\nla production interne de\nsolutions digitales\npour les activit\u00e9s de la Compagnie\ndans les 130 pays o\u00f9 elle est pr\u00e9sente.\nPour ce faire, elle allie l'\nagilit\u00e9\net l'\nesprit pionnier\nd'une entreprise technologique \u00e0 la\nrobustesse\net \u00e0 la\nrigueur\nd'une entit\u00e9 de production \u00e0 grande \u00e9chelle. Elle cr\u00e9e et d\u00e9ploie des solutions digitales sur l'ensemble des sites de la compagnie TotalEnergies afin de fournir une \u00e9nergie propre, fiable et abordable au plus grand nombre.\nRejoins-nous en plein c\u0153ur de Paris en tant que Data Architect, tu seras int\u00e9gr\u00e9(e) dans la Tech Authority qui r\u00e9unit environ une vingtaine de personnes (Assurance Qualit\u00e9, S\u00e9curit\u00e9, Architecte Software et Technique...).\nL'\u00e9quipe \u00e9volue dans un contexte agile \u00e0 tous les niveaux de l'organisation, en mode it\u00e9ratif et co-constructif, en s'appuyant sur l'intelligence collective. Au sein de la Tech Authority, tu participes \u00e0 d\u00e9terminer la gouvernance technique des projets. Tu es \u00e9galement un soutien et un accompagnateur pour les Squads durant les diff\u00e9rentes phases de leur projet.\nNous attendons techniquement de toi que tu :\nD\u00e9finisses l'architecture en phase de framing.\nCo-construises cette architecture avec les Squads en phase build. Tu seras principalement en lien avec les Data Engineers et les Tech Leads. Tu valides \u00e9galement l'architecture lorsque le besoin \u00e9volue. Tu es amen\u00e9(e) \u00e0 prendre des d\u00e9cisions d'architecture tout au long de la phase de build.\nValides les mod\u00e9lisations\nEffectues des revues p\u00e9riodiques avec la Squad pour \u00e9tudier le code et sa qualit\u00e9.\nRevois l'architecture de la solution avant le transfert au m\u00e9tier.\nTu devras \u00e9galement faire de la veille et de l'accompagnement. Ainsi, nous attendons de toi que tu :\nD\u00e9finisses les bonnes pratiques en mati\u00e8re d'architecture data et que tu t'assures qu'elles sont bien respect\u00e9es par l'ensemble des Squads.\nTe tiennes inform\u00e9(e) des tendances, des \u00e9volutions technologiques et des innovations en vigueur dans ton domaine d'intervention.\nCoaches les Squads dans les diff\u00e9rentes phases de r\u00e9alisation de leur projet avec les Chapter Lead.\nD\u00e9bloques les Squads si n\u00e9cessaire lorsqu'elles rencontrent un souci avec les architectures data dans les plateformes AWS et Azure.\nAnimes les communaut\u00e9s Tech sur l'architecture au travers des Communities of Practices pr\u00e9sentes \u00e0 la Digital Factory de TotalEnergies.\nCe que nous t'offrons:\nLe d\u00e9veloppement de tes comp\u00e9tences avec le support de la Digital Academy et une enveloppe \u00e9quivalente \u00e0 environ 10 jours de formations par an que tu peux choisir en toute autonomie (formations externes et internes).\nLa possibilit\u00e9 de te certifier sur les plateformes AWS et Azure, DataBricks, \u2026\nUn programme de mentorat pour t'accompagner.\nUn \u00e9quilibre vie professionnelle et vie personnelle avec le recours possible aux horaires flexibles et au t\u00e9l\u00e9travail \u00e0 domicile.\nUn environnement de travail international et interculturel en plein c\u0153ur de Paris, engag\u00e9 dans la diversit\u00e9 et l'inclusion\nTu as une exp\u00e9rience r\u00e9ussie de 10 minimum dans la data dont 4 ans en tant que Data Architect.\nLes comp\u00e9tences qui sont attendues de toi en tant que Data Architect :\nLes m\u00e9thodes de travail Agile vous sont famili\u00e8res.\nTu as une bonne connaissance dans les principes de base de data management, dans les traitements de data flow, dans les standards de data modeling et les bases du machine learning, deeplearning et dans l'industrialisation des architectures datascience.\nLes comp\u00e9tences technologiques qui te seront indispensables :\nCloud (Azure, AWS)\nDevOps\nLangages de scripting (Python, Java...)\nBases de donn\u00e9es SQL et NoSQL\nProcessus et outils ETL ou ELT\nLes certifications suivantes sont \u00e9galement attendues :\nMicrosoft Certified : Azure fundamentals\nAWS certified: Solution Architect Associate\nShow more\nShow less",
        "skills": {
            "ProgLanguage": [
                "Python",
                "Java",
                "R",
                "Go"
            ],
            "DataBase": [
                "SQL",
                "NoSQL"
            ],
            "DataAnalytics": [
                "R"
            ],
            "BigData": [
                "Databricks"
            ],
            "MachingLearning": [],
            "DataSerialization": [],
            "DataVisualization": [],
            "Statistics": [],
            "CloudComputing": [
                "AWS",
                "Azure"
            ],
            "DevTools": [
                "Git"
            ],
            "Os": [],
            "DBMS": [],
            "SoftBigDataProcessing": [],
            "Automation": [],
            "InfrastructureAsCode": [],
            "NetworkSecurty": [],
            "Virtualisation": [],
            "Containers": [],
            "Collaboration": [],
            "Other": [
                "DevOps",
                "Machine Learning",
                "Cloud"
            ],
            "FrSoftSkills": [
                "Organisation"
            ],
            "EnSoftSkils": []
        },
        "details": {
            "JobDetail": [],
            "TypeContract": [],
            "Salary": [],
            "Level": [],
            "Experience": [
                "a",
                "n",
                "s",
                "4",
                "4",
                "4"
            ]
        }
    },
    {
        "source": "LinkedIn",
        "title": "Architecte Data",
        "company": "Templeton and Partners - Tech Recruitment",
        "location": "Lyon, Auvergne-Rh\u00f4ne-Alpes, France",
        "link": "https://fr.linkedin.com/jobs/view/architecte-data-at-templeton-and-partners-tech-recruitment-3904841784?position=59&pageNum=0&refId=a5rwPua%2FMvx%2F2M%2FPSF0oPA%3D%3D&trackingId=RpoZyxSOnAcVD67qvV4WFQ%3D%3D&trk=public_jobs_jserp-result_search-card",
        "description": "Architecte Data\nSecteur\n: Industriel\nD\u00e9marrage:\nASAP\nMission :\nLongue\nCadence :\nFull time\nHybrid :\n3 jours sur site (Est lyonnais)\nNous recherchons un Architecte de Donn\u00e9es qui fera partie de l'\u00e9quipe stable de BI & Analytics, ax\u00e9e sur le Marketing & la Communication.\nLa Mission :\nEn tant qu'Architecte de Donn\u00e9es, vous veillerez \u00e0 ce que les produits livr\u00e9s par votre \u00e9quipe stable soient align\u00e9s sur l'architecture cible mondiale du client. Pour soutenir ce poste, nous recherchons un Architecte de Donn\u00e9es Azure avec une bonne compr\u00e9hension g\u00e9n\u00e9rale des services disponibles dans la pile d'analyse Azure.\nCette personne travaillera avec le DPO, l'Analyste de Donn\u00e9es, l'Ing\u00e9nieur de Donn\u00e9es et le Data Scientist de l'\u00e9quipe stable, mais aussi avec la communaut\u00e9 des Architectes pour d\u00e9finir une architecture de qualit\u00e9, de valeur commerciale pertinente et de maintenabilit\u00e9 \u00e0 long terme.\nDe plus, il/elle doit \u00e9galement avoir des comp\u00e9tences en leadership pour assumer le r\u00f4le de leader technique et discuter avec les Parties Prenantes M\u00e9tier et l'Architecture d'Entreprise.\nVous fournissez un leadership technique, vous participez aux efforts de d\u00e9veloppement et vous repr\u00e9sentez l'ensemble des capacit\u00e9s internes et externes de la plateforme.\nVous serez un membre actif de la guilde des architectes pour superviser le processus de gestion des donn\u00e9es et fournir des orientations aux \u00e9quipes de d\u00e9veloppement.\nVous \u00eates responsable de la conception et de la documentation de la solution dans votre domaine.\nVous avez de l'exp\u00e9rience sur Databricks, le stockage ADLS, SQL DB, ADF et Power BI.\nVous avez de l'exp\u00e9rience dans la d\u00e9finition et la possession d'une architecture de donn\u00e9es \u00e9volutive de bout en bout en tenant compte de l'architecture d'entreprise et des normes de l'industrie.\nVous \u00eates habitu\u00e9 \u00e0 d\u00e9velopper, documenter et maintenir des mod\u00e8les de donn\u00e9es logiques et physiques.\nVotre future \u00e9quipe :\nDans le cadre du Marketing & de la Communication, vous rencontrerez de nombreux d\u00e9fis et sujets int\u00e9ressants :\nCr\u00e9er un tableau de bord client 360 bas\u00e9 sur les donn\u00e9es CRM et des sources externes pour soutenir le processus marketing.\nCalculer le prix pr\u00e9dictif des produits utilis\u00e9s bas\u00e9 sur les donn\u00e9es de l'OCDE gr\u00e2ce \u00e0 un processus d'IA.\nTableau de bord des ventes pour piloter le processus de vente.\nMettre en place un produit de donn\u00e9es pour soutenir l'approche CAST (produit r\u00e9utilisable partag\u00e9) conforme \u00e0 la strat\u00e9gie du Groupe Volvo.\nFaire partie de l'\u00e9quipe de maintenance pour assurer la continuit\u00e9 des processus m\u00e9tier.\nComp\u00e9tences & Aptitudes Obligatoires :\nL'Architecture de Donn\u00e9es est votre domaine depuis au moins 4 ans.\n\u00c9crire du SQL et r\u00e9aliser de la mod\u00e9lisation de donn\u00e9es vous est naturel.\nConception d'Architecture de Donn\u00e9es.\nPower BI.\nComposants Azure comme ADFv2, Databricks, Delta Lake.\nTechnologies et cadres d'Analyse Avanc\u00e9e Azure.\nLangage de programmation li\u00e9 \u00e0 l'Analyse Avanc\u00e9e : Python, Pyspark.\nMod\u00e8le de livraison bas\u00e9 sur le Cloud Microsoft.\nGestion des Donn\u00e9es, Gouvernance des Donn\u00e9es et Qualit\u00e9 des Donn\u00e9es.\nD\u00e9ploiement d'API ou de microservices.\nDevSecOps.\nAgile.\nVous avez de l'exp\u00e9rience de travail dans un environnement mondial.\nVous avez d'excellentes comp\u00e9tences en communication en fran\u00e7ais et en anglais (niveau C1).\nShow more\nShow less",
        "skills": {
            "ProgLanguage": [
                "Python",
                "R",
                "Go"
            ],
            "DataBase": [
                "SQL"
            ],
            "DataAnalytics": [
                "R"
            ],
            "BigData": [
                "Spark",
                "Databricks"
            ],
            "MachingLearning": [],
            "DataSerialization": [],
            "DataVisualization": [
                "Tableau",
                "Power BI"
            ],
            "Statistics": [],
            "CloudComputing": [
                "Azure"
            ],
            "DevTools": [],
            "Os": [],
            "DBMS": [],
            "SoftBigDataProcessing": [],
            "Automation": [],
            "InfrastructureAsCode": [],
            "NetworkSecurty": [],
            "Virtualisation": [],
            "Containers": [],
            "Collaboration": [],
            "Other": [
                "Cloud"
            ],
            "FrSoftSkills": [
                "Communication",
                "Leadership"
            ],
            "EnSoftSkils": [
                "Communication",
                "Leadership"
            ]
        },
        "details": {
            "JobDetail": [
                "Full"
            ],
            "TypeContract": [],
            "Salary": [],
            "Level": [],
            "Experience": [
                "a",
                "n",
                "s",
                "4",
                "4",
                "4"
            ]
        }
    },
    {
        "source": "LinkedIn",
        "title": "Data architect",
        "company": "Harnham",
        "location": "Greater Paris Metropolitan Region",
        "link": "https://fr.linkedin.com/jobs/view/data-architect-at-harnham-3911912252?position=1&pageNum=2&refId=s27%2F43wenQFDag2sabINKw%3D%3D&trackingId=RVF4m9iXGLslJjBwC1Tixw%3D%3D&trk=public_jobs_jserp-result_search-card",
        "description": "DATA ARCHITECT\nPARIS (75)\nUP TO 65K\u20ac FIXE\nAWS - Tableau - Pyspark - Data Modeling\nVous \u00eates \u00e0 la recherche d'un nouveau challenge de Data Architect dans le domaine de l'assurance ? Ne cherchez plus, voici l'opportunit\u00e9 de vos r\u00eaves ! Une entreprise sp\u00e9cialis\u00e9e dans l'assurance automobile des particuliers, recherche un Data Architect dans le cadre de la cr\u00e9ation d'une nouvelle plateforme data en Europe.\nLE POSTE\nEn tant que Data Architect, vous allez d\u00e9finir les architectures et les normes pour la strat\u00e9gie de donn\u00e9es. Vous d\u00e9finirez la vision et les lignes directrices pour la livraison des produits de donn\u00e9es.\nVoici vos responsabilit\u00e9s au quotidien :\nD\u00e9finir l'architecture cible\nCommuniquer avec les Product Owner pour atteindre l'objectif du wagon\nTravailler en \u00e9troite collaboration avec les data scientists pour op\u00e9rationnaliser les mod\u00e8les ML au sein de la plateforme de donn\u00e9es\nTravailler en \u00e9troite collaboration avec les data engineer et data ops pour le suivi de l'architecture cible\nTravailler en mode agile au quotidien\nVOTRE PROFIL\nDipl\u00f4me d'ing\u00e9nieur en computer engineering ou math\u00e9matiques\n5 ans d'exp\u00e9rience en architecture data\nConnaissance des architectures de plateformes de donn\u00e9es op\u00e9rationnelles\nConnaissance de la mod\u00e9lisation de donn\u00e9es et bases de donn\u00e9es\nConnaissance du cloud AWS\nConnaissance d'outils BI principalement Tableau\nBilingue (fan\u00e7ais et anglais)\nNice to have : connaissance en Machine Learning\nPOUR POSTULER\nMerci de me faire part de votre CV et je vous recontacterai au plus vite.\nShow more\nShow less",
        "skills": {
            "ProgLanguage": [
                "R",
                "Go"
            ],
            "DataBase": [],
            "DataAnalytics": [
                "R"
            ],
            "BigData": [
                "Spark"
            ],
            "MachingLearning": [],
            "DataSerialization": [],
            "DataVisualization": [
                "Tableau"
            ],
            "Statistics": [],
            "CloudComputing": [
                "AWS"
            ],
            "DevTools": [],
            "Os": [],
            "DBMS": [],
            "SoftBigDataProcessing": [],
            "Automation": [],
            "InfrastructureAsCode": [],
            "NetworkSecurty": [],
            "Virtualisation": [],
            "Containers": [],
            "Collaboration": [],
            "Other": [
                "ML",
                "Machine Learning",
                "Cloud"
            ],
            "FrSoftSkills": [
                "Collaboration"
            ],
            "EnSoftSkils": [
                "Collaboration"
            ]
        },
        "details": {
            "JobDetail": [],
            "TypeContract": [],
            "Salary": [],
            "Level": [],
            "Experience": [
                "a",
                "n",
                "s",
                "5",
                "5",
                "5"
            ]
        }
    },
    {
        "source": "LinkedIn",
        "title": "Architecte Data",
        "company": "FRG Technology Consulting",
        "location": "Paris, \u00cele-de-France, France",
        "link": "https://fr.linkedin.com/jobs/view/architecte-data-at-frg-technology-consulting-3917370845?position=2&pageNum=2&refId=s27%2F43wenQFDag2sabINKw%3D%3D&trackingId=c%2F%2F%2BmrSZ6WTY%2B99bPhM%2Fjg%3D%3D&trk=public_jobs_jserp-result_search-card",
        "description": "Notre client, entreprise renomm\u00e9e dans le secteur du luxe et des cosm\u00e9tiques, bas\u00e9 sur Paris, est \u00e0 la recherche de son/sa futur(e) Architecte Data.\nEn tant que membre de la DSI, votre r\u00f4le est de participer \u00e0 la transformation digitale de l\u2019entreprise, par une meilleure capture, analyse et exploitation des donn\u00e9es clients.\nPrincipales missions :\nAnalyse et r\u00e9ponses aux besoins des m\u00e9tiers (BI, analyses externes, etc.),\nConception de nouveaux mod\u00e8les de donn\u00e9es\nConstruction des pipelines de donn\u00e9es\nTransformation de donn\u00e9es (Pyspark) et le stockage de donn\u00e9es dans le Data Lake / Data Warehouse du Groupe\nRun et le suivi de la TMA\nDescription du profil :\nTitulaire Bac +5 informatique ou dipl\u00f4me ing\u00e9nieur\n6 ann\u00e9es minimum en expertise Data\nUne bonne ma\u00eetrise des outils suivants : Azure, SQL, Snowflake, Databricks, Spark, Python, ELK,..\nUne bonne affinit\u00e9 avec les best practices DevOps, CI/CD, unit-testing et m\u00e9thodologies de travail agile\nDes notions en data science sur l\u2019entra\u00eenement, la validation et le d\u00e9ploiement de mod\u00e8les ML supervis\u00e9s et non-supervis\u00e9s serait un plus.\nQualit\u00e9s requises : Bon esprit analytique et de synth\u00e8se, rigoureux, autonome, bonne communication, curieux, force de proposition, vulgarisation des probl\u00e9matiques techniques aupr\u00e8s du m\u00e9tier\nAvantages :\nPackage (variable / participation / int\u00e9ressement) + avantages attractifs\n\u00c9quipe Data \u00e0 taille humaine (tr\u00e8s bon accompagnement en interne)\nForte valeur ajout\u00e9e des projets\nT\u00e9l\u00e9travail\nCandidatures confidentielles\nShow more\nShow less",
        "skills": {
            "ProgLanguage": [
                "Python",
                "R",
                "Go"
            ],
            "DataBase": [
                "SQL"
            ],
            "DataAnalytics": [
                "R"
            ],
            "BigData": [
                "Spark",
                "Databricks"
            ],
            "MachingLearning": [],
            "DataSerialization": [],
            "DataVisualization": [],
            "Statistics": [],
            "CloudComputing": [
                "Azure"
            ],
            "DevTools": [
                "Git"
            ],
            "Os": [],
            "DBMS": [
                "Snowflake",
                "Snowflake"
            ],
            "SoftBigDataProcessing": [],
            "Automation": [],
            "InfrastructureAsCode": [],
            "NetworkSecurty": [],
            "Virtualisation": [],
            "Containers": [],
            "Collaboration": [],
            "Other": [
                "DevOps",
                "ML",
                "CI/CD"
            ],
            "FrSoftSkills": [
                "Communication"
            ],
            "EnSoftSkils": [
                "Communication"
            ]
        },
        "details": {
            "JobDetail": [],
            "TypeContract": [],
            "Salary": [
                "Package"
            ],
            "Level": [],
            "Experience": [
                "a",
                "n",
                "s"
            ]
        }
    },
    {
        "source": "LinkedIn",
        "title": "Architecte Data F/H",
        "company": "Ippon Technologies",
        "location": "Greater Lyon Area",
        "link": "https://fr.linkedin.com/jobs/view/architecte-data-f-h-at-ippon-technologies-3893256404?position=3&pageNum=2&refId=s27%2F43wenQFDag2sabINKw%3D%3D&trackingId=eNgv9c6B5TkdwhMVrnYkxg%3D%3D&trk=public_jobs_jserp-result_search-card",
        "description": "Qui sommes-nous ?\nIppon\n, c'est l\u2019\u00e9nergie du collectif au service de la technologie ! Nous sommes un cabinet de conseil et d\u2019expertise technique. Nos \u00e9quipes ont pour leitmotive de transformer des id\u00e9es innovantes en solutions logicielles de haute qualit\u00e9 avec un focus particulier sur la valeur apport\u00e9e aux utilisateurs.\nCr\u00e9\u00e9e en 2017, l\u2019agence de Lyon, ce sont des passionn\u00e9s intervenant sur des projets \u00e0 forte technicit\u00e9 ou en conseil et architecture : Fullstack, Data, DevOps, Cloud, Agile, Design et ne compte pas s\u2019arr\u00eater en si bon chemin !\nLa pluridisciplinarit\u00e9, l\u2019expertise, l\u2019\u00e9coute, l\u2019adaptabilit\u00e9 mais aussi le partage de connaissances fondent notre engagement au service de nos partenariats.\nVous int\u00e9grerez notre Communaut\u00e9 Data\n, compos\u00e9e d\u2019une \u00e9quipe de\n80 experts sur 10 agences en France.\nNotre sp\u00e9cialit\u00e9 est de\nconstruire des data platforms dans le Cloud public avec les meilleures technos du moment.\nLa\nData chez Ippon, c\u2019est d\u00e9j\u00e0 plus de\n250 certifications AWS, GCP et AZURE,\ndes\nspeakers \u00e0 l\u2019AWS Summit, des partenariats avec Snowflake, Databricks, DBT, un blog technique\navec des publications r\u00e9guli\u00e8res.\nCe poste est un vrai challenge aussi bien en termes de\nd\u00e9fis techniques que de gestion d'\u00e9quipe.\nLa\nr\u00e9ussite de vos projets sera port\u00e9e par votre capacit\u00e9 \u00e0 vous adapter et \u00e0 monopoliser un large panel de comp\u00e9tences techniques. Vous devrez \u00eatre le/la leader de votre \u00e9quipe en gardant \u00e0 l\u2019esprit l\u2019ensemble des\nbonnes pratiques d'architectes\n, de s\u00e9curit\u00e9 et d\u2019automatisation n\u00e9cessaires \u00e0 la r\u00e9ussite du projet. En tant que\nrepr\u00e9sentant(e) de l\u2019engagement d\u2019Ippon\nsur les sujets qui vous seront confi\u00e9s, vous serez amen\u00e9(e) \u00e0\ntravailler avec notre \u00e9quipe Commerce d\u00e8s les phases de qualification\net lors de la validation de jalons de la roadmap que vous aurez pr\u00e9alablement valid\u00e9 avec le client. Vous interviendrez \u00e9galement dans la s\u00e9lection de l\u2019\u00e9quipe qui sera affect\u00e9e \u00e0 votre projet.\nVotre r\u00f4le :\n- Gr\u00e2ce \u00e0 votre position d\u2019architecte vous avez une vision experte et syst\u00e9mique de l\u2019ensemble des composants d\u2019une Modern Data Platform.\n- Vous ma\u00eetrisez le panel des exigences fonctionnelles et non fonctionnelles \u00e0 collecter afin d\u2019assurer l\u2019efficience op\u00e9rationnelle et la p\u00e9rennit\u00e9 de la data platform.\n- Vous \u00eates expert(e) et ma\u00eetrisez tous les outils et services d\u2019au moins un \u00e9cosyst\u00e8me parmi les 3 principaux leaders du march\u00e9 (AWS, Azure et GCP) et avez des facilit\u00e9s pour \u00e9tendre votre champ de comp\u00e9tences.\n- Vous \u00eates proactif/ve sur la veille technique et la capitalisation et veillez \u00e0 garder toujours un temps d\u2019avance sur l\u2019\u00e9tat de l\u2019art du secteur afin de pouvoir guider vos clients.\n- En tant qu\u2019architecte exp\u00e9riment\u00e9(e) vous pouvez indiff\u00e9remment intervenir sur des missions de delivery pour concevoir la solution cible ou en phase de cadrage amont pour guider les choix et construire les roadmaps.\n- Vous \u00eates p\u00e9dagogue et savez communiquer et vulgariser des r\u00e9flexions complexes pour les rendre accessibles \u00e0 tous.\nNotre \u00e9co-syst\u00e8me technique :\n- Cloud : AWS, GCP, Azure\n- Langage de programmation data : Python, SQL, Scala\n- Approche Data Warehouse : Redshift, Snowflake, BigQuery\n- Approche Data Lakehouse : Databricks, Starburst, Glue-Athena-S3Ingestion : AWS Glue, Airbyte, dbt Stockage : AWS S3, Google Cloud Storage, Azure Blob Storage\n- Orchestration : Airflow, AWS Step function\n- Gouvernance : cataloging, s\u00e9curit\u00e9, scope d'acc\u00e8sBatch et Streaming : Kafka, Amazon Kinesis, Google DataFlow\n- Outil de visualisation : Tableau, Power BI, Metabase, Superset\nVotre \u00e9volution chez Ippon :\nVous serez accompagn\u00e9(e) dans votre mont\u00e9e en comp\u00e9tences aussi bien technique que leadership gr\u00e2ce \u00e0\nnotre programme BlackBelt\n(programme de formation continue : mentoring, formations, certifications).\nEn tant que membre d\u2019une communaut\u00e9,\nvous pouvez avoir diff\u00e9rents r\u00f4les :\n- Celui de Manager Technique (MT) : manager d\u2019une \u00e9quipe de 7 ing\u00e9nieur(e)s Ippon (onboarding, suivis, accompagnement, mise en place d\u2019objectifs\u2026). Vous conduirez les entretiens techniques en bin\u00f4me\n- Responsable de l\u2019accomplissement d\u2019une ou plusieurs actions strat\u00e9giques de la CoreTeam Data\n- Devenir speaker lors de Meetup, Summit, Talks internes, aupr\u00e8s des \u00e9coles \u2026\n- Devenir formateur(trice) et accompagner la nouvelle g\u00e9n\u00e9ration d\u2019Ippon dans leur mont\u00e9e en comp\u00e9tencesVous avez d\u2019autres souhaits, pas de soucis, nous en discuterons durant notre \u00e9change et r\u00e9pondrons \u00e0 toutes vos questions.\nLes Next Steps :\n1 Echange RH\n1 Echange Technique\n1 Echange avec la Direction\nSi le match est bon des deux c\u00f4t\u00e9s : Vous vous lancerez sur le tatami Ippon !\nShow more\nShow less",
        "skills": {
            "ProgLanguage": [
                "Python",
                "Scala",
                "R",
                "Go"
            ],
            "DataBase": [
                "SQL"
            ],
            "DataAnalytics": [
                "R"
            ],
            "BigData": [
                "Databricks"
            ],
            "MachingLearning": [],
            "DataSerialization": [],
            "DataVisualization": [
                "Tableau",
                "Power BI"
            ],
            "Statistics": [],
            "CloudComputing": [
                "AWS",
                "Azure"
            ],
            "DevTools": [],
            "Os": [],
            "DBMS": [
                "Snowflake",
                "Snowflake",
                "BigQuery"
            ],
            "SoftBigDataProcessing": [],
            "Automation": [
                "Airflow"
            ],
            "InfrastructureAsCode": [],
            "NetworkSecurty": [],
            "Virtualisation": [],
            "Containers": [],
            "Collaboration": [],
            "Other": [
                "DevOps",
                "Cloud"
            ],
            "FrSoftSkills": [
                "Adaptabilit\u00e9",
                "Leadership"
            ],
            "EnSoftSkils": [
                "Leadership"
            ]
        },
        "details": {
            "JobDetail": [
                "Full"
            ],
            "TypeContract": [],
            "Salary": [],
            "Level": [],
            "Experience": [
                "a",
                "n",
                "s"
            ]
        }
    },
    {
        "source": "LinkedIn",
        "title": "DATA ANALYST JUNIOR (H/F)",
        "company": "Akademija Oxford",
        "location": "Boulogne-Billancourt, \u00cele-de-France, France",
        "link": "https://fr.linkedin.com/jobs/view/data-analyst-junior-h-f-at-akademija-oxford-3917871112?position=4&pageNum=2&refId=s27%2F43wenQFDag2sabINKw%3D%3D&trackingId=A3sTIrvtclaO2d7xjfPfTw%3D%3D&trk=public_jobs_jserp-result_search-card",
        "description": "Notre entreprise partenaire, sp\u00e9cialiste de la vente de m\u00e9dicaments et produits de sant\u00e9, recherche un apprenti Data Analyst (H/F) pr\u00e9parant un bac +4/+5 en fili\u00e8re Big Data pour la rentr\u00e9e de Septembre 2021.\nShow more\nShow less",
        "skills": {
            "ProgLanguage": [
                "R"
            ],
            "DataBase": [],
            "DataAnalytics": [
                "R"
            ],
            "BigData": [],
            "MachingLearning": [],
            "DataSerialization": [],
            "DataVisualization": [],
            "Statistics": [],
            "CloudComputing": [],
            "DevTools": [],
            "Os": [],
            "DBMS": [],
            "SoftBigDataProcessing": [],
            "Automation": [],
            "InfrastructureAsCode": [],
            "NetworkSecurty": [],
            "Virtualisation": [],
            "Containers": [],
            "Collaboration": [],
            "Other": [
                "Big Data"
            ],
            "FrSoftSkills": [],
            "EnSoftSkils": []
        },
        "details": {
            "JobDetail": [],
            "TypeContract": [],
            "Salary": [],
            "Level": [],
            "Experience": [
                "a",
                "n",
                "s"
            ]
        }
    },
    {
        "source": "LinkedIn",
        "title": "Data Architect Azure",
        "company": "FRG Technology Consulting",
        "location": "Paris, \u00cele-de-France, France",
        "link": "https://fr.linkedin.com/jobs/view/data-architect-azure-at-frg-technology-consulting-3902057360?position=5&pageNum=2&refId=s27%2F43wenQFDag2sabINKw%3D%3D&trackingId=NwAL8xb%2BL044hdpxUUfrXA%3D%3D&trk=public_jobs_jserp-result_search-card",
        "description": "FRG Consulting recrute pour l'un de ses clients, une soci\u00e9t\u00e9 finale renomm\u00e9e dans le secteur du luxe et des cosm\u00e9tiques, un Data Architect expert en Azure. Nich\u00e9 au c\u0153ur de Paris, vous aurez l'opportunit\u00e9 de travailler au sein d'une \u00e9quipe passionn\u00e9e par la recherche et l'innovation, \u00e9voluant dans un environnement stimulant et cr\u00e9atif.\nVos missions captivantes :\nContribuer \u00e0 l'\u00e9volution de nos syst\u00e8mes en d\u00e9veloppant de nouveaux connecteurs et pipelines pour l'extraction de donn\u00e9es, qu'il s'agisse de batch (utilisant Sqoop, scripts bash, Java ou des API) ou de streaming (via Kafka, ELK).\nParticiper activement \u00e0 la transformation des donn\u00e9es \u00e0 l'aide de Pyspark, ainsi qu'au stockage dans notre Data Lake et notre Data Warehouse.\nConcevoir de nouveaux mod\u00e8les de donn\u00e9es et mettre \u00e0 disposition des tables ad-hoc sur Snowflake et Impala, r\u00e9pondant ainsi aux besoins m\u00e9tier en termes de BI et d'analyses externes.\nAssurer le bon fonctionnement et le suivi de la TMA du Data Lake, garantissant ainsi la fiabilit\u00e9 et la performance de nos syst\u00e8mes.\nProfil recherch\u00e9 :\nVous b\u00e9n\u00e9ficiez d'au moins 8 ans d'exp\u00e9rience dans le domaine.\nVous ma\u00eetrisez les outils et frameworks de notre stack technique Big Data : Azure, SQL, Snowflake, Databricks, Spark, Python, ELK.\nVous \u00eates familier des best practices DevOps, CI/CD, et des m\u00e9thodologies de travail agile.\nDes comp\u00e9tences en data science, notamment sur l'entra\u00eenement, la validation et le d\u00e9ploiement de mod\u00e8les ML supervis\u00e9s et non-supervis\u00e9s, seraient grandement appr\u00e9ci\u00e9es.\nLa ma\u00eetrise de l'anglais est indispensable pour \u00e9voluer dans un environnement international et dynamique.\nShow more\nShow less",
        "skills": {
            "ProgLanguage": [
                "Python",
                "Java",
                "R",
                "Bash"
            ],
            "DataBase": [
                "SQL"
            ],
            "DataAnalytics": [
                "R"
            ],
            "BigData": [
                "Spark",
                "Databricks"
            ],
            "MachingLearning": [],
            "DataSerialization": [],
            "DataVisualization": [],
            "Statistics": [],
            "CloudComputing": [
                "Azure"
            ],
            "DevTools": [],
            "Os": [],
            "DBMS": [
                "Snowflake",
                "Snowflake"
            ],
            "SoftBigDataProcessing": [],
            "Automation": [],
            "InfrastructureAsCode": [],
            "NetworkSecurty": [],
            "Virtualisation": [],
            "Containers": [],
            "Collaboration": [],
            "Other": [
                "DevOps",
                "Big Data",
                "ML",
                "CI/CD"
            ],
            "FrSoftSkills": [],
            "EnSoftSkils": []
        },
        "details": {
            "JobDetail": [],
            "TypeContract": [],
            "Salary": [],
            "Level": [],
            "Experience": [
                "a",
                "n",
                "s",
                "8",
                "8",
                "8"
            ]
        }
    },
    {
        "source": "LinkedIn",
        "title": "Data Architect Senior - Freelance (H/F)",
        "company": "TeamWork Corporate",
        "location": "Saint-Priest, Auvergne-Rh\u00f4ne-Alpes, France",
        "link": "https://fr.linkedin.com/jobs/view/data-architect-senior-freelance-h-f-at-teamwork-corporate-3916528778?position=6&pageNum=2&refId=s27%2F43wenQFDag2sabINKw%3D%3D&trackingId=yaz2%2FJwMWVF6OWDperGC1w%3D%3D&trk=public_jobs_jserp-result_search-card",
        "description": "Description de l'entreprise\nTeamWork est un acteur majeur du conseil, de l\u2019int\u00e9gration technologique et de l\u2019innovation, implant\u00e9 en Europe, en Asie et en Am\u00e9rique du Nord.\nAu travers de ses univers, SAP Business Solutions, Data Analytics, Technology Platform et Salesforce, nous sommes reconnus par nos clients pour accro\u00eetre leur performance op\u00e9rationnelle.\nLa transformation digitale est un enjeu majeur pour toute organisation.\nLa n\u00e9cessit\u00e9 de digitaliser ses processus, d\u2019imaginer de nouvelles fa\u00e7ons d\u2019interagir avec ses clients, d\u2019en conqu\u00e9rir de nouveaux et de proposer de nouveaux outils pour anticiper les besoins de pilotage\u202fn\u2019a jamais \u00e9t\u00e9 aussi forte.\nL\u2019univers Data Analytics de TeamWork accompagne les organisations autour de :\nLa r\u00e9flexion et identification de cas d\u2019usage pour les transformer en trajectoires moyen et long terme\nLe design et l\u2019impl\u00e9mentation de plateforme de donn\u00e9es et des outils p\u00e9riph\u00e9riques (data ingestion/int\u00e9gration)\nLa mise en place des premi\u00e8res solutions\u202fd\u2019Analytics (Business Intelligence, EPM,)\nSupport, extension et optimisation des solutions\nDans le cadre du d\u00e9veloppement de ces activit\u00e9s, nous recrutons un\nData Architect Senior (H/F)\nen Freelance pour une mission entre 2 \u00e0 3 mois.\nDescription du poste\nEn tant qu\u2019Architecte Data vous intervenez dans le cadre de projets et missions qui r\u00e9pondent aux enjeux clients d\u2019exploitation des donn\u00e9es. Vous participez aux phases d\u2019avant-vente, aux \u00e9tudes d\u2019architecture, et \u00e0 la r\u00e9alisation des solutions avec une responsabilit\u00e9 d\u2019encadrement technique des projets (tant sur des forfaits que des missions clients). Vous aurez des missions avec de r\u00e9elles responsabilit\u00e9s et tr\u00e8s diversifi\u00e9es (secteurs d\u2019activit\u00e9s vari\u00e9s).\nVos principales missions s\u2019articulent autour de :\nL\u2019analyse et la qualification des besoins et probl\u00e9matiques \u00ab m\u00e9tiers \u00bb de nos clients\nAssurer la conception, le d\u00e9veloppement et la mise en oeuvre de l'architecture des donn\u00e9es sur la plateforme Databricks\nLa d\u00e9finition et mise en \u0153uvre des architectures Data adapt\u00e9es aux contextes des projets : Modern Datawarehouse, LakeHouse, DataMesh etc.\nL\u2019accompagnement des Consultants et des Ing\u00e9nieurs sp\u00e9cialistes Data sur les projets. Vous \u0153uvrez \u00e0 qualit\u00e9 de leurs r\u00e9alisations et des livrables.\nLa collaboration sur tous les domaines d\u2019activit\u00e9s DATA : BI, Big Data, IoT, IA\nL\u2019apport d\u2019un regard critique et la capacit\u00e9 \u00e0 conseiller sur le choix des technologies Data\nLa participation \u00e0 la d\u00e9finition des bonnes pratiques de mises en \u0153uvres techniques et la veille \u00e0 leurs applications selon les m\u00e9thodes en vigueur (Zero Trust Security, DataOps, Infra-as-Code, Tests automatis\u00e9s etc.)\nQualifications\nTechniques :\nVous avez :\nTr\u00e8s bonnes connaissances de Databricks\nLa capacit\u00e9 \u00e0 r\u00e9aliser la conception et l\u2019impl\u00e9mentation de solutions d\u2019analytique \u00e0 l\u2019\u00e9chelle de l\u2019entreprise ; SQL\nLa connaissance d\u2019un ou plusieurs outils ETL (Azure Data Factory ou autres) et Data Visualisation (PowerBI par exemple)\nLa capacit\u00e9 \u00e0 mettre en place une solution Data end-to-end La connaissances des typologies d\u2019architectures (Modern Datawarehouse, LakeHouse ou DataMesh)\nVous connaissez l\u2019environnement Azure, MSBI, SQL Server ou si vous avez des notions dans l\u2019IA (Python, R, Machine Learning)\nMaitrise le traitement et l'analyse des donn\u00e9es en Python (Exp\u00e9rience dans la conception et le d\u00e9veloppement de processus ETL/ELT)\nMaitrise d\u2019outils de traitement et de stockage distribu\u00e9s parmi Hadoop, Spark, Databricks, Snowflake et/ou Kafka\nConnaissance des bonnes pratiques de conception d\u2019architecture data (s\u00e9curit\u00e9, disponibilit\u00e9, scalabilit\u00e9, confidentialit\u00e9) et des principes d\u2019une architecture Data Mesh.\nCapacit\u00e9 \u00e0 concevoir des architectures bas\u00e9es sur les services d\u2019une plateforme Cloud : AWS ou Azure\nSoft Skills\n:\nVous \u00eates proactif et appr\u00e9ciez travailler dans un environnement ambitieux et innovant.\nVous aimez ne pas rester sur vos acquis et toujours apprendre par le biais de formations, votre veille technologique ou encore par la participation aux \u00e9v\u00e9nements communautaires.\nHabitu\u00e9 \u00e0 travailler aussi bien de fa\u00e7on autonome qu\u2019\u00e0 collaborer en \u00e9quipe\nConnaissance des m\u00e9thodologies Agile (SCRUM ou autres)\nEnvie d\u2019apprendre et de partager vos savoir-faire\nCuriosit\u00e9\nLangues :\nFran\u00e7ais (Courant)\nAnglais (A l\u2019aise en communication orale et \u00e9crite)\nFormation\n:\nV\u00e9ritable passionn\u00e9 par la DATA et dipl\u00f4m\u00e9 d\u2019une \u00e9cole d\u2019ing\u00e9nieur (Bac+3 minimum) ou d'une formation sp\u00e9cifique orient\u00e9e Data avec une exp\u00e9rience significative en Data Engineering et architecture.\nVous avez une exp\u00e9rience de plus de 7 ans en environnement informatique, dont 3 \u00e0 4 ans minimum sur un poste senior en environnement Databricks (Team Lead, Architecte ou encore Consultant Senior).\nNous attacherons davantage d\u2019importance \u00e0 votre capacit\u00e9 \u00e0 vouloir apprendre et progresser et votre motivation qu\u2019\u00e0 votre dipl\u00f4me.\nInformations suppl\u00e9mentaires\nTeamWork, o\u00f9 votre \u00e9panouissement professionnel est cl\u00e9. R\u00e9compens\u00e9s par le label 'Great Place to Work 2023', nous pla\u00e7ons l'humain au c\u0153ur de notre entreprise.\nAu-del\u00e0 des comp\u00e9tences, nous valorisons les personnalit\u00e9s qui partagent nos valeurs de solidarit\u00e9 et d'esprit d'\u00e9quipe.\nSi ces principes vous parlent, rejoignez-nous ! Nous sommes d\u00e9di\u00e9s \u00e0 l'\u00e9quit\u00e9 et \u00e0 la diversit\u00e9, ouvrant nos portes \u00e0 tous les talents, y compris aux personnes en situation de handicap.\nPostulez et devenez un acteur de notre r\u00e9ussite collective chez TeamWork.\nShow more\nShow less",
        "skills": {
            "ProgLanguage": [
                "Python",
                "Scala",
                "R"
            ],
            "DataBase": [
                "SQL"
            ],
            "DataAnalytics": [
                "R"
            ],
            "BigData": [
                "Hadoop",
                "Spark",
                "Databricks"
            ],
            "MachingLearning": [],
            "DataSerialization": [],
            "DataVisualization": [
                "PowerBI"
            ],
            "Statistics": [],
            "CloudComputing": [
                "AWS",
                "Azure"
            ],
            "DevTools": [
                "Git"
            ],
            "Os": [],
            "DBMS": [
                "SQL Server",
                "Snowflake",
                "Snowflake"
            ],
            "SoftBigDataProcessing": [],
            "Automation": [],
            "InfrastructureAsCode": [],
            "NetworkSecurty": [],
            "Virtualisation": [],
            "Containers": [],
            "Collaboration": [],
            "Other": [
                "Big Data",
                "Machine Learning",
                "Cloud"
            ],
            "FrSoftSkills": [
                "Communication",
                "Collaboration",
                "Organisation"
            ],
            "EnSoftSkils": [
                "Communication",
                "Teamwork",
                "Collaboration"
            ]
        },
        "details": {
            "JobDetail": [
                "Senior"
            ],
            "TypeContract": [],
            "Salary": [],
            "Level": [
                "Bac+3"
            ],
            "Experience": [
                "a",
                "n",
                "s",
                "7",
                "7",
                "7"
            ]
        }
    },
    {
        "source": "LinkedIn",
        "title": "Airbus Atlantic - Architecte Data (All Gender)",
        "company": "Airbus",
        "location": "Greater Saint-Nazaire Area",
        "link": "https://fr.linkedin.com/jobs/view/airbus-atlantic-architecte-data-all-gender-at-airbus-3916426275?position=7&pageNum=2&refId=s27%2F43wenQFDag2sabINKw%3D%3D&trackingId=bxP4EpffbA1eb29JFyQBdA%3D%3D&trk=public_jobs_jserp-result_search-card",
        "description": "Job Description\nEt si VOTRE aventure avec NOUS commen\u00e7ait ?!\nNous vous proposons de travailler chez Airbus Atlantic, nouveau champion de dimension mondiale, n\u00b02 des a\u00e9rostructures, n\u00b01 des si\u00e8ges pilotes et dans le Top 3 des fauteuils passagers Premium.\nNotre site Airbus Atlantic bas\u00e9\n\u00e0 Toulouse (possibilit\u00e9 de travailler \u00e0 Montoir de Bretagne)\nrecherche son futur\nArchitecte Data (All Gender)\nLe poste d\u2019architecte Data est rattach\u00e9 au domaine \u00ab Architecture \u00bb au sein du d\u00e9partement \u00ab Architecture Digital & S\u00e9curit\u00e9 \u00bb.\nVous serez en interface avec les architectes du Syst\u00e8me d'Information et les diff\u00e9rents m\u00e9tiers consommateurs des architectures.\nVos Principales Missions Seront Les Suivantes\nFixer les orientations et d\u00e9finir des politiques concernant la mod\u00e9lisation des donn\u00e9es, en collaboration avec les autres architectes,\nCr\u00e9er des mod\u00e8les de donn\u00e9es logiques et physiques en utilisant les meilleures pratiques pour garantir une qualit\u00e9 \u00e9lev\u00e9e des donn\u00e9es et une r\u00e9duction de leur redondance,\nInstancier, impl\u00e9menter, construire, tester et maintenir les architectures data d\u00e9finies\nAnalyser, \u00e9valuer, tester et recommander les briques technologiques n\u00e9cessaires pour l\u2019acquisition, l\u2019analyse et l\u2019impl\u00e9mentation des donn\u00e9es,\nAnalyser les probl\u00e8mes d'int\u00e9gration des syst\u00e8mes li\u00e9s aux donn\u00e9es et proposer des solutions appropri\u00e9es,\nD\u00e9terminer les \u00ab Data set process \u00bb c\u2019est \u00e0 dire comment les donn\u00e9es sont int\u00e9gr\u00e9es et transform\u00e9es pour qu\u2019elles soient pr\u00eates \u00e0 \u00eatre analys\u00e9es (ex : ETL)\nParticiper aux processus d'extraction performants et qualitatifs des donn\u00e9es des sources requises afin de r\u00e9pondre aux besoins de l'entreprise\nMaintenir les mod\u00e8les de donn\u00e9es conceptuels, logiques et physiques ainsi que les m\u00e9tadonn\u00e9es correspondantes (pour la data gouvernance).\nD\u00e9velopper les meilleures pratiques pour les conventions de d\u00e9nomination standard et les pratiques de codage afin d'assurer la coh\u00e9rence des mod\u00e8les de donn\u00e9es,\nRespecter les normes de s\u00e9curit\u00e9 des donn\u00e9es, de contr\u00f4le des exportations et de protection des donn\u00e9es.\nConstruire les pipelines qui permettront aux Data Scientist/Analysts/Developers de mettre leurs mod\u00e8les en production\nEtre garant de la fiabilit\u00e9, de la qualit\u00e9 et de l\u2019efficacit\u00e9 du traitement des donn\u00e9es\nMaintenir les mod\u00e8les cr\u00e9\u00e9s.\nParticiper aux id\u00e9ations et proposer des innovations aux services.\nDocumenter ses activit\u00e9s et mettre \u00e0 jour le r\u00e9f\u00e9rentiel documentaire.\nParlons de vous !\nVous disposez d'une\ne\nxp\n\u00e9rience de minimum 5 ans en Data & Informatique sur un poste similaire.\nLes comp\u00e9tences techniques \u00e0 d\u00e9tenir pour le poste :\nL\u2019optimisation et les standards Qualit\u00e9 des donn\u00e9es informatiques\nComprendre et savoir mettre en place les diff\u00e9rentes Structure et stockage de donn\u00e9es\nGestion des probl\u00e8mes li\u00e9 \u00e0 la donn\u00e9e, l'architecture\nId\u00e9alement, l'exp\u00e9rience des technologies suivantes serait un plus : Ressources & services data MS Azure (Databricks, Azure ML \u2026), SGBD (SQL, MongoDB, PostGreSQL, redis), Outils ETL (Qlik replicate, Alteryx, \u2026), Outils BI (PowerBI, Qlik, Grafana ...),\nLangages de programmation (python, SCALA, R, DAX)\nLes certifications de Azure (DP-203, AZ-300, AZ-303, AZ-304, AZ-400, AI-900) seraient un plus,\nVotre Personnalit\u00e9\nFort volont\u00e9 de travailler en \u00e9quipe\nBonnes habitudes de documentation\nNiveau avanc\u00e9 en Fran\u00e7ais et en Anglais (niveau minimum B1)\nFaire preuve d\u2019innovation et \u00eatre source de proposition\nSavoir exprimer ses id\u00e9es de mani\u00e8re claire et concise\nEtre \u00e0 l'\u00e9coute\nParlons de nous !\nEnvironnement & Conditions De Travail\nAirbus Atlantic c\u2019est aussi :\nPrendre part \u00e0 des projets ambitieux, \u00e0 la pointe de la technologie pour construire l\u2019avion de demain, en lien avec les enjeux environnementaux.\nUn environnement qui valorise la proximit\u00e9 et la dimension humaine, au sein d\u2019un collectif engag\u00e9 et solidaire.\nL\u2019opportunit\u00e9 d\u2019apprendre et d\u2019\u00e9voluer tout au long de votre parcours, en \u00e9tant accompagn\u00e9 dans votre d\u00e9veloppement pour une carri\u00e8re sur-mesure.\nAvoir la libert\u00e9 d\u2019entreprendre et de laisser libre court \u00e0 vos initiatives.\nSes conditions de travail attractives et ses avantages : restaurant d\u2019entreprise sur site, CSE (avantages loisirs & famille), parking entreprise, mutuelle d\u2019entreprise (famille).\nSa politique de diversit\u00e9 et d'inclusion : Airbus Atlantic s\u2019engage en faveur de l\u2019\u00e9galit\u00e9 des chances pour tous.\nSon plan d'actionnariat salari\u00e9 et son plan d\u2019\u00e9pargne salariale.\nNotre Processus De Recrutement\nNous avons \u00e0 c\u0153ur de mieux vous conna\u00eetre et de comprendre ce qui vous motive \u00e0 nous rejoindre. Aussi, notre process de recrutement se d\u00e9roule en plusieurs \u00e9tapes apr\u00e8s analyse de votre candidature :\nEntretien vid\u00e9o diff\u00e9r\u00e9 via la plateforme Hirevue\nEntretien avec le Manager Recruteur\nEntretien avec le/la Charg\u00e9(e) de Recrutement qui peut \u00eatre compl\u00e9t\u00e9 par un questionnaire de personnalit\u00e9\nEntretien avec le/la Human Resources Business Partner.\nThis job requires an awareness of any potential compliance risks and a commitment to act with integrity, as the foundation for the Company\u2019s success, reputation and sustainable growth.\nCompany\nAirbus Atlantic\nContract Type\nPermanent\nClasse Emploi (France): Classe G13\nExperience Level\nProfessional\nJob Family\nDigital\nBy submitting your CV or application you are consenting to Airbus using and storing information about you for monitoring purposes relating to your application or future employment. This information will only be used by Airbus.\nAirbus is committed to achieving workforce diversity and creating an inclusive working environment. We welcome all applications irrespective of social and cultural background, age, gender, disability, sexual orientation or religious belief.\nAirbus is, and always has been, committed to equal opportunities for all. As such, we will never ask for any type of monetary exchange in the frame of a recruitment process. Any impersonation of Airbus to do so should be reported to emsom@airbus.com.\nAt Airbus, we support you to work, connect and collaborate more easily and flexibly. Wherever possible, we foster flexible working arrangements to stimulate innovative thinking.\nShow more\nShow less",
        "skills": {
            "ProgLanguage": [
                "Python",
                "Scala",
                "R",
                "Go"
            ],
            "DataBase": [
                "SQL",
                " MongoDB"
            ],
            "DataAnalytics": [
                "R"
            ],
            "BigData": [
                "Databricks"
            ],
            "MachingLearning": [],
            "DataSerialization": [],
            "DataVisualization": [
                "PowerBI"
            ],
            "Statistics": [],
            "CloudComputing": [
                "Azure"
            ],
            "DevTools": [
                "Git"
            ],
            "Os": [],
            "DBMS": [
                "PostgreSQL"
            ],
            "SoftBigDataProcessing": [],
            "Automation": [],
            "InfrastructureAsCode": [],
            "NetworkSecurty": [],
            "Virtualisation": [],
            "Containers": [],
            "Collaboration": [],
            "Other": [
                "ML"
            ],
            "FrSoftSkills": [
                "Collaboration"
            ],
            "EnSoftSkils": [
                "Collaboration",
                "Initiative"
            ]
        },
        "details": {
            "JobDetail": [],
            "TypeContract": [],
            "Salary": [],
            "Level": [],
            "Experience": [
                "a",
                "n",
                "s",
                "5",
                "5",
                "5"
            ]
        }
    },
    {
        "source": "LinkedIn",
        "title": "Architecte Technique BI/Big Data -Nantes",
        "company": "Capgemini",
        "location": "Nantes, Pays de la Loire, France",
        "link": "https://fr.linkedin.com/jobs/view/architecte-technique-bi-big-data-nantes-at-capgemini-3803994992?position=8&pageNum=2&refId=s27%2F43wenQFDag2sabINKw%3D%3D&trackingId=7FHNSEfvjMmvL7Q5xmN9%2FQ%3D%3D&trk=public_jobs_jserp-result_search-card",
        "description": "Capgemini\nChoisir Capgemini, c'est choisir une entreprise o\u00f9 vous serez en mesure de fa\u00e7onner votre carri\u00e8re selon vos aspirations, o\u00f9 vous serez soutenu et inspir\u00e9 par une communaut\u00e9 d\u2019experts dans le monde entier, o\u00f9 vous pourrez r\u00e9\u00e9crire votre futur. Rejoignez-nous pour red\u00e9finir les limites de ce qui est possible, contribuer \u00e0 lib\u00e9rer la valeur de la technologie pour les plus grandes organisations et participez \u00e0 la construction d\u2019un monde plus durable et inclusif.\nVos missions :\nInt\u00e9gr\u00e9(e) au sein d'une \u00e9quipe projets intervenant pour des clients dans des secteurs d'activit\u00e9s vari\u00e9es, vous serez notamment en charge des missions suivantes :\nInteragir avec nos clients, nos partenaires pour concevoir et mettre en \u0153uvre des solutions/projets innovants et comp\u00e9titifs\nR\u00e9pondre aux probl\u00e9matiques de nos clients en proposant la meilleure plateforme data dans un environnement Agile\nAdapter chaque architecture en fonction du contexte gr\u00e2ce \u00e0 votre ma\u00eetrise des caract\u00e9ristiques fondamentales de chaque solution (catalogue des offres de services manag\u00e9s, performance, s\u00e9curit\u00e9, d\u00e9ploiement des data centers \u2026)\nUtiliser les solutions d\u2019int\u00e9gration associ\u00e9es et les solutions d\u00e9cisionnelles ainsi qu\u2019analytiques qui viennent consommer les donn\u00e9es manipul\u00e9es\nEncadrer les \u00e9quipes dans la mise en place des architectures pr\u00e9conis\u00e9es et/ ou des plateformes Data\nVous avez acquis de l\u2019exp\u00e9rience sur les cadres de r\u00e9f\u00e9rence et patterns d\u2019architecture Data, DevOps.\nVotre profil :\nDipl\u00f4me d\u2019ing\u00e9nieur ou \u00e9quivalent universitaire\nMinimum 6 ans d'exp\u00e9rience\nAnglais courant\nExpertise dans la conception d\u2019architecture, la mise en \u0153uvre et/ou le support d\u2019applications hautement distribu\u00e9es\nSensibilisation \u00e0 la m\u00e9thode devops et connaissance d\u2019un outil de de Continuous Integration/Continuous Delivery (CI-CD)\nExpertise sur les services Cloud Data suivants (Azure, AWS, GCP)\nGrande aisance dans la communication orale et \u00e9crite, leadership afin de f\u00e9d\u00e9rer des \u00e9quipes\n3 raisons de nous rejoindre :\nQualit\u00e9 de vie au travail : accord de t\u00e9l\u00e9travail en France et \u00e0 l\u2019international, accord sur l\u2019\u00e9galit\u00e9\nprofessionnelle, la parentalit\u00e9, l\u2019\u00e9quilibre des temps et la mobilit\u00e9 durable.\nApprentissage en continu : certifications et formations en libre acc\u00e8s, accompagnement sur mesure avec votre carreer manager, parcours d\u2019int\u00e9gration sur 9 mois.\nAvantages groupe & CSE : plan actionnariat, activit\u00e9s \u00e0 tarifs pr\u00e9f\u00e9rentiels, remboursement partiel\nvacances, remboursement de votre abonnement sportif ou culturel.\nNos engagements et priorit\u00e9s :\nLe groupe Capgemini encourage une culture inclusive dans un cadre multiculturel et handi-accueillant. En nous rejoignant, vous int\u00e9grez un collectif qui valorise la diversit\u00e9, d\u00e9veloppe le potentiel de ses talents, s\u2019engage dans des initiatives solidaires avec ses partenaires, et se mobilise pour r\u00e9duire son impact environnemental sur tous ses sites et aupr\u00e8s de ses clients.\nCapgemini\nCapgemini est un leader mondial, responsable et multiculturel, regroupant pr\u00e8s de 350 000 personnes dans plus de 50 pays. Fort de 55 ans d\u2019exp\u00e9rience, nous sommes un partenaire strat\u00e9gique des entreprises pour la transformation de leurs activit\u00e9s en tirant profit de toute la puissance de la technologie et des innovations dans les domaines en perp\u00e9tuelle \u00e9volution tels que le cloud, la data, l\u2019Intelligence Artificielle, la connectivit\u00e9, les logiciels, l\u2019ing\u00e9nierie digitale ou les plateformes.\nGet The Future You Want* | www.capgemini.com/fr-fr\n*Capgemini, le futur que vous voulez\nShow more\nShow less",
        "skills": {
            "ProgLanguage": [
                "R"
            ],
            "DataBase": [],
            "DataAnalytics": [
                "R"
            ],
            "BigData": [],
            "MachingLearning": [],
            "DataSerialization": [],
            "DataVisualization": [],
            "Statistics": [],
            "CloudComputing": [
                "AWS",
                "Azure"
            ],
            "DevTools": [
                "Git"
            ],
            "Os": [],
            "DBMS": [],
            "SoftBigDataProcessing": [],
            "Automation": [],
            "InfrastructureAsCode": [],
            "NetworkSecurty": [],
            "Virtualisation": [],
            "Containers": [],
            "Collaboration": [],
            "Other": [
                "DevOps",
                "Cloud"
            ],
            "FrSoftSkills": [
                "Communication",
                "Leadership",
                "Organisation"
            ],
            "EnSoftSkils": [
                "Communication",
                "Leadership",
                "Initiative"
            ]
        },
        "details": {
            "JobDetail": [],
            "TypeContract": [],
            "Salary": [],
            "Level": [],
            "Experience": [
                "a",
                "n",
                "s",
                "6",
                "6",
                "6"
            ]
        }
    },
    {
        "source": "LinkedIn",
        "title": "Architecte / Conseil Data H/F",
        "company": "EXAKIS NELITE",
        "location": "Grenoble, Auvergne-Rh\u00f4ne-Alpes, France",
        "link": "https://fr.linkedin.com/jobs/view/architecte-conseil-data-h-f-at-exakis-nelite-3813458944?position=9&pageNum=2&refId=s27%2F43wenQFDag2sabINKw%3D%3D&trackingId=sFkATwbM7Wt2uLFv7VyJuQ%3D%3D&trk=public_jobs_jserp-result_search-card",
        "description": "Exakis Nelite, entit\u00e9 du groupe\nMagellan Partners\n, est le\n1er partenaire pure-player Microsoft\nind\u00e9pendant en France avec l\u2019ambition de devenir le premier partenaire Europ\u00e9en et en Afrique Francophone avec sa forte pr\u00e9sence au Maroc.\nN\u00e9s du rapprochement de 2 leaders sp\u00e9cialistes de l\u2019int\u00e9gration des solutions Microsoft, nous allions expertise technique et fonctionnelle pour r\u00e9pondre concr\u00e8tement aux enjeux de demain : acc\u00e9l\u00e9ration de la transformation digitale,\nCyberS\u00e9curit\u00e9, Intelligence Artificielle, IoT, Data, transformation vers le cloud Azure, Services Cognitifs \u2026\nEn rejoignant la communaut\u00e9 Exakis Nelite dans l\u2019une de nos 12 agences (680 collaborateurs), vous int\u00e9grerez une \u00e9quipe passionn\u00e9e et impliqu\u00e9e dans les projets les plus innovants. Vous rejoindrez une structure construite autour de valeurs tourn\u00e9es vers ses collaborateurs : intelligence collective, convivialit\u00e9 et bienveillance.\nExakis Nelite a re\u00e7u la certification\nGreat Place to Work\net se place\n3\u00e8me de sa cat\u00e9gorie\nen 2024 parmi les entreprises o\u00f9 il fait bon travailler en France !\n\u00c0 quoi ressembleront vos futures missions ?\nEn tant qu\u2019Architecte et Conseil, dans les domaines Data et Business Intelligence, vous serez amen\u00e9 \u00e0 travailler sur des projets d\u2019envergure mettant \u00e0 l\u2019\u00e9preuve votre exp\u00e9rience des syst\u00e8mes de donn\u00e9es et votre ouverture vers les technologies de BI moderne et cloud.\nVotre r\u00f4le d\u2019architecte et de conseil aupr\u00e8s de nos clients trouvera son sens dans la comp\u00e9tence que pourrez apporter autour des solutions Microsoft (Power BI, Azure\u2026), et aussi dans la connaissance globale que vous aurez acquise par vos exp\u00e9riences vari\u00e9es. Cette combinaison comp\u00e9tence/exp\u00e9rience aura pour but d\u2019orchestrer l\u2019impl\u00e9mentation des technologies Microsoft dans des syst\u00e8mes d\u2019information et d\u00e9cisionnels technologiquement h\u00e9t\u00e9rog\u00e8nes.\nVotre passion, votre curiosit\u00e9 et votre envie sont les ma\u00eetres mots pour r\u00e9ussir dans ce poste. Vous \u00eates motiv\u00e9 pour travailler dans un environnement dynamique o\u00f9 la donn\u00e9e se d\u00e9cline autour de nos projets innovants (IoT, Industrie 4.0, IA\u2026). Vous avez une vision claire des enjeux actuels autour de la donn\u00e9e.\nDescription du poste\nSelon les missions vous serez amen\u00e9 \u00e0 :\nAccompagner nos clients dans leur strat\u00e9gie digitale\nAnimer des ateliers d\u2019architecture technique\nAppr\u00e9hender les besoins fonctionnels et les contraintes techniques du client\nPr\u00e9coniser des architectures complexes pour r\u00e9pondre \u00e0 une probl\u00e9matique ou un besoin m\u00e9tier\nD\u00e9finir et am\u00e9liorer les standards, patterns d\u2019architecture et le catalogue de services\nSuperviser et mettre en \u0153uvre, dans le cadre des projets, les pr\u00e9conisations techniques \u00e9tablies dans le cadre des cahiers des charges\nR\u00e9aliser l\u2019architecture de donn\u00e9es dans des environnements on Premise\nIntervenir sur l\u2019architecture Azure data\nR\u00e9diger les documents associ\u00e9s (HLD, LLD, etc.)\nPiloter des projets et des hommes\nIntervenir en toute autonomie sur les phases de cadrage technique et/ou avant ventes\nAssurer une veille technologique\nProfil\nFort d\u2019une exp\u00e9rience de 3 \u00e0 15 ans dans les domaines, Data, BI et Big Data, vous portez de l\u2019int\u00e9r\u00eat aux technologies du Cloud, aux approches de BI moderne et \u00e0 leur d\u00e9veloppement. Vous \u00eates un professionnel aguerri des environnements Data, de l\u2019architecture et de l\u2019utilisation des technologies Cloud.\nLa connaissance des environnements Microsoft (Power BI, SQL Server, Azure\u2026) est un plus mais n\u2019est pas une obligation. La diversit\u00e9 de vos exp\u00e9riences dans le champ d\u2019activit\u00e9 Data/BI est le facteur clef de succ\u00e8s de ce poste.\nCurieux et dynamique, vous avez le gout du challenge et souhaitez prendre part au d\u00e9veloppement important d\u2019Exakis Nelite et de Magellan Partners dans le domaine des Data-sciences.\nShow more\nShow less",
        "skills": {
            "ProgLanguage": [
                "R",
                "Go"
            ],
            "DataBase": [
                "SQL"
            ],
            "DataAnalytics": [
                "R"
            ],
            "BigData": [],
            "MachingLearning": [],
            "DataSerialization": [],
            "DataVisualization": [
                "Power BI"
            ],
            "Statistics": [],
            "CloudComputing": [
                "Azure"
            ],
            "DevTools": [
                "Git"
            ],
            "Os": [],
            "DBMS": [
                "SQL Server"
            ],
            "SoftBigDataProcessing": [],
            "Automation": [],
            "InfrastructureAsCode": [],
            "NetworkSecurty": [],
            "Virtualisation": [],
            "Containers": [],
            "Collaboration": [],
            "Other": [
                "Big Data",
                "Cloud"
            ],
            "FrSoftSkills": [],
            "EnSoftSkils": []
        },
        "details": {
            "JobDetail": [],
            "TypeContract": [],
            "Salary": [],
            "Level": [],
            "Experience": [
                "a",
                "n",
                "s",
                "15",
                "15",
                "15"
            ]
        }
    },
    {
        "source": "LinkedIn",
        "title": "DATA / ARCHITECT Manager",
        "company": "SIBIOS",
        "location": "Lyon, Auvergne-Rh\u00f4ne-Alpes, France",
        "link": "https://fr.linkedin.com/jobs/view/data-architect-manager-at-sibios-3881612188?position=10&pageNum=2&refId=s27%2F43wenQFDag2sabINKw%3D%3D&trackingId=VKlC%2FXFyXvWYWqlKEhzgWw%3D%3D&trk=public_jobs_jserp-result_search-card",
        "description": "SIBIOS recherche un consultant Senior DATA / ARCHITECT Manager avec minium 10 ans d'exp\u00e9rience pour un nouveau projet dans le secteur industriel.\nUne bonne connaissance d'architecture fonctionnelle et l'urbanisation data, ainsi que des r\u00e8gles de s\u00e9curit\u00e9.\nVous avez une ma\u00eetrise de la gestion des donn\u00e9es et des outils/langages correspondants (SQL, Power BI, mod\u00e9lisation et visualisation des donn\u00e9es, ...)\nDiriger des projets Data sur divers domaines fonctionnels (M\u00e9tier et IT) pour d\u00e9finir les feuilles de route.\nD\u00e9finir la gouvernance de chaque projet et suivre le planning, le budget, la qualit\u00e9 et les risques sur chaque projet\nPiloter la gestion du changement et communiquer autour des projets\nIndustrialisation des innovations digitales : gouvernance, socle technique, documentation et support\nPour un entretien imm\u00e9diat, merci de nous faire suivre votre cv mis \u00e1 jour en word format ainsi que votre date de disponibilit\u00e9 et TJM.\nShow more\nShow less",
        "skills": {
            "ProgLanguage": [
                "R",
                "Go"
            ],
            "DataBase": [
                "SQL"
            ],
            "DataAnalytics": [
                "R"
            ],
            "BigData": [],
            "MachingLearning": [],
            "DataSerialization": [],
            "DataVisualization": [
                "Power BI"
            ],
            "Statistics": [],
            "CloudComputing": [],
            "DevTools": [
                "Git"
            ],
            "Os": [],
            "DBMS": [],
            "SoftBigDataProcessing": [],
            "Automation": [],
            "InfrastructureAsCode": [],
            "NetworkSecurty": [],
            "Virtualisation": [],
            "Containers": [],
            "Collaboration": [],
            "Other": [],
            "FrSoftSkills": [],
            "EnSoftSkils": []
        },
        "details": {
            "JobDetail": [
                "Senior"
            ],
            "TypeContract": [],
            "Salary": [],
            "Level": [],
            "Experience": [
                "a",
                "n",
                "s",
                "10",
                "10",
                "10"
            ]
        }
    }
]